Workbook
Name AAI: #REF!
Name ALGDED: #REF!
Name BALANZADIC: #REF!
Name BALANZADIC14: #REF!
Name BGDECL: #REF!
Name CCF: #REF!
Name EJERCICIO: #REF!
Name ENERO16: #REF!
Name ENERO16: #REF!
Name ENERO16: #REF!
Name ENERO16: #REF!
Name ENERO16: #REF!
Name ENERO16: #REF!
Name ENERO16: #REF!
Name ERDECL: #REF!
Name inpc: #REF!
Name No_MES: #REF!
Name NombreRango1: #REF!
Name NombreRango1: #REF!
Name NombreRango1: #REF!
Name NombreRango1: #REF!
Name NombreRango1: #REF!
Name NombreRango1: #REF!
Name NombreRango1: #REF!
Name VAC: #REF!

Sheet Parametros AGS
A1: ESTIMULO FISCAL | D1: IEPS
A2: REGULAR | D2: REGULAR | E2: 0.522479 | I2: *Aumento en los ingresos en proporcion minima a la inflacion
A3: PREMIUM | D3: PREMIUM | E3: 0.637522
A4: DIESEL | D4: DIESEL | E4: 0.433626
A6: Precio final al 27 de Octubre de 2025 | D6: Precio de venta sin IVA | G6: MONTEBLANCO | H6: SAN RAFEL | I6: PUERTECITO | J6: JESUS MARIA | L6: MONTEBLANCO | M6: SAN RAFEL | N6: PUERTECITO | O6: JESUS MARIA
A7: REGULAR | B7: 24 | D7: =+B7/1.08 -> 22.222222 | G7: 21.944444 | H7: 21.944444 | I7: 21.944444 | J7: 21.944444 | L7: 21.4 | M7: 21.4 | N7: 21.4 | O7: 21.4
A8: PREMIUM | B8: 25 | D8: =+B8/1.08 -> 23.148148 | G8: 23.148148 | H8: 23.148148 | I8: 23.148148 | J8: 23.148148 | L8: 22.82 | M8: 22.82 | N8: 22.82 | O8: 22.82
A9: DIESEL | B9: 26.9 | D9: =+B9/1.08 -> 24.907407 | G9: 24.907407 | H9: 24.907407 | I9: 24.907407 | J9: 24.907407 | L9: 24.45 | M9: 24.45 | N9: 24.45 | O9: 24.45
A11: PRECIO DE VENTA sin IVA por LITRO
A12: Ags | B12: 0.004 | C12: 0.004 | D12: 0.004 | E12: 0.004 | F12: 0.004 | G12: 0.004 | H12: 0.004 | I12: 0.004 | J12: 0.004 | K12: 0.004 | L12: 0.004 | M12: 0.004
A13: P.V. | B13: Enero | C13: Febrero | D13: Marzo | E13: Abril | F13: Mayo | G13: Junio | H13: Julio | I13: Agosto | J13: Septiembre | K13: Octubre | L13: Noviembre | M13: Diciembre
A14: MAXIMA | B14: =+D7 -> 22.222222 | C14: =B14*(1+$C$12) -> 22.311111 | D14: =C14*(1+$C$12) -> 22.400356 | E14: =D14*(1+$C$12) -> 22.489957 | F14: =E14*(1+$C$12) -> 22.579917 | G14: =F14*(1+$C$12) -> 22.670236 | H14: =G14*(1+$C$12) -> 22.760917 | I14: =H14*(1+$C$12) -> 22.851961 | J14: =I14*(1+$C$12) -> 22.943369 | ... M14: =L14*(1+$C$12) -> 23.219792
A15: SUPER | B15: =+D8 -> 23.148148 | C15: =B15*(1+$C$12) -> 23.240741 | D15: =C15*(1+$C$12) -> 23.333704 | E15: =D15*(1+$C$12) -> 23.427039 | F15: =E15*(1+$C$12) -> 23.520747 | G15: =F15*(1+$C$12) -> 23.61483 | H15: =G15*(1+$C$12) -> 23.709289 | I15: =H15*(1+$C$12) -> 23.804126 | J15: =I15*(1+$C$12) -> 23.899343 | ... M15: =L15*(1+$C$12) -> 24.187283
A16: DIESEL | B16: =+D9 -> 24.907407 | C16: =B16*(1+$C$12) -> 25.007037 | D16: =C16*(1+$C$12) -> 25.107065 | E16: =D16*(1+$C$12) -> 25.207493 | F16: =E16*(1+$C$12) -> 25.308323 | G16: =F16*(1+$C$12) -> 25.409557 | H16: =G16*(1+$C$12) -> 25.511195 | I16: =H16*(1+$C$12) -> 25.61324 | J16: =I16*(1+$C$12) -> 25.715693 | ... M16: =L16*(1+$C$12) -> 26.025517
A18: Inflación 2024 | B18: ='[19]Variables Globales'!$C$3 -> 1.0351
A21: MARGEN estimado por litro
A22: Ags | B22: Margen comercial ( precio - costo según factura )
A23: P.V. | B23: Enero | C23: Febrero | D23: Marzo | E23: Abril | F23: Mayo | G23: Junio | H23: Julio | I23: Agosto | J23: Septiembre | K23: Octubre | L23: Noviembre | M23: Diciembre
A24: MAXIMA | B24: 0 | C24: 0 | D24: 0 | E24: 0 | F24: 0 | G24: 0 | H24: 0 | I24: 0 | J24: 0 | K24: 0 | L24: 0 | M24: 0
A25: SUPER | B25: 0 | C25: 0 | D25: 0 | E25: 0 | F25: 0 | G25: 0 | H25: 0 | I25: 0 | J25: 0 | K25: 0 | L25: 0 | M25: 0
A26: DIESEL | B26: 0 | C26: 0 | D26: 0 | E26: 0 | F26: 0 | G26: 0 | H26: 0 | I26: 0 | J26: 0 | K26: 0 | L26: 0 | M26: 0
B28: Margen por contrato de volumen con TESORO
A29: P.V. | B29: Enero | C29: Febrero | D29: Marzo | E29: Abril | F29: Mayo | G29: Junio | H29: Julio | I29: Agosto | J29: Septiembre | K29: Octubre | L29: Noviembre | M29: Diciembre | N29: Porcentaje
A30: MAXIMA | B30: 2.08 | N30: 0.2 | P30: =AVERAGE(B30:M30) -> 2.08
A31: SUPER | B31: 3.37 | N31: 0.2 | P31: =AVERAGE(B31:M31) -> 3.37
A32: DIESEL | B32: 1.08 | N32: 0.2 | P32: =AVERAGE(B32:M32) -> 1.08
B34: Margen por contrato de volumen con PREMIER
A35: P.V. | B35: Enero | C35: Febrero | D35: Marzo | E35: Abril | F35: Mayo | G35: Junio | H35: Julio | I35: Agosto | J35: Septiembre | K35: Octubre | L35: Noviembre | M35: Diciembre | N35: Porcentaje
A36: MAXIMA | B36: 2.26 | N36: 0.43 | P36: =AVERAGE(B36:M36) -> 2.26
A37: SUPER | B37: 2.89 | N37: 0.43 | P37: =AVERAGE(B37:M37) -> 2.89
A38: DIESEL | B38: 1.93 | N38: 0.43 | P38: =AVERAGE(B38:M38) -> 1.93
B40: Margen por contrato de volumen MGC
A41: P.V. | B41: Enero | C41: Febrero | D41: Marzo | E41: Abril | F41: Mayo | G41: Junio | H41: Julio | I41: Agosto | J41: Septiembre | K41: Octubre | L41: Noviembre | M41: Diciembre | N41: Porcentaje
A42: MAXIMA | B42: 1.93 | N42: 0.29 | P42: =AVERAGE(B42:M42) -> 1.93
A43: SUPER | B43: 2.75 | N43: 0.29 | P43: =AVERAGE(B43:M43) -> 2.75
A44: DIESEL | B44: 0.62 | N44: 0.29 | P44: =AVERAGE(B44:M44) -> 0.62
B46: Margen por contrato de volumen OTROS
A47: P.V. | B47: Enero | C47: Febrero | D47: Marzo | E47: Abril | F47: Mayo | G47: Junio | H47: Julio | I47: Agosto | J47: Septiembre | K47: Octubre | L47: Noviembre | M47: Diciembre | N47: Porcentaje
A48: MAXIMA | B48: 2.13 | N48: 0.08 | P48: =AVERAGE(B48:M48) -> 2.13
A49: SUPER | B49: 0 | C49: 0 | D49: 0 | E49: 0 | F49: 0 | G49: 0 | H49: 0 | I49: 0 | J49: 0 | K49: 0 | L49: 0 | M49: 0 | N49: 0 | P49: =AVERAGE(B49:M49) -> 0
A50: DIESEL | B50: 2.98 | N50: 0.08 | P50: =AVERAGE(B50:M50) -> 2.98
B52: Margen por contrato de volumen OTROS
A53: P.V. | B53: Enero | C53: Febrero | D53: Marzo | E53: Abril | F53: Mayo | G53: Junio | H53: Julio | I53: Agosto | J53: Septiembre | K53: Octubre | L53: Noviembre | M53: Diciembre | N53: Porcentaje
A54: MAXIMA | N54: 0 | P54: =AVERAGE(B54:M54) -> #DIV/0!
A55: SUPER | N55: 0 | P55: =AVERAGE(B55:M55) -> #DIV/0!
A56: DIESEL | N56: 0 | P56: =AVERAGE(B56:M56) -> #DIV/0!
A58: CENTAVOS POR LITRO (FLETE) | M58: MAXIMA | N58: =+N30+N36+N42+N48+N54 -> 1
A59: MAXIMA | B59: 0 | M59: SUPER | N59: =+N31+N37+N43+N49+N55 -> 0.92
A60: SUPER | B60: 0 | M60: DIESEL | N60: =+N32+N38+N44+N50+N56 -> 1
A61: DIESEL | B61: 0
A66: DESCUENTOS
A67: PRECIO REGULAR | C67: Enero | D67: Febrero | E67: Marzo | F67: Abril | G67: Mayo | H67: Junio | I67: Julio | J67: Agosto | K67: Septiembre | L67: Octubre | M67: Noviembre | N67: Diciembre
A68: 23214 | B68: HERMANOS ESCOBAR | C68: -0.2 | D68: -0.2 | E68: -0.2 | F68: -0.2 | G68: -0.2 | H68: -0.2 | I68: -0.2 | J68: -0.2 | K68: -0.2 | L68: -0.2 | M68: -0.2 | N68: -0.2
A69: 1149 | B69: LERDO | C69: -0.25 | D69: -0.25 | E69: -0.25 | F69: -0.25 | G69: -0.25 | H69: -0.25 | I69: -0.25 | J69: -0.25 | K69: -0.25 | L69: -0.25 | M69: -0.25 | N69: -0.25
A70: 1163 | B70: TECNOLOGICO | C70: -0.21 | D70: -0.21 | E70: -0.21 | F70: -0.21 | G70: -0.21 | H70: -0.21 | I70: -0.21 | J70: -0.21 | K70: -0.21 | L70: -0.21 | M70: -0.21 | N70: -0.21
A71: 1376 | B71: DELICIAS | C71: -0.2 | D71: -0.2 | E71: -0.2 | F71: -0.2 | G71: -0.2 | H71: -0.2 | I71: -0.2 | J71: -0.2 | K71: -0.2 | L71: -0.2 | M71: -0.2 | N71: -0.2
A72: 2172 | B72: PARRAL | C72: -0.2 | D72: -0.2 | E72: -0.2 | F72: -0.2 | G72: -0.2 | H72: -0.2 | I72: -0.2 | J72: -0.2 | K72: -0.2 | L72: -0.2 | M72: -0.2 | N72: -0.2
A73: 2526 | B73: LOPEZ | C73: -0.2 | D73: -0.2 | E73: -0.2 | F73: -0.2 | G73: -0.2 | H73: -0.2 | I73: -0.2 | J73: -0.2 | K73: -0.2 | L73: -0.2 | M73: -0.2 | N73: -0.2
A74: 4179 | B74: GEMELA CH | C74: -0.1 | D74: -0.1 | E74: -0.1 | F74: -0.1 | G74: -0.1 | H74: -0.1 | I74: -0.1 | J74: -0.1 | K74: -0.1 | L74: -0.1 | M74: -0.1 | N74: -0.1
A75: 4188 | B75: GEMELA G | C75: -0.21 | D75: -0.21 | E75: -0.21 | F75: -0.21 | G75: -0.21 | H75: -0.21 | I75: -0.21 | J75: -0.21 | K75: -0.21 | L75: -0.21 | M75: -0.21 | N75: -0.21
A76: 5317 | B76: MUNICIPIO | C76: -0.16 | D76: -0.16 | E76: -0.16 | F76: -0.16 | G76: -0.16 | H76: -0.16 | I76: -0.16 | J76: -0.16 | K76: -0.16 | L76: -0.16 | M76: -0.16 | N76: -0.16
A77: 6410 | B77: MISIONES | C77: -0.22 | D77: -0.22 | E77: -0.22 | F77: -0.22 | G77: -0.22 | H77: -0.22 | I77: -0.22 | J77: -0.22 | K77: -0.22 | L77: -0.22 | M77: -0.22 | N77: -0.22
A78: 6947 | B78: P PALOS | C78: -0.2 | D78: -0.2 | E78: -0.2 | F78: -0.2 | G78: -0.2 | H78: -0.2 | I78: -0.2 | J78: -0.2 | K78: -0.2 | L78: -0.2 | M78: -0.2 | N78: -0.2
A79: 7167 | B79: M MADRID | C79: -0.15 | D79: -0.15 | E79: -0.15 | F79: -0.15 | G79: -0.15 | H79: -0.15 | I79: -0.15 | J79: -0.15 | K79: -0.15 | L79: -0.15 | M79: -0.15 | N79: -0.15
... A93: 3184 | B93: PRAXEDIS | C93: -0.2 | D93: -0.2 | E93: -0.2 | F93: -0.2 | G93: -0.2 | H93: -0.2 | I93: -0.2 | J93: -0.2 | K93: -0.2 | L93: -0.2 | M93: -0.2 | N93: -0.2
A95: PRECIO PREMIUM | C95: Enero | D95: Febrero | E95: Marzo | F95: Abril | G95: Mayo | H95: Junio | I95: Julio | J95: Agosto | K95: Septiembre | L95: Octubre | M95: Noviembre | N95: Diciembre
B96: HERMANOS ESCOBAR | C96: 0 | D96: 0 | E96: 0 | F96: 0 | G96: 0 | H96: 0 | I96: 0 | J96: 0 | K96: 0 | L96: 0 | M96: 0 | N96: 0
A97: 1149 | B97: LERDO | C97: 0 | D97: 0 | E97: 0 | F97: 0 | G97: 0 | H97: 0 | I97: 0 | J97: 0 | K97: 0 | L97: 0 | M97: 0 | N97: 0
A98: 1163 | B98: TECNOLOGICO | C98: 0 | D98: 0 | E98: 0 | F98: 0 | G98: 0 | H98: 0 | I98: 0 | J98: 0 | K98: 0 | L98: 0 | M98: 0 | N98: 0
A99: 1376 | B99: DELICIAS | C99: 0 | D99: 0 | E99: 0 | F99: 0 | G99: 0 | H99: 0 | I99: 0 | J99: 0 | K99: 0 | L99: 0 | M99: 0 | N99: 0
A100: 2172 | B100: PARRAL | C100: 0 | D100: 0 | E100: 0 | F100: 0 | G100: 0 | H100: 0 | I100: 0 | J100: 0 | K100: 0 | L100: 0 | M100: 0 | N100: 0
A101: 2526 | B101: LOPEZ | C101: 0 | D101: 0 | E101: 0 | F101: 0 | G101: 0 | H101: 0 | I101: 0 | J101: 0 | K101: 0 | L101: 0 | M101: 0 | N101: 0
A102: 4179 | B102: GEMELA CH | C102: 0 | D102: 0 | E102: 0 | F102: 0 | G102: 0 | H102: 0 | I102: 0 | J102: 0 | K102: 0 | L102: 0 | M102: 0 | N102: 0
A103: 4188 | B103: GEMELA G | C103: 0 | D103: 0 | E103: 0 | F103: 0 | G103: 0 | H103: 0 | I103: 0 | J103: 0 | K103: 0 | L103: 0 | M103: 0 | N103: 0
A104: 5317 | B104: MUNICIPIO | C104: 0 | D104: 0 | E104: 0 | F104: 0 | G104: 0 | H104: 0 | I104: 0 | J104: 0 | K104: 0 | L104: 0 | M104: 0 | N104: 0
A105: 6410 | B105: MISIONES | C105: 0 | D105: 0 | E105: 0 | F105: 0 | G105: 0 | H105: 0 | I105: 0 | J105: 0 | K105: 0 | L105: 0 | M105: 0 | N105: 0
A106: 6947 | B106: P PALOS | C106: 0 | D106: 0 | E106: 0 | F106: 0 | G106: 0 | H106: 0 | I106: 0 | J106: 0 | K106: 0 | L106: 0 | M106: 0 | N106: 0
A107: 7167 | B107: M MADRID | C107: 0 | D107: 0 | E107: 0 | F107: 0 | G107: 0 | H107: 0 | I107: 0 | J107: 0 | K107: 0 | L107: 0 | M107: 0 | N107: 0
A108: 5465 | B108: AZTECAS | C108: 0 | D108: 0 | E108: 0 | F108: 0 | G108: 0 | H108: 0 | I108: 0 | J108: 0 | K108: 0 | L108: 0 | M108: 0 | N108: 0
... A121: 3184 | B121: PRAXEDIS | C121: 0 | D121: 0 | E121: 0 | F121: 0 | G121: 0 | H121: 0 | I121: 0 | J121: 0 | K121: 0 | L121: 0 | M121: 0 | N121: 0
A124: PRECIO DIESEL | C124: Enero | D124: Febrero | E124: Marzo | F124: Abril | G124: Mayo | H124: Junio | I124: Julio | J124: Agosto | K124: Septiembre | L124: Octubre | M124: Noviembre | N124: Diciembre
B125: HERMANOS ESCOBAR | C125: 0 | D125: 0 | E125: 0 | F125: 0 | G125: 0 | H125: 0 | I125: 0 | J125: 0 | K125: 0 | L125: 0 | M125: 0 | N125: 0
A126: 1149 | B126: LERDO | C126: 0 | D126: 0 | E126: 0 | F126: 0 | G126: 0 | H126: 0 | I126: 0 | J126: 0 | K126: 0 | L126: 0 | M126: 0 | N126: 0
A127: 1163 | B127: TECNOLOGICO | C127: 0 | D127: 0 | E127: 0 | F127: 0 | G127: 0 | H127: 0 | I127: 0 | J127: 0 | K127: 0 | L127: 0 | M127: 0 | N127: 0
A128: 1376 | B128: DELICIAS | C128: 0 | D128: 0 | E128: 0 | F128: 0 | G128: 0 | H128: 0 | I128: 0 | J128: 0 | K128: 0 | L128: 0 | M128: 0 | N128: 0
A129: 2172 | B129: PARRAL | C129: 0 | D129: 0 | E129: 0 | F129: 0 | G129: 0 | H129: 0 | I129: 0 | J129: 0 | K129: 0 | L129: 0 | M129: 0 | N129: 0
A130: 2526 | B130: LOPEZ | C130: 0 | D130: 0 | E130: 0 | F130: 0 | G130: 0 | H130: 0 | I130: 0 | J130: 0 | K130: 0 | L130: 0 | M130: 0 | N130: 0
A131: 4179 | B131: GEMELA CH | C131: 0 | D131: 0 | E131: 0 | F131: 0 | G131: 0 | H131: 0 | I131: 0 | J131: 0 | K131: 0 | L131: 0 | M131: 0 | N131: 0
A132: 4188 | B132: GEMELA G | C132: 0 | D132: 0 | E132: 0 | F132: 0 | G132: 0 | H132: 0 | I132: 0 | J132: 0 | K132: 0 | L132: 0 | M132: 0 | N132: 0
A133: 5317 | B133: MUNICIPIO | C133: 0 | D133: 0 | E133: 0 | F133: 0 | G133: 0 | H133: 0 | I133: 0 | J133: 0 | K133: 0 | L133: 0 | M133: 0 | N133: 0
A134: 6410 | B134: MISIONES | C134: 0 | D134: 0 | E134: 0 | F134: 0 | G134: 0 | H134: 0 | I134: 0 | J134: 0 | K134: 0 | L134: 0 | M134: 0 | N134: 0
A135: 6947 | B135: P PALOS | C135: 0 | D135: 0 | E135: 0 | F135: 0 | G135: 0 | H135: 0 | I135: 0 | J135: 0 | K135: 0 | L135: 0 | M135: 0 | N135: 0
A136: 7167 | B136: M MADRID | C136: 0 | D136: 0 | E136: 0 | F136: 0 | G136: 0 | H136: 0 | I136: 0 | J136: 0 | K136: 0 | L136: 0 | M136: 0 | N136: 0
A137: 5465 | B137: AZTECAS | C137: 0 | D137: 0 | E137: 0 | F137: 0 | G137: 0 | H137: 0 | I137: 0 | J137: 0 | K137: 0 | L137: 0 | M137: 0 | N137: 0
... A150: 3184 | B150: PRAXEDIS | C150: 0 | D150: 0 | E150: 0 | F150: 0 | G150: 0 | H150: 0 | I150: 0 | J150: 0 | K150: 0 | L150: 0 | M150: 0 | N150: 0
A154: WINDSTAR- REGULAR | C154: ENE | D154: FEB | E154: MAR | F154: ABR | G154: MAY | H154: JUN | I154: JUL | J154: AGO | K154: SEP | L154: OCT | M154: NOV | N154: DIC
A155: 1147 | B155: MALECON | C155: 0 | D155: 0 | E155: 0 | F155: 0 | G155: 0 | H155: 0 | I155: 0 | J155: 0 | K155: 0 | L155: 0 | M155: 0 | N155: 0
A156: 1149 | B156: LERDO | C156: 0 | D156: 0 | E156: 0 | F156: 0 | G156: 0 | H156: 0 | I156: 0 | J156: 0 | K156: 0 | L156: 0 | M156: 0 | N156: 0
A157: 1163 | B157: TECNOLOGICO | C157: 0 | D157: 0 | E157: 0 | F157: 0 | G157: 0 | H157: 0 | I157: 0 | J157: 0 | K157: 0 | L157: 0 | M157: 0 | N157: 0
A158: 1376 | B158: DELICIAS | C158: 0 | D158: 0 | E158: 0 | F158: 0 | G158: 0 | H158: 0 | I158: 0 | J158: 0 | K158: 0 | L158: 0 | M158: 0 | N158: 0
...

Sheet EDO RESULTADOS MISMAS EST
I1: Mantenimiento de Imagen | J1: 2 | K1: 3 | L1: 4 | M1: 5 | N1: 6 | O1: 7 | Y1: 2 | Z1: 3 | AA1: 4 | AB1: 5 | AC1: 6 | AD1: 7 | AM1: 17 | AQ1: 17
J2: 2024 | V2: TOTAL ANUAL | Y2: 2025 | AK2: PPTO ANUAL MISMAS EST | AO2: PPTO ANUAL TODAS ES
J3: ENE | K3: FEB | L3: MAR | M3: ABR | N3: MAY | O3: JUN | P3: JUL | Q3: AGO | R3: SEP | S3: OCT | T3: NOV | U3: DIC | V3: 2024 | W3: % Part | Y3: ENE | Z3: FEB | AA3: MAR | AB3: ABR | AC3: MAY | AD3: JUN | AE3: JUL | AF3: AGO | AG3: SEP | AH3: OCT | AI3: NOV | AJ3: DIC | AK3: 2025 | AL3: % Part | AM3: Var vs AA% | AO3: 2024 | AP3: % Part | AQ3: Var vs AA%
I4: INGRESOS
A6: A - INGRESOS | E6: ( mas ) | I6: A - INGRESOS | J6: =SUM(J7:J12) -> 17192824 | K6: =SUM(K7:K12) -> 15590830 | L6: =SUM(L7:L12) -> 18254554 | M6: =SUM(M7:M12) -> 17513698 | N6: =SUM(N7:N12) -> 19514034 | O6: =SUM(O7:O12) -> 18936949 | P6: =SUM(P7:P12) -> 18138616 | Q6: =SUM(Q7:Q12) -> 18621506 | ... V6: =SUM(V7:V12) -> 223872939 | W6: =V6/V$6 -> 1 | Y6: =SUM(Y7:Y12) -> 18780611 | Z6: =SUM(Z7:Z12) -> 17035192 | AA6: =SUM(AA7:AA12) -> 20269984 | AB6: =SUM(AB7:AB12) -> 19487182 | AC6: =SUM(AC7:AC12) -> 21864209 | AD6: =SUM(AD7:AD12) -> 21197316 | AE6: =SUM(AE7:AE12) -> 20370243 | AF6: =SUM(AF7:AF12) -> 20697143 | ... AK6: =SUM(AK7:AK12) -> 2.5074065e+08 | AL6: =AK6/AK$6 -> 1 | AM6: =IFERROR(AK6/V6-1,0) -> 0.12001323 | AO6: 4.4076062e+09 | AP6: 1 | AQ6: 0.16822054
A7: A - INGRESOS | B7: estaciones | C7: INGRESOS MAGNA | D7: INGRESOS FORANEOS MAGNA | I7: MAXIMA | J7: =SUM(A:B!J7) -> 13803132 | K7: =SUM(A:B!K7) -> 12317959 | L7: =SUM(A:B!L7) -> 14526332 | M7: =SUM(A:B!M7) -> 13887455 | N7: =SUM(A:B!N7) -> 15477447 | O7: =SUM(A:B!O7) -> 15236060 | P7: =SUM(A:B!P7) -> 14546459 | Q7: =SUM(A:B!Q7) -> 14677535 | ... U7: =SUM(A:B!U7) -> 15732735 | V7: =SUM(J7:U7) -> 1.7740332e+08 | W7: =V7/V$6 -> 0.79242861 | Y7: =SUM(A:B!Y7) -> 15202952 | Z7: =SUM(A:B!Z7) -> 13599664 | AA7: =SUM(A:B!AA7) -> 16337794 | AB7: =SUM(A:B!AB7) -> 15675014 | AC7: =SUM(A:B!AC7) -> 17580791 | AD7: =SUM(A:B!AD7) -> 17284829 | AE7: =SUM(A:B!AE7) -> 16564120 | AF7: =SUM(A:B!AF7) -> 16552821 | ... AJ7: =SUM(A:B!AJ7) -> 18147057 | AK7: =SUM(Y7:AJ7) -> 2.01564e+08 | AL7: =AK7/AK$6 -> 0.80387444 | AM7: =IFERROR(AK7/V7-1,0) -> 0.13619069 | AO7: 3.4888525e+09 | AP7: 0.79155268 | AQ7: 0.14554128
A8: A - INGRESOS | B8: estaciones | C8: INGRESOS PREMIUM | D8: INGRESOS FORANEOS PREMIUM | I8: SUPER | J8: =SUM(A:B!J8) -> 3260550 | K8: =SUM(A:B!K8) -> 3155615 | L8: =SUM(A:B!L8) -> 3577713 | M8: =SUM(A:B!M8) -> 3447065 | N8: =SUM(A:B!N8) -> 3825441 | O8: =SUM(A:B!O8) -> 3528128 | P8: =SUM(A:B!P8) -> 3411360 | Q8: =SUM(A:B!Q8) -> 3791076 | ... U8: =SUM(A:B!U8) -> 4133088.9 | V8: =SUM(J8:U8) -> 44529304 | W8: =V8/V$6 -> 0.19890436 | Y8: =SUM(A:B!Y8) -> 3435117.4 | Z8: =SUM(A:B!Z8) -> 3306549.5 | AA8: =SUM(A:B!AA8) -> 3769065.3 | AB8: =SUM(A:B!AB8) -> 3620940.7 | AC8: =SUM(A:B!AC8) -> 4053744.8 | AD8: =SUM(A:B!AD8) -> 3728103.4 | AE8: =SUM(A:B!AE8) -> 3609622 | AF8: =SUM(A:B!AF8) -> 3976339.4 | ... AJ8: =SUM(A:B!AJ8) -> 4355630.6 | AK8: =SUM(Y8:AJ8) -> 47141259 | AL8: =AK8/AK$6 -> 0.18800804 | AM8: =IFERROR(AK8/V8-1,0) -> 0.05865701 | AO8: 3.5285587e+08 | AP8: 0.080056124 | AQ8: 0.26460768
A9: A - INGRESOS | B9: estaciones | C9: INGRESOS DIESEL | D9: INGRESOS FORANEOS DIESEL | I9: DIESEL | J9: =SUM(A:B!J9) -> 119320 | K9: =SUM(A:B!K9) -> 108214 | L9: =SUM(A:B!L9) -> 130827 | M9: =SUM(A:B!M9) -> 157657 | N9: =SUM(A:B!N9) -> 189122 | O9: =SUM(A:B!O9) -> 151966 | P9: =SUM(A:B!P9) -> 162434 | Q9: =SUM(A:B!Q9) -> 130655 | ... U9: =SUM(A:B!U9) -> 139359.89 | V9: =SUM(J9:U9) -> 1707634.6 | W9: =V9/V$6 -> 0.0076276953 | Y9: =SUM(A:B!Y9) -> 133961.55 | Z9: =SUM(A:B!Z9) -> 121418.7 | AA9: =SUM(A:B!AA9) -> 147824.7 | AB9: =SUM(A:B!AB9) -> 176406.75 | AC9: =SUM(A:B!AC9) -> 212152.65 | AD9: =SUM(A:B!AD9) -> 169683 | AE9: =SUM(A:B!AE9) -> 180661.05 | AF9: =SUM(A:B!AF9) -> 151003.2 | ... AJ9: =SUM(A:B!AJ9) -> 132005.55 | AK9: =SUM(Y9:AJ9) -> 1842552 | AL9: =AK9/AK$6 -> 0.0073484374 | AM9: =IFERROR(AK9/V9-1,0) -> 0.079008383 | AO9: 5.6589782e+08 | AP9: 0.12839119 | AQ9: 0.3070746
I10: INGRESOS ACEITES Y LUBRICANTES | J10: =SUM(A:B!J10) -> 9822 | K10: =SUM(A:B!K10) -> 9042 | L10: =SUM(A:B!L10) -> 19682 | M10: =SUM(A:B!M10) -> 21521 | N10: =SUM(A:B!N10) -> 22024 | O10: =SUM(A:B!O10) -> 20795 | P10: =SUM(A:B!P10) -> 18363 | Q10: =SUM(A:B!Q10) -> 22240 | ... U10: =SUM(A:B!U10) -> 22297.778 | V10: =SUM(J10:U10) -> 232680.11 | W10: =V10/V$6 -> 0.00103934 | Y10: =SUM(A:B!Y10) -> 8580 | Z10: =SUM(A:B!Z10) -> 7560 | AA10: =SUM(A:B!AA10) -> 15300 | AB10: =SUM(A:B!AB10) -> 14820 | AC10: =SUM(A:B!AC10) -> 17520 | AD10: =SUM(A:B!AD10) -> 14700 | AE10: =SUM(A:B!AE10) -> 15840 | AF10: =SUM(A:B!AF10) -> 16980 | ... AJ10: =SUM(A:B!AJ10) -> 27480 | AK10: =SUM(Y10:AJ10) -> 192840 | AL10: =AK10/AK$6 -> 0.00076908151 | AM10: =IFERROR(AK10/V10-1,0) -> -0.17122268 | AO10: 0 | AP10: 0 | AQ10: -1
I11: SOBRANTE COMBUSTIBLE | J11: =SUM(A:B!J11) -> 0 | K11: =SUM(A:B!K11) -> 0 | L11: =SUM(A:B!L11) -> 0 | M11: =SUM(A:B!M11) -> 0 | N11: =SUM(A:B!N11) -> 0 | O11: =SUM(A:B!O11) -> 0 | P11: =SUM(A:B!P11) -> 0 | Q11: =SUM(A:B!Q11) -> 0 | ... U11: =SUM(A:B!U11) -> 0 | V11: =SUM(J11:U11) -> 0 | W11: =V11/V$6 -> 0 | Y11: =SUM(A:B!Y11) -> 0 | Z11: =SUM(A:B!Z11) -> 0 | AA11: =SUM(A:B!AA11) -> 0 | AB11: =SUM(A:B!AB11) -> 0 | AC11: =SUM(A:B!AC11) -> 0 | AD11: =SUM(A:B!AD11) -> 0 | AE11: =SUM(A:B!AE11) -> 0 | AF11: =SUM(A:B!AF11) -> 0 | ... AJ11: =SUM(A:B!AJ11) -> 0 | AK11: =SUM(Y11:AJ11) -> 0 | AL11: =AK11/AK$6 -> 0 | AM11: =IFERROR(AK11/V11-1,0) -> 0 | AO11: 0 | AP11: 0 | AQ11: -1
J12: =SUM(A:B!J12) -> 0 | K12: =SUM(A:B!K12) -> 0 | L12: =SUM(A:B!L12) -> 0 | M12: =SUM(A:B!M12) -> 0 | N12: =SUM(A:B!N12) -> 0 | O12: =SUM(A:B!O12) -> 0 | P12: =SUM(A:B!P12) -> 0 | Q12: =SUM(A:B!Q12) -> 0 | ... U12: =SUM(A:B!U12) -> 0 | V12: =SUM(J12:U12) -> 0 | W12: =V12/V$6 -> 0 | Y12: =SUM(A:B!Y12) -> 0 | Z12: =SUM(A:B!Z12) -> 0 | AA12: =SUM(A:B!AA12) -> 0 | AB12: =SUM(A:B!AB12) -> 0 | AC12: =SUM(A:B!AC12) -> 0 | AD12: =SUM(A:B!AD12) -> 0 | AE12: =SUM(A:B!AE12) -> 0 | AF12: =SUM(A:B!AF12) -> 0 | ... AJ12: =SUM(A:B!AJ12) -> 0 | AK12: =SUM(Y12:AJ12) -> 0 | AL12: =AK12/AK$6 -> 0 | AM12: =IFERROR(AK12/V12-1,0) -> 0 | AO12: 0 | AP12: 0 | AQ12: 0
A13: B - COSTO DE VENTA | E13: ( menos ) | I13: B - COSTO DE VENTA | J13: =SUM(J14:J30) -> 16106343 | K13: =SUM(K14:K30) -> 14418436 | L13: =SUM(L14:L30) -> 16740719 | M13: =SUM(M14:M30) -> 15910764 | N13: =SUM(N14:N30) -> 17765346 | O13: =SUM(O14:O30) -> 17171141 | P13: =SUM(P14:P30) -> 16730167 | Q13: =SUM(Q14:Q30) -> 17141232 | ... V13: =SUM(V14:V30) -> 2.0557055e+08 | W13: =V13/V$6 -> 0.91824653 | Y13: =SUM(Y14:Y30) -> 17094951 | Z13: =SUM(Z14:Z30) -> 15592766 | AA13: =SUM(AA14:AA30) -> 18304073 | AB13: =SUM(AB14:AB30) -> 17779061 | AC13: =SUM(AC14:AC30) -> 19790063 | AD13: =SUM(AD14:AD30) -> 19328858 | AE13: =SUM(AE14:AE30) -> 18583117 | AF13: =SUM(AF14:AF30) -> 18827660 | ... AJ13: =SUM(AJ14:AJ30) -> 20641001 | AK13: =SUM(Y13:AJ13) -> 2.2807815e+08 | AL13: =AK13/AK$6 -> 0.90961774 | AM13: =IFERROR(AK13/V13-1,0) -> 0.10948843 | AO13: 3.7568617e+09 | AP13: 0.85235875 | AQ13: 0.16747315
A14: B - COSTO DE VENTA | C14: COSTO MAGNA | D14: COSTO FORANEO MAGNA | I14: GASOLINA REGULAR | J14: =SUM(A:B!J14) -> 12973548 | K14: =SUM(A:B!K14) -> 11404250 | L14: =SUM(A:B!L14) -> 13331662 | M14: =SUM(A:B!M14) -> 12710487 | N14: =SUM(A:B!N14) -> 14240584 | O14: =SUM(A:B!O14) -> 14028976 | P14: =SUM(A:B!P14) -> 13394436 | Q14: =SUM(A:B!Q14) -> 13534987 | ... U14: =SUM(A:B!U14) -> 14490738 | V14: =SUM(J14:U14) -> 1.6358188e+08 | W14: =V14/V$6 -> 0.73069074 | Y14: =SUM(A:B!Y14) -> 13883313 | Z14: =SUM(A:B!Z14) -> 12500474 | AA14: =SUM(A:B!AA14) -> 14787073 | AB14: =SUM(A:B!AB14) -> 14347590 | AC14: =SUM(A:B!AC14) -> 15960345 | AD14: =SUM(A:B!AD14) -> 15798489 | AE14: =SUM(A:B!AE14) -> 15161171 | AF14: =SUM(A:B!AF14) -> 15119204 | ... AK14: =SUM(A:B!AK14) -> 1.8394188e+08 | AL14: =AK14/AK$6 -> 0.73359417 | AM14: =IFERROR(AK14/V14-1,0) -> 0.12446366 | AO14: 3.5232571e+09 | AP14: 0.7993584 | AQ14: 0.13050349
A15: B - COSTO DE VENTA | C15: COSTO PREMIUM | D15: COSTO FORANEO PREMIUM | I15: GASOLINA PREMIUM | J15: =SUM(A:B!J15) -> 2994699 | K15: =SUM(A:B!K15) -> 2908739 | L15: =SUM(A:B!L15) -> 3286842 | M15: =SUM(A:B!M15) -> 3157931 | N15: =SUM(A:B!N15) -> 3455437 | O15: =SUM(A:B!O15) -> 3184771 | P15: =SUM(A:B!P15) -> 3126152 | Q15: =SUM(A:B!Q15) -> 3519227 | ... U15: =SUM(A:B!U15) -> 3831077.2 | V15: =SUM(J15:U15) -> 40958107 | W15: =V15/V$6 -> 0.18295247 | Y15: =SUM(A:B!Y15) -> 3080784 | Z15: =SUM(A:B!Z15) -> 2973366.4 | AA15: =SUM(A:B!AA15) -> 3369026.9 | AB15: =SUM(A:B!AB15) -> 3257493.6 | AC15: =SUM(A:B!AC15) -> 3620816.1 | AD15: =SUM(A:B!AD15) -> 3359822.1 | AE15: =SUM(A:B!AE15) -> 3242504 | AF15: =SUM(A:B!AF15) -> 3553874.7 | ... AK15: =SUM(A:B!AK15) -> 42276501 | AL15: =AK15/AK$6 -> 0.16860649 | AM15: =IFERROR(AK15/V15-1,0) -> 0.032188835 | AO15: 3.4716629e+08 | AP15: 0.078765269 | AQ15: 0.24745089
A16: B - COSTO DE VENTA | C16: COSTO DIESEL | D16: COSTO FORANEO DIESEL | I16: DIESEL | J16: =SUM(A:B!J16) -> 111034 | K16: =SUM(A:B!K16) -> 101129 | L16: =SUM(A:B!L16) -> 122898 | M16: =SUM(A:B!M16) -> 146759 | N16: =SUM(A:B!N16) -> 171893 | O16: =SUM(A:B!O16) -> 138211 | P16: =SUM(A:B!P16) -> 152522 | Q16: =SUM(A:B!Q16) -> 127651 | ... U16: =SUM(A:B!U16) -> 130644.33 | V16: =SUM(J16:U16) -> 1594674.3 | W16: =V16/V$6 -> 0.0071231223 | Y16: =SUM(A:B!Y16) -> 123989.77 | Z16: =SUM(A:B!Z16) -> 112877.18 | AA16: =SUM(A:B!AA16) -> 135732.7 | AB16: =SUM(A:B!AB16) -> 162121.05 | AC16: =SUM(A:B!AC16) -> 194885.42 | AD16: =SUM(A:B!AD16) -> 158787.2 | AE16: =SUM(A:B!AE16) -> 166769.73 | AF16: =SUM(A:B!AF16) -> 140998.08 | ... AK16: =SUM(A:B!AK16) -> 1705493.2 | AL16: =AK16/AK$6 -> 0.0068018216 | AM16: =IFERROR(AK16/V16-1,0) -> 0.069493096 | AO16: 5.0123784e+08 | AP16: 0.1137211 | AQ16: 0.29638109
A17: B - COSTO DE VENTA | C17: Merma Magna | I17: MERMA GASOLINA REGULAR | J17: =SUM(A:B!J17) -> 0 | K17: =SUM(A:B!K17) -> 451 | L17: =SUM(A:B!L17) -> 0 | M17: =SUM(A:B!M17) -> 863 | N17: =SUM(A:B!N17) -> 0 | O17: =SUM(A:B!O17) -> 0 | P17: =SUM(A:B!P17) -> 1786 | Q17: =SUM(A:B!Q17) -> 0 | ... U17: =SUM(A:B!U17) -> 136.88889 | V17: =SUM(J17:U17) -> 3647.5556 | W17: =V17/V$6 -> 1.6292972e-05 | Y17: =SUM(A:B!Y17) -> 0 | Z17: =SUM(A:B!Z17) -> 0 | AA17: =SUM(A:B!AA17) -> 0 | AB17: =SUM(A:B!AB17) -> 0 | AC17: =SUM(A:B!AC17) -> 0 | AD17: =SUM(A:B!AD17) -> 0 | AE17: =SUM(A:B!AE17) -> 0 | AF17: =SUM(A:B!AF17) -> 0 | ... AK17: =SUM(A:B!AK17) -> 0 | AL17: =AK17/AK$6 -> 0 | AM17: =IFERROR(AK17/V17-1,0) -> -1 | AO17: 0 | AP17: 0 | AQ17: -1
A18: B - COSTO DE VENTA | C18: Merma Premium | I18: MERMA GASOLINA PREMIUM | J18: =SUM(A:B!J18) -> 10118 | K18: =SUM(A:B!K18) -> 11513 | L18: =SUM(A:B!L18) -> 5892 | M18: =SUM(A:B!M18) -> 235 | N18: =SUM(A:B!N18) -> 5571 | O18: =SUM(A:B!O18) -> 4098 | P18: =SUM(A:B!P18) -> 6579 | Q18: =SUM(A:B!Q18) -> 0 | ... U18: =SUM(A:B!U18) -> 6448.4444 | V18: =SUM(J18:U18) -> 69799.778 | W18: =V18/V$6 -> 0.00031178301 | Y18: =SUM(A:B!Y18) -> 0 | Z18: =SUM(A:B!Z18) -> 0 | AA18: =SUM(A:B!AA18) -> 0 | AB18: =SUM(A:B!AB18) -> 0 | AC18: =SUM(A:B!AC18) -> 0 | AD18: =SUM(A:B!AD18) -> 0 | AE18: =SUM(A:B!AE18) -> 0 | AF18: =SUM(A:B!AF18) -> 0 | ... AK18: =SUM(A:B!AK18) -> 0 | AL18: =AK18/AK$6 -> 0 | AM18: =IFERROR(AK18/V18-1,0) -> -1 | AO18: 0 | AP18: 0 | AQ18: -1
A19: B - COSTO DE VENTA | C19: Merma Diesel | I19: MERMA DIESEL | J19: =SUM(A:B!J19) -> -2264 | K19: =SUM(A:B!K19) -> 0 | L19: =SUM(A:B!L19) -> 203 | M19: =SUM(A:B!M19) -> 0 | N19: =SUM(A:B!N19) -> 0 | O19: =SUM(A:B!O19) -> 1796 | P19: =SUM(A:B!P19) -> 0 | Q19: =SUM(A:B!Q19) -> 0 | ... U19: =SUM(A:B!U19) -> 2120.8889 | V19: =SUM(J19:U19) -> 8218.5556 | W19: =V19/V$6 -> 3.6710804e-05 | Y19: =SUM(A:B!Y19) -> 0 | Z19: =SUM(A:B!Z19) -> 0 | AA19: =SUM(A:B!AA19) -> 0 | AB19: =SUM(A:B!AB19) -> 0 | AC19: =SUM(A:B!AC19) -> 0 | AD19: =SUM(A:B!AD19) -> 0 | AE19: =SUM(A:B!AE19) -> 0 | AF19: =SUM(A:B!AF19) -> 0 | ... AK19: =SUM(A:B!AK19) -> 0 | AL19: =AK19/AK$6 -> 0 | AM19: =IFERROR(AK19/V19-1,0) -> -1 | AO19: 0 | AP19: 0 | AQ19: -1
A20: B - COSTO DE VENTA | C20: ADITIVO PARA GASOLINA TMAXIMA (REGULAR) | D20: ADITIVO PARA GASOLINA TMAXIMA( REGULAR) | I20: SOBRANTE MAGNA | J20: =SUM(A:B!J20) -> -1655 | K20: =SUM(A:B!K20) -> -16260 | L20: =SUM(A:B!L20) -> -47534 | M20: =SUM(A:B!M20) -> -80019 | N20: =SUM(A:B!N20) -> -101412 | O20: =SUM(A:B!O20) -> -102362 | P20: =SUM(A:B!P20) -> -41438 | Q20: =SUM(A:B!Q20) -> -73785 | ... U20: =SUM(A:B!U20) -> -75022.778 | V20: =SUM(J20:U20) -> -764556.11 | W20: =V20/V$6 -> -0.0034151341 | Y20: =SUM(A:B!Y20) -> 0 | Z20: =SUM(A:B!Z20) -> 0 | AA20: =SUM(A:B!AA20) -> 0 | AB20: =SUM(A:B!AB20) -> 0 | AC20: =SUM(A:B!AC20) -> 0 | AD20: =SUM(A:B!AD20) -> 0 | AE20: =SUM(A:B!AE20) -> 0 | AF20: =SUM(A:B!AF20) -> 0 | ... AK20: =SUM(A:B!AK20) -> 0 | AL20: =AK20/AK$6 -> 0 | AM20: =IFERROR(AK20/V20-1,0) -> -1 | AO20: 0 | AP20: 0 | AQ20: -1
A21: B - COSTO DE VENTA | C21: ADITIVO PARA GASOLINA TSUPER (PREMIUM) | I21: SOBRANTE PREMIUM | J21: =SUM(A:B!J21) -> 15107 | K21: =SUM(A:B!K21) -> 4291 | L21: =SUM(A:B!L21) -> -4238 | M21: =SUM(A:B!M21) -> -6859 | N21: =SUM(A:B!N21) -> -21701 | O21: =SUM(A:B!O21) -> -91077 | P21: =SUM(A:B!P21) -> 77691 | Q21: =SUM(A:B!Q21) -> -5176 | ... U21: =SUM(A:B!U21) -> -13801.778 | V21: =SUM(J21:U21) -> -87169.111 | W21: =V21/V$6 -> -0.00038936868 | Y21: =SUM(A:B!Y21) -> 0 | Z21: =SUM(A:B!Z21) -> 0 | AA21: =SUM(A:B!AA21) -> 0 | AB21: =SUM(A:B!AB21) -> 0 | AC21: =SUM(A:B!AC21) -> 0 | AD21: =SUM(A:B!AD21) -> 0 | AE21: =SUM(A:B!AE21) -> 0 | AF21: =SUM(A:B!AF21) -> 0 | ... AK21: =SUM(A:B!AK21) -> 0 | AL21: =AK21/AK$6 -> 0 | AM21: =IFERROR(AK21/V21-1,0) -> -1 | AO21: 0 | AP21: 0 | AQ21: -1
A22: B - COSTO DE VENTA | C22: FLETE MAGNA | I22: SOBRANTE DIESEL | J22: =SUM(A:B!J22) -> 0 | K22: =SUM(A:B!K22) -> -1925 | L22: =SUM(A:B!L22) -> -2961 | M22: =SUM(A:B!M22) -> -232 | N22: =SUM(A:B!N22) -> -4780 | O22: =SUM(A:B!O22) -> 0 | P22: =SUM(A:B!P22) -> -2453 | Q22: =SUM(A:B!Q22) -> -1311 | ... U22: =SUM(A:B!U22) -> -2245.2222 | V22: =SUM(J22:U22) -> -22642.889 | W22: =V22/V$6 -> -0.0001011417 | Y22: =SUM(A:B!Y22) -> 0 | Z22: =SUM(A:B!Z22) -> 0 | AA22: =SUM(A:B!AA22) -> 0 | AB22: =SUM(A:B!AB22) -> 0 | AC22: =SUM(A:B!AC22) -> 0 | AD22: =SUM(A:B!AD22) -> 0 | AE22: =SUM(A:B!AE22) -> 0 | AF22: =SUM(A:B!AF22) -> 0 | ... AK22: =SUM(A:B!AK22) -> 0 | AL22: =AK22/AK$6 -> 0 | AM22: =IFERROR(AK22/V22-1,0) -> -1 | AO22: 0 | AP22: 0 | AQ22: -1
A23: B - COSTO DE VENTA | C23: FLETE PREMIUM | I23: ADITIVO TOTAL POWER GASOLINA REG | J23: =SUM(A:B!J23) -> 0 | K23: =SUM(A:B!K23) -> 0 | L23: =SUM(A:B!L23) -> 26670 | M23: =SUM(A:B!M23) -> -26670 | N23: =SUM(A:B!N23) -> 0 | O23: =SUM(A:B!O23) -> 0 | P23: =SUM(A:B!P23) -> 0 | Q23: =SUM(A:B!Q23) -> 0 | ... U23: =SUM(A:B!U23) -> 0 | V23: =SUM(J23:U23) -> 0 | W23: =V23/V$6 -> 0 | Y23: =SUM(A:B!Y23) -> 0 | Z23: =SUM(A:B!Z23) -> 0 | AA23: =SUM(A:B!AA23) -> 0 | AB23: =SUM(A:B!AB23) -> 0 | AC23: =SUM(A:B!AC23) -> 0 | AD23: =SUM(A:B!AD23) -> 0 | AE23: =SUM(A:B!AE23) -> 0 | AF23: =SUM(A:B!AF23) -> 0 | ... AK23: =SUM(A:B!AK23) -> 0 | AL23: =AK23/AK$6 -> 0 | AM23: =IFERROR(AK23/V23-1,0) -> 0 | AO23: 0 | AP23: 0 | AQ23: -1
A24: B - COSTO DE VENTA | C24: FLETE DIESEL | I24: ADITIVO TOTAL POWER GASOLINA PREM | J24: =SUM(A:B!J24) -> 0 | K24: =SUM(A:B!K24) -> 0 | L24: =SUM(A:B!L24) -> 6840 | M24: =SUM(A:B!M24) -> -6840 | N24: =SUM(A:B!N24) -> 0 | O24: =SUM(A:B!O24) -> 0 | P24: =SUM(A:B!P24) -> 0 | Q24: =SUM(A:B!Q24) -> 0 | ... U24: =SUM(A:B!U24) -> 0 | V24: =SUM(J24:U24) -> 0 | W24: =V24/V$6 -> 0 | Y24: =SUM(A:B!Y24) -> 0 | Z24: =SUM(A:B!Z24) -> 0 | AA24: =SUM(A:B!AA24) -> 0 | AB24: =SUM(A:B!AB24) -> 0 | AC24: =SUM(A:B!AC24) -> 0 | AD24: =SUM(A:B!AD24) -> 0 | AE24: =SUM(A:B!AE24) -> 0 | AF24: =SUM(A:B!AF24) -> 0 | ... AK24: =SUM(A:B!AK24) -> 0 | AL24: =AK24/AK$6 -> 0 | AM24: =IFERROR(AK24/V24-1,0) -> 0 | AO24: 0 | AP24: 0 | AQ24: -1
A25: B - COSTO DE VENTA | C25: Estimulo IEPS Magna | D25: INGRESOS FORANEOS MAGNA | I25: FLETE GASOLINA REGULAR | J25: =SUM(A:B!J25) -> 0 | K25: =SUM(A:B!K25) -> 0 | L25: =SUM(A:B!L25) -> 0 | M25: =SUM(A:B!M25) -> 1204 | N25: =SUM(A:B!N25) -> 2511 | O25: =SUM(A:B!O25) -> 0 | P25: =SUM(A:B!P25) -> 2415 | Q25: =SUM(A:B!Q25) -> 0 | ... U25: =SUM(A:B!U25) -> 4740.8889 | V25: =SUM(J25:U25) -> 25093.556 | W25: =V25/V$6 -> 0.00011208838 | Y25: =SUM(A:B!Y25) -> 0 | Z25: =SUM(A:B!Z25) -> 0 | AA25: =SUM(A:B!AA25) -> 0 | AB25: =SUM(A:B!AB25) -> 0 | AC25: =SUM(A:B!AC25) -> 0 | AD25: =SUM(A:B!AD25) -> 0 | AE25: =SUM(A:B!AE25) -> 0 | AF25: =SUM(A:B!AF25) -> 0 | ... AK25: =SUM(A:B!AK25) -> 0 | AL25: =AK25/AK$6 -> 0 | AM25: =IFERROR(AK25/V25-1,0) -> -1 | AO25: -5.7784199e+08 | AP25: -0.13110109 | AQ25: 0.066558616
I26: FLETE GASOLINA PREMIUM | J26: =SUM(A:B!J26) -> 0 | K26: =SUM(A:B!K26) -> 0 | L26: =SUM(A:B!L26) -> 0 | M26: =SUM(A:B!M26) -> 0 | N26: =SUM(A:B!N26) -> 1209 | O26: =SUM(A:B!O26) -> 0 | P26: =SUM(A:B!P26) -> 0 | Q26: =SUM(A:B!Q26) -> 0 | ... U26: =SUM(A:B!U26) -> 2136 | V26: =SUM(J26:U26) -> 9753 | W26: =V26/V$6 -> 4.356489e-05 | Y26: =SUM(A:B!Y26) -> 0 | Z26: =SUM(A:B!Z26) -> 0 | AA26: =SUM(A:B!AA26) -> 0 | AB26: =SUM(A:B!AB26) -> 0 | AC26: =SUM(A:B!AC26) -> 0 | AD26: =SUM(A:B!AD26) -> 0 | AE26: =SUM(A:B!AE26) -> 0 | AF26: =SUM(A:B!AF26) -> 0 | ... AK26: =SUM(A:B!AK26) -> 0 | AL26: =AK26/AK$6 -> 0 | AM26: =IFERROR(AK26/V26-1,0) -> -1 | AO26: -36957483 | AP26: -0.0083849329 | AQ26: 0.064257395
I27: FLETE DIESEL | J27: =SUM(A:B!J27) -> 0 | K27: =SUM(A:B!K27) -> 0 | L27: =SUM(A:B!L27) -> 0 | M27: =SUM(A:B!M27) -> 0 | N27: =SUM(A:B!N27) -> 0 | O27: =SUM(A:B!O27) -> 0 | P27: =SUM(A:B!P27) -> 0 | Q27: =SUM(A:B!Q27) -> 0 | ... U27: =SUM(A:B!U27) -> 0 | V27: =SUM(J27:U27) -> 0 | W27: =V27/V$6 -> 0 | Y27: =SUM(A:B!Y27) -> 0 | Z27: =SUM(A:B!Z27) -> 0 | AA27: =SUM(A:B!AA27) -> 0 | AB27: =SUM(A:B!AB27) -> 0 | AC27: =SUM(A:B!AC27) -> 0 | AD27: =SUM(A:B!AD27) -> 0 | AE27: =SUM(A:B!AE27) -> 0 | AF27: =SUM(A:B!AF27) -> 0 | ... AK27: =SUM(A:B!AK27) -> 0 | AL27: =AK27/AK$6 -> 0 | AM27: =IFERROR(AK27/V27-1,0) -> 0 | AO27: 0 | AP27: 0 | AQ27: -1
I28: ESTIMULO REGULAR | J28: =SUM(A:B!J28) -> 0 | K28: =SUM(A:B!K28) -> 0 | L28: =SUM(A:B!L28) -> 0 | M28: =SUM(A:B!M28) -> 0 | N28: =SUM(A:B!N28) -> 0 | O28: =SUM(A:B!O28) -> 0 | P28: =SUM(A:B!P28) -> 0 | Q28: =SUM(A:B!Q28) -> 0 | ... U28: =SUM(A:B!U28) -> 0 | V28: =SUM(J28:U28) -> 0 | W28: =V28/V$6 -> 0 | Y28: =SUM(A:B!Y28) -> 0 | Z28: =SUM(A:B!Z28) -> 0 | AA28: =SUM(A:B!AA28) -> 0 | AB28: =SUM(A:B!AB28) -> 0 | AC28: =SUM(A:B!AC28) -> 0 | AD28: =SUM(A:B!AD28) -> 0 | AE28: =SUM(A:B!AE28) -> 0 | AF28: =SUM(A:B!AF28) -> 0 | ... AK28: =SUM(A:B!AK28) -> 0 | AL28: =AK28/AK$6 -> 0 | AM28: =IFERROR(AK28/V28-1,0) -> 0 | AO28: 6.507445e+08 | AP28: 0.14764125 | AQ28: 0.17255416
I29: ESTIMULO PREMIUM | J29: =SUM(A:B!J29) -> 0 | K29: =SUM(A:B!K29) -> 0 | L29: =SUM(A:B!L29) -> 0 | M29: =SUM(A:B!M29) -> 0 | N29: =SUM(A:B!N29) -> 0 | O29: =SUM(A:B!O29) -> 0 | P29: =SUM(A:B!P29) -> 0 | Q29: =SUM(A:B!Q29) -> 0 | ... U29: =SUM(A:B!U29) -> 0 | V29: =SUM(J29:U29) -> 0 | W29: =V29/V$6 -> 0 | Y29: =SUM(A:B!Y29) -> 0 | Z29: =SUM(A:B!Z29) -> 0 | AA29: =SUM(A:B!AA29) -> 0 | AB29: =SUM(A:B!AB29) -> 0 | AC29: =SUM(A:B!AC29) -> 0 | AD29: =SUM(A:B!AD29) -> 0 | AE29: =SUM(A:B!AE29) -> 0 | AF29: =SUM(A:B!AF29) -> 0 | ... AK29: =SUM(A:B!AK29) -> 0 | AL29: =AK29/AK$6 -> 0 | AM29: =IFERROR(AK29/V29-1,0) -> 0 | AO29: 5.4343746e+08 | AP29: #REF! | AQ29: 0.13532128
I30: COSTO ACEITES Y LUBRICANTES | J30: =SUM(A:B!J30) -> 5756 | K30: =SUM(A:B!K30) -> 6248 | L30: =SUM(A:B!L30) -> 14445 | M30: =SUM(A:B!M30) -> 13905 | N30: =SUM(A:B!N30) -> 16034 | O30: =SUM(A:B!O30) -> 6728 | P30: =SUM(A:B!P30) -> 12477 | Q30: =SUM(A:B!Q30) -> 39639 | ... U30: =SUM(A:B!U30) -> 19627.444 | V30: =SUM(J30:U30) -> 193741.78 | W30: =V30/V$6 -> 0.00086540954 | Y30: =SUM(A:B!Y30) -> 6864 | Z30: =SUM(A:B!Z30) -> 6048 | AA30: =SUM(A:B!AA30) -> 12240 | AB30: =SUM(A:B!AB30) -> 11856 | AC30: =SUM(A:B!AC30) -> 14016 | AD30: =SUM(A:B!AD30) -> 11760 | AE30: =SUM(A:B!AE30) -> 12672 | AF30: =SUM(A:B!AF30) -> 13584 | ... AK30: =SUM(A:B!AK30) -> 154272 | AL30: =AK30/AK$6 -> 0.00061526521 | AM30: =IFERROR(AK30/V30-1,0) -> -0.20372363 | AO30: 42647062 | AP30: #REF! | AQ30: 0.48513341
I31: BONIFICACION COMPRA DE COMBUSTIBLE MAGNA | J31: =SUM(A:B!J31) -> -169846 | K31: =SUM(A:B!K31) -> -167978 | L31: =SUM(A:B!L31) -> -186098 | M31: =SUM(A:B!M31) -> -197938 | N31: =SUM(A:B!N31) -> -216128 | O31: =SUM(A:B!O31) -> -198097 | P31: =SUM(A:B!P31) -> -210124 | Q31: =SUM(A:B!Q31) -> -206915 | ... U31: =SUM(A:B!U31) -> -219100.33 | V31: =SUM(J31:U31) -> -2429525.3 | W31: =V31/V$6 -> -0.010852251 | Y31: =SUM(A:B!Y31) -> 0 | Z31: =SUM(A:B!Z31) -> 0 | AA31: =SUM(A:B!AA31) -> 0 | AB31: =SUM(A:B!AB31) -> 0 | AC31: =SUM(A:B!AC31) -> 0 | AD31: =SUM(A:B!AD31) -> 0 | AE31: =SUM(A:B!AE31) -> 0 | AF31: =SUM(A:B!AF31) -> 0 | ... AK31: =SUM(A:B!AK31) -> 0 | AL31: =AK31/AK$6 -> 0 | AM31: =IFERROR(AK31/V31-1,0) -> -1 | AO31: 64659974 | AP31: #REF! | AQ31: 0.41061113
I32: BONIFICACION COMPRA DE COMBUSTIBLE PREMIUM | J32: =SUM(A:B!J32) -> -30257 | K32: =SUM(A:B!K32) -> -31282 | L32: =SUM(A:B!L32) -> -37037 | M32: =SUM(A:B!M32) -> -29914 | N32: =SUM(A:B!N32) -> -42589 | O32: =SUM(A:B!O32) -> -30035 | P32: =SUM(A:B!P32) -> -37039 | Q32: =SUM(A:B!Q32) -> -37056 | ... U32: =SUM(A:B!U32) -> -42628.444 | V32: =SUM(J32:U32) -> -445722.78 | W32: =V32/V$6 -> -0.0019909632 | Y32: =SUM(A:B!Y32) -> 0 | Z32: =SUM(A:B!Z32) -> 0 | AA32: =SUM(A:B!AA32) -> 0 | AB32: =SUM(A:B!AB32) -> 0 | AC32: =SUM(A:B!AC32) -> 0 | AD32: =SUM(A:B!AD32) -> 0 | AE32: =SUM(A:B!AE32) -> 0 | AF32: =SUM(A:B!AF32) -> 0 | ... AK32: =SUM(A:B!AK32) -> 0 | AL32: =AK32/AK$6 -> 0 | AM32: =IFERROR(AK32/V32-1,0) -> -1 | AO32: 0 | AP32: #REF! | AQ32: -1
I33: BONIFICACION COMPRA DE COMBUSTIBLE DIESEL | J33: =SUM(A:B!J33) -> -3485 | K33: =SUM(A:B!K33) -> 0 | L33: =SUM(A:B!L33) -> -2310 | M33: =SUM(A:B!M33) -> 0 | N33: =SUM(A:B!N33) -> -2310 | O33: =SUM(A:B!O33) -> -4642 | P33: =SUM(A:B!P33) -> 0 | Q33: =SUM(A:B!Q33) -> 0 | ... U33: =SUM(A:B!U33) -> -2056 | V33: =SUM(J33:U33) -> -20971 | W33: =V33/V$6 -> -9.3673671e-05 | Y33: =SUM(A:B!Y33) -> 0 | Z33: =SUM(A:B!Z33) -> 0 | AA33: =SUM(A:B!AA33) -> 0 | AB33: =SUM(A:B!AB33) -> 0 | AC33: =SUM(A:B!AC33) -> 0 | AD33: =SUM(A:B!AD33) -> 0 | AE33: =SUM(A:B!AE33) -> 0 | AF33: =SUM(A:B!AF33) -> 0 | ... AK33: =SUM(A:B!AK33) -> 0 | AL33: =AK33/AK$6 -> 0 | AM33: =IFERROR(AK33/V33-1,0) -> -1 | AO33: 2.4593624e+08 | AQ33: 0.1359541
I34: MARGEN DE UTILIDAD | J34: =J6-J13 -> 1086481 | K34: =K6-K13 -> 1172394 | L34: =L6-L13 -> 1513835 | M34: =M6-M13 -> 1602934 | N34: =N6-N13 -> 1748688 | O34: =O6-O13 -> 1765808 | P34: =P6-P13 -> 1408449 | Q34: =Q6-Q13 -> 1480274 | ... V34: =V6-V13 -> 18302389 | W34: =V34/V$6 -> 0.081753468 | Y34: =Y6-Y13 -> 1685659.5 | Z34: =Z6-Z13 -> 1442426 | AA34: =AA6-AA13 -> 1965910.9 | AB34: =AB6-AB13 -> 1708121.1 | AC34: =AC6-AC13 -> 2074145.8 | AD34: =AD6-AD13 -> 1868457.3 | AE34: =AE6-AE13 -> 1787126.4 | AF34: =AF6-AF13 -> 1869483 | ... AK34: =AK6-AK13 -> 22662506 | AL34: =AK34/AK$6 -> 0.090382256 | AM34: =IFERROR(AK34/V34-1,0) -> 0.23822664 | AO34: 2.0184766e+08 | AP34: 0.045795303 | AQ34: 0.11498405
I35: *Regular | J35: =SUM(A:B!J35) -> 1001085 | K35: =SUM(A:B!K35) -> 1097495 | L35: =SUM(A:B!L35) -> 1401632 | M35: =SUM(A:B!M35) -> 1479528 | N35: =SUM(A:B!N35) -> 1551893 | O35: =SUM(A:B!O35) -> 1507543 | P35: =SUM(A:B!P35) -> 1399383 | Q35: =SUM(A:B!Q35) -> 1423247 | ... U35: =SUM(A:B!U35) -> 1533365 | V35: =SUM(J35:U35) -> 16995266 | W35: =V35/V$39 -> -810.41753 | Y35: =SUM(A:B!Y35) -> 1319638.3 | Z35: =SUM(A:B!Z35) -> 1099189.3 | AA35: =SUM(A:B!AA35) -> 1550720.4 | AB35: =SUM(A:B!AB35) -> 1327424.3 | AC35: =SUM(A:B!AC35) -> 1620445.9 | AD35: =SUM(A:B!AD35) -> 1486340.2 | AE35: =SUM(A:B!AE35) -> 1402949.1 | AF35: =SUM(A:B!AF35) -> 1433617.2 | ... AJ35: =SUM(A:B!AJ35) -> 1561605.4 | AK35: =SUM(Y35:AJ35) -> 17622120 | AL35: =AK35/AK$39 -> #DIV/0! | AM35: =IFERROR(AK35/V35-1,0) -> 0.036884058 | AO35: 17513400 | AP35: 0.0039734494 | AQ35: 0.2160961
I36: *Premium | J36: =SUM(A:B!J36) -> 270882 | K36: =SUM(A:B!K36) -> 262355 | L36: =SUM(A:B!L36) -> 319414 | M36: =SUM(A:B!M36) -> 332510 | N36: =SUM(A:B!N36) -> 427513 | O36: =SUM(A:B!O36) -> 460370 | P36: =SUM(A:B!P36) -> 237976 | Q36: =SUM(A:B!Q36) -> 314082 | ... U36: =SUM(A:B!U36) -> 350882.22 | V36: =SUM(J36:U36) -> 4028630.9 | W36: =V36/V$39 -> -192.10485 | Y36: =SUM(A:B!Y36) -> 354333.45 | Z36: =SUM(A:B!Z36) -> 333183.19 | AA36: =SUM(A:B!AA36) -> 400038.43 | AB36: =SUM(A:B!AB36) -> 363447.05 | AC36: =SUM(A:B!AC36) -> 432928.69 | AD36: =SUM(A:B!AD36) -> 368281.3 | AE36: =SUM(A:B!AE36) -> 367117.93 | AF36: =SUM(A:B!AF36) -> 422464.64 | ... AJ36: =SUM(A:B!AJ36) -> 444298.51 | AK36: =SUM(Y36:AJ36) -> 4864758.7 | AL36: =AK36/AK$39 -> #DIV/0! | AM36: =IFERROR(AK36/V36-1,0) -> 0.2075464 | AO36: 26575182 | AP36: 0.0060293911 | AQ36: 0.26135799
I37: *Diesel | J37: =SUM(A:B!J37) -> 14035 | K37: =SUM(A:B!K37) -> 9009 | L37: =SUM(A:B!L37) -> 12996 | M37: =SUM(A:B!M37) -> 11131 | N37: =SUM(A:B!N37) -> 24319 | O37: =SUM(A:B!O37) -> 16600 | P37: =SUM(A:B!P37) -> 12364 | Q37: =SUM(A:B!Q37) -> 4315 | ... U37: =SUM(A:B!U37) -> 11790.667 | V37: =SUM(J37:U37) -> 151931.67 | W37: =V37/V$39 -> -7.2448461 | Y37: =SUM(A:B!Y37) -> 9971.78 | Z37: =SUM(A:B!Z37) -> 8541.52 | AA37: =SUM(A:B!AA37) -> 12092 | AB37: =SUM(A:B!AB37) -> 14285.7 | AC37: =SUM(A:B!AC37) -> 17267.23 | AD37: =SUM(A:B!AD37) -> 10895.8 | AE37: =SUM(A:B!AE37) -> 13891.32 | AF37: =SUM(A:B!AF37) -> 10005.12 | ... AJ37: =SUM(A:B!AJ37) -> 9772.19 | AK37: =SUM(Y37:AJ37) -> 137058.81 | AL37: =AK37/AK$39 -> #DIV/0! | AM37: =IFERROR(AK37/V37-1,0) -> -0.09789175 | AO37: 2.6459886 | AQ37: 0.029597448
I38: * Aceites y Lubricantes | J38: =SUM(A:B!J38) -> 4066 | K38: =SUM(A:B!K38) -> 2794 | L38: =SUM(A:B!L38) -> 5238 | M38: =SUM(A:B!M38) -> 7617 | N38: =SUM(A:B!N38) -> 5989 | O38: =SUM(A:B!O38) -> 14066 | P38: =SUM(A:B!P38) -> 5887 | Q38: =SUM(A:B!Q38) -> -17400 | ... U38: =SUM(A:B!U38) -> 3011.3333 | V38: =SUM(J38:U38) -> 40302.333 | W38: =V38/V$39 -> -1.9218127 | Y38: =SUM(A:B!Y38) -> 0 | Z38: =SUM(A:B!Z38) -> 0 | AA38: =SUM(A:B!AA38) -> 0 | AB38: =SUM(A:B!AB38) -> 0 | AC38: =SUM(A:B!AC38) -> 0 | AD38: =SUM(A:B!AD38) -> 0 | AE38: =SUM(A:B!AE38) -> 0 | AF38: =SUM(A:B!AF38) -> 0 | ... AJ38: =SUM(A:B!AJ38) -> 0 | AK38: =SUM(Y38:AJ38) -> 0 | AL38: =AK38/AK$39 -> #DIV/0! | AM38: =IFERROR(AK38/V38-1,0) -> -1 | AO38: 2.6923149 | AP38: 6.108338e-10 | AQ38: 0.03693009
I39: Litros vendidos | J39: =SUM(A:B!J33) -> -3485 | K39: =SUM(A:B!K33) -> 0 | L39: =SUM(A:B!L33) -> -2310 | M39: =SUM(A:B!M33) -> 0 | N39: =SUM(A:B!N33) -> -2310 | O39: =SUM(A:B!O33) -> -4642 | P39: =SUM(A:B!P33) -> 0 | Q39: =SUM(A:B!Q33) -> 0 | ... U39: =SUM(A:B!U33) -> -2056 | V39: =SUM(J39:U39) -> -20971 | W39: =V39/V$39 -> 1 | Y39: =SUM(A:B!Y33) -> 0 | Z39: =SUM(A:B!Z33) -> 0 | AA39: =SUM(A:B!AA33) -> 0 | AB39: =SUM(A:B!AB33) -> 0 | AC39: =SUM(A:B!AC33) -> 0 | AD39: =SUM(A:B!AD33) -> 0 | AE39: =SUM(A:B!AE33) -> 0 | AF39: =SUM(A:B!AF33) -> 0 | ... AJ39: =SUM(A:B!AJ33) -> 0 | AK39: =SUM(Y39:AJ39) -> 0 | AL39: =AK39/AK$39 -> #DIV/0! | AM39: =IFERROR(AK39/V39-1,0) -> -1 | AO39: 2.4351104 | AP39: 5.5247911e-10 | AQ39: 0.11346523
I40: Maxima | J40: =SUM(A:B!J40) -> 652504 | K40: =SUM(A:B!K40) -> 579451 | L40: =SUM(A:B!L40) -> 706034 | M40: =SUM(A:B!M40) -> 653794 | N40: =SUM(A:B!N40) -> 753315 | O40: =SUM(A:B!O40) -> 741483 | P40: =SUM(A:B!P40) -> 707921 | Q40: =SUM(A:B!Q40) -> 715486 | ... U40: =SUM(A:B!U40) -> 782396 | V40: =SUM(J40:U40) -> 8626933 | W40: =V40/V$39 -> -411.37442 | Y40: =SUM(A:B!Y40) -> 710418.3 | Z40: =SUM(A:B!Z40) -> 635498.3 | AA40: =SUM(A:B!AA40) -> 763448.3 | AB40: =SUM(A:B!AB40) -> 732477.3 | AC40: =SUM(A:B!AC40) -> 821532.3 | AD40: =SUM(A:B!AD40) -> 807702.3 | AE40: =SUM(A:B!AE40) -> 774024.3 | AF40: =SUM(A:B!AF40) -> 773496.3 | ... AJ40: =SUM(A:B!AJ40) -> 847993.3 | AK40: =SUM(Y40:AJ40) -> 9418878.6 | AL40: =AK40/AK$39 -> #DIV/0! | AM40: =IFERROR(AK40/V40-1,0) -> 0.091799205 | AO40: 2.4330962 | AP40: 5.5202214e-10 | AQ40: 0.11307939
I41: Super | J41: =SUM(A:B!J41) -> 147578 | K41: =SUM(A:B!K41) -> 142154 | L41: =SUM(A:B!L41) -> 160901 | M41: =SUM(A:B!M41) -> 151568 | N41: =SUM(A:B!N41) -> 172299 | O41: =SUM(A:B!O41) -> 158797 | P41: =SUM(A:B!P41) -> 153571 | Q41: =SUM(A:B!Q41) -> 166736 | ... U41: =SUM(A:B!U41) -> 185941 | V41: =SUM(J41:U41) -> 2002797 | W41: =V41/V$39 -> -95.503171 | Y41: =SUM(A:B!Y41) -> 150531 | Z41: =SUM(A:B!Z41) -> 144897 | AA41: =SUM(A:B!AA41) -> 165165 | AB41: =SUM(A:B!AB41) -> 158674 | AC41: =SUM(A:B!AC41) -> 177640 | AD41: =SUM(A:B!AD41) -> 163370 | AE41: =SUM(A:B!AE41) -> 158178 | AF41: =SUM(A:B!AF41) -> 174248 | ... AJ41: =SUM(A:B!AJ41) -> 190869 | AK41: =SUM(Y41:AJ41) -> 2065787 | AL41: =AK41/AK$39 -> #DIV/0! | AM41: =IFERROR(AK41/V41-1,0) -> 0.031451016
E42: ( menos ) | I42: Diesel | J42: =SUM(A:B!J42) -> 5372 | K42: =SUM(A:B!K42) -> 4872 | L42: =SUM(A:B!L42) -> 5890 | M42: =SUM(A:B!M42) -> 7047 | N42: =SUM(A:B!N42) -> 8416 | O42: =SUM(A:B!O42) -> 6746 | P42: =SUM(A:B!P42) -> 7174 | Q42: =SUM(A:B!Q42) -> 6006 | ... U42: =SUM(A:B!U42) -> 5259 | V42: =SUM(J42:U42) -> 74500 | W42: =V42/V$39 -> -3.5525249 | Y42: =SUM(A:B!Y42) -> 5479 | Z42: =SUM(A:B!Z42) -> 4966 | AA42: =SUM(A:B!AA42) -> 6046 | AB42: =SUM(A:B!AB42) -> 7215 | AC42: =SUM(A:B!AC42) -> 8677 | AD42: =SUM(A:B!AD42) -> 6940 | AE42: =SUM(A:B!AE42) -> 7389 | AF42: =SUM(A:B!AF42) -> 6176 | ... AJ42: =SUM(A:B!AJ42) -> 5399 | AK42: =SUM(Y42:AJ42) -> 75360 | AL42: =AK42/AK$39 -> #DIV/0! | AM42: =IFERROR(AK42/V42-1,0) -> 0.011543624
I43: Margen de utilidad por combustible | J43: =J34/J39 -> -311.75925 | K43: =K34/K39 -> #DIV/0! | L43: =L34/L39 -> -655.33983 | M43: =M34/M39 -> #DIV/0! | N43: =N34/N39 -> -757.00779 | O43: =O34/O39 -> -380.3981 | P43: =P34/P39 -> #DIV/0! | Q43: =Q34/Q39 -> #DIV/0! | ... U43: =U34/U39 -> -793.23033 | V43: =AVERAGE(J43:U43) -> #DIV/0! | W43: =V43/V$39 -> #DIV/0! | Y43: =Y34/Y39 -> #DIV/0! | Z43: =Z34/Z39 -> #DIV/0! | AA43: =AA34/AA39 -> #DIV/0! | AB43: =AB34/AB39 -> #DIV/0! | AC43: =AC34/AC39 -> #DIV/0! | AD43: =AD34/AD39 -> #DIV/0! | AE43: =AE34/AE39 -> #DIV/0! | AF43: =AF34/AF39 -> #DIV/0! | ... AK43: =AK34/AK39 -> #DIV/0! | AL43: =AK43/AK$39 -> #DIV/0! | AM43: =IFERROR(AK43/V43-1,0) -> 0
A44: E - GASTOS DE OPERACIÓN | B44: estaciones | I44: Maxima | J44: =IFERROR((J7+J11-(J14+J17+J23+J25+J28))/J40,0) -> 1.2713853 | K44: =IFERROR((K7+K11-(K14+K17+K23+K25+K28))/K40,0) -> 1.5760746 | L44: =IFERROR((L7+L11-(L14+L17+L23+L25+L28))/L40,0) -> 1.6543113 | M44: =IFERROR((M7+M11-(M14+M17+M23+M25+M28))/M40,0) -> 1.8378434 | N44: =IFERROR((N7+N11-(N14+N17+N23+N25+N28))/N40,0) -> 1.6385602 | O44: =IFERROR((O7+O11-(O14+O17+O23+O25+O28))/O40,0) -> 1.6279321 | P44: =IFERROR((P7+P11-(P14+P17+P23+P25+P28))/P40,0) -> 1.6213984 | Q44: =IFERROR((Q7+Q11-(Q14+Q17+Q23+Q25+Q28))/Q40,0) -> 1.5968838 | ... S44: =IFERROR((S7+S11-(S14+S17+S23+S25+S28))/S40,0) -> 1.6163459 | T44: 2.34 | U44: 2.34 | V44: =AVERAGE(J44:U44) -> 1.7282954 | W44: =V44/V$39 -> -8.2413589e-05 | Y44: =IFERROR((Y7+Y11-(Y14+Y17+Y23+Y25+Y28))/Y40,0) -> 1.8575511 | Z44: =IFERROR((Z7+Z11-(Z14+Z17+Z23+Z25+Z28))/Z40,0) -> 1.7296495 | AA44: =IFERROR((AA7+AA11-(AA14+AA17+AA23+AA25+AA28))/AA40,0) -> 2.0312056 | AB44: =IFERROR((AB7+AB11-(AB14+AB17+AB23+AB25+AB28))/AB40,0) -> 1.8122395 | AC44: =IFERROR((AC7+AC11-(AC14+AC17+AC23+AC25+AC28))/AC40,0) -> 1.9724677 | AD44: =IFERROR((AD7+AD11-(AD14+AD17+AD23+AD25+AD28))/AD40,0) -> 1.840208 | AE44: =IFERROR((AE7+AE11-(AE14+AE17+AE23+AE25+AE28))/AE40,0) -> 1.8125389 | AF44: =IFERROR((AF7+AF11-(AF14+AF17+AF23+AF25+AF28))/AF40,0) -> 1.8534248 | ... AK44: =IFERROR((AK7+AK11-(AK14+AK17+AK23+AK25+AK28))/AK40,0) -> 1.8709361 | AL44: =AK44/AK$39 -> #DIV/0! | AM44: =IFERROR(AK44/V44-1,0) -> 0.082532626 | AO44: 19598287 | AP44: 0.0044464695 | AQ44: 0.3287516
A45: E - GASTOS DE OPERACIÓN | B45: estaciones | C45: Servicios Administrativos | I45: Super | J45: =IFERROR((J8+J12-(J15+J18+J24+J26+J29))/J41,0) -> 1.7328667 | K45: =IFERROR((K8+K12-(K15+K18+K24+K26+K29))/K41,0) -> 1.6556903 | L45: =IFERROR((L8+L12-(L15+L18+L24+L26+L29))/L41,0) -> 1.7286344 | M45: =IFERROR((M8+M12-(M15+M18+M24+M26+M29))/M41,0) -> 1.9511968 | N45: =IFERROR((N8+N12-(N15+N18+N24+N26+N29))/N41,0) -> 2.1081028 | O45: =IFERROR((O8+O12-(O15+O18+O24+O26+O29))/O41,0) -> 2.136432 | P45: =IFERROR((P8+P12-(P15+P18+P24+P26+P29))/P41,0) -> 1.8143334 | Q45: =IFERROR((Q8+Q12-(Q15+Q18+Q24+Q26+Q29))/Q41,0) -> 1.6304157 | ... S45: =IFERROR((S8+S12-(S15+S18+S24+S26+S29))/S41,0) -> 1.598053 | T45: 2.13 | U45: 2.13 | V45: =AVERAGE(J45:U45) -> 1.8476718 | W45: =V45/V$39 -> -8.8106043e-05 | Y45: =IFERROR((Y8+Y12-(Y15+Y18+Y24+Y26+Y29))/Y41,0) -> 2.3538902 | Z45: =IFERROR((Z8+Z12-(Z15+Z18+Z24+Z26+Z29))/Z41,0) -> 2.2994485 | AA45: =IFERROR((AA8+AA12-(AA15+AA18+AA24+AA26+AA29))/AA41,0) -> 2.4220533 | AB45: =IFERROR((AB8+AB12-(AB15+AB18+AB24+AB26+AB29))/AB41,0) -> 2.2905268 | AC45: =IFERROR((AC8+AC12-(AC15+AC18+AC24+AC26+AC29))/AC41,0) -> 2.4371126 | AD45: =IFERROR((AD8+AD12-(AD15+AD18+AD24+AD26+AD29))/AD41,0) -> 2.2542774 | AE45: =IFERROR((AE8+AE12-(AE15+AE18+AE24+AE26+AE29))/AE41,0) -> 2.3209165 | AF45: =IFERROR((AF8+AF12-(AF15+AF18+AF24+AF26+AF29))/AF41,0) -> 2.4245021 | ... AK45: =IFERROR((AK8+AK12-(AK15+AK18+AK24+AK26+AK29))/AK41,0) -> 2.3549179 | AL45: =AK45/AK$39 -> #DIV/0! | AM45: =IFERROR(AK45/V45-1,0) -> 0.27453254 | AO45: 7218265.7 | AP45: 0.0016376839 | AQ45: 0.24066657
A46: E - GASTOS DE OPERACIÓN | B46: estaciones | I46: Diesel | J46: =IFERROR((J9-(J16+J19+J27))/J42,0) -> 1.9638868 | K46: =IFERROR((K9-(K16+K19+K27))/K42,0) -> 1.4542282 | L46: =IFERROR((L9-(L16+L19+L27))/L42,0) -> 1.3117148 | M46: =IFERROR((M9-(M16+M19+M27))/M42,0) -> 1.5464737 | N46: =IFERROR((N9-(N16+N19+N27))/N42,0) -> 2.0471721 | O46: =IFERROR((O9-(O16+O19+O27))/O42,0) -> 1.7727542 | P46: =IFERROR((P9-(P16+P19+P27))/P42,0) -> 1.381656 | Q46: =IFERROR((Q9-(Q16+Q19+Q27))/Q42,0) -> 0.5001665 | ... S46: =IFERROR((S9-(S16+S19+S27))/S42,0) -> 1.6387371 | T46: 2.05 | U46: 2.05 | V46: =AVERAGE(J46:U46) -> 1.5235373 | W46: =V46/V$39 -> -7.2649721e-05 | Y46: =IFERROR((Y9+Y11-(Y16+Y19+Y27))/Y42,0) -> 1.82 | Z46: =IFERROR((Z9+Z11-(Z16+Z19+Z27))/Z42,0) -> 1.72 | AA46: =IFERROR((AA9+AA11-(AA16+AA19+AA27))/AA42,0) -> 2 | AB46: =IFERROR((AB9+AB11-(AB16+AB19+AB27))/AB42,0) -> 1.98 | AC46: =IFERROR((AC9+AC11-(AC16+AC19+AC27))/AC42,0) -> 1.99 | AD46: =IFERROR((AD9+AD11-(AD16+AD19+AD27))/AD42,0) -> 1.57 | AE46: =IFERROR((AE9+AE11-(AE16+AE19+AE27))/AE42,0) -> 1.88 | AF46: =IFERROR((AF9+AF11-(AF16+AF19+AF27))/AF42,0) -> 1.62 | ... AK46: =IFERROR((AK9+AK11-(AK16+AK19+AK27))/AK42,0) -> 1.8187209 | AL46: =AK46/AK$39 -> #DIV/0! | AM46: =IFERROR(AK46/V46-1,0) -> 0.19374887 | AO46: 446400 | AP46: 0.00010127947 | AQ46: 0.037504052
A47: E - GASTOS DE OPERACIÓN | B47: estaciones | AO47: 0 | AP47: 0 | AQ47: -1
A48: E - GASTOS DE OPERACIÓN | B48: estaciones | I48: GASTO ESTACIONES | AO48: 1004640 | AP48: 0.00022793325 | AQ48: 0.82748833
A49: E - GASTOS DE OPERACIÓN | B49: estaciones | C49: Costo Marketing | AO49: 230499.1 | AP49: 5.2295756e-05 | AQ49: 7.2444774
A50: E - GASTOS DE OPERACIÓN | B50: estaciones | I50: E - GASTOS DE OPERACIÓN | J50: =SUM(J51:J90) -> 122446 | K50: =SUM(K51:K90) -> 98885 | L50: =SUM(L51:L90) -> 89091 | M50: =SUM(M51:M90) -> 110272 | N50: =SUM(N51:N90) -> 232930 | O50: =SUM(O51:O90) -> 225838 | P50: =SUM(P51:P90) -> 226077 | Q50: =SUM(Q51:Q90) -> 160331 | ... V50: =SUM(V51:V90) -> 2008814.5 | W50: =V50/V$6 -> 0.0089730118 | Y50: =SUM(Y51:Y90) -> 356952.31 | Z50: =SUM(Z51:Z90) -> 395138.34 | AA50: =SUM(AA51:AA90) -> 207799.37 | AB50: =SUM(AB51:AB90) -> 208225.41 | AC50: =SUM(AC51:AC90) -> 214119.98 | AD50: =SUM(AD51:AD90) -> 167442.55 | AE50: =SUM(AE51:AE90) -> 175479.49 | AF50: =SUM(AF51:AF90) -> 171660.09 | ... AK50: =SUM(AK51:AK90) -> 2668078.6 | AL50: =AK50/AK$6 -> 0.01064079 | AM50: =IFERROR(AK50/V50-1,0) -> 0.32818566 | AO50: 0 | AP50: 0 | AQ50: -1
A51: E - GASTOS DE OPERACIÓN | B51: estaciones | I51: Traslado de Valores | J51: =SUM(A:B!J51) -> 53341 | K51: =SUM(A:B!K51) -> 46688 | L51: =SUM(A:B!L51) -> 44687 | M51: =SUM(A:B!M51) -> 44765 | N51: =SUM(A:B!N51) -> 48640 | O51: =SUM(A:B!O51) -> 49241 | P51: =SUM(A:B!P51) -> 49239 | Q51: =SUM(A:B!Q51) -> 52289 | ... U51: =SUM(A:B!U51) -> 49215.403 | V51: =SUM(J51:U51) -> 583416.24 | W51: =V51/V$6 -> 0.002606015 | Y51: =SUM(A:B!Y51) -> 50313.675 | Z51: =SUM(A:B!Z51) -> 50313.675 | AA51: =SUM(A:B!AA51) -> 50313.675 | AB51: =SUM(A:B!AB51) -> 50313.675 | AC51: =SUM(A:B!AC51) -> 50313.675 | AD51: =SUM(A:B!AD51) -> 50313.675 | AE51: =SUM(A:B!AE51) -> 50313.675 | AF51: =SUM(A:B!AF51) -> 50313.675 | ... AJ51: =SUM(A:B!AJ51) -> 50313.675 | AK51: =SUM(Y51:AJ51) -> 603764.1 | AL51: =AK51/AK$6 -> 0.0024079227 | AM51: =IFERROR(AK51/V51-1,0) -> 0.034877096 | AO51: 721958.48 | AP51: 0.00016379832 | AQ51: 0.22172791
A52: E - GASTOS DE OPERACIÓN | B52: estaciones | I52: Servicios Administrativos | J52: =SUM(A:B!J52) -> 0 | K52: =SUM(A:B!K52) -> 0 | L52: =SUM(A:B!L52) -> 7360 | M52: =SUM(A:B!M52) -> 7360 | N52: =SUM(A:B!N52) -> 7360 | O52: =SUM(A:B!O52) -> 7360 | P52: =SUM(A:B!P52) -> 7360 | Q52: =SUM(A:B!Q52) -> 7360 | ... U52: =SUM(A:B!U52) -> 7360 | V52: =SUM(J52:U52) -> 73600 | W52: =V52/V$6 -> 0.00032875791 | Y52: =SUM(A:B!Y52) -> 7360 | Z52: =SUM(A:B!Z52) -> 7360 | AA52: =SUM(A:B!AA52) -> 7360 | AB52: =SUM(A:B!AB52) -> 7360 | AC52: =SUM(A:B!AC52) -> 7360 | AD52: =SUM(A:B!AD52) -> 7360 | AE52: =SUM(A:B!AE52) -> 7360 | AF52: =SUM(A:B!AF52) -> 7360 | ... AJ52: =SUM(A:B!AJ52) -> 7360 | AK52: =SUM(Y52:AJ52) -> 88320 | AL52: =AK52/AK$6 -> 0.00035223646 | AM52: =IFERROR(AK52/V52-1,0) -> 0.2 | AO52: 1101110.8 | AP52: 0.00024982059 | AQ52: 0.24826578
A53: E - GASTOS DE OPERACIÓN | B53: estaciones | I53: Asesoría en sistemas | J53: =SUM(A:B!J53) -> 0 | K53: =SUM(A:B!K53) -> 0 | L53: =SUM(A:B!L53) -> 0 | M53: =SUM(A:B!M53) -> 0 | N53: =SUM(A:B!N53) -> 0 | O53: =SUM(A:B!O53) -> 0 | P53: =SUM(A:B!P53) -> 0 | Q53: =SUM(A:B!Q53) -> 0 | ... U53: =SUM(A:B!U53) -> 0 | V53: =SUM(J53:U53) -> 0 | W53: =V53/V$6 -> 0 | Y53: =SUM(A:B!Y53) -> 0 | Z53: =SUM(A:B!Z53) -> 0 | AA53: =SUM(A:B!AA53) -> 0 | AB53: =SUM(A:B!AB53) -> 0 | AC53: =SUM(A:B!AC53) -> 0 | AD53: =SUM(A:B!AD53) -> 0 | AE53: =SUM(A:B!AE53) -> 0 | AF53: =SUM(A:B!AF53) -> 0 | ... AJ53: =SUM(A:B!AJ53) -> 0 | AK53: =SUM(Y53:AJ53) -> 0 | AL53: =AK53/AK$6 -> 0 | AM53: =IFERROR(AK53/V53-1,0) -> 0 | AO53: 279218.19 | AP53: 6.3349169e-05 | AQ53: 497.60391
I54: Otros Gastos | J54: =SUM(A:B!J54) -> 0 | K54: =SUM(A:B!K54) -> 0 | L54: =SUM(A:B!L54) -> 0 | M54: =SUM(A:B!M54) -> 0 | N54: =SUM(A:B!N54) -> 0 | O54: =SUM(A:B!O54) -> 0 | P54: =SUM(A:B!P54) -> 0 | Q54: =SUM(A:B!Q54) -> 0 | ... U54: =SUM(A:B!U54) -> 2805.2361 | V54: =SUM(J54:U54) -> 12379.069 | W54: =V54/V$6 -> 5.5295068e-05 | Y54: =SUM(A:B!Y54) -> 0 | Z54: =SUM(A:B!Z54) -> 0 | AA54: =SUM(A:B!AA54) -> 0 | AB54: =SUM(A:B!AB54) -> 0 | AC54: =SUM(A:B!AC54) -> 0 | AD54: =SUM(A:B!AD54) -> 0 | AE54: =SUM(A:B!AE54) -> 0 | AF54: =SUM(A:B!AF54) -> 0 | ... AJ54: =SUM(A:B!AJ54) -> 4968.48 | AK54: =SUM(Y54:AJ54) -> 4968.48 | AL54: =AK54/AK$6 -> 1.9815215e-05 | AM54: =IFERROR(AK54/V54-1,0) -> -0.59863865 | AO54: 0 | AP54: 0 | AQ54: -1
I55: Otros impuestos y derechos | J55: =SUM(A:B!J55) -> 0 | K55: =SUM(A:B!K55) -> 584 | L55: =SUM(A:B!L55) -> 649 | M55: =SUM(A:B!M55) -> 479 | N55: =SUM(A:B!N55) -> 0 | O55: =SUM(A:B!O55) -> 0 | P55: =SUM(A:B!P55) -> 0 | Q55: =SUM(A:B!Q55) -> 20945 | ... U55: =SUM(A:B!U55) -> 0 | V55: =SUM(J55:U55) -> 22657 | W55: =V55/V$6 -> 0.00010120473 | Y55: =SUM(A:B!Y55) -> 47569.056 | Z55: =SUM(A:B!Z55) -> 0 | AA55: =SUM(A:B!AA55) -> 0 | AB55: =SUM(A:B!AB55) -> 0 | AC55: =SUM(A:B!AC55) -> 0 | AD55: =SUM(A:B!AD55) -> 0 | AE55: =SUM(A:B!AE55) -> 0 | AF55: =SUM(A:B!AF55) -> 0 | ... AJ55: =SUM(A:B!AJ55) -> 0 | AK55: =SUM(Y55:AJ55) -> 47569.056 | AL55: =AK55/AK$6 -> 0.00018971417 | AM55: =IFERROR(AK55/V55-1,0) -> 1.0995302 | AO55: 0 | AP55: 0 | AQ55: -1
I56: Limpieza | J56: =SUM(A:B!J56) -> 10725 | K56: =SUM(A:B!K56) -> 10467 | L56: =SUM(A:B!L56) -> 0 | M56: =SUM(A:B!M56) -> 8802 | N56: =SUM(A:B!N56) -> 3380 | O56: =SUM(A:B!O56) -> 5871 | P56: =SUM(A:B!P56) -> 3690 | Q56: =SUM(A:B!Q56) -> 6134 | ... U56: =SUM(A:B!U56) -> 6114.1736 | V56: =SUM(J56:U56) -> 72406.757 | W56: =V56/V$6 -> 0.00032342791 | Y56: =SUM(A:B!Y56) -> 6262.355 | Z56: =SUM(A:B!Z56) -> 6262.355 | AA56: =SUM(A:B!AA56) -> 6262.355 | AB56: =SUM(A:B!AB56) -> 6262.355 | AC56: =SUM(A:B!AC56) -> 6262.355 | AD56: =SUM(A:B!AD56) -> 6262.355 | AE56: =SUM(A:B!AE56) -> 6262.355 | AF56: =SUM(A:B!AF56) -> 6262.355 | ... AJ56: =SUM(A:B!AJ56) -> 6262.355 | AK56: =SUM(Y56:AJ56) -> 75148.26 | AL56: =AK56/AK$6 -> 0.00029970513 | AM56: =IFERROR(AK56/V56-1,0) -> 0.037862531 | AO56: 0 | AP56: 0 | AQ56: -1
I57: Propaganda y publicidad | J57: =SUM(A:B!J57) -> 5700 | K57: =SUM(A:B!K57) -> 9600 | L57: =SUM(A:B!L57) -> 21424 | M57: =SUM(A:B!M57) -> 16037 | N57: =SUM(A:B!N57) -> 55386 | O57: =SUM(A:B!O57) -> 28776 | P57: =SUM(A:B!P57) -> 9204 | Q57: =SUM(A:B!Q57) -> -114514 | ... U57: =SUM(A:B!U57) -> 60000 | V57: =SUM(J57:U57) -> 158326 | W57: =V57/V$6 -> 0.00070721366 | Y57: =SUM(A:B!Y57) -> 0 | Z57: =SUM(A:B!Z57) -> 931.59 | AA57: =SUM(A:B!AA57) -> 48753.21 | AB57: =SUM(A:B!AB57) -> 49684.8 | AC57: =SUM(A:B!AC57) -> 51755 | AD57: =SUM(A:B!AD57) -> 0 | AE57: =SUM(A:B!AE57) -> 1759.67 | AF57: =SUM(A:B!AF57) -> 1863.18 | ... AJ57: =SUM(A:B!AJ57) -> 0 | AK57: =SUM(Y57:AJ57) -> 154747.45 | AL57: =AK57/AK$6 -> 0.00061716139 | AM57: =IFERROR(AK57/V57-1,0) -> -0.022602415 | AO57: 0 | AP57: 0 | AQ57: 0
I58: Capacitacion al personal | J58: =SUM(A:B!J58) -> 0 | K58: =SUM(A:B!K58) -> 0 | L58: =SUM(A:B!L58) -> 0 | M58: =SUM(A:B!M58) -> 0 | N58: =SUM(A:B!N58) -> 0 | O58: =SUM(A:B!O58) -> 0 | P58: =SUM(A:B!P58) -> 0 | Q58: =SUM(A:B!Q58) -> 0 | ... U58: =SUM(A:B!U58) -> 0 | V58: =SUM(J58:U58) -> 31200 | W58: =V58/V$6 -> 0.00013936477 | Y58: =SUM(A:B!Y58) -> 1990.5769 | Z58: =SUM(A:B!Z58) -> 6369.8462 | AA58: =SUM(A:B!AA58) -> 1194.3462 | AB58: =SUM(A:B!AB58) -> 0 | AC58: =SUM(A:B!AC58) -> 0 | AD58: =SUM(A:B!AD58) -> 0 | AE58: =SUM(A:B!AE58) -> 0 | AF58: =SUM(A:B!AF58) -> 0 | ... AJ58: =SUM(A:B!AJ58) -> 0 | AK58: =SUM(Y58:AJ58) -> 9554.7692 | AL58: =AK58/AK$6 -> 3.8106183e-05 | AM58: =IFERROR(AK58/V58-1,0) -> -0.6937574 | AO58: 0 | AP58: 0 | AQ58: -1
I59: Honorarios Administrativos P.F. | J59: =SUM(A:B!J59) -> 0 | K59: =SUM(A:B!K59) -> 0 | L59: =SUM(A:B!L59) -> 0 | M59: =SUM(A:B!M59) -> 0 | N59: =SUM(A:B!N59) -> 0 | O59: =SUM(A:B!O59) -> 0 | P59: =SUM(A:B!P59) -> 0 | Q59: =SUM(A:B!Q59) -> 0 | ... U59: =SUM(A:B!U59) -> 0 | V59: =SUM(J59:U59) -> 0 | W59: =V59/V$6 -> 0 | Y59: =SUM(A:B!Y59) -> 0 | Z59: =SUM(A:B!Z59) -> 0 | AA59: =SUM(A:B!AA59) -> 0 | AB59: =SUM(A:B!AB59) -> 0 | AC59: =SUM(A:B!AC59) -> 0 | AD59: =SUM(A:B!AD59) -> 0 | AE59: =SUM(A:B!AE59) -> 0 | AF59: =SUM(A:B!AF59) -> 0 | ... AJ59: =SUM(A:B!AJ59) -> 0 | AK59: =SUM(Y59:AJ59) -> 0 | AL59: =AK59/AK$6 -> 0 | AM59: =IFERROR(AK59/V59-1,0) -> 0 | AO59: 343092 | AP59: 7.7840892e-05 | AQ59: 0.084376956
I60: Honorarios Administrativos P.M. | J60: =SUM(A:B!J60) -> 0 | K60: =SUM(A:B!K60) -> 0 | L60: =SUM(A:B!L60) -> 0 | M60: =SUM(A:B!M60) -> 0 | N60: =SUM(A:B!N60) -> 0 | O60: =SUM(A:B!O60) -> 0 | P60: =SUM(A:B!P60) -> 0 | Q60: =SUM(A:B!Q60) -> 0 | ... U60: =SUM(A:B!U60) -> 0 | V60: =SUM(J60:U60) -> 0 | W60: =V60/V$6 -> 0 | Y60: =SUM(A:B!Y60) -> 0 | Z60: =SUM(A:B!Z60) -> 0 | AA60: =SUM(A:B!AA60) -> 0 | AB60: =SUM(A:B!AB60) -> 0 | AC60: =SUM(A:B!AC60) -> 0 | AD60: =SUM(A:B!AD60) -> 0 | AE60: =SUM(A:B!AE60) -> 0 | AF60: =SUM(A:B!AF60) -> 0 | ... AJ60: =SUM(A:B!AJ60) -> 0 | AK60: =SUM(Y60:AJ60) -> 0 | AL60: =AK60/AK$6 -> 0 | AM60: =IFERROR(AK60/V60-1,0) -> 0 | AO60: 0 | AP60: 0 | AQ60: 0
A61: E - GASTOS DE OPERACIÓN | B61: estaciones | I61: Asistencia técnica | J61: =SUM(A:B!J61) -> 0 | K61: =SUM(A:B!K61) -> 0 | L61: =SUM(A:B!L61) -> 0 | M61: =SUM(A:B!M61) -> 0 | N61: =SUM(A:B!N61) -> 0 | O61: =SUM(A:B!O61) -> 0 | P61: =SUM(A:B!P61) -> 0 | Q61: =SUM(A:B!Q61) -> 0 | ... U61: =SUM(A:B!U61) -> 0 | V61: =SUM(J61:U61) -> 0 | W61: =V61/V$6 -> 0 | Y61: =SUM(A:B!Y61) -> 0 | Z61: =SUM(A:B!Z61) -> 0 | AA61: =SUM(A:B!AA61) -> 0 | AB61: =SUM(A:B!AB61) -> 0 | AC61: =SUM(A:B!AC61) -> 0 | AD61: =SUM(A:B!AD61) -> 0 | AE61: =SUM(A:B!AE61) -> 0 | AF61: =SUM(A:B!AF61) -> 0 | ... AJ61: =SUM(A:B!AJ61) -> 0 | AK61: =SUM(Y61:AJ61) -> 0 | AL61: =AK61/AK$6 -> 0 | AM61: =IFERROR(AK61/V61-1,0) -> 0 | AO61: 230499.1 | AP61: 5.2295756e-05 | AQ61: -5.8995545
A62: E - GASTOS DE OPERACIÓN | B62: estaciones | I62: Gastos no deducibles (sin requisitos fiscales) | J62: =SUM(A:B!J62) -> 1011 | K62: =SUM(A:B!K62) -> 3942 | L62: =SUM(A:B!L62) -> 2147 | M62: =SUM(A:B!M62) -> 3660 | N62: =SUM(A:B!N62) -> 1674 | O62: =SUM(A:B!O62) -> 3666 | P62: =SUM(A:B!P62) -> 14747 | Q62: =SUM(A:B!Q62) -> 16348 | ... U62: =SUM(A:B!U62) -> 0 | V62: =SUM(J62:U62) -> 23069 | W62: =V62/V$6 -> 0.00010304506 | Y62: =SUM(A:B!Y62) -> 0 | Z62: =SUM(A:B!Z62) -> 0 | AA62: =SUM(A:B!AA62) -> 0 | AB62: =SUM(A:B!AB62) -> 0 | AC62: =SUM(A:B!AC62) -> 0 | AD62: =SUM(A:B!AD62) -> 0 | AE62: =SUM(A:B!AE62) -> 0 | AF62: =SUM(A:B!AF62) -> 0 | ... AJ62: =SUM(A:B!AJ62) -> 0 | AK62: =SUM(Y62:AJ62) -> 0 | AL62: =AK62/AK$6 -> 0 | AM62: =IFERROR(AK62/V62-1,0) -> -1 | AO62: 2418673.4 | AP62: 0.00054874988 | AQ62: 0.79309425
A63: E - GASTOS DE OPERACIÓN | B63: estaciones | I63: Papelería y artículos de oficina | J63: =SUM(A:B!J63) -> 8187 | K63: =SUM(A:B!K63) -> 4482 | L63: =SUM(A:B!L63) -> 1704 | M63: =SUM(A:B!M63) -> 5280 | N63: =SUM(A:B!N63) -> 5966 | O63: =SUM(A:B!O63) -> 4080 | P63: =SUM(A:B!P63) -> 5569 | Q63: =SUM(A:B!Q63) -> 9096 | ... U63: =SUM(A:B!U63) -> 5367.8403 | V63: =SUM(J63:U63) -> 64361.424 | W63: =V63/V$6 -> 0.00028749086 | Y63: =SUM(A:B!Y63) -> 3670 | Z63: =SUM(A:B!Z63) -> 3670 | AA63: =SUM(A:B!AA63) -> 3670 | AB63: =SUM(A:B!AB63) -> 3670 | AC63: =SUM(A:B!AC63) -> 3670 | AD63: =SUM(A:B!AD63) -> 3670 | AE63: =SUM(A:B!AE63) -> 3670 | AF63: =SUM(A:B!AF63) -> 3670 | ... AJ63: =SUM(A:B!AJ63) -> 3670 | AK63: =SUM(Y63:AJ63) -> 44040 | AL63: =AK63/AK$6 -> 0.00017563965 | AM63: =IFERROR(AK63/V63-1,0) -> -0.31573919 | AO63: 0 | AP63: 0 | AQ63: 0
A64: E - GASTOS DE OPERACIÓN | B64: estaciones | I64: Faltantes | J64: =SUM(A:B!J64) -> 0 | K64: =SUM(A:B!K64) -> 0 | L64: =SUM(A:B!L64) -> 0 | M64: =SUM(A:B!M64) -> 0 | N64: =SUM(A:B!N64) -> 0 | O64: =SUM(A:B!O64) -> 0 | P64: =SUM(A:B!P64) -> 0 | Q64: =SUM(A:B!Q64) -> 0 | ... U64: =SUM(A:B!U64) -> 0 | V64: =SUM(J64:U64) -> 0 | W64: =V64/V$6 -> 0 | Y64: =SUM(A:B!Y64) -> 0 | Z64: =SUM(A:B!Z64) -> 0 | AA64: =SUM(A:B!AA64) -> 0 | AB64: =SUM(A:B!AB64) -> 0 | AC64: =SUM(A:B!AC64) -> 0 | AD64: =SUM(A:B!AD64) -> 0 | AE64: =SUM(A:B!AE64) -> 0 | AF64: =SUM(A:B!AF64) -> 0 | ... AJ64: =SUM(A:B!AJ64) -> 0 | AK64: =SUM(Y64:AJ64) -> 0 | AL64: =AK64/AK$6 -> 0 | AM64: =IFERROR(AK64/V64-1,0) -> 0 | AO64: 0 | AP64: 0 | AQ64: -1
A65: E - GASTOS DE OPERACIÓN | B65: estaciones | I65: Licencias y Permisos | J65: =SUM(A:B!J65) -> 0 | K65: =SUM(A:B!K65) -> 0 | L65: =SUM(A:B!L65) -> 0 | M65: =SUM(A:B!M65) -> 0 | N65: =SUM(A:B!N65) -> 0 | O65: =SUM(A:B!O65) -> 0 | P65: =SUM(A:B!P65) -> 0 | Q65: =SUM(A:B!Q65) -> 0 | ... U65: =SUM(A:B!U65) -> 0 | V65: =SUM(J65:U65) -> 0 | W65: =V65/V$6 -> 0 | Y65: =SUM(A:B!Y65) -> 141601.68 | Z65: =SUM(A:B!Z65) -> 233932.6 | AA65: =SUM(A:B!AA65) -> 0 | AB65: =SUM(A:B!AB65) -> 0 | AC65: =SUM(A:B!AC65) -> 0 | AD65: =SUM(A:B!AD65) -> 0 | AE65: =SUM(A:B!AE65) -> 0 | AF65: =SUM(A:B!AF65) -> 0 | ... AJ65: =SUM(A:B!AJ65) -> 0 | AK65: =SUM(Y65:AJ65) -> 375534.28 | AL65: =AK65/AK$6 -> 0.0014977 | AM65: =IFERROR(AK65/V65-1,0) -> 0 | AO65: 409356.29 | AP65: 9.2874968e-05 | AQ65: 0.11739717
A66: E - GASTOS DE OPERACIÓN | B66: estaciones | I66: Licencias, Software, Antivirus | J66: =SUM(A:B!J66) -> 0 | K66: =SUM(A:B!K66) -> 0 | L66: =SUM(A:B!L66) -> 0 | M66: =SUM(A:B!M66) -> 5370 | N66: =SUM(A:B!N66) -> 90550 | O66: =SUM(A:B!O66) -> 90550 | P66: =SUM(A:B!P66) -> 90550 | Q66: =SUM(A:B!Q66) -> 90550 | ... U66: =SUM(A:B!U66) -> 90550 | V66: =SUM(J66:U66) -> 729770 | W66: =V66/V$6 -> 0.0032597508 | Y66: =SUM(A:B!Y66) -> 23339.435 | Z66: =SUM(A:B!Z66) -> 23339.435 | AA66: =SUM(A:B!AA66) -> 23339.435 | AB66: =SUM(A:B!AB66) -> 23339.435 | AC66: =SUM(A:B!AC66) -> 28897.922 | AD66: =SUM(A:B!AD66) -> 28897.922 | AE66: =SUM(A:B!AE66) -> 28897.922 | AF66: =SUM(A:B!AF66) -> 28897.922 | ... AJ66: =SUM(A:B!AJ66) -> 28897.922 | AK66: =SUM(Y66:AJ66) -> 324541.11 | AL66: =AK66/AK$6 -> 0.0012943299 | AM66: =IFERROR(AK66/V66-1,0) -> -0.55528302 | AO66: 0 | AP66: 0 | AQ66: 0
A67: E - GASTOS DE OPERACIÓN | B67: estaciones | I67: Fletes Combustible | J67: =SUM(A:B!J67) -> 0 | K67: =SUM(A:B!K67) -> 0 | L67: =SUM(A:B!L67) -> 0 | M67: =SUM(A:B!M67) -> 0 | N67: =SUM(A:B!N67) -> 0 | O67: =SUM(A:B!O67) -> 0 | P67: =SUM(A:B!P67) -> 0 | Q67: =SUM(A:B!Q67) -> 0 | ... U67: =SUM(A:B!U67) -> 0 | V67: =SUM(J67:U67) -> 0 | W67: =V67/V$6 -> 0 | Y67: =SUM(A:B!Y67) -> 0 | Z67: =SUM(A:B!Z67) -> 0 | AA67: =SUM(A:B!AA67) -> 0 | AB67: =SUM(A:B!AB67) -> 0 | AC67: =SUM(A:B!AC67) -> 0 | AD67: =SUM(A:B!AD67) -> 0 | AE67: =SUM(A:B!AE67) -> 0 | AF67: =SUM(A:B!AF67) -> 0 | ... AJ67: =SUM(A:B!AJ67) -> 0 | AK67: =SUM(Y67:AJ67) -> 0 | AL67: =AK67/AK$6 -> 0 | AM67: =IFERROR(AK67/V67-1,0) -> 0 | AO67: 167582.09 | AP67: 3.8021112e-05 | AQ67: 0.031923392
A68: E - GASTOS DE OPERACIÓN | B68: estaciones | I68: Viáticos y gastos de viaje | J68: =SUM(A:B!J68) -> 0 | K68: =SUM(A:B!K68) -> 0 | L68: =SUM(A:B!L68) -> 0 | M68: =SUM(A:B!M68) -> 2367 | N68: =SUM(A:B!N68) -> 5088 | O68: =SUM(A:B!O68) -> 6068 | P68: =SUM(A:B!P68) -> 0 | Q68: =SUM(A:B!Q68) -> 7760 | ... U68: =SUM(A:B!U68) -> 0 | V68: =SUM(J68:U68) -> 21283 | W68: =V68/V$6 -> 9.5067319e-05 | Y68: =SUM(A:B!Y68) -> 0 | Z68: =SUM(A:B!Z68) -> 0 | AA68: =SUM(A:B!AA68) -> 0 | AB68: =SUM(A:B!AB68) -> 0 | AC68: =SUM(A:B!AC68) -> 0 | AD68: =SUM(A:B!AD68) -> 0 | AE68: =SUM(A:B!AE68) -> 0 | AF68: =SUM(A:B!AF68) -> 0 | ... AJ68: =SUM(A:B!AJ68) -> 0 | AK68: =SUM(Y68:AJ68) -> 0 | AL68: =AK68/AK$6 -> 0 | AM68: =IFERROR(AK68/V68-1,0) -> -1 | AO68: 0 | AP68: 0 | AQ68: -1
A69: E - GASTOS DE OPERACIÓN | B69: estaciones | I69: Recoleccion de Basura | J69: =SUM(A:B!J69) -> 0 | K69: =SUM(A:B!K69) -> 0 | L69: =SUM(A:B!L69) -> 0 | M69: =SUM(A:B!M69) -> 0 | N69: =SUM(A:B!N69) -> 1954 | O69: =SUM(A:B!O69) -> 4395 | P69: =SUM(A:B!P69) -> 3906 | Q69: =SUM(A:B!Q69) -> 3906 | ... U69: =SUM(A:B!U69) -> 4340.6667 | V69: =SUM(J69:U69) -> 31523.667 | W69: =V69/V$6 -> 0.00014081053 | Y69: =SUM(A:B!Y69) -> 4043.1006 | Z69: =SUM(A:B!Z69) -> 4043.1006 | AA69: =SUM(A:B!AA69) -> 4043.1006 | AB69: =SUM(A:B!AB69) -> 4043.1006 | AC69: =SUM(A:B!AC69) -> 4043.1006 | AD69: =SUM(A:B!AD69) -> 4043.1006 | AE69: =SUM(A:B!AE69) -> 4043.1006 | AF69: =SUM(A:B!AF69) -> 4043.1006 | ... AJ69: =SUM(A:B!AJ69) -> 4043.1006 | AK69: =SUM(Y69:AJ69) -> 48517.207 | AL69: =AK69/AK$6 -> 0.00019349558 | AM69: =IFERROR(AK69/V69-1,0) -> 0.53907246 | AO69: 0 | AP69: 0 | AQ69: -1
A70: E - GASTOS DE OPERACIÓN | B70: estaciones | I70: Honorarios de Consultoria | J70: =SUM(A:B!J70) -> 0 | K70: =SUM(A:B!K70) -> 0 | L70: =SUM(A:B!L70) -> 0 | M70: =SUM(A:B!M70) -> 0 | N70: =SUM(A:B!N70) -> 0 | O70: =SUM(A:B!O70) -> 0 | P70: =SUM(A:B!P70) -> 0 | Q70: =SUM(A:B!Q70) -> 0 | ... U70: =SUM(A:B!U70) -> 0 | V70: =SUM(J70:U70) -> 0 | W70: =V70/V$6 -> 0 | Y70: =SUM(A:B!Y70) -> 0 | Z70: =SUM(A:B!Z70) -> 0 | AA70: =SUM(A:B!AA70) -> 0 | AB70: =SUM(A:B!AB70) -> 0 | AC70: =SUM(A:B!AC70) -> 0 | AD70: =SUM(A:B!AD70) -> 0 | AE70: =SUM(A:B!AE70) -> 0 | AF70: =SUM(A:B!AF70) -> 0 | ... AJ70: =SUM(A:B!AJ70) -> 0 | AK70: =SUM(Y70:AJ70) -> 0 | AL70: =AK70/AK$6 -> 0 | AM70: =IFERROR(AK70/V70-1,0) -> 0 | AO70: 0 | AP70: 0 | AQ70: -1
A71: E - GASTOS DE OPERACIÓN | B71: estaciones | I71: Agua para consumo | J71: =SUM(A:B!J71) -> 0 | K71: =SUM(A:B!K71) -> 0 | L71: =SUM(A:B!L71) -> 0 | M71: =SUM(A:B!M71) -> 0 | N71: =SUM(A:B!N71) -> 0 | O71: =SUM(A:B!O71) -> 0 | P71: =SUM(A:B!P71) -> 0 | Q71: =SUM(A:B!Q71) -> 0 | ... U71: =SUM(A:B!U71) -> 0 | V71: =SUM(J71:U71) -> 0 | W71: =V71/V$6 -> 0 | Y71: =SUM(A:B!Y71) -> 2392.6294 | Z71: =SUM(A:B!Z71) -> 2161.0846 | AA71: =SUM(A:B!AA71) -> 2392.6294 | AB71: =SUM(A:B!AB71) -> 2315.4478 | AC71: =SUM(A:B!AC71) -> 2392.6294 | AD71: =SUM(A:B!AD71) -> 2315.4478 | AE71: =SUM(A:B!AE71) -> 2392.6294 | AF71: =SUM(A:B!AF71) -> 2392.6294 | ... AJ71: =SUM(A:B!AJ71) -> 2392.6294 | AK71: =SUM(Y71:AJ71) -> 28171.282 | AL71: =AK71/AK$6 -> 0.00011235227 | AM71: =IFERROR(AK71/V71-1,0) -> 0 | AO71: 231497.51 | AP71: 5.2522276e-05 | AQ71: 0.06
A72: E - GASTOS DE OPERACIÓN | B72: estaciones | I72: Fletes Mensajeria | J72: =SUM(A:B!J72) -> 0 | K72: =SUM(A:B!K72) -> 0 | L72: =SUM(A:B!L72) -> 0 | M72: =SUM(A:B!M72) -> 0 | N72: =SUM(A:B!N72) -> 0 | O72: =SUM(A:B!O72) -> 0 | P72: =SUM(A:B!P72) -> 0 | Q72: =SUM(A:B!Q72) -> 0 | ... U72: =SUM(A:B!U72) -> 0 | V72: =SUM(J72:U72) -> 0 | W72: =V72/V$6 -> 0 | Y72: =SUM(A:B!Y72) -> 0 | Z72: =SUM(A:B!Z72) -> 0 | AA72: =SUM(A:B!AA72) -> 0 | AB72: =SUM(A:B!AB72) -> 0 | AC72: =SUM(A:B!AC72) -> 0 | AD72: =SUM(A:B!AD72) -> 0 | AE72: =SUM(A:B!AE72) -> 0 | AF72: =SUM(A:B!AF72) -> 0 | ... AJ72: =SUM(A:B!AJ72) -> 0 | AK72: =SUM(Y72:AJ72) -> 0 | AL72: =AK72/AK$6 -> 0 | AM72: =IFERROR(AK72/V72-1,0) -> 0 | AO72: 817328.52 | AP72: 0.00018543592 | AQ72: 2.6545724
... A74: E - GASTOS DE OPERACIÓN | B74: estaciones | I74: Consumos Propios Combustibles | J74: =SUM(A:B!J74) -> 0 | K74: =SUM(A:B!K74) -> 7779 | L74: =SUM(A:B!L74) -> 0 | M74: =SUM(A:B!M74) -> 0 | N74: =SUM(A:B!N74) -> 0 | O74: =SUM(A:B!O74) -> 0 | P74: =SUM(A:B!P74) -> 0 | Q74: =SUM(A:B!Q74) -> 0 | ... U74: =SUM(A:B!U74) -> 0 | V74: =SUM(J74:U74) -> 7779 | W74: =V74/V$6 -> 3.4747389e-05 | Y74: =SUM(A:B!Y74) -> 0 | Z74: =SUM(A:B!Z74) -> 0 | AA74: =SUM(A:B!AA74) -> 0 | AB74: =SUM(A:B!AB74) -> 0 | AC74: =SUM(A:B!AC74) -> 0 | AD74: =SUM(A:B!AD74) -> 0 | AE74: =SUM(A:B!AE74) -> 0 | AF74: =SUM(A:B!AF74) -> 0 | ... AJ74: =SUM(A:B!AJ74) -> 0 | AK74: =SUM(Y74:AJ74) -> 0 | AL74: =AK74/AK$6 -> 0 | AM74: =IFERROR(AK74/V74-1,0) -> -1 | AO74: 3050316.1 | AP74: 0.00069205731 | AQ74: 0.063
A75: E - GASTOS DE OPERACIÓN | B75: estaciones | I75: Renta Equipo de Sistemas | J75: =SUM(A:B!J75) -> 0 | K75: =SUM(A:B!K75) -> 6711 | L75: =SUM(A:B!L75) -> 2872 | M75: =SUM(A:B!M75) -> 2892 | N75: =SUM(A:B!N75) -> 2929 | O75: =SUM(A:B!O75) -> 2938 | P75: =SUM(A:B!P75) -> 3087 | Q75: =SUM(A:B!Q75) -> 3175 | ... U75: =SUM(A:B!U75) -> 3371.8194 | Y75: =SUM(A:B!Y75) -> 4192.155 | Z75: =SUM(A:B!Z75) -> 4192.155 | AA75: =SUM(A:B!AA75) -> 4192.155 | AB75: =SUM(A:B!AB75) -> 4192.155 | AC75: =SUM(A:B!AC75) -> 4192.155 | AD75: =SUM(A:B!AD75) -> 4192.155 | AE75: =SUM(A:B!AE75) -> 4192.155 | AF75: =SUM(A:B!AF75) -> 4192.155 | ... AJ75: =SUM(A:B!AJ75) -> 4192.155 | AK75: =SUM(Y75:AJ75) -> 50305.86 | AL75: =AK75/AK$6 -> 0.00020062905 | AM75: =IFERROR(AK75/V75-1,0) -> 0 | AO75: 353957.24 | AP75: 8.0306003e-05 | AQ75: 27.041748
I76: Timbrado Facturas | J76: =SUM(A:B!J76) -> 736 | K76: =SUM(A:B!K76) -> 515 | L76: =SUM(A:B!L76) -> 472 | M76: =SUM(A:B!M76) -> 5484 | N76: =SUM(A:B!N76) -> 614 | O76: =SUM(A:B!O76) -> 13657 | P76: =SUM(A:B!P76) -> 21316 | Q76: =SUM(A:B!Q76) -> 24909 | ... U76: =SUM(A:B!U76) -> 7052.7778 | Y76: =SUM(A:B!Y76) -> 4729 | Z76: =SUM(A:B!Z76) -> 4729 | AA76: =SUM(A:B!AA76) -> 4729 | AB76: =SUM(A:B!AB76) -> 4729 | AC76: =SUM(A:B!AC76) -> 4729 | AD76: =SUM(A:B!AD76) -> 4729 | AE76: =SUM(A:B!AE76) -> 4729 | AF76: =SUM(A:B!AF76) -> 4729 | ... AJ76: =SUM(A:B!AJ76) -> 4729 | AK76: =SUM(Y76:AJ76) -> 56748 | AL76: =AK76/AK$6 -> 0.0002263215 | AM76: =IFERROR(AK76/V76-1,0) -> 0 | AO76: 0 | AP76: 0 | AQ76: 0
I77: Rentas No Deducibles | J77: =SUM(A:B!J77) -> 0 | K77: =SUM(A:B!K77) -> 0 | L77: =SUM(A:B!L77) -> 0 | M77: =SUM(A:B!M77) -> 0 | N77: =SUM(A:B!N77) -> 0 | O77: =SUM(A:B!O77) -> 0 | P77: =SUM(A:B!P77) -> 0 | Q77: =SUM(A:B!Q77) -> 0 | ... U77: =SUM(A:B!U77) -> 0 | Y77: =SUM(A:B!Y77) -> 0 | Z77: =SUM(A:B!Z77) -> 0 | AA77: =SUM(A:B!AA77) -> 0 | AB77: =SUM(A:B!AB77) -> 0 | AC77: =SUM(A:B!AC77) -> 0 | AD77: =SUM(A:B!AD77) -> 0 | AE77: =SUM(A:B!AE77) -> 0 | AF77: =SUM(A:B!AF77) -> 0 | ... AJ77: =SUM(A:B!AJ77) -> 0 | AK77: =SUM(Y77:AJ77) -> 0 | AL77: =AK77/AK$6 -> 0 | AM77: =IFERROR(AK77/V77-1,0) -> 0 | AO77: 0 | AP77: 0 | AQ77: -1
I78: Uniformes | J78: =SUM(A:B!J78) -> 34970 | K78: =SUM(A:B!K78) -> 0 | L78: =SUM(A:B!L78) -> 0 | M78: =SUM(A:B!M78) -> 0 | N78: =SUM(A:B!N78) -> 881 | O78: =SUM(A:B!O78) -> 0 | P78: =SUM(A:B!P78) -> 8901 | Q78: =SUM(A:B!Q78) -> 7288 | ... U78: =SUM(A:B!U78) -> 17232.134 | Y78: =SUM(A:B!Y78) -> 37159.676 | Z78: =SUM(A:B!Z78) -> 29727.741 | AA78: =SUM(A:B!AA78) -> 33443.708 | AB78: =SUM(A:B!AB78) -> 32098.078 | AC78: =SUM(A:B!AC78) -> 20950.176 | AD78: =SUM(A:B!AD78) -> 23993.328 | AE78: =SUM(A:B!AE78) -> 39530.014 | AF78: =SUM(A:B!AF78) -> 28382.111 | ... AJ78: =SUM(A:B!AJ78) -> 33443.708 | AK78: =SUM(Y78:AJ78) -> 327388.01 | AL78: =AK78/AK$6 -> 0.0013056838 | AM78: =IFERROR(AK78/V78-1,0) -> 0 | AO78: 0 | AP78: 0 | AQ78: 0
I79: Contratacion Empleados | J79: =SUM(A:B!J79) -> 0 | K79: =SUM(A:B!K79) -> 0 | L79: =SUM(A:B!L79) -> 0 | M79: =SUM(A:B!M79) -> 0 | N79: =SUM(A:B!N79) -> 732 | O79: =SUM(A:B!O79) -> 1460 | P79: =SUM(A:B!P79) -> 732 | Q79: =SUM(A:B!Q79) -> 0 | ... U79: =SUM(A:B!U79) -> 520 | Y79: =SUM(A:B!Y79) -> 4223.208 | Z79: =SUM(A:B!Z79) -> 0 | AA79: =SUM(A:B!AA79) -> 0 | AB79: =SUM(A:B!AB79) -> 2111.604 | AC79: =SUM(A:B!AC79) -> 3167.406 | AD79: =SUM(A:B!AD79) -> 5279.01 | AE79: =SUM(A:B!AE79) -> 4223.208 | AF79: =SUM(A:B!AF79) -> 3167.406 | ... AJ79: =SUM(A:B!AJ79) -> 4223.208 | AK79: =SUM(Y79:AJ79) -> 34841.466 | AL79: =AK79/AK$6 -> 0.0001389542 | AM79: =IFERROR(AK79/V79-1,0) -> 0 | AO79: 0 | AP79: 0 | AQ79: -1
I80: Multas y Recargos | J80: =SUM(A:B!J80) -> 0 | K80: =SUM(A:B!K80) -> 341 | L80: =SUM(A:B!L80) -> 0 | M80: =SUM(A:B!M80) -> 0 | N80: =SUM(A:B!N80) -> 0 | O80: =SUM(A:B!O80) -> 0 | P80: =SUM(A:B!P80) -> 0 | Q80: =SUM(A:B!Q80) -> 0 | ... U80: =SUM(A:B!U80) -> 0 | Y80: =SUM(A:B!Y80) -> 0 | Z80: =SUM(A:B!Z80) -> 0 | AA80: =SUM(A:B!AA80) -> 0 | AB80: =SUM(A:B!AB80) -> 0 | AC80: =SUM(A:B!AC80) -> 0 | AD80: =SUM(A:B!AD80) -> 0 | AE80: =SUM(A:B!AE80) -> 0 | AF80: =SUM(A:B!AF80) -> 0 | ... AJ80: =SUM(A:B!AJ80) -> 0 | AK80: =SUM(Y80:AJ80) -> 0 | AL80: =AK80/AK$6 -> 0 | AM80: =IFERROR(AK80/V80-1,0) -> 0 | AO80: 573892.2 | AP80: 0.00013020496 | AQ80: 0.47501311
A81: C - NOMINA | B81: estaciones | I81: Seguros y fianzas | J81: =SUM(A:B!J81) -> 3580 | K81: =SUM(A:B!K81) -> 3580 | L81: =SUM(A:B!L81) -> 3580 | M81: =SUM(A:B!M81) -> 3580 | N81: =SUM(A:B!N81) -> 3580 | O81: =SUM(A:B!O81) -> 3580 | P81: =SUM(A:B!P81) -> 3580 | Q81: =SUM(A:B!Q81) -> 14069 | ... U81: =SUM(A:B!U81) -> 18105.76 | Y81: =SUM(A:B!Y81) -> 18105.76 | Z81: =SUM(A:B!Z81) -> 18105.76 | AA81: =SUM(A:B!AA81) -> 18105.76 | AB81: =SUM(A:B!AB81) -> 18105.76 | AC81: =SUM(A:B!AC81) -> 18105.76 | AD81: =SUM(A:B!AD81) -> 18105.76 | AE81: =SUM(A:B!AE81) -> 18105.76 | AF81: =SUM(A:B!AF81) -> 18105.76 | ... AJ81: =SUM(A:B!AJ81) -> 18105.76 | AK81: =SUM(Y81:AJ81) -> 217269.12 | AL81: =AK81/AK$6 -> 0.00086650935 | AM81: =IFERROR(AK81/V81-1,0) -> 0 | AO81: 84376394 | AP81: 0.01914336 | AQ81: 0.3576927
A82: C - NOMINA | B82: estaciones | I82: Vigilancia y seguridad | J82: =SUM(A:B!J82) -> 0 | K82: =SUM(A:B!K82) -> 0 | L82: =SUM(A:B!L82) -> 0 | M82: =SUM(A:B!M82) -> 0 | N82: =SUM(A:B!N82) -> 0 | O82: =SUM(A:B!O82) -> 0 | P82: =SUM(A:B!P82) -> 0 | Q82: =SUM(A:B!Q82) -> 0 | ... U82: =SUM(A:B!U82) -> 0 | Y82: =SUM(A:B!Y82) -> 0 | Z82: =SUM(A:B!Z82) -> 0 | AA82: =SUM(A:B!AA82) -> 0 | AB82: =SUM(A:B!AB82) -> 0 | AC82: =SUM(A:B!AC82) -> 0 | AD82: =SUM(A:B!AD82) -> 0 | AE82: =SUM(A:B!AE82) -> 0 | AF82: =SUM(A:B!AF82) -> 0 | ... AJ82: =SUM(A:B!AJ82) -> 0 | AK82: =SUM(Y82:AJ82) -> 0 | AL82: =AK82/AK$6 -> 0 | AM82: =IFERROR(AK82/V82-1,0) -> 0 | AO82: 2447479.4 | AP82: 0.00055528541 | AQ82: 0.40769365
A83: C - NOMINA | B83: estaciones | I83: Honorarios Fiscales P.F. | J83: =SUM(A:B!J83) -> 4196 | K83: =SUM(A:B!K83) -> 4196 | L83: =SUM(A:B!L83) -> 4196 | M83: =SUM(A:B!M83) -> 4196 | N83: =SUM(A:B!N83) -> 4196 | O83: =SUM(A:B!O83) -> 4196 | P83: =SUM(A:B!P83) -> 4196 | Q83: =SUM(A:B!Q83) -> 5244 | ... U83: =SUM(A:B!U83) -> 0 | Y83: =SUM(A:B!Y83) -> 0 | Z83: =SUM(A:B!Z83) -> 0 | AA83: =SUM(A:B!AA83) -> 0 | AB83: =SUM(A:B!AB83) -> 0 | AC83: =SUM(A:B!AC83) -> 0 | AD83: =SUM(A:B!AD83) -> 0 | AE83: =SUM(A:B!AE83) -> 0 | AF83: =SUM(A:B!AF83) -> 0 | ... AJ83: =SUM(A:B!AJ83) -> 0 | AK83: =SUM(Y83:AJ83) -> 0 | AL83: =AK83/AK$6 -> 0 | AM83: =IFERROR(AK83/V83-1,0) -> 0 | AO83: 9194940.3 | AP83: 0.0020861529 | AQ83: 0.39739825
A84: C - NOMINA | B84: estaciones | I84: Honorarios Legales P.M. | J84: =SUM(A:B!J84) -> 0 | K84: =SUM(A:B!K84) -> 0 | L84: =SUM(A:B!L84) -> 0 | M84: =SUM(A:B!M84) -> 0 | N84: =SUM(A:B!N84) -> 0 | O84: =SUM(A:B!O84) -> 0 | P84: =SUM(A:B!P84) -> 0 | Q84: =SUM(A:B!Q84) -> 0 | ... U84: =SUM(A:B!U84) -> 0 | Y84: =SUM(A:B!Y84) -> 0 | Z84: =SUM(A:B!Z84) -> 0 | AA84: =SUM(A:B!AA84) -> 0 | AB84: =SUM(A:B!AB84) -> 0 | AC84: =SUM(A:B!AC84) -> 0 | AD84: =SUM(A:B!AD84) -> 0 | AE84: =SUM(A:B!AE84) -> 0 | AF84: =SUM(A:B!AF84) -> 0 | ... AJ84: =SUM(A:B!AJ84) -> 0 | AK84: =SUM(Y84:AJ84) -> 0 | AL84: =AK84/AK$6 -> 0 | AM84: =IFERROR(AK84/V84-1,0) -> 0 | AO84: 576608.07 | AP84: 0.00013082114 | AQ84: 0.73982376
A85: C - NOMINA | B85: estaciones | I85: Calcamonias y senalamientos | J85: =SUM(A:B!J85) -> 0 | K85: =SUM(A:B!K85) -> 0 | L85: =SUM(A:B!L85) -> 0 | M85: =SUM(A:B!M85) -> 0 | N85: =SUM(A:B!N85) -> 0 | O85: =SUM(A:B!O85) -> 0 | P85: =SUM(A:B!P85) -> 0 | Q85: =SUM(A:B!Q85) -> 0 | ... U85: =SUM(A:B!U85) -> 0 | Y85: =SUM(A:B!Y85) -> 0 | Z85: =SUM(A:B!Z85) -> 0 | AA85: =SUM(A:B!AA85) -> 0 | AB85: =SUM(A:B!AB85) -> 0 | AC85: =SUM(A:B!AC85) -> 0 | AD85: =SUM(A:B!AD85) -> 0 | AE85: =SUM(A:B!AE85) -> 0 | AF85: =SUM(A:B!AF85) -> 0 | ... AJ85: =SUM(A:B!AJ85) -> 0 | AK85: =SUM(Y85:AJ85) -> 0 | AL85: =AK85/AK$6 -> 0 | AM85: =IFERROR(AK85/V85-1,0) -> 0 | AO85: 3573320 | AP85: 0.0008107167 | AQ85: 0.55792511
A86: C - NOMINA | B86: estaciones | I86: Cuotas y suscripciones | J86: =SUM(A:B!J86) -> 0 | K86: =SUM(A:B!K86) -> 0 | L86: =SUM(A:B!L86) -> 0 | M86: =SUM(A:B!M86) -> 0 | N86: =SUM(A:B!N86) -> 0 | O86: =SUM(A:B!O86) -> 0 | P86: =SUM(A:B!P86) -> 0 | Q86: =SUM(A:B!Q86) -> 0 | ... U86: =SUM(A:B!U86) -> 0 | V86: =SUM(J86:U86) -> 0 | W86: =V86/V$6 -> 0 | Y86: =SUM(A:B!Y86) -> 0 | Z86: =SUM(A:B!Z86) -> 0 | AA86: =SUM(A:B!AA86) -> 0 | AB86: =SUM(A:B!AB86) -> 0 | AC86: =SUM(A:B!AC86) -> 0 | AD86: =SUM(A:B!AD86) -> 0 | AE86: =SUM(A:B!AE86) -> 0 | AF86: =SUM(A:B!AF86) -> 0 | ... AJ86: =SUM(A:B!AJ86) -> 0 | AK86: =SUM(Y86:AJ86) -> 0 | AL86: =AK86/AK$6 -> 0 | AM86: =IFERROR(AK86/V86-1,0) -> 0 | AO86: 0 | AP86: 0 | AQ86: -1
A87: C - NOMINA | B87: estaciones | I87: Cumplimiento Sat Anexo 30 y 31 | J87: =SUM(A:B!J87) -> 0 | K87: =SUM(A:B!K87) -> 0 | L87: =SUM(A:B!L87) -> 0 | M87: =SUM(A:B!M87) -> 0 | N87: =SUM(A:B!N87) -> 0 | O87: =SUM(A:B!O87) -> 0 | P87: =SUM(A:B!P87) -> 0 | Q87: =SUM(A:B!Q87) -> 0 | ... U87: =SUM(A:B!U87) -> 0 | V87: =SUM(J87:U87) -> 76960 | W87: =V87/V$6 -> 0.00034376643 | Y87: =SUM(A:B!Y87) -> 0 | Z87: =SUM(A:B!Z87) -> 0 | AA87: =SUM(A:B!AA87) -> 0 | AB87: =SUM(A:B!AB87) -> 0 | AC87: =SUM(A:B!AC87) -> 0 | AD87: =SUM(A:B!AD87) -> 0 | AE87: =SUM(A:B!AE87) -> 0 | AF87: =SUM(A:B!AF87) -> 0 | ... AJ87: =SUM(A:B!AJ87) -> 0 | AK87: =SUM(Y87:AJ87) -> 91192.31 | AL87: =AK87/AK$6 -> 0.00036369176 | AM87: =IFERROR(AK87/V87-1,0) -> 0.18493126 | AO87: 4364566.8 | AP87: 0.00099023518 | AQ87: 0.33067474
A88: C - NOMINA | B88: estaciones | I88: Eventos | J88: =SUM(A:B!J88) -> 0 | K88: =SUM(A:B!K88) -> 0 | L88: =SUM(A:B!L88) -> 0 | M88: =SUM(A:B!M88) -> 0 | N88: =SUM(A:B!N88) -> 0 | O88: =SUM(A:B!O88) -> 0 | P88: =SUM(A:B!P88) -> 0 | Q88: =SUM(A:B!Q88) -> 5772 | ... U88: =SUM(A:B!U88) -> 92892.8 | V88: =SUM(J88:U88) -> 100083.36 | W88: =V88/V$6 -> 0.0004470543 | Y88: =SUM(A:B!Y88) -> 0 | Z88: =SUM(A:B!Z88) -> 0 | AA88: =SUM(A:B!AA88) -> 0 | AB88: =SUM(A:B!AB88) -> 0 | AC88: =SUM(A:B!AC88) -> 8280.8 | AD88: =SUM(A:B!AD88) -> 8280.8 | AE88: =SUM(A:B!AE88) -> 0 | AF88: =SUM(A:B!AF88) -> 8280.8 | ... AJ88: =SUM(A:B!AJ88) -> 56309.44 | AK88: =SUM(Y88:AJ88) -> 85457.856 | AL88: =AK88/AK$6 -> 0.0003408217 | AM88: =IFERROR(AK88/V88-1,0) -> -0.14613322 | AO88: 3224251.1 | AP88: 0.00073151978 | AQ88: 0.39344092
A89: C - NOMINA | B89: estaciones | I89: Asesoria Acehico | J89: =SUM(A:B!J89) -> 0 | K89: =SUM(A:B!K89) -> 0 | L89: =SUM(A:B!L89) -> 0 | M89: =SUM(A:B!M89) -> 0 | N89: =SUM(A:B!N89) -> 0 | O89: =SUM(A:B!O89) -> 0 | P89: =SUM(A:B!P89) -> 0 | Q89: =SUM(A:B!Q89) -> 0 | ... U89: =SUM(A:B!U89) -> 0 | V89: =SUM(J89:U89) -> 0 | W89: =V89/V$6 -> 0 | Y89: =SUM(A:B!Y89) -> 0 | Z89: =SUM(A:B!Z89) -> 0 | AA89: =SUM(A:B!AA89) -> 0 | AB89: =SUM(A:B!AB89) -> 0 | AC89: =SUM(A:B!AC89) -> 0 | AD89: =SUM(A:B!AD89) -> 0 | AE89: =SUM(A:B!AE89) -> 0 | AF89: =SUM(A:B!AF89) -> 0 | ... AJ89: =SUM(A:B!AJ89) -> 0 | AK89: =SUM(Y89:AJ89) -> 0 | AL89: =AK89/AK$6 -> 0 | AM89: =IFERROR(AK89/V89-1,0) -> 0 | AO89: 0 | AP89: 0 | AQ89: -1
A90: C - NOMINA | B90: estaciones | I90: Prediales | J90: =SUM(A:B!J90) -> 0 | K90: =SUM(A:B!K90) -> 0 | L90: =SUM(A:B!L90) -> 0 | M90: =SUM(A:B!M90) -> 0 | N90: =SUM(A:B!N90) -> 0 | O90: =SUM(A:B!O90) -> 0 | P90: =SUM(A:B!P90) -> 0 | Q90: =SUM(A:B!Q90) -> 0 | ... U90: =SUM(A:B!U90) -> 0 | V90: =SUM(J90:U90) -> 0 | W90: =V90/V$6 -> 0 | Y90: =SUM(A:B!Y90) -> 0 | Z90: =SUM(A:B!Z90) -> 0 | AA90: =SUM(A:B!AA90) -> 0 | AB90: =SUM(A:B!AB90) -> 0 | AC90: =SUM(A:B!AC90) -> 0 | AD90: =SUM(A:B!AD90) -> 0 | AE90: =SUM(A:B!AE90) -> 0 | AF90: =SUM(A:B!AF90) -> 0 | ... AJ90: =SUM(A:B!AJ90) -> 0 | AK90: =SUM(Y90:AJ90) -> 0 | AL90: =AK90/AK$6 -> 0 | AM90: =IFERROR(AK90/V90-1,0) -> 0 | AO90: 868817.62 | AP90: 0.0001971178 | AQ90: -0.14662722
A91: C - NOMINA | B91: estaciones | I91: C - NOMINA | J91: =SUM(J92:J106) -> 694293 | K91: =SUM(K92:K106) -> 640704 | L91: =SUM(L92:L106) -> 705145 | M91: =SUM(M92:M106) -> 609334 | N91: =SUM(N92:N106) -> 575107 | O91: =SUM(O92:O106) -> 579544 | P91: =SUM(P92:P106) -> 555114 | Q91: =SUM(Q92:Q106) -> 531856 | ... V91: =SUM(V92:V106) -> 7439749.4 | W91: =V91/V$6 -> 0.033232018 | Y91: =SUM(Y92:Y106) -> 654481.99 | Z91: =SUM(Z92:Z106) -> 584894.01 | AA91: =SUM(AA92:AA106) -> 635149.7 | AB91: =SUM(AB92:AB106) -> 591373.42 | AC91: =SUM(AC92:AC106) -> 643430.5 | AD91: =SUM(AD92:AD106) -> 599654.22 | AE91: =SUM(AE92:AE106) -> 608125.32 | AF91: =SUM(AF92:AF106) -> 616406.12 | ... AK91: =SUM(AK92:AK106) -> 7565393.7 | AL91: =AK91/AK$6 -> 0.030172186 | AM91: =IFERROR(AK91/V91-1,0) -> 0.016888233 | AO91: 571078.53 | AP91: 0.0001295666 | AQ91: 0.34972762
A92: C - NOMINA | B92: estaciones | I92: Aguinaldo | J92: =SUM(A:B!J83) -> 4196 | K92: =SUM(A:B!K83) -> 4196 | L92: =SUM(A:B!L83) -> 4196 | M92: =SUM(A:B!M83) -> 4196 | N92: =SUM(A:B!N83) -> 4196 | O92: =SUM(A:B!O83) -> 4196 | P92: =SUM(A:B!P83) -> 4196 | Q92: =SUM(A:B!Q83) -> 5244 | ... U92: =SUM(A:B!U83) -> 0 | V92: =SUM(J92:U92) -> 43008 | W92: =V92/V$6 -> 0.00019210897 | Y92: =SUM(A:B!Y83) -> 0 | Z92: =SUM(A:B!Z83) -> 0 | AA92: =SUM(A:B!AA83) -> 0 | AB92: =SUM(A:B!AB83) -> 0 | AC92: =SUM(A:B!AC83) -> 0 | AD92: =SUM(A:B!AD83) -> 0 | AE92: =SUM(A:B!AE83) -> 0 | AF92: =SUM(A:B!AF83) -> 0 | ... AJ92: =SUM(A:B!AJ83) -> 0 | AK92: =SUM(Y92:AJ92) -> 0 | AL92: =AK92/AK$6 -> 0 | AM92: =IFERROR(AK92/V92-1,0) -> -1 | AO92: 0 | AP92: 0 | AQ92: -1
A93: C - NOMINA | B93: estaciones | I93: Compensaciones | J93: =SUM(A:B!J84) -> 0 | K93: =SUM(A:B!K84) -> 0 | L93: =SUM(A:B!L84) -> 0 | M93: =SUM(A:B!M84) -> 0 | N93: =SUM(A:B!N84) -> 0 | O93: =SUM(A:B!O84) -> 0 | P93: =SUM(A:B!P84) -> 0 | Q93: =SUM(A:B!Q84) -> 0 | ... U93: =SUM(A:B!U84) -> 0 | V93: =SUM(J93:U93) -> 0 | W93: =V93/V$6 -> 0 | Y93: =SUM(A:B!Y84) -> 0 | Z93: =SUM(A:B!Z84) -> 0 | AA93: =SUM(A:B!AA84) -> 0 | AB93: =SUM(A:B!AB84) -> 0 | AC93: =SUM(A:B!AC84) -> 0 | AD93: =SUM(A:B!AD84) -> 0 | AE93: =SUM(A:B!AE84) -> 0 | AF93: =SUM(A:B!AF84) -> 0 | ... AJ93: =SUM(A:B!AJ84) -> 0 | AK93: =SUM(Y93:AJ93) -> 0 | AL93: =AK93/AK$6 -> 0 | AM93: =IFERROR(AK93/V93-1,0) -> 0 | AO93: 0 | AP93: 0 | AQ93: 0
A94: C - NOMINA | B94: estaciones | I94: Días festivos | J94: =SUM(A:B!J85) -> 0 | K94: =SUM(A:B!K85) -> 0 | L94: =SUM(A:B!L85) -> 0 | M94: =SUM(A:B!M85) -> 0 | N94: =SUM(A:B!N85) -> 0 | O94: =SUM(A:B!O85) -> 0 | P94: =SUM(A:B!P85) -> 0 | Q94: =SUM(A:B!Q85) -> 0 | ... U94: =SUM(A:B!U85) -> 0 | V94: =SUM(J94:U94) -> 0 | W94: =V94/V$6 -> 0 | Y94: =SUM(A:B!Y85) -> 0 | Z94: =SUM(A:B!Z85) -> 0 | AA94: =SUM(A:B!AA85) -> 0 | AB94: =SUM(A:B!AB85) -> 0 | AC94: =SUM(A:B!AC85) -> 0 | AD94: =SUM(A:B!AD85) -> 0 | AE94: =SUM(A:B!AE85) -> 0 | AF94: =SUM(A:B!AF85) -> 0 | ... AJ94: =SUM(A:B!AJ85) -> 0 | AK94: =SUM(Y94:AJ94) -> 0 | AL94: =AK94/AK$6 -> 0 | AM94: =IFERROR(AK94/V94-1,0) -> 0 | AO94: 59555333 | AP94: 0.013511945 | AQ94: 0.50787992
A95: C - NOMINA | B95: estaciones | I95: Fondo de ahorro | J95: =SUM(A:B!J86) -> 0 | K95: =SUM(A:B!K86) -> 0 | L95: =SUM(A:B!L86) -> 0 | M95: =SUM(A:B!M86) -> 0 | N95: =SUM(A:B!N86) -> 0 | O95: =SUM(A:B!O86) -> 0 | P95: =SUM(A:B!P86) -> 0 | Q95: =SUM(A:B!Q86) -> 0 | ... U95: =SUM(A:B!U86) -> 0 | V95: =SUM(J95:U95) -> 0 | W95: =V95/V$6 -> 0 | Y95: =SUM(A:B!Y86) -> 0 | Z95: =SUM(A:B!Z86) -> 0 | AA95: =SUM(A:B!AA86) -> 0 | AB95: =SUM(A:B!AB86) -> 0 | AC95: =SUM(A:B!AC86) -> 0 | AD95: =SUM(A:B!AD86) -> 0 | AE95: =SUM(A:B!AE86) -> 0 | AF95: =SUM(A:B!AF86) -> 0 | ... AJ95: =SUM(A:B!AJ86) -> 0 | AK95: =SUM(Y95:AJ95) -> 0 | AL95: =AK95/AK$6 -> 0 | AM95: =IFERROR(AK95/V95-1,0) -> 0 | AO95: 0 | AP95: 0 | AQ95: -1
A96: C - NOMINA | B96: estaciones | I96: Indemnizaciones | J96: =SUM(A:B!J87) -> 0 | K96: =SUM(A:B!K87) -> 0 | L96: =SUM(A:B!L87) -> 0 | M96: =SUM(A:B!M87) -> 0 | N96: =SUM(A:B!N87) -> 0 | O96: =SUM(A:B!O87) -> 0 | P96: =SUM(A:B!P87) -> 0 | Q96: =SUM(A:B!Q87) -> 0 | ... U96: =SUM(A:B!U87) -> 0 | V96: =SUM(J96:U96) -> 76960 | W96: =V96/V$6 -> 0.00034376643 | Y96: =SUM(A:B!Y87) -> 0 | Z96: =SUM(A:B!Z87) -> 0 | AA96: =SUM(A:B!AA87) -> 0 | AB96: =SUM(A:B!AB87) -> 0 | AC96: =SUM(A:B!AC87) -> 0 | AD96: =SUM(A:B!AD87) -> 0 | AE96: =SUM(A:B!AE87) -> 0 | AF96: =SUM(A:B!AF87) -> 0 | ... AJ96: =SUM(A:B!AJ87) -> 0 | AK96: =SUM(Y96:AJ96) -> 91192.31 | AL96: =AK96/AK$6 -> 0.00036369176 | AM96: =IFERROR(AK96/V96-1,0) -> 0.18493126 | AO96: 0 | AP96: 0 | AQ96: -1
A97: D - COSTO SOCIAL | B97: estaciones | I97: Premios de asistencia | J97: =SUM(A:B!J88) -> 0 | K97: =SUM(A:B!K88) -> 0 | L97: =SUM(A:B!L88) -> 0 | M97: =SUM(A:B!M88) -> 0 | N97: =SUM(A:B!N88) -> 0 | O97: =SUM(A:B!O88) -> 0 | P97: =SUM(A:B!P88) -> 0 | Q97: =SUM(A:B!Q88) -> 5772 | ... U97: =SUM(A:B!U88) -> 92892.8 | V97: =SUM(J97:U97) -> 100083.36 | W97: =V97/V$6 -> 0.0004470543 | Y97: =SUM(A:B!Y88) -> 0 | Z97: =SUM(A:B!Z88) -> 0 | AA97: =SUM(A:B!AA88) -> 0 | AB97: =SUM(A:B!AB88) -> 0 | AC97: =SUM(A:B!AC88) -> 8280.8 | AD97: =SUM(A:B!AD88) -> 8280.8 | AE97: =SUM(A:B!AE88) -> 0 | AF97: =SUM(A:B!AF88) -> 8280.8 | ... AJ97: =SUM(A:B!AJ88) -> 56309.44 | AK97: =SUM(Y97:AJ97) -> 85457.856 | AL97: =AK97/AK$6 -> 0.0003408217 | AM97: =IFERROR(AK97/V97-1,0) -> -0.14613322 | AO97: 15763375 | AP97: 0.0035764027 | AQ97: 0.17030665
A98: D - COSTO SOCIAL | B98: estaciones | I98: Premios de puntualidad | J98: =SUM(A:B!J89) -> 0 | K98: =SUM(A:B!K89) -> 0 | L98: =SUM(A:B!L89) -> 0 | M98: =SUM(A:B!M89) -> 0 | N98: =SUM(A:B!N89) -> 0 | O98: =SUM(A:B!O89) -> 0 | P98: =SUM(A:B!P89) -> 0 | Q98: =SUM(A:B!Q89) -> 0 | ... U98: =SUM(A:B!U89) -> 0 | V98: =SUM(J98:U98) -> 0 | W98: =V98/V$6 -> 0 | Y98: =SUM(A:B!Y89) -> 0 | Z98: =SUM(A:B!Z89) -> 0 | AA98: =SUM(A:B!AA89) -> 0 | AB98: =SUM(A:B!AB89) -> 0 | AC98: =SUM(A:B!AC89) -> 0 | AD98: =SUM(A:B!AD89) -> 0 | AE98: =SUM(A:B!AE89) -> 0 | AF98: =SUM(A:B!AF89) -> 0 | ... AJ98: =SUM(A:B!AJ89) -> 0 | AK98: =SUM(Y98:AJ98) -> 0 | AL98: =AK98/AK$6 -> 0 | AM98: =IFERROR(AK98/V98-1,0) -> 0 | AO98: 3588441.5 | AP98: 0.00081414749 | AQ98: 0.51951629
A99: D - COSTO SOCIAL | B99: estaciones | I99: Previsión social | J99: =SUM(A:B!J90) -> 0 | K99: =SUM(A:B!K90) -> 0 | L99: =SUM(A:B!L90) -> 0 | M99: =SUM(A:B!M90) -> 0 | N99: =SUM(A:B!N90) -> 0 | O99: =SUM(A:B!O90) -> 0 | P99: =SUM(A:B!P90) -> 0 | Q99: =SUM(A:B!Q90) -> 0 | ... U99: =SUM(A:B!U90) -> 0 | V99: =SUM(J99:U99) -> 0 | W99: =V99/V$6 -> 0 | Y99: =SUM(A:B!Y90) -> 0 | Z99: =SUM(A:B!Z90) -> 0 | AA99: =SUM(A:B!AA90) -> 0 | AB99: =SUM(A:B!AB90) -> 0 | AC99: =SUM(A:B!AC90) -> 0 | AD99: =SUM(A:B!AD90) -> 0 | AE99: =SUM(A:B!AE90) -> 0 | AF99: =SUM(A:B!AF90) -> 0 | ... AJ99: =SUM(A:B!AJ90) -> 0 | AK99: =SUM(Y99:AJ99) -> 0 | AL99: =AK99/AK$6 -> 0 | AM99: =IFERROR(AK99/V99-1,0) -> 0 | AO99: 4178733.5 | AP99: 0.00094807323 | AQ99: 0.81448847
A100: D - COSTO SOCIAL | B100: estaciones | I100: Prima dominical | J100: =SUM(A:B!J91) -> 572627 | K100: =SUM(A:B!K91) -> 519516 | L100: =SUM(A:B!L91) -> 569185 | M100: =SUM(A:B!M91) -> 487941 | N100: =SUM(A:B!N91) -> 447884 | O100: =SUM(A:B!O91) -> 469573 | P100: =SUM(A:B!P91) -> 447601 | Q100: =SUM(A:B!Q91) -> 432809 | ... U100: =SUM(A:B!U91) -> 473356.42 | V100: =SUM(J100:U100) -> 5849253 | W100: =V100/V$6 -> 0.026127557 | Y100: =SUM(A:B!Y91) -> 528532.23 | Z100: =SUM(A:B!Z91) -> 466133.45 | AA100: =SUM(A:B!AA91) -> 509870.56 | AB100: =SUM(A:B!AB91) -> 481779.33 | AC100: =SUM(A:B!AC91) -> 509870.56 | AD100: =SUM(A:B!AD91) -> 481779.33 | AE100: =SUM(A:B!AE91) -> 496358.37 | AF100: =SUM(A:B!AF91) -> 496358.37 | ... AJ100: =SUM(A:B!AJ91) -> 509870.56 | AK100: =SUM(Y100:AJ100) -> 5967494.2 | AL100: =AK100/AK$6 -> 0.023799468 | AM100: =IFERROR(AK100/V100-1,0) -> 0.020214749 | AO100: 7940461.3 | AP100: 0.001801536 | AQ100: 0.20347279
A101: D - COSTO SOCIAL | B101: estaciones | I101: Prima vacacional | J101: =SUM(A:B!J92) -> 16736 | K101: =SUM(A:B!K92) -> 14901 | L101: =SUM(A:B!L92) -> 16005 | M101: =SUM(A:B!M92) -> 13919 | N101: =SUM(A:B!N92) -> 12304 | O101: =SUM(A:B!O92) -> 13178 | P101: =SUM(A:B!P92) -> 12860 | Q101: =SUM(A:B!Q92) -> 13080 | ... U101: =SUM(A:B!U92) -> 13333.896 | V101: =SUM(J101:U101) -> 166763.15 | W101: =V101/V$6 -> 0.00074490086 | Y101: =SUM(A:B!Y92) -> 15059.301 | Z101: =SUM(A:B!Z92) -> 12956.895 | AA101: =SUM(A:B!AA92) -> 14345.134 | AB101: =SUM(A:B!AB92) -> 13882.388 | AC101: =SUM(A:B!AC92) -> 14345.134 | AD101: =SUM(A:B!AD92) -> 13882.388 | AE101: =SUM(A:B!AE92) -> 14345.134 | AF101: =SUM(A:B!AF92) -> 14345.134 | ... AJ101: =SUM(A:B!AJ92) -> 14345.134 | AK101: =SUM(Y101:AJ101) -> 169616.55 | AL101: =AK101/AK$6 -> 0.00067646212 | AM101: =IFERROR(AK101/V101-1,0) -> 0.017110544 | AO101: 55738.326 | AP101: 1.264594e-05 | AQ101: -0.97474399
A102: F - MANTENIMIENTO | B102: estaciones | C102: Mantenimiento de Imagen | I102: Primas de antigüedad | J102: =SUM(A:B!J93) -> 19800 | K102: =SUM(A:B!K93) -> 29407 | L102: =SUM(A:B!L93) -> 37315 | M102: =SUM(A:B!M93) -> 53806 | N102: =SUM(A:B!N93) -> 53059 | O102: =SUM(A:B!O93) -> 41042 | P102: =SUM(A:B!P93) -> 40487 | Q102: =SUM(A:B!Q93) -> 29123 | ... U102: =SUM(A:B!U93) -> 46787.007 | V102: =SUM(J102:U102) -> 493518.59 | W102: =V102/V$6 -> 0.0022044584 | Y102: =SUM(A:B!Y93) -> 44408.263 | Z102: =SUM(A:B!Z93) -> 44408.263 | AA102: =SUM(A:B!AA93) -> 44408.263 | AB102: =SUM(A:B!AB93) -> 44408.263 | AC102: =SUM(A:B!AC93) -> 44408.263 | AD102: =SUM(A:B!AD93) -> 44408.263 | AE102: =SUM(A:B!AE93) -> 44408.263 | AF102: =SUM(A:B!AF93) -> 44408.263 | ... AJ102: =SUM(A:B!AJ93) -> 44408.263 | AK102: =SUM(Y102:AJ102) -> 532899.15 | AL102: =AK102/AK$6 -> 0.0021253002 | AM102: =IFERROR(AK102/V102-1,0) -> 0.079795503 | AO102: 17625022 | AP102: 0.0039987742 | AQ102: 0.23759562
...

Sheet S

Sheet COM-MKT
I1: Mantenimiento de Imagen | Y1: 2 | Z1: 3 | AA1: 4 | AB1: 5 | AC1: 6 | AD1: 7 | AE1: 8 | AF1: 9 | AG1: 10 | AH1: 11 | AI1: 12 | AJ1: 13 | AM1: 17
J2: 2024 | V2: TOTAL ANUAL | Y2: 2025 | AK2: TOTAL ANUAL
J3: ENE | K3: FEB | L3: MAR | M3: ABR | N3: MAY | O3: JUN | P3: JUL | Q3: AGO | R3: SEP | S3: OCT | T3: NOV | U3: DIC | V3: 2024 | W3: % Part | Y3: ENE | Z3: FEB | AA3: MAR | AB3: ABR | AC3: MAY | AD3: JUN | AE3: JUL | AF3: AGO | AG3: SEP | AH3: OCT | AI3: NOV | AJ3: DIC | AK3: 2025 | AL3: % Part | AM3: Var vs AA%
I4: INGRESOS
A6: A - INGRESOS | E6: ( mas ) | I6: A - INGRESOS | V6: =SUM(J6:U6) -> 0 | W6: =V6/V$6 -> #DIV/0! | Y6: =SUM(Y7:Y10) -> 0 | Z6: =SUM(Z7:Z10) -> 0 | AA6: =SUM(AA7:AA10) -> 0 | AB6: =SUM(AB7:AB10) -> 0 | AC6: =SUM(AC7:AC10) -> 0 | AD6: =SUM(AD7:AD10) -> 0 | AE6: =SUM(AE7:AE10) -> 0 | AF6: =SUM(AF7:AF10) -> 0 | ... AJ6: =SUM(AJ7:AJ10) -> 0 | AK6: =SUM(Y6:AJ6) -> 0 | AL6: =AK6/AK$6 -> #DIV/0! | AM6: =IFERROR(AK6/V6-1,0) -> 0
A7: A - INGRESOS | B7: estaciones | C7: INGRESOS MAGNA | D7: INGRESOS FORANEOS MAGNA | I7: T-MAXIMA REGULAR | V7: =SUM(J7:U7) -> 0 | W7: =V7/V$6 -> #DIV/0! | Y7: 0 | Z7: 0 | AA7: 0 | AB7: 0 | AC7: 0 | AD7: 0 | AE7: 0 | AF7: 0 | AG7: 0 | AH7: 0 | AI7: 0 | AJ7: 0 | AK7: =SUM(Y7:AJ7) -> 0 | AL7: =AK7/AK$6 -> #DIV/0! | AM7: =IFERROR(AK7/V7-1,0) -> 0
A8: A - INGRESOS | B8: estaciones | C8: INGRESOS PREMIUM | D8: INGRESOS FORANEOS PREMIUM | I8: T-SUPER PREMIUM | V8: =SUM(J8:U8) -> 0 | W8: =V8/V$6 -> #DIV/0! | Y8: 0 | Z8: 0 | AA8: 0 | AB8: 0 | AC8: 0 | AD8: 0 | AE8: 0 | AF8: 0 | AG8: 0 | AH8: 0 | AI8: 0 | AJ8: 0 | AK8: =SUM(Y8:AJ8) -> 0 | AL8: =AK8/AK$6 -> #DIV/0! | AM8: =IFERROR(AK8/V8-1,0) -> 0
A9: A - INGRESOS | B9: estaciones | C9: INGRESOS DIESEL | D9: INGRESOS FORANEOS DIESEL | I9: DIESEL AUTOMOTRIZ | V9: =SUM(J9:U9) -> 0 | W9: =V9/V$6 -> #DIV/0! | Y9: 0 | Z9: 0 | AA9: 0 | AB9: 0 | AC9: 0 | AD9: 0 | AE9: 0 | AF9: 0 | AG9: 0 | AH9: 0 | AI9: 0 | AJ9: 0 | AK9: =SUM(Y9:AJ9) -> 0 | AL9: =AK9/AK$6 -> #DIV/0! | AM9: =IFERROR(AK9/V9-1,0) -> 0
A10: A - INGRESOS | B10: estaciones | C10: INGRESOS ADITIVOS | D10: INGRESOS ESPECIALES | F10: INGRESOS FORANEOS ESPECIALES | G10: INGRESOS FORANEOS LUBRICANTES | H10: INGRESOS LUBRICANTES | I10: PREPAGO facturación (neto) | V10: =SUM(J10:U10) -> 0 | W10: =V10/V$6 -> #DIV/0! | Y10: 0 | Z10: 0 | AA10: 0 | AB10: 0 | AC10: 0 | AD10: 0 | AE10: 0 | AF10: 0 | AG10: 0 | AH10: 0 | AI10: 0 | AJ10: 0 | AK10: =SUM(Y10:AJ10) -> 0 | AL10: =AK10/AK$6 -> #DIV/0! | AM10: =IFERROR(AK10/V10-1,0) -> 0
A11: A - INGRESOS | B11: estaciones | C11: INGRESOS ADITIVOS | D11: INGRESOS ESPECIALES | E11: INGRESOS FORANEOS ADITIVOS | F11: INGRESOS FORANEOS ESPECIALES | G11: INGRESOS FORANEOS LUBRICANTES | H11: INGRESOS LUBRICANTES | I11: INGRESOS ACEITES Y LUBRICANTES | V11: =SUM(J11:U11) -> 0 | W11: =V11/V$6 -> #DIV/0! | Y11: 0 | Z11: 0 | AA11: 0 | AB11: 0 | AC11: 0 | AD11: 0 | AE11: 0 | AF11: 0 | AG11: 0 | AH11: 0 | AI11: 0 | AJ11: 0 | AK11: =SUM(Y11:AJ11) -> 0 | AL11: =AK11/AK$6 -> #DIV/0! | AM11: =IFERROR(AK11/V11-1,0) -> 0
I12: SOBRANTE REGULAR
I13: SOBRANTE PREMIUM
I14: SOBRANTE DIESEL
A15: B - COSTO DE VENTA | E15: ( menos ) | I15: B - COSTO DE VENTA | V15: =SUM(J15:U15) -> 0 | W15: =V15/V$6 -> #DIV/0! | Y15: =SUM(Y16:Y31) -> 0 | Z15: =SUM(Z16:Z31) -> 0 | AA15: =SUM(AA16:AA31) -> 0 | AB15: =SUM(AB16:AB31) -> 0 | AC15: =SUM(AC16:AC31) -> 0 | AD15: =SUM(AD16:AD31) -> 0 | AE15: =SUM(AE16:AE31) -> 0 | AF15: =SUM(AF16:AF31) -> 0 | ... AJ15: =SUM(AJ16:AJ31) -> 0 | AK15: =SUM(Y15:AJ15) -> 0 | AL15: =AK15/AK$6 -> #DIV/0! | AM15: =IFERROR(AK15/V15-1,0) -> 0
A16: B - COSTO DE VENTA | C16: COSTO MAGNA | D16: COSTO FORANEO MAGNA | I16: GASOLINA REGULAR | V16: =SUM(J16:U16) -> 0 | W16: =V16/V$6 -> #DIV/0! | Y16: 0 | Z16: 0 | AA16: 0 | AB16: 0 | AC16: 0 | AD16: 0 | AE16: 0 | AF16: 0 | AG16: 0 | AH16: 0 | AI16: 0 | AJ16: 0 | AK16: =SUM(Y16:AJ16) -> 0 | AL16: =AK16/AK$6 -> #DIV/0! | AM16: =IFERROR(AK16/V16-1,0) -> 0
A17: B - COSTO DE VENTA | C17: COSTO PREMIUM | D17: COSTO FORANEO PREMIUM | I17: GASOLINA PREMIUM | V17: =SUM(J17:U17) -> 0 | W17: =V17/V$6 -> #DIV/0! | Y17: 0 | Z17: 0 | AA17: 0 | AB17: 0 | AC17: 0 | AD17: 0 | AE17: 0 | AF17: 0 | AG17: 0 | AH17: 0 | AI17: 0 | AJ17: 0 | AK17: =SUM(Y17:AJ17) -> 0 | AL17: =AK17/AK$6 -> #DIV/0! | AM17: =IFERROR(AK17/V17-1,0) -> 0
A18: B - COSTO DE VENTA | C18: COSTO DIESEL | D18: COSTO FORANEO DIESEL | I18: DIESEL | V18: =SUM(J18:U18) -> 0 | W18: =V18/V$6 -> #DIV/0! | Y18: 0 | Z18: 0 | AA18: 0 | AB18: 0 | AC18: 0 | AD18: 0 | AE18: 0 | AF18: 0 | AG18: 0 | AH18: 0 | AI18: 0 | AJ18: 0 | AK18: =SUM(Y18:AJ18) -> 0 | AL18: =AK18/AK$6 -> #DIV/0! | AM18: =IFERROR(AK18/V18-1,0) -> 0
A19: B - COSTO DE VENTA | C19: Merma Magna | I19: MERMA GASOLINA REGULAR | V19: =SUM(J19:U19) -> 0 | W19: =V19/V$6 -> #DIV/0! | Y19: 0 | Z19: 0 | AA19: 0 | AB19: 0 | AC19: 0 | AD19: 0 | AE19: 0 | AF19: 0 | AG19: 0 | AH19: 0 | AI19: 0 | AJ19: 0 | AK19: =SUM(Y19:AJ19) -> 0 | AL19: =AK19/AK$6 -> #DIV/0! | AM19: =IFERROR(AK19/V19-1,0) -> 0
A20: B - COSTO DE VENTA | C20: Merma Premium | I20: MERMA GASOLINA PREMIUM | V20: =SUM(J20:U20) -> 0 | W20: =V20/V$6 -> #DIV/0! | Y20: 0 | Z20: 0 | AA20: 0 | AB20: 0 | AC20: 0 | AD20: 0 | AE20: 0 | AF20: 0 | AG20: 0 | AH20: 0 | AI20: 0 | AJ20: 0 | AK20: =SUM(Y20:AJ20) -> 0 | AL20: =AK20/AK$6 -> #DIV/0! | AM20: =IFERROR(AK20/V20-1,0) -> 0
A21: B - COSTO DE VENTA | C21: Merma Diesel | I21: MERMA DIESEL | V21: =SUM(J21:U21) -> 0 | W21: =V21/V$6 -> #DIV/0! | Y21: 0 | Z21: 0 | AA21: 0 | AB21: 0 | AC21: 0 | AD21: 0 | AE21: 0 | AF21: 0 | AG21: 0 | AH21: 0 | AI21: 0 | AJ21: 0 | AK21: =SUM(Y21:AJ21) -> 0 | AL21: =AK21/AK$6 -> #DIV/0! | AM21: =IFERROR(AK21/V21-1,0) -> 0
A22: B - COSTO DE VENTA | C22: ADITIVO PARA GASOLINA TMAXIMA (REGULAR) | D22: ADITIVO PARA GASOLINA TMAXIMA( REGULAR) | I22: ADITIVO TOTAL POWER GASOLINA REG | V22: =SUM(J22:U22) -> 0 | W22: =V22/V$6 -> #DIV/0! | Y22: 0 | Z22: 0 | AA22: 0 | AB22: 0 | AC22: 0 | AD22: 0 | AE22: 0 | AF22: 0 | AG22: 0 | AH22: 0 | AI22: 0 | AJ22: 0 | AK22: =SUM(Y22:AJ22) -> 0 | AL22: =AK22/AK$6 -> #DIV/0! | AM22: =IFERROR(AK22/V22-1,0) -> 0
A23: B - COSTO DE VENTA | C23: ADITIVO PARA GASOLINA TSUPER (PREMIUM) | I23: ADITIVO TOTAL POWER GASOLINA PREM | V23: =SUM(J23:U23) -> 0 | W23: =V23/V$6 -> #DIV/0! | Y23: 0 | Z23: 0 | AA23: 0 | AB23: 0 | AC23: 0 | AD23: 0 | AE23: 0 | AF23: 0 | AG23: 0 | AH23: 0 | AI23: 0 | AJ23: 0 | AK23: =SUM(Y23:AJ23) -> 0 | AL23: =AK23/AK$6 -> #DIV/0! | AM23: =IFERROR(AK23/V23-1,0) -> 0
A24: B - COSTO DE VENTA | C24: FLETE MAGNA | I24: FLETE GASOLINA REGULAR | V24: =SUM(J24:U24) -> 0 | W24: =V24/V$6 -> #DIV/0! | Y24: 0 | Z24: 0 | AA24: 0 | AB24: 0 | AC24: 0 | AD24: 0 | AE24: 0 | AF24: 0 | AG24: 0 | AH24: 0 | AI24: 0 | AJ24: 0 | AK24: =SUM(Y24:AJ24) -> 0 | AL24: =AK24/AK$6 -> #DIV/0! | AM24: =IFERROR(AK24/V24-1,0) -> 0
A25: B - COSTO DE VENTA | C25: FLETE PREMIUM | I25: FLETE GASOLINA PREMIUM | V25: =SUM(J25:U25) -> 0 | W25: =V25/V$6 -> #DIV/0! | Y25: 0 | Z25: 0 | AA25: 0 | AB25: 0 | AC25: 0 | AD25: 0 | AE25: 0 | AF25: 0 | AG25: 0 | AH25: 0 | AI25: 0 | AJ25: 0 | AK25: =SUM(Y25:AJ25) -> 0 | AL25: =AK25/AK$6 -> #DIV/0! | AM25: =IFERROR(AK25/V25-1,0) -> 0
A26: B - COSTO DE VENTA | C26: FLETE DIESEL | I26: FLETE DIESEL | V26: =SUM(J26:U26) -> 0 | W26: =V26/V$6 -> #DIV/0! | Y26: 0 | Z26: 0 | AA26: 0 | AB26: 0 | AC26: 0 | AD26: 0 | AE26: 0 | AF26: 0 | AG26: 0 | AH26: 0 | AI26: 0 | AJ26: 0 | AK26: =SUM(Y26:AJ26) -> 0 | AL26: =AK26/AK$6 -> #DIV/0! | AM26: =IFERROR(AK26/V26-1,0) -> 0
A27: B - COSTO DE VENTA | C27: Estimulo IEPS Magna | D27: INGRESOS FORANEOS MAGNA | I27: ESTIMULO REGULAR | V27: =SUM(J27:U27) -> 0 | W27: =V27/V$6 -> #DIV/0! | Y27: 0 | Z27: 0 | AA27: 0 | AB27: 0 | AC27: 0 | AD27: 0 | AE27: 0 | AF27: 0 | AG27: 0 | AH27: 0 | AI27: 0 | AJ27: 0 | AK27: =SUM(Y27:AJ27) -> 0 | AL27: =AK27/AK$6 -> #DIV/0! | AM27: =IFERROR(AK27/V27-1,0) -> 0
A28: B - COSTO DE VENTA | C28: Estimulo IEPS Premium | D28: INGRESOS FORANEOS MAGNA | I28: ESTIMULO PREMIUM | V28: =SUM(J28:U28) -> 0 | W28: =V28/V$6 -> #DIV/0! | Y28: 0 | Z28: 0 | AA28: 0 | AB28: 0 | AC28: 0 | AD28: 0 | AE28: 0 | AF28: 0 | AG28: 0 | AH28: 0 | AI28: 0 | AJ28: 0 | AK28: =SUM(Y28:AJ28) -> 0 | AL28: =AK28/AK$6 -> #DIV/0! | AM28: =IFERROR(AK28/V28-1,0) -> 0
I29: DESCUENTO SOBRE VENTA
I30: COSTO UNIFORMES
I31: COSTO ACEITES Y LUBRICANTES | V31: =SUM(J31:U31) -> 0 | W31: =V31/V$6 -> #DIV/0! | Y31: 0 | Z31: 0 | AA31: 0 | AB31: 0 | AC31: 0 | AD31: 0 | AE31: 0 | AF31: 0 | AG31: 0 | AH31: 0 | AI31: 0 | AJ31: 0 | AK31: =SUM(Y31:AJ31) -> 0 | AL31: =AK31/AK$6 -> #DIV/0! | AM31: =IFERROR(AK31/V31-1,0) -> 0
I32: MARGEN DE UTILIDAD | V32: =V6-V15 -> 0 | W32: =V32/V$6 -> #DIV/0! | Y32: =Y6-Y15 -> 0 | Z32: =Z6-Z15 -> 0 | AA32: =AA6-AA15 -> 0 | AB32: =AB6-AB15 -> 0 | AC32: =AC6-AC15 -> 0 | AD32: =AD6-AD15 -> 0 | AE32: =AE6-AE15 -> 0 | AF32: =AF6-AF15 -> 0 | ... AK32: =AK6-AK15 -> 0 | AL32: =AK32/AK$6 -> #DIV/0! | AM32: =IFERROR(AK32/V32-1,0) -> 0
I33: Regular | V33: =SUM(J33:U33) -> 0 | Y33: =+Y43*Y39 -> 0 | Z33: =+Z43*Z39 -> 0 | AA33: =+AA43*AA39 -> 0 | AB33: =+AB43*AB39 -> 0 | AC33: =+AC43*AC39 -> 0 | AD33: =+AD43*AD39 -> 0 | AE33: =+AE43*AE39 -> 0 | AF33: =+AF43*AF39 -> 0 | ... AJ33: =+AJ43*AJ39 -> 0 | AK33: =SUM(Y33:AJ33) -> 0 | AM33: =IFERROR(AK33/V33-1,0) -> 0
I34: Premium | V34: =SUM(J34:U34) -> 0 | Y34: =+Y44*Y40 -> 0 | Z34: =+Z44*Z40 -> 0 | AA34: =+AA44*AA40 -> 0 | AB34: =+AB44*AB40 -> 0 | AC34: =+AC44*AC40 -> 0 | AD34: =+AD44*AD40 -> 0 | AE34: =+AE44*AE40 -> 0 | AF34: =+AF44*AF40 -> 0 | ... AJ34: =+AJ44*AJ40 -> 0 | AK34: =SUM(Y34:AJ34) -> 0 | AM34: =IFERROR(AK34/V34-1,0) -> 0
I35: Diesel | V35: =SUM(J35:U35) -> 0 | Y35: =+Y45*Y41 -> 0 | Z35: =+Z45*Z41 -> 0 | AA35: =+AA45*AA41 -> 0 | AB35: =+AB45*AB41 -> 0 | AC35: =+AC45*AC41 -> 0 | AD35: =+AD45*AD41 -> 0 | AE35: =+AE45*AE41 -> 0 | AF35: =+AF45*AF41 -> 0 | ... AJ35: =+AJ45*AJ41 -> 0 | AK35: =SUM(Y35:AJ35) -> 0 | AM35: =IFERROR(AK35/V35-1,0) -> 0
I36: *Otros Conceptos
I37: * Aceites y Lubricantes
I38: Litros vendidos | V38: =SUM(J38:U38) -> 0 | W38: =V38/V$38 -> #DIV/0! | Y38: =SUM(Y39:Y41) -> 0 | Z38: =SUM(Z39:Z41) -> 0 | AA38: =SUM(AA39:AA41) -> 0 | AB38: =SUM(AB39:AB41) -> 0 | AC38: =SUM(AC39:AC41) -> 0 | AD38: =SUM(AD39:AD41) -> 0 | AE38: =SUM(AE39:AE41) -> 0 | AF38: =SUM(AF39:AF41) -> 0 | ... AJ38: =SUM(AJ39:AJ41) -> 0 | AK38: =SUM(Y38:AJ38) -> 0 | AL38: =AK38/AK$38 -> #DIV/0! | AM38: =IFERROR(AK38/V38-1,0) -> 0
I39: Regular | V39: =SUM(J39:U39) -> 0 | W39: =V39/V$38 -> #DIV/0! | Y39: 0 | Z39: 0 | AA39: 0 | AB39: 0 | AC39: 0 | AD39: 0 | AE39: 0 | AF39: 0 | AG39: 0 | AH39: 0 | AI39: 0 | AJ39: 0 | AK39: =SUM(Y39:AJ39) -> 0 | AL39: =AK39/AK$38 -> #DIV/0! | AM39: =IFERROR(AK39/V39-1,0) -> 0
I40: Premium | V40: =SUM(J40:U40) -> 0 | W40: =V40/V$38 -> #DIV/0! | Y40: 0 | Z40: 0 | AA40: 0 | AB40: 0 | AC40: 0 | AD40: 0 | AE40: 0 | AF40: 0 | AG40: 0 | AH40: 0 | AI40: 0 | AJ40: 0 | AK40: =SUM(Y40:AJ40) -> 0 | AL40: =AK40/AK$38 -> #DIV/0! | AM40: =IFERROR(AK40/V40-1,0) -> 0
I41: Diesel | V41: =SUM(J41:U41) -> 0 | W41: =V41/V$38 -> #DIV/0! | Y41: 0 | Z41: 0 | AA41: 0 | AB41: 0 | AC41: 0 | AD41: 0 | AE41: 0 | AF41: 0 | AG41: 0 | AH41: 0 | AI41: 0 | AJ41: 0 | AK41: =SUM(Y41:AJ41) -> 0 | AL41: =AK41/AK$38 -> #DIV/0! | AM41: =IFERROR(AK41/V41-1,0) -> 0
I42: Margen de utilidad por litro | V42: =SUM(J42:U42) -> 0 | Y42: =IFERROR(Y32/Y38,0) -> 0 | Z42: =IFERROR(Z32/Z38,0) -> 0 | AA42: =IFERROR(AA32/AA38,0) -> 0 | AB42: =IFERROR(AB32/AB38,0) -> 0 | AC42: =IFERROR(AC32/AC38,0) -> 0 | AD42: =IFERROR(AD32/AD38,0) -> 0 | AE42: =IFERROR(AE32/AE38,0) -> 0 | AF42: =IFERROR(AF32/AF38,0) -> 0 | ... AJ42: =IFERROR(AJ32/AJ38,0) -> 0 | AK42: =SUM(Y42:AJ42) -> 0 | AM42: =IFERROR(AK42/V42-1,0) -> 0
I43: Regular | V43: =IFERROR((V7-(V16+V19+V22+V24+V27))/V39,0) -> 0 | Y43: =IFERROR((Y7-(Y16+Y19+Y22+Y24+Y27))/Y39,0) -> 0 | Z43: =IFERROR((Z7-(Z16+Z19+Z22+Z24+Z27))/Z39,0) -> 0 | AA43: =IFERROR((AA7-(AA16+AA19+AA22+AA24+AA27))/AA39,0) -> 0 | AB43: =IFERROR((AB7-(AB16+AB19+AB22+AB24+AB27))/AB39,0) -> 0 | AC43: =IFERROR((AC7-(AC16+AC19+AC22+AC24+AC27))/AC39,0) -> 0 | AD43: =IFERROR((AD7-(AD16+AD19+AD22+AD24+AD27))/AD39,0) -> 0 | AE43: =IFERROR((AE7-(AE16+AE19+AE22+AE24+AE27))/AE39,0) -> 0 | AF43: =IFERROR((AF7-(AF16+AF19+AF22+AF24+AF27))/AF39,0) -> 0 | ... AK43: =IFERROR((AK7-(AK16+AK19+AK22+AK24+AK27))/AK39,0) -> 0 | AM43: =IFERROR(AK43/V43-1,0) -> 0
I44: Premium | V44: =IFERROR((V8-(V17+V20+V23+V25+V28))/V40,0) -> 0 | Y44: =IFERROR((Y8-(Y17+Y20+Y23+Y25+Y28))/Y40,0) -> 0 | Z44: =IFERROR((Z8-(Z17+Z20+Z23+Z25+Z28))/Z40,0) -> 0 | AA44: =IFERROR((AA8-(AA17+AA20+AA23+AA25+AA28))/AA40,0) -> 0 | AB44: =IFERROR((AB8-(AB17+AB20+AB23+AB25+AB28))/AB40,0) -> 0 | AC44: =IFERROR((AC8-(AC17+AC20+AC23+AC25+AC28))/AC40,0) -> 0 | AD44: =IFERROR((AD8-(AD17+AD20+AD23+AD25+AD28))/AD40,0) -> 0 | AE44: =IFERROR((AE8-(AE17+AE20+AE23+AE25+AE28))/AE40,0) -> 0 | AF44: =IFERROR((AF8-(AF17+AF20+AF23+AF25+AF28))/AF40,0) -> 0 | ... AK44: =IFERROR((AK8-(AK17+AK20+AK23+AK25+AK28))/AK40,0) -> 0 | AM44: =IFERROR(AK44/V44-1,0) -> 0
I45: Diesel | V45: =IFERROR((V9-(V18+V21+V26))/V41,0) -> 0 | Y45: =IFERROR((Y9-(Y18+Y21+Y26))/Y41,0) -> 0 | Z45: =IFERROR((Z9-(Z18+Z21+Z26))/Z41,0) -> 0 | AA45: =IFERROR((AA9-(AA18+AA21+AA26))/AA41,0) -> 0 | AB45: =IFERROR((AB9-(AB18+AB21+AB26))/AB41,0) -> 0 | AC45: =IFERROR((AC9-(AC18+AC21+AC26))/AC41,0) -> 0 | AD45: =IFERROR((AD9-(AD18+AD21+AD26))/AD41,0) -> 0 | AE45: =IFERROR((AE9-(AE18+AE21+AE26))/AE41,0) -> 0 | AF45: =IFERROR((AF9-(AF18+AF21+AF26))/AF41,0) -> 0 | ... AK45: =IFERROR((AK9-(AK18+AK21+AK26))/AK41,0) -> 0 | AM45: =IFERROR(AK45/V45-1,0) -> 0
E47: ( menos ) | I47: GASTO ESTACIONES
A49: E - GASTOS DE OPERACIÓN | B49: estaciones | I49: E - GASTOS DE OPERACIÓN | V49: =SUM(V50:V87) -> 0 | W49: =V49/V$6 -> #DIV/0! | Y49: =SUM(Y50:Y87) -> 0 | Z49: =SUM(Z50:Z87) -> 0 | AA49: =SUM(AA50:AA87) -> 0 | AB49: =SUM(AB50:AB87) -> 0 | AC49: =SUM(AC50:AC87) -> 0 | AD49: =SUM(AD50:AD87) -> 0 | AE49: =SUM(AE50:AE87) -> 0 | AF49: =SUM(AF50:AF87) -> 0 | ... AK49: =SUM(AK50:AK87) -> 0 | AL49: =AK49/AK$6 -> #DIV/0! | AM49: =IFERROR(AK49/V49-1,0) -> 0
A50: E - GASTOS DE OPERACIÓN | B50: estaciones | C50: Servicios Administrativos | I50: Traslado de Valores | V50: =SUM(J50:U50) -> 0 | W50: =V50/V$6 -> #DIV/0! | Y50: 0 | Z50: 0 | AA50: 0 | AB50: 0 | AC50: 0 | AD50: 0 | AE50: 0 | AF50: 0 | AG50: 0 | AH50: 0 | AI50: 0 | AJ50: 0 | AK50: =SUM(Y50:AJ50) -> 0 | AL50: =AK50/AK$6 -> #DIV/0! | AM50: =IFERROR(AK50/V50-1,0) -> 0
A51: E - GASTOS DE OPERACIÓN | B51: estaciones | I51: Servicios Administrativos | V51: =SUM(J51:U51) -> 0 | W51: =V51/V$6 -> #DIV/0! | Y51: 0 | Z51: 0 | AA51: 0 | AB51: 0 | AC51: 0 | AD51: 0 | AE51: 0 | AF51: 0 | AG51: 0 | AH51: 0 | AI51: 0 | AJ51: 0 | AK51: =SUM(Y51:AJ51) -> 0 | AL51: =AK51/AK$6 -> #DIV/0! | AM51: =IFERROR(AK51/V51-1,0) -> 0
A52: E - GASTOS DE OPERACIÓN | B52: estaciones | I52: Eventos | V52: =SUM(J52:U52) -> 0 | W52: =V52/V$6 -> #DIV/0! | Y52: 0 | Z52: 0 | AA52: 0 | AB52: 0 | AC52: 0 | AD52: 0 | AE52: 0 | AF52: 0 | AG52: 0 | AH52: 0 | AI52: 0 | AJ52: 0 | AK52: =SUM(Y52:AJ52) -> 0 | AL52: =AK52/AK$6 -> #DIV/0! | AM52: =IFERROR(AK52/V52-1,0) -> 0
A53: E - GASTOS DE OPERACIÓN | B53: estaciones | I53: Otros Gastos | V53: =SUM(J53:U53) -> 0 | W53: =V53/V$6 -> #DIV/0! | Y53: 0 | Z53: 0 | AA53: 0 | AB53: 0 | AC53: 0 | AD53: 0 | AE53: 0 | AF53: 0 | AG53: 0 | AH53: 0 | AI53: 0 | AJ53: 0 | AK53: =SUM(Y53:AJ53) -> 0 | AL53: =AK53/AK$6 -> #DIV/0! | AM53: =IFERROR(AK53/V53-1,0) -> 0
A54: E - GASTOS DE OPERACIÓN | B54: estaciones | C54: Costo Marketing | I54: Otros impuestos y derechos | V54: =SUM(J54:U54) -> 0 | W54: =V54/V$6 -> #DIV/0! | Y54: 0 | Z54: 0 | AA54: 0 | AB54: 0 | AC54: 0 | AD54: 0 | AE54: 0 | AF54: 0 | AG54: 0 | AH54: 0 | AI54: 0 | AJ54: 0 | AK54: =SUM(Y54:AJ54) -> 0 | AL54: =AK54/AK$6 -> #DIV/0! | AM54: =IFERROR(AK54/V54-1,0) -> 0
A55: E - GASTOS DE OPERACIÓN | B55: estaciones | I55: Gas Natural | V55: =SUM(J55:U55) -> 0 | W55: =V55/V$6 -> #DIV/0! | Y55: 0 | Z55: 0 | AA55: 0 | AB55: 0 | AC55: 0 | AD55: 0 | AE55: 0 | AF55: 0 | AG55: 0 | AH55: 0 | AI55: 0 | AJ55: 0 | AK55: =SUM(Y55:AJ55) -> 0 | AL55: =AK55/AK$6 -> #DIV/0! | AM55: =IFERROR(AK55/V55-1,0) -> 0
A56: E - GASTOS DE OPERACIÓN | B56: estaciones | I56: Limpieza | V56: =SUM(J56:U56) -> 0 | W56: =V56/V$6 -> #DIV/0! | Y56: 0 | Z56: 0 | AA56: 0 | AB56: 0 | AC56: 0 | AD56: 0 | AE56: 0 | AF56: 0 | AG56: 0 | AH56: 0 | AI56: 0 | AJ56: 0 | AK56: =SUM(Y56:AJ56) -> 0 | AL56: =AK56/AK$6 -> #DIV/0! | AM56: =IFERROR(AK56/V56-1,0) -> 0
A57: E - GASTOS DE OPERACIÓN | B57: estaciones | I57: Propaganda y publicidad | V57: =SUM(J57:U57) -> 0 | W57: =V57/V$6 -> #DIV/0! | Y57: 0 | Z57: 0 | AA57: 0 | AB57: 0 | AC57: 0 | AD57: 0 | AE57: 0 | AF57: 0 | AG57: 0 | AH57: 0 | AI57: 0 | AJ57: 0 | AK57: =SUM(Y57:AJ57) -> 0 | AL57: =AK57/AK$6 -> #DIV/0! | AM57: =IFERROR(AK57/V57-1,0) -> 0
A58: E - GASTOS DE OPERACIÓN | B58: estaciones | I58: Contingencia Covid | V58: =SUM(J58:U58) -> 0 | W58: =V58/V$6 -> #DIV/0! | Y58: 0 | Z58: 0 | AA58: 0 | AB58: 0 | AC58: 0 | AD58: 0 | AE58: 0 | AF58: 0 | AG58: 0 | AH58: 0 | AI58: 0 | AJ58: 0 | AK58: =SUM(Y58:AJ58) -> 0 | AL58: =AK58/AK$6 -> #DIV/0! | AM58: =IFERROR(AK58/V58-1,0) -> 0
A59: E - GASTOS DE OPERACIÓN | B59: estaciones | I59: Gastos no deducibles (sin requisitos fiscales) | V59: =SUM(J59:U59) -> 0 | W59: =V59/V$6 -> #DIV/0! | Y59: 0 | Z59: 0 | AA59: 0 | AB59: 0 | AC59: 0 | AD59: 0 | AE59: 0 | AF59: 0 | AG59: 0 | AH59: 0 | AI59: 0 | AJ59: 0 | AK59: =SUM(Y59:AJ59) -> 0 | AL59: =AK59/AK$6 -> #DIV/0! | AM59: =IFERROR(AK59/V59-1,0) -> 0
A60: E - GASTOS DE OPERACIÓN | B60: estaciones | I60: Asesoría en sistemas | V60: =SUM(J60:U60) -> 0 | W60: =V60/V$6 -> #DIV/0! | Y60: 0 | Z60: 0 | AA60: 0 | AB60: 0 | AC60: 0 | AD60: 0 | AE60: 0 | AF60: 0 | AG60: 0 | AH60: 0 | AI60: 0 | AJ60: 0 | AK60: =SUM(Y60:AJ60) -> 0 | AL60: =AK60/AK$6 -> #DIV/0! | AM60: =IFERROR(AK60/V60-1,0) -> 0
A61: E - GASTOS DE OPERACIÓN | B61: estaciones | I61: Papelería y artículos de oficina | V61: =SUM(J61:U61) -> 0 | W61: =V61/V$6 -> #DIV/0! | Y61: 0 | Z61: 0 | AA61: 0 | AB61: 0 | AC61: 0 | AD61: 0 | AE61: 0 | AF61: 0 | AG61: 0 | AH61: 0 | AI61: 0 | AJ61: 0 | AK61: =SUM(Y61:AJ61) -> 0 | AL61: =AK61/AK$6 -> #DIV/0! | AM61: =IFERROR(AK61/V61-1,0) -> 0
A62: E - GASTOS DE OPERACIÓN | B62: estaciones | I62: Faltantes | V62: =SUM(J62:U62) -> 0 | W62: =V62/V$6 -> #DIV/0! | Y62: 0 | Z62: 0 | AA62: 0 | AB62: 0 | AC62: 0 | AD62: 0 | AE62: 0 | AF62: 0 | AG62: 0 | AH62: 0 | AI62: 0 | AJ62: 0 | AK62: =SUM(Y62:AJ62) -> 0 | AL62: =AK62/AK$6 -> #DIV/0! | AM62: =IFERROR(AK62/V62-1,0) -> 0
A63: E - GASTOS DE OPERACIÓN | B63: estaciones | I63: Licencias y Permisos | V63: =SUM(J63:U63) -> 0 | W63: =V63/V$6 -> #DIV/0! | Y63: 0 | Z63: 0 | AA63: 0 | AB63: 0 | AC63: 0 | AD63: 0 | AE63: 0 | AF63: 0 | AG63: 0 | AH63: 0 | AI63: 0 | AJ63: 0 | AK63: =SUM(Y63:AJ63) -> 0 | AL63: =AK63/AK$6 -> #DIV/0! | AM63: =IFERROR(AK63/V63-1,0) -> 0
A64: E - GASTOS DE OPERACIÓN | B64: estaciones | I64: Capacitación al personal | V64: =SUM(J64:U64) -> 0 | W64: =V64/V$6 -> #DIV/0! | Y64: 0 | Z64: 0 | AA64: 0 | AB64: 0 | AC64: 0 | AD64: 0 | AE64: 0 | AF64: 0 | AG64: 0 | AH64: 0 | AI64: 0 | AJ64: 0 | AK64: =SUM(Y64:AJ64) -> 0 | AL64: =AK64/AK$6 -> #DIV/0! | AM64: =IFERROR(AK64/V64-1,0) -> 0
A65: E - GASTOS DE OPERACIÓN | B65: estaciones | I65: Licencias, Software, Antivirus | V65: =SUM(J65:U65) -> 0 | W65: =V65/V$6 -> #DIV/0! | Y65: 0 | Z65: 0 | AA65: 0 | AB65: 0 | AC65: 0 | AD65: 0 | AE65: 0 | AF65: 0 | AG65: 0 | AH65: 0 | AI65: 0 | AJ65: 0 | AK65: =SUM(Y65:AJ65) -> 0 | AL65: =AK65/AK$6 -> #DIV/0! | AM65: =IFERROR(AK65/V65-1,0) -> 0
A66: E - GASTOS DE OPERACIÓN | B66: estaciones | I66: Fletes Combustible | V66: =SUM(J66:U66) -> 0 | W66: =V66/V$6 -> #DIV/0! | Y66: 0 | Z66: 0 | AA66: 0 | AB66: 0 | AC66: 0 | AD66: 0 | AE66: 0 | AF66: 0 | AG66: 0 | AH66: 0 | AI66: 0 | AJ66: 0 | AK66: =SUM(Y66:AJ66) -> 0 | AL66: =AK66/AK$6 -> #DIV/0! | AM66: =IFERROR(AK66/V66-1,0) -> 0
... A72: E - GASTOS DE OPERACIÓN | B72: estaciones | I72: Asistencia técnica | V72: =SUM(J72:U72) -> 0 | W72: =V72/V$6 -> #DIV/0! | Y72: 0 | Z72: 0 | AA72: 0 | AB72: 0 | AC72: 0 | AD72: 0 | AE72: 0 | AF72: 0 | AG72: 0 | AH72: 0 | AI72: 0 | AJ72: 0 | AK72: =SUM(Y72:AJ72) -> 0 | AL72: =AK72/AK$6 -> #DIV/0! | AM72: =IFERROR(AK72/V72-1,0) -> 0
I73: Combustibles Reembolsos
I74: Renta Equipo de Sistemas
I75: Timbrado Facturas
I76: Rentas No Deducibles
I77: Uniformes
I78: Contratacion Empleados
I79: Multas y Recargos
I80: Honorarios Administrativos P.F.
I81: Honorarios Administrativos P.M.
I82: Honorarios Legales P.F.
I83: Honorarios Legales P.M.
I84: Honorarios de Consultoria
... I87: Prediales
A88: C - NOMINA | B88: estaciones | I88: C - NOMINA | V88: =SUM(V89:V103) -> 0 | W88: =V88/V$6 -> #DIV/0! | Y88: =SUM(Y89:Y103) -> 0 | Z88: =SUM(Z89:Z103) -> 0 | AA88: =SUM(AA89:AA103) -> 0 | AB88: =SUM(AB89:AB103) -> 0 | AC88: =SUM(AC89:AC103) -> 0 | AD88: =SUM(AD89:AD103) -> 0 | AE88: =SUM(AE89:AE103) -> 0 | AF88: =SUM(AF89:AF103) -> 0 | ... AK88: =SUM(AK89:AK103) -> 0 | AL88: =AK88/AK$6 -> #DIV/0! | AM88: =IFERROR(AK88/V88-1,0) -> 0
A89: C - NOMINA | B89: estaciones | I89: Aguinaldo | V89: =SUM(J89:U89) -> 0 | W89: =V89/V$6 -> #DIV/0! | AK89: =SUM(Y89:AJ89) -> 0 | AL89: =AK89/AK$6 -> #DIV/0! | AM89: =IFERROR(AK89/V89-1,0) -> 0
A90: C - NOMINA | B90: estaciones | I90: Compensaciones | V90: =SUM(J90:U90) -> 0 | W90: =V90/V$6 -> #DIV/0! | AK90: =SUM(Y90:AJ90) -> 0 | AL90: =AK90/AK$6 -> #DIV/0! | AM90: =IFERROR(AK90/V90-1,0) -> 0
A91: C - NOMINA | B91: estaciones | I91: Días festivos | V91: =SUM(J91:U91) -> 0 | W91: =V91/V$6 -> #DIV/0! | AK91: =SUM(Y91:AJ91) -> 0 | AL91: =AK91/AK$6 -> #DIV/0! | AM91: =IFERROR(AK91/V91-1,0) -> 0
A92: C - NOMINA | B92: estaciones | I92: Fondo de ahorro | V92: =SUM(J92:U92) -> 0 | W92: =V92/V$6 -> #DIV/0! | AK92: =SUM(Y92:AJ92) -> 0 | AL92: =AK92/AK$6 -> #DIV/0! | AM92: =IFERROR(AK92/V92-1,0) -> 0
A93: C - NOMINA | B93: estaciones | I93: Indemnizaciones | V93: =SUM(J93:U93) -> 0 | W93: =V93/V$6 -> #DIV/0! | AK93: =SUM(Y93:AJ93) -> 0 | AL93: =AK93/AK$6 -> #DIV/0! | AM93: =IFERROR(AK93/V93-1,0) -> 0
A94: C - NOMINA | B94: estaciones | I94: Premios de asistencia | V94: =SUM(J94:U94) -> 0 | W94: =V94/V$6 -> #DIV/0! | AK94: =SUM(Y94:AJ94) -> 0 | AL94: =AK94/AK$6 -> #DIV/0! | AM94: =IFERROR(AK94/V94-1,0) -> 0
A95: C - NOMINA | B95: estaciones | I95: Premios de puntualidad | V95: =SUM(J95:U95) -> 0 | W95: =V95/V$6 -> #DIV/0! | AK95: =SUM(Y95:AJ95) -> 0 | AL95: =AK95/AK$6 -> #DIV/0! | AM95: =IFERROR(AK95/V95-1,0) -> 0
A96: C - NOMINA | B96: estaciones | I96: Previsión social | V96: =SUM(J96:U96) -> 0 | W96: =V96/V$6 -> #DIV/0! | AK96: =SUM(Y96:AJ96) -> 0 | AL96: =AK96/AK$6 -> #DIV/0! | AM96: =IFERROR(AK96/V96-1,0) -> 0
A97: C - NOMINA | B97: estaciones | I97: Prima dominical | V97: =SUM(J97:U97) -> 0 | W97: =V97/V$6 -> #DIV/0! | AK97: =SUM(Y97:AJ97) -> 0 | AL97: =AK97/AK$6 -> #DIV/0! | AM97: =IFERROR(AK97/V97-1,0) -> 0
A98: C - NOMINA | B98: estaciones | I98: Prima vacacional | V98: =SUM(J98:U98) -> 0 | W98: =V98/V$6 -> #DIV/0! | AK98: =SUM(Y98:AJ98) -> 0 | AL98: =AK98/AK$6 -> #DIV/0! | AM98: =IFERROR(AK98/V98-1,0) -> 0
A99: C - NOMINA | B99: estaciones | I99: Primas de antigüedad | V99: =SUM(J99:U99) -> 0 | W99: =V99/V$6 -> #DIV/0! | AK99: =SUM(Y99:AJ99) -> 0 | AL99: =AK99/AK$6 -> #DIV/0! | AM99: =IFERROR(AK99/V99-1,0) -> 0
A100: C - NOMINA | B100: estaciones | I100: PTU | V100: =SUM(J100:U100) -> 0 | W100: =V100/V$6 -> #DIV/0! | AK100: =SUM(Y100:AJ100) -> 0 | AL100: =AK100/AK$6 -> #DIV/0! | AM100: =IFERROR(AK100/V100-1,0) -> 0
... A103: C - NOMINA | B103: estaciones | I103: Vacaciones | V103: =SUM(J103:U103) -> 0 | W103: =V103/V$6 -> #DIV/0! | AK103: =SUM(Y103:AJ103) -> 0 | AL103: =AK103/AK$6 -> #DIV/0! | AM103: =IFERROR(AK103/V103-1,0) -> 0
A104: D - COSTO SOCIAL | B104: estaciones | I104: D - COSTO SOCIAL | V104: =SUM(V105:V108) -> 0 | W104: =V104/V$6 -> #DIV/0! | Y104: =SUM(Y105:Y108) -> 0 | Z104: =SUM(Z105:Z108) -> 0 | AA104: =SUM(AA105:AA108) -> 0 | AB104: =SUM(AB105:AB108) -> 0 | AC104: =SUM(AC105:AC108) -> 0 | AD104: =SUM(AD105:AD108) -> 0 | AE104: =SUM(AE105:AE108) -> 0 | AF104: =SUM(AF105:AF108) -> 0 | ... AK104: =SUM(AK105:AK108) -> 0 | AL104: =AK104/AK$6 -> #DIV/0! | AM104: =IFERROR(AK104/V104-1,0) -> 0
A105: D - COSTO SOCIAL | B105: estaciones | I105: Aportaciones al infonavit | V105: =SUM(J105:U105) -> 0 | W105: =V105/V$6 -> #DIV/0! | AK105: =SUM(Y105:AJ105) -> 0 | AL105: =AK105/AK$6 -> #DIV/0! | AM105: =IFERROR(AK105/V105-1,0) -> 0
A106: D - COSTO SOCIAL | B106: estaciones | I106: Aportaciones al SAR | V106: =SUM(J106:U106) -> 0 | W106: =V106/V$6 -> #DIV/0! | AK106: =SUM(Y106:AJ106) -> 0 | AL106: =AK106/AK$6 -> #DIV/0! | AM106: =IFERROR(AK106/V106-1,0) -> 0
A107: D - COSTO SOCIAL | B107: estaciones | I107: Cuotas al IMSS | V107: =SUM(J107:U107) -> 0 | W107: =V107/V$6 -> #DIV/0! | AK107: =SUM(Y107:AJ107) -> 0 | AL107: =AK107/AK$6 -> #DIV/0! | AM107: =IFERROR(AK107/V107-1,0) -> 0
A108: D - COSTO SOCIAL | B108: estaciones | I108: Impuesto Estatal | V108: =SUM(J108:U108) -> 0 | W108: =V108/V$6 -> #DIV/0! | AK108: =SUM(Y108:AJ108) -> 0 | AL108: =AK108/AK$6 -> #DIV/0! | AM108: =IFERROR(AK108/V108-1,0) -> 0
A109: F - MANTENIMIENTO | B109: estaciones | C109: Mantenimiento de Imagen | I109: F - MANTENIMIENTO | V109: =SUM(V110:V112) -> 0 | W109: =V109/V$6 -> #DIV/0! | Y109: =SUM(Y110:Y112) -> 0 | Z109: =SUM(Z110:Z112) -> 0 | AA109: =SUM(AA110:AA112) -> 0 | AB109: =SUM(AB110:AB112) -> 0 | AC109: =SUM(AC110:AC112) -> 0 | AD109: =SUM(AD110:AD112) -> 0 | AE109: =SUM(AE110:AE112) -> 0 | AF109: =SUM(AF110:AF112) -> 0 | ... AK109: =SUM(AK110:AK112) -> 0 | AL109: =AK109/AK$6 -> #DIV/0! | AM109: =IFERROR(AK109/V109-1,0) -> 0
A110: F - MANTENIMIENTO | B110: estaciones | I110: Mantenimiento de Equipo de Computo | V110: =SUM(J110:U110) -> 0 | W110: =V110/V$6 -> #DIV/0! | Y110: 0 | Z110: 0 | AA110: 0 | AB110: 0 | AC110: 0 | AD110: 0 | AE110: 0 | AF110: 0 | AG110: 0 | AH110: 0 | AI110: 0 | AJ110: 0 | AK110: =SUM(Y110:AJ110) -> 0 | AL110: =AK110/AK$6 -> #DIV/0! | AM110: =IFERROR(AK110/V110-1,0) -> 0
A111: F - MANTENIMIENTO | B111: estaciones | I111: Mantenimiento de Vehiculos | V111: =SUM(J111:U111) -> 0 | W111: =V111/V$6 -> #DIV/0! | Y111: 0 | Z111: 0 | AA111: 0 | AB111: 0 | AC111: 0 | AD111: 0 | AE111: 0 | AF111: 0 | AG111: 0 | AH111: 0 | AI111: 0 | AJ111: 0 | AK111: =SUM(Y111:AJ111) -> 0 | AL111: =AK111/AK$6 -> #DIV/0! | AM111: =IFERROR(AK111/V111-1,0) -> 0
A112: F - MANTENIMIENTO | B112: estaciones | I112: Seguridad e Higiene Ambiental | V112: =SUM(J112:U112) -> 0 | W112: =V112/V$6 -> #DIV/0! | Y112: 0 | Z112: 0 | AA112: 0 | AB112: 0 | AC112: 0 | AD112: 0 | AE112: 0 | AF112: 0 | AG112: 0 | AH112: 0 | AI112: 0 | AJ112: 0 | AK112: =SUM(Y112:AJ112) -> 0 | AL112: =AK112/AK$6 -> #DIV/0! | AM112: =IFERROR(AK112/V112-1,0) -> 0
...

Sheet Z

Sheet TOTAL ESTACIONES
I1: 1147 | J1: 2 | K1: 3 | L1: 4 | M1: 5 | N1: 6 | O1: 7 | Y1: 2 | Z1: =+Y1+1 -> 3 | AA1: =+Z1+1 -> 4 | AB1: =+AA1+1 -> 5 | AC1: =+AB1+1 -> 6 | AD1: =+AC1+1 -> 7 | AE1: =+AD1+1 -> 8 | AF1: =+AE1+1 -> 9 | AG1: =+AF1+1 -> 10 | ... AK1: =+AJ1+1 -> 14 | AM1: 17
J2: 2025 | V2: TOTAL ANUAL | Y2: 2026 | AK2: TOTAL ANUAL
J3: ENE | K3: FEB | L3: MAR | M3: ABR | N3: MAY | O3: JUN | P3: JUL | Q3: AGO | R3: SEP | S3: OCT | T3: NOV | U3: DIC | V3: 2025 | W3: % Part | Y3: ENE | Z3: FEB | AA3: MAR | AB3: ABR | AC3: MAY | AD3: JUN | AE3: JUL | AF3: AGO | AG3: SEP | AH3: OCT | AI3: NOV | AJ3: DIC | AK3: 2026 | AL3: % Part | AM3: Var vs AA%
I4: INGRESOS
A6: A - INGRESOS | E6: ( mas ) | I6: A - INGRESOS | J6: =SUM(J7:J12) -> 17192824 | K6: =SUM(K7:K12) -> 15590830 | L6: =SUM(L7:L12) -> 18254554 | M6: =SUM(M7:M12) -> 17513698 | N6: =SUM(N7:N12) -> 19514034 | O6: =SUM(O7:O12) -> 18936949 | P6: =SUM(P7:P12) -> 18138616 | Q6: =SUM(Q7:Q12) -> 18621506 | ... V6: =SUM(V7:V12) -> 223872939 | W6: =V6/V$6 -> 1 | Y6: =SUM(Y7:Y12) -> 18780611 | Z6: =SUM(Z7:Z12) -> 17035192 | AA6: =SUM(AA7:AA12) -> 20269984 | AB6: =SUM(AB7:AB12) -> 19487182 | AC6: =SUM(AC7:AC12) -> 21864209 | AD6: =SUM(AD7:AD12) -> 21197316 | AE6: =SUM(AE7:AE12) -> 20370243 | AF6: =SUM(AF7:AF12) -> 20697143 | ... AK6: =SUM(AK7:AK12) -> 2.5074065e+08 | AL6: =AK6/AK$6 -> 1 | AM6: =IFERROR(AK6/V6-1,0) -> 0.12001323
A7: A - INGRESOS | B7: estaciones | C7: INGRESOS MAGNA | D7: INGRESOS FORANEOS MAGNA | I7: MAXIMA | J7: =SUM(A:B!J7) -> 13803132 | K7: =SUM(A:B!K7) -> 12317959 | L7: =SUM(A:B!L7) -> 14526332 | M7: =SUM(A:B!M7) -> 13887455 | N7: =SUM(A:B!N7) -> 15477447 | O7: =SUM(A:B!O7) -> 15236060 | P7: =SUM(A:B!P7) -> 14546459 | Q7: =SUM(A:B!Q7) -> 14677535 | ... U7: =SUM(A:B!U7) -> 15732735 | V7: =SUM(J7:U7) -> 1.7740332e+08 | W7: =V7/V$6 -> 0.79242861 | Y7: =SUM(A:B!Y7) -> 15202952 | Z7: =SUM(A:B!Z7) -> 13599664 | AA7: =SUM(A:B!AA7) -> 16337794 | AB7: =SUM(A:B!AB7) -> 15675014 | AC7: =SUM(A:B!AC7) -> 17580791 | AD7: =SUM(A:B!AD7) -> 17284829 | AE7: =SUM(A:B!AE7) -> 16564120 | AF7: =SUM(A:B!AF7) -> 16552821 | ... AJ7: =SUM(A:B!AJ7) -> 18147057 | AK7: =SUM(Y7:AJ7) -> 2.01564e+08 | AL7: =AK7/AK$6 -> 0.80387444 | AM7: =IFERROR(AK7/V7-1,0) -> 0.13619069
A8: A - INGRESOS | B8: estaciones | C8: INGRESOS PREMIUM | D8: INGRESOS FORANEOS PREMIUM | I8: SUPER | J8: =SUM(A:B!J8) -> 3260550 | K8: =SUM(A:B!K8) -> 3155615 | L8: =SUM(A:B!L8) -> 3577713 | M8: =SUM(A:B!M8) -> 3447065 | N8: =SUM(A:B!N8) -> 3825441 | O8: =SUM(A:B!O8) -> 3528128 | P8: =SUM(A:B!P8) -> 3411360 | Q8: =SUM(A:B!Q8) -> 3791076 | ... U8: =SUM(A:B!U8) -> 4133088.9 | V8: =SUM(J8:U8) -> 44529304 | W8: =V8/V$6 -> 0.19890436 | Y8: =SUM(A:B!Y8) -> 3435117.4 | Z8: =SUM(A:B!Z8) -> 3306549.5 | AA8: =SUM(A:B!AA8) -> 3769065.3 | AB8: =SUM(A:B!AB8) -> 3620940.7 | AC8: =SUM(A:B!AC8) -> 4053744.8 | AD8: =SUM(A:B!AD8) -> 3728103.4 | AE8: =SUM(A:B!AE8) -> 3609622 | AF8: =SUM(A:B!AF8) -> 3976339.4 | ... AJ8: =SUM(A:B!AJ8) -> 4355630.6 | AK8: =SUM(Y8:AJ8) -> 47141259 | AL8: =AK8/AK$6 -> 0.18800804 | AM8: =IFERROR(AK8/V8-1,0) -> 0.05865701
A9: A - INGRESOS | B9: estaciones | C9: INGRESOS DIESEL | D9: INGRESOS FORANEOS DIESEL | I9: DIESEL | J9: =SUM(A:B!J9) -> 119320 | K9: =SUM(A:B!K9) -> 108214 | L9: =SUM(A:B!L9) -> 130827 | M9: =SUM(A:B!M9) -> 157657 | N9: =SUM(A:B!N9) -> 189122 | O9: =SUM(A:B!O9) -> 151966 | P9: =SUM(A:B!P9) -> 162434 | Q9: =SUM(A:B!Q9) -> 130655 | ... U9: =SUM(A:B!U9) -> 139359.89 | V9: =SUM(J9:U9) -> 1707634.6 | W9: =V9/V$6 -> 0.0076276953 | Y9: =SUM(A:B!Y9) -> 133961.55 | Z9: =SUM(A:B!Z9) -> 121418.7 | AA9: =SUM(A:B!AA9) -> 147824.7 | AB9: =SUM(A:B!AB9) -> 176406.75 | AC9: =SUM(A:B!AC9) -> 212152.65 | AD9: =SUM(A:B!AD9) -> 169683 | AE9: =SUM(A:B!AE9) -> 180661.05 | AF9: =SUM(A:B!AF9) -> 151003.2 | ... AJ9: =SUM(A:B!AJ9) -> 132005.55 | AK9: =SUM(Y9:AJ9) -> 1842552 | AL9: =AK9/AK$6 -> 0.0073484374 | AM9: =IFERROR(AK9/V9-1,0) -> 0.079008383
I10: INGRESOS ACEITES Y LUBRICANTES | J10: =SUM(A:B!J10) -> 9822 | K10: =SUM(A:B!K10) -> 9042 | L10: =SUM(A:B!L10) -> 19682 | M10: =SUM(A:B!M10) -> 21521 | N10: =SUM(A:B!N10) -> 22024 | O10: =SUM(A:B!O10) -> 20795 | P10: =SUM(A:B!P10) -> 18363 | Q10: =SUM(A:B!Q10) -> 22240 | ... U10: =SUM(A:B!U10) -> 22297.778 | V10: =SUM(J10:U10) -> 232680.11 | W10: =V10/V$6 -> 0.00103934 | Y10: =SUM(A:B!Y10) -> 8580 | Z10: =SUM(A:B!Z10) -> 7560 | AA10: =SUM(A:B!AA10) -> 15300 | AB10: =SUM(A:B!AB10) -> 14820 | AC10: =SUM(A:B!AC10) -> 17520 | AD10: =SUM(A:B!AD10) -> 14700 | AE10: =SUM(A:B!AE10) -> 15840 | AF10: =SUM(A:B!AF10) -> 16980 | ... AJ10: =SUM(A:B!AJ10) -> 27480 | AK10: =SUM(Y10:AJ10) -> 192840 | AL10: =AK10/AK$6 -> 0.00076908151 | AM10: =IFERROR(AK10/V10-1,0) -> -0.17122268
I11: SOBRANTE COMBUSTIBLE | J11: =SUM(A:B!J11) -> 0 | K11: =SUM(A:B!K11) -> 0 | L11: =SUM(A:B!L11) -> 0 | M11: =SUM(A:B!M11) -> 0 | N11: =SUM(A:B!N11) -> 0 | O11: =SUM(A:B!O11) -> 0 | P11: =SUM(A:B!P11) -> 0 | Q11: =SUM(A:B!Q11) -> 0 | ... U11: =SUM(A:B!U11) -> 0 | V11: =SUM(J11:U11) -> 0 | W11: =V11/V$6 -> 0 | Y11: =SUM(A:B!Y11) -> 0 | Z11: =SUM(A:B!Z11) -> 0 | AA11: =SUM(A:B!AA11) -> 0 | AB11: =SUM(A:B!AB11) -> 0 | AC11: =SUM(A:B!AC11) -> 0 | AD11: =SUM(A:B!AD11) -> 0 | AE11: =SUM(A:B!AE11) -> 0 | AF11: =SUM(A:B!AF11) -> 0 | ... AJ11: =SUM(A:B!AJ11) -> 0 | AK11: =SUM(Y11:AJ11) -> 0 | AL11: =AK11/AK$6 -> 0 | AM11: =IFERROR(AK11/V11-1,0) -> 0
J12: =SUM(A:B!J12) -> 0 | K12: =SUM(A:B!K12) -> 0 | L12: =SUM(A:B!L12) -> 0 | M12: =SUM(A:B!M12) -> 0 | N12: =SUM(A:B!N12) -> 0 | O12: =SUM(A:B!O12) -> 0 | P12: =SUM(A:B!P12) -> 0 | Q12: =SUM(A:B!Q12) -> 0 | ... U12: =SUM(A:B!U12) -> 0 | V12: =SUM(J12:U12) -> 0 | W12: =V12/V$6 -> 0 | Y12: =SUM(A:B!Y12) -> 0 | Z12: =SUM(A:B!Z12) -> 0 | AA12: =SUM(A:B!AA12) -> 0 | AB12: =SUM(A:B!AB12) -> 0 | AC12: =SUM(A:B!AC12) -> 0 | AD12: =SUM(A:B!AD12) -> 0 | AE12: =SUM(A:B!AE12) -> 0 | AF12: =SUM(A:B!AF12) -> 0 | ... AJ12: =SUM(A:B!AJ12) -> 0 | AK12: =SUM(Y12:AJ12) -> 0 | AL12: =AK12/AK$6 -> 0 | AM12: =IFERROR(AK12/V12-1,0) -> 0
A13: B - COSTO DE VENTA | E13: ( menos ) | I13: B - COSTO DE VENTA | J13: =SUM(J14:J33) -> 15902755 | K13: =SUM(K14:K33) -> 14219176 | L13: =SUM(L14:L33) -> 16515274 | M13: =SUM(M14:M33) -> 15682912 | N13: =SUM(N14:N33) -> 17504319 | O13: =SUM(O14:O33) -> 16938367 | P13: =SUM(P14:P33) -> 16483004 | Q13: =SUM(Q14:Q33) -> 16897261 | ... V13: =SUM(V14:V33) -> 2.0267433e+08 | W13: =V13/V$6 -> 0.90530964 | Y13: =SUM(Y14:Y30) -> 17094951 | Z13: =SUM(Z14:Z30) -> 15592766 | AA13: =SUM(AA14:AA30) -> 18304073 | AB13: =SUM(AB14:AB30) -> 17779061 | AC13: =SUM(AC14:AC30) -> 19790063 | AD13: =SUM(AD14:AD30) -> 19328858 | AE13: =SUM(AE14:AE30) -> 18583117 | AF13: =SUM(AF14:AF30) -> 18827660 | ... AJ13: =SUM(AJ14:AJ30) -> 20641001 | AK13: =SUM(Y13:AJ13) -> 2.2807815e+08 | AL13: =AK13/AK$6 -> 0.90961774 | AM13: =IFERROR(AK13/V13-1,0) -> 0.12534304
A14: B - COSTO DE VENTA | C14: COSTO MAGNA | D14: COSTO FORANEO MAGNA | I14: GASOLINA REGULAR | J14: =SUM(A:B!J14) -> 12973548 | K14: =SUM(A:B!K14) -> 11404250 | L14: =SUM(A:B!L14) -> 13331662 | M14: =SUM(A:B!M14) -> 12710487 | N14: =SUM(A:B!N14) -> 14240584 | O14: =SUM(A:B!O14) -> 14028976 | P14: =SUM(A:B!P14) -> 13394436 | Q14: =SUM(A:B!Q14) -> 13534987 | ... U14: =SUM(A:B!U14) -> 14490738 | V14: =SUM(J14:U14) -> 1.6358188e+08 | W14: =V14/V$6 -> 0.73069074 | Y14: =SUM(A:B!Y14) -> 13883313 | Z14: =SUM(A:B!Z14) -> 12500474 | AA14: =SUM(A:B!AA14) -> 14787073 | AB14: =SUM(A:B!AB14) -> 14347590 | AC14: =SUM(A:B!AC14) -> 15960345 | AD14: =SUM(A:B!AD14) -> 15798489 | AE14: =SUM(A:B!AE14) -> 15161171 | AF14: =SUM(A:B!AF14) -> 15119204 | ... AK14: =SUM(A:B!AK14) -> 1.8394188e+08 | AL14: =AK14/AK$6 -> 0.73359417 | AM14: =IFERROR(AK14/V14-1,0) -> 0.12446366
A15: B - COSTO DE VENTA | C15: COSTO PREMIUM | D15: COSTO FORANEO PREMIUM | I15: GASOLINA PREMIUM | J15: =SUM(A:B!J15) -> 2994699 | K15: =SUM(A:B!K15) -> 2908739 | L15: =SUM(A:B!L15) -> 3286842 | M15: =SUM(A:B!M15) -> 3157931 | N15: =SUM(A:B!N15) -> 3455437 | O15: =SUM(A:B!O15) -> 3184771 | P15: =SUM(A:B!P15) -> 3126152 | Q15: =SUM(A:B!Q15) -> 3519227 | ... U15: =SUM(A:B!U15) -> 3831077.2 | V15: =SUM(J15:U15) -> 40958107 | W15: =V15/V$6 -> 0.18295247 | Y15: =SUM(A:B!Y15) -> 3080784 | Z15: =SUM(A:B!Z15) -> 2973366.4 | AA15: =SUM(A:B!AA15) -> 3369026.9 | AB15: =SUM(A:B!AB15) -> 3257493.6 | AC15: =SUM(A:B!AC15) -> 3620816.1 | AD15: =SUM(A:B!AD15) -> 3359822.1 | AE15: =SUM(A:B!AE15) -> 3242504 | AF15: =SUM(A:B!AF15) -> 3553874.7 | ... AK15: =SUM(A:B!AK15) -> 42276501 | AL15: =AK15/AK$6 -> 0.16860649 | AM15: =IFERROR(AK15/V15-1,0) -> 0.032188835
A16: B - COSTO DE VENTA | C16: COSTO DIESEL | D16: COSTO FORANEO DIESEL | I16: DIESEL | J16: =SUM(A:B!J16) -> 111034 | K16: =SUM(A:B!K16) -> 101129 | L16: =SUM(A:B!L16) -> 122898 | M16: =SUM(A:B!M16) -> 146759 | N16: =SUM(A:B!N16) -> 171893 | O16: =SUM(A:B!O16) -> 138211 | P16: =SUM(A:B!P16) -> 152522 | Q16: =SUM(A:B!Q16) -> 127651 | ... U16: =SUM(A:B!U16) -> 130644.33 | V16: =SUM(J16:U16) -> 1594674.3 | W16: =V16/V$6 -> 0.0071231223 | Y16: =SUM(A:B!Y16) -> 123989.77 | Z16: =SUM(A:B!Z16) -> 112877.18 | AA16: =SUM(A:B!AA16) -> 135732.7 | AB16: =SUM(A:B!AB16) -> 162121.05 | AC16: =SUM(A:B!AC16) -> 194885.42 | AD16: =SUM(A:B!AD16) -> 158787.2 | AE16: =SUM(A:B!AE16) -> 166769.73 | AF16: =SUM(A:B!AF16) -> 140998.08 | ... AK16: =SUM(A:B!AK16) -> 1705493.2 | AL16: =AK16/AK$6 -> 0.0068018216 | AM16: =IFERROR(AK16/V16-1,0) -> 0.069493096
A17: B - COSTO DE VENTA | C17: Merma Magna | I17: MERMA GASOLINA REGULAR | J17: =SUM(A:B!J17) -> 0 | K17: =SUM(A:B!K17) -> 451 | L17: =SUM(A:B!L17) -> 0 | M17: =SUM(A:B!M17) -> 863 | N17: =SUM(A:B!N17) -> 0 | O17: =SUM(A:B!O17) -> 0 | P17: =SUM(A:B!P17) -> 1786 | Q17: =SUM(A:B!Q17) -> 0 | ... U17: =SUM(A:B!U17) -> 136.88889 | V17: =SUM(J17:U17) -> 3647.5556 | W17: =V17/V$6 -> 1.6292972e-05 | Y17: =SUM(A:B!Y17) -> 0 | Z17: =SUM(A:B!Z17) -> 0 | AA17: =SUM(A:B!AA17) -> 0 | AB17: =SUM(A:B!AB17) -> 0 | AC17: =SUM(A:B!AC17) -> 0 | AD17: =SUM(A:B!AD17) -> 0 | AE17: =SUM(A:B!AE17) -> 0 | AF17: =SUM(A:B!AF17) -> 0 | ... AK17: =SUM(A:B!AK17) -> 0 | AL17: =AK17/AK$6 -> 0 | AM17: =IFERROR(AK17/V17-1,0) -> -1
A18: B - COSTO DE VENTA | C18: Merma Premium | I18: MERMA GASOLINA PREMIUM | J18: =SUM(A:B!J18) -> 10118 | K18: =SUM(A:B!K18) -> 11513 | L18: =SUM(A:B!L18) -> 5892 | M18: =SUM(A:B!M18) -> 235 | N18: =SUM(A:B!N18) -> 5571 | O18: =SUM(A:B!O18) -> 4098 | P18: =SUM(A:B!P18) -> 6579 | Q18: =SUM(A:B!Q18) -> 0 | ... U18: =SUM(A:B!U18) -> 6448.4444 | V18: =SUM(J18:U18) -> 69799.778 | W18: =V18/V$6 -> 0.00031178301 | Y18: =SUM(A:B!Y18) -> 0 | Z18: =SUM(A:B!Z18) -> 0 | AA18: =SUM(A:B!AA18) -> 0 | AB18: =SUM(A:B!AB18) -> 0 | AC18: =SUM(A:B!AC18) -> 0 | AD18: =SUM(A:B!AD18) -> 0 | AE18: =SUM(A:B!AE18) -> 0 | AF18: =SUM(A:B!AF18) -> 0 | ... AK18: =SUM(A:B!AK18) -> 0 | AL18: =AK18/AK$6 -> 0 | AM18: =IFERROR(AK18/V18-1,0) -> -1
A19: B - COSTO DE VENTA | C19: Merma Diesel | I19: MERMA DIESEL | J19: =SUM(A:B!J19) -> -2264 | K19: =SUM(A:B!K19) -> 0 | L19: =SUM(A:B!L19) -> 203 | M19: =SUM(A:B!M19) -> 0 | N19: =SUM(A:B!N19) -> 0 | O19: =SUM(A:B!O19) -> 1796 | P19: =SUM(A:B!P19) -> 0 | Q19: =SUM(A:B!Q19) -> 0 | ... U19: =SUM(A:B!U19) -> 2120.8889 | V19: =SUM(J19:U19) -> 8218.5556 | W19: =V19/V$6 -> 3.6710804e-05 | Y19: =SUM(A:B!Y19) -> 0 | Z19: =SUM(A:B!Z19) -> 0 | AA19: =SUM(A:B!AA19) -> 0 | AB19: =SUM(A:B!AB19) -> 0 | AC19: =SUM(A:B!AC19) -> 0 | AD19: =SUM(A:B!AD19) -> 0 | AE19: =SUM(A:B!AE19) -> 0 | AF19: =SUM(A:B!AF19) -> 0 | ... AK19: =SUM(A:B!AK19) -> 0 | AL19: =AK19/AK$6 -> 0 | AM19: =IFERROR(AK19/V19-1,0) -> -1
I20: SOBRANTE MAGNA | J20: =SUM(A:B!J20) -> -1655 | K20: =SUM(A:B!K20) -> -16260 | L20: =SUM(A:B!L20) -> -47534 | M20: =SUM(A:B!M20) -> -80019 | N20: =SUM(A:B!N20) -> -101412 | O20: =SUM(A:B!O20) -> -102362 | P20: =SUM(A:B!P20) -> -41438 | Q20: =SUM(A:B!Q20) -> -73785 | ... U20: =SUM(A:B!U20) -> -75022.778 | V20: =SUM(J20:U20) -> -764556.11 | W20: =V20/V$6 -> -0.0034151341 | Y20: =SUM(A:B!Y20) -> 0 | Z20: =SUM(A:B!Z20) -> 0 | AA20: =SUM(A:B!AA20) -> 0 | AB20: =SUM(A:B!AB20) -> 0 | AC20: =SUM(A:B!AC20) -> 0 | AD20: =SUM(A:B!AD20) -> 0 | AE20: =SUM(A:B!AE20) -> 0 | AF20: =SUM(A:B!AF20) -> 0 | ... AK20: =SUM(A:B!AK20) -> 0 | AL20: =AK20/AK$6 -> 0 | AM20: =IFERROR(AK20/V20-1,0) -> -1
I21: SOBRANTE PREMIUM | J21: =SUM(A:B!J21) -> 15107 | K21: =SUM(A:B!K21) -> 4291 | L21: =SUM(A:B!L21) -> -4238 | M21: =SUM(A:B!M21) -> -6859 | N21: =SUM(A:B!N21) -> -21701 | O21: =SUM(A:B!O21) -> -91077 | P21: =SUM(A:B!P21) -> 77691 | Q21: =SUM(A:B!Q21) -> -5176 | ... U21: =SUM(A:B!U21) -> -13801.778 | V21: =SUM(J21:U21) -> -87169.111 | W21: =V21/V$6 -> -0.00038936868 | Y21: =SUM(A:B!Y21) -> 0 | Z21: =SUM(A:B!Z21) -> 0 | AA21: =SUM(A:B!AA21) -> 0 | AB21: =SUM(A:B!AB21) -> 0 | AC21: =SUM(A:B!AC21) -> 0 | AD21: =SUM(A:B!AD21) -> 0 | AE21: =SUM(A:B!AE21) -> 0 | AF21: =SUM(A:B!AF21) -> 0 | ... AK21: =SUM(A:B!AK21) -> 0 | AL21: =AK21/AK$6 -> 0 | AM21: =IFERROR(AK21/V21-1,0) -> -1
I22: SOBRANTE DIESEL | J22: =SUM(A:B!J22) -> 0 | K22: =SUM(A:B!K22) -> -1925 | L22: =SUM(A:B!L22) -> -2961 | M22: =SUM(A:B!M22) -> -232 | N22: =SUM(A:B!N22) -> -4780 | O22: =SUM(A:B!O22) -> 0 | P22: =SUM(A:B!P22) -> -2453 | Q22: =SUM(A:B!Q22) -> -1311 | ... U22: =SUM(A:B!U22) -> -2245.2222 | V22: =SUM(J22:U22) -> -22642.889 | W22: =V22/V$6 -> -0.0001011417 | Y22: =SUM(A:B!Y22) -> 0 | Z22: =SUM(A:B!Z22) -> 0 | AA22: =SUM(A:B!AA22) -> 0 | AB22: =SUM(A:B!AB22) -> 0 | AC22: =SUM(A:B!AC22) -> 0 | AD22: =SUM(A:B!AD22) -> 0 | AE22: =SUM(A:B!AE22) -> 0 | AF22: =SUM(A:B!AF22) -> 0 | ... AK22: =SUM(A:B!AK22) -> 0 | AL22: =AK22/AK$6 -> 0 | AM22: =IFERROR(AK22/V22-1,0) -> -1
A23: B - COSTO DE VENTA | C23: ADITIVO PARA GASOLINA TMAXIMA (REGULAR) | D23: ADITIVO PARA GASOLINA TMAXIMA( REGULAR) | I23: ADITIVO TOTAL POWER GASOLINA REG | J23: =SUM(A:B!J23) -> 0 | K23: =SUM(A:B!K23) -> 0 | L23: =SUM(A:B!L23) -> 26670 | M23: =SUM(A:B!M23) -> -26670 | N23: =SUM(A:B!N23) -> 0 | O23: =SUM(A:B!O23) -> 0 | P23: =SUM(A:B!P23) -> 0 | Q23: =SUM(A:B!Q23) -> 0 | ... U23: =SUM(A:B!U23) -> 0 | V23: =SUM(J23:U23) -> 0 | W23: =V23/V$6 -> 0 | Y23: =SUM(A:B!Y23) -> 0 | Z23: =SUM(A:B!Z23) -> 0 | AA23: =SUM(A:B!AA23) -> 0 | AB23: =SUM(A:B!AB23) -> 0 | AC23: =SUM(A:B!AC23) -> 0 | AD23: =SUM(A:B!AD23) -> 0 | AE23: =SUM(A:B!AE23) -> 0 | AF23: =SUM(A:B!AF23) -> 0 | ... AK23: =SUM(A:B!AK23) -> 0 | AL23: =AK23/AK$6 -> 0 | AM23: =IFERROR(AK23/V23-1,0) -> 0
A24: B - COSTO DE VENTA | C24: ADITIVO PARA GASOLINA TSUPER (PREMIUM) | I24: ADITIVO TOTAL POWER GASOLINA PREM | J24: =SUM(A:B!J24) -> 0 | K24: =SUM(A:B!K24) -> 0 | L24: =SUM(A:B!L24) -> 6840 | M24: =SUM(A:B!M24) -> -6840 | N24: =SUM(A:B!N24) -> 0 | O24: =SUM(A:B!O24) -> 0 | P24: =SUM(A:B!P24) -> 0 | Q24: =SUM(A:B!Q24) -> 0 | ... U24: =SUM(A:B!U24) -> 0 | V24: =SUM(J24:U24) -> 0 | W24: =V24/V$6 -> 0 | Y24: =SUM(A:B!Y24) -> 0 | Z24: =SUM(A:B!Z24) -> 0 | AA24: =SUM(A:B!AA24) -> 0 | AB24: =SUM(A:B!AB24) -> 0 | AC24: =SUM(A:B!AC24) -> 0 | AD24: =SUM(A:B!AD24) -> 0 | AE24: =SUM(A:B!AE24) -> 0 | AF24: =SUM(A:B!AF24) -> 0 | ... AK24: =SUM(A:B!AK24) -> 0 | AL24: =AK24/AK$6 -> 0 | AM24: =IFERROR(AK24/V24-1,0) -> 0
A25: B - COSTO DE VENTA | C25: FLETE MAGNA | I25: FLETE GASOLINA REGULAR | J25: =SUM(A:B!J25) -> 0 | K25: =SUM(A:B!K25) -> 0 | L25: =SUM(A:B!L25) -> 0 | M25: =SUM(A:B!M25) -> 1204 | N25: =SUM(A:B!N25) -> 2511 | O25: =SUM(A:B!O25) -> 0 | P25: =SUM(A:B!P25) -> 2415 | Q25: =SUM(A:B!Q25) -> 0 | ... U25: =SUM(A:B!U25) -> 4740.8889 | V25: =SUM(J25:U25) -> 25093.556 | W25: =V25/V$6 -> 0.00011208838 | Y25: =SUM(A:B!Y25) -> 0 | Z25: =SUM(A:B!Z25) -> 0 | AA25: =SUM(A:B!AA25) -> 0 | AB25: =SUM(A:B!AB25) -> 0 | AC25: =SUM(A:B!AC25) -> 0 | AD25: =SUM(A:B!AD25) -> 0 | AE25: =SUM(A:B!AE25) -> 0 | AF25: =SUM(A:B!AF25) -> 0 | ... AK25: =SUM(A:B!AK25) -> 0 | AL25: =AK25/AK$6 -> 0 | AM25: =IFERROR(AK25/V25-1,0) -> -1
A26: B - COSTO DE VENTA | C26: FLETE PREMIUM | I26: FLETE GASOLINA PREMIUM | J26: =SUM(A:B!J26) -> 0 | K26: =SUM(A:B!K26) -> 0 | L26: =SUM(A:B!L26) -> 0 | M26: =SUM(A:B!M26) -> 0 | N26: =SUM(A:B!N26) -> 1209 | O26: =SUM(A:B!O26) -> 0 | P26: =SUM(A:B!P26) -> 0 | Q26: =SUM(A:B!Q26) -> 0 | ... U26: =SUM(A:B!U26) -> 2136 | V26: =SUM(J26:U26) -> 9753 | W26: =V26/V$6 -> 4.356489e-05 | Y26: =SUM(A:B!Y26) -> 0 | Z26: =SUM(A:B!Z26) -> 0 | AA26: =SUM(A:B!AA26) -> 0 | AB26: =SUM(A:B!AB26) -> 0 | AC26: =SUM(A:B!AC26) -> 0 | AD26: =SUM(A:B!AD26) -> 0 | AE26: =SUM(A:B!AE26) -> 0 | AF26: =SUM(A:B!AF26) -> 0 | ... AK26: =SUM(A:B!AK26) -> 0 | AL26: =AK26/AK$6 -> 0 | AM26: =IFERROR(AK26/V26-1,0) -> -1
A27: B - COSTO DE VENTA | C27: FLETE DIESEL | I27: FLETE DIESEL | J27: =SUM(A:B!J27) -> 0 | K27: =SUM(A:B!K27) -> 0 | L27: =SUM(A:B!L27) -> 0 | M27: =SUM(A:B!M27) -> 0 | N27: =SUM(A:B!N27) -> 0 | O27: =SUM(A:B!O27) -> 0 | P27: =SUM(A:B!P27) -> 0 | Q27: =SUM(A:B!Q27) -> 0 | ... U27: =SUM(A:B!U27) -> 0 | V27: =SUM(J27:U27) -> 0 | W27: =V27/V$6 -> 0 | Y27: =SUM(A:B!Y27) -> 0 | Z27: =SUM(A:B!Z27) -> 0 | AA27: =SUM(A:B!AA27) -> 0 | AB27: =SUM(A:B!AB27) -> 0 | AC27: =SUM(A:B!AC27) -> 0 | AD27: =SUM(A:B!AD27) -> 0 | AE27: =SUM(A:B!AE27) -> 0 | AF27: =SUM(A:B!AF27) -> 0 | ... AK27: =SUM(A:B!AK27) -> 0 | AL27: =AK27/AK$6 -> 0 | AM27: =IFERROR(AK27/V27-1,0) -> 0
A28: B - COSTO DE VENTA | C28: Estimulo IEPS Magna | D28: INGRESOS FORANEOS MAGNA | I28: ESTIMULO REGULAR | J28: =SUM(A:B!J28) -> 0 | K28: =SUM(A:B!K28) -> 0 | L28: =SUM(A:B!L28) -> 0 | M28: =SUM(A:B!M28) -> 0 | N28: =SUM(A:B!N28) -> 0 | O28: =SUM(A:B!O28) -> 0 | P28: =SUM(A:B!P28) -> 0 | Q28: =SUM(A:B!Q28) -> 0 | ... U28: =SUM(A:B!U28) -> 0 | V28: =SUM(J28:U28) -> 0 | W28: =V28/V$6 -> 0 | Y28: =SUM(A:B!Y28) -> 0 | Z28: =SUM(A:B!Z28) -> 0 | AA28: =SUM(A:B!AA28) -> 0 | AB28: =SUM(A:B!AB28) -> 0 | AC28: =SUM(A:B!AC28) -> 0 | AD28: =SUM(A:B!AD28) -> 0 | AE28: =SUM(A:B!AE28) -> 0 | AF28: =SUM(A:B!AF28) -> 0 | ... AK28: =SUM(A:B!AK28) -> 0 | AL28: =AK28/AK$6 -> 0 | AM28: =IFERROR(AK28/V28-1,0) -> 0
A29: B - COSTO DE VENTA | C29: Estimulo IEPS Premium | D29: INGRESOS FORANEOS MAGNA | I29: ESTIMULO PREMIUM | J29: =SUM(A:B!J29) -> 0 | K29: =SUM(A:B!K29) -> 0 | L29: =SUM(A:B!L29) -> 0 | M29: =SUM(A:B!M29) -> 0 | N29: =SUM(A:B!N29) -> 0 | O29: =SUM(A:B!O29) -> 0 | P29: =SUM(A:B!P29) -> 0 | Q29: =SUM(A:B!Q29) -> 0 | ... U29: =SUM(A:B!U29) -> 0 | V29: =SUM(J29:U29) -> 0 | W29: =V29/V$6 -> 0 | Y29: =SUM(A:B!Y29) -> 0 | Z29: =SUM(A:B!Z29) -> 0 | AA29: =SUM(A:B!AA29) -> 0 | AB29: =SUM(A:B!AB29) -> 0 | AC29: =SUM(A:B!AC29) -> 0 | AD29: =SUM(A:B!AD29) -> 0 | AE29: =SUM(A:B!AE29) -> 0 | AF29: =SUM(A:B!AF29) -> 0 | ... AK29: =SUM(A:B!AK29) -> 0 | AL29: =AK29/AK$6 -> 0 | AM29: =IFERROR(AK29/V29-1,0) -> 0
I30: COSTO ACEITES Y LUBRICANTES | J30: =SUM(A:B!J30) -> 5756 | K30: =SUM(A:B!K30) -> 6248 | L30: =SUM(A:B!L30) -> 14445 | M30: =SUM(A:B!M30) -> 13905 | N30: =SUM(A:B!N30) -> 16034 | O30: =SUM(A:B!O30) -> 6728 | P30: =SUM(A:B!P30) -> 12477 | Q30: =SUM(A:B!Q30) -> 39639 | ... U30: =SUM(A:B!U30) -> 19627.444 | V30: =SUM(J30:U30) -> 193741.78 | W30: =V30/V$6 -> 0.00086540954 | Y30: =SUM(A:B!Y30) -> 6864 | Z30: =SUM(A:B!Z30) -> 6048 | AA30: =SUM(A:B!AA30) -> 12240 | AB30: =SUM(A:B!AB30) -> 11856 | AC30: =SUM(A:B!AC30) -> 14016 | AD30: =SUM(A:B!AD30) -> 11760 | AE30: =SUM(A:B!AE30) -> 12672 | AF30: =SUM(A:B!AF30) -> 13584 | ... AK30: =SUM(A:B!AK30) -> 154272 | AL30: =AK30/AK$6 -> 0.00061526521 | AM30: =IFERROR(AK30/V30-1,0) -> -0.20372363
I31: BONIFICACION COMPRA DE COMBUSTIBLE MAGNA | J31: =SUM(A:B!J31) -> -169846 | K31: =SUM(A:B!K31) -> -167978 | L31: =SUM(A:B!L31) -> -186098 | M31: =SUM(A:B!M31) -> -197938 | N31: =SUM(A:B!N31) -> -216128 | O31: =SUM(A:B!O31) -> -198097 | P31: =SUM(A:B!P31) -> -210124 | Q31: =SUM(A:B!Q31) -> -206915 | ... U31: =SUM(A:B!U31) -> -219100.33 | V31: =SUM(J31:U31) -> -2429525.3 | W31: =V31/V$6 -> -0.010852251 | Y31: =SUM(A:B!Y31) -> 0 | Z31: =SUM(A:B!Z31) -> 0 | AA31: =SUM(A:B!AA31) -> 0 | AB31: =SUM(A:B!AB31) -> 0 | AC31: =SUM(A:B!AC31) -> 0 | AD31: =SUM(A:B!AD31) -> 0 | AE31: =SUM(A:B!AE31) -> 0 | AF31: =SUM(A:B!AF31) -> 0 | ... AK31: =SUM(A:B!AK31) -> 0 | AL31: =AK31/AK$6 -> 0 | AM31: =IFERROR(AK31/V31-1,0) -> -1
I32: BONIFICACION COMPRA DE COMBUSTIBLE PREMIUM | J32: =SUM(A:B!J32) -> -30257 | K32: =SUM(A:B!K32) -> -31282 | L32: =SUM(A:B!L32) -> -37037 | M32: =SUM(A:B!M32) -> -29914 | N32: =SUM(A:B!N32) -> -42589 | O32: =SUM(A:B!O32) -> -30035 | P32: =SUM(A:B!P32) -> -37039 | Q32: =SUM(A:B!Q32) -> -37056 | ... U32: =SUM(A:B!U32) -> -42628.444 | V32: =SUM(J32:U32) -> -445722.78 | W32: =V32/V$6 -> -0.0019909632 | Y32: =SUM(A:B!Y32) -> 0 | Z32: =SUM(A:B!Z32) -> 0 | AA32: =SUM(A:B!AA32) -> 0 | AB32: =SUM(A:B!AB32) -> 0 | AC32: =SUM(A:B!AC32) -> 0 | AD32: =SUM(A:B!AD32) -> 0 | AE32: =SUM(A:B!AE32) -> 0 | AF32: =SUM(A:B!AF32) -> 0 | ... AK32: =SUM(A:B!AK32) -> 0 | AL32: =AK32/AK$6 -> 0 | AM32: =IFERROR(AK32/V32-1,0) -> -1
I33: BONIFICACION COMPRA DE COMBUSTIBLE DIESEL | J33: =SUM(A:B!J33) -> -3485 | K33: =SUM(A:B!K33) -> 0 | L33: =SUM(A:B!L33) -> -2310 | M33: =SUM(A:B!M33) -> 0 | N33: =SUM(A:B!N33) -> -2310 | O33: =SUM(A:B!O33) -> -4642 | P33: =SUM(A:B!P33) -> 0 | Q33: =SUM(A:B!Q33) -> 0 | ... U33: =SUM(A:B!U33) -> -2056 | V33: =SUM(J33:U33) -> -20971 | W33: =V33/V$6 -> -9.3673671e-05 | Y33: =SUM(A:B!Y33) -> 0 | Z33: =SUM(A:B!Z33) -> 0 | AA33: =SUM(A:B!AA33) -> 0 | AB33: =SUM(A:B!AB33) -> 0 | AC33: =SUM(A:B!AC33) -> 0 | AD33: =SUM(A:B!AD33) -> 0 | AE33: =SUM(A:B!AE33) -> 0 | AF33: =SUM(A:B!AF33) -> 0 | ... AK33: =SUM(A:B!AK33) -> 0 | AL33: =AK33/AK$6 -> 0 | AM33: =IFERROR(AK33/V33-1,0) -> -1
I34: MARGEN DE UTILIDAD | J34: =J6-J13 -> 1290069 | K34: =K6-K13 -> 1371654 | L34: =L6-L13 -> 1739280 | M34: =M6-M13 -> 1830786 | N34: =N6-N13 -> 2009715 | O34: =O6-O13 -> 1998582 | P34: =P6-P13 -> 1655612 | Q34: =Q6-Q13 -> 1724245 | R34: =SUM(R35:R38) -> 1800607.3 | S34: =SUM(S35:S38) -> 1737309.1 | T34: =SUM(T35:T38) -> 1761815.8 | U34: =SUM(U35:U38) -> 1766577.4 | V34: =SUM(V35:V38) -> 20686244 | W34: =V34/V$6 -> 0.092401716 | Y34: =Y6-Y13 -> 1685659.5 | Z34: =Z6-Z13 -> 1442426 | AA34: =AA6-AA13 -> 1965910.9 | AB34: =AB6-AB13 -> 1708121.1 | AC34: =AC6-AC13 -> 2074145.8 | AD34: =AD6-AD13 -> 1868457.3 | AE34: =AE6-AE13 -> 1787126.4 | AF34: =AF6-AF13 -> 1869483 | ... AK34: =AK6-AK13 -> 22662506 | AL34: =AK34/AK$6 -> 0.090382256 | AM34: =IFERROR(AK34/V34-1,0) -> 0.095535093 | AN34: =+AK34-V34 -> 1976262.2
I35: *Regular | J35: =SUM(A:B!J35) -> 1001085 | K35: =SUM(A:B!K35) -> 1097495 | L35: =SUM(A:B!L35) -> 1401632 | M35: =SUM(A:B!M35) -> 1479528 | N35: =SUM(A:B!N35) -> 1551893 | O35: =SUM(A:B!O35) -> 1507543 | P35: =SUM(A:B!P35) -> 1399383 | Q35: =SUM(A:B!Q35) -> 1423247 | R35: =+AVERAGE(O35:Q35) -> 1443391 | S35: =+AVERAGE(P35:R35) -> 1422007 | T35: =+AVERAGE(Q35:S35) -> 1429548.3 | U35: =+AVERAGE(R35:T35) -> 1431648.8 | V35: =SUM(J35:U35) -> 16588401 | W35: =V35/V$39 -> 1.5497059 | Y35: =SUM(A:B!Y35) -> 1319638.3 | Z35: =SUM(A:B!Z35) -> 1099189.3 | AA35: =SUM(A:B!AA35) -> 1550720.4 | AB35: =SUM(A:B!AB35) -> 1327424.3 | AC35: =SUM(A:B!AC35) -> 1620445.9 | AD35: =SUM(A:B!AD35) -> 1486340.2 | AE35: =SUM(A:B!AE35) -> 1402949.1 | AF35: =SUM(A:B!AF35) -> 1433617.2 | ... AJ35: =SUM(A:B!AJ35) -> 1561605.4 | AK35: =SUM(Y35:AJ35) -> 17622120 | AL35: =AK35/AK$39 -> 1.5244015 | AM35: =IFERROR(AK35/V35-1,0) -> 0.062315786
I36: *Premium | J36: =SUM(A:B!J36) -> 270882 | K36: =SUM(A:B!K36) -> 262355 | L36: =SUM(A:B!L36) -> 319414 | M36: =SUM(A:B!M36) -> 332510 | N36: =SUM(A:B!N36) -> 427513 | O36: =SUM(A:B!O36) -> 460370 | P36: =SUM(A:B!P36) -> 237976 | Q36: =SUM(A:B!Q36) -> 314082 | R36: =+AVERAGE(O36:Q36) -> 337476 | S36: =+AVERAGE(P36:R36) -> 296511.33 | T36: =+AVERAGE(Q36:S36) -> 316023.11 | U36: =+AVERAGE(R36:T36) -> 316670.15 | V36: =SUM(J36:U36) -> 3891782.6 | W36: =V36/V$39 -> 0.36357444 | Y36: =SUM(A:B!Y36) -> 354333.45 | Z36: =SUM(A:B!Z36) -> 333183.19 | AA36: =SUM(A:B!AA36) -> 400038.43 | AB36: =SUM(A:B!AB36) -> 363447.05 | AC36: =SUM(A:B!AC36) -> 432928.69 | AD36: =SUM(A:B!AD36) -> 368281.3 | AE36: =SUM(A:B!AE36) -> 367117.93 | AF36: =SUM(A:B!AF36) -> 422464.64 | ... AJ36: =SUM(A:B!AJ36) -> 444298.51 | AK36: =SUM(Y36:AJ36) -> 4864758.7 | AL36: =AK36/AK$39 -> 0.42082595 | AM36: =IFERROR(AK36/V36-1,0) -> 0.25000783
I37: *Diesel | J37: =SUM(A:B!J37) -> 14035 | K37: =SUM(A:B!K37) -> 9009 | L37: =SUM(A:B!L37) -> 12996 | M37: =SUM(A:B!M37) -> 11131 | N37: =SUM(A:B!N37) -> 24319 | O37: =SUM(A:B!O37) -> 16600 | P37: =SUM(A:B!P37) -> 12364 | Q37: =SUM(A:B!Q37) -> 4315 | R37: =+AVERAGE(O37:Q37) -> 11093 | S37: =+AVERAGE(P37:R37) -> 9257.3333 | T37: =+AVERAGE(Q37:S37) -> 8221.7778 | U37: =+AVERAGE(R37:T37) -> 9524.037 | V37: =SUM(J37:U37) -> 142865.15 | W37: =V37/V$39 -> 0.013346613 | Y37: =SUM(A:B!Y37) -> 9971.78 | Z37: =SUM(A:B!Z37) -> 8541.52 | AA37: =SUM(A:B!AA37) -> 12092 | AB37: =SUM(A:B!AB37) -> 14285.7 | AC37: =SUM(A:B!AC37) -> 17267.23 | AD37: =SUM(A:B!AD37) -> 10895.8 | AE37: =SUM(A:B!AE37) -> 13891.32 | AF37: =SUM(A:B!AF37) -> 10005.12 | ... AJ37: =SUM(A:B!AJ37) -> 9772.19 | AK37: =SUM(Y37:AJ37) -> 137058.81 | AL37: =AK37/AK$39 -> 0.011856272 | AM37: =IFERROR(AK37/V37-1,0) -> -0.04064209
I38: * Aceites y Lubricantes | J38: =SUM(A:B!J38) -> 4066 | K38: =SUM(A:B!K38) -> 2794 | L38: =SUM(A:B!L38) -> 5238 | M38: =SUM(A:B!M38) -> 7617 | N38: =SUM(A:B!N38) -> 5989 | O38: =SUM(A:B!O38) -> 14066 | P38: =SUM(A:B!P38) -> 5887 | Q38: =SUM(A:B!Q38) -> -17400 | R38: =+AVERAGE(N38:P38) -> 8647.3333 | S38: =+AVERAGE(R38,P38,O38) -> 9533.4444 | T38: =+AVERAGE(R38:S38,P38) -> 8022.5926 | U38: =+AVERAGE(R38:T38) -> 8734.4568 | V38: =SUM(J38:U38) -> 63194.827 | W38: =V38/V$39 -> 0.0059037275 | Y38: =SUM(A:B!Y38) -> 0 | Z38: =SUM(A:B!Z38) -> 0 | AA38: =SUM(A:B!AA38) -> 0 | AB38: =SUM(A:B!AB38) -> 0 | AC38: =SUM(A:B!AC38) -> 0 | AD38: =SUM(A:B!AD38) -> 0 | AE38: =SUM(A:B!AE38) -> 0 | AF38: =SUM(A:B!AF38) -> 0 | ... AJ38: =SUM(A:B!AJ38) -> 0 | AK38: =SUM(Y38:AJ38) -> 0 | AL38: =AK38/AK$39 -> 0 | AM38: =IFERROR(AK38/V38-1,0) -> -1
I39: Litros vendidos | J39: =SUM(A:B!J39) -> 805453 | K39: =SUM(A:B!K39) -> 726479 | L39: =SUM(A:B!L39) -> 872823 | M39: =SUM(A:B!M39) -> 812408 | N39: =SUM(A:B!N39) -> 934031 | O39: =SUM(A:B!O39) -> 907026 | P39: =SUM(A:B!P39) -> 868664 | Q39: =SUM(A:B!Q39) -> 888226 | ... U39: =SUM(A:B!U39) -> 973596 | V39: =SUM(J39:U39) -> 10704225 | W39: =V39/V$39 -> 1 | Y39: =SUM(A:B!Y39) -> 866428.3 | Z39: =SUM(A:B!Z39) -> 785361.3 | AA39: =SUM(A:B!AA39) -> 934659.3 | AB39: =SUM(A:B!AB39) -> 898366.3 | AC39: =SUM(A:B!AC39) -> 1007849.3 | AD39: =SUM(A:B!AD39) -> 978012.3 | AE39: =SUM(A:B!AE39) -> 939591.3 | AF39: =SUM(A:B!AF39) -> 953920.3 | ... AJ39: =SUM(A:B!AJ39) -> 1044261.3 | AK39: =SUM(Y39:AJ39) -> 11560026 | AL39: =AK39/AK$39 -> 1 | AM39: =IFERROR(AK39/V39-1,0) -> 0.079949795 | AN39: =+AK39-V39 -> 855800.59 | AO39: =+AK39/12 -> 963335.47 | AP39: Modificar
I40: Maxima | J40: =SUM(A:B!J40) -> 652504 | K40: =SUM(A:B!K40) -> 579451 | L40: =SUM(A:B!L40) -> 706034 | M40: =SUM(A:B!M40) -> 653794 | N40: =SUM(A:B!N40) -> 753315 | O40: =SUM(A:B!O40) -> 741483 | P40: =SUM(A:B!P40) -> 707921 | Q40: =SUM(A:B!Q40) -> 715486 | ... U40: =SUM(A:B!U40) -> 782396 | V40: =SUM(J40:U40) -> 8626933 | W40: =V40/V$39 -> 0.80593719 | Y40: =SUM(A:B!Y40) -> 710418.3 | Z40: =SUM(A:B!Z40) -> 635498.3 | AA40: =SUM(A:B!AA40) -> 763448.3 | AB40: =SUM(A:B!AB40) -> 732477.3 | AC40: =SUM(A:B!AC40) -> 821532.3 | AD40: =SUM(A:B!AD40) -> 807702.3 | AE40: =SUM(A:B!AE40) -> 774024.3 | AF40: =SUM(A:B!AF40) -> 773496.3 | ... AJ40: =SUM(A:B!AJ40) -> 847993.3 | AK40: =SUM(Y40:AJ40) -> 9418878.6 | AL40: =AK40/AK$39 -> 0.81478008 | AM40: =IFERROR(AK40/V40-1,0) -> 0.091799205
I41: Super | J41: =SUM(A:B!J41) -> 147578 | K41: =SUM(A:B!K41) -> 142154 | L41: =SUM(A:B!L41) -> 160901 | M41: =SUM(A:B!M41) -> 151568 | N41: =SUM(A:B!N41) -> 172299 | O41: =SUM(A:B!O41) -> 158797 | P41: =SUM(A:B!P41) -> 153571 | Q41: =SUM(A:B!Q41) -> 166736 | ... U41: =SUM(A:B!U41) -> 185941 | V41: =SUM(J41:U41) -> 2002797 | W41: =V41/V$39 -> 0.18710341 | Y41: =SUM(A:B!Y41) -> 150531 | Z41: =SUM(A:B!Z41) -> 144897 | AA41: =SUM(A:B!AA41) -> 165165 | AB41: =SUM(A:B!AB41) -> 158674 | AC41: =SUM(A:B!AC41) -> 177640 | AD41: =SUM(A:B!AD41) -> 163370 | AE41: =SUM(A:B!AE41) -> 158178 | AF41: =SUM(A:B!AF41) -> 174248 | ... AJ41: =SUM(A:B!AJ41) -> 190869 | AK41: =SUM(Y41:AJ41) -> 2065787 | AL41: =AK41/AK$39 -> 0.1787009 | AM41: =IFERROR(AK41/V41-1,0) -> 0.031451016
I42: Diesel | J42: =SUM(A:B!J42) -> 5372 | K42: =SUM(A:B!K42) -> 4872 | L42: =SUM(A:B!L42) -> 5890 | M42: =SUM(A:B!M42) -> 7047 | N42: =SUM(A:B!N42) -> 8416 | O42: =SUM(A:B!O42) -> 6746 | P42: =SUM(A:B!P42) -> 7174 | Q42: =SUM(A:B!Q42) -> 6006 | ... U42: =SUM(A:B!U42) -> 5259 | V42: =SUM(J42:U42) -> 74500 | W42: =V42/V$39 -> 0.0069598686 | Y42: =SUM(A:B!Y42) -> 5479 | Z42: =SUM(A:B!Z42) -> 4966 | AA42: =SUM(A:B!AA42) -> 6046 | AB42: =SUM(A:B!AB42) -> 7215 | AC42: =SUM(A:B!AC42) -> 8677 | AD42: =SUM(A:B!AD42) -> 6940 | AE42: =SUM(A:B!AE42) -> 7389 | AF42: =SUM(A:B!AF42) -> 6176 | ... AJ42: =SUM(A:B!AJ42) -> 5399 | AK42: =SUM(Y42:AJ42) -> 75360 | AL42: =AK42/AK$39 -> 0.0065190167 | AM42: =IFERROR(AK42/V42-1,0) -> 0.011543624
I43: Margen de utilidad por combustible | J43: =J34/J39 -> 1.6016689 | K43: =K34/K39 -> 1.8880849 | L43: =L34/L39 -> 1.9927064 | M43: =M34/M39 -> 2.2535302 | N43: =N34/N39 -> 2.1516577 | O43: =O34/O39 -> 2.2034451 | P43: =P34/P39 -> 1.9059291 | Q43: =Q34/Q39 -> 1.9412233 | R43: =+R34/R39 -> 1.9206355 | S43: =+S34/S39 -> 1.7467714 | T43: =+T34/T39 -> 1.791501 | U43: =+U34/U39 -> 1.8144871 | V43: =+V34/V39 -> 1.9325307 | W43: =V43/V$39 -> 1.8053906e-07 | Y43: =Y34/Y39 -> 1.9455269 | Z43: =Z34/Z39 -> 1.83664 | AA43: =AA34/AA39 -> 2.1033449 | AB43: =AB34/AB39 -> 1.9013637 | AC43: =AC34/AC39 -> 2.057992 | AD43: =AD34/AD39 -> 1.910464 | AE43: =AE34/AE39 -> 1.9020253 | AF43: =AF34/AF39 -> 1.9597895 | ... AK43: =AK34/AK39 -> 1.96042 | AL43: =AK43/AK$39 -> 1.6958613e-07 | AM43: =IFERROR(AK43/V43-1,0) -> 0.014431503 | AN43: =+AK6/AK39 -> 21.69032
I44: Maxima | J44: =IFERROR((J7+J11-(J14+J17+J23+J25+J28))/J40,0) -> 1.2713853 | K44: =IFERROR((K7+K11-(K14+K17+K23+K25+K28))/K40,0) -> 1.5760746 | L44: =IFERROR((L7+L11-(L14+L17+L23+L25+L28))/L40,0) -> 1.6543113 | M44: =IFERROR((M7+M11-(M14+M17+M23+M25+M28))/M40,0) -> 1.8378434 | N44: =IFERROR((N7+N11-(N14+N17+N23+N25+N28))/N40,0) -> 1.6385602 | O44: =IFERROR((O7+O11-(O14+O17+O23+O25+O28))/O40,0) -> 1.6279321 | P44: =IFERROR((P7+P11-(P14+P17+P23+P25+P28))/P40,0) -> 1.6213984 | Q44: =IFERROR((Q7+Q11-(Q14+Q17+Q23+Q25+Q28))/Q40,0) -> 1.5968838 | R44: =+R35/R40 -> 1.9327678 | S44: =+S35/S40 -> 1.7831927 | T44: =+T35/T40 -> 1.8088702 | U44: =+U35/U40 -> 1.8298263 | V44: =+V35/V40 -> 1.9228619 | W44: =V44/V$39 -> 1.7963579e-07 | Y44: =IFERROR((Y7+Y11-(Y14+Y17+Y23+Y25+Y28))/Y40,0) -> 1.8575511 | Z44: =IFERROR((Z7+Z11-(Z14+Z17+Z23+Z25+Z28))/Z40,0) -> 1.7296495 | AA44: =IFERROR((AA7+AA11-(AA14+AA17+AA23+AA25+AA28))/AA40,0) -> 2.0312056 | AB44: =IFERROR((AB7+AB11-(AB14+AB17+AB23+AB25+AB28))/AB40,0) -> 1.8122395 | AC44: =IFERROR((AC7+AC11-(AC14+AC17+AC23+AC25+AC28))/AC40,0) -> 1.9724677 | AD44: =IFERROR((AD7+AD11-(AD14+AD17+AD23+AD25+AD28))/AD40,0) -> 1.840208 | AE44: =IFERROR((AE7+AE11-(AE14+AE17+AE23+AE25+AE28))/AE40,0) -> 1.8125389 | AF44: =IFERROR((AF7+AF11-(AF14+AF17+AF23+AF25+AF28))/AF40,0) -> 1.8534248 | ... AK44: =IFERROR((AK7+AK11-(AK14+AK17+AK23+AK25+AK28))/AK40,0) -> 1.8709361 | AL44: =AK44/AK$39 -> 1.6184533e-07 | AM44: =IFERROR(AK44/V44-1,0) -> -0.027004433
I45: Super | J45: =IFERROR((J8+J12-(J15+J18+J24+J26+J29))/J41,0) -> 1.7328667 | K45: =IFERROR((K8+K12-(K15+K18+K24+K26+K29))/K41,0) -> 1.6556903 | L45: =IFERROR((L8+L12-(L15+L18+L24+L26+L29))/L41,0) -> 1.7286344 | M45: =IFERROR((M8+M12-(M15+M18+M24+M26+M29))/M41,0) -> 1.9511968 | N45: =IFERROR((N8+N12-(N15+N18+N24+N26+N29))/N41,0) -> 2.1081028 | O45: =IFERROR((O8+O12-(O15+O18+O24+O26+O29))/O41,0) -> 2.136432 | P45: =IFERROR((P8+P12-(P15+P18+P24+P26+P29))/P41,0) -> 1.8143334 | Q45: =IFERROR((Q8+Q12-(Q15+Q18+Q24+Q26+Q29))/Q41,0) -> 1.6304157 | R45: =+R36/R41 -> 1.8252996 | S45: =+S36/S41 -> 1.5561224 | T45: =+T36/T41 -> 1.6825939 | U45: =+U36/U41 -> 1.7030679 | V45: =+V36/V41 -> 1.9431738 | W45: =V45/V$39 -> 1.8153334e-07 | Y45: =IFERROR((Y8+Y12-(Y15+Y18+Y24+Y26+Y29))/Y41,0) -> 2.3538902 | Z45: =IFERROR((Z8+Z12-(Z15+Z18+Z24+Z26+Z29))/Z41,0) -> 2.2994485 | AA45: =IFERROR((AA8+AA12-(AA15+AA18+AA24+AA26+AA29))/AA41,0) -> 2.4220533 | AB45: =IFERROR((AB8+AB12-(AB15+AB18+AB24+AB26+AB29))/AB41,0) -> 2.2905268 | AC45: =IFERROR((AC8+AC12-(AC15+AC18+AC24+AC26+AC29))/AC41,0) -> 2.4371126 | AD45: =IFERROR((AD8+AD12-(AD15+AD18+AD24+AD26+AD29))/AD41,0) -> 2.2542774 | AE45: =IFERROR((AE8+AE12-(AE15+AE18+AE24+AE26+AE29))/AE41,0) -> 2.3209165 | AF45: =IFERROR((AF8+AF12-(AF15+AF18+AF24+AF26+AF29))/AF41,0) -> 2.4245021 | ... AK45: =IFERROR((AK8+AK12-(AK15+AK18+AK24+AK26+AK29))/AK41,0) -> 2.3549179 | AL45: =AK45/AK$39 -> 2.0371217e-07 | AM45: =IFERROR(AK45/V45-1,0) -> 0.21189258
I46: Diesel | J46: =IFERROR((J9-(J16+J19+J27))/J42,0) -> 1.9638868 | K46: =IFERROR((K9-(K16+K19+K27))/K42,0) -> 1.4542282 | L46: =IFERROR((L9-(L16+L19+L27))/L42,0) -> 1.3117148 | M46: =IFERROR((M9-(M16+M19+M27))/M42,0) -> 1.5464737 | N46: =IFERROR((N9-(N16+N19+N27))/N42,0) -> 2.0471721 | O46: =IFERROR((O9-(O16+O19+O27))/O42,0) -> 1.7727542 | P46: =IFERROR((P9-(P16+P19+P27))/P42,0) -> 1.381656 | Q46: =IFERROR((Q9-(Q16+Q19+Q27))/Q42,0) -> 0.5001665 | R46: =+R37/R42 -> 1.906669 | S46: =+S37/S42 -> 1.4051811 | T46: =+T37/T42 -> 1.5477744 | U46: =+U37/U42 -> 1.8109977 | V46: =+V37/V42 -> 1.917653 | W46: =V46/V$39 -> 1.7914917e-07 | Y46: =IFERROR((Y9+Y11-(Y16+Y19+Y27))/Y42,0) -> 1.82 | Z46: =IFERROR((Z9+Z11-(Z16+Z19+Z27))/Z42,0) -> 1.72 | AA46: =IFERROR((AA9+AA11-(AA16+AA19+AA27))/AA42,0) -> 2 | AB46: =IFERROR((AB9+AB11-(AB16+AB19+AB27))/AB42,0) -> 1.98 | AC46: =IFERROR((AC9+AC11-(AC16+AC19+AC27))/AC42,0) -> 1.99 | AD46: =IFERROR((AD9+AD11-(AD16+AD19+AD27))/AD42,0) -> 1.57 | AE46: =IFERROR((AE9+AE11-(AE16+AE19+AE27))/AE42,0) -> 1.88 | AF46: =IFERROR((AF9+AF11-(AF16+AF19+AF27))/AF42,0) -> 1.62 | ... AK46: =IFERROR((AK9+AK11-(AK16+AK19+AK27))/AK42,0) -> 1.8187209 | AL46: =AK46/AK$39 -> 1.5732845e-07 | AM46: =IFERROR(AK46/V46-1,0) -> -0.051590176
E48: ( menos ) | I48: GASTO ESTACIONES
A50: E - GASTOS DE OPERACIÓN | B50: estaciones | I50: E - GASTOS DE OPERACIÓN | J50: =SUM(J51:J90) -> 122446 | K50: =SUM(K51:K90) -> 106245 | L50: =SUM(L51:L90) -> 89091 | M50: =SUM(M51:M90) -> 110272 | N50: =SUM(N51:N90) -> 232930 | O50: =SUM(O51:O90) -> 225838 | P50: =SUM(P51:P90) -> 226077 | Q50: =SUM(Q51:Q90) -> 160331 | ... V50: =SUM(V51:V90) -> 2442318 | W50: =V50/V$6 -> 0.010909394 | Y50: =SUM(Y51:Y90) -> 356952.31 | Z50: =SUM(Z51:Z90) -> 395138.34 | AA50: =SUM(AA51:AA90) -> 207799.37 | AB50: =SUM(AB51:AB90) -> 208225.41 | AC50: =SUM(AC51:AC90) -> 214119.98 | AD50: =SUM(AD51:AD90) -> 167442.55 | AE50: =SUM(AE51:AE90) -> 175479.49 | AF50: =SUM(AF51:AF90) -> 171660.09 | ... AK50: =SUM(AK51:AK90) -> 2668078.6 | AL50: =AK50/AK$6 -> 0.01064079 | AM50: =IFERROR(AK50/V50-1,0) -> 0.092437015 | AN50: =+AK50-V50 -> 225760.59
A51: E - GASTOS DE OPERACIÓN | B51: estaciones | C51: Servicios Administrativos | I51: Traslado de Valores | J51: =SUM(A:B!J51) -> 53341 | K51: =SUM(A:B!K51) -> 46688 | L51: =SUM(A:B!L51) -> 44687 | M51: =SUM(A:B!M51) -> 44765 | N51: =SUM(A:B!N51) -> 48640 | O51: =SUM(A:B!O51) -> 49241 | P51: =SUM(A:B!P51) -> 49239 | Q51: =SUM(A:B!Q51) -> 52289 | ... U51: =SUM(A:B!U51) -> 49215.403 | V51: =SUM(J51:U51) -> 583416.24 | W51: =V51/V$6 -> 0.002606015 | Y51: =SUM(A:B!Y51) -> 50313.675 | Z51: =SUM(A:B!Z51) -> 50313.675 | AA51: =SUM(A:B!AA51) -> 50313.675 | AB51: =SUM(A:B!AB51) -> 50313.675 | AC51: =SUM(A:B!AC51) -> 50313.675 | AD51: =SUM(A:B!AD51) -> 50313.675 | AE51: =SUM(A:B!AE51) -> 50313.675 | AF51: =SUM(A:B!AF51) -> 50313.675 | ... AJ51: =SUM(A:B!AJ51) -> 50313.675 | AK51: =SUM(Y51:AJ51) -> 603764.1 | AL51: =AK51/AK$6 -> 0.0024079227 | AM51: =IFERROR(AK51/V51-1,0) -> 0.034877096 | AN51: =+AK51-V51 -> 20347.864
A52: E - GASTOS DE OPERACIÓN | B52: estaciones | I52: Servicios Administrativos | K52: 7360 | L52: =SUM(A:B!L52) -> 7360 | M52: =SUM(A:B!M52) -> 7360 | N52: =SUM(A:B!N52) -> 7360 | O52: =SUM(A:B!O52) -> 7360 | P52: =SUM(A:B!P52) -> 7360 | Q52: =SUM(A:B!Q52) -> 7360 | R52: 7360 | S52: =SUM(A:B!S52) -> 7360 | T52: 7360 | U52: 7360 | V52: =SUM(J52:U52) -> 80960 | W52: =V52/V$6 -> 0.0003616337 | Y52: =SUM(A:B!Y52) -> 7360 | Z52: =SUM(A:B!Z52) -> 7360 | AA52: =SUM(A:B!AA52) -> 7360 | AB52: =SUM(A:B!AB52) -> 7360 | AC52: =SUM(A:B!AC52) -> 7360 | AD52: =SUM(A:B!AD52) -> 7360 | AE52: =SUM(A:B!AE52) -> 7360 | AF52: =SUM(A:B!AF52) -> 7360 | ... AJ52: =SUM(A:B!AJ52) -> 7360 | AK52: =SUM(Y52:AJ52) -> 88320 | AL52: =AK52/AK$6 -> 0.00035223646 | AM52: =IFERROR(AK52/V52-1,0) -> 0.090909091 | AN52: =+AK52-V52 -> 7360 | AO52: 1 MES SIN GASTO
A53: E - GASTOS DE OPERACIÓN | B53: estaciones | I53: Asesoría en sistemas | J53: =SUM(A:B!J53) -> 0 | K53: =SUM(A:B!K53) -> 0 | L53: =SUM(A:B!L53) -> 0 | M53: =SUM(A:B!M53) -> 0 | N53: =SUM(A:B!N53) -> 0 | O53: =SUM(A:B!O53) -> 0 | P53: =SUM(A:B!P53) -> 0 | Q53: =SUM(A:B!Q53) -> 0 | ... U53: =SUM(A:B!U53) -> 0 | V53: =SUM(J53:U53) -> 0 | W53: =V53/V$6 -> 0 | Y53: =SUM(A:B!Y53) -> 0 | Z53: =SUM(A:B!Z53) -> 0 | AA53: =SUM(A:B!AA53) -> 0 | AB53: =SUM(A:B!AB53) -> 0 | AC53: =SUM(A:B!AC53) -> 0 | AD53: =SUM(A:B!AD53) -> 0 | AE53: =SUM(A:B!AE53) -> 0 | AF53: =SUM(A:B!AF53) -> 0 | ... AJ53: =SUM(A:B!AJ53) -> 0 | AK53: =SUM(Y53:AJ53) -> 0 | AL53: =AK53/AK$6 -> 0 | AM53: =IFERROR(AK53/V53-1,0) -> 0 | AN53: =+AK53-V53 -> 0
A54: E - GASTOS DE OPERACIÓN | B54: estaciones | I54: Otros Gastos | J54: =SUM(A:B!J54) -> 0 | K54: =SUM(A:B!K54) -> 0 | L54: =SUM(A:B!L54) -> 0 | M54: =SUM(A:B!M54) -> 0 | N54: =SUM(A:B!N54) -> 0 | O54: =SUM(A:B!O54) -> 0 | P54: =SUM(A:B!P54) -> 0 | Q54: =SUM(A:B!Q54) -> 0 | ... U54: =SUM(A:B!U54) -> 2805.2361 | V54: =SUM(J54:U54) -> 12379.069 | W54: =V54/V$6 -> 5.5295068e-05 | Y54: =SUM(A:B!Y54) -> 0 | Z54: =SUM(A:B!Z54) -> 0 | AA54: =SUM(A:B!AA54) -> 0 | AB54: =SUM(A:B!AB54) -> 0 | AC54: =SUM(A:B!AC54) -> 0 | AD54: =SUM(A:B!AD54) -> 0 | AE54: =SUM(A:B!AE54) -> 0 | AF54: =SUM(A:B!AF54) -> 0 | ... AJ54: =SUM(A:B!AJ54) -> 4968.48 | AK54: =SUM(Y54:AJ54) -> 4968.48 | AL54: =AK54/AK$6 -> 1.9815215e-05 | AM54: =IFERROR(AK54/V54-1,0) -> -0.59863865 | AN54: =+AK54-V54 -> -7410.5894
A55: E - GASTOS DE OPERACIÓN | B55: estaciones | C55: Costo Marketing | I55: Otros impuestos y derechos | J55: =SUM(A:B!J55) -> 0 | K55: =SUM(A:B!K55) -> 584 | L55: =SUM(A:B!L55) -> 649 | M55: =SUM(A:B!M55) -> 479 | N55: =SUM(A:B!N55) -> 0 | O55: =SUM(A:B!O55) -> 0 | P55: =SUM(A:B!P55) -> 0 | Q55: =SUM(A:B!Q55) -> 20945 | ... U55: =SUM(A:B!U55) -> 0 | V55: =SUM(J55:U55) -> 22657 | W55: =V55/V$6 -> 0.00010120473 | Y55: =SUM(A:B!Y55) -> 47569.056 | Z55: =SUM(A:B!Z55) -> 0 | AA55: =SUM(A:B!AA55) -> 0 | AB55: =SUM(A:B!AB55) -> 0 | AC55: =SUM(A:B!AC55) -> 0 | AD55: =SUM(A:B!AD55) -> 0 | AE55: =SUM(A:B!AE55) -> 0 | AF55: =SUM(A:B!AF55) -> 0 | ... AJ55: =SUM(A:B!AJ55) -> 0 | AK55: =SUM(Y55:AJ55) -> 47569.056 | AL55: =AK55/AK$6 -> 0.00018971417 | AM55: =IFERROR(AK55/V55-1,0) -> 1.0995302 | AN55: =+AK55-V55 -> 24912.056
A56: E - GASTOS DE OPERACIÓN | B56: estaciones | I56: Limpieza | J56: =SUM(A:B!J56) -> 10725 | K56: =SUM(A:B!K56) -> 10467 | L56: =SUM(A:B!L56) -> 0 | M56: =SUM(A:B!M56) -> 8802 | N56: =SUM(A:B!N56) -> 3380 | O56: =SUM(A:B!O56) -> 5871 | P56: =SUM(A:B!P56) -> 3690 | Q56: =SUM(A:B!Q56) -> 6134 | ... U56: =SUM(A:B!U56) -> 6114.1736 | V56: =SUM(J56:U56) -> 72406.757 | W56: =V56/V$6 -> 0.00032342791 | Y56: =SUM(A:B!Y56) -> 6262.355 | Z56: =SUM(A:B!Z56) -> 6262.355 | AA56: =SUM(A:B!AA56) -> 6262.355 | AB56: =SUM(A:B!AB56) -> 6262.355 | AC56: =SUM(A:B!AC56) -> 6262.355 | AD56: =SUM(A:B!AD56) -> 6262.355 | AE56: =SUM(A:B!AE56) -> 6262.355 | AF56: =SUM(A:B!AF56) -> 6262.355 | ... AJ56: =SUM(A:B!AJ56) -> 6262.355 | AK56: =SUM(Y56:AJ56) -> 75148.26 | AL56: =AK56/AK$6 -> 0.00029970513 | AM56: =IFERROR(AK56/V56-1,0) -> 0.037862531 | AN56: =+AK56-V56 -> 2741.5031
A57: E - GASTOS DE OPERACIÓN | B57: estaciones | E57: x | I57: Propaganda y publicidad | J57: =SUM(A:B!J57) -> 5700 | K57: =SUM(A:B!K57) -> 9600 | L57: =SUM(A:B!L57) -> 21424 | M57: =SUM(A:B!M57) -> 16037 | N57: =SUM(A:B!N57) -> 55386 | O57: =SUM(A:B!O57) -> 28776 | P57: =SUM(A:B!P57) -> 9204 | Q57: =SUM(A:B!Q57) -> -114514 | ... U57: =SUM(A:B!U57) -> 60000 | V57: =SUM(J57:U57) -> 158326 | W57: =V57/V$6 -> 0.00070721366 | Y57: =SUM(A:B!Y57) -> 0 | Z57: =SUM(A:B!Z57) -> 931.59 | AA57: =SUM(A:B!AA57) -> 48753.21 | AB57: =SUM(A:B!AB57) -> 49684.8 | AC57: =SUM(A:B!AC57) -> 51755 | AD57: =SUM(A:B!AD57) -> 0 | AE57: =SUM(A:B!AE57) -> 1759.67 | AF57: =SUM(A:B!AF57) -> 1863.18 | ... AJ57: =SUM(A:B!AJ57) -> 0 | AK57: =SUM(Y57:AJ57) -> 154747.45 | AL57: =AK57/AK$6 -> 0.00061716139 | AM57: =IFERROR(AK57/V57-1,0) -> -0.022602415 | AN57: =+AK57-V57 -> -3578.55
A58: E - GASTOS DE OPERACIÓN | B58: estaciones | E58: x | I58: Capacitacion al personal | J58: =SUM(A:B!J58) -> 0 | K58: =SUM(A:B!K58) -> 0 | L58: =SUM(A:B!L58) -> 0 | M58: =SUM(A:B!M58) -> 0 | N58: =SUM(A:B!N58) -> 0 | O58: =SUM(A:B!O58) -> 0 | P58: =SUM(A:B!P58) -> 0 | Q58: =SUM(A:B!Q58) -> 0 | ... U58: =SUM(A:B!U58) -> 0 | V58: =SUM(J58:U58) -> 31200 | W58: =V58/V$6 -> 0.00013936477 | Y58: =SUM(A:B!Y58) -> 1990.5769 | Z58: =SUM(A:B!Z58) -> 6369.8462 | AA58: =SUM(A:B!AA58) -> 1194.3462 | AB58: =SUM(A:B!AB58) -> 0 | AC58: =SUM(A:B!AC58) -> 0 | AD58: =SUM(A:B!AD58) -> 0 | AE58: =SUM(A:B!AE58) -> 0 | AF58: =SUM(A:B!AF58) -> 0 | ... AJ58: =SUM(A:B!AJ58) -> 0 | AK58: =SUM(Y58:AJ58) -> 9554.7692 | AL58: =AK58/AK$6 -> 3.8106183e-05 | AM58: =IFERROR(AK58/V58-1,0) -> -0.6937574 | AN58: =+AK58-V58 -> -21645.231
A59: E - GASTOS DE OPERACIÓN | B59: estaciones | I59: Honorarios Administrativos P.F. | J59: =SUM(A:B!J59) -> 0 | K59: =SUM(A:B!K59) -> 0 | L59: =SUM(A:B!L59) -> 0 | M59: =SUM(A:B!M59) -> 0 | N59: =SUM(A:B!N59) -> 0 | O59: =SUM(A:B!O59) -> 0 | P59: =SUM(A:B!P59) -> 0 | Q59: =SUM(A:B!Q59) -> 0 | ... U59: =SUM(A:B!U59) -> 0 | V59: =SUM(J59:U59) -> 0 | W59: =V59/V$6 -> 0 | Y59: =SUM(A:B!Y59) -> 0 | Z59: =SUM(A:B!Z59) -> 0 | AA59: =SUM(A:B!AA59) -> 0 | AB59: =SUM(A:B!AB59) -> 0 | AC59: =SUM(A:B!AC59) -> 0 | AD59: =SUM(A:B!AD59) -> 0 | AE59: =SUM(A:B!AE59) -> 0 | AF59: =SUM(A:B!AF59) -> 0 | ... AJ59: =SUM(A:B!AJ59) -> 0 | AK59: =SUM(Y59:AJ59) -> 0 | AL59: =AK59/AK$6 -> 0 | AM59: =IFERROR(AK59/V59-1,0) -> 0 | AN59: =+AK59-V59 -> 0
A60: E - GASTOS DE OPERACIÓN | B60: estaciones | I60: Honorarios Administrativos P.M. | J60: =SUM(A:B!J60) -> 0 | K60: =SUM(A:B!K60) -> 0 | L60: =SUM(A:B!L60) -> 0 | M60: =SUM(A:B!M60) -> 0 | N60: =SUM(A:B!N60) -> 0 | O60: =SUM(A:B!O60) -> 0 | P60: =SUM(A:B!P60) -> 0 | Q60: =SUM(A:B!Q60) -> 0 | ... U60: =SUM(A:B!U60) -> 0 | V60: =SUM(J60:U60) -> 0 | W60: =V60/V$6 -> 0 | Y60: =SUM(A:B!Y60) -> 0 | Z60: =SUM(A:B!Z60) -> 0 | AA60: =SUM(A:B!AA60) -> 0 | AB60: =SUM(A:B!AB60) -> 0 | AC60: =SUM(A:B!AC60) -> 0 | AD60: =SUM(A:B!AD60) -> 0 | AE60: =SUM(A:B!AE60) -> 0 | AF60: =SUM(A:B!AF60) -> 0 | ... AJ60: =SUM(A:B!AJ60) -> 0 | AK60: =SUM(Y60:AJ60) -> 0 | AL60: =AK60/AK$6 -> 0 | AM60: =IFERROR(AK60/V60-1,0) -> 0 | AN60: =+AK60-V60 -> 0
A61: E - GASTOS DE OPERACIÓN | B61: estaciones | I61: Asistencia técnica | J61: =SUM(A:B!J61) -> 0 | K61: =SUM(A:B!K61) -> 0 | L61: =SUM(A:B!L61) -> 0 | M61: =SUM(A:B!M61) -> 0 | N61: =SUM(A:B!N61) -> 0 | O61: =SUM(A:B!O61) -> 0 | P61: =SUM(A:B!P61) -> 0 | Q61: =SUM(A:B!Q61) -> 0 | ... U61: =SUM(A:B!U61) -> 0 | V61: =SUM(J61:U61) -> 0 | W61: =V61/V$6 -> 0 | Y61: =SUM(A:B!Y61) -> 0 | Z61: =SUM(A:B!Z61) -> 0 | AA61: =SUM(A:B!AA61) -> 0 | AB61: =SUM(A:B!AB61) -> 0 | AC61: =SUM(A:B!AC61) -> 0 | AD61: =SUM(A:B!AD61) -> 0 | AE61: =SUM(A:B!AE61) -> 0 | AF61: =SUM(A:B!AF61) -> 0 | ... AJ61: =SUM(A:B!AJ61) -> 0 | AK61: =SUM(Y61:AJ61) -> 0 | AL61: =AK61/AK$6 -> 0 | AM61: =IFERROR(AK61/V61-1,0) -> 0 | AN61: =+AK61-V61 -> 0
A62: E - GASTOS DE OPERACIÓN | B62: estaciones | I62: Gastos no deducibles (sin requisitos fiscales) | J62: =SUM(A:B!J62) -> 1011 | K62: =SUM(A:B!K62) -> 3942 | L62: =SUM(A:B!L62) -> 2147 | M62: =SUM(A:B!M62) -> 3660 | N62: =SUM(A:B!N62) -> 1674 | O62: =SUM(A:B!O62) -> 3666 | P62: =SUM(A:B!P62) -> 14747 | Q62: =SUM(A:B!Q62) -> 16348 | ... U62: =SUM(A:B!U62) -> 0 | V62: =SUM(J62:U62) -> 23069 | W62: =V62/V$6 -> 0.00010304506 | Y62: =SUM(A:B!Y62) -> 0 | Z62: =SUM(A:B!Z62) -> 0 | AA62: =SUM(A:B!AA62) -> 0 | AB62: =SUM(A:B!AB62) -> 0 | AC62: =SUM(A:B!AC62) -> 0 | AD62: =SUM(A:B!AD62) -> 0 | AE62: =SUM(A:B!AE62) -> 0 | AF62: =SUM(A:B!AF62) -> 0 | ... AJ62: =SUM(A:B!AJ62) -> 0 | AK62: =SUM(Y62:AJ62) -> 0 | AL62: =AK62/AK$6 -> 0 | AM62: =IFERROR(AK62/V62-1,0) -> -1 | AN62: =+AK62-V62 -> -23069
A63: E - GASTOS DE OPERACIÓN | B63: estaciones | I63: Papelería y artículos de oficina | J63: =SUM(A:B!J63) -> 8187 | K63: =SUM(A:B!K63) -> 4482 | L63: =SUM(A:B!L63) -> 1704 | M63: =SUM(A:B!M63) -> 5280 | N63: =SUM(A:B!N63) -> 5966 | O63: =SUM(A:B!O63) -> 4080 | P63: =SUM(A:B!P63) -> 5569 | Q63: =SUM(A:B!Q63) -> 9096 | ... U63: =SUM(A:B!U63) -> 5367.8403 | V63: =SUM(J63:U63) -> 64361.424 | W63: =V63/V$6 -> 0.00028749086 | Y63: =SUM(A:B!Y63) -> 3670 | Z63: =SUM(A:B!Z63) -> 3670 | AA63: =SUM(A:B!AA63) -> 3670 | AB63: =SUM(A:B!AB63) -> 3670 | AC63: =SUM(A:B!AC63) -> 3670 | AD63: =SUM(A:B!AD63) -> 3670 | AE63: =SUM(A:B!AE63) -> 3670 | AF63: =SUM(A:B!AF63) -> 3670 | ... AJ63: =SUM(A:B!AJ63) -> 3670 | AK63: =SUM(Y63:AJ63) -> 44040 | AL63: =AK63/AK$6 -> 0.00017563965 | AM63: =IFERROR(AK63/V63-1,0) -> -0.31573919 | AN63: =+AK63-V63 -> -20321.424
A64: E - GASTOS DE OPERACIÓN | B64: estaciones | I64: Faltantes | J64: =SUM(A:B!J64) -> 0 | K64: =SUM(A:B!K64) -> 0 | L64: =SUM(A:B!L64) -> 0 | M64: =SUM(A:B!M64) -> 0 | N64: =SUM(A:B!N64) -> 0 | O64: =SUM(A:B!O64) -> 0 | P64: =SUM(A:B!P64) -> 0 | Q64: =SUM(A:B!Q64) -> 0 | ... U64: =SUM(A:B!U64) -> 0 | V64: =SUM(J64:U64) -> 0 | W64: =V64/V$6 -> 0 | Y64: =SUM(A:B!Y64) -> 0 | Z64: =SUM(A:B!Z64) -> 0 | AA64: =SUM(A:B!AA64) -> 0 | AB64: =SUM(A:B!AB64) -> 0 | AC64: =SUM(A:B!AC64) -> 0 | AD64: =SUM(A:B!AD64) -> 0 | AE64: =SUM(A:B!AE64) -> 0 | AF64: =SUM(A:B!AF64) -> 0 | ... AJ64: =SUM(A:B!AJ64) -> 0 | AK64: =SUM(Y64:AJ64) -> 0 | AL64: =AK64/AK$6 -> 0 | AM64: =IFERROR(AK64/V64-1,0) -> 0 | AN64: =+AK64-V64 -> 0
A65: E - GASTOS DE OPERACIÓN | B65: estaciones | I65: Licencias y Permisos | J65: =SUM(A:B!J65) -> 0 | K65: =SUM(A:B!K65) -> 0 | L65: =SUM(A:B!L65) -> 0 | M65: =SUM(A:B!M65) -> 0 | N65: =SUM(A:B!N65) -> 0 | O65: =SUM(A:B!O65) -> 0 | P65: =SUM(A:B!P65) -> 0 | Q65: =SUM(A:B!Q65) -> 0 | ... U65: =SUM(A:B!U65) -> 0 | V65: =SUM(J65:U65) -> 0 | W65: =V65/V$6 -> 0 | Y65: =SUM(A:B!Y65) -> 141601.68 | Z65: =SUM(A:B!Z65) -> 233932.6 | AA65: =SUM(A:B!AA65) -> 0 | AB65: =SUM(A:B!AB65) -> 0 | AC65: =SUM(A:B!AC65) -> 0 | AD65: =SUM(A:B!AD65) -> 0 | AE65: =SUM(A:B!AE65) -> 0 | AF65: =SUM(A:B!AF65) -> 0 | ... AJ65: =SUM(A:B!AJ65) -> 0 | AK65: =SUM(Y65:AJ65) -> 375534.28 | AL65: =AK65/AK$6 -> 0.0014977 | AM65: =IFERROR(AK65/V65-1,0) -> 0 | AN65: =+AK65-V65 -> 375534.28 | AO65: Revisar con Oliver
A66: E - GASTOS DE OPERACIÓN | B66: estaciones | I66: Licencias, Software, Antivirus | J66: =SUM(A:B!J66) -> 0 | K66: =SUM(A:B!K66) -> 0 | L66: =SUM(A:B!L66) -> 0 | M66: =SUM(A:B!M66) -> 5370 | N66: =SUM(A:B!N66) -> 90550 | O66: =SUM(A:B!O66) -> 90550 | P66: =SUM(A:B!P66) -> 90550 | Q66: =SUM(A:B!Q66) -> 90550 | ... U66: =SUM(A:B!U66) -> 90550 | V66: =SUM(J66:U66) -> 729770 | W66: =V66/V$6 -> 0.0032597508 | Y66: =SUM(A:B!Y66) -> 23339.435 | Z66: =SUM(A:B!Z66) -> 23339.435 | AA66: =SUM(A:B!AA66) -> 23339.435 | AB66: =SUM(A:B!AB66) -> 23339.435 | AC66: =SUM(A:B!AC66) -> 28897.922 | AD66: =SUM(A:B!AD66) -> 28897.922 | AE66: =SUM(A:B!AE66) -> 28897.922 | AF66: =SUM(A:B!AF66) -> 28897.922 | ... AJ66: =SUM(A:B!AJ66) -> 28897.922 | AK66: =SUM(Y66:AJ66) -> 324541.11 | AL66: =AK66/AK$6 -> 0.0012943299 | AM66: =IFERROR(AK66/V66-1,0) -> -0.55528302 | AN66: =+AK66-V66 -> -405228.89
A67: E - GASTOS DE OPERACIÓN | B67: estaciones | I67: Fletes Combustible | J67: =SUM(A:B!J67) -> 0 | K67: =SUM(A:B!K67) -> 0 | L67: =SUM(A:B!L67) -> 0 | M67: =SUM(A:B!M67) -> 0 | N67: =SUM(A:B!N67) -> 0 | O67: =SUM(A:B!O67) -> 0 | P67: =SUM(A:B!P67) -> 0 | Q67: =SUM(A:B!Q67) -> 0 | ... U67: =SUM(A:B!U67) -> 0 | V67: =SUM(J67:U67) -> 0 | W67: =V67/V$6 -> 0 | Y67: =SUM(A:B!Y67) -> 0 | Z67: =SUM(A:B!Z67) -> 0 | AA67: =SUM(A:B!AA67) -> 0 | AB67: =SUM(A:B!AB67) -> 0 | AC67: =SUM(A:B!AC67) -> 0 | AD67: =SUM(A:B!AD67) -> 0 | AE67: =SUM(A:B!AE67) -> 0 | AF67: =SUM(A:B!AF67) -> 0 | ... AJ67: =SUM(A:B!AJ67) -> 0 | AK67: =SUM(Y67:AJ67) -> 0 | AL67: =AK67/AK$6 -> 0 | AM67: =IFERROR(AK67/V67-1,0) -> 0 | AN67: =+AK67-V67 -> 0 | AO67: Se tiene que ir al Costo
A68: E - GASTOS DE OPERACIÓN | B68: estaciones | I68: Viáticos y gastos de viaje | J68: =SUM(A:B!J68) -> 0 | K68: =SUM(A:B!K68) -> 0 | L68: =SUM(A:B!L68) -> 0 | M68: =SUM(A:B!M68) -> 2367 | N68: =SUM(A:B!N68) -> 5088 | O68: =SUM(A:B!O68) -> 6068 | P68: =SUM(A:B!P68) -> 0 | Q68: =SUM(A:B!Q68) -> 7760 | ... U68: =SUM(A:B!U68) -> 0 | V68: =SUM(J68:U68) -> 21283 | W68: =V68/V$6 -> 9.5067319e-05 | Y68: =SUM(A:B!Y68) -> 0 | Z68: =SUM(A:B!Z68) -> 0 | AA68: =SUM(A:B!AA68) -> 0 | AB68: =SUM(A:B!AB68) -> 0 | AC68: =SUM(A:B!AC68) -> 0 | AD68: =SUM(A:B!AD68) -> 0 | AE68: =SUM(A:B!AE68) -> 0 | AF68: =SUM(A:B!AF68) -> 0 | ... AJ68: =SUM(A:B!AJ68) -> 0 | AK68: =SUM(Y68:AJ68) -> 0 | AL68: =AK68/AK$6 -> 0 | AM68: =IFERROR(AK68/V68-1,0) -> -1 | AN68: =+AK68-V68 -> -21283
A69: E - GASTOS DE OPERACIÓN | B69: estaciones | I69: Recoleccion de Basura | J69: =SUM(A:B!J69) -> 0 | K69: =SUM(A:B!K69) -> 0 | L69: =SUM(A:B!L69) -> 0 | M69: =SUM(A:B!M69) -> 0 | N69: =SUM(A:B!N69) -> 1954 | O69: =SUM(A:B!O69) -> 4395 | P69: =SUM(A:B!P69) -> 3906 | Q69: =SUM(A:B!Q69) -> 3906 | ... U69: =SUM(A:B!U69) -> 4340.6667 | V69: =SUM(J69:U69) -> 31523.667 | W69: =V69/V$6 -> 0.00014081053 | Y69: =SUM(A:B!Y69) -> 4043.1006 | Z69: =SUM(A:B!Z69) -> 4043.1006 | AA69: =SUM(A:B!AA69) -> 4043.1006 | AB69: =SUM(A:B!AB69) -> 4043.1006 | AC69: =SUM(A:B!AC69) -> 4043.1006 | AD69: =SUM(A:B!AD69) -> 4043.1006 | AE69: =SUM(A:B!AE69) -> 4043.1006 | AF69: =SUM(A:B!AF69) -> 4043.1006 | ... AJ69: =SUM(A:B!AJ69) -> 4043.1006 | AK69: =SUM(Y69:AJ69) -> 48517.207 | AL69: =AK69/AK$6 -> 0.00019349558 | AM69: =IFERROR(AK69/V69-1,0) -> 0.53907246 | AN69: =+AK69-V69 -> 16993.541
A70: E - GASTOS DE OPERACIÓN | B70: estaciones | I70: Honorarios de Consultoria | J70: =SUM(A:B!J70) -> 0 | K70: =SUM(A:B!K70) -> 0 | L70: =SUM(A:B!L70) -> 0 | M70: =SUM(A:B!M70) -> 0 | N70: =SUM(A:B!N70) -> 0 | O70: =SUM(A:B!O70) -> 0 | P70: =SUM(A:B!P70) -> 0 | Q70: =SUM(A:B!Q70) -> 0 | ... U70: =SUM(A:B!U70) -> 0 | V70: =SUM(J70:U70) -> 0 | W70: =V70/V$6 -> 0 | Y70: =SUM(A:B!Y70) -> 0 | Z70: =SUM(A:B!Z70) -> 0 | AA70: =SUM(A:B!AA70) -> 0 | AB70: =SUM(A:B!AB70) -> 0 | AC70: =SUM(A:B!AC70) -> 0 | AD70: =SUM(A:B!AD70) -> 0 | AE70: =SUM(A:B!AE70) -> 0 | AF70: =SUM(A:B!AF70) -> 0 | ... AJ70: =SUM(A:B!AJ70) -> 0 | AK70: =SUM(Y70:AJ70) -> 0 | AL70: =AK70/AK$6 -> 0 | AM70: =IFERROR(AK70/V70-1,0) -> 0 | AN70: =+AK70-V70 -> 0
A71: E - GASTOS DE OPERACIÓN | B71: estaciones | I71: Agua para consumo | J71: =SUM(A:B!J71) -> 0 | K71: =SUM(A:B!K71) -> 0 | L71: =SUM(A:B!L71) -> 0 | M71: =SUM(A:B!M71) -> 0 | N71: =SUM(A:B!N71) -> 0 | O71: =SUM(A:B!O71) -> 0 | P71: =SUM(A:B!P71) -> 0 | Q71: =SUM(A:B!Q71) -> 0 | ... U71: =SUM(A:B!U71) -> 0 | V71: =SUM(J71:U71) -> 0 | W71: =V71/V$6 -> 0 | Y71: =SUM(A:B!Y71) -> 2392.6294 | Z71: =SUM(A:B!Z71) -> 2161.0846 | AA71: =SUM(A:B!AA71) -> 2392.6294 | AB71: =SUM(A:B!AB71) -> 2315.4478 | AC71: =SUM(A:B!AC71) -> 2392.6294 | AD71: =SUM(A:B!AD71) -> 2315.4478 | AE71: =SUM(A:B!AE71) -> 2392.6294 | AF71: =SUM(A:B!AF71) -> 2392.6294 | ... AJ71: =SUM(A:B!AJ71) -> 2392.6294 | AK71: =SUM(Y71:AJ71) -> 28171.282 | AL71: =AK71/AK$6 -> 0.00011235227 | AM71: =IFERROR(AK71/V71-1,0) -> 0 | AN71: =+AK71-V71 -> 28171.282 | AO71: Esta en Otros Gastos, modificar
I72: Fletes Mensajeria | J72: =SUM(A:B!J72) -> 0 | K72: =SUM(A:B!K72) -> 0 | L72: =SUM(A:B!L72) -> 0 | M72: =SUM(A:B!M72) -> 0 | N72: =SUM(A:B!N72) -> 0 | O72: =SUM(A:B!O72) -> 0 | P72: =SUM(A:B!P72) -> 0 | Q72: =SUM(A:B!Q72) -> 0 | ... U72: =SUM(A:B!U72) -> 0 | V72: =SUM(J72:U72) -> 0 | W72: =V72/V$6 -> 0 | Y72: =SUM(A:B!Y72) -> 0 | Z72: =SUM(A:B!Z72) -> 0 | AA72: =SUM(A:B!AA72) -> 0 | AB72: =SUM(A:B!AB72) -> 0 | AC72: =SUM(A:B!AC72) -> 0 | AD72: =SUM(A:B!AD72) -> 0 | AE72: =SUM(A:B!AE72) -> 0 | AF72: =SUM(A:B!AF72) -> 0 | ... AJ72: =SUM(A:B!AJ72) -> 0 | AK72: =SUM(Y72:AJ72) -> 0 | AL72: =AK72/AK$6 -> 0 | AM72: =IFERROR(AK72/V72-1,0) -> 0 | AN72: =+AK72-V72 -> 0
I73: Honorarios Admvos P.F. | J73: =SUM(A:B!J73) -> 0 | K73: =SUM(A:B!K73) -> 0 | L73: =SUM(A:B!L73) -> 0 | M73: =SUM(A:B!M73) -> 0 | N73: =SUM(A:B!N73) -> 0 | O73: =SUM(A:B!O73) -> 0 | P73: =SUM(A:B!P73) -> 0 | Q73: =SUM(A:B!Q73) -> 0 | ... U73: =SUM(A:B!U73) -> 0 | V73: =SUM(J73:U73) -> 0 | W73: =V73/V$6 -> 0 | Y73: =SUM(A:B!Y73) -> 0 | Z73: =SUM(A:B!Z73) -> 0 | AA73: =SUM(A:B!AA73) -> 0 | AB73: =SUM(A:B!AB73) -> 0 | AC73: =SUM(A:B!AC73) -> 0 | AD73: =SUM(A:B!AD73) -> 0 | AE73: =SUM(A:B!AE73) -> 0 | AF73: =SUM(A:B!AF73) -> 0 | ... AJ73: =SUM(A:B!AJ73) -> 0 | AK73: =SUM(Y73:AJ73) -> 0 | AL73: =AK73/AK$6 -> 0 | AM73: =IFERROR(AK73/V73-1,0) -> 0 | AN73: =+AK73-V73 -> 0
I74: Consumos Propios Combustibles | J74: =SUM(A:B!J74) -> 0 | K74: =SUM(A:B!K74) -> 7779 | L74: =SUM(A:B!L74) -> 0 | M74: =SUM(A:B!M74) -> 0 | N74: =SUM(A:B!N74) -> 0 | O74: =SUM(A:B!O74) -> 0 | P74: =SUM(A:B!P74) -> 0 | Q74: =SUM(A:B!Q74) -> 0 | ... U74: =SUM(A:B!U74) -> 0 | V74: =SUM(J74:U74) -> 7779 | W74: =V74/V$6 -> 3.4747389e-05 | Y74: =SUM(A:B!Y74) -> 0 | Z74: =SUM(A:B!Z74) -> 0 | AA74: =SUM(A:B!AA74) -> 0 | AB74: =SUM(A:B!AB74) -> 0 | AC74: =SUM(A:B!AC74) -> 0 | AD74: =SUM(A:B!AD74) -> 0 | AE74: =SUM(A:B!AE74) -> 0 | AF74: =SUM(A:B!AF74) -> 0 | ... AJ74: =SUM(A:B!AJ74) -> 0 | AK74: =SUM(Y74:AJ74) -> 0 | AL74: =AK74/AK$6 -> 0 | AM74: =IFERROR(AK74/V74-1,0) -> -1 | AN74: =+AK74-V74 -> -7779
I75: Renta Equipo de Sistemas | J75: =SUM(A:B!J75) -> 0 | K75: =SUM(A:B!K75) -> 6711 | L75: =SUM(A:B!L75) -> 2872 | M75: =SUM(A:B!M75) -> 2892 | N75: =SUM(A:B!N75) -> 2929 | O75: =SUM(A:B!O75) -> 2938 | P75: =SUM(A:B!P75) -> 3087 | Q75: =SUM(A:B!Q75) -> 3175 | ... U75: =SUM(A:B!U75) -> 3371.8194 | V75: =SUM(J75:U75) -> 38195.653 | W75: =V75/V$6 -> 0.00017061309 | Y75: =SUM(A:B!Y75) -> 4192.155 | Z75: =SUM(A:B!Z75) -> 4192.155 | AA75: =SUM(A:B!AA75) -> 4192.155 | AB75: =SUM(A:B!AB75) -> 4192.155 | AC75: =SUM(A:B!AC75) -> 4192.155 | AD75: =SUM(A:B!AD75) -> 4192.155 | AE75: =SUM(A:B!AE75) -> 4192.155 | AF75: =SUM(A:B!AF75) -> 4192.155 | ... AJ75: =SUM(A:B!AJ75) -> 4192.155 | AK75: =SUM(Y75:AJ75) -> 50305.86 | AL75: =AK75/AK$6 -> 0.00020062905 | AM75: =IFERROR(AK75/V75-1,0) -> 0.31705721 | AN75: =+AK75-V75 -> 12110.207
I76: Timbrado Facturas | J76: =SUM(A:B!J76) -> 736 | K76: =SUM(A:B!K76) -> 515 | L76: =SUM(A:B!L76) -> 472 | M76: =SUM(A:B!M76) -> 5484 | N76: =SUM(A:B!N76) -> 614 | O76: =SUM(A:B!O76) -> 13657 | P76: =SUM(A:B!P76) -> 21316 | Q76: =SUM(A:B!Q76) -> 24909 | ... U76: =SUM(A:B!U76) -> 7052.7778 | V76: =SUM(J76:U76) -> 84960.111 | W76: =V76/V$6 -> 0.00037950148 | Y76: =SUM(A:B!Y76) -> 4729 | Z76: =SUM(A:B!Z76) -> 4729 | AA76: =SUM(A:B!AA76) -> 4729 | AB76: =SUM(A:B!AB76) -> 4729 | AC76: =SUM(A:B!AC76) -> 4729 | AD76: =SUM(A:B!AD76) -> 4729 | AE76: =SUM(A:B!AE76) -> 4729 | AF76: =SUM(A:B!AF76) -> 4729 | ... AJ76: =SUM(A:B!AJ76) -> 4729 | AK76: =SUM(Y76:AJ76) -> 56748 | AL76: =AK76/AK$6 -> 0.0002263215 | AM76: =IFERROR(AK76/V76-1,0) -> -0.33206302 | AN76: =+AK76-V76 -> -28212.111
I77: Rentas No Deducibles | J77: =SUM(A:B!J77) -> 0 | K77: =SUM(A:B!K77) -> 0 | L77: =SUM(A:B!L77) -> 0 | M77: =SUM(A:B!M77) -> 0 | N77: =SUM(A:B!N77) -> 0 | O77: =SUM(A:B!O77) -> 0 | P77: =SUM(A:B!P77) -> 0 | Q77: =SUM(A:B!Q77) -> 0 | ... U77: =SUM(A:B!U77) -> 0 | V77: =SUM(J77:U77) -> 0 | W77: =V77/V$6 -> 0 | Y77: =SUM(A:B!Y77) -> 0 | Z77: =SUM(A:B!Z77) -> 0 | AA77: =SUM(A:B!AA77) -> 0 | AB77: =SUM(A:B!AB77) -> 0 | AC77: =SUM(A:B!AC77) -> 0 | AD77: =SUM(A:B!AD77) -> 0 | AE77: =SUM(A:B!AE77) -> 0 | AF77: =SUM(A:B!AF77) -> 0 | ... AJ77: =SUM(A:B!AJ77) -> 0 | AK77: =SUM(Y77:AJ77) -> 0 | AL77: =AK77/AK$6 -> 0 | AM77: =IFERROR(AK77/V77-1,0) -> 0 | AN77: =+AK77-V77 -> 0
E78: x | I78: Uniformes | J78: =SUM(A:B!J78) -> 34970 | K78: =SUM(A:B!K78) -> 0 | L78: =SUM(A:B!L78) -> 0 | M78: =SUM(A:B!M78) -> 0 | N78: =SUM(A:B!N78) -> 881 | O78: =SUM(A:B!O78) -> 0 | P78: =SUM(A:B!P78) -> 8901 | Q78: =SUM(A:B!Q78) -> 7288 | ... U78: =SUM(A:B!U78) -> 17232.134 | V78: =SUM(J78:U78) -> 152196.24 | W78: =V78/V$6 -> 0.0006798331 | Y78: =SUM(A:B!Y78) -> 37159.676 | Z78: =SUM(A:B!Z78) -> 29727.741 | AA78: =SUM(A:B!AA78) -> 33443.708 | AB78: =SUM(A:B!AB78) -> 32098.078 | AC78: =SUM(A:B!AC78) -> 20950.176 | AD78: =SUM(A:B!AD78) -> 23993.328 | AE78: =SUM(A:B!AE78) -> 39530.014 | AF78: =SUM(A:B!AF78) -> 28382.111 | ... AJ78: =SUM(A:B!AJ78) -> 33443.708 | AK78: =SUM(Y78:AJ78) -> 327388.01 | AL78: =AK78/AK$6 -> 0.0013056838 | AM78: =IFERROR(AK78/V78-1,0) -> 1.1510914 | AN78: =+AK78-V78 -> 175191.78 | AO78: Rebajar Diana
E79: x | I79: Contratacion Empleados | J79: =SUM(A:B!J79) -> 0 | K79: =SUM(A:B!K79) -> 0 | L79: =SUM(A:B!L79) -> 0 | M79: =SUM(A:B!M79) -> 0 | N79: =SUM(A:B!N79) -> 732 | O79: =SUM(A:B!O79) -> 1460 | P79: =SUM(A:B!P79) -> 732 | Q79: =SUM(A:B!Q79) -> 0 | ... U79: =SUM(A:B!U79) -> 520 | V79: =SUM(J79:U79) -> 3964 | W79: =V79/V$6 -> 1.7706472e-05 | Y79: =SUM(A:B!Y79) -> 4223.208 | Z79: =SUM(A:B!Z79) -> 0 | AA79: =SUM(A:B!AA79) -> 0 | AB79: =SUM(A:B!AB79) -> 2111.604 | AC79: =SUM(A:B!AC79) -> 3167.406 | AD79: =SUM(A:B!AD79) -> 5279.01 | AE79: =SUM(A:B!AE79) -> 4223.208 | AF79: =SUM(A:B!AF79) -> 3167.406 | ... AJ79: =SUM(A:B!AJ79) -> 4223.208 | AK79: =SUM(Y79:AJ79) -> 34841.466 | AL79: =AK79/AK$6 -> 0.0001389542 | AM79: =IFERROR(AK79/V79-1,0) -> 7.7894717 | AN79: =+AK79-V79 -> 30877.466
I80: Multas y Recargos | J80: =SUM(A:B!J80) -> 0 | K80: =SUM(A:B!K80) -> 341 | L80: =SUM(A:B!L80) -> 0 | M80: =SUM(A:B!M80) -> 0 | N80: =SUM(A:B!N80) -> 0 | O80: =SUM(A:B!O80) -> 0 | P80: =SUM(A:B!P80) -> 0 | Q80: =SUM(A:B!Q80) -> 0 | ... U80: =SUM(A:B!U80) -> 0 | V80: =SUM(J80:U80) -> 341 | W80: =V80/V$6 -> 1.5231854e-06 | Y80: =SUM(A:B!Y80) -> 0 | Z80: =SUM(A:B!Z80) -> 0 | AA80: =SUM(A:B!AA80) -> 0 | AB80: =SUM(A:B!AB80) -> 0 | AC80: =SUM(A:B!AC80) -> 0 | AD80: =SUM(A:B!AD80) -> 0 | AE80: =SUM(A:B!AE80) -> 0 | AF80: =SUM(A:B!AF80) -> 0 | ... AJ80: =SUM(A:B!AJ80) -> 0 | AK80: =SUM(Y80:AJ80) -> 0 | AL80: =AK80/AK$6 -> 0 | AM80: =IFERROR(AK80/V80-1,0) -> -1 | AN80: =+AK80-V80 -> -341
I81: Seguros y fianzas | J81: =SUM(A:B!J81) -> 3580 | K81: =SUM(A:B!K81) -> 3580 | L81: =SUM(A:B!L81) -> 3580 | M81: =SUM(A:B!M81) -> 3580 | N81: =SUM(A:B!N81) -> 3580 | O81: =SUM(A:B!O81) -> 3580 | P81: =SUM(A:B!P81) -> 3580 | Q81: =SUM(A:B!Q81) -> 14069 | ... U81: =SUM(A:B!U81) -> 18105.76 | V81: =SUM(J81:U81) -> 103478.52 | W81: =V81/V$6 -> 0.00046221987 | Y81: =SUM(A:B!Y81) -> 18105.76 | Z81: =SUM(A:B!Z81) -> 18105.76 | AA81: =SUM(A:B!AA81) -> 18105.76 | AB81: =SUM(A:B!AB81) -> 18105.76 | AC81: =SUM(A:B!AC81) -> 18105.76 | AD81: =SUM(A:B!AD81) -> 18105.76 | AE81: =SUM(A:B!AE81) -> 18105.76 | AF81: =SUM(A:B!AF81) -> 18105.76 | ... AJ81: =SUM(A:B!AJ81) -> 18105.76 | AK81: =SUM(Y81:AJ81) -> 217269.12 | AL81: =AK81/AK$6 -> 0.00086650935 | AM81: =IFERROR(AK81/V81-1,0) -> 1.0996543 | AN81: =+AK81-V81 -> 113790.6
I82: Vigilancia y seguridad | J82: =SUM(A:B!J82) -> 0 | K82: =SUM(A:B!K82) -> 0 | L82: =SUM(A:B!L82) -> 0 | M82: =SUM(A:B!M82) -> 0 | N82: =SUM(A:B!N82) -> 0 | O82: =SUM(A:B!O82) -> 0 | P82: =SUM(A:B!P82) -> 0 | Q82: =SUM(A:B!Q82) -> 0 | ... U82: =SUM(A:B!U82) -> 0 | V82: =SUM(J82:U82) -> 0 | W82: =V82/V$6 -> 0 | Y82: =SUM(A:B!Y82) -> 0 | Z82: =SUM(A:B!Z82) -> 0 | AA82: =SUM(A:B!AA82) -> 0 | AB82: =SUM(A:B!AB82) -> 0 | AC82: =SUM(A:B!AC82) -> 0 | AD82: =SUM(A:B!AD82) -> 0 | AE82: =SUM(A:B!AE82) -> 0 | AF82: =SUM(A:B!AF82) -> 0 | ... AJ82: =SUM(A:B!AJ82) -> 0 | AK82: =SUM(Y82:AJ82) -> 0 | AL82: =AK82/AK$6 -> 0 | AM82: =IFERROR(AK82/V82-1,0) -> 0 | AN82: =+AK82-V82 -> 0
I83: Honorarios Fiscales P.F. | J83: =SUM(A:B!J83) -> 4196 | K83: =SUM(A:B!K83) -> 4196 | L83: =SUM(A:B!L83) -> 4196 | M83: =SUM(A:B!M83) -> 4196 | N83: =SUM(A:B!N83) -> 4196 | O83: =SUM(A:B!O83) -> 4196 | P83: =SUM(A:B!P83) -> 4196 | Q83: =SUM(A:B!Q83) -> 5244 | ... U83: =SUM(A:B!U83) -> 0 | V83: =SUM(J83:U83) -> 43008 | W83: =V83/V$6 -> 0.00019210897 | Y83: =SUM(A:B!Y83) -> 0 | Z83: =SUM(A:B!Z83) -> 0 | AA83: =SUM(A:B!AA83) -> 0 | AB83: =SUM(A:B!AB83) -> 0 | AC83: =SUM(A:B!AC83) -> 0 | AD83: =SUM(A:B!AD83) -> 0 | AE83: =SUM(A:B!AE83) -> 0 | AF83: =SUM(A:B!AF83) -> 0 | ... AJ83: =SUM(A:B!AJ83) -> 0 | AK83: =SUM(Y83:AJ83) -> 0 | AL83: =AK83/AK$6 -> 0 | AM83: =IFERROR(AK83/V83-1,0) -> -1 | AN83: =+AK83-V83 -> -43008 | AO83: Revisar contabilidad, no se PPTO
I84: Honorarios Legales P.M. | J84: =SUM(A:B!J84) -> 0 | K84: =SUM(A:B!K84) -> 0 | L84: =SUM(A:B!L84) -> 0 | M84: =SUM(A:B!M84) -> 0 | N84: =SUM(A:B!N84) -> 0 | O84: =SUM(A:B!O84) -> 0 | P84: =SUM(A:B!P84) -> 0 | Q84: =SUM(A:B!Q84) -> 0 | ... U84: =SUM(A:B!U84) -> 0 | V84: =SUM(J84:U84) -> 0 | W84: =V84/V$6 -> 0 | Y84: =SUM(A:B!Y84) -> 0 | Z84: =SUM(A:B!Z84) -> 0 | AA84: =SUM(A:B!AA84) -> 0 | AB84: =SUM(A:B!AB84) -> 0 | AC84: =SUM(A:B!AC84) -> 0 | AD84: =SUM(A:B!AD84) -> 0 | AE84: =SUM(A:B!AE84) -> 0 | AF84: =SUM(A:B!AF84) -> 0 | ... AJ84: =SUM(A:B!AJ84) -> 0 | AK84: =SUM(Y84:AJ84) -> 0 | AL84: =AK84/AK$6 -> 0 | AM84: =IFERROR(AK84/V84-1,0) -> 0 | AN84: =+AK84-V84 -> 0
I85: Calcamonias y senalamientos | J85: =SUM(A:B!J85) -> 0 | K85: =SUM(A:B!K85) -> 0 | L85: =SUM(A:B!L85) -> 0 | M85: =SUM(A:B!M85) -> 0 | N85: =SUM(A:B!N85) -> 0 | O85: =SUM(A:B!O85) -> 0 | P85: =SUM(A:B!P85) -> 0 | Q85: =SUM(A:B!Q85) -> 0 | ... U85: =SUM(A:B!U85) -> 0 | V85: =SUM(J85:U85) -> 0 | W85: =V85/V$6 -> 0 | Y85: =SUM(A:B!Y85) -> 0 | Z85: =SUM(A:B!Z85) -> 0 | AA85: =SUM(A:B!AA85) -> 0 | AB85: =SUM(A:B!AB85) -> 0 | AC85: =SUM(A:B!AC85) -> 0 | AD85: =SUM(A:B!AD85) -> 0 | AE85: =SUM(A:B!AE85) -> 0 | AF85: =SUM(A:B!AF85) -> 0 | ... AJ85: =SUM(A:B!AJ85) -> 0 | AK85: =SUM(Y85:AJ85) -> 0 | AL85: =AK85/AK$6 -> 0 | AM85: =IFERROR(AK85/V85-1,0) -> 0 | AN85: =+AK85-V85 -> 0
I86: Cuotas y suscripciones | J86: =SUM(A:B!J86) -> 0 | K86: =SUM(A:B!K86) -> 0 | L86: =SUM(A:B!L86) -> 0 | M86: =SUM(A:B!M86) -> 0 | N86: =SUM(A:B!N86) -> 0 | O86: =SUM(A:B!O86) -> 0 | P86: =SUM(A:B!P86) -> 0 | Q86: =SUM(A:B!Q86) -> 0 | ... U86: =SUM(A:B!U86) -> 0 | V86: =SUM(J86:U86) -> 0 | W86: =V86/V$6 -> 0 | Y86: =SUM(A:B!Y86) -> 0 | Z86: =SUM(A:B!Z86) -> 0 | AA86: =SUM(A:B!AA86) -> 0 | AB86: =SUM(A:B!AB86) -> 0 | AC86: =SUM(A:B!AC86) -> 0 | AD86: =SUM(A:B!AD86) -> 0 | AE86: =SUM(A:B!AE86) -> 0 | AF86: =SUM(A:B!AF86) -> 0 | ... AJ86: =SUM(A:B!AJ86) -> 0 | AK86: =SUM(Y86:AJ86) -> 0 | AL86: =AK86/AK$6 -> 0 | AM86: =IFERROR(AK86/V86-1,0) -> 0 | AN86: =+AK86-V86 -> 0
I87: Cumplimiento Sat Anexo 30 y 31 | J87: =SUM(A:B!J87) -> 0 | K87: =SUM(A:B!K87) -> 0 | L87: =SUM(A:B!L87) -> 0 | M87: =SUM(A:B!M87) -> 0 | N87: =SUM(A:B!N87) -> 0 | O87: =SUM(A:B!O87) -> 0 | P87: =SUM(A:B!P87) -> 0 | Q87: =SUM(A:B!Q87) -> 0 | ... U87: =SUM(A:B!U87) -> 0 | V87: =SUM(J87:U87) -> 76960 | W87: =V87/V$6 -> 0.00034376643 | Y87: =SUM(A:B!Y87) -> 0 | Z87: =SUM(A:B!Z87) -> 0 | AA87: =SUM(A:B!AA87) -> 0 | AB87: =SUM(A:B!AB87) -> 0 | AC87: =SUM(A:B!AC87) -> 0 | AD87: =SUM(A:B!AD87) -> 0 | AE87: =SUM(A:B!AE87) -> 0 | AF87: =SUM(A:B!AF87) -> 0 | ... AJ87: =SUM(A:B!AJ87) -> 0 | AK87: =SUM(Y87:AJ87) -> 91192.31 | AL87: =AK87/AK$6 -> 0.00036369176 | AM87: =IFERROR(AK87/V87-1,0) -> 0.18493126 | AN87: =+AK87-V87 -> 14232.31
E88: x | I88: Eventos | J88: =SUM(A:B!J88) -> 0 | K88: =SUM(A:B!K88) -> 0 | L88: =SUM(A:B!L88) -> 0 | M88: =SUM(A:B!M88) -> 0 | N88: =SUM(A:B!N88) -> 0 | O88: =SUM(A:B!O88) -> 0 | P88: =SUM(A:B!P88) -> 0 | Q88: =SUM(A:B!Q88) -> 5772 | ... U88: =SUM(A:B!U88) -> 92892.8 | V88: =SUM(J88:U88) -> 100083.36 | W88: =V88/V$6 -> 0.0004470543 | Y88: =SUM(A:B!Y88) -> 0 | Z88: =SUM(A:B!Z88) -> 0 | AA88: =SUM(A:B!AA88) -> 0 | AB88: =SUM(A:B!AB88) -> 0 | AC88: =SUM(A:B!AC88) -> 8280.8 | AD88: =SUM(A:B!AD88) -> 8280.8 | AE88: =SUM(A:B!AE88) -> 0 | AF88: =SUM(A:B!AF88) -> 8280.8 | ... AJ88: =SUM(A:B!AJ88) -> 56309.44 | AK88: =SUM(Y88:AJ88) -> 85457.856 | AL88: =AK88/AK$6 -> 0.0003408217 | AM88: =IFERROR(AK88/V88-1,0) -> -0.14613322 | AN88: =+AK88-V88 -> -14625.504
A89: E - GASTOS DE OPERACIÓN | B89: estaciones | I89: Asesoria Acehico | J89: =SUM(A:B!J89) -> 0 | K89: =SUM(A:B!K89) -> 0 | L89: =SUM(A:B!L89) -> 0 | M89: =SUM(A:B!M89) -> 0 | N89: =SUM(A:B!N89) -> 0 | O89: =SUM(A:B!O89) -> 0 | P89: =SUM(A:B!P89) -> 0 | Q89: =SUM(A:B!Q89) -> 0 | ... U89: =SUM(A:B!U89) -> 0 | V89: =SUM(J89:U89) -> 0 | W89: =V89/V$6 -> 0 | Y89: =SUM(A:B!Y89) -> 0 | Z89: =SUM(A:B!Z89) -> 0 | AA89: =SUM(A:B!AA89) -> 0 | AB89: =SUM(A:B!AB89) -> 0 | AC89: =SUM(A:B!AC89) -> 0 | AD89: =SUM(A:B!AD89) -> 0 | AE89: =SUM(A:B!AE89) -> 0 | AF89: =SUM(A:B!AF89) -> 0 | ... AJ89: =SUM(A:B!AJ89) -> 0 | AK89: =SUM(Y89:AJ89) -> 0 | AL89: =AK89/AK$6 -> 0 | AM89: =IFERROR(AK89/V89-1,0) -> 0 | AN89: =+AK89-V89 -> 0
A90: E - GASTOS DE OPERACIÓN | B90: estaciones | I90: Prediales | J90: =SUM(A:B!J90) -> 0 | K90: =SUM(A:B!K90) -> 0 | L90: =SUM(A:B!L90) -> 0 | M90: =SUM(A:B!M90) -> 0 | N90: =SUM(A:B!N90) -> 0 | O90: =SUM(A:B!O90) -> 0 | P90: =SUM(A:B!P90) -> 0 | Q90: =SUM(A:B!Q90) -> 0 | ... U90: =SUM(A:B!U90) -> 0 | V90: =SUM(J90:U90) -> 0 | W90: =V90/V$6 -> 0 | Y90: =SUM(A:B!Y90) -> 0 | Z90: =SUM(A:B!Z90) -> 0 | AA90: =SUM(A:B!AA90) -> 0 | AB90: =SUM(A:B!AB90) -> 0 | AC90: =SUM(A:B!AC90) -> 0 | AD90: =SUM(A:B!AD90) -> 0 | AE90: =SUM(A:B!AE90) -> 0 | AF90: =SUM(A:B!AF90) -> 0 | ... AJ90: =SUM(A:B!AJ90) -> 0 | AK90: =SUM(Y90:AJ90) -> 0 | AL90: =AK90/AK$6 -> 0 | AM90: =IFERROR(AK90/V90-1,0) -> 0 | AN90: =+AK90-V90 -> 0
A91: C - NOMINA | B91: estaciones | I91: C - NOMINA | J91: =SUM(J92:J106) -> 572626 | K91: =SUM(K92:K106) -> 519514 | L91: =SUM(L92:L106) -> 569180 | M91: =SUM(M92:M106) -> 487941 | N91: =SUM(N92:N106) -> 447886 | O91: =SUM(O92:O106) -> 469573 | P91: =SUM(P92:P106) -> 447603 | Q91: =SUM(Q92:Q106) -> 432809 | ... V91: =SUM(V92:V106) -> 5849250 | W91: =V91/V$6 -> 0.026127544 | Y91: =SUM(Y92:Y106) -> 528532.23 | Z91: =SUM(Z92:Z106) -> 466133.45 | AA91: =SUM(AA92:AA106) -> 509870.56 | AB91: =SUM(AB92:AB106) -> 481779.33 | AC91: =SUM(AC92:AC106) -> 509870.56 | AD91: =SUM(AD92:AD106) -> 481779.33 | AE91: =SUM(AE92:AE106) -> 496358.37 | AF91: =SUM(AF92:AF106) -> 496358.37 | ... AK91: =SUM(AK92:AK106) -> 5967494.2 | AL91: =AK91/AK$6 -> 0.023799468 | AM91: =IFERROR(AK91/V91-1,0) -> 0.020215272 | AN91: =+AK91-V91 -> 118244.18
A92: C - NOMINA | B92: estaciones | I92: Aguinaldo | J92: =SUM(A:B!J92) -> 16736 | K92: =SUM(A:B!K92) -> 14901 | L92: =SUM(A:B!L92) -> 16005 | M92: =SUM(A:B!M92) -> 13919 | N92: =SUM(A:B!N92) -> 12304 | O92: =SUM(A:B!O92) -> 13178 | P92: =SUM(A:B!P92) -> 12860 | Q92: =SUM(A:B!Q92) -> 13080 | ... U92: =SUM(A:B!U92) -> 13333.896 | V92: =SUM(J92:U92) -> 166763.15 | W92: =V92/V$6 -> 0.00074490086 | Y92: =SUM(A:B!Y92) -> 15059.301 | Z92: =SUM(A:B!Z92) -> 12956.895 | AA92: =SUM(A:B!AA92) -> 14345.134 | AB92: =SUM(A:B!AB92) -> 13882.388 | AC92: =SUM(A:B!AC92) -> 14345.134 | AD92: =SUM(A:B!AD92) -> 13882.388 | AE92: =SUM(A:B!AE92) -> 14345.134 | AF92: =SUM(A:B!AF92) -> 14345.134 | ... AJ92: =SUM(A:B!AJ92) -> 14345.134 | AK92: =SUM(Y92:AJ92) -> 169616.55 | AL92: =AK92/AK$6 -> 0.00067646212 | AM92: =IFERROR(AK92/V92-1,0) -> 0.017110544
A93: C - NOMINA | B93: estaciones | I93: Compensaciones | J93: =SUM(A:B!J93) -> 19800 | K93: =SUM(A:B!K93) -> 29407 | L93: =SUM(A:B!L93) -> 37315 | M93: =SUM(A:B!M93) -> 53806 | N93: =SUM(A:B!N93) -> 53059 | O93: =SUM(A:B!O93) -> 41042 | P93: =SUM(A:B!P93) -> 40487 | Q93: =SUM(A:B!Q93) -> 29123 | ... U93: =SUM(A:B!U93) -> 46787.007 | V93: =SUM(J93:U93) -> 493518.59 | W93: =V93/V$6 -> 0.0022044584 | Y93: =SUM(A:B!Y93) -> 44408.263 | Z93: =SUM(A:B!Z93) -> 44408.263 | AA93: =SUM(A:B!AA93) -> 44408.263 | AB93: =SUM(A:B!AB93) -> 44408.263 | AC93: =SUM(A:B!AC93) -> 44408.263 | AD93: =SUM(A:B!AD93) -> 44408.263 | AE93: =SUM(A:B!AE93) -> 44408.263 | AF93: =SUM(A:B!AF93) -> 44408.263 | ... AJ93: =SUM(A:B!AJ93) -> 44408.263 | AK93: =SUM(Y93:AJ93) -> 532899.15 | AL93: =AK93/AK$6 -> 0.0021253002 | AM93: =IFERROR(AK93/V93-1,0) -> 0.079795503
A94: C - NOMINA | B94: estaciones | I94: Días festivos | J94: =SUM(A:B!J94) -> 18040 | K94: =SUM(A:B!K94) -> 17183 | L94: =SUM(A:B!L94) -> 18339 | M94: =SUM(A:B!M94) -> 0 | N94: =SUM(A:B!N94) -> 12287 | O94: =SUM(A:B!O94) -> 0 | P94: =SUM(A:B!P94) -> 1156 | Q94: =SUM(A:B!Q94) -> 0 | ... U94: =SUM(A:B!U94) -> 5331.8542 | V94: =SUM(J94:U94) -> 90109.604 | W94: =V94/V$6 -> 0.00040250333 | Y94: =SUM(A:B!Y94) -> 14184.89 | Z94: =SUM(A:B!Z94) -> 13512.191 | AA94: =SUM(A:B!AA94) -> 13512.191 | AB94: =SUM(A:B!AB94) -> 0 | AC94: =SUM(A:B!AC94) -> 13512.191 | AD94: =SUM(A:B!AD94) -> 0 | AE94: =SUM(A:B!AE94) -> 0 | AF94: =SUM(A:B!AF94) -> 0 | ... AJ94: =SUM(A:B!AJ94) -> 13512.191 | AK94: =SUM(Y94:AJ94) -> 95258.036 | AL94: =AK94/AK$6 -> 0.00037990663 | AM94: =IFERROR(AK94/V94-1,0) -> 0.057135215
A95: C - NOMINA | B95: estaciones | I95: Fondo de ahorro | J95: =SUM(A:B!J95) -> 23352 | K95: =SUM(A:B!K95) -> 20698 | L95: =SUM(A:B!L95) -> 22415 | M95: =SUM(A:B!M95) -> 18589 | N95: =SUM(A:B!N95) -> 16779 | O95: =SUM(A:B!O95) -> 18822 | P95: =SUM(A:B!P95) -> 17503 | Q95: =SUM(A:B!Q95) -> 17969 | ... U95: =SUM(A:B!U95) -> 18420.91 | V95: =SUM(J95:U95) -> 230396.33 | W95: =V95/V$6 -> 0.0010291388 | Y95: =SUM(A:B!Y95) -> 20227.653 | Z95: =SUM(A:B!Z95) -> 18917.067 | AA95: =SUM(A:B!AA95) -> 20943.896 | AB95: =SUM(A:B!AB95) -> 20268.286 | AC95: =SUM(A:B!AC95) -> 20943.896 | AD95: =SUM(A:B!AD95) -> 20268.286 | AE95: =SUM(A:B!AE95) -> 20943.896 | AF95: =SUM(A:B!AF95) -> 20943.896 | ... AJ95: =SUM(A:B!AJ95) -> 20943.896 | AK95: =SUM(Y95:AJ95) -> 245881.24 | AL95: =AK95/AK$6 -> 0.00098061977 | AM95: =IFERROR(AK95/V95-1,0) -> 0.067209909
A96: C - NOMINA | B96: estaciones | I96: Indemnizaciones | J96: =SUM(A:B!J96) -> 0 | K96: =SUM(A:B!K96) -> 0 | L96: =SUM(A:B!L96) -> 0 | M96: =SUM(A:B!M96) -> 0 | N96: =SUM(A:B!N96) -> 0 | O96: =SUM(A:B!O96) -> 0 | P96: =SUM(A:B!P96) -> 0 | Q96: =SUM(A:B!Q96) -> 0 | ... U96: =SUM(A:B!U96) -> 0 | V96: =SUM(J96:U96) -> 0 | W96: =V96/V$6 -> 0 | Y96: =SUM(A:B!Y96) -> 0 | Z96: =SUM(A:B!Z96) -> 0 | AA96: =SUM(A:B!AA96) -> 0 | AB96: =SUM(A:B!AB96) -> 0 | AC96: =SUM(A:B!AC96) -> 0 | AD96: =SUM(A:B!AD96) -> 0 | AE96: =SUM(A:B!AE96) -> 0 | AF96: =SUM(A:B!AF96) -> 0 | ... AJ96: =SUM(A:B!AJ96) -> 0 | AK96: =SUM(Y96:AJ96) -> 0 | AL96: =AK96/AK$6 -> 0 | AM96: =IFERROR(AK96/V96-1,0) -> 0
A97: C - NOMINA | B97: estaciones | I97: Premios de asistencia | J97: =SUM(A:B!J97) -> 39542 | K97: =SUM(A:B!K97) -> 34803 | L97: =SUM(A:B!L97) -> 37690 | M97: =SUM(A:B!M97) -> 30883 | N97: =SUM(A:B!N97) -> 28598 | O97: =SUM(A:B!O97) -> 32733 | P97: =SUM(A:B!P97) -> 31311 | Q97: =SUM(A:B!Q97) -> 27859 | ... U97: =SUM(A:B!U97) -> 31396.993 | V97: =SUM(J97:U97) -> 389657.41 | W97: =V97/V$6 -> 0.0017405293 | Y97: =SUM(A:B!Y97) -> 32069.655 | Z97: =SUM(A:B!Z97) -> 28966.14 | AA97: =SUM(A:B!AA97) -> 32069.655 | AB97: =SUM(A:B!AB97) -> 31035.15 | AC97: =SUM(A:B!AC97) -> 32069.655 | AD97: =SUM(A:B!AD97) -> 31035.15 | AE97: =SUM(A:B!AE97) -> 32069.655 | AF97: =SUM(A:B!AF97) -> 32069.655 | ... AJ97: =SUM(A:B!AJ97) -> 32069.655 | AK97: =SUM(Y97:AJ97) -> 377594.33 | AL97: =AK97/AK$6 -> 0.0015059159 | AM97: =IFERROR(AK97/V97-1,0) -> -0.030958181
A98: C - NOMINA | B98: estaciones | I98: Premios de puntualidad | J98: =SUM(A:B!J98) -> 36672 | K98: =SUM(A:B!K98) -> 33040 | L98: =SUM(A:B!L98) -> 34986 | M98: =SUM(A:B!M98) -> 26468 | N98: =SUM(A:B!N98) -> 23150 | O98: =SUM(A:B!O98) -> 28704 | P98: =SUM(A:B!P98) -> 26537 | Q98: =SUM(A:B!Q98) -> 23715 | ... U98: =SUM(A:B!U98) -> 27195.319 | V98: =SUM(J98:U98) -> 342633.15 | W98: =V98/V$6 -> 0.0015304804 | Y98: =SUM(A:B!Y98) -> 24618.309 | Z98: =SUM(A:B!Z98) -> 22235.892 | AA98: =SUM(A:B!AA98) -> 24618.309 | AB98: =SUM(A:B!AB98) -> 23824.17 | AC98: =SUM(A:B!AC98) -> 24618.309 | AD98: =SUM(A:B!AD98) -> 23824.17 | AE98: =SUM(A:B!AE98) -> 24618.309 | AF98: =SUM(A:B!AF98) -> 24618.309 | ... AJ98: =SUM(A:B!AJ98) -> 24618.309 | AK98: =SUM(Y98:AJ98) -> 289860.73 | AL98: =AK98/AK$6 -> 0.0011560181 | AM98: =IFERROR(AK98/V98-1,0) -> -0.15402017
A99: C - NOMINA | B99: estaciones | I99: Previsión social | J99: =SUM(A:B!J99) -> 0 | K99: =SUM(A:B!K99) -> 0 | L99: =SUM(A:B!L99) -> 0 | M99: =SUM(A:B!M99) -> 0 | N99: =SUM(A:B!N99) -> 0 | O99: =SUM(A:B!O99) -> 0 | P99: =SUM(A:B!P99) -> 0 | Q99: =SUM(A:B!Q99) -> 0 | ... U99: =SUM(A:B!U99) -> 0 | V99: =SUM(J99:U99) -> 0 | W99: =V99/V$6 -> 0 | Y99: =SUM(A:B!Y99) -> 0 | Z99: =SUM(A:B!Z99) -> 0 | AA99: =SUM(A:B!AA99) -> 0 | AB99: =SUM(A:B!AB99) -> 0 | AC99: =SUM(A:B!AC99) -> 0 | AD99: =SUM(A:B!AD99) -> 0 | AE99: =SUM(A:B!AE99) -> 0 | AF99: =SUM(A:B!AF99) -> 0 | ... AJ99: =SUM(A:B!AJ99) -> 0 | AK99: =SUM(Y99:AJ99) -> 0 | AL99: =AK99/AK$6 -> 0 | AM99: =IFERROR(AK99/V99-1,0) -> 0
A100: C - NOMINA | B100: estaciones | I100: Prima dominical | J100: =SUM(A:B!J100) -> 11011 | K100: =SUM(A:B!K100) -> 8661 | L100: =SUM(A:B!L100) -> 8845 | M100: =SUM(A:B!M100) -> 7195 | N100: =SUM(A:B!N100) -> 6909 | O100: =SUM(A:B!O100) -> 7713 | P100: =SUM(A:B!P100) -> 8121 | Q100: =SUM(A:B!Q100) -> 7589 | ... U100: =SUM(A:B!U100) -> 8005.2639 | V100: =SUM(J100:U100) -> 98152.431 | W100: =V100/V$6 -> 0.00043842919 | Y100: =SUM(A:B!Y100) -> 7756.346 | Z100: =SUM(A:B!Z100) -> 6613.3242 | AA100: =SUM(A:B!AA100) -> 7321.8947 | AB100: =SUM(A:B!AB100) -> 7085.7045 | AC100: =SUM(A:B!AC100) -> 7321.8947 | AD100: =SUM(A:B!AD100) -> 7085.7045 | AE100: =SUM(A:B!AE100) -> 7321.8947 | AF100: =SUM(A:B!AF100) -> 7321.8947 | ... AJ100: =SUM(A:B!AJ100) -> 7321.8947 | AK100: =SUM(Y100:AJ100) -> 86643.856 | AL100: =AK100/AK$6 -> 0.00034555169 | AM100: =IFERROR(AK100/V100-1,0) -> -0.11725206
A101: C - NOMINA | B101: estaciones | I101: Prima vacacional | J101: =SUM(A:B!J101) -> 3422 | K101: =SUM(A:B!K101) -> 3054 | L101: =SUM(A:B!L101) -> 3333 | M101: =SUM(A:B!M101) -> 2908 | N101: =SUM(A:B!N101) -> 2560 | O101: =SUM(A:B!O101) -> 2702 | P101: =SUM(A:B!P101) -> 2656 | Q101: =SUM(A:B!Q101) -> 2684 | ... U101: =SUM(A:B!U101) -> 2794.8889 | V101: =SUM(J101:U101) -> 34604.556 | W101: =V101/V$6 -> 0.0001545723 | Y101: =SUM(A:B!Y101) -> 3764.8252 | Z101: =SUM(A:B!Z101) -> 3239.2239 | AA101: =SUM(A:B!AA101) -> 3586.2836 | AB101: =SUM(A:B!AB101) -> 3470.597 | AC101: =SUM(A:B!AC101) -> 3586.2836 | AD101: =SUM(A:B!AD101) -> 3470.597 | AE101: =SUM(A:B!AE101) -> 3586.2836 | AF101: =SUM(A:B!AF101) -> 3586.2836 | ... AJ101: =SUM(A:B!AJ101) -> 3586.2836 | AK101: =SUM(Y101:AJ101) -> 42404.138 | AL101: =AK101/AK$6 -> 0.00016911553 | AM101: =IFERROR(AK101/V101-1,0) -> 0.2253918
A102: C - NOMINA | B102: estaciones | I102: Primas de antigüedad | J102: =SUM(A:B!J102) -> 0 | K102: =SUM(A:B!K102) -> 0 | L102: =SUM(A:B!L102) -> 0 | M102: =SUM(A:B!M102) -> 9394 | N102: =SUM(A:B!N102) -> 0 | O102: =SUM(A:B!O102) -> 181 | P102: =SUM(A:B!P102) -> 0 | Q102: =SUM(A:B!Q102) -> 0 | ... U102: =SUM(A:B!U102) -> 0 | V102: =SUM(J102:U102) -> 9575 | W102: =V102/V$6 -> 4.2769796e-05 | Y102: =SUM(A:B!Y102) -> 0 | Z102: =SUM(A:B!Z102) -> 0 | AA102: =SUM(A:B!AA102) -> 0 | AB102: =SUM(A:B!AB102) -> 0 | AC102: =SUM(A:B!AC102) -> 0 | AD102: =SUM(A:B!AD102) -> 0 | AE102: =SUM(A:B!AE102) -> 0 | AF102: =SUM(A:B!AF102) -> 0 | ... AJ102: =SUM(A:B!AJ102) -> 0 | AK102: =SUM(Y102:AJ102) -> 0 | AL102: =AK102/AK$6 -> 0 | AM102: =IFERROR(AK102/V102-1,0) -> -1
A103: C - NOMINA | B103: estaciones | I103: PTU | J103: =SUM(A:B!J103) -> 0 | K103: =SUM(A:B!K103) -> 0 | L103: =SUM(A:B!L103) -> 0 | M103: =SUM(A:B!M103) -> 0 | N103: =SUM(A:B!N103) -> 0 | O103: =SUM(A:B!O103) -> 0 | P103: =SUM(A:B!P103) -> 0 | Q103: =SUM(A:B!Q103) -> 0 | ... U103: =SUM(A:B!U103) -> 0 | V103: =SUM(J103:U103) -> 0 | W103: =V103/V$6 -> 0 | Y103: =SUM(A:B!Y103) -> 0 | Z103: =SUM(A:B!Z103) -> 0 | AA103: =SUM(A:B!AA103) -> 0 | AB103: =SUM(A:B!AB103) -> 0 | AC103: =SUM(A:B!AC103) -> 0 | AD103: =SUM(A:B!AD103) -> 0 | AE103: =SUM(A:B!AE103) -> 0 | AF103: =SUM(A:B!AF103) -> 0 | ... AJ103: =SUM(A:B!AJ103) -> 0 | AK103: =SUM(Y103:AJ103) -> 0 | AL103: =AK103/AK$6 -> 0 | AM103: =IFERROR(AK103/V103-1,0) -> 0
...

Sheet A

Sheet Colosio 
E1: Colosio | I1: 1147 | J1: 2 | K1: 3 | L1: 4 | M1: 5 | N1: 6 | O1: 7 | Y1: 2 | Z1: =+Y1+1 -> 3 | AA1: =+Z1+1 -> 4 | AB1: =+AA1+1 -> 5 | AC1: =+AB1+1 -> 6 | AD1: =+AC1+1 -> 7 | AE1: =+AD1+1 -> 8 | AF1: =+AE1+1 -> 9 | AG1: =+AF1+1 -> 10 | ... AK1: =+AJ1+1 -> 14 | AM1: 17
J2: 2025 | V2: TOTAL ANUAL | Y2: 2026 | AK2: TOTAL ANUAL
J3: ENE | K3: FEB | L3: MAR | M3: ABR | N3: MAY | O3: JUN | P3: JUL | Q3: AGO | R3: SEP | S3: OCT | T3: NOV | U3: DIC | V3: 2025 | W3: % Part | Y3: ENE | Z3: FEB | AA3: MAR | AB3: ABR | AC3: MAY | AD3: JUN | AE3: JUL | AF3: AGO | AG3: SEP | AH3: OCT | AI3: NOV | AJ3: DIC | AK3: 2026 | AL3: % Part | AM3: Var vs AA%
I4: INGRESOS
A6: A - INGRESOS | E6: ( mas ) | I6: A - INGRESOS | J6: 1679941 | K6: 1710290 | L6: 1874301 | M6: 1738490 | N6: 1902701 | O6: 1862854 | P6: 1754879 | Q6: 1760069 | R6: 1987540 | S6: 2142507 | T6: =SUM(T7:T12) -> 1963372.3 | U6: =SUM(U7:U12) -> 2031140.1 | V6: =SUM(V7:V12) -> 22408085 | W6: =V6/V$6 -> 1 | Y6: =SUM(Y7:Y12) -> 1751115.9 | Z6: =SUM(Z7:Z12) -> 1776373.1 | AA6: =SUM(AA7:AA12) -> 1969207.5 | AB6: =SUM(AB7:AB12) -> 1830087.6 | AC6: =SUM(AC7:AC12) -> 2013900 | AD6: =SUM(AD7:AD12) -> 1967859.9 | AE6: =SUM(AE7:AE12) -> 1856177.3 | AF6: =SUM(AF7:AF12) -> 1858813.8 | ... AK6: =SUM(AK7:AK12) -> 23597094 | AL6: =AK6/AK$6 -> 1 | AM6: =IFERROR(AK6/V6-1,0) -> 0.053061584
A7: A - INGRESOS | B7: estaciones | C7: INGRESOS MAGNA | D7: INGRESOS FORANEOS MAGNA | I7: MAXIMA | J7: 1003020 | K7: 992085 | L7: 1020162 | M7: 991737 | N7: 1069832 | O7: 1084784 | P7: 1032101 | Q7: 1027653 | R7: 1134813 | S7: 1205377 | T7: =AVERAGE(Q7:S7) -> 1122614.3 | U7: =AVERAGE(R7:T7) -> 1154268.1 | V7: =SUM(J7:U7) -> 12838446 | W7: =V7/V$6 -> 0.57293812 | Y7: =IFERROR(Y40*'Parametros AGS'!$L$7,0) -> 1037686 | Z7: =IFERROR(Z40*'Parametros AGS'!$L$7,0) -> 1022877.2 | AA7: =IFERROR(AA40*'Parametros AGS'!$L$7,0) -> 1071797.6 | AB7: =IFERROR(AB40*'Parametros AGS'!$L$7,0) -> 1048129.2 | AC7: =IFERROR(AC40*'Parametros AGS'!$L$7,0) -> 1137024.8 | AD7: =IFERROR(AD40*'Parametros AGS'!$L$7,0) -> 1150442.6 | AE7: =IFERROR(AE40*'Parametros AGS'!$L$7,0) -> 1095872.6 | AF7: =IFERROR(AF40*'Parametros AGS'!$L$7,0) -> 1089538.2 | ... AJ7: =IFERROR(AJ40*'Parametros AGS'!$L$7,0) -> 1178070 | AK7: =SUM(Y7:AJ7) -> 13454522 | AL7: =AK7/AK$6 -> 0.57017709 | AM7: =IFERROR(AK7/V7-1,0) -> 0.0479868
A8: A - INGRESOS | B8: estaciones | C8: INGRESOS PREMIUM | D8: INGRESOS FORANEOS PREMIUM | I8: SUPER | J8: 675874 | K8: 718041 | L8: 854139 | M8: 746515 | N8: 832708 | O8: 778028 | P8: 722609 | Q8: 732416 | R8: 851986 | S8: 934894 | T8: =AVERAGE(Q8:S8) -> 839765.33 | U8: =AVERAGE(R8:T8) -> 875548.44 | V8: =SUM(J8:U8) -> 9562523.8 | W8: =V8/V$6 -> 0.42674435 | Y8: =IFERROR(Y41*'Parametros AGS'!$L$8,0) -> 711869.9 | Z8: =IFERROR(Z41*'Parametros AGS'!$L$8,0) -> 752055.92 | AA8: =IFERROR(AA41*'Parametros AGS'!$L$8,0) -> 896209.86 | AB8: =IFERROR(AB41*'Parametros AGS'!$L$8,0) -> 780398.36 | AC8: =IFERROR(AC41*'Parametros AGS'!$L$8,0) -> 875375.2 | AD8: =IFERROR(AD41*'Parametros AGS'!$L$8,0) -> 816157.3 | AE8: =IFERROR(AE41*'Parametros AGS'!$L$8,0) -> 758924.74 | AF8: =IFERROR(AF41*'Parametros AGS'!$L$8,0) -> 768075.56 | ... AJ8: =IFERROR(AJ41*'Parametros AGS'!$L$8,0) -> 938837.62 | AK8: =SUM(Y8:AJ8) -> 10119712 | AL8: =AK8/AK$6 -> 0.42885415 | AM8: =IFERROR(AK8/V8-1,0) -> 0.058267858
A9: A - INGRESOS | B9: estaciones | C9: INGRESOS DIESEL | D9: INGRESOS FORANEOS DIESEL | I9: DIESEL | J9: 0 | K9: 0 | L9: 0 | M9: 0 | N9: 0 | O9: 0 | P9: 0 | Q9: 0 | R9: 0 | S9: 0 | T9: =AVERAGE(Q9:S9) -> 0 | U9: =AVERAGE(R9:T9) -> 0 | V9: =SUM(J9:U9) -> 0 | W9: =V9/V$6 -> 0 | Y9: =IFERROR(Y42*'[1]Margen Ctvs-Ltr'!W$15,0) -> 0 | Z9: =IFERROR(+Z42*('Parametros AGS'!C16+VLOOKUP($E$1,'Parametros AGS'!$B$125:$N$150,Z$1,0)),0) -> 0 | AA9: =IFERROR(+AA42*('Parametros AGS'!D16+VLOOKUP($E$1,'Parametros AGS'!$B$125:$N$150,AA$1,0)),0) -> 0 | AB9: =IFERROR(+AB42*('Parametros AGS'!E16+VLOOKUP($E$1,'Parametros AGS'!$B$125:$N$150,AB$1,0)),0) -> 0 | AC9: =IFERROR(+AC42*('Parametros AGS'!F16+VLOOKUP($E$1,'Parametros AGS'!$B$125:$N$150,AC$1,0)),0) -> 0 | AD9: =IFERROR(+AD42*('Parametros AGS'!G16+VLOOKUP($E$1,'Parametros AGS'!$B$125:$N$150,AD$1,0)),0) -> 0 | AE9: =IFERROR(+AE42*('Parametros AGS'!H16+VLOOKUP($E$1,'Parametros AGS'!$B$125:$N$150,AE$1,0)),0) -> 0 | AF9: =IFERROR(+AF42*('Parametros AGS'!I16+VLOOKUP($E$1,'Parametros AGS'!$B$125:$N$150,AF$1,0)),0) -> 0 | AG9: =IFERROR(+AG42*('Parametros AGS'!J16+VLOOKUP($E$1,'Parametros AGS'!$B$125:$N$150,AG$1,0)),0) -> 0 | ... AJ9: =IFERROR(+AJ42*('Parametros AGS'!M16+VLOOKUP($E$1,'Parametros AGS'!$B$125:$N$150,AJ$1,0)),0) -> 0 | AK9: =SUM(Y9:AJ9) -> 0 | AL9: =AK9/AK$6 -> 0 | AM9: =IFERROR(AK9/V9-1,0) -> 0
I10: INGRESOS ACEITES Y LUBRICANTES | J10: 1047 | K10: 164 | L10: 0 | M10: 238 | N10: 161 | O10: 42 | P10: 169 | Q10: 0 | R10: 741 | S10: 2237 | T10: =AVERAGE(Q10:S10) -> 992.66667 | U10: =AVERAGE(R10:T10) -> 1323.5556 | V10: =SUM(J10:U10) -> 7115.2222 | W10: =V10/V$6 -> 0.00031752923 | Y10: =VLOOKUP($E$1,'[2]Resumen x Tipo Combustible'!$C$45:$P$48,Y1,0) -> 1560 | Z10: =VLOOKUP($E$1,'[2]Resumen x Tipo Combustible'!$C$45:$P$48,Z1,0) -> 1440 | AA10: =VLOOKUP($E$1,'[2]Resumen x Tipo Combustible'!$C$45:$P$48,AA1,0) -> 1200 | AB10: =VLOOKUP($E$1,'[2]Resumen x Tipo Combustible'!$C$45:$P$48,AB1,0) -> 1560 | AC10: =VLOOKUP($E$1,'[2]Resumen x Tipo Combustible'!$C$45:$P$48,AC1,0) -> 1500 | AD10: =VLOOKUP($E$1,'[2]Resumen x Tipo Combustible'!$C$45:$P$48,AD1,0) -> 1260 | AE10: =VLOOKUP($E$1,'[2]Resumen x Tipo Combustible'!$C$45:$P$48,AE1,0) -> 1380 | AF10: =VLOOKUP($E$1,'[2]Resumen x Tipo Combustible'!$C$45:$P$48,AF1,0) -> 1200 | ... AJ10: =VLOOKUP($E$1,'[2]Resumen x Tipo Combustible'!$C$45:$P$48,AJ1,0) -> 2940 | AK10: =SUM(Y10:AJ10) -> 22860 | AL10: =AK10/AK$6 -> 0.00096876336 | AM10: =IFERROR(AK10/V10-1,0) -> 2.2128301
I11: SOBRANTE COMBUSTIBLES | J11: 0 | K11: 0 | L11: 0 | M11: 0 | N11: 0 | O11: 0 | P11: 0 | Q11: 0 | R11: 0 | S11: 0 | T11: =AVERAGE(Q11:S11) -> 0 | U11: 0 | V11: =SUM(J11:U11) -> 0 | W11: =V11/V$6 -> 0 | Y11: 0 | Z11: 0 | AA11: 0 | AB11: 0 | AC11: 0 | AD11: 0 | AE11: 0 | AF11: 0 | AG11: 0 | AH11: 0 | AI11: 0 | AJ11: 0 | AK11: =SUM(Y11:AJ11) -> 0 | AL11: =AK11/AK$6 -> 0 | AM11: =IFERROR(AK11/V11-1,0) -> 0
T12: 0 | V12: =SUM(J12:U12) -> 0 | W12: =V12/V$6 -> 0 | AK12: =SUM(Y12:AJ12) -> 0 | AL12: =AK12/AK$6 -> 0 | AM12: =IFERROR(AK12/V12-1,0) -> 0
A13: B - COSTO DE VENTA | E13: ( menos ) | I13: B - COSTO DE VENTA | J13: 1587187 | K13: 1598946 | L13: 1762983 | M13: 1637478 | N13: 1786406 | O13: 1641678 | P13: 1774734 | Q13: 1641744 | R13: 1859487 | S13: 2016399 | T13: =SUM(T14:T33) -> 1839210.3 | U13: =SUM(U14:U33) -> 1905032.4 | V13: =SUM(V14:V33) -> 21051285 | W13: =V13/V$6 -> 0.9394504 | Y13: =SUM(Y14:Y33) -> 1588830 | Z13: =SUM(Z14:Z33) -> 1610244.9 | AA13: =SUM(AA14:AA33) -> 1785659.8 | AB13: =SUM(AB14:AB33) -> 1666176.7 | AC13: =SUM(AC14:AC33) -> 1818164.5 | AD13: =SUM(AD14:AD33) -> 1787320.4 | AE13: =SUM(AE14:AE33) -> 1686695.5 | AF13: =SUM(AF14:AF33) -> 1686626.2 | ... AK13: =SUM(AK14:AK33) -> 21404370 | AL13: =AK13/AK$6 -> 0.90707653 | AM13: =IFERROR(AK13/V13-1,0) -> 0.016772622
