Workbook
Name AAI: #REF!
Name ALGDED: #REF!
Name BALANZADIC: #REF!
Name BALANZADIC14: #REF!
Name BGDECL: #REF!
Name CCF: #REF!
Name EJERCICIO: #REF!
Name ENERO16: #REF!
Name ENERO16: #REF!
Name ENERO16: #REF!
Name ENERO16: #REF!
Name ENERO16: #REF!
Name ENERO16: #REF!
Name ENERO16: #REF!
Name ENERO16: #REF!
Name ENERO16: #REF!
Name ENERO16: #REF!
Name ENERO16: #REF!
Name ERDECL: #REF!
Name inpc: #REF!
Name No_MES: #REF!
Name NombreRango1: #REF!
Name NombreRango1: #REF!
Name NombreRango1: #REF!
Name NombreRango1: #REF!
Name NombreRango1: #REF!
Name NombreRango1: #REF!
Name NombreRango1: #REF!
Name NombreRango1: #REF!
Name NombreRango1: #REF!
Name NombreRango1: #REF!
Name NombreRango1: #REF!
Name VAC: #REF!

Sheet Parametros JRZ
A1: ESTIMULO FISCAL | D1: IEPS
A2: REGULAR | B2: ='[1]Parametros Jrz'!$B$2 -> 3.41 | D2: REGULAR | E2: ='[1]Parametros Jrz'!$E$2 -> 0.522479 | I2: *Aumento en los ingresos en proporcion minima a la inflacion
A3: PREMIUM | B3: ='[1]Parametros Jrz'!$B$3 -> 2.86 | D3: PREMIUM | E3: ='[1]Parametros Jrz'!$E$3 -> 0.637522
A4: DIESEL | B4: ='[1]Parametros Jrz'!$B$4 -> 0 | D4: DIESEL | E4: ='[1]Parametros Jrz'!$E$4 -> 0.433626
A6: ='[1]Parametros Jrz'!$A$6 -> Precio final al 04 de sep 2024 | D6: Precio de venta sin IVA
A7: REGULAR | B7: ='[1]Parametros Jrz'!$B$7 -> 18.99 | D7: ='[1]Parametros Jrz'!$D$7 -> 17.583333
A8: PREMIUM | B8: ='[1]Parametros Jrz'!$B$8 -> 20.99 | D8: ='[1]Parametros Jrz'!$D$8 -> 19.435185
A9: DIESEL | B9: ='[1]Parametros Jrz'!$B$9 -> 23.79 | D9: ='[1]Parametros Jrz'!$D$9 -> 22.027778
A11: PRECIO DE VENTA sin IVA por LITRO
A12: Juarez | B12: ='[1]Parametros Jrz'!B12 -> 0.005 | C12: ='[1]Parametros Jrz'!C12 -> 0.005 | D12: ='[1]Parametros Jrz'!D12 -> 0.005 | E12: ='[1]Parametros Jrz'!E12 -> 0.005 | F12: ='[1]Parametros Jrz'!F12 -> 0.005 | G12: ='[1]Parametros Jrz'!G12 -> 0.005 | H12: ='[1]Parametros Jrz'!H12 -> 0.005 | I12: ='[1]Parametros Jrz'!I12 -> 0.005 | ... M12: ='[1]Parametros Jrz'!M12 -> 0.005
A13: P.V. | B13: Enero | C13: Febrero | D13: Marzo | E13: Abril | F13: Mayo | G13: Junio | H13: Julio | I13: Agosto | J13: Septiembre | K13: Octubre | L13: Noviembre | M13: Diciembre
A14: MAXIMA | B14: ='[1]Parametros Jrz'!B14 -> 17.583333 | C14: ='[1]Parametros Jrz'!C14 -> 17.67125 | D14: ='[1]Parametros Jrz'!D14 -> 17.759606 | E14: ='[1]Parametros Jrz'!E14 -> 17.848404 | F14: ='[1]Parametros Jrz'!F14 -> 17.937646 | G14: ='[1]Parametros Jrz'!G14 -> 18.027335 | H14: ='[1]Parametros Jrz'!H14 -> 18.117471 | I14: ='[1]Parametros Jrz'!I14 -> 18.208059 | ... M14: ='[1]Parametros Jrz'!M14 -> 18.57496
A15: SUPER | B15: ='[1]Parametros Jrz'!B15 -> 19.435185 | C15: ='[1]Parametros Jrz'!C15 -> 19.532361 | D15: ='[1]Parametros Jrz'!D15 -> 19.630023 | E15: ='[1]Parametros Jrz'!E15 -> 19.728173 | F15: ='[1]Parametros Jrz'!F15 -> 19.826814 | G15: ='[1]Parametros Jrz'!G15 -> 19.925948 | H15: ='[1]Parametros Jrz'!H15 -> 20.025578 | I15: ='[1]Parametros Jrz'!I15 -> 20.125706 | ... M15: ='[1]Parametros Jrz'!M15 -> 20.531249
A16: DIESEL | B16: ='[1]Parametros Jrz'!B16 -> 22.027778 | C16: ='[1]Parametros Jrz'!C16 -> 22.137917 | D16: ='[1]Parametros Jrz'!D16 -> 22.248606 | E16: ='[1]Parametros Jrz'!E16 -> 22.359849 | F16: ='[1]Parametros Jrz'!F16 -> 22.471649 | G16: ='[1]Parametros Jrz'!G16 -> 22.584007 | H16: ='[1]Parametros Jrz'!H16 -> 22.696927 | I16: ='[1]Parametros Jrz'!I16 -> 22.810411 | ... M16: ='[1]Parametros Jrz'!M16 -> 23.270053
A18: ='[1]Parametros Jrz'!$A$18 -> Inflación 2024 | B18: ='[1]Parametros Jrz'!$B$18 -> 1.04
A21: MARGEN estimado por litro
A22: Juarez | B22: Margen comercial ( precio - costo según factura )
A23: P.V. | B23: Enero | C23: Febrero | D23: Marzo | E23: Abril | F23: Mayo | G23: Junio | H23: Julio | I23: Agosto | J23: Septiembre | K23: Octubre | L23: Noviembre | M23: Diciembre
A24: MAXIMA | B24: ='[1]Parametros Jrz'!B24 -> 0 | C24: ='[1]Parametros Jrz'!C24 -> 0 | D24: ='[1]Parametros Jrz'!D24 -> 0 | E24: ='[1]Parametros Jrz'!E24 -> 0 | F24: ='[1]Parametros Jrz'!F24 -> 0 | G24: ='[1]Parametros Jrz'!G24 -> 0 | H24: ='[1]Parametros Jrz'!H24 -> 0 | I24: ='[1]Parametros Jrz'!I24 -> 0 | ... M24: ='[1]Parametros Jrz'!M24 -> 0
A25: SUPER | B25: ='[1]Parametros Jrz'!B25 -> 0 | C25: ='[1]Parametros Jrz'!C25 -> 0 | D25: ='[1]Parametros Jrz'!D25 -> 0 | E25: ='[1]Parametros Jrz'!E25 -> 0 | F25: ='[1]Parametros Jrz'!F25 -> 0 | G25: ='[1]Parametros Jrz'!G25 -> 0 | H25: ='[1]Parametros Jrz'!H25 -> 0 | I25: ='[1]Parametros Jrz'!I25 -> 0 | ... M25: ='[1]Parametros Jrz'!M25 -> 0
A26: DIESEL | B26: ='[1]Parametros Jrz'!B26 -> 0 | C26: ='[1]Parametros Jrz'!C26 -> 0 | D26: ='[1]Parametros Jrz'!D26 -> 0 | E26: ='[1]Parametros Jrz'!E26 -> 0 | F26: ='[1]Parametros Jrz'!F26 -> 0 | G26: ='[1]Parametros Jrz'!G26 -> 0 | H26: ='[1]Parametros Jrz'!H26 -> 0 | I26: ='[1]Parametros Jrz'!I26 -> 0 | ... M26: ='[1]Parametros Jrz'!M26 -> 0
B28: ='[1]Parametros Jrz'!$B$28 -> Margen por contrato de volumen con TESORO
A29: P.V. | B29: Enero | C29: Febrero | D29: Marzo | E29: Abril | F29: Mayo | G29: Junio | H29: Julio | I29: Agosto | J29: Septiembre | K29: Octubre | L29: Noviembre | M29: Diciembre | N29: Porcentaje
A30: MAXIMA | B30: ='[1]Parametros Jrz'!B30 -> 2.08 | C30: ='[1]Parametros Jrz'!C30 -> 2.28 | D30: ='[1]Parametros Jrz'!D30 -> 2.58 | E30: ='[1]Parametros Jrz'!E30 -> 2.21 | F30: ='[1]Parametros Jrz'!F30 -> 2.34 | G30: ='[1]Parametros Jrz'!G30 -> 2.06 | H30: ='[1]Parametros Jrz'!H30 -> 2.26 | I30: ='[1]Parametros Jrz'!I30 -> 2 | ... N30: ='[1]Parametros Jrz'!N30 -> 0.48 | P30: =AVERAGE(B30:M30) -> 2.4216667
A31: SUPER | B31: ='[1]Parametros Jrz'!B31 -> 3.37 | C31: ='[1]Parametros Jrz'!C31 -> 2.79 | D31: ='[1]Parametros Jrz'!D31 -> 2.2 | E31: ='[1]Parametros Jrz'!E31 -> 2.04 | F31: ='[1]Parametros Jrz'!F31 -> 2.95 | G31: ='[1]Parametros Jrz'!G31 -> 2.63 | H31: ='[1]Parametros Jrz'!H31 -> 2.63 | I31: ='[1]Parametros Jrz'!I31 -> 2.33 | ... N31: ='[1]Parametros Jrz'!N31 -> 0.47 | P31: =AVERAGE(B31:M31) -> 2.985
A32: DIESEL | B32: ='[1]Parametros Jrz'!B32 -> 1.08 | C32: ='[1]Parametros Jrz'!C32 -> 2.3 | D32: ='[1]Parametros Jrz'!D32 -> 2.84 | E32: ='[1]Parametros Jrz'!E32 -> 2.82 | F32: ='[1]Parametros Jrz'!F32 -> 3.38 | G32: ='[1]Parametros Jrz'!G32 -> 2.79 | H32: ='[1]Parametros Jrz'!H32 -> 2.49 | I32: ='[1]Parametros Jrz'!I32 -> 2.45 | ... N32: ='[1]Parametros Jrz'!N32 -> 0.8 | P32: =AVERAGE(B32:M32) -> 2.2766667
B34: ='[1]Parametros Jrz'!$B$34 -> Margen por contrato de volumen con MGC
A35: P.V. | B35: Enero | C35: Febrero | D35: Marzo | E35: Abril | F35: Mayo | G35: Junio | H35: Julio | I35: Agosto | J35: Septiembre | K35: Octubre | L35: Noviembre | M35: Diciembre | N35: Porcentaje
A36: MAXIMA | B36: ='[1]Parametros Jrz'!B36 -> 1.93 | C36: ='[1]Parametros Jrz'!C36 -> 2.19 | D36: ='[1]Parametros Jrz'!D36 -> 2.51 | E36: ='[1]Parametros Jrz'!E36 -> 2.16 | F36: ='[1]Parametros Jrz'!F36 -> 2.23 | G36: ='[1]Parametros Jrz'!G36 -> 2.04 | H36: ='[1]Parametros Jrz'!H36 -> 2.16 | I36: ='[1]Parametros Jrz'!I36 -> 1.98 | ... N36: ='[1]Parametros Jrz'!N36 -> 0.21 | P36: =AVERAGE(B36:M36) -> 2.2625
A37: SUPER | B37: ='[1]Parametros Jrz'!B37 -> 2.75 | C37: ='[1]Parametros Jrz'!C37 -> 2.08 | D37: ='[1]Parametros Jrz'!D37 -> 1.52 | E37: ='[1]Parametros Jrz'!E37 -> 1.44 | F37: ='[1]Parametros Jrz'!F37 -> 2.43 | G37: ='[1]Parametros Jrz'!G37 -> 1.63 | H37: ='[1]Parametros Jrz'!H37 -> 1.6 | I37: ='[1]Parametros Jrz'!I37 -> 1.82 | ... N37: ='[1]Parametros Jrz'!N37 -> 0.39 | P37: =AVERAGE(B37:M37) -> 2.2075
A38: DIESEL | B38: ='[1]Parametros Jrz'!B38 -> 0.62 | C38: ='[1]Parametros Jrz'!C38 -> 1.71 | D38: ='[1]Parametros Jrz'!D38 -> 2.66 | E38: ='[1]Parametros Jrz'!E38 -> 2.71 | F38: ='[1]Parametros Jrz'!F38 -> 3.36 | G38: ='[1]Parametros Jrz'!G38 -> 2.63 | H38: ='[1]Parametros Jrz'!H38 -> 2.41 | I38: ='[1]Parametros Jrz'!I38 -> 0 | ... N38: ='[1]Parametros Jrz'!N38 -> 0.1 | P38: =AVERAGE(B38:M38) -> 1.8808333
B40: ='[1]Parametros Jrz'!$B$40 -> Margen por contrato de volumen PREMIERGAS
A41: P.V. | B41: Enero | C41: Febrero | D41: Marzo | E41: Abril | F41: Mayo | G41: Junio | H41: Julio | I41: Agosto | J41: Septiembre | K41: Octubre | L41: Noviembre | M41: Diciembre | N41: Porcentaje
A42: MAXIMA | B42: ='[1]Parametros Jrz'!B42 -> 2.26 | C42: ='[1]Parametros Jrz'!C42 -> 2.71 | D42: ='[1]Parametros Jrz'!D42 -> 3.09 | E42: ='[1]Parametros Jrz'!E42 -> 2.69 | F42: ='[1]Parametros Jrz'!F42 -> 2.69 | G42: ='[1]Parametros Jrz'!G42 -> 2.48 | H42: ='[1]Parametros Jrz'!H42 -> 2.55 | I42: ='[1]Parametros Jrz'!I42 -> 2.38 | ... N42: ='[1]Parametros Jrz'!N42 -> 0.23 | P42: =AVERAGE(B42:M42) -> 2.7258333
A43: SUPER | B43: ='[1]Parametros Jrz'!B43 -> 2.89 | C43: ='[1]Parametros Jrz'!C43 -> 2.42 | D43: ='[1]Parametros Jrz'!D43 -> 2.38 | E43: ='[1]Parametros Jrz'!E43 -> 2.1 | F43: ='[1]Parametros Jrz'!F43 -> 2.84 | G43: ='[1]Parametros Jrz'!G43 -> 2.74 | H43: ='[1]Parametros Jrz'!H43 -> 2.02 | I43: ='[1]Parametros Jrz'!I43 -> 2.02 | ... N43: ='[1]Parametros Jrz'!N43 -> 0.14 | P43: =AVERAGE(B43:M43) -> 2.7516667
A44: DIESEL | B44: ='[1]Parametros Jrz'!B44 -> 1.93 | C44: ='[1]Parametros Jrz'!C44 -> 2.89 | D44: ='[1]Parametros Jrz'!D44 -> 3.55 | E44: ='[1]Parametros Jrz'!E44 -> 3.43 | F44: ='[1]Parametros Jrz'!F44 -> 3.82 | G44: ='[1]Parametros Jrz'!G44 -> 2.9 | H44: ='[1]Parametros Jrz'!H44 -> 3.38 | I44: ='[1]Parametros Jrz'!I44 -> 3.01 | ... N44: ='[1]Parametros Jrz'!N44 -> 0.05 | P44: =AVERAGE(B44:M44) -> 2.6741667
B46: ='[1]Parametros Jrz'!$B$46 -> Margen por contrato de volumen AMCA
A47: P.V. | B47: Enero | C47: Febrero | D47: Marzo | E47: Abril | F47: Mayo | G47: Junio | H47: Julio | I47: Agosto | J47: Septiembre | K47: Octubre | L47: Noviembre | M47: Diciembre | N47: Porcentaje
A48: MAXIMA | B48: ='[1]Parametros Jrz'!B48 -> 1.74 | C48: ='[1]Parametros Jrz'!C48 -> 2.48 | D48: ='[1]Parametros Jrz'!D48 -> 2.41 | E48: ='[1]Parametros Jrz'!E48 -> 2.34 | F48: ='[1]Parametros Jrz'!F48 -> 2.56 | G48: ='[1]Parametros Jrz'!G48 -> 2.46 | H48: ='[1]Parametros Jrz'!H48 -> 2.42 | I48: ='[1]Parametros Jrz'!I48 -> 2.89 | ... N48: ='[1]Parametros Jrz'!N48 -> 0.05 | P48: =AVERAGE(B48:M48) -> 2.2366667
A49: SUPER | B49: ='[1]Parametros Jrz'!B49 -> 0 | C49: ='[1]Parametros Jrz'!C49 -> 0 | D49: ='[1]Parametros Jrz'!D49 -> 0 | E49: ='[1]Parametros Jrz'!E49 -> 0 | F49: ='[1]Parametros Jrz'!F49 -> 0 | G49: ='[1]Parametros Jrz'!G49 -> 0 | H49: ='[1]Parametros Jrz'!H49 -> 0 | I49: ='[1]Parametros Jrz'!I49 -> 0 | ... N49: ='[1]Parametros Jrz'!N49 -> 0 | P49: =AVERAGE(B49:M49) -> 0
A50: DIESEL | B50: ='[1]Parametros Jrz'!B50 -> 0 | C50: ='[1]Parametros Jrz'!C50 -> 0 | D50: ='[1]Parametros Jrz'!D50 -> 0 | E50: ='[1]Parametros Jrz'!E50 -> 0 | F50: ='[1]Parametros Jrz'!F50 -> 0 | G50: ='[1]Parametros Jrz'!G50 -> 0 | H50: ='[1]Parametros Jrz'!H50 -> 0 | I50: ='[1]Parametros Jrz'!I50 -> 0 | ... N50: ='[1]Parametros Jrz'!N50 -> 0 | P50: =AVERAGE(B50:M50) -> 0
B52: ='[1]Parametros Jrz'!$B$52 -> Margen por contrato de volumen OTROS
A53: P.V. | B53: Enero | C53: Febrero | D53: Marzo | E53: Abril | F53: Mayo | G53: Junio | H53: Julio | I53: Agosto | J53: Septiembre | K53: Octubre | L53: Noviembre | M53: Diciembre | N53: Porcentaje
A54: MAXIMA | B54: ='[1]Parametros Jrz'!B54 -> 2.86 | C54: ='[1]Parametros Jrz'!C54 -> 2.99 | D54: ='[1]Parametros Jrz'!D54 -> 2.31 | E54: ='[1]Parametros Jrz'!E54 -> 2.26 | F54: ='[1]Parametros Jrz'!F54 -> 2.75 | G54: ='[1]Parametros Jrz'!G54 -> 0 | H54: ='[1]Parametros Jrz'!H54 -> 0 | I54: ='[1]Parametros Jrz'!I54 -> 2.37 | ... N54: ='[1]Parametros Jrz'!N54 -> 0.03 | P54: =AVERAGE(B54:M54) -> 2.0883333
A55: SUPER | B55: ='[1]Parametros Jrz'!B55 -> 0 | C55: ='[1]Parametros Jrz'!C55 -> 0 | D55: ='[1]Parametros Jrz'!D55 -> 0 | E55: ='[1]Parametros Jrz'!E55 -> 0 | F55: ='[1]Parametros Jrz'!F55 -> 0 | G55: ='[1]Parametros Jrz'!G55 -> 0 | H55: ='[1]Parametros Jrz'!H55 -> 0 | I55: ='[1]Parametros Jrz'!I55 -> 0 | ... N55: ='[1]Parametros Jrz'!N55 -> 0 | P55: =AVERAGE(B55:M55) -> 0
A56: DIESEL | B56: ='[1]Parametros Jrz'!B56 -> 2.98 | C56: ='[1]Parametros Jrz'!C56 -> 0 | D56: ='[1]Parametros Jrz'!D56 -> 3.22 | E56: ='[1]Parametros Jrz'!E56 -> 0 | F56: ='[1]Parametros Jrz'!F56 -> 3.13 | G56: ='[1]Parametros Jrz'!G56 -> 2.56 | H56: ='[1]Parametros Jrz'!H56 -> 1.96 | I56: ='[1]Parametros Jrz'!I56 -> 0 | ... N56: ='[1]Parametros Jrz'!N56 -> 0.05 | P56: =AVERAGE(B56:M56) -> 1.885
A58: CENTAVOS POR LITRO (FLETE) | M58: MAXIMA | N58: ='[1]Parametros Jrz'!$N$59 -> 1
A59: MAXIMA | B59: ='[1]Parametros Jrz'!$B$60 -> 0 | M59: SUPER | N59: ='[1]Parametros Jrz'!$N$60 -> 1
A60: SUPER | B60: ='[1]Parametros Jrz'!$B$61 -> 0 | M60: DIESEL | N60: ='[1]Parametros Jrz'!$N$61 -> 1
A61: DIESEL | B61: ='[1]Parametros Jrz'!$B$62 -> 0
A66: DESCUENTOS
A67: PRECIO REGULAR | C67: Enero | D67: Febrero | E67: Marzo | F67: Abril | G67: Mayo | H67: Junio | I67: Julio | J67: Agosto | K67: Septiembre | L67: Octubre | M67: Noviembre | N67: Diciembre
A68: 23214 | B68: HERMANOS ESCOBAR | C68: ='[1]Parametros Jrz'!C69 -> 0 | D68: ='[1]Parametros Jrz'!D69 -> 0 | E68: ='[1]Parametros Jrz'!E69 -> 0 | F68: ='[1]Parametros Jrz'!F69 -> 0 | G68: ='[1]Parametros Jrz'!G69 -> 0 | H68: ='[1]Parametros Jrz'!H69 -> 0 | I68: ='[1]Parametros Jrz'!I69 -> 0 | J68: ='[1]Parametros Jrz'!J69 -> 0 | ... N68: ='[1]Parametros Jrz'!N69 -> 0
A69: 1149 | B69: LERDO | C69: ='[1]Parametros Jrz'!C70 -> 0 | D69: ='[1]Parametros Jrz'!D70 -> 0 | E69: ='[1]Parametros Jrz'!E70 -> 0 | F69: ='[1]Parametros Jrz'!F70 -> 0 | G69: ='[1]Parametros Jrz'!G70 -> 0 | H69: ='[1]Parametros Jrz'!H70 -> 0 | I69: ='[1]Parametros Jrz'!I70 -> 0 | J69: ='[1]Parametros Jrz'!J70 -> 0 | ... N69: ='[1]Parametros Jrz'!N70 -> 0
A70: 1163 | B70: TECNOLOGICO | C70: ='[1]Parametros Jrz'!C71 -> 0 | D70: ='[1]Parametros Jrz'!D71 -> 0 | E70: ='[1]Parametros Jrz'!E71 -> 0 | F70: ='[1]Parametros Jrz'!F71 -> 0 | G70: ='[1]Parametros Jrz'!G71 -> 0 | H70: ='[1]Parametros Jrz'!H71 -> 0 | I70: ='[1]Parametros Jrz'!I71 -> 0 | J70: ='[1]Parametros Jrz'!J71 -> 0 | ... N70: ='[1]Parametros Jrz'!N71 -> 0
A71: 1376 | B71: DELICIAS | C71: ='[1]Parametros Jrz'!C72 -> 0 | D71: ='[1]Parametros Jrz'!D72 -> 0 | E71: ='[1]Parametros Jrz'!E72 -> 0 | F71: ='[1]Parametros Jrz'!F72 -> 0 | G71: ='[1]Parametros Jrz'!G72 -> 0 | H71: ='[1]Parametros Jrz'!H72 -> 0 | I71: ='[1]Parametros Jrz'!I72 -> 0 | J71: ='[1]Parametros Jrz'!J72 -> 0 | ... N71: ='[1]Parametros Jrz'!N72 -> 0
A72: 2172 | B72: PARRAL | C72: ='[1]Parametros Jrz'!C73 -> 0 | D72: ='[1]Parametros Jrz'!D73 -> 0 | E72: ='[1]Parametros Jrz'!E73 -> 0 | F72: ='[1]Parametros Jrz'!F73 -> 0 | G72: ='[1]Parametros Jrz'!G73 -> 0 | H72: ='[1]Parametros Jrz'!H73 -> 0 | I72: ='[1]Parametros Jrz'!I73 -> 0 | J72: ='[1]Parametros Jrz'!J73 -> 0 | ... N72: ='[1]Parametros Jrz'!N73 -> 0
A73: 2526 | B73: LOPEZ | C73: ='[1]Parametros Jrz'!C74 -> 0 | D73: ='[1]Parametros Jrz'!D74 -> 0 | E73: ='[1]Parametros Jrz'!E74 -> 0 | F73: ='[1]Parametros Jrz'!F74 -> 0 | G73: ='[1]Parametros Jrz'!G74 -> 0 | H73: ='[1]Parametros Jrz'!H74 -> 0 | I73: ='[1]Parametros Jrz'!I74 -> 0 | J73: ='[1]Parametros Jrz'!J74 -> 0 | ... N73: ='[1]Parametros Jrz'!N74 -> 0
A74: 4179 | B74: GEMELA CH | C74: ='[1]Parametros Jrz'!C75 -> 0 | D74: ='[1]Parametros Jrz'!D75 -> 0 | E74: ='[1]Parametros Jrz'!E75 -> 0 | F74: ='[1]Parametros Jrz'!F75 -> 0 | G74: ='[1]Parametros Jrz'!G75 -> 0 | H74: ='[1]Parametros Jrz'!H75 -> 0 | I74: ='[1]Parametros Jrz'!I75 -> 0 | J74: ='[1]Parametros Jrz'!J75 -> 0 | ... N74: ='[1]Parametros Jrz'!N75 -> 0
A75: 4188 | B75: GEMELA G | C75: ='[1]Parametros Jrz'!C76 -> 0 | D75: ='[1]Parametros Jrz'!D76 -> 0 | E75: ='[1]Parametros Jrz'!E76 -> 0 | F75: ='[1]Parametros Jrz'!F76 -> 0 | G75: ='[1]Parametros Jrz'!G76 -> 0 | H75: ='[1]Parametros Jrz'!H76 -> 0 | I75: ='[1]Parametros Jrz'!I76 -> 0 | J75: ='[1]Parametros Jrz'!J76 -> 0 | ... N75: ='[1]Parametros Jrz'!N76 -> 0
A76: 5317 | B76: MUNICIPIO | C76: ='[1]Parametros Jrz'!C77 -> 0 | D76: ='[1]Parametros Jrz'!D77 -> 0 | E76: ='[1]Parametros Jrz'!E77 -> 0 | F76: ='[1]Parametros Jrz'!F77 -> 0 | G76: ='[1]Parametros Jrz'!G77 -> 0 | H76: ='[1]Parametros Jrz'!H77 -> 0 | I76: ='[1]Parametros Jrz'!I77 -> 0 | J76: ='[1]Parametros Jrz'!J77 -> 0 | ... N76: ='[1]Parametros Jrz'!N77 -> 0
A77: 6410 | B77: MISIONES | C77: ='[1]Parametros Jrz'!C78 -> 0 | D77: ='[1]Parametros Jrz'!D78 -> 0 | E77: ='[1]Parametros Jrz'!E78 -> 0 | F77: ='[1]Parametros Jrz'!F78 -> 0 | G77: ='[1]Parametros Jrz'!G78 -> 0 | H77: ='[1]Parametros Jrz'!H78 -> 0 | I77: ='[1]Parametros Jrz'!I78 -> 0 | J77: ='[1]Parametros Jrz'!J78 -> 0 | ... N77: ='[1]Parametros Jrz'!N78 -> 0
A78: 6947 | B78: P PALOS | C78: ='[1]Parametros Jrz'!C79 -> 0 | D78: ='[1]Parametros Jrz'!D79 -> 0 | E78: ='[1]Parametros Jrz'!E79 -> 0 | F78: ='[1]Parametros Jrz'!F79 -> 0 | G78: ='[1]Parametros Jrz'!G79 -> 0 | H78: ='[1]Parametros Jrz'!H79 -> 0 | I78: ='[1]Parametros Jrz'!I79 -> 0 | J78: ='[1]Parametros Jrz'!J79 -> 0 | ... N78: ='[1]Parametros Jrz'!N79 -> 0
A79: 7167 | B79: M MADRID | C79: ='[1]Parametros Jrz'!C80 -> 0 | D79: ='[1]Parametros Jrz'!D80 -> 0 | E79: ='[1]Parametros Jrz'!E80 -> 0 | F79: ='[1]Parametros Jrz'!F80 -> 0 | G79: ='[1]Parametros Jrz'!G80 -> 0 | H79: ='[1]Parametros Jrz'!H80 -> 0 | I79: ='[1]Parametros Jrz'!I80 -> 0 | J79: ='[1]Parametros Jrz'!J80 -> 0 | ... N79: ='[1]Parametros Jrz'!N80 -> 0
... A93: 3184 | B93: PRAXEDIS | C93: ='[1]Parametros Jrz'!C94 -> 0 | D93: ='[1]Parametros Jrz'!D94 -> 0 | E93: ='[1]Parametros Jrz'!E94 -> 0 | F93: ='[1]Parametros Jrz'!F94 -> 0 | G93: ='[1]Parametros Jrz'!G94 -> 0 | H93: ='[1]Parametros Jrz'!H94 -> 0 | I93: ='[1]Parametros Jrz'!I94 -> 0 | J93: ='[1]Parametros Jrz'!J94 -> 0 | ... N93: ='[1]Parametros Jrz'!N94 -> 0
A95: PRECIO PREMIUM | C95: Enero | D95: Febrero | E95: Marzo | F95: Abril | G95: Mayo | H95: Junio | I95: Julio | J95: Agosto | K95: Septiembre | L95: Octubre | M95: Noviembre | N95: Diciembre
B96: HERMANOS ESCOBAR | C96: ='[1]Parametros Jrz'!C97 -> 0 | D96: ='[1]Parametros Jrz'!D97 -> 0 | E96: ='[1]Parametros Jrz'!E97 -> 0 | F96: ='[1]Parametros Jrz'!F97 -> 0 | G96: ='[1]Parametros Jrz'!G97 -> 0 | H96: ='[1]Parametros Jrz'!H97 -> 0 | I96: ='[1]Parametros Jrz'!I97 -> 0 | J96: ='[1]Parametros Jrz'!J97 -> 0 | ... N96: ='[1]Parametros Jrz'!N97 -> 0
A97: 1149 | B97: LERDO | C97: ='[1]Parametros Jrz'!C98 -> 0 | D97: ='[1]Parametros Jrz'!D98 -> 0 | E97: ='[1]Parametros Jrz'!E98 -> 0 | F97: ='[1]Parametros Jrz'!F98 -> 0 | G97: ='[1]Parametros Jrz'!G98 -> 0 | H97: ='[1]Parametros Jrz'!H98 -> 0 | I97: ='[1]Parametros Jrz'!I98 -> 0 | J97: ='[1]Parametros Jrz'!J98 -> 0 | ... N97: ='[1]Parametros Jrz'!N98 -> 0
A98: 1163 | B98: TECNOLOGICO | C98: ='[1]Parametros Jrz'!C99 -> 0 | D98: ='[1]Parametros Jrz'!D99 -> 0 | E98: ='[1]Parametros Jrz'!E99 -> 0 | F98: ='[1]Parametros Jrz'!F99 -> 0 | G98: ='[1]Parametros Jrz'!G99 -> 0 | H98: ='[1]Parametros Jrz'!H99 -> 0 | I98: ='[1]Parametros Jrz'!I99 -> 0 | J98: ='[1]Parametros Jrz'!J99 -> 0 | ... N98: ='[1]Parametros Jrz'!N99 -> 0
A99: 1376 | B99: DELICIAS | C99: ='[1]Parametros Jrz'!C100 -> 0 | D99: ='[1]Parametros Jrz'!D100 -> 0 | E99: ='[1]Parametros Jrz'!E100 -> 0 | F99: ='[1]Parametros Jrz'!F100 -> 0 | G99: ='[1]Parametros Jrz'!G100 -> 0 | H99: ='[1]Parametros Jrz'!H100 -> 0 | I99: ='[1]Parametros Jrz'!I100 -> 0 | J99: ='[1]Parametros Jrz'!J100 -> 0 | ... N99: ='[1]Parametros Jrz'!N100 -> 0
A100: 2172 | B100: PARRAL | C100: ='[1]Parametros Jrz'!C101 -> 0 | D100: ='[1]Parametros Jrz'!D101 -> 0 | E100: ='[1]Parametros Jrz'!E101 -> 0 | F100: ='[1]Parametros Jrz'!F101 -> 0 | G100: ='[1]Parametros Jrz'!G101 -> 0 | H100: ='[1]Parametros Jrz'!H101 -> 0 | I100: ='[1]Parametros Jrz'!I101 -> 0 | J100: ='[1]Parametros Jrz'!J101 -> 0 | ... N100: ='[1]Parametros Jrz'!N101 -> 0
A101: 2526 | B101: LOPEZ | C101: ='[1]Parametros Jrz'!C102 -> 0 | D101: ='[1]Parametros Jrz'!D102 -> 0 | E101: ='[1]Parametros Jrz'!E102 -> 0 | F101: ='[1]Parametros Jrz'!F102 -> 0 | G101: ='[1]Parametros Jrz'!G102 -> 0 | H101: ='[1]Parametros Jrz'!H102 -> 0 | I101: ='[1]Parametros Jrz'!I102 -> 0 | J101: ='[1]Parametros Jrz'!J102 -> 0 | ... N101: ='[1]Parametros Jrz'!N102 -> 0
A102: 4179 | B102: GEMELA CH | C102: ='[1]Parametros Jrz'!C103 -> 0 | D102: ='[1]Parametros Jrz'!D103 -> 0 | E102: ='[1]Parametros Jrz'!E103 -> 0 | F102: ='[1]Parametros Jrz'!F103 -> 0 | G102: ='[1]Parametros Jrz'!G103 -> 0 | H102: ='[1]Parametros Jrz'!H103 -> 0 | I102: ='[1]Parametros Jrz'!I103 -> 0 | J102: ='[1]Parametros Jrz'!J103 -> 0 | ... N102: ='[1]Parametros Jrz'!N103 -> 0
A103: 4188 | B103: GEMELA G | C103: ='[1]Parametros Jrz'!C104 -> 0 | D103: ='[1]Parametros Jrz'!D104 -> 0 | E103: ='[1]Parametros Jrz'!E104 -> 0 | F103: ='[1]Parametros Jrz'!F104 -> 0 | G103: ='[1]Parametros Jrz'!G104 -> 0 | H103: ='[1]Parametros Jrz'!H104 -> 0 | I103: ='[1]Parametros Jrz'!I104 -> 0 | J103: ='[1]Parametros Jrz'!J104 -> 0 | ... N103: ='[1]Parametros Jrz'!N104 -> 0
A104: 5317 | B104: MUNICIPIO | C104: ='[1]Parametros Jrz'!C105 -> 0 | D104: ='[1]Parametros Jrz'!D105 -> 0 | E104: ='[1]Parametros Jrz'!E105 -> 0 | F104: ='[1]Parametros Jrz'!F105 -> 0 | G104: ='[1]Parametros Jrz'!G105 -> 0 | H104: ='[1]Parametros Jrz'!H105 -> 0 | I104: ='[1]Parametros Jrz'!I105 -> 0 | J104: ='[1]Parametros Jrz'!J105 -> 0 | ... N104: ='[1]Parametros Jrz'!N105 -> 0
A105: 6410 | B105: MISIONES | C105: ='[1]Parametros Jrz'!C106 -> 0 | D105: ='[1]Parametros Jrz'!D106 -> 0 | E105: ='[1]Parametros Jrz'!E106 -> 0 | F105: ='[1]Parametros Jrz'!F106 -> 0 | G105: ='[1]Parametros Jrz'!G106 -> 0 | H105: ='[1]Parametros Jrz'!H106 -> 0 | I105: ='[1]Parametros Jrz'!I106 -> 0 | J105: ='[1]Parametros Jrz'!J106 -> 0 | ... N105: ='[1]Parametros Jrz'!N106 -> 0
A106: 6947 | B106: P PALOS | C106: ='[1]Parametros Jrz'!C107 -> 0 | D106: ='[1]Parametros Jrz'!D107 -> 0 | E106: ='[1]Parametros Jrz'!E107 -> 0 | F106: ='[1]Parametros Jrz'!F107 -> 0 | G106: ='[1]Parametros Jrz'!G107 -> 0 | H106: ='[1]Parametros Jrz'!H107 -> 0 | I106: ='[1]Parametros Jrz'!I107 -> 0 | J106: ='[1]Parametros Jrz'!J107 -> 0 | ... N106: ='[1]Parametros Jrz'!N107 -> 0
A107: 7167 | B107: M MADRID | C107: ='[1]Parametros Jrz'!C108 -> 0 | D107: ='[1]Parametros Jrz'!D108 -> 0 | E107: ='[1]Parametros Jrz'!E108 -> 0 | F107: ='[1]Parametros Jrz'!F108 -> 0 | G107: ='[1]Parametros Jrz'!G108 -> 0 | H107: ='[1]Parametros Jrz'!H108 -> 0 | I107: ='[1]Parametros Jrz'!I108 -> 0 | J107: ='[1]Parametros Jrz'!J108 -> 0 | ... N107: ='[1]Parametros Jrz'!N108 -> 0
A108: 5465 | B108: AZTECAS | C108: ='[1]Parametros Jrz'!C109 -> 0 | D108: ='[1]Parametros Jrz'!D109 -> 0 | E108: ='[1]Parametros Jrz'!E109 -> 0 | F108: ='[1]Parametros Jrz'!F109 -> 0 | G108: ='[1]Parametros Jrz'!G109 -> 0 | H108: ='[1]Parametros Jrz'!H109 -> 0 | I108: ='[1]Parametros Jrz'!I109 -> 0 | J108: ='[1]Parametros Jrz'!J109 -> 0 | ... N108: ='[1]Parametros Jrz'!N109 -> 0
... A121: 3184 | B121: PRAXEDIS | C121: ='[1]Parametros Jrz'!C122 -> 0 | D121: ='[1]Parametros Jrz'!D122 -> 0 | E121: ='[1]Parametros Jrz'!E122 -> 0 | F121: ='[1]Parametros Jrz'!F122 -> 0 | G121: ='[1]Parametros Jrz'!G122 -> 0 | H121: ='[1]Parametros Jrz'!H122 -> 0 | I121: ='[1]Parametros Jrz'!I122 -> 0 | J121: ='[1]Parametros Jrz'!J122 -> 0 | ... N121: ='[1]Parametros Jrz'!N122 -> 0
A124: PRECIO DIESEL | C124: Enero | D124: Febrero | E124: Marzo | F124: Abril | G124: Mayo | H124: Junio | I124: Julio | J124: Agosto | K124: Septiembre | L124: Octubre | M124: Noviembre | N124: Diciembre
B125: HERMANOS ESCOBAR | C125: ='[1]Parametros Jrz'!C126 -> 0 | D125: ='[1]Parametros Jrz'!D126 -> 0 | E125: ='[1]Parametros Jrz'!E126 -> 0 | F125: ='[1]Parametros Jrz'!F126 -> 0 | G125: ='[1]Parametros Jrz'!G126 -> 0 | H125: ='[1]Parametros Jrz'!H126 -> 0 | I125: ='[1]Parametros Jrz'!I126 -> 0 | J125: ='[1]Parametros Jrz'!J126 -> 0 | ... N125: ='[1]Parametros Jrz'!N126 -> 0
A126: 1149 | B126: LERDO | C126: ='[1]Parametros Jrz'!C127 -> 0 | D126: ='[1]Parametros Jrz'!D127 -> 0 | E126: ='[1]Parametros Jrz'!E127 -> 0 | F126: ='[1]Parametros Jrz'!F127 -> 0 | G126: ='[1]Parametros Jrz'!G127 -> 0 | H126: ='[1]Parametros Jrz'!H127 -> 0 | I126: ='[1]Parametros Jrz'!I127 -> 0 | J126: ='[1]Parametros Jrz'!J127 -> 0 | ... N126: ='[1]Parametros Jrz'!N127 -> 0
A127: 1163 | B127: TECNOLOGICO | C127: ='[1]Parametros Jrz'!C128 -> 0 | D127: ='[1]Parametros Jrz'!D128 -> 0 | E127: ='[1]Parametros Jrz'!E128 -> 0 | F127: ='[1]Parametros Jrz'!F128 -> 0 | G127: ='[1]Parametros Jrz'!G128 -> 0 | H127: ='[1]Parametros Jrz'!H128 -> 0 | I127: ='[1]Parametros Jrz'!I128 -> 0 | J127: ='[1]Parametros Jrz'!J128 -> 0 | ... N127: ='[1]Parametros Jrz'!N128 -> 0
A128: 1376 | B128: DELICIAS | C128: ='[1]Parametros Jrz'!C129 -> 0 | D128: ='[1]Parametros Jrz'!D129 -> 0 | E128: ='[1]Parametros Jrz'!E129 -> 0 | F128: ='[1]Parametros Jrz'!F129 -> 0 | G128: ='[1]Parametros Jrz'!G129 -> 0 | H128: ='[1]Parametros Jrz'!H129 -> 0 | I128: ='[1]Parametros Jrz'!I129 -> 0 | J128: ='[1]Parametros Jrz'!J129 -> 0 | ... N128: ='[1]Parametros Jrz'!N129 -> 0
A129: 2172 | B129: PARRAL | C129: ='[1]Parametros Jrz'!C130 -> 0 | D129: ='[1]Parametros Jrz'!D130 -> 0 | E129: ='[1]Parametros Jrz'!E130 -> 0 | F129: ='[1]Parametros Jrz'!F130 -> 0 | G129: ='[1]Parametros Jrz'!G130 -> 0 | H129: ='[1]Parametros Jrz'!H130 -> 0 | I129: ='[1]Parametros Jrz'!I130 -> 0 | J129: ='[1]Parametros Jrz'!J130 -> 0 | ... N129: ='[1]Parametros Jrz'!N130 -> 0
A130: 2526 | B130: LOPEZ | C130: ='[1]Parametros Jrz'!C131 -> 0 | D130: ='[1]Parametros Jrz'!D131 -> 0 | E130: ='[1]Parametros Jrz'!E131 -> 0 | F130: ='[1]Parametros Jrz'!F131 -> 0 | G130: ='[1]Parametros Jrz'!G131 -> 0 | H130: ='[1]Parametros Jrz'!H131 -> 0 | I130: ='[1]Parametros Jrz'!I131 -> 0 | J130: ='[1]Parametros Jrz'!J131 -> 0 | ... N130: ='[1]Parametros Jrz'!N131 -> 0
A131: 4179 | B131: GEMELA CH | C131: ='[1]Parametros Jrz'!C132 -> 0 | D131: ='[1]Parametros Jrz'!D132 -> 0 | E131: ='[1]Parametros Jrz'!E132 -> 0 | F131: ='[1]Parametros Jrz'!F132 -> 0 | G131: ='[1]Parametros Jrz'!G132 -> 0 | H131: ='[1]Parametros Jrz'!H132 -> 0 | I131: ='[1]Parametros Jrz'!I132 -> 0 | J131: ='[1]Parametros Jrz'!J132 -> 0 | ... N131: ='[1]Parametros Jrz'!N132 -> 0
A132: 4188 | B132: GEMELA G | C132: ='[1]Parametros Jrz'!C133 -> 0 | D132: ='[1]Parametros Jrz'!D133 -> 0 | E132: ='[1]Parametros Jrz'!E133 -> 0 | F132: ='[1]Parametros Jrz'!F133 -> 0 | G132: ='[1]Parametros Jrz'!G133 -> 0 | H132: ='[1]Parametros Jrz'!H133 -> 0 | I132: ='[1]Parametros Jrz'!I133 -> 0 | J132: ='[1]Parametros Jrz'!J133 -> 0 | ... N132: ='[1]Parametros Jrz'!N133 -> 0
A133: 5317 | B133: MUNICIPIO | C133: ='[1]Parametros Jrz'!C134 -> 0 | D133: ='[1]Parametros Jrz'!D134 -> 0 | E133: ='[1]Parametros Jrz'!E134 -> 0 | F133: ='[1]Parametros Jrz'!F134 -> 0 | G133: ='[1]Parametros Jrz'!G134 -> 0 | H133: ='[1]Parametros Jrz'!H134 -> 0 | I133: ='[1]Parametros Jrz'!I134 -> 0 | J133: ='[1]Parametros Jrz'!J134 -> 0 | ... N133: ='[1]Parametros Jrz'!N134 -> 0
A134: 6410 | B134: MISIONES | C134: ='[1]Parametros Jrz'!C135 -> 0 | D134: ='[1]Parametros Jrz'!D135 -> 0 | E134: ='[1]Parametros Jrz'!E135 -> 0 | F134: ='[1]Parametros Jrz'!F135 -> 0 | G134: ='[1]Parametros Jrz'!G135 -> 0 | H134: ='[1]Parametros Jrz'!H135 -> 0 | I134: ='[1]Parametros Jrz'!I135 -> 0 | J134: ='[1]Parametros Jrz'!J135 -> 0 | ... N134: ='[1]Parametros Jrz'!N135 -> 0
A135: 6947 | B135: P PALOS | C135: ='[1]Parametros Jrz'!C136 -> 0 | D135: ='[1]Parametros Jrz'!D136 -> 0 | E135: ='[1]Parametros Jrz'!E136 -> 0 | F135: ='[1]Parametros Jrz'!F136 -> 0 | G135: ='[1]Parametros Jrz'!G136 -> 0 | H135: ='[1]Parametros Jrz'!H136 -> 0 | I135: ='[1]Parametros Jrz'!I136 -> 0 | J135: ='[1]Parametros Jrz'!J136 -> 0 | ... N135: ='[1]Parametros Jrz'!N136 -> 0
A136: 7167 | B136: M MADRID | C136: ='[1]Parametros Jrz'!C137 -> 0 | D136: ='[1]Parametros Jrz'!D137 -> 0 | E136: ='[1]Parametros Jrz'!E137 -> 0 | F136: ='[1]Parametros Jrz'!F137 -> 0 | G136: ='[1]Parametros Jrz'!G137 -> 0 | H136: ='[1]Parametros Jrz'!H137 -> 0 | I136: ='[1]Parametros Jrz'!I137 -> 0 | J136: ='[1]Parametros Jrz'!J137 -> 0 | ... N136: ='[1]Parametros Jrz'!N137 -> 0
A137: 5465 | B137: AZTECAS | C137: ='[1]Parametros Jrz'!C138 -> 0 | D137: ='[1]Parametros Jrz'!D138 -> 0 | E137: ='[1]Parametros Jrz'!E138 -> 0 | F137: ='[1]Parametros Jrz'!F138 -> 0 | G137: ='[1]Parametros Jrz'!G138 -> 0 | H137: ='[1]Parametros Jrz'!H138 -> 0 | I137: ='[1]Parametros Jrz'!I138 -> 0 | J137: ='[1]Parametros Jrz'!J138 -> 0 | ... N137: ='[1]Parametros Jrz'!N138 -> 0
... A150: 3184 | B150: PRAXEDIS | C150: ='[1]Parametros Jrz'!C151 -> 0 | D150: ='[1]Parametros Jrz'!D151 -> 0 | E150: ='[1]Parametros Jrz'!E151 -> 0 | F150: ='[1]Parametros Jrz'!F151 -> 0 | G150: ='[1]Parametros Jrz'!G151 -> 0 | H150: ='[1]Parametros Jrz'!H151 -> 0 | I150: ='[1]Parametros Jrz'!I151 -> 0 | J150: ='[1]Parametros Jrz'!J151 -> 0 | ... N150: ='[1]Parametros Jrz'!N151 -> 0
A154: WINDSTAR- REGULAR | C154: ENE | D154: FEB | E154: MAR | F154: ABR | G154: MAY | H154: JUN | I154: JUL | J154: AGO | K154: SEP | L154: OCT | M154: NOV | N154: DIC
A155: 1147 | B155: MALECON | C155: 0 | D155: 0 | E155: 0 | F155: 0 | G155: 0 | H155: 0 | I155: 0 | J155: 0 | K155: 0 | L155: 0 | M155: 0 | N155: 0
A156: 1149 | B156: LERDO | C156: 0 | D156: 0 | E156: 0 | F156: 0 | G156: 0 | H156: 0 | I156: 0 | J156: 0 | K156: 0 | L156: 0 | M156: 0 | N156: 0
A157: 1163 | B157: TECNOLOGICO | C157: 0 | D157: 0 | E157: 0 | F157: 0 | G157: 0 | H157: 0 | I157: 0 | J157: 0 | K157: 0 | L157: 0 | M157: 0 | N157: 0
A158: 1376 | B158: DELICIAS | C158: 0 | D158: 0 | E158: 0 | F158: 0 | G158: 0 | H158: 0 | I158: 0 | J158: 0 | K158: 0 | L158: 0 | M158: 0 | N158: 0
...

Sheet EDO RESULTADOS TOTAL EST.
I1: 1147 | J1: 2 | K1: 3 | L1: 4 | M1: 5 | N1: 6 | O1: 7 | Y1: 2 | Z1: =+Y1+1 -> 3 | AA1: =+Z1+1 -> 4 | AB1: =+AA1+1 -> 5 | AC1: =+AB1+1 -> 6 | AD1: =+AC1+1 -> 7 | AE1: =+AD1+1 -> 8 | AF1: =+AE1+1 -> 9 | AG1: =+AF1+1 -> 10 | ... AK1: =+AJ1+1 -> 14 | AM1: 17
J2: 2024 | V2: TOTAL ANUAL | Y2: 2025 | AK2: TOTAL ANUAL
J3: ENE | K3: FEB | L3: MAR | M3: ABR | N3: MAY | O3: JUN | P3: JUL | Q3: AGO | R3: SEP | S3: OCT | T3: NOV | U3: DIC | V3: 2024 | W3: % Part | Y3: ENE | Z3: FEB | AA3: MAR | AB3: ABR | AC3: MAY | AD3: JUN | AE3: JUL | AF3: AGO | AG3: SEP | AH3: OCT | AI3: NOV | AJ3: DIC | AK3: 2025 | AL3: % Part | AM3: Var vs AA%
I4: INGRESOS
A6: A - INGRESOS | E6: ( mas ) | I6: A - INGRESOS | J6: =SUM(J7:J12) -> 69452870 | K6: =SUM(K7:K12) -> 68676679 | L6: =SUM(L7:L12) -> 74038427 | M6: =SUM(M7:M12) -> 69224559 | N6: =SUM(N7:N12) -> 77933808 | O6: =SUM(O7:O12) -> 77696456 | P6: =SUM(P7:P12) -> 76552162 | Q6: =SUM(Q7:Q12) -> 70332214 | ... V6: =SUM(V7:V12) -> 8.9616389e+08 | W6: =V6/V$6 -> 1 | Y6: =SUM(Y7:Y12) -> 69733029 | Z6: =SUM(Z7:Z12) -> 69139078 | AA6: =SUM(AA7:AA12) -> 76712717 | AB6: =SUM(AB7:AB12) -> 72969416 | AC6: =SUM(AC7:AC12) -> 84041095 | AD6: =SUM(AD7:AD12) -> 83841112 | AE6: =SUM(AE7:AE12) -> 83649040 | AF6: =SUM(AF7:AF12) -> 85393702 | ... AK6: =SUM(AK7:AK12) -> 9.6317828e+08 | AL6: =AK6/AK$6 -> 1 | AM6: =IFERROR(AK6/V6-1,0) -> 0.074779166
A7: A - INGRESOS | B7: estaciones | C7: INGRESOS MAGNA | D7: INGRESOS FORANEOS MAGNA | I7: MAXIMA | J7: =SUM(A:B!J7) -> 52024925 | K7: =SUM(A:B!K7) -> 51666858 | L7: =SUM(A:B!L7) -> 55424481 | M7: =SUM(A:B!M7) -> 52126321 | N7: =SUM(A:B!N7) -> 58611053 | O7: =SUM(A:B!O7) -> 57223116 | P7: =SUM(A:B!P7) -> 55837049 | Q7: =SUM(A:B!Q7) -> 53402377 | ... U7: =SUM(A:B!U7) -> 62663938 | V7: =SUM(J7:U7) -> 6.7596297e+08 | W7: =V7/V$6 -> 0.75428499 | Y7: =SUM(A:B!Y7) -> 51376336 | Z7: =SUM(A:B!Z7) -> 51093583 | AA7: =SUM(A:B!AA7) -> 56927257 | AB7: =SUM(A:B!AB7) -> 54191883 | AC7: =SUM(A:B!AC7) -> 63090563 | AD7: =SUM(A:B!AD7) -> 62100321 | AE7: =SUM(A:B!AE7) -> 61646409 | AF7: =SUM(A:B!AF7) -> 64583060 | ... AJ7: =SUM(A:B!AJ7) -> 60670598 | AK7: =SUM(Y7:AJ7) -> 7.175899e+08 | AL7: =AK7/AK$6 -> 0.74502293 | AM7: =IFERROR(AK7/V7-1,0) -> 0.06158167
A8: A - INGRESOS | B8: estaciones | C8: INGRESOS PREMIUM | D8: INGRESOS FORANEOS PREMIUM | I8: SUPER | J8: =SUM(A:B!J8) -> 5468366 | K8: =SUM(A:B!K8) -> 5650927 | L8: =SUM(A:B!L8) -> 6229300 | M8: =SUM(A:B!M8) -> 5959245 | N8: =SUM(A:B!N8) -> 6580767 | O8: =SUM(A:B!O8) -> 6797460 | P8: =SUM(A:B!P8) -> 6511011 | Q8: =SUM(A:B!Q8) -> 4596705 | ... U8: =SUM(A:B!U8) -> 6115975.3 | V8: =SUM(J8:U8) -> 71743880 | W8: =V8/V$6 -> 0.080056651 | Y8: =SUM(A:B!Y8) -> 5360351.8 | Z8: =SUM(A:B!Z8) -> 5553280.4 | AA8: =SUM(A:B!AA8) -> 6278391.1 | AB8: =SUM(A:B!AB8) -> 5971144.2 | AC8: =SUM(A:B!AC8) -> 6969804.5 | AD8: =SUM(A:B!AD8) -> 7376824 | AE8: =SUM(A:B!AE8) -> 7096503.4 | AF8: =SUM(A:B!AF8) -> 7282731 | ... AJ8: =SUM(A:B!AJ8) -> 6418291.8 | AK8: =SUM(Y8:AJ8) -> 79107483 | AL8: =AK8/AK$6 -> 0.082131714 | AM8: =IFERROR(AK8/V8-1,0) -> 0.10263738
A9: A - INGRESOS | B9: estaciones | C9: INGRESOS DIESEL | D9: INGRESOS FORANEOS DIESEL | I9: DIESEL | J9: =SUM(A:B!J9) -> 11903653 | K9: =SUM(A:B!K9) -> 11298703 | L9: =SUM(A:B!L9) -> 12326817 | M9: =SUM(A:B!M9) -> 11076012 | N9: =SUM(A:B!N9) -> 12676022 | O9: =SUM(A:B!O9) -> 13611508 | P9: =SUM(A:B!P9) -> 14146233 | Q9: =SUM(A:B!Q9) -> 12274004 | ... U9: =SUM(A:B!U9) -> 10676098 | V9: =SUM(J9:U9) -> 1.4772481e+08 | W9: =V9/V$6 -> 0.16484128 | Y9: =SUM(A:B!Y9) -> 12921702 | Z9: =SUM(A:B!Z9) -> 12420215 | AA9: =SUM(A:B!AA9) -> 13411609 | AB9: =SUM(A:B!AB9) -> 12736669 | AC9: =SUM(A:B!AC9) -> 13904947 | AD9: =SUM(A:B!AD9) -> 14292866 | AE9: =SUM(A:B!AE9) -> 14834428 | AF9: =SUM(A:B!AF9) -> 13459330 | ... AJ9: =SUM(A:B!AJ9) -> 13925549 | AK9: =SUM(Y9:AJ9) -> 1.6558143e+08 | AL9: =AK9/AK$6 -> 0.17191151 | AM9: =IFERROR(AK9/V9-1,0) -> 0.12087765
I10: INGRESOS ACEITES Y LUBRICANTES | J10: =SUM(A:B!J10) -> 55926 | K10: =SUM(A:B!K10) -> 60191 | L10: =SUM(A:B!L10) -> 57829 | M10: =SUM(A:B!M10) -> 62981 | N10: =SUM(A:B!N10) -> 65966 | O10: =SUM(A:B!O10) -> 64372 | P10: =SUM(A:B!P10) -> 57869 | Q10: =SUM(A:B!Q10) -> 59128 | ... U10: =SUM(A:B!U10) -> 66823.2 | V10: =SUM(J10:U10) -> 732231.8 | W10: =V10/V$6 -> 0.00081707354 | Y10: =SUM(A:B!Y10) -> 74640 | Z10: =SUM(A:B!Z10) -> 72000 | AA10: =SUM(A:B!AA10) -> 95460 | AB10: =SUM(A:B!AB10) -> 69720 | AC10: =SUM(A:B!AC10) -> 75780 | AD10: =SUM(A:B!AD10) -> 71100 | AE10: =SUM(A:B!AE10) -> 71700 | AF10: =SUM(A:B!AF10) -> 68580 | ... AJ10: =SUM(A:B!AJ10) -> 76260 | AK10: =SUM(Y10:AJ10) -> 899460 | AL10: =AK10/AK$6 -> 0.00093384581 | AM10: =IFERROR(AK10/V10-1,0) -> 0.2283815
I11: SOBRANTE COMBUSTIBLE | J11: =SUM(A:B!J11) -> 0 | K11: =SUM(A:B!K11) -> 0 | L11: =SUM(A:B!L11) -> 0 | M11: =SUM(A:B!M11) -> 0 | N11: =SUM(A:B!N11) -> 0 | O11: =SUM(A:B!O11) -> 0 | P11: =SUM(A:B!P11) -> 0 | Q11: =SUM(A:B!Q11) -> 0 | ... U11: =SUM(A:B!U11) -> 0 | V11: =SUM(J11:U11) -> 0 | W11: =V11/V$6 -> 0 | Y11: =SUM(A:B!Y11) -> 0 | Z11: =SUM(A:B!Z11) -> 0 | AA11: =SUM(A:B!AA11) -> 0 | AB11: =SUM(A:B!AB11) -> 0 | AC11: =SUM(A:B!AC11) -> 0 | AD11: =SUM(A:B!AD11) -> 0 | AE11: =SUM(A:B!AE11) -> 0 | AF11: =SUM(A:B!AF11) -> 0 | ... AJ11: =SUM(A:B!AJ11) -> 0 | AK11: =SUM(Y11:AJ11) -> 0 | AL11: =AK11/AK$6 -> 0 | AM11: =IFERROR(AK11/V11-1,0) -> 0
J12: =SUM(A:B!J12) -> 0 | K12: =SUM(A:B!K12) -> 0 | L12: =SUM(A:B!L12) -> 0 | M12: =SUM(A:B!M12) -> 0 | N12: =SUM(A:B!N12) -> 0 | O12: =SUM(A:B!O12) -> 0 | P12: =SUM(A:B!P12) -> 0 | Q12: =SUM(A:B!Q12) -> 0 | ... U12: =SUM(A:B!U12) -> 0 | V12: =SUM(J12:U12) -> 0 | W12: =V12/V$6 -> 0 | Y12: =SUM(A:B!Y12) -> 0 | Z12: =SUM(A:B!Z12) -> 0 | AA12: =SUM(A:B!AA12) -> 0 | AB12: =SUM(A:B!AB12) -> 0 | AC12: =SUM(A:B!AC12) -> 0 | AD12: =SUM(A:B!AD12) -> 0 | AE12: =SUM(A:B!AE12) -> 0 | AF12: =SUM(A:B!AF12) -> 0 | ... AJ12: =SUM(A:B!AJ12) -> 0 | AK12: =SUM(Y12:AJ12) -> 0 | AL12: =AK12/AK$6 -> 0 | AM12: =IFERROR(AK12/V12-1,0) -> 0
A13: B - COSTO DE VENTA | E13: ( menos ) | I13: B - COSTO DE VENTA | J13: =SUM(J14:J33) -> 59783497 | K13: =SUM(K14:K33) -> 58274255 | L13: =SUM(L14:L33) -> 63406479 | M13: =SUM(M14:M33) -> 59049480 | N13: =SUM(N14:N33) -> 65462131 | O13: =SUM(O14:O33) -> 66797081 | P13: =SUM(P14:P33) -> 66311059 | Q13: =SUM(Q14:Q33) -> 61034025 | ... V13: =SUM(V14:V33) -> 7.6792499e+08 | W13: =V13/V$6 -> 0.8569024 | Y13: =SUM(Y14:Y33) -> 60165791 | Z13: =SUM(Z14:Z33) -> 59829241 | AA13: =SUM(AA14:AA33) -> 66068704 | AB13: =SUM(AB14:AB33) -> 63509117 | AC13: =SUM(AC14:AC33) -> 72484085 | AD13: =SUM(AD14:AD33) -> 73043997 | AE13: =SUM(AE14:AE33) -> 72992851 | AF13: =SUM(AF14:AF33) -> 74396670 | ... AJ13: =SUM(AJ14:AJ33) -> 71476884 | AK13: =SUM(Y13:AJ13) -> 8.3887815e+08 | AL13: =AK13/AK$6 -> 0.87094795 | AM13: =IFERROR(AK13/V13-1,0) -> 0.092395952
A14: B - COSTO DE VENTA | C14: COSTO MAGNA | D14: COSTO FORANEO MAGNA | I14: GASOLINA REGULAR | J14: =SUM(A:B!J14) -> 54037503 | K14: =SUM(A:B!K14) -> 52988836 | L14: =SUM(A:B!L14) -> 58109663 | M14: =SUM(A:B!M14) -> 54182667 | N14: =SUM(A:B!N14) -> 61241981 | O14: =SUM(A:B!O14) -> 60864148 | P14: =SUM(A:B!P14) -> 59642077 | Q14: =SUM(A:B!Q14) -> 56951729 | ... U14: =SUM(A:B!U14) -> 53503309 | V14: =SUM(J14:U14) -> 6.827669e+08 | W14: =V14/V$6 -> 0.76187727 | Y14: =SUM(A:B!Y14) -> 43965152 | Z14: =SUM(A:B!Z14) -> 43858767 | AA14: =SUM(A:B!AA14) -> 48610578 | AB14: =SUM(A:B!AB14) -> 46833763 | AC14: =SUM(A:B!AC14) -> 53940557 | AD14: =SUM(A:B!AD14) -> 53743511 | AE14: =SUM(A:B!AE14) -> 53413437 | AF14: =SUM(A:B!AF14) -> 55867226 | ... AJ14: =SUM(A:B!AJ14) -> 53142545 | AK14: =SUM(Y14:AJ14) -> 6.2048976e+08 | AL14: =AK14/AK$6 -> 0.64421071 | AM14: =IFERROR(AK14/V14-1,0) -> -0.091212883
A15: B - COSTO DE VENTA | C15: COSTO PREMIUM | D15: COSTO FORANEO PREMIUM | I15: GASOLINA PREMIUM | J15: =SUM(A:B!J15) -> 5319273 | K15: =SUM(A:B!K15) -> 5477157 | L15: =SUM(A:B!L15) -> 6024604 | M15: =SUM(A:B!M15) -> 5759007 | N15: =SUM(A:B!N15) -> 6417905 | O15: =SUM(A:B!O15) -> 6709392 | P15: =SUM(A:B!P15) -> 6539768 | Q15: =SUM(A:B!Q15) -> 4716580 | ... U15: =SUM(A:B!U15) -> 5274244.5 | V15: =SUM(J15:U15) -> 69441601 | W15: =V15/V$6 -> 0.077487614 | Y15: =SUM(A:B!Y15) -> 4659126.8 | Z15: =SUM(A:B!Z15) -> 4832868.2 | AA15: =SUM(A:B!AA15) -> 5459075.2 | AB15: =SUM(A:B!AB15) -> 5216593.9 | AC15: =SUM(A:B!AC15) -> 6098775.6 | AD15: =SUM(A:B!AD15) -> 6452142 | AE15: =SUM(A:B!AE15) -> 6245227.6 | AF15: =SUM(A:B!AF15) -> 6398892.4 | ... AJ15: =SUM(A:B!AJ15) -> 5685605.9 | AK15: =SUM(Y15:AJ15) -> 69403895 | AL15: =AK15/AK$6 -> 0.072057163 | AM15: =IFERROR(AK15/V15-1,0) -> -0.00054299936
A16: B - COSTO DE VENTA | C16: COSTO DIESEL | D16: COSTO FORANEO DIESEL | I16: DIESEL | J16: =SUM(A:B!J16) -> 10212607 | K16: =SUM(A:B!K16) -> 10010596 | L16: =SUM(A:B!L16) -> 10864455 | M16: =SUM(A:B!M16) -> 9847047 | N16: =SUM(A:B!N16) -> 11207696 | O16: =SUM(A:B!O16) -> 12305498 | P16: =SUM(A:B!P16) -> 12857250 | Q16: =SUM(A:B!Q16) -> 10940446 | ... U16: =SUM(A:B!U16) -> 9471412.1 | V16: =SUM(J16:U16) -> 1.3157793e+08 | W16: =V16/V$6 -> 0.14682351 | Y16: =SUM(A:B!Y16) -> 11478068 | Z16: =SUM(A:B!Z16) -> 11076406 | AA16: =SUM(A:B!AA16) -> 11917910 | AB16: =SUM(A:B!AB16) -> 11399498 | AC16: =SUM(A:B!AC16) -> 12380340 | AD16: =SUM(A:B!AD16) -> 12787909 | AE16: =SUM(A:B!AE16) -> 13273242 | AF16: =SUM(A:B!AF16) -> 12072259 | ... AJ16: =SUM(A:B!AJ16) -> 12583912 | AK16: =SUM(Y16:AJ16) -> 1.4821995e+08 | AL16: =AK16/AK$6 -> 0.15388631 | AM16: =IFERROR(AK16/V16-1,0) -> 0.12648037
A17: B - COSTO DE VENTA | C17: Merma Magna | I17: MERMA GASOLINA REGULAR | J17: =SUM(A:B!J17) -> 667991 | K17: =SUM(A:B!K17) -> 194258 | L17: =SUM(A:B!L17) -> 95173 | M17: =SUM(A:B!M17) -> 32472 | N17: =SUM(A:B!N17) -> 0 | O17: =SUM(A:B!O17) -> 0 | P17: =SUM(A:B!P17) -> 0 | Q17: =SUM(A:B!Q17) -> 0 | ... U17: =SUM(A:B!U17) -> 0 | V17: =SUM(J17:U17) -> 989894 | W17: =V17/V$6 -> 0.0011045904 | Y17: =SUM(A:B!Y17) -> 0 | Z17: =SUM(A:B!Z17) -> 0 | AA17: =SUM(A:B!AA17) -> 0 | AB17: =SUM(A:B!AB17) -> 0 | AC17: =SUM(A:B!AC17) -> 0 | AD17: =SUM(A:B!AD17) -> 0 | AE17: =SUM(A:B!AE17) -> 0 | AF17: =SUM(A:B!AF17) -> 0 | ... AJ17: =SUM(A:B!AJ17) -> 0 | AK17: =SUM(Y17:AJ17) -> 0 | AL17: =AK17/AK$6 -> 0 | AM17: =IFERROR(AK17/V17-1,0) -> -1
A18: B - COSTO DE VENTA | C18: Merma Premium | I18: MERMA GASOLINA PREMIUM | J18: =SUM(A:B!J18) -> 112597 | K18: =SUM(A:B!K18) -> 32019 | L18: =SUM(A:B!L18) -> -1798 | M18: =SUM(A:B!M18) -> 5421 | N18: =SUM(A:B!N18) -> 1054 | O18: =SUM(A:B!O18) -> 0 | P18: =SUM(A:B!P18) -> 4980 | Q18: =SUM(A:B!Q18) -> 0 | ... U18: =SUM(A:B!U18) -> 0 | V18: =SUM(J18:U18) -> 176195 | W18: =V18/V$6 -> 0.00019661024 | Y18: =SUM(A:B!Y18) -> 0 | Z18: =SUM(A:B!Z18) -> 0 | AA18: =SUM(A:B!AA18) -> 0 | AB18: =SUM(A:B!AB18) -> 0 | AC18: =SUM(A:B!AC18) -> 0 | AD18: =SUM(A:B!AD18) -> 0 | AE18: =SUM(A:B!AE18) -> 0 | AF18: =SUM(A:B!AF18) -> 0 | ... AJ18: =SUM(A:B!AJ18) -> 0 | AK18: =SUM(Y18:AJ18) -> 0 | AL18: =AK18/AK$6 -> 0 | AM18: =IFERROR(AK18/V18-1,0) -> -1
A19: B - COSTO DE VENTA | C19: Merma Diesel | I19: MERMA DIESEL | J19: =SUM(A:B!J19) -> 852 | K19: =SUM(A:B!K19) -> 0 | L19: =SUM(A:B!L19) -> 302 | M19: =SUM(A:B!M19) -> 384 | N19: =SUM(A:B!N19) -> 1771 | O19: =SUM(A:B!O19) -> 0 | P19: =SUM(A:B!P19) -> 0 | Q19: =SUM(A:B!Q19) -> 9479 | ... U19: =SUM(A:B!U19) -> 0 | V19: =SUM(J19:U19) -> 14972 | W19: =V19/V$6 -> 1.6706766e-05 | Y19: =SUM(A:B!Y19) -> 0 | Z19: =SUM(A:B!Z19) -> 0 | AA19: =SUM(A:B!AA19) -> 0 | AB19: =SUM(A:B!AB19) -> 0 | AC19: =SUM(A:B!AC19) -> 0 | AD19: =SUM(A:B!AD19) -> 0 | AE19: =SUM(A:B!AE19) -> 0 | AF19: =SUM(A:B!AF19) -> 0 | ... AJ19: =SUM(A:B!AJ19) -> 0 | AK19: =SUM(Y19:AJ19) -> 0 | AL19: =AK19/AK$6 -> 0 | AM19: =IFERROR(AK19/V19-1,0) -> -1
I20: SOBRANTE MAGNA | J20: =SUM(A:B!J20) -> 0 | K20: =SUM(A:B!K20) -> -29285 | L20: =SUM(A:B!L20) -> -144224 | M20: =SUM(A:B!M20) -> -252600 | N20: =SUM(A:B!N20) -> -542629 | O20: =SUM(A:B!O20) -> -772168 | P20: =SUM(A:B!P20) -> -628594 | Q20: =SUM(A:B!Q20) -> -417439 | ... U20: =SUM(A:B!U20) -> 0 | V20: =SUM(J20:U20) -> -3818112 | W20: =V20/V$6 -> -0.0042605064 | Y20: =SUM(A:B!Y20) -> 0 | Z20: =SUM(A:B!Z20) -> 0 | AA20: =SUM(A:B!AA20) -> 0 | AB20: =SUM(A:B!AB20) -> 0 | AC20: =SUM(A:B!AC20) -> 0 | AD20: =SUM(A:B!AD20) -> 0 | AE20: =SUM(A:B!AE20) -> 0 | AF20: =SUM(A:B!AF20) -> 0 | ... AJ20: =SUM(A:B!AJ20) -> 0 | AK20: =SUM(Y20:AJ20) -> 0 | AL20: =AK20/AK$6 -> 0 | AM20: =IFERROR(AK20/V20-1,0) -> -1
I21: SOBRANTE PREMIUM | J21: =SUM(A:B!J21) -> -11558 | K21: =SUM(A:B!K21) -> -10191 | L21: =SUM(A:B!L21) -> -23886 | M21: =SUM(A:B!M21) -> -25404 | N21: =SUM(A:B!N21) -> -70527 | O21: =SUM(A:B!O21) -> -88473 | P21: =SUM(A:B!P21) -> -75995 | Q21: =SUM(A:B!Q21) -> -29922 | ... U21: =SUM(A:B!U21) -> 0 | V21: =SUM(J21:U21) -> -411781 | W21: =V21/V$6 -> -0.00045949296 | Y21: =SUM(A:B!Y21) -> 0 | Z21: =SUM(A:B!Z21) -> 0 | AA21: =SUM(A:B!AA21) -> 0 | AB21: =SUM(A:B!AB21) -> 0 | AC21: =SUM(A:B!AC21) -> 0 | AD21: =SUM(A:B!AD21) -> 0 | AE21: =SUM(A:B!AE21) -> 0 | AF21: =SUM(A:B!AF21) -> 0 | ... AJ21: =SUM(A:B!AJ21) -> 0 | AK21: =SUM(Y21:AJ21) -> 0 | AL21: =AK21/AK$6 -> 0 | AM21: =IFERROR(AK21/V21-1,0) -> -1
I22: SOBRANTE DIESEL | J22: =SUM(A:B!J22) -> -59339 | K22: =SUM(A:B!K22) -> -93897 | L22: =SUM(A:B!L22) -> -118699 | M22: =SUM(A:B!M22) -> -121515 | N22: =SUM(A:B!N22) -> -185372 | O22: =SUM(A:B!O22) -> -209250 | P22: =SUM(A:B!P22) -> -242095 | Q22: =SUM(A:B!Q22) -> -81498 | ... U22: =SUM(A:B!U22) -> 0 | V22: =SUM(J22:U22) -> -1515930 | W22: =V22/V$6 -> -0.0016915767 | Y22: =SUM(A:B!Y22) -> 0 | Z22: =SUM(A:B!Z22) -> 0 | AA22: =SUM(A:B!AA22) -> 0 | AB22: =SUM(A:B!AB22) -> 0 | AC22: =SUM(A:B!AC22) -> 0 | AD22: =SUM(A:B!AD22) -> 0 | AE22: =SUM(A:B!AE22) -> 0 | AF22: =SUM(A:B!AF22) -> 0 | ... AJ22: =SUM(A:B!AJ22) -> 0 | AK22: =SUM(Y22:AJ22) -> 0 | AL22: =AK22/AK$6 -> 0 | AM22: =IFERROR(AK22/V22-1,0) -> -1
A23: B - COSTO DE VENTA | C23: ADITIVO PARA GASOLINA TMAXIMA (REGULAR) | D23: ADITIVO PARA GASOLINA TMAXIMA( REGULAR) | I23: ADITIVO TOTAL POWER GASOLINA REG | J23: =SUM(A:B!J23) -> 110309 | K23: =SUM(A:B!K23) -> 183033 | L23: =SUM(A:B!L23) -> 118902 | M23: =SUM(A:B!M23) -> 491588 | N23: =SUM(A:B!N23) -> -240501 | O23: =SUM(A:B!O23) -> 129867 | P23: =SUM(A:B!P23) -> 132184 | Q23: =SUM(A:B!Q23) -> 108896 | ... U23: =SUM(A:B!U23) -> 0 | V23: =SUM(J23:U23) -> 1273002 | W23: =V23/V$6 -> 0.0014205013 | Y23: =SUM(A:B!Y23) -> 0 | Z23: =SUM(A:B!Z23) -> 0 | AA23: =SUM(A:B!AA23) -> 0 | AB23: =SUM(A:B!AB23) -> 0 | AC23: =SUM(A:B!AC23) -> 0 | AD23: =SUM(A:B!AD23) -> 0 | AE23: =SUM(A:B!AE23) -> 0 | AF23: =SUM(A:B!AF23) -> 0 | ... AJ23: =SUM(A:B!AJ23) -> 0 | AK23: =SUM(Y23:AJ23) -> 0 | AL23: =AK23/AK$6 -> 0 | AM23: =IFERROR(AK23/V23-1,0) -> -1
A24: B - COSTO DE VENTA | C24: ADITIVO PARA GASOLINA TSUPER (PREMIUM) | I24: ADITIVO TOTAL POWER GASOLINA PREM | J24: =SUM(A:B!J24) -> 10018 | K24: =SUM(A:B!K24) -> 20216 | L24: =SUM(A:B!L24) -> 12073 | M24: =SUM(A:B!M24) -> 11105 | N24: =SUM(A:B!N24) -> 12892 | O24: =SUM(A:B!O24) -> 14241 | P24: =SUM(A:B!P24) -> 14417 | Q24: =SUM(A:B!Q24) -> 3951 | ... U24: =SUM(A:B!U24) -> 0 | V24: =SUM(J24:U24) -> 125941 | W24: =V24/V$6 -> 0.00014053345 | Y24: =SUM(A:B!Y24) -> 0 | Z24: =SUM(A:B!Z24) -> 0 | AA24: =SUM(A:B!AA24) -> 0 | AB24: =SUM(A:B!AB24) -> 0 | AC24: =SUM(A:B!AC24) -> 0 | AD24: =SUM(A:B!AD24) -> 0 | AE24: =SUM(A:B!AE24) -> 0 | AF24: =SUM(A:B!AF24) -> 0 | ... AJ24: =SUM(A:B!AJ24) -> 0 | AK24: =SUM(Y24:AJ24) -> 0 | AL24: =AK24/AK$6 -> 0 | AM24: =IFERROR(AK24/V24-1,0) -> -1
A25: B - COSTO DE VENTA | C25: FLETE MAGNA | I25: FLETE GASOLINA REGULAR | J25: =SUM(A:B!J25) -> 0 | K25: =SUM(A:B!K25) -> 0 | L25: =SUM(A:B!L25) -> 0 | M25: =SUM(A:B!M25) -> 0 | N25: =SUM(A:B!N25) -> 1841 | O25: =SUM(A:B!O25) -> 0 | P25: =SUM(A:B!P25) -> 0 | Q25: =SUM(A:B!Q25) -> 916 | ... U25: =SUM(A:B!U25) -> 0 | V25: =SUM(J25:U25) -> 2757 | W25: =V25/V$6 -> 3.0764462e-06 | Y25: =SUM(A:B!Y25) -> 0 | Z25: =SUM(A:B!Z25) -> 0 | AA25: =SUM(A:B!AA25) -> 0 | AB25: =SUM(A:B!AB25) -> 0 | AC25: =SUM(A:B!AC25) -> 0 | AD25: =SUM(A:B!AD25) -> 0 | AE25: =SUM(A:B!AE25) -> 0 | AF25: =SUM(A:B!AF25) -> 0 | ... AJ25: =SUM(A:B!AJ25) -> 0 | AK25: =SUM(Y25:AJ25) -> 0 | AL25: =AK25/AK$6 -> 0 | AM25: =IFERROR(AK25/V25-1,0) -> -1
A26: B - COSTO DE VENTA | C26: FLETE PREMIUM | I26: FLETE GASOLINA PREMIUM | J26: =SUM(A:B!J26) -> 0 | K26: =SUM(A:B!K26) -> 0 | L26: =SUM(A:B!L26) -> 0 | M26: =SUM(A:B!M26) -> 0 | N26: =SUM(A:B!N26) -> 0 | O26: =SUM(A:B!O26) -> 0 | P26: =SUM(A:B!P26) -> 0 | Q26: =SUM(A:B!Q26) -> 0 | ... U26: =SUM(A:B!U26) -> 0 | V26: =SUM(J26:U26) -> 0 | W26: =V26/V$6 -> 0 | Y26: =SUM(A:B!Y26) -> 0 | Z26: =SUM(A:B!Z26) -> 0 | AA26: =SUM(A:B!AA26) -> 0 | AB26: =SUM(A:B!AB26) -> 0 | AC26: =SUM(A:B!AC26) -> 0 | AD26: =SUM(A:B!AD26) -> 0 | AE26: =SUM(A:B!AE26) -> 0 | AF26: =SUM(A:B!AF26) -> 0 | ... AJ26: =SUM(A:B!AJ26) -> 0 | AK26: =SUM(Y26:AJ26) -> 0 | AL26: =AK26/AK$6 -> 0 | AM26: =IFERROR(AK26/V26-1,0) -> 0
A27: B - COSTO DE VENTA | C27: FLETE DIESEL | I27: FLETE DIESEL | J27: =SUM(A:B!J27) -> 0 | K27: =SUM(A:B!K27) -> 0 | L27: =SUM(A:B!L27) -> 0 | M27: =SUM(A:B!M27) -> 0 | N27: =SUM(A:B!N27) -> 0 | O27: =SUM(A:B!O27) -> 0 | P27: =SUM(A:B!P27) -> 0 | Q27: =SUM(A:B!Q27) -> 0 | ... U27: =SUM(A:B!U27) -> 0 | V27: =SUM(J27:U27) -> 0 | W27: =V27/V$6 -> 0 | Y27: =SUM(A:B!Y27) -> 0 | Z27: =SUM(A:B!Z27) -> 0 | AA27: =SUM(A:B!AA27) -> 0 | AB27: =SUM(A:B!AB27) -> 0 | AC27: =SUM(A:B!AC27) -> 0 | AD27: =SUM(A:B!AD27) -> 0 | AE27: =SUM(A:B!AE27) -> 0 | AF27: =SUM(A:B!AF27) -> 0 | ... AJ27: =SUM(A:B!AJ27) -> 0 | AK27: =SUM(Y27:AJ27) -> 0 | AL27: =AK27/AK$6 -> 0 | AM27: =IFERROR(AK27/V27-1,0) -> 0
A28: B - COSTO DE VENTA | C28: Estimulo IEPS Magna | D28: INGRESOS FORANEOS MAGNA | I28: ESTIMULO REGULAR | J28: =SUM(A:B!J28) -> -9895352 | K28: =SUM(A:B!K28) -> -9741490 | L28: =SUM(A:B!L28) -> -10698216 | M28: =SUM(A:B!M28) -> -10091896 | N28: =SUM(A:B!N28) -> -11479619 | O28: =SUM(A:B!O28) -> -11206376 | P28: =SUM(A:B!P28) -> -11021279 | Q28: =SUM(A:B!Q28) -> -10539195 | ... U28: =SUM(A:B!U28) -> 0 | V28: =SUM(J28:U28) -> -104718341 | W28: =V28/V$6 -> -0.11685177 | Y28: =SUM(A:B!Y28) -> 0 | Z28: =SUM(A:B!Z28) -> 0 | AA28: =SUM(A:B!AA28) -> 0 | AB28: =SUM(A:B!AB28) -> 0 | AC28: =SUM(A:B!AC28) -> 0 | AD28: =SUM(A:B!AD28) -> 0 | AE28: =SUM(A:B!AE28) -> 0 | AF28: =SUM(A:B!AF28) -> 0 | ... AJ28: =SUM(A:B!AJ28) -> 0 | AK28: =SUM(Y28:AJ28) -> 0 | AL28: =AK28/AK$6 -> 0 | AM28: =IFERROR(AK28/V28-1,0) -> -1
A29: B - COSTO DE VENTA | C29: Estimulo IEPS Premium | D29: INGRESOS FORANEOS MAGNA | I29: ESTIMULO PREMIUM | J29: =SUM(A:B!J29) -> -775258 | K29: =SUM(A:B!K29) -> -798009 | L29: =SUM(A:B!L29) -> -878327 | M29: =SUM(A:B!M29) -> -837300 | N29: =SUM(A:B!N29) -> -954984 | O29: =SUM(A:B!O29) -> -999309 | P29: =SUM(A:B!P29) -> -956207 | Q29: =SUM(A:B!Q29) -> -675074 | ... U29: =SUM(A:B!U29) -> 0 | V29: =SUM(J29:U29) -> -8579690 | W29: =V29/V$6 -> -0.0095737957 | Y29: =SUM(A:B!Y29) -> 0 | Z29: =SUM(A:B!Z29) -> 0 | AA29: =SUM(A:B!AA29) -> 0 | AB29: =SUM(A:B!AB29) -> 0 | AC29: =SUM(A:B!AC29) -> 0 | AD29: =SUM(A:B!AD29) -> 0 | AE29: =SUM(A:B!AE29) -> 0 | AF29: =SUM(A:B!AF29) -> 0 | ... AJ29: =SUM(A:B!AJ29) -> 0 | AK29: =SUM(Y29:AJ29) -> 0 | AL29: =AK29/AK$6 -> 0 | AM29: =IFERROR(AK29/V29-1,0) -> -1
I30: COSTO ACEITES Y LUBRICANTES | J30: =SUM(A:B!J30) -> 53854 | K30: =SUM(A:B!K30) -> 41012 | L30: =SUM(A:B!L30) -> 46457 | M30: =SUM(A:B!M30) -> 48504 | N30: =SUM(A:B!N30) -> 50623 | O30: =SUM(A:B!O30) -> 49511 | P30: =SUM(A:B!P30) -> 44553 | Q30: =SUM(A:B!Q30) -> 45156 | ... U30: =SUM(A:B!U30) -> 56799.72 | V30: =SUM(J30:U30) -> 599655.58 | W30: =V30/V$6 -> 0.00066913607 | Y30: =SUM(A:B!Y30) -> 63444 | Z30: =SUM(A:B!Z30) -> 61200 | AA30: =SUM(A:B!AA30) -> 81141 | AB30: =SUM(A:B!AB30) -> 59262 | AC30: =SUM(A:B!AC30) -> 64413 | AD30: =SUM(A:B!AD30) -> 60435 | AE30: =SUM(A:B!AE30) -> 60945 | AF30: =SUM(A:B!AF30) -> 58293 | ... AJ30: =SUM(A:B!AJ30) -> 64821 | AK30: =SUM(Y30:AJ30) -> 764541 | AL30: =AK30/AK$6 -> 0.00079376894 | AM30: =IFERROR(AK30/V30-1,0) -> 0.27496687
I31: BONIFICACION COMPRA DE COMBUSTIBLE MAGNA | J31: =SUM(A:B!J31) -> 0 | K31: =SUM(A:B!K31) -> 0 | L31: =SUM(A:B!L31) -> 0 | M31: =SUM(A:B!M31) -> 0 | N31: =SUM(A:B!N31) -> 0 | O31: =SUM(A:B!O31) -> 0 | P31: =SUM(A:B!P31) -> 0 | Q31: =SUM(A:B!Q31) -> 0 | ... U31: =SUM(A:B!U31) -> 0 | V31: =SUM(J31:U31) -> 0 | W31: =V31/V$6 -> 0 | Y31: =SUM(A:B!Y31) -> 0 | Z31: =SUM(A:B!Z31) -> 0 | AA31: =SUM(A:B!AA31) -> 0 | AB31: =SUM(A:B!AB31) -> 0 | AC31: =SUM(A:B!AC31) -> 0 | AD31: =SUM(A:B!AD31) -> 0 | AE31: =SUM(A:B!AE31) -> 0 | AF31: =SUM(A:B!AF31) -> 0 | ... AJ31: =SUM(A:B!AJ31) -> 0 | AK31: =SUM(Y31:AJ31) -> 0 | AL31: =AK31/AK$6 -> 0 | AM31: =IFERROR(AK31/V31-1,0) -> 0
I32: BONIFICACION COMPRA DE COMBUSTIBLE PREMIUM | J32: =SUM(A:B!J32) -> 0 | K32: =SUM(A:B!K32) -> 0 | L32: =SUM(A:B!L32) -> 0 | M32: =SUM(A:B!M32) -> 0 | N32: =SUM(A:B!N32) -> 0 | O32: =SUM(A:B!O32) -> 0 | P32: =SUM(A:B!P32) -> 0 | Q32: =SUM(A:B!Q32) -> 0 | ... U32: =SUM(A:B!U32) -> 0 | V32: =SUM(J32:U32) -> 0 | W32: =V32/V$6 -> 0 | Y32: =SUM(A:B!Y32) -> 0 | Z32: =SUM(A:B!Z32) -> 0 | AA32: =SUM(A:B!AA32) -> 0 | AB32: =SUM(A:B!AB32) -> 0 | AC32: =SUM(A:B!AC32) -> 0 | AD32: =SUM(A:B!AD32) -> 0 | AE32: =SUM(A:B!AE32) -> 0 | AF32: =SUM(A:B!AF32) -> 0 | ... AJ32: =SUM(A:B!AJ32) -> 0 | AK32: =SUM(Y32:AJ32) -> 0 | AL32: =AK32/AK$6 -> 0 | AM32: =IFERROR(AK32/V32-1,0) -> 0
I33: BONIFICACION COMPRA DE COMBUSTIBLE DIESEL | J33: =SUM(A:B!J33) -> 0 | K33: =SUM(A:B!K33) -> 0 | L33: =SUM(A:B!L33) -> 0 | M33: =SUM(A:B!M33) -> 0 | N33: =SUM(A:B!N33) -> 0 | O33: =SUM(A:B!O33) -> 0 | P33: =SUM(A:B!P33) -> 0 | Q33: =SUM(A:B!Q33) -> 0 | ... U33: =SUM(A:B!U33) -> 0 | V33: =SUM(J33:U33) -> 0 | W33: =V33/V$6 -> 0 | Y33: =SUM(A:B!Y33) -> 0 | Z33: =SUM(A:B!Z33) -> 0 | AA33: =SUM(A:B!AA33) -> 0 | AB33: =SUM(A:B!AB33) -> 0 | AC33: =SUM(A:B!AC33) -> 0 | AD33: =SUM(A:B!AD33) -> 0 | AE33: =SUM(A:B!AE33) -> 0 | AF33: =SUM(A:B!AF33) -> 0 | ... AJ33: =SUM(A:B!AJ33) -> 0 | AK33: =SUM(Y33:AJ33) -> 0 | AL33: =AK33/AK$6 -> 0 | AM33: =IFERROR(AK33/V33-1,0) -> 0
I34: MARGEN DE UTILIDAD | J34: =J6-J13 -> 9669373 | K34: =K6-K13 -> 10402424 | L34: =L6-L13 -> 10631948 | M34: =M6-M13 -> 10175079 | N34: =N6-N13 -> 12471677 | O34: =O6-O13 -> 10899375 | P34: =P6-P13 -> 10241103 | Q34: =Q6-Q13 -> 9298189 | ... V34: =V6-V13 -> 1.282389e+08 | W34: =V34/V$6 -> 0.1430976 | Y34: =Y6-Y13 -> 9567238.4 | Z34: =Z6-Z13 -> 9309837 | AA34: =AA6-AA13 -> 10644012 | AB34: =AB6-AB13 -> 9460298.8 | AC34: =AC6-AC13 -> 11557010 | AD34: =AD6-AD13 -> 10797115 | AE34: =AE6-AE13 -> 10656189 | AF34: =AF6-AF13 -> 10997032 | ... AK34: =AK6-AK13 -> 1.2430013e+08 | AL34: =AK34/AK$6 -> 0.12905205 | AM34: =IFERROR(AK34/V34-1,0) -> -0.03071433
I35: *Regular | J35: =SUM(A:B!J35) -> 7104474 | K35: =SUM(A:B!K35) -> 8071504 | L35: =SUM(A:B!L35) -> 7943183 | M35: =SUM(A:B!M35) -> 7764090 | N35: =SUM(A:B!N35) -> 9629979 | O35: =SUM(A:B!O35) -> 8207647 | P35: =SUM(A:B!P35) -> 7712661 | Q35: =SUM(A:B!Q35) -> 7297471 | ... U35: =SUM(A:B!U35) -> 8363594.4 | V35: =SUM(J35:U35) -> 97185386 | W35: =V35/V$39 -> 2.0333925 | Y35: =SUM(A:B!Y35) -> 7411184.1 | Z35: =SUM(A:B!Z35) -> 7234815.7 | AA35: =SUM(A:B!AA35) -> 8316678.4 | AB35: =SUM(A:B!AB35) -> 7358119.8 | AC35: =SUM(A:B!AC35) -> 9150006.6 | AD35: =SUM(A:B!AD35) -> 8356810.8 | AE35: =SUM(A:B!AE35) -> 8232972 | AF35: =SUM(A:B!AF35) -> 8715834.2 | ... AJ35: =SUM(A:B!AJ35) -> 7528052.6 | AK35: =SUM(Y35:AJ35) -> 97100144 | AL35: =AK35/AK$39 -> 1.9585461 | AM35: =IFERROR(AK35/V35-1,0) -> -0.00087711419
I36: *Premium | J36: =SUM(A:B!J36) -> 813291 | K36: =SUM(A:B!K36) -> 929738 | L36: =SUM(A:B!L36) -> 1096634 | M36: =SUM(A:B!M36) -> 1046417 | N36: =SUM(A:B!N36) -> 1174426 | O36: =SUM(A:B!O36) -> 1161608 | P36: =SUM(A:B!P36) -> 984047 | Q36: =SUM(A:B!Q36) -> 581170 | ... U36: =SUM(A:B!U36) -> 775550.78 | V36: =SUM(J36:U36) -> 10889534 | W36: =V36/V$39 -> 0.22783978 | Y36: =SUM(A:B!Y36) -> 701224.92 | Z36: =SUM(A:B!Z36) -> 720412.16 | AA36: =SUM(A:B!AA36) -> 819315.89 | AB36: =SUM(A:B!AB36) -> 754550.32 | AC36: =SUM(A:B!AC36) -> 871028.95 | AD36: =SUM(A:B!AD36) -> 924681.99 | AE36: =SUM(A:B!AE36) -> 851275.86 | AF36: =SUM(A:B!AF36) -> 883838.65 | ... AJ36: =SUM(A:B!AJ36) -> 732685.83 | AK36: =SUM(Y36:AJ36) -> 9703588.7 | AL36: =AK36/AK$39 -> 0.195725 | AM36: =IFERROR(AK36/V36-1,0) -> -0.1089069
I37: *Diesel | J37: =SUM(A:B!J37) -> 1749533 | K37: =SUM(A:B!K37) -> 1382005 | L37: =SUM(A:B!L37) -> 1580760 | M37: =SUM(A:B!M37) -> 1350095 | N37: =SUM(A:B!N37) -> 1651925 | O37: =SUM(A:B!O37) -> 1515260 | P37: =SUM(A:B!P37) -> 1531075 | Q37: =SUM(A:B!Q37) -> 1405577 | ... U37: =SUM(A:B!U37) -> 1493095.4 | V37: =SUM(J37:U37) -> 18138611 | W37: =V37/V$39 -> 0.37951094 | Y37: =SUM(A:B!Y37) -> 1443633.3 | Z37: =SUM(A:B!Z37) -> 1343809.2 | AA37: =SUM(A:B!AA37) -> 1493698.9 | AB37: =SUM(A:B!AB37) -> 1337170.6 | AC37: =SUM(A:B!AC37) -> 1524607.2 | AD37: =SUM(A:B!AD37) -> 1504957.2 | AE37: =SUM(A:B!AE37) -> 1561186.1 | AF37: =SUM(A:B!AF37) -> 1387071.7 | ... AJ37: =SUM(A:B!AJ37) -> 1341637.5 | AK37: =SUM(Y37:AJ37) -> 17361480 | AL37: =AK37/AK$39 -> 0.35018752 | AM37: =IFERROR(AK37/V37-1,0) -> -0.042844068
I38: * Aceites y Lubricantes | J38: =SUM(A:B!J38) -> 2073 | K38: =SUM(A:B!K38) -> 19180 | L38: =SUM(A:B!L38) -> 11371 | M38: =SUM(A:B!M38) -> 14475 | N38: =SUM(A:B!N38) -> 15343 | O38: =SUM(A:B!O38) -> 14861 | P38: =SUM(A:B!P38) -> 13316 | Q38: =SUM(A:B!Q38) -> 13972 | ... U38: =SUM(A:B!U38) -> 4184.7407 | V38: =SUM(J38:U38) -> 121329.96 | W38: =V38/V$39 -> 0.0025385652 | Y38: =SUM(A:B!Y38) -> 11196 | Z38: =SUM(A:B!Z38) -> 10800 | AA38: =SUM(A:B!AA38) -> 14319 | AB38: =SUM(A:B!AB38) -> 10458 | AC38: =SUM(A:B!AC38) -> 11367 | AD38: =SUM(A:B!AD38) -> 10665 | AE38: =SUM(A:B!AE38) -> 10755 | AF38: =SUM(A:B!AF38) -> 10287 | ... AJ38: =SUM(A:B!AJ38) -> 11439 | AK38: =SUM(Y38:AJ38) -> 134919 | AL38: =AK38/AK$39 -> 0.0027213666 | AM38: =IFERROR(AK38/V38-1,0) -> 0.11200067
I39: Litros vendidos | J39: =SUM(A:B!J39) -> 3700569 | K39: =SUM(A:B!K39) -> 3632738 | L39: =SUM(A:B!L39) -> 3988189 | M39: =SUM(A:B!M39) -> 3743720 | N39: =SUM(A:B!N39) -> 4276090 | O39: =SUM(A:B!O39) -> 4259792 | P39: =SUM(A:B!P39) -> 4201852 | Q39: =SUM(A:B!Q39) -> 3874166 | ... V39: =SUM(A:B!V39) -> 47794700 | W39: =V39/V$39 -> 1 | Y39: =SUM(A:B!Y39) -> 3821480 | Z39: =SUM(A:B!Z39) -> 3748758 | AA39: =SUM(A:B!AA39) -> 4114391 | AB39: =SUM(A:B!AB39) -> 3870153 | AC39: =SUM(A:B!AC39) -> 4414525 | AD39: =SUM(A:B!AD39) -> 4346815 | AE39: =SUM(A:B!AE39) -> 4282241 | AF39: =SUM(A:B!AF39) -> 4339623 | ... AJ39: =SUM(A:B!AJ39) -> 3925340 | AK39: =SUM(Y39:AJ39) -> 49577665 | AL39: =AK39/AK$39 -> 1 | AM39: =IFERROR(AK39/V39-1,0) -> 0.037304659 | AN39: 48793805
I40: Maxima | J40: =SUM(A:B!J40) -> 2902809 | K40: =SUM(A:B!K40) -> 2857785 | L40: =SUM(A:B!L40) -> 3134970 | M40: =SUM(A:B!M40) -> 2960554 | N40: =SUM(A:B!N40) -> 3367706 | O40: =SUM(A:B!O40) -> 3288023 | P40: =SUM(A:B!P40) -> 3234223 | Q40: =SUM(A:B!Q40) -> 3091988 | ... U40: =SUM(A:B!U40) -> 3012428 | V40: =SUM(J40:U40) -> 37433009 | W40: =V40/V$39 -> 0.78320418 | Y40: =SUM(A:B!Y40) -> 2952663 | Z40: =SUM(A:B!Z40) -> 2902741 | AA40: =SUM(A:B!AA40) -> 3197079 | AB40: =SUM(A:B!AB40) -> 3008559 | AC40: =SUM(A:B!AC40) -> 3462421 | AD40: =SUM(A:B!AD40) -> 3368996 | AE40: =SUM(A:B!AE40) -> 3306021 | AF40: =SUM(A:B!AF40) -> 3423794 | ... AJ40: =SUM(A:B!AJ40) -> 3071369 | AK40: =SUM(Y40:AJ40) -> 38635804 | AL40: =AK40/AK$39 -> 0.77929858 | AM40: =IFERROR(AK40/V40-1,0) -> 0.032131935
I41: Super | J41: =SUM(A:B!J41) -> 271069 | K41: =SUM(A:B!K41) -> 279451 | L41: =SUM(A:B!L41) -> 310795 | M41: =SUM(A:B!M41) -> 292788 | N41: =SUM(A:B!N41) -> 333910 | O41: =SUM(A:B!O41) -> 349797 | P41: =SUM(A:B!P41) -> 334339 | Q41: =SUM(A:B!Q41) -> 236040 | ... U41: =SUM(A:B!U41) -> 286641 | V41: =SUM(J41:U41) -> 3592939 | W41: =V41/V$39 -> 0.075174423 | Y41: =SUM(A:B!Y41) -> 277164 | Z41: =SUM(A:B!Z41) -> 283847 | AA41: =SUM(A:B!AA41) -> 317230 | AB41: =SUM(A:B!AB41) -> 298246 | AC41: =SUM(A:B!AC41) -> 344135 | AD41: =SUM(A:B!AD41) -> 360055 | AE41: =SUM(A:B!AE41) -> 342401 | AF41: =SUM(A:B!AF41) -> 347357 | ... AJ41: =SUM(A:B!AJ41) -> 292325 | AK41: =SUM(Y41:AJ41) -> 3832524 | AL41: =AK41/AK$39 -> 0.077303439 | AM41: =IFERROR(AK41/V41-1,0) -> 0.066682179
I42: Diesel | J42: =SUM(A:B!J42) -> 526691 | K42: =SUM(A:B!K42) -> 495501 | L42: =SUM(A:B!L42) -> 542424 | M42: =SUM(A:B!M42) -> 490379 | N42: =SUM(A:B!N42) -> 574474 | O42: =SUM(A:B!O42) -> 621973 | P42: =SUM(A:B!P42) -> 633290 | Q42: =SUM(A:B!Q42) -> 546137 | ... U42: =SUM(A:B!U42) -> 551641 | V42: =SUM(J42:U42) -> 6768751 | W42: =V42/V$39 -> 0.14162137 | Y42: =SUM(A:B!Y42) -> 591653 | Z42: =SUM(A:B!Z42) -> 562170 | AA42: =SUM(A:B!AA42) -> 600082 | AB42: =SUM(A:B!AB42) -> 563348 | AC42: =SUM(A:B!AC42) -> 607969 | AD42: =SUM(A:B!AD42) -> 617764 | AE42: =SUM(A:B!AE42) -> 633819 | AF42: =SUM(A:B!AF42) -> 568472 | ... AJ42: =SUM(A:B!AJ42) -> 561646 | AK42: =SUM(Y42:AJ42) -> 7109337 | AL42: =AK42/AK$39 -> 0.14339798 | AM42: =IFERROR(AK42/V42-1,0) -> 0.050317407
I43: Margen de utilidad por combustible | J43: =J34/J39 -> 2.6129422 | K43: =K34/K39 -> 2.8635217 | L43: =L34/L39 -> 2.6658586 | M43: =M34/M39 -> 2.717906 | N43: =N34/N39 -> 2.9166077 | O43: =O34/O39 -> 2.5586637 | P43: =P34/P39 -> 2.4372831 | Q43: =Q34/Q39 -> 2.4000492 | ... U43: =U34/U39 -> 2.9129876 | V43: =+V34/V39 -> 2.6831197 | W43: =V43/V$39 -> 5.6138437e-08 | Y43: =Y34/Y39 -> 2.5035427 | Z43: =Z34/Z39 -> 2.4834457 | AA43: =AA34/AA39 -> 2.5870201 | AB43: =AB34/AB39 -> 2.444425 | AC43: =AC34/AC39 -> 2.6179509 | AD43: =AD34/AD39 -> 2.4839141 | AE43: =AE34/AE39 -> 2.4884608 | AF43: =AF34/AF39 -> 2.5340984 | ... AJ43: =AJ34/AJ39 -> 2.4491674 | AK43: =+AK34/AK39 -> 2.50718 | AL43: =AK43/AK$39 -> 5.0570756e-08 | AM43: =IFERROR(AK43/V43-1,0) -> -0.065572818 | AN43: 2.8 | AO43: =+AN39*AN43 -> 136622654
I44: Maxima | J44: =IFERROR((J7+J11-(J14+J17+J23+J25+J28))/J40,0) -> 2.447448 | K44: =IFERROR((K7+K11-(K14+K17+K23+K25+K28))/K40,0) -> 2.8141449 | L44: =IFERROR((L7+L11-(L14+L17+L23+L25+L28))/L40,0) -> 2.48773 | M44: =IFERROR((M7+M11-(M14+M17+M23+M25+M28))/M40,0) -> 2.5371907 | N44: =IFERROR((N7+N11-(N14+N17+N23+N25+N28))/N40,0) -> 2.6983801 | O44: =IFERROR((O7+O11-(O14+O17+O23+O25+O28))/O40,0) -> 2.2613823 | P44: =IFERROR((P7+P11-(P14+P17+P23+P25+P28))/P40,0) -> 2.1903459 | Q44: =IFERROR((Q7+Q11-(Q14+Q17+Q23+Q25+Q28))/Q40,0) -> 2.2251157 | ... S44: =IFERROR((S7+S11-(S14+S17+S23+S25+S28))/S40,0) -> 2.7412466 | T44: 2.34 | U44: 2.34 | V44: =+V35/V40 -> 2.5962483 | W44: =V44/V$39 -> 5.4320841e-08 | Y44: =IFERROR((Y7+Y11-(Y14+Y17+Y23+Y25+Y28))/Y40,0) -> 2.51 | Z44: =IFERROR((Z7+Z11-(Z14+Z17+Z23+Z25+Z28))/Z40,0) -> 2.4924083 | AA44: =IFERROR((AA7+AA11-(AA14+AA17+AA23+AA25+AA28))/AA40,0) -> 2.6013365 | AB44: =IFERROR((AB7+AB11-(AB14+AB17+AB23+AB25+AB28))/AB40,0) -> 2.4457289 | AC44: =IFERROR((AC7+AC11-(AC14+AC17+AC23+AC25+AC28))/AC40,0) -> 2.6426615 | AD44: =IFERROR((AD7+AD11-(AD14+AD17+AD23+AD25+AD28))/AD40,0) -> 2.4805048 | AE44: =IFERROR((AE7+AE11-(AE14+AE17+AE23+AE25+AE28))/AE40,0) -> 2.4902963 | AF44: =IFERROR((AF7+AF11-(AF14+AF17+AF23+AF25+AF28))/AF40,0) -> 2.5456655 | ... AJ44: =IFERROR((AJ7+AJ11-(AJ14+AJ17+AJ23+AJ25+AJ28))/AJ40,0) -> 2.4510414 | AK44: =+AK35/AK40 -> 2.5132166 | AL44: =AK44/AK$39 -> 5.0692516e-08 | AM44: =IFERROR(AK44/V44-1,0) -> -0.031981424
I45: Super | J45: =IFERROR((J8+J12-(J15+J18+J24+J26+J29))/J41,0) -> 2.9576824 | K45: =IFERROR((K8+K12-(K15+K18+K24+K26+K29))/K41,0) -> 3.2905375 | L45: =IFERROR((L8+L12-(L15+L18+L24+L26+L29))/L41,0) -> 3.4516257 | M45: =IFERROR((M8+M12-(M15+M18+M24+M26+M29))/M41,0) -> 3.4872058 | N45: =IFERROR((N8+N12-(N15+N18+N24+N26+N29))/N41,0) -> 3.3059807 | O45: =IFERROR((O8+O12-(O15+O18+O24+O26+O29))/O41,0) -> 3.0678822 | P45: =IFERROR((P8+P12-(P15+P18+P24+P26+P29))/P41,0) -> 2.7159649 | Q45: =IFERROR((Q8+Q12-(Q15+Q18+Q24+Q26+Q29))/Q41,0) -> 2.3354008 | ... S45: =IFERROR((S8+S12-(S15+S18+S24+S26+S29))/S41,0) -> 2.5335175 | T45: 2.13 | U45: 2.13 | V45: =+V36/V41 -> 3.0308152 | W45: =V45/V$39 -> 6.3413207e-08 | Y45: =IFERROR((Y8+Y12-(Y15+Y18+Y24+Y26+Y29))/Y41,0) -> 2.53 | Z45: =IFERROR((Z8+Z12-(Z15+Z18+Z24+Z26+Z29))/Z41,0) -> 2.5380299 | AA45: =IFERROR((AA8+AA12-(AA15+AA18+AA24+AA26+AA29))/AA41,0) -> 2.5827188 | AB45: =IFERROR((AB8+AB12-(AB15+AB18+AB24+AB26+AB29))/AB41,0) -> 2.5299596 | AC45: =IFERROR((AC8+AC12-(AC15+AC18+AC24+AC26+AC29))/AC41,0) -> 2.5310676 | AD45: =IFERROR((AD8+AD12-(AD15+AD18+AD24+AD26+AD29))/AD41,0) -> 2.5681687 | AE45: =IFERROR((AE8+AE12-(AE15+AE18+AE24+AE26+AE29))/AE41,0) -> 2.4861956 | AF45: =IFERROR((AF8+AF12-(AF15+AF18+AF24+AF26+AF29))/AF41,0) -> 2.5444677 | ... AJ45: =IFERROR((AJ8+AJ12-(AJ15+AJ18+AJ24+AJ26+AJ29))/AJ41,0) -> 2.5064084 | AK45: =+AK36/AK41 -> 2.5319055 | AL45: =AK45/AK$39 -> 5.1069479e-08 | AM45: =IFERROR(AK45/V45-1,0) -> -0.16461237
I46: Diesel | J46: =IFERROR((J9-(J16+J19+J27))/J42,0) -> 3.2090808 | K46: =IFERROR((K9-(K16+K19+K27))/K42,0) -> 2.5996052 | L46: =IFERROR((L9-(L16+L19+L27))/L42,0) -> 2.6954191 | M46: =IFERROR((M9-(M16+M19+M27))/M42,0) -> 2.5053703 | N46: =IFERROR((N9-(N16+N19+N27))/N42,0) -> 2.5528658 | O46: =IFERROR((O9-(O16+O19+O27))/O42,0) -> 2.0997857 | P46: =IFERROR((P9-(P16+P19+P27))/P42,0) -> 2.0353756 | Q46: =IFERROR((Q9-(Q16+Q19+Q27))/Q42,0) -> 2.4244448 | ... S46: =IFERROR((S9-(S16+S19+S27))/S42,0) -> 2.7484219 | T46: 2.05 | U46: 2.05 | V46: =IFERROR(+V37/V42,0) -> 2.6797575 | W46: =V46/V$39 -> 5.606809e-08 | Y46: =IFERROR((Y9+Y11-(Y16+Y19+Y27))/Y42,0) -> 2.44 | Z46: =IFERROR((Z9+Z11-(Z16+Z19+Z27))/Z42,0) -> 2.3903965 | AA46: =IFERROR((AA9+AA11-(AA16+AA19+AA27))/AA42,0) -> 2.4891581 | AB46: =IFERROR((AB9+AB11-(AB16+AB19+AB27))/AB42,0) -> 2.3736138 | AC46: =IFERROR((AC9+AC11-(AC16+AC19+AC27))/AC42,0) -> 2.5077055 | AD46: =IFERROR((AD9+AD11-(AD16+AD19+AD27))/AD42,0) -> 2.4361362 | AE46: =IFERROR((AE9+AE11-(AE16+AE19+AE27))/AE42,0) -> 2.4631419 | AF46: =IFERROR((AF9+AF11-(AF16+AF19+AF27))/AF42,0) -> 2.44 | ... AJ46: =IFERROR((AJ9+AJ11-(AJ16+AJ19+AJ27))/AJ42,0) -> 2.3887601 | AK46: =IFERROR(+AK37/AK42,0) -> 2.4420673 | AL46: =AK46/AK$39 -> 4.9257409e-08 | AM46: =IFERROR(AK46/V46-1,0) -> -0.088698401
E48: ( menos ) | I48: GASTO ESTACIONES
A50: E - GASTOS DE OPERACIÓN | B50: estaciones | I50: E - GASTOS DE OPERACIÓN | J50: =SUM(J51:J90) -> 1461923 | K50: =SUM(K51:K90) -> 1540749 | L50: =SUM(L51:L90) -> 1586455 | M50: =SUM(M51:M90) -> 1475793 | N50: =SUM(N51:N90) -> 1563436 | O50: =SUM(O51:O90) -> 1546044 | P50: =SUM(P51:P90) -> 1664258 | Q50: =SUM(Q51:Q90) -> 1730204 | ... V50: =SUM(V51:V90) -> 19224301 | W50: =V50/V$6 -> 0.021451769 | Y50: =SUM(Y51:Y90) -> 1618230.5 | Z50: =SUM(Z51:Z90) -> 1580031.9 | AA50: =SUM(AA51:AA90) -> 2041213.3 | AB50: =SUM(AB51:AB90) -> 1599133.9 | AC50: =SUM(AC51:AC90) -> 1576904.9 | AD50: =SUM(AD51:AD90) -> 1685312.9 | AE50: =SUM(AE51:AE90) -> 1668523.6 | AF50: =SUM(AF51:AF90) -> 1770034 | ... AK50: =SUM(AK51:AK90) -> 20707077 | AL50: =AK50/AK$6 -> 0.021498696 | AM50: =IFERROR(AK50/V50-1,0) -> 0.077130287
A51: E - GASTOS DE OPERACIÓN | B51: estaciones | C51: Servicios Administrativos | I51: Traslado de Valores | J51: =SUM(A:B!J51) -> 260645 | K51: =SUM(A:B!K51) -> 231021 | L51: =SUM(A:B!L51) -> 337830 | M51: =SUM(A:B!M51) -> 235718 | N51: =SUM(A:B!N51) -> 275972 | O51: =SUM(A:B!O51) -> 184532 | P51: =SUM(A:B!P51) -> 231937 | Q51: =SUM(A:B!Q51) -> 332077 | ... U51: =SUM(A:B!U51) -> 287887.22 | V51: =SUM(J51:U51) -> 3241280.9 | W51: =V51/V$6 -> 0.0036168394 | Y51: =SUM(A:B!Y51) -> 262450.43 | Z51: =SUM(A:B!Z51) -> 252088.36 | AA51: =SUM(A:B!AA51) -> 280138.02 | AB51: =SUM(A:B!AB51) -> 269811.61 | AC51: =SUM(A:B!AC51) -> 293266.45 | AD51: =SUM(A:B!AD51) -> 288475.3 | AE51: =SUM(A:B!AE51) -> 287748.21 | AF51: =SUM(A:B!AF51) -> 292873.61 | ... AJ51: =SUM(A:B!AJ51) -> 280903.84 | AK51: =SUM(Y51:AJ51) -> 3373437.6 | AL51: =AK51/AK$6 -> 0.0035024021 | AM51: =IFERROR(AK51/V51-1,0) -> 0.040772985 | AN51: =+AK51-V51 -> 132156.7 | AO51: Nueva Cotizacion Armstrong
A52: E - GASTOS DE OPERACIÓN | B52: estaciones | I52: Servicios Administrativos | J52: =SUM(A:B!J52) -> 426209 | K52: =SUM(A:B!K52) -> 426209 | L52: =SUM(A:B!L52) -> 426209 | M52: =SUM(A:B!M52) -> 426209 | N52: =SUM(A:B!N52) -> 426209 | O52: =SUM(A:B!O52) -> 426209 | P52: =SUM(A:B!P52) -> 426209 | Q52: =SUM(A:B!Q52) -> 426209 | ... U52: =SUM(A:B!U52) -> 441378 | V52: =SUM(J52:U52) -> 5175184 | W52: =V52/V$6 -> 0.0057748187 | Y52: =SUM(A:B!Y52) -> 451038 | Z52: =SUM(A:B!Z52) -> 451038 | AA52: =SUM(A:B!AA52) -> 451038 | AB52: =SUM(A:B!AB52) -> 451038 | AC52: =SUM(A:B!AC52) -> 451038 | AD52: =SUM(A:B!AD52) -> 451038 | AE52: =SUM(A:B!AE52) -> 451038 | AF52: =SUM(A:B!AF52) -> 451038 | ... AJ52: =SUM(A:B!AJ52) -> 468693.12 | AK52: =SUM(Y52:AJ52) -> 5483076.5 | AL52: =AK52/AK$6 -> 0.0056926912 | AM52: =IFERROR(AK52/V52-1,0) -> 0.059494016 | AN52: Ok, dentro premisa
A53: E - GASTOS DE OPERACIÓN | B53: estaciones | I53: Asesoría en sistemas | J53: =SUM(A:B!J53) -> 0 | K53: =SUM(A:B!K53) -> 0 | L53: =SUM(A:B!L53) -> 0 | M53: =SUM(A:B!M53) -> 0 | N53: =SUM(A:B!N53) -> 0 | O53: =SUM(A:B!O53) -> 0 | P53: =SUM(A:B!P53) -> 0 | Q53: =SUM(A:B!Q53) -> 0 | ... U53: =SUM(A:B!U53) -> 0 | V53: =SUM(J53:U53) -> 0 | W53: =V53/V$6 -> 0 | Y53: =SUM(A:B!Y53) -> 0 | Z53: =SUM(A:B!Z53) -> 0 | AA53: =SUM(A:B!AA53) -> 0 | AB53: =SUM(A:B!AB53) -> 0 | AC53: =SUM(A:B!AC53) -> 0 | AD53: =SUM(A:B!AD53) -> 0 | AE53: =SUM(A:B!AE53) -> 0 | AF53: =SUM(A:B!AF53) -> 0 | ... AJ53: =SUM(A:B!AJ53) -> 0 | AK53: =SUM(Y53:AJ53) -> 0 | AL53: =AK53/AK$6 -> 0 | AM53: =IFERROR(AK53/V53-1,0) -> 0
A54: E - GASTOS DE OPERACIÓN | B54: estaciones | I54: Otros Gastos | J54: =SUM(A:B!J54) -> 0 | K54: =SUM(A:B!K54) -> 0 | L54: =SUM(A:B!L54) -> 0 | M54: =SUM(A:B!M54) -> 0 | N54: =SUM(A:B!N54) -> 0 | O54: =SUM(A:B!O54) -> 0 | P54: =SUM(A:B!P54) -> 1160 | Q54: =SUM(A:B!Q54) -> 0 | ... U54: =SUM(A:B!U54) -> 0 | V54: =SUM(J54:U54) -> 1160 | W54: =V54/V$6 -> 1.2944061e-06 | Y54: =SUM(A:B!Y54) -> 0 | Z54: =SUM(A:B!Z54) -> 0 | AA54: =SUM(A:B!AA54) -> 0 | AB54: =SUM(A:B!AB54) -> 0 | AC54: =SUM(A:B!AC54) -> 0 | AD54: =SUM(A:B!AD54) -> 0 | AE54: =SUM(A:B!AE54) -> 0 | AF54: =SUM(A:B!AF54) -> 0 | ... AJ54: =SUM(A:B!AJ54) -> 8694.84 | AK54: =SUM(Y54:AJ54) -> 8694.84 | AL54: =AK54/AK$6 -> 9.0272385e-06 | AM54: =IFERROR(AK54/V54-1,0) -> 6.4955517 | AN54: =+AK54-V54 -> 7534.84 | AO54: Ok Revisado
A55: E - GASTOS DE OPERACIÓN | B55: estaciones | C55: Costo Marketing | I55: Otros impuestos y derechos | J55: =SUM(A:B!J55) -> 0 | K55: =SUM(A:B!K55) -> 0 | L55: =SUM(A:B!L55) -> 0 | M55: =SUM(A:B!M55) -> 0 | N55: =SUM(A:B!N55) -> 0 | O55: =SUM(A:B!O55) -> 0 | P55: =SUM(A:B!P55) -> 0 | Q55: =SUM(A:B!Q55) -> 0 | ... U55: =SUM(A:B!U55) -> 0 | V55: =SUM(J55:U55) -> 0 | W55: =V55/V$6 -> 0 | Y55: =SUM(A:B!Y55) -> 15505.798 | Z55: =SUM(A:B!Z55) -> 0 | AA55: =SUM(A:B!AA55) -> 358383.71 | AB55: =SUM(A:B!AB55) -> 0 | AC55: =SUM(A:B!AC55) -> 15505.798 | AD55: =SUM(A:B!AD55) -> 0 | AE55: =SUM(A:B!AE55) -> 0 | AF55: =SUM(A:B!AF55) -> 0 | ... AJ55: =SUM(A:B!AJ55) -> 0 | AK55: =SUM(Y55:AJ55) -> 389395.3 | AL55: =AK55/AK$6 -> 0.00040428165 | AM55: =IFERROR(AK55/V55-1,0) -> 0 | AO55: Satelite IP y Pruebas Mecanicas tanques
A56: E - GASTOS DE OPERACIÓN | B56: estaciones | I56: Limpieza | J56: =SUM(A:B!J56) -> 13379 | K56: =SUM(A:B!K56) -> 22956 | L56: =SUM(A:B!L56) -> 20639 | M56: =SUM(A:B!M56) -> 20334 | N56: =SUM(A:B!N56) -> 21736 | O56: =SUM(A:B!O56) -> 22160 | P56: =SUM(A:B!P56) -> 17121 | Q56: =SUM(A:B!Q56) -> 19114 | ... U56: =SUM(A:B!U56) -> 26641.852 | V56: =SUM(J56:U56) -> 264006.41 | W56: =V56/V$6 -> 0.00029459612 | Y56: =SUM(A:B!Y56) -> 22888.131 | Z56: =SUM(A:B!Z56) -> 22888.131 | AA56: =SUM(A:B!AA56) -> 22888.131 | AB56: =SUM(A:B!AB56) -> 22888.131 | AC56: =SUM(A:B!AC56) -> 22888.131 | AD56: =SUM(A:B!AD56) -> 22888.131 | AE56: =SUM(A:B!AE56) -> 22888.131 | AF56: =SUM(A:B!AF56) -> 22888.131 | ... AJ56: =SUM(A:B!AJ56) -> 22888.131 | AK56: =SUM(Y56:AJ56) -> 274657.57 | AL56: =AK56/AK$6 -> 0.00028515757 | AM56: =IFERROR(AK56/V56-1,0) -> 0.04034435 | AN56: =+AK56-V56 -> 10651.167 | AO56: =+AK56/7/12 -> 3269.733 | AP56: =+V56/7/12 -> 3142.9334 | AQ56: =+AP56*1.04 -> 3268.6508
A57: E - GASTOS DE OPERACIÓN | B57: estaciones | I57: Propaganda y publicidad | J57: =SUM(A:B!J57) -> 27502 | K57: =SUM(A:B!K57) -> 78424 | L57: =SUM(A:B!L57) -> 57419 | M57: =SUM(A:B!M57) -> 76267 | N57: =SUM(A:B!N57) -> 123704 | O57: =SUM(A:B!O57) -> 55712 | P57: =SUM(A:B!P57) -> 176653 | Q57: =SUM(A:B!Q57) -> 80915 | ... U57: =SUM(A:B!U57) -> 0 | V57: =SUM(J57:U57) -> 750370.6 | W57: =V57/V$6 -> 0.00083731403 | Y57: =SUM(A:B!Y57) -> 49063.74 | Z57: =SUM(A:B!Z57) -> 10868.55 | AA57: =SUM(A:B!AA57) -> 135204.76 | AB57: =SUM(A:B!AB57) -> 56516.46 | AC57: =SUM(A:B!AC57) -> 13042.26 | AD57: =SUM(A:B!AD57) -> 65625.34 | AE57: =SUM(A:B!AE57) -> 44322.982 | AF57: =SUM(A:B!AF57) -> 59621.76 | ... AJ57: =SUM(A:B!AJ57) -> 61588.45 | AK57: =SUM(Y57:AJ57) -> 769244.92 | AL57: =AK57/AK$6 -> 0.00079865268 | AM57: =IFERROR(AK57/V57-1,0) -> 0.025153326
A58: E - GASTOS DE OPERACIÓN | B58: estaciones | I58: Capacitacion al personal | J58: =SUM(A:B!J58) -> 0 | K58: =SUM(A:B!K58) -> 0 | L58: =SUM(A:B!L58) -> 0 | M58: =SUM(A:B!M58) -> 0 | N58: =SUM(A:B!N58) -> 0 | O58: =SUM(A:B!O58) -> 0 | P58: =SUM(A:B!P58) -> 0 | Q58: =SUM(A:B!Q58) -> 0 | ... U58: =SUM(A:B!U58) -> 0 | V58: =SUM(J58:U58) -> 9100 | W58: =V58/V$6 -> 1.0154393e-05 | Y58: =SUM(A:B!Y58) -> 6033.9363 | Z58: =SUM(A:B!Z58) -> 19308.596 | AA58: =SUM(A:B!AA58) -> 3620.3618 | AB58: =SUM(A:B!AB58) -> 0 | AC58: =SUM(A:B!AC58) -> 0 | AD58: =SUM(A:B!AD58) -> 0 | AE58: =SUM(A:B!AE58) -> 0 | AF58: =SUM(A:B!AF58) -> 0 | ... AJ58: =SUM(A:B!AJ58) -> 0 | AK58: =SUM(Y58:AJ58) -> 28962.894 | AL58: =AK58/AK$6 -> 3.0070128e-05 | AM58: =IFERROR(AK58/V58-1,0) -> 2.1827356 | AN58: =+AK58-V58 -> 19862.894
A59: E - GASTOS DE OPERACIÓN | B59: estaciones | I59: Honorarios Administrativos P.F. | J59: =SUM(A:B!J59) -> 0 | K59: =SUM(A:B!K59) -> 0 | L59: =SUM(A:B!L59) -> 0 | M59: =SUM(A:B!M59) -> 0 | N59: =SUM(A:B!N59) -> 0 | O59: =SUM(A:B!O59) -> 0 | P59: =SUM(A:B!P59) -> 0 | Q59: =SUM(A:B!Q59) -> 0 | ... U59: =SUM(A:B!U59) -> 0 | V59: =SUM(J59:U59) -> 0 | W59: =V59/V$6 -> 0 | Y59: =SUM(A:B!Y59) -> 0 | Z59: =SUM(A:B!Z59) -> 0 | AA59: =SUM(A:B!AA59) -> 0 | AB59: =SUM(A:B!AB59) -> 0 | AC59: =SUM(A:B!AC59) -> 0 | AD59: =SUM(A:B!AD59) -> 0 | AE59: =SUM(A:B!AE59) -> 0 | AF59: =SUM(A:B!AF59) -> 0 | ... AJ59: =SUM(A:B!AJ59) -> 0 | AK59: =SUM(Y59:AJ59) -> 0 | AL59: =AK59/AK$6 -> 0 | AM59: =IFERROR(AK59/V59-1,0) -> 0
A60: E - GASTOS DE OPERACIÓN | B60: estaciones | I60: Honorarios Administrativos P.M. | J60: =SUM(A:B!J60) -> 35000 | K60: =SUM(A:B!K60) -> 0 | L60: =SUM(A:B!L60) -> 0 | M60: =SUM(A:B!M60) -> 14250 | N60: =SUM(A:B!N60) -> 0 | O60: =SUM(A:B!O60) -> 104998 | P60: =SUM(A:B!P60) -> 84960 | Q60: =SUM(A:B!Q60) -> 132000 | ... U60: =SUM(A:B!U60) -> 60000 | V60: =SUM(J60:U60) -> 611208 | W60: =V60/V$6 -> 0.00068202703 | Y60: =SUM(A:B!Y60) -> 36312.5 | Z60: =SUM(A:B!Z60) -> 0 | AA60: =SUM(A:B!AA60) -> 0 | AB60: =SUM(A:B!AB60) -> 14784.375 | AC60: =SUM(A:B!AC60) -> 0 | AD60: =SUM(A:B!AD60) -> 108935.43 | AE60: =SUM(A:B!AE60) -> 88146 | AF60: =SUM(A:B!AF60) -> 136950 | ... AJ60: =SUM(A:B!AJ60) -> 62250 | AK60: =SUM(Y60:AJ60) -> 634128.3 | AL60: =AK60/AK$6 -> 0.00065837064 | AM60: =IFERROR(AK60/V60-1,0) -> 0.0375
A61: E - GASTOS DE OPERACIÓN | B61: estaciones | I61: Asistencia técnica | J61: =SUM(A:B!J61) -> 7125 | K61: =SUM(A:B!K61) -> 7125 | L61: =SUM(A:B!L61) -> 0 | M61: =SUM(A:B!M61) -> 0 | N61: =SUM(A:B!N61) -> 0 | O61: =SUM(A:B!O61) -> 0 | P61: =SUM(A:B!P61) -> 7125 | Q61: =SUM(A:B!Q61) -> 0 | ... U61: =SUM(A:B!U61) -> 0 | V61: =SUM(J61:U61) -> 21375 | W61: =V61/V$6 -> 2.3851664e-05 | Y61: =SUM(A:B!Y61) -> 7392.1875 | Z61: =SUM(A:B!Z61) -> 7392.1875 | AA61: =SUM(A:B!AA61) -> 0 | AB61: =SUM(A:B!AB61) -> 0 | AC61: =SUM(A:B!AC61) -> 0 | AD61: =SUM(A:B!AD61) -> 0 | AE61: =SUM(A:B!AE61) -> 7392.1875 | AF61: =SUM(A:B!AF61) -> 0 | ... AJ61: =SUM(A:B!AJ61) -> 0 | AK61: =SUM(Y61:AJ61) -> 22176.563 | AL61: =AK61/AK$6 -> 2.3024359e-05 | AM61: =IFERROR(AK61/V61-1,0) -> 0.0375
A62: E - GASTOS DE OPERACIÓN | B62: estaciones | I62: Gastos no deducibles (sin requisitos fiscales) | J62: =SUM(A:B!J62) -> 0 | K62: =SUM(A:B!K62) -> 0 | L62: =SUM(A:B!L62) -> 0 | M62: =SUM(A:B!M62) -> 0 | N62: =SUM(A:B!N62) -> 2390 | O62: =SUM(A:B!O62) -> 0 | P62: =SUM(A:B!P62) -> 0 | Q62: =SUM(A:B!Q62) -> 0 | ... U62: =SUM(A:B!U62) -> 0 | V62: =SUM(J62:U62) -> 2390 | W62: =V62/V$6 -> 2.6669229e-06 | Y62: =SUM(A:B!Y62) -> 0 | Z62: =SUM(A:B!Z62) -> 0 | AA62: =SUM(A:B!AA62) -> 0 | AB62: =SUM(A:B!AB62) -> 0 | AC62: =SUM(A:B!AC62) -> 2479.625 | AD62: =SUM(A:B!AD62) -> 0 | AE62: =SUM(A:B!AE62) -> 0 | AF62: =SUM(A:B!AF62) -> 0 | ... AJ62: =SUM(A:B!AJ62) -> 0 | AK62: =SUM(Y62:AJ62) -> 2479.625 | AL62: =AK62/AK$6 -> 2.5744196e-06 | AM62: =IFERROR(AK62/V62-1,0) -> 0.0375
A63: E - GASTOS DE OPERACIÓN | B63: estaciones | I63: Papelería y artículos de oficina | J63: =SUM(A:B!J63) -> 4090 | K63: =SUM(A:B!K63) -> -3499 | L63: =SUM(A:B!L63) -> 2988 | M63: =SUM(A:B!M63) -> 216 | N63: =SUM(A:B!N63) -> 781 | O63: =SUM(A:B!O63) -> 122 | P63: =SUM(A:B!P63) -> 186 | Q63: =SUM(A:B!Q63) -> 163 | ... U63: =SUM(A:B!U63) -> 0 | V63: =SUM(J63:U63) -> 5432 | W63: =V63/V$6 -> 6.0613913e-06 | Y63: =SUM(A:B!Y63) -> 0 | Z63: =SUM(A:B!Z63) -> 0 | AA63: =SUM(A:B!AA63) -> 0 | AB63: =SUM(A:B!AB63) -> 0 | AC63: =SUM(A:B!AC63) -> 0 | AD63: =SUM(A:B!AD63) -> 0 | AE63: =SUM(A:B!AE63) -> 0 | AF63: =SUM(A:B!AF63) -> 0 | ... AJ63: =SUM(A:B!AJ63) -> 0 | AK63: =SUM(Y63:AJ63) -> 0 | AL63: =AK63/AK$6 -> 0 | AM63: =IFERROR(AK63/V63-1,0) -> -1 | AN63: =+AK63-V63 -> -5432 | AO63: Rollos termicos
A64: E - GASTOS DE OPERACIÓN | B64: estaciones | I64: Faltantes | J64: =SUM(A:B!J64) -> 4633 | K64: =SUM(A:B!K64) -> 5751 | L64: =SUM(A:B!L64) -> 7472 | M64: =SUM(A:B!M64) -> 9066 | N64: =SUM(A:B!N64) -> 6060 | O64: =SUM(A:B!O64) -> 6638 | P64: =SUM(A:B!P64) -> 1363 | Q64: =SUM(A:B!Q64) -> 11196 | ... U64: =SUM(A:B!U64) -> 8078.5185 | V64: =SUM(J64:U64) -> 84493.074 | W64: =V64/V$6 -> 9.428306e-05 | Y64: =SUM(A:B!Y64) -> 8298.3967 | Z64: =SUM(A:B!Z64) -> 8298.3967 | AA64: =SUM(A:B!AA64) -> 8298.3967 | AB64: =SUM(A:B!AB64) -> 8298.3967 | AC64: =SUM(A:B!AC64) -> 8298.3967 | AD64: =SUM(A:B!AD64) -> 8298.3967 | AE64: =SUM(A:B!AE64) -> 8298.3967 | AF64: =SUM(A:B!AF64) -> 8298.3967 | ... AJ64: =SUM(A:B!AJ64) -> 8298.3967 | AK64: =SUM(Y64:AJ64) -> 99580.76 | AL64: =AK64/AK$6 -> 0.00010338767 | AM64: =IFERROR(AK64/V64-1,0) -> 0.17856714
A65: E - GASTOS DE OPERACIÓN | B65: estaciones | I65: Licencias y Permisos | J65: =SUM(A:B!J65) -> 0 | K65: =SUM(A:B!K65) -> 0 | L65: =SUM(A:B!L65) -> 0 | M65: =SUM(A:B!M65) -> 0 | N65: =SUM(A:B!N65) -> 0 | O65: =SUM(A:B!O65) -> 0 | P65: =SUM(A:B!P65) -> 0 | Q65: =SUM(A:B!Q65) -> 0 | ... U65: =SUM(A:B!U65) -> 0 | V65: =SUM(J65:U65) -> 0 | W65: =V65/V$6 -> 0 | Y65: =SUM(A:B!Y65) -> 0 | Z65: =SUM(A:B!Z65) -> 0 | AA65: =SUM(A:B!AA65) -> 0 | AB65: =SUM(A:B!AB65) -> 0 | AC65: =SUM(A:B!AC65) -> 0 | AD65: =SUM(A:B!AD65) -> 0 | AE65: =SUM(A:B!AE65) -> 0 | AF65: =SUM(A:B!AF65) -> 0 | ... AJ65: =SUM(A:B!AJ65) -> 0 | AK65: =SUM(Y65:AJ65) -> 0 | AL65: =AK65/AK$6 -> 0 | AM65: =IFERROR(AK65/V65-1,0) -> 0 | AN65: =+AK65-V65 -> 0 | AO65: Ok, Revisado (Licencia de suelo, funcionamiento, CANACO, SIEM y aguas residuales
A66: E - GASTOS DE OPERACIÓN | B66: estaciones | I66: Licencias, Software, Antivirus | J66: =SUM(A:B!J66) -> 8219 | K66: =SUM(A:B!K66) -> 0 | L66: =SUM(A:B!L66) -> 0 | M66: =SUM(A:B!M66) -> 24988 | N66: =SUM(A:B!N66) -> 0 | O66: =SUM(A:B!O66) -> 0 | P66: =SUM(A:B!P66) -> 0 | Q66: =SUM(A:B!Q66) -> 7411 | ... U66: =SUM(A:B!U66) -> 0 | V66: =SUM(J66:U66) -> 54784.6 | W66: =V66/V$6 -> 6.1132345e-05 | Y66: =SUM(A:B!Y66) -> 0 | Z66: =SUM(A:B!Z66) -> 15458.183 | AA66: =SUM(A:B!AA66) -> 0 | AB66: =SUM(A:B!AB66) -> 24925.208 | AC66: =SUM(A:B!AC66) -> 0 | AD66: =SUM(A:B!AD66) -> 0 | AE66: =SUM(A:B!AE66) -> 15898.101 | AF66: =SUM(A:B!AF66) -> 15288.427 | ... AJ66: =SUM(A:B!AJ66) -> 0 | AK66: =SUM(Y66:AJ66) -> 71569.919 | AL66: =AK66/AK$6 -> 7.4305994e-05 | AM66: =IFERROR(AK66/V66-1,0) -> 0.30638755 | AN66: =+AK66-V66 -> 16785.319
A67: E - GASTOS DE OPERACIÓN | B67: estaciones | I67: Fletes Combustible | J67: =SUM(A:B!J67) -> 23086 | K67: =SUM(A:B!K67) -> 23086 | L67: =SUM(A:B!L67) -> 23086 | M67: =SUM(A:B!M67) -> 23086 | N67: =SUM(A:B!N67) -> 23086 | O67: =SUM(A:B!O67) -> 23086 | P67: =SUM(A:B!P67) -> 23086 | Q67: =SUM(A:B!Q67) -> 23086 | ... U67: =SUM(A:B!U67) -> 23086 | V67: =SUM(J67:U67) -> 277032 | W67: =V67/V$6 -> 0.00030913096 | Y67: =SUM(A:B!Y67) -> 34598.217 | Z67: =SUM(A:B!Z67) -> 34598.217 | AA67: =SUM(A:B!AA67) -> 34598.217 | AB67: =SUM(A:B!AB67) -> 34598.217 | AC67: =SUM(A:B!AC67) -> 34598.217 | AD67: =SUM(A:B!AD67) -> 34598.217 | AE67: =SUM(A:B!AE67) -> 34598.217 | AF67: =SUM(A:B!AF67) -> 34598.217 | ... AJ67: =SUM(A:B!AJ67) -> 34598.217 | AK67: =SUM(Y67:AJ67) -> 415178.61 | AL67: =AK67/AK$6 -> 0.00043105064 | AM67: =IFERROR(AK67/V67-1,0) -> 0.49866662
A68: E - GASTOS DE OPERACIÓN | B68: estaciones | I68: Viáticos y gastos de viaje | J68: =SUM(A:B!J68) -> 0 | K68: =SUM(A:B!K68) -> 0 | L68: =SUM(A:B!L68) -> 0 | M68: =SUM(A:B!M68) -> 0 | N68: =SUM(A:B!N68) -> 0 | O68: =SUM(A:B!O68) -> 0 | P68: =SUM(A:B!P68) -> 0 | Q68: =SUM(A:B!Q68) -> 0 | ... U68: =SUM(A:B!U68) -> 0 | V68: =SUM(J68:U68) -> 0 | W68: =V68/V$6 -> 0 | Y68: =SUM(A:B!Y68) -> 0 | Z68: =SUM(A:B!Z68) -> 0 | AA68: =SUM(A:B!AA68) -> 0 | AB68: =SUM(A:B!AB68) -> 0 | AC68: =SUM(A:B!AC68) -> 0 | AD68: =SUM(A:B!AD68) -> 0 | AE68: =SUM(A:B!AE68) -> 0 | AF68: =SUM(A:B!AF68) -> 0 | ... AJ68: =SUM(A:B!AJ68) -> 0 | AK68: =SUM(Y68:AJ68) -> 0 | AL68: =AK68/AK$6 -> 0 | AM68: =IFERROR(AK68/V68-1,0) -> 0
A69: E - GASTOS DE OPERACIÓN | B69: estaciones | I69: Recoleccion de Basura | J69: =SUM(A:B!J69) -> 0 | K69: =SUM(A:B!K69) -> 0 | L69: =SUM(A:B!L69) -> 0 | M69: =SUM(A:B!M69) -> 0 | N69: =SUM(A:B!N69) -> 662 | O69: =SUM(A:B!O69) -> 0 | P69: =SUM(A:B!P69) -> 0 | Q69: =SUM(A:B!Q69) -> 0 | ... U69: =SUM(A:B!U69) -> 0 | V69: =SUM(J69:U69) -> 845 | W69: =V69/V$6 -> 9.4290789e-07 | Y69: =SUM(A:B!Y69) -> 0 | Z69: =SUM(A:B!Z69) -> 0 | AA69: =SUM(A:B!AA69) -> 0 | AB69: =SUM(A:B!AB69) -> 0 | AC69: =SUM(A:B!AC69) -> 0 | AD69: =SUM(A:B!AD69) -> 0 | AE69: =SUM(A:B!AE69) -> 0 | AF69: =SUM(A:B!AF69) -> 0 | ... AJ69: =SUM(A:B!AJ69) -> 0 | AK69: =SUM(Y69:AJ69) -> 0 | AL69: =AK69/AK$6 -> 0 | AM69: =IFERROR(AK69/V69-1,0) -> -1
A70: E - GASTOS DE OPERACIÓN | B70: estaciones | I70: Honorarios de Consultoria | J70: =SUM(A:B!J70) -> 15144 | K70: =SUM(A:B!K70) -> 21968 | L70: =SUM(A:B!L70) -> 12968 | M70: =SUM(A:B!M70) -> 0 | N70: =SUM(A:B!N70) -> 9800 | O70: =SUM(A:B!O70) -> 17450 | P70: =SUM(A:B!P70) -> 9800 | Q70: =SUM(A:B!Q70) -> 9800 | ... U70: =SUM(A:B!U70) -> 10600 | V70: =SUM(J70:U70) -> 139330 | W70: =V70/V$6 -> 0.00015547379 | Y70: =SUM(A:B!Y70) -> 10500 | Z70: =SUM(A:B!Z70) -> 10500 | AA70: =SUM(A:B!AA70) -> 10500 | AB70: =SUM(A:B!AB70) -> 10500 | AC70: =SUM(A:B!AC70) -> 10500 | AD70: =SUM(A:B!AD70) -> 10500 | AE70: =SUM(A:B!AE70) -> 10500 | AF70: =SUM(A:B!AF70) -> 10500 | ... AJ70: =SUM(A:B!AJ70) -> 10500 | AK70: =SUM(Y70:AJ70) -> 126000 | AL70: =AK70/AK$6 -> 0.0001308169 | AM70: =IFERROR(AK70/V70-1,0) -> -0.095672145
A71: E - GASTOS DE OPERACIÓN | B71: estaciones | I71: Agua para consumo | J71: =SUM(A:B!J71) -> 0 | K71: =SUM(A:B!K71) -> 0 | L71: =SUM(A:B!L71) -> 0 | M71: =SUM(A:B!M71) -> 0 | N71: =SUM(A:B!N71) -> 0 | O71: =SUM(A:B!O71) -> 0 | P71: =SUM(A:B!P71) -> 0 | Q71: =SUM(A:B!Q71) -> 0 | ... U71: =SUM(A:B!U71) -> 0 | V71: =SUM(J71:U71) -> 0 | W71: =V71/V$6 -> 0 | Y71: =SUM(A:B!Y71) -> 0 | Z71: =SUM(A:B!Z71) -> 0 | AA71: =SUM(A:B!AA71) -> 0 | AB71: =SUM(A:B!AB71) -> 0 | AC71: =SUM(A:B!AC71) -> 0 | AD71: =SUM(A:B!AD71) -> 0 | AE71: =SUM(A:B!AE71) -> 0 | AF71: =SUM(A:B!AF71) -> 0 | ... AJ71: =SUM(A:B!AJ71) -> 0 | AK71: =SUM(Y71:AJ71) -> 0 | AL71: =AK71/AK$6 -> 0 | AM71: =IFERROR(AK71/V71-1,0) -> 0
I72: Fletes Mensajeria | J72: =SUM(A:B!J72) -> 6314 | K72: =SUM(A:B!K72) -> 6314 | L72: =SUM(A:B!L72) -> 6314 | M72: =SUM(A:B!M72) -> 6314 | N72: =SUM(A:B!N72) -> 6314 | O72: =SUM(A:B!O72) -> 6314 | P72: =SUM(A:B!P72) -> 6314 | Q72: =SUM(A:B!Q72) -> 6314 | ... U72: =SUM(A:B!U72) -> 6314 | V72: =SUM(J72:U72) -> 75768 | W72: =V72/V$6 -> 8.4547035e-05 | Y72: =SUM(A:B!Y72) -> 6550.775 | Z72: =SUM(A:B!Z72) -> 6550.775 | AA72: =SUM(A:B!AA72) -> 6550.775 | AB72: =SUM(A:B!AB72) -> 6550.775 | AC72: =SUM(A:B!AC72) -> 6550.775 | AD72: =SUM(A:B!AD72) -> 6550.775 | AE72: =SUM(A:B!AE72) -> 6550.775 | AF72: =SUM(A:B!AF72) -> 6550.775 | ... AJ72: =SUM(A:B!AJ72) -> 6550.775 | AK72: =SUM(Y72:AJ72) -> 78609.3 | AL72: =AK72/AK$6 -> 8.1614486e-05 | AM72: =IFERROR(AK72/V72-1,0) -> 0.0375
I73: Honorarios Admvos P.F. | J73: =SUM(A:B!J73) -> 0 | K73: =SUM(A:B!K73) -> 0 | L73: =SUM(A:B!L73) -> 0 | M73: =SUM(A:B!M73) -> 0 | N73: =SUM(A:B!N73) -> 0 | O73: =SUM(A:B!O73) -> 22400 | P73: =SUM(A:B!P73) -> 0 | Q73: =SUM(A:B!Q73) -> 0 | ... U73: =SUM(A:B!U73) -> 0 | V73: =SUM(J73:U73) -> 22400 | W73: =V73/V$6 -> 2.4995428e-05 | Y73: =SUM(A:B!Y73) -> 0 | Z73: =SUM(A:B!Z73) -> 0 | AA73: =SUM(A:B!AA73) -> 0 | AB73: =SUM(A:B!AB73) -> 0 | AC73: =SUM(A:B!AC73) -> 0 | AD73: =SUM(A:B!AD73) -> 0 | AE73: =SUM(A:B!AE73) -> 0 | AF73: =SUM(A:B!AF73) -> 0 | ... AJ73: =SUM(A:B!AJ73) -> 0 | AK73: =SUM(Y73:AJ73) -> 0 | AL73: =AK73/AK$6 -> 0 | AM73: =IFERROR(AK73/V73-1,0) -> -1
I74: Consumos Propios Combustibles | J74: =SUM(A:B!J74) -> 9100 | K74: =SUM(A:B!K74) -> 9100 | L74: =SUM(A:B!L74) -> 25900 | M74: =SUM(A:B!M74) -> 9100 | N74: =SUM(A:B!N74) -> 9100 | O74: =SUM(A:B!O74) -> 9100 | P74: =SUM(A:B!P74) -> 9100 | Q74: =SUM(A:B!Q74) -> 9100 | ... U74: =SUM(A:B!U74) -> 9100 | V74: =SUM(J74:U74) -> 126000 | W74: =V74/V$6 -> 0.00014059928 | Y74: =SUM(A:B!Y74) -> 9441.25 | Z74: =SUM(A:B!Z74) -> 9441.25 | AA74: =SUM(A:B!AA74) -> 26871.25 | AB74: =SUM(A:B!AB74) -> 9441.25 | AC74: =SUM(A:B!AC74) -> 9441.25 | AD74: =SUM(A:B!AD74) -> 9441.25 | AE74: =SUM(A:B!AE74) -> 9441.25 | AF74: =SUM(A:B!AF74) -> 9441.25 | ... AJ74: =SUM(A:B!AJ74) -> 9441.25 | AK74: =SUM(Y74:AJ74) -> 130725 | AL74: =AK74/AK$6 -> 0.00013572254 | AM74: =IFERROR(AK74/V74-1,0) -> 0.0375
I75: Renta Equipo de Sistemas | J75: =SUM(A:B!J75) -> 0 | K75: =SUM(A:B!K75) -> 0 | L75: =SUM(A:B!L75) -> 0 | M75: =SUM(A:B!M75) -> 0 | N75: =SUM(A:B!N75) -> 0 | O75: =SUM(A:B!O75) -> 0 | P75: =SUM(A:B!P75) -> 0 | Q75: =SUM(A:B!Q75) -> 0 | ... U75: =SUM(A:B!U75) -> 0 | V75: =SUM(J75:U75) -> 0 | W75: =V75/V$6 -> 0 | Y75: =SUM(A:B!Y75) -> 0 | Z75: =SUM(A:B!Z75) -> 0 | AA75: =SUM(A:B!AA75) -> 0 | AB75: =SUM(A:B!AB75) -> 0 | AC75: =SUM(A:B!AC75) -> 0 | AD75: =SUM(A:B!AD75) -> 0 | AE75: =SUM(A:B!AE75) -> 0 | AF75: =SUM(A:B!AF75) -> 0 | ... AJ75: =SUM(A:B!AJ75) -> 0 | AK75: =SUM(Y75:AJ75) -> 0 | AL75: =AK75/AK$6 -> 0 | AM75: =IFERROR(AK75/V75-1,0) -> 0
I76: Timbrado Facturas | J76: =SUM(A:B!J76) -> 7032 | K76: =SUM(A:B!K76) -> 6170 | L76: =SUM(A:B!L76) -> 6043 | M76: =SUM(A:B!M76) -> 6026 | N76: =SUM(A:B!N76) -> 5614 | O76: =SUM(A:B!O76) -> 6375 | P76: =SUM(A:B!P76) -> 6423 | Q76: =SUM(A:B!Q76) -> 6222 | ... U76: =SUM(A:B!U76) -> 6299.9259 | V76: =SUM(J76:U76) -> 75104.704 | W76: =V76/V$6 -> 8.3806884e-05 | Y76: =SUM(A:B!Y76) -> 6883.415 | Z76: =SUM(A:B!Z76) -> 6883.415 | AA76: =SUM(A:B!AA76) -> 6883.415 | AB76: =SUM(A:B!AB76) -> 6883.415 | AC76: =SUM(A:B!AC76) -> 6883.415 | AD76: =SUM(A:B!AD76) -> 6883.415 | AE76: =SUM(A:B!AE76) -> 6883.415 | AF76: =SUM(A:B!AF76) -> 6883.415 | ... AJ76: =SUM(A:B!AJ76) -> 6883.415 | AK76: =SUM(Y76:AJ76) -> 82600.98 | AL76: =AK76/AK$6 -> 8.5758765e-05 | AM76: =IFERROR(AK76/V76-1,0) -> 0.09981101
I77: Rentas No Deducibles | J77: =SUM(A:B!J77) -> 3787 | K77: =SUM(A:B!K77) -> 3608 | L77: =SUM(A:B!L77) -> 3675 | M77: =SUM(A:B!M77) -> 3984 | N77: =SUM(A:B!N77) -> 3884 | O77: =SUM(A:B!O77) -> 4109 | P77: =SUM(A:B!P77) -> 3912 | Q77: =SUM(A:B!Q77) -> 4420 | ... U77: =SUM(A:B!U77) -> 3782.5185 | V77: =SUM(J77:U77) -> 46509.074 | W77: =V77/V$6 -> 5.1897956e-05 | Y77: =SUM(A:B!Y77) -> 3929.0125 | Z77: =SUM(A:B!Z77) -> 3743.3 | AA77: =SUM(A:B!AA77) -> 3812.8125 | AB77: =SUM(A:B!AB77) -> 4133.4 | AC77: =SUM(A:B!AC77) -> 4029.65 | AD77: =SUM(A:B!AD77) -> 4263.0875 | AE77: =SUM(A:B!AE77) -> 4058.7 | AF77: =SUM(A:B!AF77) -> 4585.75 | ... AJ77: =SUM(A:B!AJ77) -> 3924.363 | AK77: =SUM(Y77:AJ77) -> 48253.164 | AL77: =AK77/AK$6 -> 5.0097854e-05 | AM77: =IFERROR(AK77/V77-1,0) -> 0.0375
I78: Uniformes | J78: =SUM(A:B!J78) -> 0 | K78: =SUM(A:B!K78) -> 0 | L78: =SUM(A:B!L78) -> 0 | M78: =SUM(A:B!M78) -> 0 | N78: =SUM(A:B!N78) -> 0 | O78: =SUM(A:B!O78) -> 0 | P78: =SUM(A:B!P78) -> 0 | Q78: =SUM(A:B!Q78) -> 0 | ... U78: =SUM(A:B!U78) -> 0 | V78: =SUM(J78:U78) -> 0 | W78: =V78/V$6 -> 0 | Y78: =SUM(A:B!Y78) -> 0 | Z78: =SUM(A:B!Z78) -> 0 | AA78: =SUM(A:B!AA78) -> 0 | AB78: =SUM(A:B!AB78) -> 0 | AC78: =SUM(A:B!AC78) -> 0 | AD78: =SUM(A:B!AD78) -> 0 | AE78: =SUM(A:B!AE78) -> 0 | AF78: =SUM(A:B!AF78) -> 0 | ... AJ78: =SUM(A:B!AJ78) -> 0 | AK78: =SUM(Y78:AJ78) -> 0 | AL78: =AK78/AK$6 -> 0 | AM78: =IFERROR(AK78/V78-1,0) -> 0
I79: Contratacion Empleados | J79: =SUM(A:B!J79) -> 23656 | K79: =SUM(A:B!K79) -> 90215 | L79: =SUM(A:B!L79) -> 56390 | M79: =SUM(A:B!M79) -> 29112 | N79: =SUM(A:B!N79) -> 47011 | O79: =SUM(A:B!O79) -> 51226 | P79: =SUM(A:B!P79) -> 43481 | Q79: =SUM(A:B!Q79) -> 37842 | ... U79: =SUM(A:B!U79) -> 37500.403 | V79: =SUM(J79:U79) -> 695003.7 | W79: =V79/V$6 -> 0.00077553191 | Y79: =SUM(A:B!Y79) -> 58039.907 | Z79: =SUM(A:B!Z79) -> 53966.291 | AA79: =SUM(A:B!AA79) -> 62546.173 | AB79: =SUM(A:B!AB79) -> 49076.924 | AC79: =SUM(A:B!AC79) -> 51936.884 | AD79: =SUM(A:B!AD79) -> 17617.357 | AE79: =SUM(A:B!AE79) -> 40497.042 | AF79: =SUM(A:B!AF79) -> 63376.727 | ... AJ79: =SUM(A:B!AJ79) -> 63919.264 | AK79: =SUM(Y79:AJ79) -> 766623.72 | AL79: =AK79/AK$6 -> 0.00079593128 | AM79: =IFERROR(AK79/V79-1,0) -> 0.10304985 | AN79: =+AK79-V79 -> 71620.028
I80: Multas y Recargos | J80: =SUM(A:B!J80) -> 0 | K80: =SUM(A:B!K80) -> 0 | L80: =SUM(A:B!L80) -> 0 | M80: =SUM(A:B!M80) -> 0 | N80: =SUM(A:B!N80) -> 730 | O80: =SUM(A:B!O80) -> 1460 | P80: =SUM(A:B!P80) -> 730 | Q80: =SUM(A:B!Q80) -> 730 | ... U80: =SUM(A:B!U80) -> 750.36 | V80: =SUM(J80:U80) -> 6651.44 | W80: =V80/V$6 -> 7.4221245e-06 | Y80: =SUM(A:B!Y80) -> 978.1695 | Z80: =SUM(A:B!Z80) -> 4042.0655 | AA80: =SUM(A:B!AA80) -> 1552.65 | AB80: =SUM(A:B!AB80) -> 1361.1565 | AC80: =SUM(A:B!AC80) -> 1552.65 | AD80: =SUM(A:B!AD80) -> 3296.7935 | AE80: =SUM(A:B!AE80) -> 1935.637 | AF80: =SUM(A:B!AF80) -> 1744.1435 | ... AJ80: =SUM(A:B!AJ80) -> 1169.663 | AK80: =SUM(Y80:AJ80) -> 21716.398 | AL80: =AK80/AK$6 -> 2.2546603e-05 | AM80: =IFERROR(AK80/V80-1,0) -> 2.2649168
I81: Seguros y fianzas | J81: =SUM(A:B!J81) -> 0 | K81: =SUM(A:B!K81) -> 2659 | L81: =SUM(A:B!L81) -> 0 | M81: =SUM(A:B!M81) -> 0 | N81: =SUM(A:B!N81) -> 0 | O81: =SUM(A:B!O81) -> 0 | P81: =SUM(A:B!P81) -> 11560 | Q81: =SUM(A:B!Q81) -> 0 | ... U81: =SUM(A:B!U81) -> 0 | V81: =SUM(J81:U81) -> 14219 | W81: =V81/V$6 -> 1.5866517e-05 | Y81: =SUM(A:B!Y81) -> 0 | Z81: =SUM(A:B!Z81) -> 0 | AA81: =SUM(A:B!AA81) -> 0 | AB81: =SUM(A:B!AB81) -> 0 | AC81: =SUM(A:B!AC81) -> 0 | AD81: =SUM(A:B!AD81) -> 0 | AE81: =SUM(A:B!AE81) -> 0 | AF81: =SUM(A:B!AF81) -> 0 | ... AJ81: =SUM(A:B!AJ81) -> 0 | AK81: =SUM(Y81:AJ81) -> 0 | AL81: =AK81/AK$6 -> 0 | AM81: =IFERROR(AK81/V81-1,0) -> -1
I82: Vigilancia y seguridad | J82: =SUM(A:B!J82) -> 21806 | K82: =SUM(A:B!K82) -> 18801 | L82: =SUM(A:B!L82) -> 18801 | M82: =SUM(A:B!M82) -> 18801 | N82: =SUM(A:B!N82) -> 18801 | O82: =SUM(A:B!O82) -> 18801 | P82: =SUM(A:B!P82) -> 18801 | Q82: =SUM(A:B!Q82) -> 41113 | ... U82: =SUM(A:B!U82) -> 41113 | V82: =SUM(J82:U82) -> 340177 | W82: =V82/V$6 -> 0.0003795924 | Y82: =SUM(A:B!Y82) -> 41935.26 | Z82: =SUM(A:B!Z82) -> 41935.26 | AA82: =SUM(A:B!AA82) -> 41935.26 | AB82: =SUM(A:B!AB82) -> 41935.26 | AC82: =SUM(A:B!AC82) -> 41935.26 | AD82: =SUM(A:B!AD82) -> 41935.26 | AE82: =SUM(A:B!AE82) -> 41935.26 | AF82: =SUM(A:B!AF82) -> 41935.26 | ... AJ82: =SUM(A:B!AJ82) -> 41935.26 | AK82: =SUM(Y82:AJ82) -> 503223.12 | AL82: =AK82/AK$6 -> 0.00052246103 | AM82: =IFERROR(AK82/V82-1,0) -> 0.47929789
I83: Honorarios Fiscales P.F. | J83: =SUM(A:B!J83) -> 0 | K83: =SUM(A:B!K83) -> 0 | L83: =SUM(A:B!L83) -> 0 | M83: =SUM(A:B!M83) -> 0 | N83: =SUM(A:B!N83) -> 0 | O83: =SUM(A:B!O83) -> 0 | P83: =SUM(A:B!P83) -> 0 | Q83: =SUM(A:B!Q83) -> 0 | ... U83: =SUM(A:B!U83) -> 0 | V83: =SUM(J83:U83) -> 0 | W83: =V83/V$6 -> 0 | Y83: =SUM(A:B!Y83) -> 0 | Z83: =SUM(A:B!Z83) -> 0 | AA83: =SUM(A:B!AA83) -> 0 | AB83: =SUM(A:B!AB83) -> 0 | AC83: =SUM(A:B!AC83) -> 0 | AD83: =SUM(A:B!AD83) -> 0 | AE83: =SUM(A:B!AE83) -> 0 | AF83: =SUM(A:B!AF83) -> 0 | ... AJ83: =SUM(A:B!AJ83) -> 0 | AK83: =SUM(Y83:AJ83) -> 0 | AL83: =AK83/AK$6 -> 0 | AM83: =IFERROR(AK83/V83-1,0) -> 0
I84: Honorarios Legales P.M. | J84: =SUM(A:B!J84) -> 0 | K84: =SUM(A:B!K84) -> 0 | L84: =SUM(A:B!L84) -> 0 | M84: =SUM(A:B!M84) -> 0 | N84: =SUM(A:B!N84) -> 0 | O84: =SUM(A:B!O84) -> 0 | P84: =SUM(A:B!P84) -> 0 | Q84: =SUM(A:B!Q84) -> 0 | ... U84: =SUM(A:B!U84) -> 0 | V84: =SUM(J84:U84) -> 0 | W84: =V84/V$6 -> 0 | Y84: =SUM(A:B!Y84) -> 0 | Z84: =SUM(A:B!Z84) -> 0 | AA84: =SUM(A:B!AA84) -> 0 | AB84: =SUM(A:B!AB84) -> 0 | AC84: =SUM(A:B!AC84) -> 0 | AD84: =SUM(A:B!AD84) -> 0 | AE84: =SUM(A:B!AE84) -> 0 | AF84: =SUM(A:B!AF84) -> 0 | ... AJ84: =SUM(A:B!AJ84) -> 0 | AK84: =SUM(Y84:AJ84) -> 0 | AL84: =AK84/AK$6 -> 0 | AM84: =IFERROR(AK84/V84-1,0) -> 0
I85: Calcamonias y senalamientos | J85: =SUM(A:B!J85) -> 0 | K85: =SUM(A:B!K85) -> 0 | L85: =SUM(A:B!L85) -> 7125 | M85: =SUM(A:B!M85) -> 7125 | N85: =SUM(A:B!N85) -> 7125 | O85: =SUM(A:B!O85) -> 7125 | P85: =SUM(A:B!P85) -> 0 | Q85: =SUM(A:B!Q85) -> 7125 | ... U85: =SUM(A:B!U85) -> 0 | V85: =SUM(J85:U85) -> 48450 | W85: =V85/V$6 -> 5.4063772e-05 | Y85: =SUM(A:B!Y85) -> 0 | Z85: =SUM(A:B!Z85) -> 0 | AA85: =SUM(A:B!AA85) -> 0 | AB85: =SUM(A:B!AB85) -> 0 | AC85: =SUM(A:B!AC85) -> 0 | AD85: =SUM(A:B!AD85) -> 0 | AE85: =SUM(A:B!AE85) -> 0 | AF85: =SUM(A:B!AF85) -> 0 | ... AJ85: =SUM(A:B!AJ85) -> 0 | AK85: =SUM(Y85:AJ85) -> 0 | AL85: =AK85/AK$6 -> 0 | AM85: =IFERROR(AK85/V85-1,0) -> -1
I86: Cuotas y suscripciones | J86: =SUM(A:B!J86) -> 0 | K86: =SUM(A:B!K86) -> 0 | L86: =SUM(A:B!L86) -> 8400 | M86: =SUM(A:B!M86) -> 0 | N86: =SUM(A:B!N86) -> 0 | O86: =SUM(A:B!O86) -> 0 | P86: =SUM(A:B!P86) -> 1640 | Q86: =SUM(A:B!Q86) -> 0 | ... U86: =SUM(A:B!U86) -> 0 | V86: =SUM(J86:U86) -> 10040 | W86: =V86/V$6 -> 1.1203308e-05 | Y86: =SUM(A:B!Y86) -> 0 | Z86: =SUM(A:B!Z86) -> 0 | AA86: =SUM(A:B!AA86) -> 0 | AB86: =SUM(A:B!AB86) -> 0 | AC86: =SUM(A:B!AC86) -> 0 | AD86: =SUM(A:B!AD86) -> 0 | AE86: =SUM(A:B!AE86) -> 0 | AF86: =SUM(A:B!AF86) -> 0 | ... AJ86: =SUM(A:B!AJ86) -> 0 | AK86: =SUM(Y86:AJ86) -> 0 | AL86: =AK86/AK$6 -> 0 | AM86: =IFERROR(AK86/V86-1,0) -> -1
I87: Cumplimiento Sat Anexo 30 y 31 | J87: =SUM(A:B!J87) -> 0 | K87: =SUM(A:B!K87) -> 0 | L87: =SUM(A:B!L87) -> 0 | M87: =SUM(A:B!M87) -> 0 | N87: =SUM(A:B!N87) -> 0 | O87: =SUM(A:B!O87) -> 0 | P87: =SUM(A:B!P87) -> 0 | Q87: =SUM(A:B!Q87) -> 0 | ... U87: =SUM(A:B!U87) -> 0 | V87: =SUM(J87:U87) -> 0 | W87: =V87/V$6 -> 0 | Y87: =SUM(A:B!Y87) -> 0 | Z87: =SUM(A:B!Z87) -> 0 | AA87: =SUM(A:B!AA87) -> 0 | AB87: =SUM(A:B!AB87) -> 0 | AC87: =SUM(A:B!AC87) -> 0 | AD87: =SUM(A:B!AD87) -> 0 | AE87: =SUM(A:B!AE87) -> 0 | AF87: =SUM(A:B!AF87) -> 0 | ... AJ87: =SUM(A:B!AJ87) -> 0 | AK87: =SUM(Y87:AJ87) -> 0 | AL87: =AK87/AK$6 -> 0 | AM87: =IFERROR(AK87/V87-1,0) -> 0
I88: Eventos | J88: =SUM(A:B!J88) -> 0 | K88: =SUM(A:B!K88) -> 0 | L88: =SUM(A:B!L88) -> 0 | M88: =SUM(A:B!M88) -> 0 | N88: =SUM(A:B!N88) -> 0 | O88: =SUM(A:B!O88) -> 0 | P88: =SUM(A:B!P88) -> 17500 | Q88: =SUM(A:B!Q88) -> 0 | ... U88: =SUM(A:B!U88) -> 0 | V88: =SUM(J88:U88) -> 152180 | W88: =V88/V$6 -> 0.00016981269 | Y88: =SUM(A:B!Y88) -> 0 | Z88: =SUM(A:B!Z88) -> 0 | AA88: =SUM(A:B!AA88) -> 0 | AB88: =SUM(A:B!AB88) -> 0 | AC88: =SUM(A:B!AC88) -> 0 | AD88: =SUM(A:B!AD88) -> 0 | AE88: =SUM(A:B!AE88) -> 0 | AF88: =SUM(A:B!AF88) -> 0 | ... AJ88: =SUM(A:B!AJ88) -> 0 | AK88: =SUM(Y88:AJ88) -> 129698.03 | AL88: =AK88/AK$6 -> 0.00013465631 | AM88: =IFERROR(AK88/V88-1,0) -> -0.14773275
A89: E - GASTOS DE OPERACIÓN | B89: estaciones | I89: Asesoria Acehico | J89: =SUM(A:B!J89) -> 0 | K89: =SUM(A:B!K89) -> 25645 | L89: =SUM(A:B!L89) -> 0 | M89: =SUM(A:B!M89) -> 0 | N89: =SUM(A:B!N89) -> 9260 | O89: =SUM(A:B!O89) -> 13030 | P89: =SUM(A:B!P89) -> 0 | Q89: =SUM(A:B!Q89) -> 10170 | ... U89: =SUM(A:B!U89) -> 0 | V89: =SUM(J89:U89) -> 191448.6 | W89: =V89/V$6 -> 0.00021363124 | Y89: =SUM(A:B!Y89) -> 0 | Z89: =SUM(A:B!Z89) -> 34639.622 | AA89: =SUM(A:B!AA89) -> 0 | AB89: =SUM(A:B!AB89) -> 0 | AC89: =SUM(A:B!AC89) -> 16566.775 | AD89: =SUM(A:B!AD89) -> 18574.869 | AE89: =SUM(A:B!AE89) -> 0 | AF89: =SUM(A:B!AF89) -> 17068.799 | ... AJ89: =SUM(A:B!AJ89) -> 0 | AK89: =SUM(Y89:AJ89) -> 210347.85 | AL89: =AK89/AK$6 -> 0.00021838932 | AM89: =IFERROR(AK89/V89-1,0) -> 0.098717079
A90: E - GASTOS DE OPERACIÓN | B90: estaciones | I90: Prediales | J90: =SUM(A:B!J90) -> 565196 | K90: =SUM(A:B!K90) -> 565196 | L90: =SUM(A:B!L90) -> 565196 | M90: =SUM(A:B!M90) -> 565197 | N90: =SUM(A:B!N90) -> 565197 | O90: =SUM(A:B!O90) -> 565197 | P90: =SUM(A:B!P90) -> 565197 | Q90: =SUM(A:B!Q90) -> 565197 | ... U90: =SUM(A:B!U90) -> 565196.46 | V90: =SUM(J90:U90) -> 6782357.9 | W90: =V90/V$6 -> 0.0075682116 | Y90: =SUM(A:B!Y90) -> 586391.33 | Z90: =SUM(A:B!Z90) -> 586391.33 | AA90: =SUM(A:B!AA90) -> 586391.33 | AB90: =SUM(A:B!AB90) -> 586391.33 | AC90: =SUM(A:B!AC90) -> 586391.33 | AD90: =SUM(A:B!AD90) -> 586391.33 | AE90: =SUM(A:B!AE90) -> 586391.33 | AF90: =SUM(A:B!AF90) -> 586391.33 | ... AJ90: =SUM(A:B!AJ90) -> 586391.33 | AK90: =SUM(Y90:AJ90) -> 7036695.9 | AL90: =AK90/AK$6 -> 0.0073057045 | AM90: =IFERROR(AK90/V90-1,0) -> 0.037499939
A91: C - NOMINA | B91: estaciones | I91: C - NOMINA | J91: =SUM(J92:J107) -> 2882928 | K91: =SUM(K92:K107) -> 2953750 | L91: =SUM(L92:L107) -> 3674660 | M91: =SUM(M92:M107) -> 3318997 | N91: =SUM(N92:N107) -> 3375658 | O91: =SUM(O92:O107) -> 3301196 | P91: =SUM(P92:P107) -> 3343093 | Q91: =SUM(Q92:Q107) -> 3368435 | ... V91: =SUM(V92:V107) -> 39528082 | W91: =V91/V$6 -> 0.044108095 | Y91: =SUM(Y92:Y107) -> 3677193.9 | Z91: =SUM(Z92:Z107) -> 3359561.2 | AA91: =SUM(AA92:AA107) -> 3677193.9 | AB91: =SUM(AB92:AB107) -> 3468545.8 | AC91: =SUM(AC92:AC107) -> 3677193.9 | AD91: =SUM(AD92:AD107) -> 3468545.8 | AE91: =SUM(AE92:AE107) -> 3574423.4 | AF91: =SUM(AF92:AF107) -> 3574423.4 | ... AK91: =SUM(AK92:AK107) -> 42871331 | AL91: =AK91/AK$6 -> 0.044510276 | AM91: =IFERROR(AK91/V91-1,0) -> 0.084579088
A92: C - NOMINA | B92: estaciones | I92: Aguinaldo | J92: =SUM(A:B!J92) -> 1463898 | K92: =SUM(A:B!K92) -> 1498655 | L92: =SUM(A:B!L92) -> 1863059 | M92: =SUM(A:B!M92) -> 1705997 | N92: =SUM(A:B!N92) -> 1712949 | O92: =SUM(A:B!O92) -> 1674811 | P92: =SUM(A:B!P92) -> 1697284 | Q92: =SUM(A:B!Q92) -> 1709780 | ... U92: =SUM(A:B!U92) -> 1695712.3 | V92: =SUM(J92:U92) -> 20081804 | W92: =V92/V$6 -> 0.022408629 | Y92: =SUM(A:B!Y92) -> 1838597 | Z92: =SUM(A:B!Z92) -> 1679780.6 | AA92: =SUM(A:B!AA92) -> 1838597 | AB92: =SUM(A:B!AB92) -> 1734272.9 | AC92: =SUM(A:B!AC92) -> 1838597 | AD92: =SUM(A:B!AD92) -> 1734272.9 | AE92: =SUM(A:B!AE92) -> 1787211.7 | AF92: =SUM(A:B!AF92) -> 1787211.7 | ... AJ92: =SUM(A:B!AJ92) -> 1838597 | AK92: =SUM(Y92:AJ92) -> 21435666 | AL92: =AK92/AK$6 -> 0.022255138 | AM92: =IFERROR(AK92/V92-1,0) -> 0.067417317
A93: C - NOMINA | B93: estaciones | I93: Compensaciones | J93: =SUM(A:B!J93) -> 45887 | K93: =SUM(A:B!K93) -> 45117 | L93: =SUM(A:B!L93) -> 53778 | M93: =SUM(A:B!M93) -> 50409 | N93: =SUM(A:B!N93) -> 51511 | O93: =SUM(A:B!O93) -> 49905 | P93: =SUM(A:B!P93) -> 52895 | Q93: =SUM(A:B!Q93) -> 53050 | ... U93: =SUM(A:B!U93) -> 51413.556 | V93: =SUM(J93:U93) -> 608206.22 | W93: =V93/V$6 -> 0.00067867745 | Y93: =SUM(A:B!Y93) -> 54552.863 | Z93: =SUM(A:B!Z93) -> 49273.554 | AA93: =SUM(A:B!AA93) -> 54552.863 | AB93: =SUM(A:B!AB93) -> 52793.094 | AC93: =SUM(A:B!AC93) -> 54552.863 | AD93: =SUM(A:B!AD93) -> 52793.094 | AE93: =SUM(A:B!AE93) -> 54552.863 | AF93: =SUM(A:B!AF93) -> 54552.863 | ... AJ93: =SUM(A:B!AJ93) -> 54552.863 | AK93: =SUM(Y93:AJ93) -> 642315.97 | AL93: =AK93/AK$6 -> 0.00066687132 | AM93: =IFERROR(AK93/V93-1,0) -> 0.056082539 | AN93: =+AK93-V93 -> 34109.749
A94: C - NOMINA | B94: estaciones | I94: Días festivos | J94: =SUM(A:B!J94) -> 114728 | K94: =SUM(A:B!K94) -> 101673 | L94: =SUM(A:B!L94) -> 124487 | M94: =SUM(A:B!M94) -> 210934 | N94: =SUM(A:B!N94) -> 154002 | O94: =SUM(A:B!O94) -> 185659 | P94: =SUM(A:B!P94) -> 151601 | Q94: =SUM(A:B!Q94) -> 129491 | ... U94: =SUM(A:B!U94) -> 138214.56 | V94: =SUM(J94:U94) -> 1725433.2 | W94: =V94/V$6 -> 0.0019253545 | Y94: =SUM(A:B!Y94) -> 146109.24 | Z94: =SUM(A:B!Z94) -> 146109.24 | AA94: =SUM(A:B!AA94) -> 146109.24 | AB94: =SUM(A:B!AB94) -> 146109.24 | AC94: =SUM(A:B!AC94) -> 146109.24 | AD94: =SUM(A:B!AD94) -> 146109.24 | AE94: =SUM(A:B!AE94) -> 146109.24 | AF94: =SUM(A:B!AF94) -> 146109.24 | ... AJ94: =SUM(A:B!AJ94) -> 146109.24 | AK94: =SUM(Y94:AJ94) -> 1753310.9 | AL94: =AK94/AK$6 -> 0.0018203389 | AM94: =IFERROR(AK94/V94-1,0) -> 0.016156903 | AN94: =+AK94-V94 -> 27877.658
A95: C - NOMINA | B95: estaciones | I95: Fondo de ahorro | J95: =SUM(A:B!J95) -> 40603 | K95: =SUM(A:B!K95) -> 50455 | L95: =SUM(A:B!L95) -> 60338 | M95: =SUM(A:B!M95) -> 0 | N95: =SUM(A:B!N95) -> 62612 | O95: =SUM(A:B!O95) -> 0 | P95: =SUM(A:B!P95) -> 0 | Q95: =SUM(A:B!Q95) -> 0 | ... U95: =SUM(A:B!U95) -> 28250.074 | V95: =SUM(J95:U95) -> 327008.3 | W95: =V95/V$6 -> 0.00036489787 | Y95: =SUM(A:B!Y95) -> 51385.278 | Z95: =SUM(A:B!Z95) -> 51385.278 | AA95: =SUM(A:B!AA95) -> 51385.278 | AB95: =SUM(A:B!AB95) -> 0 | AC95: =SUM(A:B!AC95) -> 51385.278 | AD95: =SUM(A:B!AD95) -> 0 | AE95: =SUM(A:B!AE95) -> 0 | AF95: =SUM(A:B!AF95) -> 0 | ... AJ95: =SUM(A:B!AJ95) -> 51385.278 | AK95: =SUM(Y95:AJ95) -> 359696.94 | AL95: =AK95/AK$6 -> 0.00037344794 | AM95: =IFERROR(AK95/V95-1,0) -> 0.099962747 | AN95: =+AK95-V95 -> 32688.648
A96: C - NOMINA | B96: estaciones | I96: Gratificaciones | J96: =SUM(A:B!J96) -> 59080 | K96: =SUM(A:B!K96) -> 60666 | L96: =SUM(A:B!L96) -> 72868 | M96: =SUM(A:B!M96) -> 65732 | N96: =SUM(A:B!N96) -> 67100 | O96: =SUM(A:B!O96) -> 67500 | P96: =SUM(A:B!P96) -> 68858 | Q96: =SUM(A:B!Q96) -> 71162 | ... U96: =SUM(A:B!U96) -> 68063.481 | V96: =SUM(J96:U96) -> 805219.93 | W96: =V96/V$6 -> 0.0008985186 | Y96: =SUM(A:B!Y96) -> 71682.462 | Z96: =SUM(A:B!Z96) -> 64745.45 | AA96: =SUM(A:B!AA96) -> 71682.462 | AB96: =SUM(A:B!AB96) -> 69370.125 | AC96: =SUM(A:B!AC96) -> 71682.462 | AD96: =SUM(A:B!AD96) -> 69370.125 | AE96: =SUM(A:B!AE96) -> 71682.462 | AF96: =SUM(A:B!AF96) -> 71682.462 | ... AJ96: =SUM(A:B!AJ96) -> 71682.462 | AK96: =SUM(Y96:AJ96) -> 844003.19 | AL96: =AK96/AK$6 -> 0.00087626892 | AM96: =IFERROR(AK96/V96-1,0) -> 0.048164804
A97: C - NOMINA | B97: estaciones | I97: Premios de asistencia | J97: =SUM(A:B!J97) -> 0 | K97: =SUM(A:B!K97) -> 0 | L97: =SUM(A:B!L97) -> 0 | M97: =SUM(A:B!M97) -> 0 | N97: =SUM(A:B!N97) -> 0 | O97: =SUM(A:B!O97) -> 0 | P97: =SUM(A:B!P97) -> 0 | Q97: =SUM(A:B!Q97) -> 13738 | ... U97: =SUM(A:B!U97) -> 13738 | V97: =SUM(J97:U97) -> 41214 | W97: =V97/V$6 -> 4.5989356e-05 | Y97: =SUM(A:B!Y97) -> 0 | Z97: =SUM(A:B!Z97) -> 0 | AA97: =SUM(A:B!AA97) -> 0 | AB97: =SUM(A:B!AB97) -> 0 | AC97: =SUM(A:B!AC97) -> 0 | AD97: =SUM(A:B!AD97) -> 0 | AE97: =SUM(A:B!AE97) -> 0 | AF97: =SUM(A:B!AF97) -> 0 | ... AJ97: =SUM(A:B!AJ97) -> 0 | AK97: =SUM(Y97:AJ97) -> 0 | AL97: =AK97/AK$6 -> 0 | AM97: =IFERROR(AK97/V97-1,0) -> -1 | AN97: =+AK97-V97 -> -41214
A98: C - NOMINA | B98: estaciones | I98: Premios de puntualidad | J98: =SUM(A:B!J98) -> 76734 | K98: =SUM(A:B!K98) -> 83523 | L98: =SUM(A:B!L98) -> 96835 | M98: =SUM(A:B!M98) -> 81785 | N98: =SUM(A:B!N98) -> 93568 | O98: =SUM(A:B!O98) -> 87175 | P98: =SUM(A:B!P98) -> 92086 | Q98: =SUM(A:B!Q98) -> 96275 | ... U98: =SUM(A:B!U98) -> 92061.963 | V98: =SUM(J98:U98) -> 1076228.9 | W98: =V98/V$6 -> 0.0012009286 | Y98: =SUM(A:B!Y98) -> 94196.296 | Z98: =SUM(A:B!Z98) -> 85080.526 | AA98: =SUM(A:B!AA98) -> 94196.296 | AB98: =SUM(A:B!AB98) -> 91157.706 | AC98: =SUM(A:B!AC98) -> 94196.296 | AD98: =SUM(A:B!AD98) -> 91157.706 | AE98: =SUM(A:B!AE98) -> 94196.296 | AF98: =SUM(A:B!AF98) -> 94196.296 | ... AJ98: =SUM(A:B!AJ98) -> 94196.296 | AK98: =SUM(Y98:AJ98) -> 1109085.4 | AL98: =AK98/AK$6 -> 0.0011514851 | AM98: =IFERROR(AK98/V98-1,0) -> 0.030529354 | AN98: =+AK98-V98 -> 32856.571
A99: C - NOMINA | B99: estaciones | I99: Previsión social | J99: =SUM(A:B!J99) -> 32983 | K99: =SUM(A:B!K99) -> 42398 | L99: =SUM(A:B!L99) -> 46319 | M99: =SUM(A:B!M99) -> 38333 | N99: =SUM(A:B!N99) -> 43745 | O99: =SUM(A:B!O99) -> 43847 | P99: =SUM(A:B!P99) -> 43882 | Q99: =SUM(A:B!Q99) -> 50900 | ... U99: =SUM(A:B!U99) -> 48584.444 | V99: =SUM(J99:U99) -> 536744.78 | W99: =V99/V$6 -> 0.00059893596 | Y99: =SUM(A:B!Y99) -> 50274.507 | Z99: =SUM(A:B!Z99) -> 45409.232 | AA99: =SUM(A:B!AA99) -> 50274.507 | AB99: =SUM(A:B!AB99) -> 48652.749 | AC99: =SUM(A:B!AC99) -> 50274.507 | AD99: =SUM(A:B!AD99) -> 48652.749 | AE99: =SUM(A:B!AE99) -> 50274.507 | AF99: =SUM(A:B!AF99) -> 50274.507 | ... AJ99: =SUM(A:B!AJ99) -> 50274.507 | AK99: =SUM(Y99:AJ99) -> 591941.78 | AL99: =AK99/AK$6 -> 0.00061457135 | AM99: =IFERROR(AK99/V99-1,0) -> 0.10283659
A100: C - NOMINA | B100: estaciones | I100: Prima dominical | J100: =SUM(A:B!J100) -> 0 | K100: =SUM(A:B!K100) -> 0 | L100: =SUM(A:B!L100) -> 0 | M100: =SUM(A:B!M100) -> 0 | N100: =SUM(A:B!N100) -> 0 | O100: =SUM(A:B!O100) -> 0 | P100: =SUM(A:B!P100) -> 0 | Q100: =SUM(A:B!Q100) -> 0 | ... U100: =SUM(A:B!U100) -> 0 | V100: =SUM(J100:U100) -> 0 | W100: =V100/V$6 -> 0 | Y100: =SUM(A:B!Y100) -> 0 | Z100: =SUM(A:B!Z100) -> 0 | AA100: =SUM(A:B!AA100) -> 0 | AB100: =SUM(A:B!AB100) -> 0 | AC100: =SUM(A:B!AC100) -> 0 | AD100: =SUM(A:B!AD100) -> 0 | AE100: =SUM(A:B!AE100) -> 0 | AF100: =SUM(A:B!AF100) -> 0 | ... AJ100: =SUM(A:B!AJ100) -> 0 | AK100: =SUM(Y100:AJ100) -> 0 | AL100: =AK100/AK$6 -> 0 | AM100: =IFERROR(AK100/V100-1,0) -> 0 | AN100: =+AK100-V100 -> 0 | AO100: Falta Ajustar (Quitar a Gtes)
A101: C - NOMINA | B101: estaciones | I101: Prima vacacional | J101: =SUM(A:B!J101) -> 30523 | K101: =SUM(A:B!K101) -> 26153 | L101: =SUM(A:B!L101) -> 31041 | M101: =SUM(A:B!M101) -> 29383 | N101: =SUM(A:B!N101) -> 26704 | O101: =SUM(A:B!O101) -> 26851 | P101: =SUM(A:B!P101) -> 30853 | Q101: =SUM(A:B!Q101) -> 28212 | ... U101: =SUM(A:B!U101) -> 28853.63 | V101: =SUM(J101:U101) -> 345134.52 | W101: =V101/V$6 -> 0.00038512433 | Y101: =SUM(A:B!Y101) -> 31123.512 | Z101: =SUM(A:B!Z101) -> 28111.559 | AA101: =SUM(A:B!AA101) -> 31123.512 | AB101: =SUM(A:B!AB101) -> 30119.528 | AC101: =SUM(A:B!AC101) -> 31123.512 | AD101: =SUM(A:B!AD101) -> 30119.528 | AE101: =SUM(A:B!AE101) -> 31123.512 | AF101: =SUM(A:B!AF101) -> 31123.512 | ... AJ101: =SUM(A:B!AJ101) -> 31123.512 | AK101: =SUM(Y101:AJ101) -> 366454.26 | AL101: =AK101/AK$6 -> 0.00038046358 | AM101: =IFERROR(AK101/V101-1,0) -> 0.061772255 | AN101: =+AK101-V101 -> 21319.737
A102: C - NOMINA | B102: estaciones | I102: Primas de antigüedad | J102: =SUM(A:B!J102) -> 11283 | K102: =SUM(A:B!K102) -> 10890 | L102: =SUM(A:B!L102) -> 12867 | M102: =SUM(A:B!M102) -> 12307 | N102: =SUM(A:B!N102) -> 12562 | O102: =SUM(A:B!O102) -> 12107 | P102: =SUM(A:B!P102) -> 12869 | Q102: =SUM(A:B!Q102) -> 12780 | ... U102: =SUM(A:B!U102) -> 12586.519 | V102: =SUM(J102:U102) -> 148011.07 | W102: =V102/V$6 -> 0.00016516072 | Y102: =SUM(A:B!Y102) -> 11819.787 | Z102: =SUM(A:B!Z102) -> 10675.937 | AA102: =SUM(A:B!AA102) -> 11819.787 | AB102: =SUM(A:B!AB102) -> 11438.504 | AC102: =SUM(A:B!AC102) -> 11819.787 | AD102: =SUM(A:B!AD102) -> 11438.504 | AE102: =SUM(A:B!AE102) -> 11819.787 | AF102: =SUM(A:B!AF102) -> 11819.787 | ... AJ102: =SUM(A:B!AJ102) -> 11819.787 | AK102: =SUM(Y102:AJ102) -> 139168.46 | AL102: =AK102/AK$6 -> 0.00014448879 | AM102: =IFERROR(AK102/V102-1,0) -> -0.059742919
A103: C - NOMINA | B103: estaciones | I103: Indemnizaciones | J103: =SUM(A:B!J103) -> 0 | K103: =SUM(A:B!K103) -> 0 | L103: =SUM(A:B!L103) -> 48937 | M103: =SUM(A:B!M103) -> 0 | N103: =SUM(A:B!N103) -> 0 | O103: =SUM(A:B!O103) -> 0 | P103: =SUM(A:B!P103) -> 8036 | Q103: =SUM(A:B!Q103) -> 0 | ... U103: =SUM(A:B!U103) -> 0 | V103: =SUM(J103:U103) -> 56973 | W103: =V103/V$6 -> 6.3574309e-05 | Y103: =SUM(A:B!Y103) -> 0 | Z103: =SUM(A:B!Z103) -> 0 | AA103: =SUM(A:B!AA103) -> 0 | AB103: =SUM(A:B!AB103) -> 0 | AC103: =SUM(A:B!AC103) -> 0 | AD103: =SUM(A:B!AD103) -> 0 | AE103: =SUM(A:B!AE103) -> 0 | AF103: =SUM(A:B!AF103) -> 0 | ... AJ103: =SUM(A:B!AJ103) -> 0 | AK103: =SUM(Y103:AJ103) -> 0 | AL103: =AK103/AK$6 -> 0 | AM103: =IFERROR(AK103/V103-1,0) -> -1
...

Sheet S

Sheet COM-MKT
I1: Mantenimiento de Imagen | Y1: 2 | Z1: 3 | AA1: 4 | AB1: 5 | AC1: 6 | AD1: 7 | AE1: 8 | AF1: 9 | AG1: 10 | AH1: 11 | AI1: 12 | AJ1: 13 | AM1: 17
J2: 2024 | V2: TOTAL ANUAL | Y2: 2025 | AK2: TOTAL ANUAL
J3: ENE | K3: FEB | L3: MAR | M3: ABR | N3: MAY | O3: JUN | P3: JUL | Q3: AGO | R3: SEP | S3: OCT | T3: NOV | U3: DIC | V3: 2024 | W3: % Part | Y3: ENE | Z3: FEB | AA3: MAR | AB3: ABR | AC3: MAY | AD3: JUN | AE3: JUL | AF3: AGO | AG3: SEP | AH3: OCT | AI3: NOV | AJ3: DIC | AK3: 2025 | AL3: % Part | AM3: Var vs AA%
I4: INGRESOS
A6: A - INGRESOS | E6: ( mas ) | I6: A - INGRESOS | V6: =SUM(J6:U6) -> 0 | W6: =V6/V$6 -> #DIV/0! | Y6: =SUM(Y7:Y10) -> 0 | Z6: =SUM(Z7:Z10) -> 0 | AA6: =SUM(AA7:AA10) -> 0 | AB6: =SUM(AB7:AB10) -> 0 | AC6: =SUM(AC7:AC10) -> 0 | AD6: =SUM(AD7:AD10) -> 0 | AE6: =SUM(AE7:AE10) -> 0 | AF6: =SUM(AF7:AF10) -> 0 | ... AJ6: =SUM(AJ7:AJ10) -> 0 | AK6: =SUM(Y6:AJ6) -> 0 | AL6: =AK6/AK$6 -> #DIV/0! | AM6: =IFERROR(AK6/V6-1,0) -> 0
A7: A - INGRESOS | B7: estaciones | C7: INGRESOS MAGNA | D7: INGRESOS FORANEOS MAGNA | I7: T-MAXIMA REGULAR | V7: =SUM(J7:U7) -> 0 | W7: =V7/V$6 -> #DIV/0! | Y7: 0 | Z7: 0 | AA7: 0 | AB7: 0 | AC7: 0 | AD7: 0 | AE7: 0 | AF7: 0 | AG7: 0 | AH7: 0 | AI7: 0 | AJ7: 0 | AK7: =SUM(Y7:AJ7) -> 0 | AL7: =AK7/AK$6 -> #DIV/0! | AM7: =IFERROR(AK7/V7-1,0) -> 0
A8: A - INGRESOS | B8: estaciones | C8: INGRESOS PREMIUM | D8: INGRESOS FORANEOS PREMIUM | I8: T-SUPER PREMIUM | V8: =SUM(J8:U8) -> 0 | W8: =V8/V$6 -> #DIV/0! | Y8: 0 | Z8: 0 | AA8: 0 | AB8: 0 | AC8: 0 | AD8: 0 | AE8: 0 | AF8: 0 | AG8: 0 | AH8: 0 | AI8: 0 | AJ8: 0 | AK8: =SUM(Y8:AJ8) -> 0 | AL8: =AK8/AK$6 -> #DIV/0! | AM8: =IFERROR(AK8/V8-1,0) -> 0
A9: A - INGRESOS | B9: estaciones | C9: INGRESOS DIESEL | D9: INGRESOS FORANEOS DIESEL | I9: DIESEL AUTOMOTRIZ | V9: =SUM(J9:U9) -> 0 | W9: =V9/V$6 -> #DIV/0! | Y9: 0 | Z9: 0 | AA9: 0 | AB9: 0 | AC9: 0 | AD9: 0 | AE9: 0 | AF9: 0 | AG9: 0 | AH9: 0 | AI9: 0 | AJ9: 0 | AK9: =SUM(Y9:AJ9) -> 0 | AL9: =AK9/AK$6 -> #DIV/0! | AM9: =IFERROR(AK9/V9-1,0) -> 0
A10: A - INGRESOS | B10: estaciones | C10: INGRESOS ADITIVOS | D10: INGRESOS ESPECIALES | F10: INGRESOS FORANEOS ESPECIALES | G10: INGRESOS FORANEOS LUBRICANTES | H10: INGRESOS LUBRICANTES | I10: PREPAGO facturación (neto) | V10: =SUM(J10:U10) -> 0 | W10: =V10/V$6 -> #DIV/0! | Y10: 0 | Z10: 0 | AA10: 0 | AB10: 0 | AC10: 0 | AD10: 0 | AE10: 0 | AF10: 0 | AG10: 0 | AH10: 0 | AI10: 0 | AJ10: 0 | AK10: =SUM(Y10:AJ10) -> 0 | AL10: =AK10/AK$6 -> #DIV/0! | AM10: =IFERROR(AK10/V10-1,0) -> 0
A11: A - INGRESOS | B11: estaciones | C11: INGRESOS ADITIVOS | D11: INGRESOS ESPECIALES | E11: INGRESOS FORANEOS ADITIVOS | F11: INGRESOS FORANEOS ESPECIALES | G11: INGRESOS FORANEOS LUBRICANTES | H11: INGRESOS LUBRICANTES | I11: INGRESOS ACEITES Y LUBRICANTES | V11: =SUM(J11:U11) -> 0 | W11: =V11/V$6 -> #DIV/0! | Y11: 0 | Z11: 0 | AA11: 0 | AB11: 0 | AC11: 0 | AD11: 0 | AE11: 0 | AF11: 0 | AG11: 0 | AH11: 0 | AI11: 0 | AJ11: 0 | AK11: =SUM(Y11:AJ11) -> 0 | AL11: =AK11/AK$6 -> #DIV/0! | AM11: =IFERROR(AK11/V11-1,0) -> 0
I12: SOBRANTE REGULAR
I13: SOBRANTE PREMIUM
I14: SOBRANTE DIESEL
A15: B - COSTO DE VENTA | E15: ( menos ) | I15: B - COSTO DE VENTA | V15: =SUM(J15:U15) -> 0 | W15: =V15/V$6 -> #DIV/0! | Y15: =SUM(Y16:Y31) -> 0 | Z15: =SUM(Z16:Z31) -> 0 | AA15: =SUM(AA16:AA31) -> 0 | AB15: =SUM(AB16:AB31) -> 0 | AC15: =SUM(AC16:AC31) -> 0 | AD15: =SUM(AD16:AD31) -> 0 | AE15: =SUM(AE16:AE31) -> 0 | AF15: =SUM(AF16:AF31) -> 0 | ... AJ15: =SUM(AJ16:AJ31) -> 0 | AK15: =SUM(Y15:AJ15) -> 0 | AL15: =AK15/AK$6 -> #DIV/0! | AM15: =IFERROR(AK15/V15-1,0) -> 0
A16: B - COSTO DE VENTA | C16: COSTO MAGNA | D16: COSTO FORANEO MAGNA | I16: GASOLINA REGULAR | V16: =SUM(J16:U16) -> 0 | W16: =V16/V$6 -> #DIV/0! | Y16: 0 | Z16: 0 | AA16: 0 | AB16: 0 | AC16: 0 | AD16: 0 | AE16: 0 | AF16: 0 | AG16: 0 | AH16: 0 | AI16: 0 | AJ16: 0 | AK16: =SUM(Y16:AJ16) -> 0 | AL16: =AK16/AK$6 -> #DIV/0! | AM16: =IFERROR(AK16/V16-1,0) -> 0
A17: B - COSTO DE VENTA | C17: COSTO PREMIUM | D17: COSTO FORANEO PREMIUM | I17: GASOLINA PREMIUM | V17: =SUM(J17:U17) -> 0 | W17: =V17/V$6 -> #DIV/0! | Y17: 0 | Z17: 0 | AA17: 0 | AB17: 0 | AC17: 0 | AD17: 0 | AE17: 0 | AF17: 0 | AG17: 0 | AH17: 0 | AI17: 0 | AJ17: 0 | AK17: =SUM(Y17:AJ17) -> 0 | AL17: =AK17/AK$6 -> #DIV/0! | AM17: =IFERROR(AK17/V17-1,0) -> 0
A18: B - COSTO DE VENTA | C18: COSTO DIESEL | D18: COSTO FORANEO DIESEL | I18: DIESEL | V18: =SUM(J18:U18) -> 0 | W18: =V18/V$6 -> #DIV/0! | Y18: 0 | Z18: 0 | AA18: 0 | AB18: 0 | AC18: 0 | AD18: 0 | AE18: 0 | AF18: 0 | AG18: 0 | AH18: 0 | AI18: 0 | AJ18: 0 | AK18: =SUM(Y18:AJ18) -> 0 | AL18: =AK18/AK$6 -> #DIV/0! | AM18: =IFERROR(AK18/V18-1,0) -> 0
A19: B - COSTO DE VENTA | C19: Merma Magna | I19: MERMA GASOLINA REGULAR | V19: =SUM(J19:U19) -> 0 | W19: =V19/V$6 -> #DIV/0! | Y19: 0 | Z19: 0 | AA19: 0 | AB19: 0 | AC19: 0 | AD19: 0 | AE19: 0 | AF19: 0 | AG19: 0 | AH19: 0 | AI19: 0 | AJ19: 0 | AK19: =SUM(Y19:AJ19) -> 0 | AL19: =AK19/AK$6 -> #DIV/0! | AM19: =IFERROR(AK19/V19-1,0) -> 0
A20: B - COSTO DE VENTA | C20: Merma Premium | I20: MERMA GASOLINA PREMIUM | V20: =SUM(J20:U20) -> 0 | W20: =V20/V$6 -> #DIV/0! | Y20: 0 | Z20: 0 | AA20: 0 | AB20: 0 | AC20: 0 | AD20: 0 | AE20: 0 | AF20: 0 | AG20: 0 | AH20: 0 | AI20: 0 | AJ20: 0 | AK20: =SUM(Y20:AJ20) -> 0 | AL20: =AK20/AK$6 -> #DIV/0! | AM20: =IFERROR(AK20/V20-1,0) -> 0
A21: B - COSTO DE VENTA | C21: Merma Diesel | I21: MERMA DIESEL | V21: =SUM(J21:U21) -> 0 | W21: =V21/V$6 -> #DIV/0! | Y21: 0 | Z21: 0 | AA21: 0 | AB21: 0 | AC21: 0 | AD21: 0 | AE21: 0 | AF21: 0 | AG21: 0 | AH21: 0 | AI21: 0 | AJ21: 0 | AK21: =SUM(Y21:AJ21) -> 0 | AL21: =AK21/AK$6 -> #DIV/0! | AM21: =IFERROR(AK21/V21-1,0) -> 0
A22: B - COSTO DE VENTA | C22: ADITIVO PARA GASOLINA TMAXIMA (REGULAR) | D22: ADITIVO PARA GASOLINA TMAXIMA( REGULAR) | I22: ADITIVO TOTAL POWER GASOLINA REG | V22: =SUM(J22:U22) -> 0 | W22: =V22/V$6 -> #DIV/0! | Y22: 0 | Z22: 0 | AA22: 0 | AB22: 0 | AC22: 0 | AD22: 0 | AE22: 0 | AF22: 0 | AG22: 0 | AH22: 0 | AI22: 0 | AJ22: 0 | AK22: =SUM(Y22:AJ22) -> 0 | AL22: =AK22/AK$6 -> #DIV/0! | AM22: =IFERROR(AK22/V22-1,0) -> 0
A23: B - COSTO DE VENTA | C23: ADITIVO PARA GASOLINA TSUPER (PREMIUM) | I23: ADITIVO TOTAL POWER GASOLINA PREM | V23: =SUM(J23:U23) -> 0 | W23: =V23/V$6 -> #DIV/0! | Y23: 0 | Z23: 0 | AA23: 0 | AB23: 0 | AC23: 0 | AD23: 0 | AE23: 0 | AF23: 0 | AG23: 0 | AH23: 0 | AI23: 0 | AJ23: 0 | AK23: =SUM(Y23:AJ23) -> 0 | AL23: =AK23/AK$6 -> #DIV/0! | AM23: =IFERROR(AK23/V23-1,0) -> 0
A24: B - COSTO DE VENTA | C24: FLETE MAGNA | I24: FLETE GASOLINA REGULAR | V24: =SUM(J24:U24) -> 0 | W24: =V24/V$6 -> #DIV/0! | Y24: 0 | Z24: 0 | AA24: 0 | AB24: 0 | AC24: 0 | AD24: 0 | AE24: 0 | AF24: 0 | AG24: 0 | AH24: 0 | AI24: 0 | AJ24: 0 | AK24: =SUM(Y24:AJ24) -> 0 | AL24: =AK24/AK$6 -> #DIV/0! | AM24: =IFERROR(AK24/V24-1,0) -> 0
A25: B - COSTO DE VENTA | C25: FLETE PREMIUM | I25: FLETE GASOLINA PREMIUM | V25: =SUM(J25:U25) -> 0 | W25: =V25/V$6 -> #DIV/0! | Y25: 0 | Z25: 0 | AA25: 0 | AB25: 0 | AC25: 0 | AD25: 0 | AE25: 0 | AF25: 0 | AG25: 0 | AH25: 0 | AI25: 0 | AJ25: 0 | AK25: =SUM(Y25:AJ25) -> 0 | AL25: =AK25/AK$6 -> #DIV/0! | AM25: =IFERROR(AK25/V25-1,0) -> 0
A26: B - COSTO DE VENTA | C26: FLETE DIESEL | I26: FLETE DIESEL | V26: =SUM(J26:U26) -> 0 | W26: =V26/V$6 -> #DIV/0! | Y26: 0 | Z26: 0 | AA26: 0 | AB26: 0 | AC26: 0 | AD26: 0 | AE26: 0 | AF26: 0 | AG26: 0 | AH26: 0 | AI26: 0 | AJ26: 0 | AK26: =SUM(Y26:AJ26) -> 0 | AL26: =AK26/AK$6 -> #DIV/0! | AM26: =IFERROR(AK26/V26-1,0) -> 0
A27: B - COSTO DE VENTA | C27: Estimulo IEPS Magna | D27: INGRESOS FORANEOS MAGNA | I27: ESTIMULO REGULAR | V27: =SUM(J27:U27) -> 0 | W27: =V27/V$6 -> #DIV/0! | Y27: 0 | Z27: 0 | AA27: 0 | AB27: 0 | AC27: 0 | AD27: 0 | AE27: 0 | AF27: 0 | AG27: 0 | AH27: 0 | AI27: 0 | AJ27: 0 | AK27: =SUM(Y27:AJ27) -> 0 | AL27: =AK27/AK$6 -> #DIV/0! | AM27: =IFERROR(AK27/V27-1,0) -> 0
A28: B - COSTO DE VENTA | C28: Estimulo IEPS Premium | D28: INGRESOS FORANEOS MAGNA | I28: ESTIMULO PREMIUM | V28: =SUM(J28:U28) -> 0 | W28: =V28/V$6 -> #DIV/0! | Y28: 0 | Z28: 0 | AA28: 0 | AB28: 0 | AC28: 0 | AD28: 0 | AE28: 0 | AF28: 0 | AG28: 0 | AH28: 0 | AI28: 0 | AJ28: 0 | AK28: =SUM(Y28:AJ28) -> 0 | AL28: =AK28/AK$6 -> #DIV/0! | AM28: =IFERROR(AK28/V28-1,0) -> 0
I29: DESCUENTO SOBRE VENTA
I30: COSTO UNIFORMES
I31: COSTO ACEITES Y LUBRICANTES | V31: =SUM(J31:U31) -> 0 | W31: =V31/V$6 -> #DIV/0! | Y31: 0 | Z31: 0 | AA31: 0 | AB31: 0 | AC31: 0 | AD31: 0 | AE31: 0 | AF31: 0 | AG31: 0 | AH31: 0 | AI31: 0 | AJ31: 0 | AK31: =SUM(Y31:AJ31) -> 0 | AL31: =AK31/AK$6 -> #DIV/0! | AM31: =IFERROR(AK31/V31-1,0) -> 0
I32: MARGEN DE UTILIDAD | V32: =V6-V15 -> 0 | W32: =V32/V$6 -> #DIV/0! | Y32: =Y6-Y15 -> 0 | Z32: =Z6-Z15 -> 0 | AA32: =AA6-AA15 -> 0 | AB32: =AB6-AB15 -> 0 | AC32: =AC6-AC15 -> 0 | AD32: =AD6-AD15 -> 0 | AE32: =AE6-AE15 -> 0 | AF32: =AF6-AF15 -> 0 | ... AK32: =AK6-AK15 -> 0 | AL32: =AK32/AK$6 -> #DIV/0! | AM32: =IFERROR(AK32/V32-1,0) -> 0
I33: Regular | V33: =SUM(J33:U33) -> 0 | Y33: =+Y43*Y39 -> 0 | Z33: =+Z43*Z39 -> 0 | AA33: =+AA43*AA39 -> 0 | AB33: =+AB43*AB39 -> 0 | AC33: =+AC43*AC39 -> 0 | AD33: =+AD43*AD39 -> 0 | AE33: =+AE43*AE39 -> 0 | AF33: =+AF43*AF39 -> 0 | ... AJ33: =+AJ43*AJ39 -> 0 | AK33: =SUM(Y33:AJ33) -> 0 | AM33: =IFERROR(AK33/V33-1,0) -> 0
I34: Premium | V34: =SUM(J34:U34) -> 0 | Y34: =+Y44*Y40 -> 0 | Z34: =+Z44*Z40 -> 0 | AA34: =+AA44*AA40 -> 0 | AB34: =+AB44*AB40 -> 0 | AC34: =+AC44*AC40 -> 0 | AD34: =+AD44*AD40 -> 0 | AE34: =+AE44*AE40 -> 0 | AF34: =+AF44*AF40 -> 0 | ... AJ34: =+AJ44*AJ40 -> 0 | AK34: =SUM(Y34:AJ34) -> 0 | AM34: =IFERROR(AK34/V34-1,0) -> 0
I35: Diesel | V35: =SUM(J35:U35) -> 0 | Y35: =+Y45*Y41 -> 0 | Z35: =+Z45*Z41 -> 0 | AA35: =+AA45*AA41 -> 0 | AB35: =+AB45*AB41 -> 0 | AC35: =+AC45*AC41 -> 0 | AD35: =+AD45*AD41 -> 0 | AE35: =+AE45*AE41 -> 0 | AF35: =+AF45*AF41 -> 0 | ... AJ35: =+AJ45*AJ41 -> 0 | AK35: =SUM(Y35:AJ35) -> 0 | AM35: =IFERROR(AK35/V35-1,0) -> 0
I36: *Otros Conceptos
I37: * Aceites y Lubricantes
I38: Litros vendidos | V38: =SUM(J38:U38) -> 0 | W38: =V38/V$38 -> #DIV/0! | Y38: =SUM(Y39:Y41) -> 0 | Z38: =SUM(Z39:Z41) -> 0 | AA38: =SUM(AA39:AA41) -> 0 | AB38: =SUM(AB39:AB41) -> 0 | AC38: =SUM(AC39:AC41) -> 0 | AD38: =SUM(AD39:AD41) -> 0 | AE38: =SUM(AE39:AE41) -> 0 | AF38: =SUM(AF39:AF41) -> 0 | ... AJ38: =SUM(AJ39:AJ41) -> 0 | AK38: =SUM(Y38:AJ38) -> 0 | AL38: =AK38/AK$38 -> #DIV/0! | AM38: =IFERROR(AK38/V38-1,0) -> 0
I39: Regular | V39: =SUM(J39:U39) -> 0 | W39: =V39/V$38 -> #DIV/0! | Y39: 0 | Z39: 0 | AA39: 0 | AB39: 0 | AC39: 0 | AD39: 0 | AE39: 0 | AF39: 0 | AG39: 0 | AH39: 0 | AI39: 0 | AJ39: 0 | AK39: =SUM(Y39:AJ39) -> 0 | AL39: =AK39/AK$38 -> #DIV/0! | AM39: =IFERROR(AK39/V39-1,0) -> 0
I40: Premium | V40: =SUM(J40:U40) -> 0 | W40: =V40/V$38 -> #DIV/0! | Y40: 0 | Z40: 0 | AA40: 0 | AB40: 0 | AC40: 0 | AD40: 0 | AE40: 0 | AF40: 0 | AG40: 0 | AH40: 0 | AI40: 0 | AJ40: 0 | AK40: =SUM(Y40:AJ40) -> 0 | AL40: =AK40/AK$38 -> #DIV/0! | AM40: =IFERROR(AK40/V40-1,0) -> 0
I41: Diesel | V41: =SUM(J41:U41) -> 0 | W41: =V41/V$38 -> #DIV/0! | Y41: 0 | Z41: 0 | AA41: 0 | AB41: 0 | AC41: 0 | AD41: 0 | AE41: 0 | AF41: 0 | AG41: 0 | AH41: 0 | AI41: 0 | AJ41: 0 | AK41: =SUM(Y41:AJ41) -> 0 | AL41: =AK41/AK$38 -> #DIV/0! | AM41: =IFERROR(AK41/V41-1,0) -> 0
I42: Margen de utilidad por litro | V42: =SUM(J42:U42) -> 0 | Y42: =IFERROR(Y32/Y38,0) -> 0 | Z42: =IFERROR(Z32/Z38,0) -> 0 | AA42: =IFERROR(AA32/AA38,0) -> 0 | AB42: =IFERROR(AB32/AB38,0) -> 0 | AC42: =IFERROR(AC32/AC38,0) -> 0 | AD42: =IFERROR(AD32/AD38,0) -> 0 | AE42: =IFERROR(AE32/AE38,0) -> 0 | AF42: =IFERROR(AF32/AF38,0) -> 0 | ... AJ42: =IFERROR(AJ32/AJ38,0) -> 0 | AK42: =SUM(Y42:AJ42) -> 0 | AM42: =IFERROR(AK42/V42-1,0) -> 0
I43: Regular | V43: =IFERROR((V7-(V16+V19+V22+V24+V27))/V39,0) -> 0 | Y43: =IFERROR((Y7-(Y16+Y19+Y22+Y24+Y27))/Y39,0) -> 0 | Z43: =IFERROR((Z7-(Z16+Z19+Z22+Z24+Z27))/Z39,0) -> 0 | AA43: =IFERROR((AA7-(AA16+AA19+AA22+AA24+AA27))/AA39,0) -> 0 | AB43: =IFERROR((AB7-(AB16+AB19+AB22+AB24+AB27))/AB39,0) -> 0 | AC43: =IFERROR((AC7-(AC16+AC19+AC22+AC24+AC27))/AC39,0) -> 0 | AD43: =IFERROR((AD7-(AD16+AD19+AD22+AD24+AD27))/AD39,0) -> 0 | AE43: =IFERROR((AE7-(AE16+AE19+AE22+AE24+AE27))/AE39,0) -> 0 | AF43: =IFERROR((AF7-(AF16+AF19+AF22+AF24+AF27))/AF39,0) -> 0 | ... AK43: =IFERROR((AK7-(AK16+AK19+AK22+AK24+AK27))/AK39,0) -> 0 | AM43: =IFERROR(AK43/V43-1,0) -> 0
I44: Premium | V44: =IFERROR((V8-(V17+V20+V23+V25+V28))/V40,0) -> 0 | Y44: =IFERROR((Y8-(Y17+Y20+Y23+Y25+Y28))/Y40,0) -> 0 | Z44: =IFERROR((Z8-(Z17+Z20+Z23+Z25+Z28))/Z40,0) -> 0 | AA44: =IFERROR((AA8-(AA17+AA20+AA23+AA25+AA28))/AA40,0) -> 0 | AB44: =IFERROR((AB8-(AB17+AB20+AB23+AB25+AB28))/AB40,0) -> 0 | AC44: =IFERROR((AC8-(AC17+AC20+AC23+AC25+AC28))/AC40,0) -> 0 | AD44: =IFERROR((AD8-(AD17+AD20+AD23+AD25+AD28))/AD40,0) -> 0 | AE44: =IFERROR((AE8-(AE17+AE20+AE23+AE25+AE28))/AE40,0) -> 0 | AF44: =IFERROR((AF8-(AF17+AF20+AF23+AF25+AF28))/AF40,0) -> 0 | ... AK44: =IFERROR((AK8-(AK17+AK20+AK23+AK25+AK28))/AK40,0) -> 0 | AM44: =IFERROR(AK44/V44-1,0) -> 0
I45: Diesel | V45: =IFERROR((V9-(V18+V21+V26))/V41,0) -> 0 | Y45: =IFERROR((Y9-(Y18+Y21+Y26))/Y41,0) -> 0 | Z45: =IFERROR((Z9-(Z18+Z21+Z26))/Z41,0) -> 0 | AA45: =IFERROR((AA9-(AA18+AA21+AA26))/AA41,0) -> 0 | AB45: =IFERROR((AB9-(AB18+AB21+AB26))/AB41,0) -> 0 | AC45: =IFERROR((AC9-(AC18+AC21+AC26))/AC41,0) -> 0 | AD45: =IFERROR((AD9-(AD18+AD21+AD26))/AD41,0) -> 0 | AE45: =IFERROR((AE9-(AE18+AE21+AE26))/AE41,0) -> 0 | AF45: =IFERROR((AF9-(AF18+AF21+AF26))/AF41,0) -> 0 | ... AK45: =IFERROR((AK9-(AK18+AK21+AK26))/AK41,0) -> 0 | AM45: =IFERROR(AK45/V45-1,0) -> 0
E47: ( menos ) | I47: GASTO ESTACIONES
A49: E - GASTOS DE OPERACIÓN | B49: estaciones | I49: E - GASTOS DE OPERACIÓN | V49: =SUM(V50:V87) -> 0 | W49: =V49/V$6 -> #DIV/0! | Y49: =SUM(Y50:Y87) -> 0 | Z49: =SUM(Z50:Z87) -> 0 | AA49: =SUM(AA50:AA87) -> 0 | AB49: =SUM(AB50:AB87) -> 0 | AC49: =SUM(AC50:AC87) -> 0 | AD49: =SUM(AD50:AD87) -> 0 | AE49: =SUM(AE50:AE87) -> 0 | AF49: =SUM(AF50:AF87) -> 0 | ... AK49: =SUM(AK50:AK87) -> 0 | AL49: =AK49/AK$6 -> #DIV/0! | AM49: =IFERROR(AK49/V49-1,0) -> 0
A50: E - GASTOS DE OPERACIÓN | B50: estaciones | C50: Servicios Administrativos | I50: Traslado de Valores | V50: =SUM(J50:U50) -> 0 | W50: =V50/V$6 -> #DIV/0! | Y50: 0 | Z50: 0 | AA50: 0 | AB50: 0 | AC50: 0 | AD50: 0 | AE50: 0 | AF50: 0 | AG50: 0 | AH50: 0 | AI50: 0 | AJ50: 0 | AK50: =SUM(Y50:AJ50) -> 0 | AL50: =AK50/AK$6 -> #DIV/0! | AM50: =IFERROR(AK50/V50-1,0) -> 0
A51: E - GASTOS DE OPERACIÓN | B51: estaciones | I51: Servicios Administrativos | V51: =SUM(J51:U51) -> 0 | W51: =V51/V$6 -> #DIV/0! | Y51: 0 | Z51: 0 | AA51: 0 | AB51: 0 | AC51: 0 | AD51: 0 | AE51: 0 | AF51: 0 | AG51: 0 | AH51: 0 | AI51: 0 | AJ51: 0 | AK51: =SUM(Y51:AJ51) -> 0 | AL51: =AK51/AK$6 -> #DIV/0! | AM51: =IFERROR(AK51/V51-1,0) -> 0
A52: E - GASTOS DE OPERACIÓN | B52: estaciones | I52: Eventos | V52: =SUM(J52:U52) -> 0 | W52: =V52/V$6 -> #DIV/0! | Y52: 0 | Z52: 0 | AA52: 0 | AB52: 0 | AC52: 0 | AD52: 0 | AE52: 0 | AF52: 0 | AG52: 0 | AH52: 0 | AI52: 0 | AJ52: 0 | AK52: =SUM(Y52:AJ52) -> 0 | AL52: =AK52/AK$6 -> #DIV/0! | AM52: =IFERROR(AK52/V52-1,0) -> 0
A53: E - GASTOS DE OPERACIÓN | B53: estaciones | I53: Otros Gastos | V53: =SUM(J53:U53) -> 0 | W53: =V53/V$6 -> #DIV/0! | Y53: 0 | Z53: 0 | AA53: 0 | AB53: 0 | AC53: 0 | AD53: 0 | AE53: 0 | AF53: 0 | AG53: 0 | AH53: 0 | AI53: 0 | AJ53: 0 | AK53: =SUM(Y53:AJ53) -> 0 | AL53: =AK53/AK$6 -> #DIV/0! | AM53: =IFERROR(AK53/V53-1,0) -> 0
A54: E - GASTOS DE OPERACIÓN | B54: estaciones | C54: Costo Marketing | I54: Otros impuestos y derechos | V54: =SUM(J54:U54) -> 0 | W54: =V54/V$6 -> #DIV/0! | Y54: 0 | Z54: 0 | AA54: 0 | AB54: 0 | AC54: 0 | AD54: 0 | AE54: 0 | AF54: 0 | AG54: 0 | AH54: 0 | AI54: 0 | AJ54: 0 | AK54: =SUM(Y54:AJ54) -> 0 | AL54: =AK54/AK$6 -> #DIV/0! | AM54: =IFERROR(AK54/V54-1,0) -> 0
A55: E - GASTOS DE OPERACIÓN | B55: estaciones | I55: Gas Natural | V55: =SUM(J55:U55) -> 0 | W55: =V55/V$6 -> #DIV/0! | Y55: 0 | Z55: 0 | AA55: 0 | AB55: 0 | AC55: 0 | AD55: 0 | AE55: 0 | AF55: 0 | AG55: 0 | AH55: 0 | AI55: 0 | AJ55: 0 | AK55: =SUM(Y55:AJ55) -> 0 | AL55: =AK55/AK$6 -> #DIV/0! | AM55: =IFERROR(AK55/V55-1,0) -> 0
A56: E - GASTOS DE OPERACIÓN | B56: estaciones | I56: Limpieza | V56: =SUM(J56:U56) -> 0 | W56: =V56/V$6 -> #DIV/0! | Y56: 0 | Z56: 0 | AA56: 0 | AB56: 0 | AC56: 0 | AD56: 0 | AE56: 0 | AF56: 0 | AG56: 0 | AH56: 0 | AI56: 0 | AJ56: 0 | AK56: =SUM(Y56:AJ56) -> 0 | AL56: =AK56/AK$6 -> #DIV/0! | AM56: =IFERROR(AK56/V56-1,0) -> 0
A57: E - GASTOS DE OPERACIÓN | B57: estaciones | I57: Propaganda y publicidad | V57: =SUM(J57:U57) -> 0 | W57: =V57/V$6 -> #DIV/0! | Y57: 0 | Z57: 0 | AA57: 0 | AB57: 0 | AC57: 0 | AD57: 0 | AE57: 0 | AF57: 0 | AG57: 0 | AH57: 0 | AI57: 0 | AJ57: 0 | AK57: =SUM(Y57:AJ57) -> 0 | AL57: =AK57/AK$6 -> #DIV/0! | AM57: =IFERROR(AK57/V57-1,0) -> 0
A58: E - GASTOS DE OPERACIÓN | B58: estaciones | I58: Contingencia Covid | V58: =SUM(J58:U58) -> 0 | W58: =V58/V$6 -> #DIV/0! | Y58: 0 | Z58: 0 | AA58: 0 | AB58: 0 | AC58: 0 | AD58: 0 | AE58: 0 | AF58: 0 | AG58: 0 | AH58: 0 | AI58: 0 | AJ58: 0 | AK58: =SUM(Y58:AJ58) -> 0 | AL58: =AK58/AK$6 -> #DIV/0! | AM58: =IFERROR(AK58/V58-1,0) -> 0
A59: E - GASTOS DE OPERACIÓN | B59: estaciones | I59: Gastos no deducibles (sin requisitos fiscales) | V59: =SUM(J59:U59) -> 0 | W59: =V59/V$6 -> #DIV/0! | Y59: 0 | Z59: 0 | AA59: 0 | AB59: 0 | AC59: 0 | AD59: 0 | AE59: 0 | AF59: 0 | AG59: 0 | AH59: 0 | AI59: 0 | AJ59: 0 | AK59: =SUM(Y59:AJ59) -> 0 | AL59: =AK59/AK$6 -> #DIV/0! | AM59: =IFERROR(AK59/V59-1,0) -> 0
A60: E - GASTOS DE OPERACIÓN | B60: estaciones | I60: Asesoría en sistemas | V60: =SUM(J60:U60) -> 0 | W60: =V60/V$6 -> #DIV/0! | Y60: 0 | Z60: 0 | AA60: 0 | AB60: 0 | AC60: 0 | AD60: 0 | AE60: 0 | AF60: 0 | AG60: 0 | AH60: 0 | AI60: 0 | AJ60: 0 | AK60: =SUM(Y60:AJ60) -> 0 | AL60: =AK60/AK$6 -> #DIV/0! | AM60: =IFERROR(AK60/V60-1,0) -> 0
A61: E - GASTOS DE OPERACIÓN | B61: estaciones | I61: Papelería y artículos de oficina | V61: =SUM(J61:U61) -> 0 | W61: =V61/V$6 -> #DIV/0! | Y61: 0 | Z61: 0 | AA61: 0 | AB61: 0 | AC61: 0 | AD61: 0 | AE61: 0 | AF61: 0 | AG61: 0 | AH61: 0 | AI61: 0 | AJ61: 0 | AK61: =SUM(Y61:AJ61) -> 0 | AL61: =AK61/AK$6 -> #DIV/0! | AM61: =IFERROR(AK61/V61-1,0) -> 0
A62: E - GASTOS DE OPERACIÓN | B62: estaciones | I62: Faltantes | V62: =SUM(J62:U62) -> 0 | W62: =V62/V$6 -> #DIV/0! | Y62: 0 | Z62: 0 | AA62: 0 | AB62: 0 | AC62: 0 | AD62: 0 | AE62: 0 | AF62: 0 | AG62: 0 | AH62: 0 | AI62: 0 | AJ62: 0 | AK62: =SUM(Y62:AJ62) -> 0 | AL62: =AK62/AK$6 -> #DIV/0! | AM62: =IFERROR(AK62/V62-1,0) -> 0
A63: E - GASTOS DE OPERACIÓN | B63: estaciones | I63: Licencias y Permisos | V63: =SUM(J63:U63) -> 0 | W63: =V63/V$6 -> #DIV/0! | Y63: 0 | Z63: 0 | AA63: 0 | AB63: 0 | AC63: 0 | AD63: 0 | AE63: 0 | AF63: 0 | AG63: 0 | AH63: 0 | AI63: 0 | AJ63: 0 | AK63: =SUM(Y63:AJ63) -> 0 | AL63: =AK63/AK$6 -> #DIV/0! | AM63: =IFERROR(AK63/V63-1,0) -> 0
A64: E - GASTOS DE OPERACIÓN | B64: estaciones | I64: Capacitación al personal | V64: =SUM(J64:U64) -> 0 | W64: =V64/V$6 -> #DIV/0! | Y64: 0 | Z64: 0 | AA64: 0 | AB64: 0 | AC64: 0 | AD64: 0 | AE64: 0 | AF64: 0 | AG64: 0 | AH64: 0 | AI64: 0 | AJ64: 0 | AK64: =SUM(Y64:AJ64) -> 0 | AL64: =AK64/AK$6 -> #DIV/0! | AM64: =IFERROR(AK64/V64-1,0) -> 0
A65: E - GASTOS DE OPERACIÓN | B65: estaciones | I65: Licencias, Software, Antivirus | V65: =SUM(J65:U65) -> 0 | W65: =V65/V$6 -> #DIV/0! | Y65: 0 | Z65: 0 | AA65: 0 | AB65: 0 | AC65: 0 | AD65: 0 | AE65: 0 | AF65: 0 | AG65: 0 | AH65: 0 | AI65: 0 | AJ65: 0 | AK65: =SUM(Y65:AJ65) -> 0 | AL65: =AK65/AK$6 -> #DIV/0! | AM65: =IFERROR(AK65/V65-1,0) -> 0
A66: E - GASTOS DE OPERACIÓN | B66: estaciones | I66: Fletes Combustible | V66: =SUM(J66:U66) -> 0 | W66: =V66/V$6 -> #DIV/0! | Y66: 0 | Z66: 0 | AA66: 0 | AB66: 0 | AC66: 0 | AD66: 0 | AE66: 0 | AF66: 0 | AG66: 0 | AH66: 0 | AI66: 0 | AJ66: 0 | AK66: =SUM(Y66:AJ66) -> 0 | AL66: =AK66/AK$6 -> #DIV/0! | AM66: =IFERROR(AK66/V66-1,0) -> 0
... A72: E - GASTOS DE OPERACIÓN | B72: estaciones | I72: Asistencia técnica | V72: =SUM(J72:U72) -> 0 | W72: =V72/V$6 -> #DIV/0! | Y72: 0 | Z72: 0 | AA72: 0 | AB72: 0 | AC72: 0 | AD72: 0 | AE72: 0 | AF72: 0 | AG72: 0 | AH72: 0 | AI72: 0 | AJ72: 0 | AK72: =SUM(Y72:AJ72) -> 0 | AL72: =AK72/AK$6 -> #DIV/0! | AM72: =IFERROR(AK72/V72-1,0) -> 0
I73: Combustibles Reembolsos
I74: Renta Equipo de Sistemas
I75: Timbrado Facturas
I76: Rentas No Deducibles
I77: Uniformes
I78: Contratacion Empleados
I79: Multas y Recargos
I80: Honorarios Administrativos P.F.
I81: Honorarios Administrativos P.M.
I82: Honorarios Legales P.F.
I83: Honorarios Legales P.M.
I84: Honorarios de Consultoria
... I87: Prediales
A88: C - NOMINA | B88: estaciones | I88: C - NOMINA | V88: =SUM(V89:V103) -> 0 | W88: =V88/V$6 -> #DIV/0! | Y88: =SUM(Y89:Y103) -> 0 | Z88: =SUM(Z89:Z103) -> 0 | AA88: =SUM(AA89:AA103) -> 0 | AB88: =SUM(AB89:AB103) -> 0 | AC88: =SUM(AC89:AC103) -> 0 | AD88: =SUM(AD89:AD103) -> 0 | AE88: =SUM(AE89:AE103) -> 0 | AF88: =SUM(AF89:AF103) -> 0 | ... AK88: =SUM(AK89:AK103) -> 0 | AL88: =AK88/AK$6 -> #DIV/0! | AM88: =IFERROR(AK88/V88-1,0) -> 0
A89: C - NOMINA | B89: estaciones | I89: Aguinaldo | V89: =SUM(J89:U89) -> 0 | W89: =V89/V$6 -> #DIV/0! | AK89: =SUM(Y89:AJ89) -> 0 | AL89: =AK89/AK$6 -> #DIV/0! | AM89: =IFERROR(AK89/V89-1,0) -> 0
A90: C - NOMINA | B90: estaciones | I90: Compensaciones | V90: =SUM(J90:U90) -> 0 | W90: =V90/V$6 -> #DIV/0! | AK90: =SUM(Y90:AJ90) -> 0 | AL90: =AK90/AK$6 -> #DIV/0! | AM90: =IFERROR(AK90/V90-1,0) -> 0
A91: C - NOMINA | B91: estaciones | I91: Días festivos | V91: =SUM(J91:U91) -> 0 | W91: =V91/V$6 -> #DIV/0! | AK91: =SUM(Y91:AJ91) -> 0 | AL91: =AK91/AK$6 -> #DIV/0! | AM91: =IFERROR(AK91/V91-1,0) -> 0
A92: C - NOMINA | B92: estaciones | I92: Fondo de ahorro | V92: =SUM(J92:U92) -> 0 | W92: =V92/V$6 -> #DIV/0! | AK92: =SUM(Y92:AJ92) -> 0 | AL92: =AK92/AK$6 -> #DIV/0! | AM92: =IFERROR(AK92/V92-1,0) -> 0
A93: C - NOMINA | B93: estaciones | I93: Indemnizaciones | V93: =SUM(J93:U93) -> 0 | W93: =V93/V$6 -> #DIV/0! | AK93: =SUM(Y93:AJ93) -> 0 | AL93: =AK93/AK$6 -> #DIV/0! | AM93: =IFERROR(AK93/V93-1,0) -> 0
A94: C - NOMINA | B94: estaciones | I94: Premios de asistencia | V94: =SUM(J94:U94) -> 0 | W94: =V94/V$6 -> #DIV/0! | AK94: =SUM(Y94:AJ94) -> 0 | AL94: =AK94/AK$6 -> #DIV/0! | AM94: =IFERROR(AK94/V94-1,0) -> 0
A95: C - NOMINA | B95: estaciones | I95: Premios de puntualidad | V95: =SUM(J95:U95) -> 0 | W95: =V95/V$6 -> #DIV/0! | AK95: =SUM(Y95:AJ95) -> 0 | AL95: =AK95/AK$6 -> #DIV/0! | AM95: =IFERROR(AK95/V95-1,0) -> 0
A96: C - NOMINA | B96: estaciones | I96: Previsión social | V96: =SUM(J96:U96) -> 0 | W96: =V96/V$6 -> #DIV/0! | AK96: =SUM(Y96:AJ96) -> 0 | AL96: =AK96/AK$6 -> #DIV/0! | AM96: =IFERROR(AK96/V96-1,0) -> 0
A97: C - NOMINA | B97: estaciones | I97: Prima dominical | V97: =SUM(J97:U97) -> 0 | W97: =V97/V$6 -> #DIV/0! | AK97: =SUM(Y97:AJ97) -> 0 | AL97: =AK97/AK$6 -> #DIV/0! | AM97: =IFERROR(AK97/V97-1,0) -> 0
A98: C - NOMINA | B98: estaciones | I98: Prima vacacional | V98: =SUM(J98:U98) -> 0 | W98: =V98/V$6 -> #DIV/0! | AK98: =SUM(Y98:AJ98) -> 0 | AL98: =AK98/AK$6 -> #DIV/0! | AM98: =IFERROR(AK98/V98-1,0) -> 0
A99: C - NOMINA | B99: estaciones | I99: Primas de antigüedad | V99: =SUM(J99:U99) -> 0 | W99: =V99/V$6 -> #DIV/0! | AK99: =SUM(Y99:AJ99) -> 0 | AL99: =AK99/AK$6 -> #DIV/0! | AM99: =IFERROR(AK99/V99-1,0) -> 0
A100: C - NOMINA | B100: estaciones | I100: PTU | V100: =SUM(J100:U100) -> 0 | W100: =V100/V$6 -> #DIV/0! | AK100: =SUM(Y100:AJ100) -> 0 | AL100: =AK100/AK$6 -> #DIV/0! | AM100: =IFERROR(AK100/V100-1,0) -> 0
... A103: C - NOMINA | B103: estaciones | I103: Vacaciones | V103: =SUM(J103:U103) -> 0 | W103: =V103/V$6 -> #DIV/0! | AK103: =SUM(Y103:AJ103) -> 0 | AL103: =AK103/AK$6 -> #DIV/0! | AM103: =IFERROR(AK103/V103-1,0) -> 0
A104: D - COSTO SOCIAL | B104: estaciones | I104: D - COSTO SOCIAL | V104: =SUM(V105:V108) -> 0 | W104: =V104/V$6 -> #DIV/0! | Y104: =SUM(Y105:Y108) -> 0 | Z104: =SUM(Z105:Z108) -> 0 | AA104: =SUM(AA105:AA108) -> 0 | AB104: =SUM(AB105:AB108) -> 0 | AC104: =SUM(AC105:AC108) -> 0 | AD104: =SUM(AD105:AD108) -> 0 | AE104: =SUM(AE105:AE108) -> 0 | AF104: =SUM(AF105:AF108) -> 0 | ... AK104: =SUM(AK105:AK108) -> 0 | AL104: =AK104/AK$6 -> #DIV/0! | AM104: =IFERROR(AK104/V104-1,0) -> 0
A105: D - COSTO SOCIAL | B105: estaciones | I105: Aportaciones al infonavit | V105: =SUM(J105:U105) -> 0 | W105: =V105/V$6 -> #DIV/0! | AK105: =SUM(Y105:AJ105) -> 0 | AL105: =AK105/AK$6 -> #DIV/0! | AM105: =IFERROR(AK105/V105-1,0) -> 0
A106: D - COSTO SOCIAL | B106: estaciones | I106: Aportaciones al SAR | V106: =SUM(J106:U106) -> 0 | W106: =V106/V$6 -> #DIV/0! | AK106: =SUM(Y106:AJ106) -> 0 | AL106: =AK106/AK$6 -> #DIV/0! | AM106: =IFERROR(AK106/V106-1,0) -> 0
A107: D - COSTO SOCIAL | B107: estaciones | I107: Cuotas al IMSS | V107: =SUM(J107:U107) -> 0 | W107: =V107/V$6 -> #DIV/0! | AK107: =SUM(Y107:AJ107) -> 0 | AL107: =AK107/AK$6 -> #DIV/0! | AM107: =IFERROR(AK107/V107-1,0) -> 0
A108: D - COSTO SOCIAL | B108: estaciones | I108: Impuesto Estatal | V108: =SUM(J108:U108) -> 0 | W108: =V108/V$6 -> #DIV/0! | AK108: =SUM(Y108:AJ108) -> 0 | AL108: =AK108/AK$6 -> #DIV/0! | AM108: =IFERROR(AK108/V108-1,0) -> 0
A109: F - MANTENIMIENTO | B109: estaciones | C109: Mantenimiento de Imagen | I109: F - MANTENIMIENTO | V109: =SUM(V110:V112) -> 0 | W109: =V109/V$6 -> #DIV/0! | Y109: =SUM(Y110:Y112) -> 0 | Z109: =SUM(Z110:Z112) -> 0 | AA109: =SUM(AA110:AA112) -> 0 | AB109: =SUM(AB110:AB112) -> 0 | AC109: =SUM(AC110:AC112) -> 0 | AD109: =SUM(AD110:AD112) -> 0 | AE109: =SUM(AE110:AE112) -> 0 | AF109: =SUM(AF110:AF112) -> 0 | ... AK109: =SUM(AK110:AK112) -> 0 | AL109: =AK109/AK$6 -> #DIV/0! | AM109: =IFERROR(AK109/V109-1,0) -> 0
A110: F - MANTENIMIENTO | B110: estaciones | I110: Mantenimiento de Equipo de Computo | V110: =SUM(J110:U110) -> 0 | W110: =V110/V$6 -> #DIV/0! | Y110: 0 | Z110: 0 | AA110: 0 | AB110: 0 | AC110: 0 | AD110: 0 | AE110: 0 | AF110: 0 | AG110: 0 | AH110: 0 | AI110: 0 | AJ110: 0 | AK110: =SUM(Y110:AJ110) -> 0 | AL110: =AK110/AK$6 -> #DIV/0! | AM110: =IFERROR(AK110/V110-1,0) -> 0
A111: F - MANTENIMIENTO | B111: estaciones | I111: Mantenimiento de Vehiculos | V111: =SUM(J111:U111) -> 0 | W111: =V111/V$6 -> #DIV/0! | Y111: 0 | Z111: 0 | AA111: 0 | AB111: 0 | AC111: 0 | AD111: 0 | AE111: 0 | AF111: 0 | AG111: 0 | AH111: 0 | AI111: 0 | AJ111: 0 | AK111: =SUM(Y111:AJ111) -> 0 | AL111: =AK111/AK$6 -> #DIV/0! | AM111: =IFERROR(AK111/V111-1,0) -> 0
A112: F - MANTENIMIENTO | B112: estaciones | I112: Seguridad e Higiene Ambiental | V112: =SUM(J112:U112) -> 0 | W112: =V112/V$6 -> #DIV/0! | Y112: 0 | Z112: 0 | AA112: 0 | AB112: 0 | AC112: 0 | AD112: 0 | AE112: 0 | AF112: 0 | AG112: 0 | AH112: 0 | AI112: 0 | AJ112: 0 | AK112: =SUM(Y112:AJ112) -> 0 | AL112: =AK112/AK$6 -> #DIV/0! | AM112: =IFERROR(AK112/V112-1,0) -> 0
...

Sheet Z

Sheet EDO RESULTADOS MISMAS EST
I1: Mantenimiento de Imagen | J1: 2 | K1: 3 | L1: 4 | M1: 5 | N1: 6 | O1: 7 | Y1: 2 | Z1: 3 | AA1: 4 | AB1: 5 | AC1: 6 | AD1: 7 | AE1: 8 | AF1: 9 | AG1: 10 | AH1: 11 | AI1: 12 | AJ1: 13 | AM1: 17
J2: 2025 | V2: TOTAL ANUAL | Y2: 2026 | AK2: PPTO ANUAL MISMAS EST | AS2: PPTO ANUAL MISMAS EST
J3: ENE | K3: FEB | L3: MAR | M3: ABR | N3: MAY | O3: JUN | P3: JUL | Q3: AGO | R3: SEP | S3: OCT | T3: NOV | U3: DIC | V3: 2025 | W3: % Part | Y3: ENE | Z3: FEB | AA3: MAR | AB3: ABR | AC3: MAY | AD3: JUN | AE3: JUL | AF3: AGO | AG3: SEP | AH3: OCT | AI3: NOV | AJ3: DIC | AK3: 2026 | AL3: % Part | AM3: Var vs AA% | AS3: 2026
I4: INGRESOS
A6: A - INGRESOS | E6: ( mas ) | I6: A - INGRESOS | J6: ='TOTAL ESTACIONES'!J6 -> 69452870 | K6: ='TOTAL ESTACIONES'!K6 -> 68676679 | L6: ='TOTAL ESTACIONES'!L6 -> 74038427 | M6: ='TOTAL ESTACIONES'!M6 -> 69224559 | N6: ='TOTAL ESTACIONES'!N6 -> 77933808 | O6: ='TOTAL ESTACIONES'!O6 -> 77696456 | P6: ='TOTAL ESTACIONES'!P6 -> 76552162 | Q6: ='TOTAL ESTACIONES'!Q6 -> 70332214 | ... W6: ='TOTAL ESTACIONES'!W6 -> 1 | Y6: ='TOTAL ESTACIONES'!Y6 -> 69733029 | Z6: ='TOTAL ESTACIONES'!Z6 -> 69139078 | AA6: ='TOTAL ESTACIONES'!AA6 -> 76712717 | AB6: ='TOTAL ESTACIONES'!AB6 -> 72969416 | AC6: ='TOTAL ESTACIONES'!AC6 -> 84041095 | AD6: ='TOTAL ESTACIONES'!AD6 -> 83841112 | AE6: ='TOTAL ESTACIONES'!AE6 -> 83649040 | AF6: ='TOTAL ESTACIONES'!AF6 -> 85393702 | ... AM6: ='TOTAL ESTACIONES'!AM6 -> 0.074779166 | AS6: 9.6284792e+08
A7: A - INGRESOS | B7: estaciones | C7: INGRESOS MAGNA | D7: INGRESOS FORANEOS MAGNA | I7: MAXIMA | J7: ='TOTAL ESTACIONES'!J7 -> 52024925 | K7: ='TOTAL ESTACIONES'!K7 -> 51666858 | L7: ='TOTAL ESTACIONES'!L7 -> 55424481 | M7: ='TOTAL ESTACIONES'!M7 -> 52126321 | N7: ='TOTAL ESTACIONES'!N7 -> 58611053 | O7: ='TOTAL ESTACIONES'!O7 -> 57223116 | P7: ='TOTAL ESTACIONES'!P7 -> 55837049 | Q7: ='TOTAL ESTACIONES'!Q7 -> 53402377 | ... W7: ='TOTAL ESTACIONES'!W7 -> 0.75428499 | Y7: ='TOTAL ESTACIONES'!Y7 -> 51376336 | Z7: ='TOTAL ESTACIONES'!Z7 -> 51093583 | AA7: ='TOTAL ESTACIONES'!AA7 -> 56927257 | AB7: ='TOTAL ESTACIONES'!AB7 -> 54191883 | AC7: ='TOTAL ESTACIONES'!AC7 -> 63090563 | AD7: ='TOTAL ESTACIONES'!AD7 -> 62100321 | AE7: ='TOTAL ESTACIONES'!AE7 -> 61646409 | AF7: ='TOTAL ESTACIONES'!AF7 -> 64583060 | ... AM7: ='TOTAL ESTACIONES'!AM7 -> 0.06158167 | AS7: 7.175899e+08
A8: A - INGRESOS | B8: estaciones | C8: INGRESOS PREMIUM | D8: INGRESOS FORANEOS PREMIUM | I8: SUPER | J8: ='TOTAL ESTACIONES'!J8 -> 5468366 | K8: ='TOTAL ESTACIONES'!K8 -> 5650927 | L8: ='TOTAL ESTACIONES'!L8 -> 6229300 | M8: ='TOTAL ESTACIONES'!M8 -> 5959245 | N8: ='TOTAL ESTACIONES'!N8 -> 6580767 | O8: ='TOTAL ESTACIONES'!O8 -> 6797460 | P8: ='TOTAL ESTACIONES'!P8 -> 6511011 | Q8: ='TOTAL ESTACIONES'!Q8 -> 4596705 | ... W8: ='TOTAL ESTACIONES'!W8 -> 0.080056651 | Y8: ='TOTAL ESTACIONES'!Y8 -> 5360351.8 | Z8: ='TOTAL ESTACIONES'!Z8 -> 5553280.4 | AA8: ='TOTAL ESTACIONES'!AA8 -> 6278391.1 | AB8: ='TOTAL ESTACIONES'!AB8 -> 5971144.2 | AC8: ='TOTAL ESTACIONES'!AC8 -> 6969804.5 | AD8: ='TOTAL ESTACIONES'!AD8 -> 7376824 | AE8: ='TOTAL ESTACIONES'!AE8 -> 7096503.4 | AF8: ='TOTAL ESTACIONES'!AF8 -> 7282731 | ... AM8: ='TOTAL ESTACIONES'!AM8 -> 0.10263738 | AS8: 79107483
A9: A - INGRESOS | B9: estaciones | C9: INGRESOS DIESEL | D9: INGRESOS FORANEOS DIESEL | I9: DIESEL | J9: ='TOTAL ESTACIONES'!J9 -> 11903653 | K9: ='TOTAL ESTACIONES'!K9 -> 11298703 | L9: ='TOTAL ESTACIONES'!L9 -> 12326817 | M9: ='TOTAL ESTACIONES'!M9 -> 11076012 | N9: ='TOTAL ESTACIONES'!N9 -> 12676022 | O9: ='TOTAL ESTACIONES'!O9 -> 13611508 | P9: ='TOTAL ESTACIONES'!P9 -> 14146233 | Q9: ='TOTAL ESTACIONES'!Q9 -> 12274004 | ... W9: ='TOTAL ESTACIONES'!W9 -> 0.16484128 | Y9: ='TOTAL ESTACIONES'!Y9 -> 12921702 | Z9: ='TOTAL ESTACIONES'!Z9 -> 12420215 | AA9: ='TOTAL ESTACIONES'!AA9 -> 13411609 | AB9: ='TOTAL ESTACIONES'!AB9 -> 12736669 | AC9: ='TOTAL ESTACIONES'!AC9 -> 13904947 | AD9: ='TOTAL ESTACIONES'!AD9 -> 14292866 | AE9: ='TOTAL ESTACIONES'!AE9 -> 14834428 | AF9: ='TOTAL ESTACIONES'!AF9 -> 13459330 | ... AM9: ='TOTAL ESTACIONES'!AM9 -> 0.12087765 | AS9: 1.6558143e+08
I10: INGRESOS ACEITES Y LUBRICANTES | J10: ='TOTAL ESTACIONES'!J10 -> 55926 | K10: ='TOTAL ESTACIONES'!K10 -> 60191 | L10: ='TOTAL ESTACIONES'!L10 -> 57829 | M10: ='TOTAL ESTACIONES'!M10 -> 62981 | N10: ='TOTAL ESTACIONES'!N10 -> 65966 | O10: ='TOTAL ESTACIONES'!O10 -> 64372 | P10: ='TOTAL ESTACIONES'!P10 -> 57869 | Q10: ='TOTAL ESTACIONES'!Q10 -> 59128 | ... W10: ='TOTAL ESTACIONES'!W10 -> 0.00081707354 | Y10: ='TOTAL ESTACIONES'!Y10 -> 74640 | Z10: ='TOTAL ESTACIONES'!Z10 -> 72000 | AA10: ='TOTAL ESTACIONES'!AA10 -> 95460 | AB10: ='TOTAL ESTACIONES'!AB10 -> 69720 | AC10: ='TOTAL ESTACIONES'!AC10 -> 75780 | AD10: ='TOTAL ESTACIONES'!AD10 -> 71100 | AE10: ='TOTAL ESTACIONES'!AE10 -> 71700 | AF10: ='TOTAL ESTACIONES'!AF10 -> 68580 | ... AM10: ='TOTAL ESTACIONES'!AM10 -> 0.2283815 | AS10: 569100
I11: SOBRANTE COMBUSTIBLE | J11: ='TOTAL ESTACIONES'!J11 -> 0 | K11: ='TOTAL ESTACIONES'!K11 -> 0 | L11: ='TOTAL ESTACIONES'!L11 -> 0 | M11: ='TOTAL ESTACIONES'!M11 -> 0 | N11: ='TOTAL ESTACIONES'!N11 -> 0 | O11: ='TOTAL ESTACIONES'!O11 -> 0 | P11: ='TOTAL ESTACIONES'!P11 -> 0 | Q11: ='TOTAL ESTACIONES'!Q11 -> 0 | ... W11: ='TOTAL ESTACIONES'!W11 -> 0 | Y11: ='TOTAL ESTACIONES'!Y11 -> 0 | Z11: ='TOTAL ESTACIONES'!Z11 -> 0 | AA11: ='TOTAL ESTACIONES'!AA11 -> 0 | AB11: ='TOTAL ESTACIONES'!AB11 -> 0 | AC11: ='TOTAL ESTACIONES'!AC11 -> 0 | AD11: ='TOTAL ESTACIONES'!AD11 -> 0 | AE11: ='TOTAL ESTACIONES'!AE11 -> 0 | AF11: ='TOTAL ESTACIONES'!AF11 -> 0 | ... AM11: ='TOTAL ESTACIONES'!AM11 -> 0 | AS11: 0
J12: ='TOTAL ESTACIONES'!J12 -> 0 | K12: ='TOTAL ESTACIONES'!K12 -> 0 | L12: ='TOTAL ESTACIONES'!L12 -> 0 | M12: ='TOTAL ESTACIONES'!M12 -> 0 | N12: ='TOTAL ESTACIONES'!N12 -> 0 | O12: ='TOTAL ESTACIONES'!O12 -> 0 | P12: ='TOTAL ESTACIONES'!P12 -> 0 | Q12: ='TOTAL ESTACIONES'!Q12 -> 0 | ... W12: ='TOTAL ESTACIONES'!W12 -> 0 | Y12: ='TOTAL ESTACIONES'!Y12 -> 0 | Z12: ='TOTAL ESTACIONES'!Z12 -> 0 | AA12: ='TOTAL ESTACIONES'!AA12 -> 0 | AB12: ='TOTAL ESTACIONES'!AB12 -> 0 | AC12: ='TOTAL ESTACIONES'!AC12 -> 0 | AD12: ='TOTAL ESTACIONES'!AD12 -> 0 | AE12: ='TOTAL ESTACIONES'!AE12 -> 0 | AF12: ='TOTAL ESTACIONES'!AF12 -> 0 | ... AM12: ='TOTAL ESTACIONES'!AM12 -> 0 | AS12: 0
A13: B - COSTO DE VENTA | E13: ( menos ) | I13: B - COSTO DE VENTA | J13: ='TOTAL ESTACIONES'!J13 -> 59783497 | K13: ='TOTAL ESTACIONES'!K13 -> 58274255 | L13: ='TOTAL ESTACIONES'!L13 -> 63406479 | M13: ='TOTAL ESTACIONES'!M13 -> 59049480 | N13: ='TOTAL ESTACIONES'!N13 -> 65462131 | O13: ='TOTAL ESTACIONES'!O13 -> 66797081 | P13: ='TOTAL ESTACIONES'!P13 -> 66311059 | Q13: ='TOTAL ESTACIONES'!Q13 -> 61034025 | ... W13: ='TOTAL ESTACIONES'!W13 -> 0.8569024 | Y13: ='TOTAL ESTACIONES'!Y13 -> 60165791 | Z13: ='TOTAL ESTACIONES'!Z13 -> 59829241 | AA13: ='TOTAL ESTACIONES'!AA13 -> 66068704 | AB13: ='TOTAL ESTACIONES'!AB13 -> 63509117 | AC13: ='TOTAL ESTACIONES'!AC13 -> 72484085 | AD13: ='TOTAL ESTACIONES'!AD13 -> 73043997 | AE13: ='TOTAL ESTACIONES'!AE13 -> 72992851 | AF13: ='TOTAL ESTACIONES'!AF13 -> 74396670 | ... AM13: ='TOTAL ESTACIONES'!AM13 -> 0.092395952 | AS13: 8.3859734e+08
A14: B - COSTO DE VENTA | C14: COSTO MAGNA | D14: COSTO FORANEO MAGNA | I14: GASOLINA REGULAR | J14: ='TOTAL ESTACIONES'!J14 -> 54037503 | K14: ='TOTAL ESTACIONES'!K14 -> 52988836 | L14: ='TOTAL ESTACIONES'!L14 -> 58109663 | M14: ='TOTAL ESTACIONES'!M14 -> 54182667 | N14: ='TOTAL ESTACIONES'!N14 -> 61241981 | O14: ='TOTAL ESTACIONES'!O14 -> 60864148 | P14: ='TOTAL ESTACIONES'!P14 -> 59642077 | Q14: ='TOTAL ESTACIONES'!Q14 -> 56951729 | ... W14: ='TOTAL ESTACIONES'!W14 -> 0.76187727 | Y14: ='TOTAL ESTACIONES'!Y14 -> 43965152 | Z14: ='TOTAL ESTACIONES'!Z14 -> 43858767 | AA14: ='TOTAL ESTACIONES'!AA14 -> 48610578 | AB14: ='TOTAL ESTACIONES'!AB14 -> 46833763 | AC14: ='TOTAL ESTACIONES'!AC14 -> 53940557 | AD14: ='TOTAL ESTACIONES'!AD14 -> 53743511 | AE14: ='TOTAL ESTACIONES'!AE14 -> 53413437 | AF14: ='TOTAL ESTACIONES'!AF14 -> 55867226 | ... AM14: ='TOTAL ESTACIONES'!AM14 -> -0.091212883 | AS14: 6.2048976e+08
A15: B - COSTO DE VENTA | C15: COSTO PREMIUM | D15: COSTO FORANEO PREMIUM | I15: GASOLINA PREMIUM | J15: ='TOTAL ESTACIONES'!J15 -> 5319273 | K15: ='TOTAL ESTACIONES'!K15 -> 5477157 | L15: ='TOTAL ESTACIONES'!L15 -> 6024604 | M15: ='TOTAL ESTACIONES'!M15 -> 5759007 | N15: ='TOTAL ESTACIONES'!N15 -> 6417905 | O15: ='TOTAL ESTACIONES'!O15 -> 6709392 | P15: ='TOTAL ESTACIONES'!P15 -> 6539768 | Q15: ='TOTAL ESTACIONES'!Q15 -> 4716580 | ... W15: ='TOTAL ESTACIONES'!W15 -> 0.077487614 | Y15: ='TOTAL ESTACIONES'!Y15 -> 4659126.8 | Z15: ='TOTAL ESTACIONES'!Z15 -> 4832868.2 | AA15: ='TOTAL ESTACIONES'!AA15 -> 5459075.2 | AB15: ='TOTAL ESTACIONES'!AB15 -> 5216593.9 | AC15: ='TOTAL ESTACIONES'!AC15 -> 6098775.6 | AD15: ='TOTAL ESTACIONES'!AD15 -> 6452142 | AE15: ='TOTAL ESTACIONES'!AE15 -> 6245227.6 | AF15: ='TOTAL ESTACIONES'!AF15 -> 6398892.4 | ... AM15: ='TOTAL ESTACIONES'!AM15 -> -0.00054299936 | AS15: 69403895
A16: B - COSTO DE VENTA | C16: COSTO DIESEL | D16: COSTO FORANEO DIESEL | I16: DIESEL | J16: ='TOTAL ESTACIONES'!J16 -> 10212607 | K16: ='TOTAL ESTACIONES'!K16 -> 10010596 | L16: ='TOTAL ESTACIONES'!L16 -> 10864455 | M16: ='TOTAL ESTACIONES'!M16 -> 9847047 | N16: ='TOTAL ESTACIONES'!N16 -> 11207696 | O16: ='TOTAL ESTACIONES'!O16 -> 12305498 | P16: ='TOTAL ESTACIONES'!P16 -> 12857250 | Q16: ='TOTAL ESTACIONES'!Q16 -> 10940446 | ... W16: ='TOTAL ESTACIONES'!W16 -> 0.14682351 | Y16: ='TOTAL ESTACIONES'!Y16 -> 11478068 | Z16: ='TOTAL ESTACIONES'!Z16 -> 11076406 | AA16: ='TOTAL ESTACIONES'!AA16 -> 11917910 | AB16: ='TOTAL ESTACIONES'!AB16 -> 11399498 | AC16: ='TOTAL ESTACIONES'!AC16 -> 12380340 | AD16: ='TOTAL ESTACIONES'!AD16 -> 12787909 | AE16: ='TOTAL ESTACIONES'!AE16 -> 13273242 | AF16: ='TOTAL ESTACIONES'!AF16 -> 12072259 | ... AM16: ='TOTAL ESTACIONES'!AM16 -> 0.12648037 | AS16: 1.4821995e+08
A17: B - COSTO DE VENTA | C17: Merma Magna | I17: MERMA GASOLINA REGULAR | J17: ='TOTAL ESTACIONES'!J17 -> 667991 | K17: ='TOTAL ESTACIONES'!K17 -> 194258 | L17: ='TOTAL ESTACIONES'!L17 -> 95173 | M17: ='TOTAL ESTACIONES'!M17 -> 32472 | N17: ='TOTAL ESTACIONES'!N17 -> 0 | O17: ='TOTAL ESTACIONES'!O17 -> 0 | P17: ='TOTAL ESTACIONES'!P17 -> 0 | Q17: ='TOTAL ESTACIONES'!Q17 -> 0 | ... W17: ='TOTAL ESTACIONES'!W17 -> 0.0011045904 | Y17: ='TOTAL ESTACIONES'!Y17 -> 0 | Z17: ='TOTAL ESTACIONES'!Z17 -> 0 | AA17: ='TOTAL ESTACIONES'!AA17 -> 0 | AB17: ='TOTAL ESTACIONES'!AB17 -> 0 | AC17: ='TOTAL ESTACIONES'!AC17 -> 0 | AD17: ='TOTAL ESTACIONES'!AD17 -> 0 | AE17: ='TOTAL ESTACIONES'!AE17 -> 0 | AF17: ='TOTAL ESTACIONES'!AF17 -> 0 | ... AM17: ='TOTAL ESTACIONES'!AM17 -> -1 | AS17: 0
A18: B - COSTO DE VENTA | C18: Merma Premium | I18: MERMA GASOLINA PREMIUM | J18: ='TOTAL ESTACIONES'!J18 -> 112597 | K18: ='TOTAL ESTACIONES'!K18 -> 32019 | L18: ='TOTAL ESTACIONES'!L18 -> -1798 | M18: ='TOTAL ESTACIONES'!M18 -> 5421 | N18: ='TOTAL ESTACIONES'!N18 -> 1054 | O18: ='TOTAL ESTACIONES'!O18 -> 0 | P18: ='TOTAL ESTACIONES'!P18 -> 4980 | Q18: ='TOTAL ESTACIONES'!Q18 -> 0 | ... W18: ='TOTAL ESTACIONES'!W18 -> 0.00019661024 | Y18: ='TOTAL ESTACIONES'!Y18 -> 0 | Z18: ='TOTAL ESTACIONES'!Z18 -> 0 | AA18: ='TOTAL ESTACIONES'!AA18 -> 0 | AB18: ='TOTAL ESTACIONES'!AB18 -> 0 | AC18: ='TOTAL ESTACIONES'!AC18 -> 0 | AD18: ='TOTAL ESTACIONES'!AD18 -> 0 | AE18: ='TOTAL ESTACIONES'!AE18 -> 0 | AF18: ='TOTAL ESTACIONES'!AF18 -> 0 | ... AM18: ='TOTAL ESTACIONES'!AM18 -> -1 | AS18: 0
A19: B - COSTO DE VENTA | C19: Merma Diesel | I19: MERMA DIESEL | J19: ='TOTAL ESTACIONES'!J19 -> 852 | K19: ='TOTAL ESTACIONES'!K19 -> 0 | L19: ='TOTAL ESTACIONES'!L19 -> 302 | M19: ='TOTAL ESTACIONES'!M19 -> 384 | N19: ='TOTAL ESTACIONES'!N19 -> 1771 | O19: ='TOTAL ESTACIONES'!O19 -> 0 | P19: ='TOTAL ESTACIONES'!P19 -> 0 | Q19: ='TOTAL ESTACIONES'!Q19 -> 9479 | ... W19: ='TOTAL ESTACIONES'!W19 -> 1.6706766e-05 | Y19: ='TOTAL ESTACIONES'!Y19 -> 0 | Z19: ='TOTAL ESTACIONES'!Z19 -> 0 | AA19: ='TOTAL ESTACIONES'!AA19 -> 0 | AB19: ='TOTAL ESTACIONES'!AB19 -> 0 | AC19: ='TOTAL ESTACIONES'!AC19 -> 0 | AD19: ='TOTAL ESTACIONES'!AD19 -> 0 | AE19: ='TOTAL ESTACIONES'!AE19 -> 0 | AF19: ='TOTAL ESTACIONES'!AF19 -> 0 | ... AM19: ='TOTAL ESTACIONES'!AM19 -> -1 | AS19: 0
A20: B - COSTO DE VENTA | C20: ADITIVO PARA GASOLINA TMAXIMA (REGULAR) | D20: ADITIVO PARA GASOLINA TMAXIMA( REGULAR) | I20: SOBRANTE MAGNA | J20: ='TOTAL ESTACIONES'!J20 -> 0 | K20: ='TOTAL ESTACIONES'!K20 -> -29285 | L20: ='TOTAL ESTACIONES'!L20 -> -144224 | M20: ='TOTAL ESTACIONES'!M20 -> -252600 | N20: ='TOTAL ESTACIONES'!N20 -> -542629 | O20: ='TOTAL ESTACIONES'!O20 -> -772168 | P20: ='TOTAL ESTACIONES'!P20 -> -628594 | Q20: ='TOTAL ESTACIONES'!Q20 -> -417439 | ... W20: ='TOTAL ESTACIONES'!W20 -> -0.0042605064 | Y20: ='TOTAL ESTACIONES'!Y20 -> 0 | Z20: ='TOTAL ESTACIONES'!Z20 -> 0 | AA20: ='TOTAL ESTACIONES'!AA20 -> 0 | AB20: ='TOTAL ESTACIONES'!AB20 -> 0 | AC20: ='TOTAL ESTACIONES'!AC20 -> 0 | AD20: ='TOTAL ESTACIONES'!AD20 -> 0 | AE20: ='TOTAL ESTACIONES'!AE20 -> 0 | AF20: ='TOTAL ESTACIONES'!AF20 -> 0 | ... AM20: ='TOTAL ESTACIONES'!AM20 -> -1 | AS20: 0
A21: B - COSTO DE VENTA | C21: ADITIVO PARA GASOLINA TSUPER (PREMIUM) | I21: SOBRANTE PREMIUM | J21: ='TOTAL ESTACIONES'!J21 -> -11558 | K21: ='TOTAL ESTACIONES'!K21 -> -10191 | L21: ='TOTAL ESTACIONES'!L21 -> -23886 | M21: ='TOTAL ESTACIONES'!M21 -> -25404 | N21: ='TOTAL ESTACIONES'!N21 -> -70527 | O21: ='TOTAL ESTACIONES'!O21 -> -88473 | P21: ='TOTAL ESTACIONES'!P21 -> -75995 | Q21: ='TOTAL ESTACIONES'!Q21 -> -29922 | ... W21: ='TOTAL ESTACIONES'!W21 -> -0.00045949296 | Y21: ='TOTAL ESTACIONES'!Y21 -> 0 | Z21: ='TOTAL ESTACIONES'!Z21 -> 0 | AA21: ='TOTAL ESTACIONES'!AA21 -> 0 | AB21: ='TOTAL ESTACIONES'!AB21 -> 0 | AC21: ='TOTAL ESTACIONES'!AC21 -> 0 | AD21: ='TOTAL ESTACIONES'!AD21 -> 0 | AE21: ='TOTAL ESTACIONES'!AE21 -> 0 | AF21: ='TOTAL ESTACIONES'!AF21 -> 0 | ... AM21: ='TOTAL ESTACIONES'!AM21 -> -1 | AS21: 0
A22: B - COSTO DE VENTA | C22: FLETE MAGNA | I22: SOBRANTE DIESEL | J22: ='TOTAL ESTACIONES'!J22 -> -59339 | K22: ='TOTAL ESTACIONES'!K22 -> -93897 | L22: ='TOTAL ESTACIONES'!L22 -> -118699 | M22: ='TOTAL ESTACIONES'!M22 -> -121515 | N22: ='TOTAL ESTACIONES'!N22 -> -185372 | O22: ='TOTAL ESTACIONES'!O22 -> -209250 | P22: ='TOTAL ESTACIONES'!P22 -> -242095 | Q22: ='TOTAL ESTACIONES'!Q22 -> -81498 | ... W22: ='TOTAL ESTACIONES'!W22 -> -0.0016915767 | Y22: ='TOTAL ESTACIONES'!Y22 -> 0 | Z22: ='TOTAL ESTACIONES'!Z22 -> 0 | AA22: ='TOTAL ESTACIONES'!AA22 -> 0 | AB22: ='TOTAL ESTACIONES'!AB22 -> 0 | AC22: ='TOTAL ESTACIONES'!AC22 -> 0 | AD22: ='TOTAL ESTACIONES'!AD22 -> 0 | AE22: ='TOTAL ESTACIONES'!AE22 -> 0 | AF22: ='TOTAL ESTACIONES'!AF22 -> 0 | ... AM22: ='TOTAL ESTACIONES'!AM22 -> -1 | AS22: 0
A23: B - COSTO DE VENTA | C23: FLETE PREMIUM | I23: ADITIVO TOTAL POWER GASOLINA REG | J23: ='TOTAL ESTACIONES'!J23 -> 110309 | K23: ='TOTAL ESTACIONES'!K23 -> 183033 | L23: ='TOTAL ESTACIONES'!L23 -> 118902 | M23: ='TOTAL ESTACIONES'!M23 -> 491588 | N23: ='TOTAL ESTACIONES'!N23 -> -240501 | O23: ='TOTAL ESTACIONES'!O23 -> 129867 | P23: ='TOTAL ESTACIONES'!P23 -> 132184 | Q23: ='TOTAL ESTACIONES'!Q23 -> 108896 | ... W23: ='TOTAL ESTACIONES'!W23 -> 0.0014205013 | Y23: ='TOTAL ESTACIONES'!Y23 -> 0 | Z23: ='TOTAL ESTACIONES'!Z23 -> 0 | AA23: ='TOTAL ESTACIONES'!AA23 -> 0 | AB23: ='TOTAL ESTACIONES'!AB23 -> 0 | AC23: ='TOTAL ESTACIONES'!AC23 -> 0 | AD23: ='TOTAL ESTACIONES'!AD23 -> 0 | AE23: ='TOTAL ESTACIONES'!AE23 -> 0 | AF23: ='TOTAL ESTACIONES'!AF23 -> 0 | ... AM23: ='TOTAL ESTACIONES'!AM23 -> -1 | AS23: 0
A24: B - COSTO DE VENTA | C24: FLETE DIESEL | I24: ADITIVO TOTAL POWER GASOLINA PREM | J24: ='TOTAL ESTACIONES'!J24 -> 10018 | K24: ='TOTAL ESTACIONES'!K24 -> 20216 | L24: ='TOTAL ESTACIONES'!L24 -> 12073 | M24: ='TOTAL ESTACIONES'!M24 -> 11105 | N24: ='TOTAL ESTACIONES'!N24 -> 12892 | O24: ='TOTAL ESTACIONES'!O24 -> 14241 | P24: ='TOTAL ESTACIONES'!P24 -> 14417 | Q24: ='TOTAL ESTACIONES'!Q24 -> 3951 | ... W24: ='TOTAL ESTACIONES'!W24 -> 0.00014053345 | Y24: ='TOTAL ESTACIONES'!Y24 -> 0 | Z24: ='TOTAL ESTACIONES'!Z24 -> 0 | AA24: ='TOTAL ESTACIONES'!AA24 -> 0 | AB24: ='TOTAL ESTACIONES'!AB24 -> 0 | AC24: ='TOTAL ESTACIONES'!AC24 -> 0 | AD24: ='TOTAL ESTACIONES'!AD24 -> 0 | AE24: ='TOTAL ESTACIONES'!AE24 -> 0 | AF24: ='TOTAL ESTACIONES'!AF24 -> 0 | ... AM24: ='TOTAL ESTACIONES'!AM24 -> -1 | AS24: 0
A25: B - COSTO DE VENTA | C25: Estimulo IEPS Magna | D25: INGRESOS FORANEOS MAGNA | I25: FLETE GASOLINA REGULAR | J25: ='TOTAL ESTACIONES'!J25 -> 0 | K25: ='TOTAL ESTACIONES'!K25 -> 0 | L25: ='TOTAL ESTACIONES'!L25 -> 0 | M25: ='TOTAL ESTACIONES'!M25 -> 0 | N25: ='TOTAL ESTACIONES'!N25 -> 1841 | O25: ='TOTAL ESTACIONES'!O25 -> 0 | P25: ='TOTAL ESTACIONES'!P25 -> 0 | Q25: ='TOTAL ESTACIONES'!Q25 -> 916 | ... W25: ='TOTAL ESTACIONES'!W25 -> 3.0764462e-06 | Y25: ='TOTAL ESTACIONES'!Y25 -> 0 | Z25: ='TOTAL ESTACIONES'!Z25 -> 0 | AA25: ='TOTAL ESTACIONES'!AA25 -> 0 | AB25: ='TOTAL ESTACIONES'!AB25 -> 0 | AC25: ='TOTAL ESTACIONES'!AC25 -> 0 | AD25: ='TOTAL ESTACIONES'!AD25 -> 0 | AE25: ='TOTAL ESTACIONES'!AE25 -> 0 | AF25: ='TOTAL ESTACIONES'!AF25 -> 0 | ... AM25: ='TOTAL ESTACIONES'!AM25 -> -1 | AS25: 0
I26: FLETE GASOLINA PREMIUM | J26: ='TOTAL ESTACIONES'!J26 -> 0 | K26: ='TOTAL ESTACIONES'!K26 -> 0 | L26: ='TOTAL ESTACIONES'!L26 -> 0 | M26: ='TOTAL ESTACIONES'!M26 -> 0 | N26: ='TOTAL ESTACIONES'!N26 -> 0 | O26: ='TOTAL ESTACIONES'!O26 -> 0 | P26: ='TOTAL ESTACIONES'!P26 -> 0 | Q26: ='TOTAL ESTACIONES'!Q26 -> 0 | ... W26: ='TOTAL ESTACIONES'!W26 -> 0 | Y26: ='TOTAL ESTACIONES'!Y26 -> 0 | Z26: ='TOTAL ESTACIONES'!Z26 -> 0 | AA26: ='TOTAL ESTACIONES'!AA26 -> 0 | AB26: ='TOTAL ESTACIONES'!AB26 -> 0 | AC26: ='TOTAL ESTACIONES'!AC26 -> 0 | AD26: ='TOTAL ESTACIONES'!AD26 -> 0 | AE26: ='TOTAL ESTACIONES'!AE26 -> 0 | AF26: ='TOTAL ESTACIONES'!AF26 -> 0 | ... AM26: ='TOTAL ESTACIONES'!AM26 -> 0 | AS26: 0
I27: FLETE DIESEL | J27: ='TOTAL ESTACIONES'!J27 -> 0 | K27: ='TOTAL ESTACIONES'!K27 -> 0 | L27: ='TOTAL ESTACIONES'!L27 -> 0 | M27: ='TOTAL ESTACIONES'!M27 -> 0 | N27: ='TOTAL ESTACIONES'!N27 -> 0 | O27: ='TOTAL ESTACIONES'!O27 -> 0 | P27: ='TOTAL ESTACIONES'!P27 -> 0 | Q27: ='TOTAL ESTACIONES'!Q27 -> 0 | ... W27: ='TOTAL ESTACIONES'!W27 -> 0 | Y27: ='TOTAL ESTACIONES'!Y27 -> 0 | Z27: ='TOTAL ESTACIONES'!Z27 -> 0 | AA27: ='TOTAL ESTACIONES'!AA27 -> 0 | AB27: ='TOTAL ESTACIONES'!AB27 -> 0 | AC27: ='TOTAL ESTACIONES'!AC27 -> 0 | AD27: ='TOTAL ESTACIONES'!AD27 -> 0 | AE27: ='TOTAL ESTACIONES'!AE27 -> 0 | AF27: ='TOTAL ESTACIONES'!AF27 -> 0 | ... AM27: ='TOTAL ESTACIONES'!AM27 -> 0 | AS27: 0
I28: ESTIMULO REGULAR | J28: ='TOTAL ESTACIONES'!J28 -> -9895352 | K28: ='TOTAL ESTACIONES'!K28 -> -9741490 | L28: ='TOTAL ESTACIONES'!L28 -> -10698216 | M28: ='TOTAL ESTACIONES'!M28 -> -10091896 | N28: ='TOTAL ESTACIONES'!N28 -> -11479619 | O28: ='TOTAL ESTACIONES'!O28 -> -11206376 | P28: ='TOTAL ESTACIONES'!P28 -> -11021279 | Q28: ='TOTAL ESTACIONES'!Q28 -> -10539195 | ... W28: ='TOTAL ESTACIONES'!W28 -> -0.11685177 | Y28: ='TOTAL ESTACIONES'!Y28 -> 0 | Z28: ='TOTAL ESTACIONES'!Z28 -> 0 | AA28: ='TOTAL ESTACIONES'!AA28 -> 0 | AB28: ='TOTAL ESTACIONES'!AB28 -> 0 | AC28: ='TOTAL ESTACIONES'!AC28 -> 0 | AD28: ='TOTAL ESTACIONES'!AD28 -> 0 | AE28: ='TOTAL ESTACIONES'!AE28 -> 0 | AF28: ='TOTAL ESTACIONES'!AF28 -> 0 | ... AM28: ='TOTAL ESTACIONES'!AM28 -> -1 | AS28: 0
I29: ESTIMULO PREMIUM | J29: ='TOTAL ESTACIONES'!J29 -> -775258 | K29: ='TOTAL ESTACIONES'!K29 -> -798009 | L29: ='TOTAL ESTACIONES'!L29 -> -878327 | M29: ='TOTAL ESTACIONES'!M29 -> -837300 | N29: ='TOTAL ESTACIONES'!N29 -> -954984 | O29: ='TOTAL ESTACIONES'!O29 -> -999309 | P29: ='TOTAL ESTACIONES'!P29 -> -956207 | Q29: ='TOTAL ESTACIONES'!Q29 -> -675074 | ... W29: ='TOTAL ESTACIONES'!W29 -> -0.0095737957 | Y29: ='TOTAL ESTACIONES'!Y29 -> 0 | Z29: ='TOTAL ESTACIONES'!Z29 -> 0 | AA29: ='TOTAL ESTACIONES'!AA29 -> 0 | AB29: ='TOTAL ESTACIONES'!AB29 -> 0 | AC29: ='TOTAL ESTACIONES'!AC29 -> 0 | AD29: ='TOTAL ESTACIONES'!AD29 -> 0 | AE29: ='TOTAL ESTACIONES'!AE29 -> 0 | AF29: ='TOTAL ESTACIONES'!AF29 -> 0 | ... AM29: ='TOTAL ESTACIONES'!AM29 -> -1 | AS29: 0
I30: COSTO ACEITES Y LUBRICANTES | J30: ='TOTAL ESTACIONES'!J30 -> 53854 | K30: ='TOTAL ESTACIONES'!K30 -> 41012 | L30: ='TOTAL ESTACIONES'!L30 -> 46457 | M30: ='TOTAL ESTACIONES'!M30 -> 48504 | N30: ='TOTAL ESTACIONES'!N30 -> 50623 | O30: ='TOTAL ESTACIONES'!O30 -> 49511 | P30: ='TOTAL ESTACIONES'!P30 -> 44553 | Q30: ='TOTAL ESTACIONES'!Q30 -> 45156 | ... W30: ='TOTAL ESTACIONES'!W30 -> 0.00066913607 | Y30: ='TOTAL ESTACIONES'!Y30 -> 63444 | Z30: ='TOTAL ESTACIONES'!Z30 -> 61200 | AA30: ='TOTAL ESTACIONES'!AA30 -> 81141 | AB30: ='TOTAL ESTACIONES'!AB30 -> 59262 | AC30: ='TOTAL ESTACIONES'!AC30 -> 64413 | AD30: ='TOTAL ESTACIONES'!AD30 -> 60435 | AE30: ='TOTAL ESTACIONES'!AE30 -> 60945 | AF30: ='TOTAL ESTACIONES'!AF30 -> 58293 | ... AM30: ='TOTAL ESTACIONES'!AM30 -> 0.27496687 | AS30: 483735
I31: BONIFICACION COMPRA DE COMBUSTIBLE MAGNA | J31: ='TOTAL ESTACIONES'!J31 -> 0 | K31: ='TOTAL ESTACIONES'!K31 -> 0 | L31: ='TOTAL ESTACIONES'!L31 -> 0 | M31: ='TOTAL ESTACIONES'!M31 -> 0 | N31: ='TOTAL ESTACIONES'!N31 -> 0 | O31: ='TOTAL ESTACIONES'!O31 -> 0 | P31: ='TOTAL ESTACIONES'!P31 -> 0 | Q31: ='TOTAL ESTACIONES'!Q31 -> 0 | ... W31: ='TOTAL ESTACIONES'!W31 -> 0 | Y31: ='TOTAL ESTACIONES'!Y31 -> 0 | Z31: ='TOTAL ESTACIONES'!Z31 -> 0 | AA31: ='TOTAL ESTACIONES'!AA31 -> 0 | AB31: ='TOTAL ESTACIONES'!AB31 -> 0 | AC31: ='TOTAL ESTACIONES'!AC31 -> 0 | AD31: ='TOTAL ESTACIONES'!AD31 -> 0 | AE31: ='TOTAL ESTACIONES'!AE31 -> 0 | AF31: ='TOTAL ESTACIONES'!AF31 -> 0 | ... AM31: ='TOTAL ESTACIONES'!AM31 -> 0 | AS31: 0
I32: BONIFICACION COMPRA DE COMBUSTIBLE PREMIUM | J32: ='TOTAL ESTACIONES'!J32 -> 0 | K32: ='TOTAL ESTACIONES'!K32 -> 0 | L32: ='TOTAL ESTACIONES'!L32 -> 0 | M32: ='TOTAL ESTACIONES'!M32 -> 0 | N32: ='TOTAL ESTACIONES'!N32 -> 0 | O32: ='TOTAL ESTACIONES'!O32 -> 0 | P32: ='TOTAL ESTACIONES'!P32 -> 0 | Q32: ='TOTAL ESTACIONES'!Q32 -> 0 | ... W32: ='TOTAL ESTACIONES'!W32 -> 0 | Y32: ='TOTAL ESTACIONES'!Y32 -> 0 | Z32: ='TOTAL ESTACIONES'!Z32 -> 0 | AA32: ='TOTAL ESTACIONES'!AA32 -> 0 | AB32: ='TOTAL ESTACIONES'!AB32 -> 0 | AC32: ='TOTAL ESTACIONES'!AC32 -> 0 | AD32: ='TOTAL ESTACIONES'!AD32 -> 0 | AE32: ='TOTAL ESTACIONES'!AE32 -> 0 | AF32: ='TOTAL ESTACIONES'!AF32 -> 0 | ... AM32: ='TOTAL ESTACIONES'!AM32 -> 0 | AS32: 0
I33: BONIFICACION COMPRA DE COMBUSTIBLE DIESEL | J33: ='TOTAL ESTACIONES'!J33 -> 0 | K33: ='TOTAL ESTACIONES'!K33 -> 0 | L33: ='TOTAL ESTACIONES'!L33 -> 0 | M33: ='TOTAL ESTACIONES'!M33 -> 0 | N33: ='TOTAL ESTACIONES'!N33 -> 0 | O33: ='TOTAL ESTACIONES'!O33 -> 0 | P33: ='TOTAL ESTACIONES'!P33 -> 0 | Q33: ='TOTAL ESTACIONES'!Q33 -> 0 | ... W33: ='TOTAL ESTACIONES'!W33 -> 0 | Y33: ='TOTAL ESTACIONES'!Y33 -> 0 | Z33: ='TOTAL ESTACIONES'!Z33 -> 0 | AA33: ='TOTAL ESTACIONES'!AA33 -> 0 | AB33: ='TOTAL ESTACIONES'!AB33 -> 0 | AC33: ='TOTAL ESTACIONES'!AC33 -> 0 | AD33: ='TOTAL ESTACIONES'!AD33 -> 0 | AE33: ='TOTAL ESTACIONES'!AE33 -> 0 | AF33: ='TOTAL ESTACIONES'!AF33 -> 0 | ... AM33: ='TOTAL ESTACIONES'!AM33 -> 0 | AS33: 0
I34: MARGEN DE UTILIDAD | J34: ='TOTAL ESTACIONES'!J34 -> 9669373 | K34: ='TOTAL ESTACIONES'!K34 -> 10402424 | L34: ='TOTAL ESTACIONES'!L34 -> 10631948 | M34: ='TOTAL ESTACIONES'!M34 -> 10175079 | N34: ='TOTAL ESTACIONES'!N34 -> 12471677 | O34: ='TOTAL ESTACIONES'!O34 -> 10899375 | P34: ='TOTAL ESTACIONES'!P34 -> 10241103 | Q34: ='TOTAL ESTACIONES'!Q34 -> 9298189 | ... W34: ='TOTAL ESTACIONES'!W34 -> 0.13786633 | Y34: ='TOTAL ESTACIONES'!Y34 -> 9567238.4 | Z34: ='TOTAL ESTACIONES'!Z34 -> 9309837 | AA34: ='TOTAL ESTACIONES'!AA34 -> 10644012 | AB34: ='TOTAL ESTACIONES'!AB34 -> 9460298.8 | AC34: ='TOTAL ESTACIONES'!AC34 -> 11557010 | AD34: ='TOTAL ESTACIONES'!AD34 -> 10797115 | AE34: ='TOTAL ESTACIONES'!AE34 -> 10656189 | AF34: ='TOTAL ESTACIONES'!AF34 -> 10997032 | ... AM34: ='TOTAL ESTACIONES'!AM34 -> 0.0060647108 | AS34: 1.2425058e+08
I35: *Regular | J35: ='TOTAL ESTACIONES'!J35 -> 7104474 | K35: ='TOTAL ESTACIONES'!K35 -> 8071504 | L35: ='TOTAL ESTACIONES'!L35 -> 7943183 | M35: ='TOTAL ESTACIONES'!M35 -> 7764090 | N35: ='TOTAL ESTACIONES'!N35 -> 9629979 | O35: ='TOTAL ESTACIONES'!O35 -> 8207647 | P35: ='TOTAL ESTACIONES'!P35 -> 7712661 | Q35: ='TOTAL ESTACIONES'!Q35 -> 7297471 | ... W35: ='TOTAL ESTACIONES'!W35 -> 1.9712256 | Y35: ='TOTAL ESTACIONES'!Y35 -> 7411184.1 | Z35: ='TOTAL ESTACIONES'!Z35 -> 7234815.7 | AA35: ='TOTAL ESTACIONES'!AA35 -> 8316678.4 | AB35: ='TOTAL ESTACIONES'!AB35 -> 7358119.8 | AC35: ='TOTAL ESTACIONES'!AC35 -> 9150006.6 | AD35: ='TOTAL ESTACIONES'!AD35 -> 8356810.8 | AE35: ='TOTAL ESTACIONES'!AE35 -> 8232972 | AF35: ='TOTAL ESTACIONES'!AF35 -> 8715834.2 | ... AM35: ='TOTAL ESTACIONES'!AM35 -> 0.030632447 | AS35: 97100144
I36: *Premium | J36: ='TOTAL ESTACIONES'!J36 -> 813291 | K36: ='TOTAL ESTACIONES'!K36 -> 929738 | L36: ='TOTAL ESTACIONES'!L36 -> 1096634 | M36: ='TOTAL ESTACIONES'!M36 -> 1046417 | N36: ='TOTAL ESTACIONES'!N36 -> 1174426 | O36: ='TOTAL ESTACIONES'!O36 -> 1161608 | P36: ='TOTAL ESTACIONES'!P36 -> 984047 | Q36: ='TOTAL ESTACIONES'!Q36 -> 581170 | ... W36: ='TOTAL ESTACIONES'!W36 -> 0.23282274 | Y36: ='TOTAL ESTACIONES'!Y36 -> 701224.92 | Z36: ='TOTAL ESTACIONES'!Z36 -> 720412.16 | AA36: ='TOTAL ESTACIONES'!AA36 -> 819315.89 | AB36: ='TOTAL ESTACIONES'!AB36 -> 754550.32 | AC36: ='TOTAL ESTACIONES'!AC36 -> 871028.95 | AD36: ='TOTAL ESTACIONES'!AD36 -> 924681.99 | AE36: ='TOTAL ESTACIONES'!AE36 -> 851275.86 | AF36: ='TOTAL ESTACIONES'!AF36 -> 883838.65 | ... AM36: ='TOTAL ESTACIONES'!AM36 -> -0.12797841 | AS36: 9703588.7
I37: *Diesel | J37: ='TOTAL ESTACIONES'!J37 -> 1749533 | K37: ='TOTAL ESTACIONES'!K37 -> 1382005 | L37: ='TOTAL ESTACIONES'!L37 -> 1580760 | M37: ='TOTAL ESTACIONES'!M37 -> 1350095 | N37: ='TOTAL ESTACIONES'!N37 -> 1651925 | O37: ='TOTAL ESTACIONES'!O37 -> 1515260 | P37: ='TOTAL ESTACIONES'!P37 -> 1531075 | Q37: ='TOTAL ESTACIONES'!Q37 -> 1405577 | ... W37: ='TOTAL ESTACIONES'!W37 -> 0.37763035 | Y37: ='TOTAL ESTACIONES'!Y37 -> 1443633.3 | Z37: ='TOTAL ESTACIONES'!Z37 -> 1343809.2 | AA37: ='TOTAL ESTACIONES'!AA37 -> 1493698.9 | AB37: ='TOTAL ESTACIONES'!AB37 -> 1337170.6 | AC37: ='TOTAL ESTACIONES'!AC37 -> 1524607.2 | AD37: ='TOTAL ESTACIONES'!AD37 -> 1504957.2 | AE37: ='TOTAL ESTACIONES'!AE37 -> 1561186.1 | AF37: ='TOTAL ESTACIONES'!AF37 -> 1387071.7 | ... AM37: ='TOTAL ESTACIONES'!AM37 -> -0.038077453 | AS37: 17361480
I38: * Aceites y Lubricantes | J38: ='TOTAL ESTACIONES'!J38 -> 2073 | K38: ='TOTAL ESTACIONES'!K38 -> 19180 | L38: ='TOTAL ESTACIONES'!L38 -> 11371 | M38: ='TOTAL ESTACIONES'!M38 -> 14475 | N38: ='TOTAL ESTACIONES'!N38 -> 15343 | O38: ='TOTAL ESTACIONES'!O38 -> 14861 | P38: ='TOTAL ESTACIONES'!P38 -> 13316 | Q38: ='TOTAL ESTACIONES'!Q38 -> 13972 | ... W38: ='TOTAL ESTACIONES'!W38 -> 0.0033533919 | Y38: ='TOTAL ESTACIONES'!Y38 -> 11196 | Z38: ='TOTAL ESTACIONES'!Z38 -> 10800 | AA38: ='TOTAL ESTACIONES'!AA38 -> 14319 | AB38: ='TOTAL ESTACIONES'!AB38 -> 10458 | AC38: ='TOTAL ESTACIONES'!AC38 -> 11367 | AD38: ='TOTAL ESTACIONES'!AD38 -> 10665 | AE38: ='TOTAL ESTACIONES'!AE38 -> 10755 | AF38: ='TOTAL ESTACIONES'!AF38 -> 10287 | ... AM38: ='TOTAL ESTACIONES'!AM38 -> -0.15819972 | AS38: 85365
I39: Litros vendidos | J39: ='TOTAL ESTACIONES'!J39 -> 3700569 | K39: ='TOTAL ESTACIONES'!K39 -> 3632738 | L39: ='TOTAL ESTACIONES'!L39 -> 3988189 | M39: ='TOTAL ESTACIONES'!M39 -> 3743720 | N39: ='TOTAL ESTACIONES'!N39 -> 4276090 | O39: ='TOTAL ESTACIONES'!O39 -> 4259792 | P39: ='TOTAL ESTACIONES'!P39 -> 4201852 | Q39: ='TOTAL ESTACIONES'!Q39 -> 3874166 | ... W39: ='TOTAL ESTACIONES'!W39 -> 1 | Y39: ='TOTAL ESTACIONES'!Y39 -> 3821480 | Z39: ='TOTAL ESTACIONES'!Z39 -> 3748758 | AA39: ='TOTAL ESTACIONES'!AA39 -> 4114391 | AB39: ='TOTAL ESTACIONES'!AB39 -> 3870153 | AC39: ='TOTAL ESTACIONES'!AC39 -> 4414525 | AD39: ='TOTAL ESTACIONES'!AD39 -> 4346815 | AE39: ='TOTAL ESTACIONES'!AE39 -> 4282241 | AF39: ='TOTAL ESTACIONES'!AF39 -> 4339623 | ... AM39: ='TOTAL ESTACIONES'!AM39 -> 0.037304659 | AO39: =+AK39/12 -> 4131472.1 | AS39: 49577665
I40: Maxima | J40: ='TOTAL ESTACIONES'!J40 -> 2902809 | K40: ='TOTAL ESTACIONES'!K40 -> 2857785 | L40: ='TOTAL ESTACIONES'!L40 -> 3134970 | M40: ='TOTAL ESTACIONES'!M40 -> 2960554 | N40: ='TOTAL ESTACIONES'!N40 -> 3367706 | O40: ='TOTAL ESTACIONES'!O40 -> 3288023 | P40: ='TOTAL ESTACIONES'!P40 -> 3234223 | Q40: ='TOTAL ESTACIONES'!Q40 -> 3091988 | ... W40: ='TOTAL ESTACIONES'!W40 -> 0.78320418 | Y40: ='TOTAL ESTACIONES'!Y40 -> 2952663 | Z40: ='TOTAL ESTACIONES'!Z40 -> 2902741 | AA40: ='TOTAL ESTACIONES'!AA40 -> 3197079 | AB40: ='TOTAL ESTACIONES'!AB40 -> 3008559 | AC40: ='TOTAL ESTACIONES'!AC40 -> 3462421 | AD40: ='TOTAL ESTACIONES'!AD40 -> 3368996 | AE40: ='TOTAL ESTACIONES'!AE40 -> 3306021 | AF40: ='TOTAL ESTACIONES'!AF40 -> 3423794 | ... AM40: ='TOTAL ESTACIONES'!AM40 -> 0.032131935 | AS40: 38635804
I41: Super | J41: ='TOTAL ESTACIONES'!J41 -> 271069 | K41: ='TOTAL ESTACIONES'!K41 -> 279451 | L41: ='TOTAL ESTACIONES'!L41 -> 310795 | M41: ='TOTAL ESTACIONES'!M41 -> 292788 | N41: ='TOTAL ESTACIONES'!N41 -> 333910 | O41: ='TOTAL ESTACIONES'!O41 -> 349797 | P41: ='TOTAL ESTACIONES'!P41 -> 334339 | Q41: ='TOTAL ESTACIONES'!Q41 -> 236040 | ... W41: ='TOTAL ESTACIONES'!W41 -> 0.075174423 | Y41: ='TOTAL ESTACIONES'!Y41 -> 277164 | Z41: ='TOTAL ESTACIONES'!Z41 -> 283847 | AA41: ='TOTAL ESTACIONES'!AA41 -> 317230 | AB41: ='TOTAL ESTACIONES'!AB41 -> 298246 | AC41: ='TOTAL ESTACIONES'!AC41 -> 344135 | AD41: ='TOTAL ESTACIONES'!AD41 -> 360055 | AE41: ='TOTAL ESTACIONES'!AE41 -> 342401 | AF41: ='TOTAL ESTACIONES'!AF41 -> 347357 | ... AM41: ='TOTAL ESTACIONES'!AM41 -> 0.066682179 | AS41: 3832524
E42: ( menos ) | I42: Diesel | J42: ='TOTAL ESTACIONES'!J42 -> 526691 | K42: ='TOTAL ESTACIONES'!K42 -> 495501 | L42: ='TOTAL ESTACIONES'!L42 -> 542424 | M42: ='TOTAL ESTACIONES'!M42 -> 490379 | N42: ='TOTAL ESTACIONES'!N42 -> 574474 | O42: ='TOTAL ESTACIONES'!O42 -> 621973 | P42: ='TOTAL ESTACIONES'!P42 -> 633290 | Q42: ='TOTAL ESTACIONES'!Q42 -> 546137 | ... W42: ='TOTAL ESTACIONES'!W42 -> 0.14162137 | Y42: ='TOTAL ESTACIONES'!Y42 -> 591653 | Z42: ='TOTAL ESTACIONES'!Z42 -> 562170 | AA42: ='TOTAL ESTACIONES'!AA42 -> 600082 | AB42: ='TOTAL ESTACIONES'!AB42 -> 563348 | AC42: ='TOTAL ESTACIONES'!AC42 -> 607969 | AD42: ='TOTAL ESTACIONES'!AD42 -> 617764 | AE42: ='TOTAL ESTACIONES'!AE42 -> 633819 | AF42: ='TOTAL ESTACIONES'!AF42 -> 568472 | ... AM42: ='TOTAL ESTACIONES'!AM42 -> 0.050317407 | AS42: 7109337
I43: Margen de utilidad por combustible | J43: ='TOTAL ESTACIONES'!J43 -> 2.6129422 | K43: ='TOTAL ESTACIONES'!K43 -> 2.8635217 | L43: ='TOTAL ESTACIONES'!L43 -> 2.6658586 | M43: ='TOTAL ESTACIONES'!M43 -> 2.717906 | N43: ='TOTAL ESTACIONES'!N43 -> 2.9166077 | O43: ='TOTAL ESTACIONES'!O43 -> 2.5586637 | P43: ='TOTAL ESTACIONES'!P43 -> 2.4372831 | Q43: ='TOTAL ESTACIONES'!Q43 -> 2.4000492 | ... W43: ='TOTAL ESTACIONES'!W43 -> 5.4086165e-08 | Y43: ='TOTAL ESTACIONES'!Y43 -> 2.5035427 | Z43: ='TOTAL ESTACIONES'!Z43 -> 2.4834457 | AA43: ='TOTAL ESTACIONES'!AA43 -> 2.5870201 | AB43: ='TOTAL ESTACIONES'!AB43 -> 2.444425 | AC43: ='TOTAL ESTACIONES'!AC43 -> 2.6179509 | AD43: ='TOTAL ESTACIONES'!AD43 -> 2.4839141 | AE43: ='TOTAL ESTACIONES'!AE43 -> 2.4884608 | AF43: ='TOTAL ESTACIONES'!AF43 -> 2.5340984 | ... AM43: ='TOTAL ESTACIONES'!AM43 -> -0.030116464 | AS43: 2.5061805
A44: E - GASTOS DE OPERACIÓN | B44: estaciones | I44: Maxima | J44: ='TOTAL ESTACIONES'!J44 -> 2.447448 | K44: ='TOTAL ESTACIONES'!K44 -> 2.8141449 | L44: ='TOTAL ESTACIONES'!L44 -> 2.48773 | M44: ='TOTAL ESTACIONES'!M44 -> 2.5371907 | N44: ='TOTAL ESTACIONES'!N44 -> 2.6983801 | O44: ='TOTAL ESTACIONES'!O44 -> 2.2613823 | P44: ='TOTAL ESTACIONES'!P44 -> 2.1903459 | Q44: ='TOTAL ESTACIONES'!Q44 -> 2.2251157 | ... W44: ='TOTAL ESTACIONES'!W44 -> 5.2660088e-08 | Y44: ='TOTAL ESTACIONES'!Y44 -> 2.51 | Z44: ='TOTAL ESTACIONES'!Z44 -> 2.4924083 | AA44: ='TOTAL ESTACIONES'!AA44 -> 2.6013365 | AB44: ='TOTAL ESTACIONES'!AB44 -> 2.4457289 | AC44: ='TOTAL ESTACIONES'!AC44 -> 2.6426615 | AD44: ='TOTAL ESTACIONES'!AD44 -> 2.4805048 | AE44: ='TOTAL ESTACIONES'!AE44 -> 2.4902963 | AF44: ='TOTAL ESTACIONES'!AF44 -> 2.5456655 | ... AM44: ='TOTAL ESTACIONES'!AM44 -> -0.0014528058 | AS44: 2.5132166
A45: E - GASTOS DE OPERACIÓN | B45: estaciones | C45: Servicios Administrativos | I45: Super | J45: ='TOTAL ESTACIONES'!J45 -> 2.9576824 | K45: ='TOTAL ESTACIONES'!K45 -> 3.2905375 | L45: ='TOTAL ESTACIONES'!L45 -> 3.4516257 | M45: ='TOTAL ESTACIONES'!M45 -> 3.4872058 | N45: ='TOTAL ESTACIONES'!N45 -> 3.3059807 | O45: ='TOTAL ESTACIONES'!O45 -> 3.0678822 | P45: ='TOTAL ESTACIONES'!P45 -> 2.7159649 | Q45: ='TOTAL ESTACIONES'!Q45 -> 2.3354008 | ... W45: ='TOTAL ESTACIONES'!W45 -> 6.4800082e-08 | Y45: ='TOTAL ESTACIONES'!Y45 -> 2.53 | Z45: ='TOTAL ESTACIONES'!Z45 -> 2.5380299 | AA45: ='TOTAL ESTACIONES'!AA45 -> 2.5827188 | AB45: ='TOTAL ESTACIONES'!AB45 -> 2.5299596 | AC45: ='TOTAL ESTACIONES'!AC45 -> 2.5310676 | AD45: ='TOTAL ESTACIONES'!AD45 -> 2.5681687 | AE45: ='TOTAL ESTACIONES'!AE45 -> 2.4861956 | AF45: ='TOTAL ESTACIONES'!AF45 -> 2.5444677 | ... AM45: ='TOTAL ESTACIONES'!AM45 -> -0.18249165 | AS45: 2.5319055
A46: E - GASTOS DE OPERACIÓN | B46: estaciones | I46: Diesel | J46: ='TOTAL ESTACIONES'!J46 -> 3.2090808 | K46: ='TOTAL ESTACIONES'!K46 -> 2.5996052 | L46: ='TOTAL ESTACIONES'!L46 -> 2.6954191 | M46: ='TOTAL ESTACIONES'!M46 -> 2.5053703 | N46: ='TOTAL ESTACIONES'!N46 -> 2.5528658 | O46: ='TOTAL ESTACIONES'!O46 -> 2.0997857 | P46: ='TOTAL ESTACIONES'!P46 -> 2.0353756 | Q46: ='TOTAL ESTACIONES'!Q46 -> 2.4244448 | ... W46: ='TOTAL ESTACIONES'!W46 -> 5.5790256e-08 | Y46: ='TOTAL ESTACIONES'!Y46 -> 2.44 | Z46: ='TOTAL ESTACIONES'!Z46 -> 2.3903965 | AA46: ='TOTAL ESTACIONES'!AA46 -> 2.4891581 | AB46: ='TOTAL ESTACIONES'!AB46 -> 2.3736138 | AC46: ='TOTAL ESTACIONES'!AC46 -> 2.5077055 | AD46: ='TOTAL ESTACIONES'!AD46 -> 2.4361362 | AE46: ='TOTAL ESTACIONES'!AE46 -> 2.4631419 | AF46: ='TOTAL ESTACIONES'!AF46 -> 2.44 | ... AM46: ='TOTAL ESTACIONES'!AM46 -> -0.08416014 | AS46: 2.4420673
A47: E - GASTOS DE OPERACIÓN | B47: estaciones | AO47: =+AK6/AK39 -> 19.427665
A48: E - GASTOS DE OPERACIÓN | B48: estaciones | I48: GASTO ESTACIONES
A49: E - GASTOS DE OPERACIÓN | B49: estaciones | C49: Costo Marketing
A50: E - GASTOS DE OPERACIÓN | B50: estaciones | I50: E - GASTOS DE OPERACIÓN | J50: ='TOTAL ESTACIONES'!J50 -> 2052258 | K50: ='TOTAL ESTACIONES'!K50 -> 1540749 | L50: ='TOTAL ESTACIONES'!L50 -> 1586455 | M50: ='TOTAL ESTACIONES'!M50 -> 1475793 | N50: ='TOTAL ESTACIONES'!N50 -> 1563436 | O50: ='TOTAL ESTACIONES'!O50 -> 1546044 | P50: ='TOTAL ESTACIONES'!P50 -> 1664258 | Q50: ='TOTAL ESTACIONES'!Q50 -> 1730204 | ... W50: ='TOTAL ESTACIONES'!W50 -> 0.022110505 | Y50: ='TOTAL ESTACIONES'!Y50 -> 1920544.6 | Z50: ='TOTAL ESTACIONES'!Z50 -> 1580031.9 | AA50: ='TOTAL ESTACIONES'!AA50 -> 2041213.3 | AB50: ='TOTAL ESTACIONES'!AB50 -> 1599133.9 | AC50: ='TOTAL ESTACIONES'!AC50 -> 1576904.9 | AD50: ='TOTAL ESTACIONES'!AD50 -> 1685312.9 | AE50: ='TOTAL ESTACIONES'!AE50 -> 1668523.6 | AF50: ='TOTAL ESTACIONES'!AF50 -> 1770034 | ... AM50: ='TOTAL ESTACIONES'!AM50 -> 0.060296589 | AS50: 21009391
A51: E - GASTOS DE OPERACIÓN | B51: estaciones | I51: Traslado de Valores | J51: ='TOTAL ESTACIONES'!J51 -> 260645 | K51: ='TOTAL ESTACIONES'!K51 -> 231021 | L51: ='TOTAL ESTACIONES'!L51 -> 337830 | M51: ='TOTAL ESTACIONES'!M51 -> 235718 | N51: ='TOTAL ESTACIONES'!N51 -> 275972 | O51: ='TOTAL ESTACIONES'!O51 -> 184532 | P51: ='TOTAL ESTACIONES'!P51 -> 231937 | Q51: ='TOTAL ESTACIONES'!Q51 -> 332077 | ... W51: ='TOTAL ESTACIONES'!W51 -> 0.0036168394 | Y51: ='TOTAL ESTACIONES'!Y51 -> 262450.43 | Z51: ='TOTAL ESTACIONES'!Z51 -> 252088.36 | AA51: ='TOTAL ESTACIONES'!AA51 -> 280138.02 | AB51: ='TOTAL ESTACIONES'!AB51 -> 269811.61 | AC51: ='TOTAL ESTACIONES'!AC51 -> 293266.45 | AD51: ='TOTAL ESTACIONES'!AD51 -> 288475.3 | AE51: ='TOTAL ESTACIONES'!AE51 -> 287748.21 | AF51: ='TOTAL ESTACIONES'!AF51 -> 292873.61 | ... AM51: ='TOTAL ESTACIONES'!AM51 -> 0.040772985 | AO51: =+AK51-V51 -> 132156.7 | AS51: 3373437.6
A52: E - GASTOS DE OPERACIÓN | B52: estaciones | I52: Servicios Administrativos | J52: ='TOTAL ESTACIONES'!J52 -> 426209 | K52: ='TOTAL ESTACIONES'!K52 -> 426209 | L52: ='TOTAL ESTACIONES'!L52 -> 426209 | M52: ='TOTAL ESTACIONES'!M52 -> 426209 | N52: ='TOTAL ESTACIONES'!N52 -> 426209 | O52: ='TOTAL ESTACIONES'!O52 -> 426209 | P52: ='TOTAL ESTACIONES'!P52 -> 426209 | Q52: ='TOTAL ESTACIONES'!Q52 -> 426209 | ... W52: ='TOTAL ESTACIONES'!W52 -> 0.0057748187 | Y52: ='TOTAL ESTACIONES'!Y52 -> 451038 | Z52: ='TOTAL ESTACIONES'!Z52 -> 451038 | AA52: ='TOTAL ESTACIONES'!AA52 -> 451038 | AB52: ='TOTAL ESTACIONES'!AB52 -> 451038 | AC52: ='TOTAL ESTACIONES'!AC52 -> 451038 | AD52: ='TOTAL ESTACIONES'!AD52 -> 451038 | AE52: ='TOTAL ESTACIONES'!AE52 -> 451038 | AF52: ='TOTAL ESTACIONES'!AF52 -> 451038 | ... AM52: ='TOTAL ESTACIONES'!AM52 -> 0.059494016 | AO52: =+AK52-V52 -> 307892.48 | AP52: =+V52*1.0375 -> 5369253.4 | AQ52: =+AK52-AP52 -> 113823.08 | AS52: 5483076.5
A53: E - GASTOS DE OPERACIÓN | B53: estaciones | I53: Asesoría en sistemas | J53: ='TOTAL ESTACIONES'!J53 -> 0 | K53: ='TOTAL ESTACIONES'!K53 -> 0 | L53: ='TOTAL ESTACIONES'!L53 -> 0 | M53: ='TOTAL ESTACIONES'!M53 -> 0 | N53: ='TOTAL ESTACIONES'!N53 -> 0 | O53: ='TOTAL ESTACIONES'!O53 -> 0 | P53: ='TOTAL ESTACIONES'!P53 -> 0 | Q53: ='TOTAL ESTACIONES'!Q53 -> 0 | ... W53: ='TOTAL ESTACIONES'!W53 -> 0 | Y53: ='TOTAL ESTACIONES'!Y53 -> 0 | Z53: ='TOTAL ESTACIONES'!Z53 -> 0 | AA53: ='TOTAL ESTACIONES'!AA53 -> 0 | AB53: ='TOTAL ESTACIONES'!AB53 -> 0 | AC53: ='TOTAL ESTACIONES'!AC53 -> 0 | AD53: ='TOTAL ESTACIONES'!AD53 -> 0 | AE53: ='TOTAL ESTACIONES'!AE53 -> 0 | AF53: ='TOTAL ESTACIONES'!AF53 -> 0 | ... AM53: ='TOTAL ESTACIONES'!AM53 -> 0 | AO53: =+AK53-V53 -> 0 | AS53: 0
I54: Otros Gastos | J54: ='TOTAL ESTACIONES'!J54 -> 0 | K54: ='TOTAL ESTACIONES'!K54 -> 0 | L54: ='TOTAL ESTACIONES'!L54 -> 0 | M54: ='TOTAL ESTACIONES'!M54 -> 0 | N54: ='TOTAL ESTACIONES'!N54 -> 0 | O54: ='TOTAL ESTACIONES'!O54 -> 0 | P54: ='TOTAL ESTACIONES'!P54 -> 1160 | Q54: ='TOTAL ESTACIONES'!Q54 -> 0 | ... W54: ='TOTAL ESTACIONES'!W54 -> 1.2944061e-06 | Y54: ='TOTAL ESTACIONES'!Y54 -> 0 | Z54: ='TOTAL ESTACIONES'!Z54 -> 0 | AA54: ='TOTAL ESTACIONES'!AA54 -> 0 | AB54: ='TOTAL ESTACIONES'!AB54 -> 0 | AC54: ='TOTAL ESTACIONES'!AC54 -> 0 | AD54: ='TOTAL ESTACIONES'!AD54 -> 0 | AE54: ='TOTAL ESTACIONES'!AE54 -> 0 | AF54: ='TOTAL ESTACIONES'!AF54 -> 0 | ... AM54: ='TOTAL ESTACIONES'!AM54 -> 6.4955517 | AO54: =+AK54-V54 -> 7534.84 | AS54: 8694.84
I55: Otros impuestos y derechos | J55: ='TOTAL ESTACIONES'!J55 -> 0 | K55: ='TOTAL ESTACIONES'!K55 -> 0 | L55: ='TOTAL ESTACIONES'!L55 -> 0 | M55: ='TOTAL ESTACIONES'!M55 -> 0 | N55: ='TOTAL ESTACIONES'!N55 -> 0 | O55: ='TOTAL ESTACIONES'!O55 -> 0 | P55: ='TOTAL ESTACIONES'!P55 -> 0 | Q55: ='TOTAL ESTACIONES'!Q55 -> 0 | ... W55: ='TOTAL ESTACIONES'!W55 -> 0 | Y55: ='TOTAL ESTACIONES'!Y55 -> 15505.798 | Z55: ='TOTAL ESTACIONES'!Z55 -> 0 | AA55: ='TOTAL ESTACIONES'!AA55 -> 358383.71 | AB55: ='TOTAL ESTACIONES'!AB55 -> 0 | AC55: ='TOTAL ESTACIONES'!AC55 -> 15505.798 | AD55: ='TOTAL ESTACIONES'!AD55 -> 0 | AE55: ='TOTAL ESTACIONES'!AE55 -> 0 | AF55: ='TOTAL ESTACIONES'!AF55 -> 0 | ... AM55: ='TOTAL ESTACIONES'!AM55 -> 0 | AO55: =+AK55-V55 -> 389395.3 | AP55: Pruebas de Integridad Mecanica | AS55: 389395.3
I56: Limpieza | J56: ='TOTAL ESTACIONES'!J56 -> 13379 | K56: ='TOTAL ESTACIONES'!K56 -> 22956 | L56: ='TOTAL ESTACIONES'!L56 -> 20639 | M56: ='TOTAL ESTACIONES'!M56 -> 20334 | N56: ='TOTAL ESTACIONES'!N56 -> 21736 | O56: ='TOTAL ESTACIONES'!O56 -> 22160 | P56: ='TOTAL ESTACIONES'!P56 -> 17121 | Q56: ='TOTAL ESTACIONES'!Q56 -> 19114 | ... W56: ='TOTAL ESTACIONES'!W56 -> 0.00029459612 | Y56: ='TOTAL ESTACIONES'!Y56 -> 22888.131 | Z56: ='TOTAL ESTACIONES'!Z56 -> 22888.131 | AA56: ='TOTAL ESTACIONES'!AA56 -> 22888.131 | AB56: ='TOTAL ESTACIONES'!AB56 -> 22888.131 | AC56: ='TOTAL ESTACIONES'!AC56 -> 22888.131 | AD56: ='TOTAL ESTACIONES'!AD56 -> 22888.131 | AE56: ='TOTAL ESTACIONES'!AE56 -> 22888.131 | AF56: ='TOTAL ESTACIONES'!AF56 -> 22888.131 | ... AM56: ='TOTAL ESTACIONES'!AM56 -> 0.04034435 | AO56: =+AK56-V56 -> 10651.167 | AS56: 274657.57
I57: Propaganda y publicidad | J57: ='TOTAL ESTACIONES'!J57 -> 27502 | K57: ='TOTAL ESTACIONES'!K57 -> 78424 | L57: ='TOTAL ESTACIONES'!L57 -> 57419 | M57: ='TOTAL ESTACIONES'!M57 -> 76267 | N57: ='TOTAL ESTACIONES'!N57 -> 123704 | O57: ='TOTAL ESTACIONES'!O57 -> 55712 | P57: ='TOTAL ESTACIONES'!P57 -> 176653 | Q57: ='TOTAL ESTACIONES'!Q57 -> 80915 | ... W57: ='TOTAL ESTACIONES'!W57 -> 0.00083731403 | Y57: ='TOTAL ESTACIONES'!Y57 -> 49063.74 | Z57: ='TOTAL ESTACIONES'!Z57 -> 10868.55 | AA57: ='TOTAL ESTACIONES'!AA57 -> 135204.76 | AB57: ='TOTAL ESTACIONES'!AB57 -> 56516.46 | AC57: ='TOTAL ESTACIONES'!AC57 -> 13042.26 | AD57: ='TOTAL ESTACIONES'!AD57 -> 65625.34 | AE57: ='TOTAL ESTACIONES'!AE57 -> 44322.982 | AF57: ='TOTAL ESTACIONES'!AF57 -> 59621.76 | ... AM57: ='TOTAL ESTACIONES'!AM57 -> 0.025153326 | AO57: =+AK57-V57 -> 18874.316 | AS57: 769244.92
I58: Capacitacion al personal | J58: ='TOTAL ESTACIONES'!J58 -> 0 | K58: ='TOTAL ESTACIONES'!K58 -> 0 | L58: ='TOTAL ESTACIONES'!L58 -> 0 | M58: ='TOTAL ESTACIONES'!M58 -> 0 | N58: ='TOTAL ESTACIONES'!N58 -> 0 | O58: ='TOTAL ESTACIONES'!O58 -> 0 | P58: ='TOTAL ESTACIONES'!P58 -> 0 | Q58: ='TOTAL ESTACIONES'!Q58 -> 0 | ... W58: ='TOTAL ESTACIONES'!W58 -> 1.0154393e-05 | Y58: ='TOTAL ESTACIONES'!Y58 -> 6033.9363 | Z58: ='TOTAL ESTACIONES'!Z58 -> 19308.596 | AA58: ='TOTAL ESTACIONES'!AA58 -> 3620.3618 | AB58: ='TOTAL ESTACIONES'!AB58 -> 0 | AC58: ='TOTAL ESTACIONES'!AC58 -> 0 | AD58: ='TOTAL ESTACIONES'!AD58 -> 0 | AE58: ='TOTAL ESTACIONES'!AE58 -> 0 | AF58: ='TOTAL ESTACIONES'!AF58 -> 0 | ... AM58: ='TOTAL ESTACIONES'!AM58 -> 2.1827356 | AO58: =+AK58-V58 -> 19862.894 | AS58: 28962.894
I59: Honorarios Administrativos P.F. | J59: ='TOTAL ESTACIONES'!J59 -> 0 | K59: ='TOTAL ESTACIONES'!K59 -> 0 | L59: ='TOTAL ESTACIONES'!L59 -> 0 | M59: ='TOTAL ESTACIONES'!M59 -> 0 | N59: ='TOTAL ESTACIONES'!N59 -> 0 | O59: ='TOTAL ESTACIONES'!O59 -> 0 | P59: ='TOTAL ESTACIONES'!P59 -> 0 | Q59: ='TOTAL ESTACIONES'!Q59 -> 0 | ... W59: ='TOTAL ESTACIONES'!W59 -> 0 | Y59: ='TOTAL ESTACIONES'!Y59 -> 0 | Z59: ='TOTAL ESTACIONES'!Z59 -> 0 | AA59: ='TOTAL ESTACIONES'!AA59 -> 0 | AB59: ='TOTAL ESTACIONES'!AB59 -> 0 | AC59: ='TOTAL ESTACIONES'!AC59 -> 0 | AD59: ='TOTAL ESTACIONES'!AD59 -> 0 | AE59: ='TOTAL ESTACIONES'!AE59 -> 0 | AF59: ='TOTAL ESTACIONES'!AF59 -> 0 | ... AM59: ='TOTAL ESTACIONES'!AM59 -> 0 | AO59: =+AK59-V59 -> 0 | AS59: 0
I60: Honorarios Administrativos P.M. | J60: ='TOTAL ESTACIONES'!J60 -> 35000 | K60: ='TOTAL ESTACIONES'!K60 -> 0 | L60: ='TOTAL ESTACIONES'!L60 -> 0 | M60: ='TOTAL ESTACIONES'!M60 -> 14250 | N60: ='TOTAL ESTACIONES'!N60 -> 0 | O60: ='TOTAL ESTACIONES'!O60 -> 104998 | P60: ='TOTAL ESTACIONES'!P60 -> 84960 | Q60: ='TOTAL ESTACIONES'!Q60 -> 132000 | ... W60: ='TOTAL ESTACIONES'!W60 -> 0.00068202703 | Y60: ='TOTAL ESTACIONES'!Y60 -> 36312.5 | Z60: ='TOTAL ESTACIONES'!Z60 -> 0 | AA60: ='TOTAL ESTACIONES'!AA60 -> 0 | AB60: ='TOTAL ESTACIONES'!AB60 -> 14784.375 | AC60: ='TOTAL ESTACIONES'!AC60 -> 0 | AD60: ='TOTAL ESTACIONES'!AD60 -> 108935.43 | AE60: ='TOTAL ESTACIONES'!AE60 -> 88146 | AF60: ='TOTAL ESTACIONES'!AF60 -> 136950 | ... AM60: ='TOTAL ESTACIONES'!AM60 -> 0.0375 | AO60: =+AK60-V60 -> 22920.3 | AP60: Listo | AS60: 634128.3
A61: E - GASTOS DE OPERACIÓN | B61: estaciones | I61: Honorarios Fiscales P.M. | J61: ='TOTAL ESTACIONES'!J61 -> 7125 | K61: ='TOTAL ESTACIONES'!K61 -> 7125 | L61: ='TOTAL ESTACIONES'!L61 -> 0 | M61: ='TOTAL ESTACIONES'!M61 -> 0 | N61: ='TOTAL ESTACIONES'!N61 -> 0 | O61: ='TOTAL ESTACIONES'!O61 -> 0 | P61: ='TOTAL ESTACIONES'!P61 -> 7125 | Q61: ='TOTAL ESTACIONES'!Q61 -> 0 | ... W61: ='TOTAL ESTACIONES'!W61 -> 2.3851664e-05 | Y61: ='TOTAL ESTACIONES'!Y61 -> 7392.1875 | Z61: ='TOTAL ESTACIONES'!Z61 -> 7392.1875 | AA61: ='TOTAL ESTACIONES'!AA61 -> 0 | AB61: ='TOTAL ESTACIONES'!AB61 -> 0 | AC61: ='TOTAL ESTACIONES'!AC61 -> 0 | AD61: ='TOTAL ESTACIONES'!AD61 -> 0 | AE61: ='TOTAL ESTACIONES'!AE61 -> 7392.1875 | AF61: ='TOTAL ESTACIONES'!AF61 -> 0 | ... AM61: ='TOTAL ESTACIONES'!AM61 -> 0.0375 | AO61: =+AK61-V61 -> 801.5625 | AP61: Listo | AS61: 22176.563
A62: E - GASTOS DE OPERACIÓN | B62: estaciones | I62: Asistencia técnica | J62: ='TOTAL ESTACIONES'!J62 -> 0 | K62: ='TOTAL ESTACIONES'!K62 -> 0 | L62: ='TOTAL ESTACIONES'!L62 -> 0 | M62: ='TOTAL ESTACIONES'!M62 -> 0 | N62: ='TOTAL ESTACIONES'!N62 -> 2390 | O62: ='TOTAL ESTACIONES'!O62 -> 0 | P62: ='TOTAL ESTACIONES'!P62 -> 0 | Q62: ='TOTAL ESTACIONES'!Q62 -> 0 | ... W62: ='TOTAL ESTACIONES'!W62 -> 2.6669229e-06 | Y62: ='TOTAL ESTACIONES'!Y62 -> 0 | Z62: ='TOTAL ESTACIONES'!Z62 -> 0 | AA62: ='TOTAL ESTACIONES'!AA62 -> 0 | AB62: ='TOTAL ESTACIONES'!AB62 -> 0 | AC62: ='TOTAL ESTACIONES'!AC62 -> 2479.625 | AD62: ='TOTAL ESTACIONES'!AD62 -> 0 | AE62: ='TOTAL ESTACIONES'!AE62 -> 0 | AF62: ='TOTAL ESTACIONES'!AF62 -> 0 | ... AM62: ='TOTAL ESTACIONES'!AM62 -> 0.0375 | AO62: =+AK62-V62 -> 89.625 | AP62: Listo | AS62: 2479.625
A63: E - GASTOS DE OPERACIÓN | B63: estaciones | I63: Gastos no deducibles (sin requisitos fiscales) | J63: ='TOTAL ESTACIONES'!J63 -> 4090 | K63: ='TOTAL ESTACIONES'!K63 -> -3499 | L63: ='TOTAL ESTACIONES'!L63 -> 2988 | M63: ='TOTAL ESTACIONES'!M63 -> 216 | N63: ='TOTAL ESTACIONES'!N63 -> 781 | O63: ='TOTAL ESTACIONES'!O63 -> 122 | P63: ='TOTAL ESTACIONES'!P63 -> 186 | Q63: ='TOTAL ESTACIONES'!Q63 -> 163 | ... W63: ='TOTAL ESTACIONES'!W63 -> 6.0613913e-06 | Y63: ='TOTAL ESTACIONES'!Y63 -> 0 | Z63: ='TOTAL ESTACIONES'!Z63 -> 0 | AA63: ='TOTAL ESTACIONES'!AA63 -> 0 | AB63: ='TOTAL ESTACIONES'!AB63 -> 0 | AC63: ='TOTAL ESTACIONES'!AC63 -> 0 | AD63: ='TOTAL ESTACIONES'!AD63 -> 0 | AE63: ='TOTAL ESTACIONES'!AE63 -> 0 | AF63: ='TOTAL ESTACIONES'!AF63 -> 0 | ... AM63: ='TOTAL ESTACIONES'!AM63 -> -1 | AO63: =+AK63-V63 -> -5432 | AS63: 0
A64: E - GASTOS DE OPERACIÓN | B64: estaciones | I64: Papelería y artículos de oficina | J64: ='TOTAL ESTACIONES'!J64 -> 4633 | K64: ='TOTAL ESTACIONES'!K64 -> 5751 | L64: ='TOTAL ESTACIONES'!L64 -> 7472 | M64: ='TOTAL ESTACIONES'!M64 -> 9066 | N64: ='TOTAL ESTACIONES'!N64 -> 6060 | O64: ='TOTAL ESTACIONES'!O64 -> 6638 | P64: ='TOTAL ESTACIONES'!P64 -> 1363 | Q64: ='TOTAL ESTACIONES'!Q64 -> 11196 | ... W64: ='TOTAL ESTACIONES'!W64 -> 9.428306e-05 | Y64: ='TOTAL ESTACIONES'!Y64 -> 8298.3967 | Z64: ='TOTAL ESTACIONES'!Z64 -> 8298.3967 | AA64: ='TOTAL ESTACIONES'!AA64 -> 8298.3967 | AB64: ='TOTAL ESTACIONES'!AB64 -> 8298.3967 | AC64: ='TOTAL ESTACIONES'!AC64 -> 8298.3967 | AD64: ='TOTAL ESTACIONES'!AD64 -> 8298.3967 | AE64: ='TOTAL ESTACIONES'!AE64 -> 8298.3967 | AF64: ='TOTAL ESTACIONES'!AF64 -> 8298.3967 | ... AM64: ='TOTAL ESTACIONES'!AM64 -> 0.17856714 | AO64: =+AK64-V64 -> 15087.686 | AS64: 99580.76
A65: E - GASTOS DE OPERACIÓN | B65: estaciones | I65: Faltantes | J65: ='TOTAL ESTACIONES'!J65 -> 0 | K65: ='TOTAL ESTACIONES'!K65 -> 0 | L65: ='TOTAL ESTACIONES'!L65 -> 0 | M65: ='TOTAL ESTACIONES'!M65 -> 0 | N65: ='TOTAL ESTACIONES'!N65 -> 0 | O65: ='TOTAL ESTACIONES'!O65 -> 0 | P65: ='TOTAL ESTACIONES'!P65 -> 0 | Q65: ='TOTAL ESTACIONES'!Q65 -> 0 | ... W65: ='TOTAL ESTACIONES'!W65 -> 0 | Y65: ='TOTAL ESTACIONES'!Y65 -> 0 | Z65: ='TOTAL ESTACIONES'!Z65 -> 0 | AA65: ='TOTAL ESTACIONES'!AA65 -> 0 | AB65: ='TOTAL ESTACIONES'!AB65 -> 0 | AC65: ='TOTAL ESTACIONES'!AC65 -> 0 | AD65: ='TOTAL ESTACIONES'!AD65 -> 0 | AE65: ='TOTAL ESTACIONES'!AE65 -> 0 | AF65: ='TOTAL ESTACIONES'!AF65 -> 0 | ... AM65: ='TOTAL ESTACIONES'!AM65 -> 0 | AO65: =+AK65-V65 -> 0 | AS65: 0
A66: E - GASTOS DE OPERACIÓN | B66: estaciones | I66: Licencias y Permisos | J66: ='TOTAL ESTACIONES'!J66 -> 8219 | K66: ='TOTAL ESTACIONES'!K66 -> 0 | L66: ='TOTAL ESTACIONES'!L66 -> 0 | M66: ='TOTAL ESTACIONES'!M66 -> 24988 | N66: ='TOTAL ESTACIONES'!N66 -> 0 | O66: ='TOTAL ESTACIONES'!O66 -> 0 | P66: ='TOTAL ESTACIONES'!P66 -> 0 | Q66: ='TOTAL ESTACIONES'!Q66 -> 7411 | ... W66: ='TOTAL ESTACIONES'!W66 -> 6.1132345e-05 | Y66: ='TOTAL ESTACIONES'!Y66 -> 0 | Z66: ='TOTAL ESTACIONES'!Z66 -> 15458.183 | AA66: ='TOTAL ESTACIONES'!AA66 -> 0 | AB66: ='TOTAL ESTACIONES'!AB66 -> 24925.208 | AC66: ='TOTAL ESTACIONES'!AC66 -> 0 | AD66: ='TOTAL ESTACIONES'!AD66 -> 0 | AE66: ='TOTAL ESTACIONES'!AE66 -> 15898.101 | AF66: ='TOTAL ESTACIONES'!AF66 -> 15288.427 | ... AM66: ='TOTAL ESTACIONES'!AM66 -> 0.30638755 | AO66: =+AK66-V66 -> 16785.319 | AS66: 71569.919
A67: E - GASTOS DE OPERACIÓN | B67: estaciones | I67: Licencias, Software, Antivirus | J67: ='TOTAL ESTACIONES'!J67 -> 23086 | K67: ='TOTAL ESTACIONES'!K67 -> 23086 | L67: ='TOTAL ESTACIONES'!L67 -> 23086 | M67: ='TOTAL ESTACIONES'!M67 -> 23086 | N67: ='TOTAL ESTACIONES'!N67 -> 23086 | O67: ='TOTAL ESTACIONES'!O67 -> 23086 | P67: ='TOTAL ESTACIONES'!P67 -> 23086 | Q67: ='TOTAL ESTACIONES'!Q67 -> 23086 | ... W67: ='TOTAL ESTACIONES'!W67 -> 0.00030913096 | Y67: ='TOTAL ESTACIONES'!Y67 -> 34598.217 | Z67: ='TOTAL ESTACIONES'!Z67 -> 34598.217 | AA67: ='TOTAL ESTACIONES'!AA67 -> 34598.217 | AB67: ='TOTAL ESTACIONES'!AB67 -> 34598.217 | AC67: ='TOTAL ESTACIONES'!AC67 -> 34598.217 | AD67: ='TOTAL ESTACIONES'!AD67 -> 34598.217 | AE67: ='TOTAL ESTACIONES'!AE67 -> 34598.217 | AF67: ='TOTAL ESTACIONES'!AF67 -> 34598.217 | ... AM67: ='TOTAL ESTACIONES'!AM67 -> 0.49866662 | AO67: =+AK67-V67 -> 138146.61 | AP67: Listo, confirmar con Hizel Vybro | AS67: 415178.61
A68: E - GASTOS DE OPERACIÓN | B68: estaciones | I68: Fletes Combustible | J68: ='TOTAL ESTACIONES'!J68 -> 0 | K68: ='TOTAL ESTACIONES'!K68 -> 0 | L68: ='TOTAL ESTACIONES'!L68 -> 0 | M68: ='TOTAL ESTACIONES'!M68 -> 0 | N68: ='TOTAL ESTACIONES'!N68 -> 0 | O68: ='TOTAL ESTACIONES'!O68 -> 0 | P68: ='TOTAL ESTACIONES'!P68 -> 0 | Q68: ='TOTAL ESTACIONES'!Q68 -> 0 | ... W68: ='TOTAL ESTACIONES'!W68 -> 0 | Y68: ='TOTAL ESTACIONES'!Y68 -> 0 | Z68: ='TOTAL ESTACIONES'!Z68 -> 0 | AA68: ='TOTAL ESTACIONES'!AA68 -> 0 | AB68: ='TOTAL ESTACIONES'!AB68 -> 0 | AC68: ='TOTAL ESTACIONES'!AC68 -> 0 | AD68: ='TOTAL ESTACIONES'!AD68 -> 0 | AE68: ='TOTAL ESTACIONES'!AE68 -> 0 | AF68: ='TOTAL ESTACIONES'!AF68 -> 0 | ... AM68: ='TOTAL ESTACIONES'!AM68 -> 0 | AO68: =+AK68-V68 -> 0 | AS68: 0
A69: E - GASTOS DE OPERACIÓN | B69: estaciones | I69: Viáticos y gastos de viaje | J69: ='TOTAL ESTACIONES'!J69 -> 0 | K69: ='TOTAL ESTACIONES'!K69 -> 0 | L69: ='TOTAL ESTACIONES'!L69 -> 0 | M69: ='TOTAL ESTACIONES'!M69 -> 0 | N69: ='TOTAL ESTACIONES'!N69 -> 662 | O69: ='TOTAL ESTACIONES'!O69 -> 0 | P69: ='TOTAL ESTACIONES'!P69 -> 0 | Q69: ='TOTAL ESTACIONES'!Q69 -> 0 | ... W69: ='TOTAL ESTACIONES'!W69 -> 9.4290789e-07 | Y69: ='TOTAL ESTACIONES'!Y69 -> 0 | Z69: ='TOTAL ESTACIONES'!Z69 -> 0 | AA69: ='TOTAL ESTACIONES'!AA69 -> 0 | AB69: ='TOTAL ESTACIONES'!AB69 -> 0 | AC69: ='TOTAL ESTACIONES'!AC69 -> 0 | AD69: ='TOTAL ESTACIONES'!AD69 -> 0 | AE69: ='TOTAL ESTACIONES'!AE69 -> 0 | AF69: ='TOTAL ESTACIONES'!AF69 -> 0 | ... AM69: ='TOTAL ESTACIONES'!AM69 -> -1 | AO69: =+AK69-V69 -> -845 | AS69: 0
A70: E - GASTOS DE OPERACIÓN | B70: estaciones | I70: Recoleccion de Basura | J70: ='TOTAL ESTACIONES'!J70 -> 15144 | K70: ='TOTAL ESTACIONES'!K70 -> 21968 | L70: ='TOTAL ESTACIONES'!L70 -> 12968 | M70: ='TOTAL ESTACIONES'!M70 -> 0 | N70: ='TOTAL ESTACIONES'!N70 -> 9800 | O70: ='TOTAL ESTACIONES'!O70 -> 17450 | P70: ='TOTAL ESTACIONES'!P70 -> 9800 | Q70: ='TOTAL ESTACIONES'!Q70 -> 9800 | ... W70: ='TOTAL ESTACIONES'!W70 -> 0.00015547379 | Y70: ='TOTAL ESTACIONES'!Y70 -> 10500 | Z70: ='TOTAL ESTACIONES'!Z70 -> 10500 | AA70: ='TOTAL ESTACIONES'!AA70 -> 10500 | AB70: ='TOTAL ESTACIONES'!AB70 -> 10500 | AC70: ='TOTAL ESTACIONES'!AC70 -> 10500 | AD70: ='TOTAL ESTACIONES'!AD70 -> 10500 | AE70: ='TOTAL ESTACIONES'!AE70 -> 10500 | AF70: ='TOTAL ESTACIONES'!AF70 -> 10500 | ... AM70: ='TOTAL ESTACIONES'!AM70 -> -0.095672145 | AO70: =+AK70-V70 -> -13330 | AS70: 126000
A71: E - GASTOS DE OPERACIÓN | B71: estaciones | I71: Honorarios de Consultoria | J71: ='TOTAL ESTACIONES'!J71 -> 0 | K71: ='TOTAL ESTACIONES'!K71 -> 0 | L71: ='TOTAL ESTACIONES'!L71 -> 0 | M71: ='TOTAL ESTACIONES'!M71 -> 0 | N71: ='TOTAL ESTACIONES'!N71 -> 0 | O71: ='TOTAL ESTACIONES'!O71 -> 0 | P71: ='TOTAL ESTACIONES'!P71 -> 0 | Q71: ='TOTAL ESTACIONES'!Q71 -> 0 | ... W71: ='TOTAL ESTACIONES'!W71 -> 0 | Y71: ='TOTAL ESTACIONES'!Y71 -> 0 | Z71: ='TOTAL ESTACIONES'!Z71 -> 0 | AA71: ='TOTAL ESTACIONES'!AA71 -> 0 | AB71: ='TOTAL ESTACIONES'!AB71 -> 0 | AC71: ='TOTAL ESTACIONES'!AC71 -> 0 | AD71: ='TOTAL ESTACIONES'!AD71 -> 0 | AE71: ='TOTAL ESTACIONES'!AE71 -> 0 | AF71: ='TOTAL ESTACIONES'!AF71 -> 0 | ... AM71: ='TOTAL ESTACIONES'!AM71 -> 0 | AO71: =+AK71-V71 -> 0 | AS71: 0
A72: E - GASTOS DE OPERACIÓN | B72: estaciones | I72: Agua para consumo | J72: ='TOTAL ESTACIONES'!J72 -> 6314 | K72: ='TOTAL ESTACIONES'!K72 -> 6314 | L72: ='TOTAL ESTACIONES'!L72 -> 6314 | M72: ='TOTAL ESTACIONES'!M72 -> 6314 | N72: ='TOTAL ESTACIONES'!N72 -> 6314 | O72: ='TOTAL ESTACIONES'!O72 -> 6314 | P72: ='TOTAL ESTACIONES'!P72 -> 6314 | Q72: ='TOTAL ESTACIONES'!Q72 -> 6314 | ... W72: ='TOTAL ESTACIONES'!W72 -> 8.4547035e-05 | Y72: ='TOTAL ESTACIONES'!Y72 -> 6550.775 | Z72: ='TOTAL ESTACIONES'!Z72 -> 6550.775 | AA72: ='TOTAL ESTACIONES'!AA72 -> 6550.775 | AB72: ='TOTAL ESTACIONES'!AB72 -> 6550.775 | AC72: ='TOTAL ESTACIONES'!AC72 -> 6550.775 | AD72: ='TOTAL ESTACIONES'!AD72 -> 6550.775 | AE72: ='TOTAL ESTACIONES'!AE72 -> 6550.775 | AF72: ='TOTAL ESTACIONES'!AF72 -> 6550.775 | ... AM72: ='TOTAL ESTACIONES'!AM72 -> 0.0375 | AO72: =+AK72-V72 -> 2841.3 | AS72: 78609.3
A73: E - GASTOS DE OPERACIÓN | B73: estaciones | I73: Fletes Mensajeria | J73: ='TOTAL ESTACIONES'!J73 -> 0 | K73: ='TOTAL ESTACIONES'!K73 -> 0 | L73: ='TOTAL ESTACIONES'!L73 -> 0 | M73: ='TOTAL ESTACIONES'!M73 -> 0 | N73: ='TOTAL ESTACIONES'!N73 -> 0 | O73: ='TOTAL ESTACIONES'!O73 -> 22400 | P73: ='TOTAL ESTACIONES'!P73 -> 0 | Q73: ='TOTAL ESTACIONES'!Q73 -> 0 | ... W73: ='TOTAL ESTACIONES'!W73 -> 2.4995428e-05 | Y73: ='TOTAL ESTACIONES'!Y73 -> 0 | Z73: ='TOTAL ESTACIONES'!Z73 -> 0 | AA73: ='TOTAL ESTACIONES'!AA73 -> 0 | AB73: ='TOTAL ESTACIONES'!AB73 -> 0 | AC73: ='TOTAL ESTACIONES'!AC73 -> 0 | AD73: ='TOTAL ESTACIONES'!AD73 -> 0 | AE73: ='TOTAL ESTACIONES'!AE73 -> 0 | AF73: ='TOTAL ESTACIONES'!AF73 -> 0 | ... AM73: ='TOTAL ESTACIONES'!AM73 -> -1 | AO73: =+AK73-V73 -> -22400 | AS73: 0
A74: E - GASTOS DE OPERACIÓN | B74: estaciones | I74: Honorarios Admvos P.F. | J74: ='TOTAL ESTACIONES'!J74 -> 9100 | K74: ='TOTAL ESTACIONES'!K74 -> 9100 | L74: ='TOTAL ESTACIONES'!L74 -> 25900 | M74: ='TOTAL ESTACIONES'!M74 -> 9100 | N74: ='TOTAL ESTACIONES'!N74 -> 9100 | O74: ='TOTAL ESTACIONES'!O74 -> 9100 | P74: ='TOTAL ESTACIONES'!P74 -> 9100 | Q74: ='TOTAL ESTACIONES'!Q74 -> 9100 | ... W74: ='TOTAL ESTACIONES'!W74 -> 0.00014059928 | Y74: ='TOTAL ESTACIONES'!Y74 -> 9441.25 | Z74: ='TOTAL ESTACIONES'!Z74 -> 9441.25 | AA74: ='TOTAL ESTACIONES'!AA74 -> 26871.25 | AB74: ='TOTAL ESTACIONES'!AB74 -> 9441.25 | AC74: ='TOTAL ESTACIONES'!AC74 -> 9441.25 | AD74: ='TOTAL ESTACIONES'!AD74 -> 9441.25 | AE74: ='TOTAL ESTACIONES'!AE74 -> 9441.25 | AF74: ='TOTAL ESTACIONES'!AF74 -> 9441.25 | ... AM74: ='TOTAL ESTACIONES'!AM74 -> 0.0375 | AO74: =+AK74-V74 -> 4725 | AP74: Listo | AS74: 130725
A75: E - GASTOS DE OPERACIÓN | B75: estaciones | I75: Consumos Propios Combustibles | J75: ='TOTAL ESTACIONES'!J75 -> 0 | K75: ='TOTAL ESTACIONES'!K75 -> 0 | L75: ='TOTAL ESTACIONES'!L75 -> 0 | M75: ='TOTAL ESTACIONES'!M75 -> 0 | N75: ='TOTAL ESTACIONES'!N75 -> 0 | O75: ='TOTAL ESTACIONES'!O75 -> 0 | P75: ='TOTAL ESTACIONES'!P75 -> 0 | Q75: ='TOTAL ESTACIONES'!Q75 -> 0 | ... W75: ='TOTAL ESTACIONES'!W75 -> 0 | Y75: ='TOTAL ESTACIONES'!Y75 -> 0 | Z75: ='TOTAL ESTACIONES'!Z75 -> 0 | AA75: ='TOTAL ESTACIONES'!AA75 -> 0 | AB75: ='TOTAL ESTACIONES'!AB75 -> 0 | AC75: ='TOTAL ESTACIONES'!AC75 -> 0 | AD75: ='TOTAL ESTACIONES'!AD75 -> 0 | AE75: ='TOTAL ESTACIONES'!AE75 -> 0 | AF75: ='TOTAL ESTACIONES'!AF75 -> 0 | ... AM75: ='TOTAL ESTACIONES'!AM75 -> 0 | AO75: =+AK75-V75 -> 0 | AS75: 0
A76: E - GASTOS DE OPERACIÓN | B76: estaciones | I76: Renta Equipo de Sistemas | J76: ='TOTAL ESTACIONES'!J76 -> 7032 | K76: ='TOTAL ESTACIONES'!K76 -> 6170 | L76: ='TOTAL ESTACIONES'!L76 -> 6043 | M76: ='TOTAL ESTACIONES'!M76 -> 6026 | N76: ='TOTAL ESTACIONES'!N76 -> 5614 | O76: ='TOTAL ESTACIONES'!O76 -> 6375 | P76: ='TOTAL ESTACIONES'!P76 -> 6423 | Q76: ='TOTAL ESTACIONES'!Q76 -> 6222 | ... W76: ='TOTAL ESTACIONES'!W76 -> 8.3806884e-05 | Y76: ='TOTAL ESTACIONES'!Y76 -> 6883.415 | Z76: ='TOTAL ESTACIONES'!Z76 -> 6883.415 | AA76: ='TOTAL ESTACIONES'!AA76 -> 6883.415 | AB76: ='TOTAL ESTACIONES'!AB76 -> 6883.415 | AC76: ='TOTAL ESTACIONES'!AC76 -> 6883.415 | AD76: ='TOTAL ESTACIONES'!AD76 -> 6883.415 | AE76: ='TOTAL ESTACIONES'!AE76 -> 6883.415 | AF76: ='TOTAL ESTACIONES'!AF76 -> 6883.415 | ... AM76: ='TOTAL ESTACIONES'!AM76 -> 0.09981101 | AO76: =+AK76-V76 -> 7496.2763 | AS76: 82600.98
I77: Timbrado Facturas | J77: ='TOTAL ESTACIONES'!J77 -> 3787 | K77: ='TOTAL ESTACIONES'!K77 -> 3608 | L77: ='TOTAL ESTACIONES'!L77 -> 3675 | M77: ='TOTAL ESTACIONES'!M77 -> 3984 | N77: ='TOTAL ESTACIONES'!N77 -> 3884 | O77: ='TOTAL ESTACIONES'!O77 -> 4109 | P77: ='TOTAL ESTACIONES'!P77 -> 3912 | Q77: ='TOTAL ESTACIONES'!Q77 -> 4420 | ... W77: ='TOTAL ESTACIONES'!W77 -> 5.1897956e-05 | Y77: ='TOTAL ESTACIONES'!Y77 -> 3929.0125 | Z77: ='TOTAL ESTACIONES'!Z77 -> 3743.3 | AA77: ='TOTAL ESTACIONES'!AA77 -> 3812.8125 | AB77: ='TOTAL ESTACIONES'!AB77 -> 4133.4 | AC77: ='TOTAL ESTACIONES'!AC77 -> 4029.65 | AD77: ='TOTAL ESTACIONES'!AD77 -> 4263.0875 | AE77: ='TOTAL ESTACIONES'!AE77 -> 4058.7 | AF77: ='TOTAL ESTACIONES'!AF77 -> 4585.75 | ... AM77: ='TOTAL ESTACIONES'!AM77 -> 0.0375 | AO77: =+AK77-V77 -> 1744.0903 | AS77: 48253.164
I78: Rentas No Deducibles | J78: ='TOTAL ESTACIONES'!J78 -> 0 | K78: ='TOTAL ESTACIONES'!K78 -> 0 | L78: ='TOTAL ESTACIONES'!L78 -> 0 | M78: ='TOTAL ESTACIONES'!M78 -> 0 | N78: ='TOTAL ESTACIONES'!N78 -> 0 | O78: ='TOTAL ESTACIONES'!O78 -> 0 | P78: ='TOTAL ESTACIONES'!P78 -> 0 | Q78: ='TOTAL ESTACIONES'!Q78 -> 0 | ... W78: ='TOTAL ESTACIONES'!W78 -> 0 | Y78: ='TOTAL ESTACIONES'!Y78 -> 0 | Z78: ='TOTAL ESTACIONES'!Z78 -> 0 | AA78: ='TOTAL ESTACIONES'!AA78 -> 0 | AB78: ='TOTAL ESTACIONES'!AB78 -> 0 | AC78: ='TOTAL ESTACIONES'!AC78 -> 0 | AD78: ='TOTAL ESTACIONES'!AD78 -> 0 | AE78: ='TOTAL ESTACIONES'!AE78 -> 0 | AF78: ='TOTAL ESTACIONES'!AF78 -> 0 | ... AM78: ='TOTAL ESTACIONES'!AM78 -> 0 | AO78: =+AK78-V78 -> 0 | AS78: 0
I79: Uniformes | J79: ='TOTAL ESTACIONES'!J79 -> 23656 | K79: ='TOTAL ESTACIONES'!K79 -> 90215 | L79: ='TOTAL ESTACIONES'!L79 -> 56390 | M79: ='TOTAL ESTACIONES'!M79 -> 29112 | N79: ='TOTAL ESTACIONES'!N79 -> 47011 | O79: ='TOTAL ESTACIONES'!O79 -> 51226 | P79: ='TOTAL ESTACIONES'!P79 -> 43481 | Q79: ='TOTAL ESTACIONES'!Q79 -> 37842 | ... W79: ='TOTAL ESTACIONES'!W79 -> 0.00077553191 | Y79: ='TOTAL ESTACIONES'!Y79 -> 58039.907 | Z79: ='TOTAL ESTACIONES'!Z79 -> 53966.291 | AA79: ='TOTAL ESTACIONES'!AA79 -> 62546.173 | AB79: ='TOTAL ESTACIONES'!AB79 -> 49076.924 | AC79: ='TOTAL ESTACIONES'!AC79 -> 51936.884 | AD79: ='TOTAL ESTACIONES'!AD79 -> 17617.357 | AE79: ='TOTAL ESTACIONES'!AE79 -> 40497.042 | AF79: ='TOTAL ESTACIONES'!AF79 -> 63376.727 | ... AM79: ='TOTAL ESTACIONES'!AM79 -> 0.10304985 | AO79: =+AK79-V79 -> 71620.028 | AP79: ver con Diana | AS79: 766623.72
I80: Contratacion Empleados | J80: ='TOTAL ESTACIONES'!J80 -> 0 | K80: ='TOTAL ESTACIONES'!K80 -> 0 | L80: ='TOTAL ESTACIONES'!L80 -> 0 | M80: ='TOTAL ESTACIONES'!M80 -> 0 | N80: ='TOTAL ESTACIONES'!N80 -> 730 | O80: ='TOTAL ESTACIONES'!O80 -> 1460 | P80: ='TOTAL ESTACIONES'!P80 -> 730 | Q80: ='TOTAL ESTACIONES'!Q80 -> 730 | ... W80: ='TOTAL ESTACIONES'!W80 -> 7.4221245e-06 | Y80: ='TOTAL ESTACIONES'!Y80 -> 978.1695 | Z80: ='TOTAL ESTACIONES'!Z80 -> 4042.0655 | AA80: ='TOTAL ESTACIONES'!AA80 -> 1552.65 | AB80: ='TOTAL ESTACIONES'!AB80 -> 1361.1565 | AC80: ='TOTAL ESTACIONES'!AC80 -> 1552.65 | AD80: ='TOTAL ESTACIONES'!AD80 -> 3296.7935 | AE80: ='TOTAL ESTACIONES'!AE80 -> 1935.637 | AF80: ='TOTAL ESTACIONES'!AF80 -> 1744.1435 | ... AM80: ='TOTAL ESTACIONES'!AM80 -> 2.2649168 | AO80: =+AK80-V80 -> 15064.958 | AS80: 21716.398
I81: Multas y Recargos | J81: ='TOTAL ESTACIONES'!J81 -> 0 | K81: ='TOTAL ESTACIONES'!K81 -> 2659 | L81: ='TOTAL ESTACIONES'!L81 -> 0 | M81: ='TOTAL ESTACIONES'!M81 -> 0 | N81: ='TOTAL ESTACIONES'!N81 -> 0 | O81: ='TOTAL ESTACIONES'!O81 -> 0 | P81: ='TOTAL ESTACIONES'!P81 -> 11560 | Q81: ='TOTAL ESTACIONES'!Q81 -> 0 | ... W81: ='TOTAL ESTACIONES'!W81 -> 1.5866517e-05 | Y81: ='TOTAL ESTACIONES'!Y81 -> 0 | Z81: ='TOTAL ESTACIONES'!Z81 -> 0 | AA81: ='TOTAL ESTACIONES'!AA81 -> 0 | AB81: ='TOTAL ESTACIONES'!AB81 -> 0 | AC81: ='TOTAL ESTACIONES'!AC81 -> 0 | AD81: ='TOTAL ESTACIONES'!AD81 -> 0 | AE81: ='TOTAL ESTACIONES'!AE81 -> 0 | AF81: ='TOTAL ESTACIONES'!AF81 -> 0 | ... AM81: ='TOTAL ESTACIONES'!AM81 -> -1 | AO81: =+AK81-V81 -> -14219 | AS81: 0
A82: C - NOMINA | B82: estaciones | I82: Seguros y fianzas | J82: ='TOTAL ESTACIONES'!J82 -> 21806 | K82: ='TOTAL ESTACIONES'!K82 -> 18801 | L82: ='TOTAL ESTACIONES'!L82 -> 18801 | M82: ='TOTAL ESTACIONES'!M82 -> 18801 | N82: ='TOTAL ESTACIONES'!N82 -> 18801 | O82: ='TOTAL ESTACIONES'!O82 -> 18801 | P82: ='TOTAL ESTACIONES'!P82 -> 18801 | Q82: ='TOTAL ESTACIONES'!Q82 -> 41113 | ... W82: ='TOTAL ESTACIONES'!W82 -> 0.0003795924 | Y82: ='TOTAL ESTACIONES'!Y82 -> 41935.26 | Z82: ='TOTAL ESTACIONES'!Z82 -> 41935.26 | AA82: ='TOTAL ESTACIONES'!AA82 -> 41935.26 | AB82: ='TOTAL ESTACIONES'!AB82 -> 41935.26 | AC82: ='TOTAL ESTACIONES'!AC82 -> 41935.26 | AD82: ='TOTAL ESTACIONES'!AD82 -> 41935.26 | AE82: ='TOTAL ESTACIONES'!AE82 -> 41935.26 | AF82: ='TOTAL ESTACIONES'!AF82 -> 41935.26 | ... AM82: ='TOTAL ESTACIONES'!AM82 -> 0.47929789 | AO82: =+AK82-V82 -> 163046.12 | AP82: OK, INCREMENTO FIANZA LOBO Y FIANZA MGC, NO EN AÑO COMPLETO 2025 | AS82: 503223.12
A83: C - NOMINA | B83: estaciones | I83: Vigilancia y seguridad | J83: ='TOTAL ESTACIONES'!J83 -> 0 | K83: ='TOTAL ESTACIONES'!K83 -> 0 | L83: ='TOTAL ESTACIONES'!L83 -> 0 | M83: ='TOTAL ESTACIONES'!M83 -> 0 | N83: ='TOTAL ESTACIONES'!N83 -> 0 | O83: ='TOTAL ESTACIONES'!O83 -> 0 | P83: ='TOTAL ESTACIONES'!P83 -> 0 | Q83: ='TOTAL ESTACIONES'!Q83 -> 0 | ... W83: ='TOTAL ESTACIONES'!W83 -> 0 | Y83: ='TOTAL ESTACIONES'!Y83 -> 0 | Z83: ='TOTAL ESTACIONES'!Z83 -> 0 | AA83: ='TOTAL ESTACIONES'!AA83 -> 0 | AB83: ='TOTAL ESTACIONES'!AB83 -> 0 | AC83: ='TOTAL ESTACIONES'!AC83 -> 0 | AD83: ='TOTAL ESTACIONES'!AD83 -> 0 | AE83: ='TOTAL ESTACIONES'!AE83 -> 0 | AF83: ='TOTAL ESTACIONES'!AF83 -> 0 | ... AM83: ='TOTAL ESTACIONES'!AM83 -> 0 | AO83: =+AK83-V83 -> 0 | AS83: 0
A84: C - NOMINA | B84: estaciones | I84: Honorarios Fiscales P.F. | J84: ='TOTAL ESTACIONES'!J84 -> 0 | K84: ='TOTAL ESTACIONES'!K84 -> 0 | L84: ='TOTAL ESTACIONES'!L84 -> 0 | M84: ='TOTAL ESTACIONES'!M84 -> 0 | N84: ='TOTAL ESTACIONES'!N84 -> 0 | O84: ='TOTAL ESTACIONES'!O84 -> 0 | P84: ='TOTAL ESTACIONES'!P84 -> 0 | Q84: ='TOTAL ESTACIONES'!Q84 -> 0 | ... W84: ='TOTAL ESTACIONES'!W84 -> 0 | Y84: ='TOTAL ESTACIONES'!Y84 -> 0 | Z84: ='TOTAL ESTACIONES'!Z84 -> 0 | AA84: ='TOTAL ESTACIONES'!AA84 -> 0 | AB84: ='TOTAL ESTACIONES'!AB84 -> 0 | AC84: ='TOTAL ESTACIONES'!AC84 -> 0 | AD84: ='TOTAL ESTACIONES'!AD84 -> 0 | AE84: ='TOTAL ESTACIONES'!AE84 -> 0 | AF84: ='TOTAL ESTACIONES'!AF84 -> 0 | ... AM84: ='TOTAL ESTACIONES'!AM84 -> 0 | AO84: =+AK84-V84 -> 0 | AS84: 0
A85: C - NOMINA | B85: estaciones | I85: Honorarios Legales P.M. | J85: ='TOTAL ESTACIONES'!J85 -> 0 | K85: ='TOTAL ESTACIONES'!K85 -> 0 | L85: ='TOTAL ESTACIONES'!L85 -> 7125 | M85: ='TOTAL ESTACIONES'!M85 -> 7125 | N85: ='TOTAL ESTACIONES'!N85 -> 7125 | O85: ='TOTAL ESTACIONES'!O85 -> 7125 | P85: ='TOTAL ESTACIONES'!P85 -> 0 | Q85: ='TOTAL ESTACIONES'!Q85 -> 7125 | ... W85: ='TOTAL ESTACIONES'!W85 -> 5.4063772e-05 | Y85: ='TOTAL ESTACIONES'!Y85 -> 0 | Z85: ='TOTAL ESTACIONES'!Z85 -> 0 | AA85: ='TOTAL ESTACIONES'!AA85 -> 0 | AB85: ='TOTAL ESTACIONES'!AB85 -> 0 | AC85: ='TOTAL ESTACIONES'!AC85 -> 0 | AD85: ='TOTAL ESTACIONES'!AD85 -> 0 | AE85: ='TOTAL ESTACIONES'!AE85 -> 0 | AF85: ='TOTAL ESTACIONES'!AF85 -> 0 | ... AM85: ='TOTAL ESTACIONES'!AM85 -> -1 | AO85: =+AK85-V85 -> -48450 | AP85: FALTA | AS85: 0
A86: C - NOMINA | B86: estaciones | I86: Calcamonias y senalamientos | J86: ='TOTAL ESTACIONES'!J86 -> 0 | K86: ='TOTAL ESTACIONES'!K86 -> 0 | L86: ='TOTAL ESTACIONES'!L86 -> 8400 | M86: ='TOTAL ESTACIONES'!M86 -> 0 | N86: ='TOTAL ESTACIONES'!N86 -> 0 | O86: ='TOTAL ESTACIONES'!O86 -> 0 | P86: ='TOTAL ESTACIONES'!P86 -> 1640 | Q86: ='TOTAL ESTACIONES'!Q86 -> 0 | ... W86: ='TOTAL ESTACIONES'!W86 -> 1.1203308e-05 | Y86: ='TOTAL ESTACIONES'!Y86 -> 0 | Z86: ='TOTAL ESTACIONES'!Z86 -> 0 | AA86: ='TOTAL ESTACIONES'!AA86 -> 0 | AB86: ='TOTAL ESTACIONES'!AB86 -> 0 | AC86: ='TOTAL ESTACIONES'!AC86 -> 0 | AD86: ='TOTAL ESTACIONES'!AD86 -> 0 | AE86: ='TOTAL ESTACIONES'!AE86 -> 0 | AF86: ='TOTAL ESTACIONES'!AF86 -> 0 | ... AM86: ='TOTAL ESTACIONES'!AM86 -> -1 | AO86: =+AK86-V86 -> -10040 | AS86: 0
A87: C - NOMINA | B87: estaciones | I87: Cuotas y suscripciones | J87: ='TOTAL ESTACIONES'!J87 -> 0 | K87: ='TOTAL ESTACIONES'!K87 -> 0 | L87: ='TOTAL ESTACIONES'!L87 -> 0 | M87: ='TOTAL ESTACIONES'!M87 -> 0 | N87: ='TOTAL ESTACIONES'!N87 -> 0 | O87: ='TOTAL ESTACIONES'!O87 -> 0 | P87: ='TOTAL ESTACIONES'!P87 -> 0 | Q87: ='TOTAL ESTACIONES'!Q87 -> 0 | ... W87: ='TOTAL ESTACIONES'!W87 -> 0 | Y87: ='TOTAL ESTACIONES'!Y87 -> 0 | Z87: ='TOTAL ESTACIONES'!Z87 -> 0 | AA87: ='TOTAL ESTACIONES'!AA87 -> 0 | AB87: ='TOTAL ESTACIONES'!AB87 -> 0 | AC87: ='TOTAL ESTACIONES'!AC87 -> 0 | AD87: ='TOTAL ESTACIONES'!AD87 -> 0 | AE87: ='TOTAL ESTACIONES'!AE87 -> 0 | AF87: ='TOTAL ESTACIONES'!AF87 -> 0 | ... AM87: ='TOTAL ESTACIONES'!AM87 -> 0 | AO87: =+AK87-V87 -> 0 | AS87: 0
A88: C - NOMINA | B88: estaciones | I88: Cumplimiento Sat Anexo 30 y 31 | J88: ='TOTAL ESTACIONES'!J88 -> 0 | K88: ='TOTAL ESTACIONES'!K88 -> 0 | L88: ='TOTAL ESTACIONES'!L88 -> 0 | M88: ='TOTAL ESTACIONES'!M88 -> 0 | N88: ='TOTAL ESTACIONES'!N88 -> 0 | O88: ='TOTAL ESTACIONES'!O88 -> 0 | P88: ='TOTAL ESTACIONES'!P88 -> 17500 | Q88: ='TOTAL ESTACIONES'!Q88 -> 0 | ... W88: ='TOTAL ESTACIONES'!W88 -> 0.00016981269 | Y88: ='TOTAL ESTACIONES'!Y88 -> 0 | Z88: ='TOTAL ESTACIONES'!Z88 -> 0 | AA88: ='TOTAL ESTACIONES'!AA88 -> 0 | AB88: ='TOTAL ESTACIONES'!AB88 -> 0 | AC88: ='TOTAL ESTACIONES'!AC88 -> 0 | AD88: ='TOTAL ESTACIONES'!AD88 -> 0 | AE88: ='TOTAL ESTACIONES'!AE88 -> 0 | AF88: ='TOTAL ESTACIONES'!AF88 -> 0 | ... AM88: ='TOTAL ESTACIONES'!AM88 -> -0.14773275 | AO88: =+AK88-V88 -> -22481.97 | AS88: 129698.03
