Workbook
Name AAI: #REF!
Name ALGDED: #REF!
Name BALANZADIC: #REF!
Name BALANZADIC14: #REF!
Name BGDECL: #REF!
Name CCF: #REF!
Name EJERCICIO: #REF!
Name ENERO16: #REF!
Name ENERO16: #REF!
Name ENERO16: #REF!
Name ENERO16: #REF!
Name ENERO16: #REF!
Name ERDECL: #REF!
Name inpc: #REF!
Name No_MES: #REF!
Name NombreRango1: #REF!
Name NombreRango1: #REF!
Name NombreRango1: #REF!
Name NombreRango1: #REF!
Name NombreRango1: #REF!
Name VAC: #REF!

Sheet Parametros SMA
A1: ESTIMULO FISCAL | D1: IEPS
A2: REGULAR | B2: ='[2]Parametros SMA'!$B$2 -> 0 | D2: REGULAR | E2: ='[2]Parametros SMA'!$E$2 -> 0.522479 | I2: *Aumento en los ingresos en proporcion minima a la inflacion
A3: PREMIUM | B3: ='[2]Parametros SMA'!$B$3 -> 0 | D3: PREMIUM | E3: ='[2]Parametros SMA'!$E$3 -> 0.637522
A4: DIESEL | B4: ='[2]Parametros SMA'!$B$4 -> 0 | D4: DIESEL | E4: ='[2]Parametros SMA'!$E$4 -> 0.433626
A6: ='[2]Parametros SMA'!$A$6 -> Precio final al 04 de sep 2024 | D6: Precio de venta sin IVA
A7: REGULAR | B7: ='[2]Parametros SMA'!$B$7 -> 24.33 | D7: =+B7/1.16 -> 20.974138
A8: PREMIUM | B8: ='[2]Parametros SMA'!$B$8 -> 26.69 | D8: =+B8/1.16 -> 23.008621
A9: DIESEL | B9: ='[2]Parametros SMA'!$B$9 -> 25.69 | D9: =+B9/1.16 -> 22.146552
A11: PRECIO DE VENTA sin IVA por LITRO
A12: Juarez | B12: ='[2]Parametros SMA'!B12 -> 0.005 | C12: ='[2]Parametros SMA'!C12 -> 0.005 | D12: ='[2]Parametros SMA'!D12 -> 0.005 | E12: ='[2]Parametros SMA'!E12 -> 0.005 | F12: ='[2]Parametros SMA'!F12 -> 0.005 | G12: ='[2]Parametros SMA'!G12 -> 0.005 | H12: ='[2]Parametros SMA'!H12 -> 0.005 | I12: ='[2]Parametros SMA'!I12 -> 0.005 | ... M12: ='[2]Parametros SMA'!M12 -> 0.005
A13: P.V. | B13: Enero | C13: Febrero | D13: Marzo | E13: Abril | F13: Mayo | G13: Junio | H13: Julio | I13: Agosto | J13: Septiembre | K13: Octubre | L13: Noviembre | M13: Diciembre
A14: MAXIMA | B14: ='[2]Parametros SMA'!B14 -> 20.974138 | C14: ='[2]Parametros SMA'!C14 -> 21.079009 | D14: ='[2]Parametros SMA'!D14 -> 21.184404 | E14: ='[2]Parametros SMA'!E14 -> 21.290326 | F14: ='[2]Parametros SMA'!F14 -> 21.396777 | G14: ='[2]Parametros SMA'!G14 -> 21.503761 | H14: ='[2]Parametros SMA'!H14 -> 21.61128 | I14: ='[2]Parametros SMA'!I14 -> 21.719336 | ... M14: ='[2]Parametros SMA'!M14 -> 22.156992
A15: SUPER | B15: ='[2]Parametros SMA'!B15 -> 23.008621 | C15: ='[2]Parametros SMA'!C15 -> 23.123664 | D15: ='[2]Parametros SMA'!D15 -> 23.239282 | E15: ='[2]Parametros SMA'!E15 -> 23.355479 | F15: ='[2]Parametros SMA'!F15 -> 23.472256 | G15: ='[2]Parametros SMA'!G15 -> 23.589617 | H15: ='[2]Parametros SMA'!H15 -> 23.707565 | I15: ='[2]Parametros SMA'!I15 -> 23.826103 | ... M15: ='[2]Parametros SMA'!M15 -> 24.306211
A16: DIESEL | B16: ='[2]Parametros SMA'!B16 -> 22.146552 | C16: ='[2]Parametros SMA'!C16 -> 22.257284 | D16: ='[2]Parametros SMA'!D16 -> 22.368571 | E16: ='[2]Parametros SMA'!E16 -> 22.480414 | F16: ='[2]Parametros SMA'!F16 -> 22.592816 | G16: ='[2]Parametros SMA'!G16 -> 22.70578 | H16: ='[2]Parametros SMA'!H16 -> 22.819309 | I16: ='[2]Parametros SMA'!I16 -> 22.933405 | ... M16: ='[2]Parametros SMA'!M16 -> 23.395525
A18: ='[2]Parametros SMA'!$A$18 -> Inflacion | B18: ='[2]Parametros SMA'!$B$18 -> 0.07
A21: MARGEN estimado por litro
A22: Juarez | B22: Margen comercial ( precio - costo según factura )
A23: P.V. | B23: Enero | C23: Febrero | D23: Marzo | E23: Abril | F23: Mayo | G23: Junio | H23: Julio | I23: Agosto | J23: Septiembre | K23: Octubre | L23: Noviembre | M23: Diciembre
A24: MAXIMA | B24: ='[2]Parametros SMA'!B24 -> 0 | C24: ='[2]Parametros SMA'!C24 -> 0 | D24: ='[2]Parametros SMA'!D24 -> 0 | E24: ='[2]Parametros SMA'!E24 -> 0 | F24: ='[2]Parametros SMA'!F24 -> 0 | G24: ='[2]Parametros SMA'!G24 -> 0 | H24: ='[2]Parametros SMA'!H24 -> 0 | I24: ='[2]Parametros SMA'!I24 -> 0 | ... M24: ='[2]Parametros SMA'!M24 -> 0
A25: SUPER | B25: ='[2]Parametros SMA'!B25 -> 0 | C25: ='[2]Parametros SMA'!C25 -> 0 | D25: ='[2]Parametros SMA'!D25 -> 0 | E25: ='[2]Parametros SMA'!E25 -> 0 | F25: ='[2]Parametros SMA'!F25 -> 0 | G25: ='[2]Parametros SMA'!G25 -> 0 | H25: ='[2]Parametros SMA'!H25 -> 0 | I25: ='[2]Parametros SMA'!I25 -> 0 | ... M25: ='[2]Parametros SMA'!M25 -> 0
A26: DIESEL | B26: ='[2]Parametros SMA'!B26 -> 0 | C26: ='[2]Parametros SMA'!C26 -> 0 | D26: ='[2]Parametros SMA'!D26 -> 0 | E26: ='[2]Parametros SMA'!E26 -> 0 | F26: ='[2]Parametros SMA'!F26 -> 0 | G26: ='[2]Parametros SMA'!G26 -> 0 | H26: ='[2]Parametros SMA'!H26 -> 0 | I26: ='[2]Parametros SMA'!I26 -> 0 | ... M26: ='[2]Parametros SMA'!M26 -> 0
B28: ='[2]Parametros SMA'!$B$28 -> Margen por contrato de volumen con PETROTAMPS
A29: P.V. | B29: Enero | C29: Febrero | D29: Marzo | E29: Abril | F29: Mayo | G29: Junio | H29: Julio | I29: Agosto | J29: Septiembre | K29: Octubre | L29: Noviembre | M29: Diciembre | N29: Porcentaje
A30: MAXIMA | B30: ='[2]Parametros SMA'!B36 -> 0 | C30: ='[2]Parametros SMA'!C36 -> 0 | D30: ='[2]Parametros SMA'!D36 -> 0 | E30: ='[2]Parametros SMA'!E36 -> 0 | F30: ='[2]Parametros SMA'!F36 -> 0 | G30: ='[2]Parametros SMA'!G36 -> 0 | H30: ='[2]Parametros SMA'!H36 -> 0 | I30: ='[2]Parametros SMA'!I36 -> 0 | ... N30: ='[2]Parametros SMA'!N36 -> 0
A31: SUPER | B31: ='[2]Parametros SMA'!B37 -> 0 | C31: ='[2]Parametros SMA'!C37 -> 0 | D31: ='[2]Parametros SMA'!D37 -> 0 | E31: ='[2]Parametros SMA'!E37 -> 0 | F31: ='[2]Parametros SMA'!F37 -> 0 | G31: ='[2]Parametros SMA'!G37 -> 0 | H31: ='[2]Parametros SMA'!H37 -> 0 | I31: ='[2]Parametros SMA'!I37 -> 0 | ... N31: ='[2]Parametros SMA'!N37 -> 0
A32: DIESEL | B32: ='[2]Parametros SMA'!B38 -> 0 | C32: ='[2]Parametros SMA'!C38 -> 0 | D32: ='[2]Parametros SMA'!D38 -> 0 | E32: ='[2]Parametros SMA'!E38 -> 0 | F32: ='[2]Parametros SMA'!F38 -> 0 | G32: ='[2]Parametros SMA'!G38 -> 0 | H32: ='[2]Parametros SMA'!H38 -> 0 | I32: ='[2]Parametros SMA'!I38 -> 0 | ... N32: ='[2]Parametros SMA'!N38 -> 0
B34: ='[2]Parametros SMA'!$B$34 -> Margen por contrato de volumen con ALLIOTH
A35: P.V. | B35: Enero | C35: Febrero | D35: Marzo | E35: Abril | F35: Mayo | G35: Junio | H35: Julio | I35: Agosto | J35: Septiembre | K35: Octubre | L35: Noviembre | M35: Diciembre | N35: Porcentaje
A36: MAXIMA | B36: ='[2]Parametros SMA'!B36 -> 0 | C36: ='[2]Parametros SMA'!C36 -> 0 | D36: ='[2]Parametros SMA'!D36 -> 0 | E36: ='[2]Parametros SMA'!E36 -> 0 | F36: ='[2]Parametros SMA'!F36 -> 0 | G36: ='[2]Parametros SMA'!G36 -> 0 | H36: ='[2]Parametros SMA'!H36 -> 0 | I36: ='[2]Parametros SMA'!I36 -> 0 | ... N36: ='[2]Parametros SMA'!N36 -> 0
A37: SUPER | B37: ='[2]Parametros SMA'!B37 -> 0 | C37: ='[2]Parametros SMA'!C37 -> 0 | D37: ='[2]Parametros SMA'!D37 -> 0 | E37: ='[2]Parametros SMA'!E37 -> 0 | F37: ='[2]Parametros SMA'!F37 -> 0 | G37: ='[2]Parametros SMA'!G37 -> 0 | H37: ='[2]Parametros SMA'!H37 -> 0 | I37: ='[2]Parametros SMA'!I37 -> 0 | ... N37: ='[2]Parametros SMA'!N37 -> 0
A38: DIESEL | B38: ='[2]Parametros SMA'!B38 -> 0 | C38: ='[2]Parametros SMA'!C38 -> 0 | D38: ='[2]Parametros SMA'!D38 -> 0 | E38: ='[2]Parametros SMA'!E38 -> 0 | F38: ='[2]Parametros SMA'!F38 -> 0 | G38: ='[2]Parametros SMA'!G38 -> 0 | H38: ='[2]Parametros SMA'!H38 -> 0 | I38: ='[2]Parametros SMA'!I38 -> 0 | ... N38: ='[2]Parametros SMA'!N38 -> 0
B40: ='[2]Parametros SMA'!$B$40 -> Margen por contrato de volumen MGC
A41: P.V. | B41: Enero | C41: Febrero | D41: Marzo | E41: Abril | F41: Mayo | G41: Junio | H41: Julio | I41: Agosto | J41: Septiembre | K41: Octubre | L41: Noviembre | M41: Diciembre | N41: Porcentaje
A42: MAXIMA | B42: ='[2]Parametros SMA'!B42 -> 0 | C42: ='[2]Parametros SMA'!C42 -> 1.22 | D42: ='[2]Parametros SMA'!D42 -> 0.51 | E42: ='[2]Parametros SMA'!E42 -> 0.48 | F42: ='[2]Parametros SMA'!F42 -> 1.34 | G42: ='[2]Parametros SMA'!G42 -> 1.19 | H42: ='[2]Parametros SMA'!H42 -> 1.25 | I42: ='[2]Parametros SMA'!I42 -> 1.19 | ... N42: ='[2]Parametros SMA'!N42 -> 1
A43: SUPER | B43: ='[2]Parametros SMA'!B43 -> 0 | C43: ='[2]Parametros SMA'!C43 -> 1.47 | D43: ='[2]Parametros SMA'!D43 -> 1.21 | E43: ='[2]Parametros SMA'!E43 -> 1.55 | F43: ='[2]Parametros SMA'!F43 -> 3.41 | G43: ='[2]Parametros SMA'!G43 -> 3.06 | H43: ='[2]Parametros SMA'!H43 -> 2.73 | I43: ='[2]Parametros SMA'!I43 -> 2.67 | ... N43: ='[2]Parametros SMA'!N43 -> 1
A44: DIESEL | B44: ='[2]Parametros SMA'!B44 -> 1.12 | C44: ='[2]Parametros SMA'!C44 -> 1.18 | D44: ='[2]Parametros SMA'!D44 -> 1.44 | E44: ='[2]Parametros SMA'!E44 -> 2.34 | F44: ='[2]Parametros SMA'!F44 -> 1.43 | G44: ='[2]Parametros SMA'!G44 -> 1.56 | H44: ='[2]Parametros SMA'!H44 -> 0 | I44: ='[2]Parametros SMA'!I44 -> 0 | ... N44: ='[2]Parametros SMA'!N44 -> 1
B46: ='[2]Parametros SMA'!$B$46 -> Margen por contrato de volumen OTROS
A47: P.V. | B47: Enero | C47: Febrero | D47: Marzo | E47: Abril | F47: Mayo | G47: Junio | H47: Julio | I47: Agosto | J47: Septiembre | K47: Octubre | L47: Noviembre | M47: Diciembre | N47: Porcentaje
A48: MAXIMA | B48: ='[2]Parametros SMA'!B48 -> 0 | C48: ='[2]Parametros SMA'!C48 -> 0 | D48: ='[2]Parametros SMA'!D48 -> 0 | E48: ='[2]Parametros SMA'!E48 -> 0 | F48: ='[2]Parametros SMA'!F48 -> 0 | G48: ='[2]Parametros SMA'!G48 -> 0 | H48: ='[2]Parametros SMA'!H48 -> 0 | I48: ='[2]Parametros SMA'!I48 -> 0 | ... N48: ='[2]Parametros SMA'!N48 -> 0
A49: SUPER | B49: ='[2]Parametros SMA'!B49 -> 0 | C49: ='[2]Parametros SMA'!C49 -> 0 | D49: ='[2]Parametros SMA'!D49 -> 0 | E49: ='[2]Parametros SMA'!E49 -> 0 | F49: ='[2]Parametros SMA'!F49 -> 0 | G49: ='[2]Parametros SMA'!G49 -> 0 | H49: ='[2]Parametros SMA'!H49 -> 0 | I49: ='[2]Parametros SMA'!I49 -> 0 | ... N49: ='[2]Parametros SMA'!N49 -> 0
A50: DIESEL | B50: ='[2]Parametros SMA'!B50 -> 0 | C50: ='[2]Parametros SMA'!C50 -> 0 | D50: ='[2]Parametros SMA'!D50 -> 0 | E50: ='[2]Parametros SMA'!E50 -> 0 | F50: ='[2]Parametros SMA'!F50 -> 0 | G50: ='[2]Parametros SMA'!G50 -> 0 | H50: ='[2]Parametros SMA'!H50 -> 0 | I50: ='[2]Parametros SMA'!I50 -> 0 | ... N50: ='[2]Parametros SMA'!N50 -> 0
B52: ='[2]Parametros SMA'!$B$52 -> Margen por contrato de volumen PETRODIESEL
A53: P.V. | B53: Enero | C53: Febrero | D53: Marzo | E53: Abril | F53: Mayo | G53: Junio | H53: Julio | I53: Agosto | J53: Septiembre | K53: Octubre | L53: Noviembre | M53: Diciembre | N53: Porcentaje
A54: MAXIMA | B54: ='[2]Parametros SMA'!B54 -> 0 | C54: ='[2]Parametros SMA'!C54 -> 0 | D54: ='[2]Parametros SMA'!D54 -> 0 | E54: ='[2]Parametros SMA'!E54 -> 0 | F54: ='[2]Parametros SMA'!F54 -> 0 | G54: ='[2]Parametros SMA'!G54 -> 0 | H54: ='[2]Parametros SMA'!H54 -> 0 | I54: ='[2]Parametros SMA'!I54 -> 0 | ... N54: ='[2]Parametros SMA'!N54 -> 0
A55: SUPER | B55: ='[2]Parametros SMA'!B55 -> 0 | C55: ='[2]Parametros SMA'!C55 -> 0 | D55: ='[2]Parametros SMA'!D55 -> 0 | E55: ='[2]Parametros SMA'!E55 -> 0 | F55: ='[2]Parametros SMA'!F55 -> 0 | G55: ='[2]Parametros SMA'!G55 -> 0 | H55: ='[2]Parametros SMA'!H55 -> 0 | I55: ='[2]Parametros SMA'!I55 -> 0 | ... N55: ='[2]Parametros SMA'!N55 -> 0
A56: DIESEL | B56: ='[2]Parametros SMA'!B56 -> 0 | C56: ='[2]Parametros SMA'!C56 -> 0 | D56: ='[2]Parametros SMA'!D56 -> 0 | E56: ='[2]Parametros SMA'!E56 -> 0 | F56: ='[2]Parametros SMA'!F56 -> 0 | G56: ='[2]Parametros SMA'!G56 -> 0 | H56: ='[2]Parametros SMA'!H56 -> 0 | I56: ='[2]Parametros SMA'!I56 -> 0 | ... N56: ='[2]Parametros SMA'!N56 -> 0
A58: CENTAVOS POR LITRO (FLETE) | M58: MAXIMA | N58: ='[2]Parametros SMA'!$N$58 -> 1
A59: MAXIMA | B59: ='[2]Parametros SMA'!$B$59 -> 0 | M59: SUPER | N59: ='[2]Parametros SMA'!$N$59 -> 1
A60: SUPER | B60: ='[2]Parametros SMA'!$B$60 -> 0 | M60: DIESEL | N60: ='[2]Parametros SMA'!$N$60 -> 1
A61: DIESEL | B61: ='[2]Parametros SMA'!$B$61 -> 0
A66: DESCUENTOS
A67: PRECIO REGULAR | C67: Enero | D67: Febrero | E67: Marzo | F67: Abril | G67: Mayo | H67: Junio | I67: Julio | J67: Agosto | K67: Septiembre | L67: Octubre | M67: Noviembre | N67: Diciembre
A68: 23214 | B68: HERMANOS ESCOBAR | C68: ='[2]Parametros SMA'!C68 -> 0 | D68: ='[2]Parametros SMA'!D68 -> 0 | E68: ='[2]Parametros SMA'!E68 -> 0 | F68: ='[2]Parametros SMA'!F68 -> 0 | G68: ='[2]Parametros SMA'!G68 -> 0 | H68: ='[2]Parametros SMA'!H68 -> 0 | I68: ='[2]Parametros SMA'!I68 -> 0 | J68: ='[2]Parametros SMA'!J68 -> 0 | ... N68: ='[2]Parametros SMA'!N68 -> 0
A69: 1149 | B69: LERDO | C69: ='[2]Parametros SMA'!C69 -> 0 | D69: ='[2]Parametros SMA'!D69 -> 0 | E69: ='[2]Parametros SMA'!E69 -> 0 | F69: ='[2]Parametros SMA'!F69 -> 0 | G69: ='[2]Parametros SMA'!G69 -> 0 | H69: ='[2]Parametros SMA'!H69 -> 0 | I69: ='[2]Parametros SMA'!I69 -> 0 | J69: ='[2]Parametros SMA'!J69 -> 0 | ... N69: ='[2]Parametros SMA'!N69 -> 0
A70: 1163 | B70: TECNOLOGICO | C70: ='[2]Parametros SMA'!C70 -> 0 | D70: ='[2]Parametros SMA'!D70 -> 0 | E70: ='[2]Parametros SMA'!E70 -> 0 | F70: ='[2]Parametros SMA'!F70 -> 0 | G70: ='[2]Parametros SMA'!G70 -> 0 | H70: ='[2]Parametros SMA'!H70 -> 0 | I70: ='[2]Parametros SMA'!I70 -> 0 | J70: ='[2]Parametros SMA'!J70 -> 0 | ... N70: ='[2]Parametros SMA'!N70 -> 0
A71: 1376 | B71: DELICIAS | C71: ='[2]Parametros SMA'!C71 -> 0 | D71: ='[2]Parametros SMA'!D71 -> 0 | E71: ='[2]Parametros SMA'!E71 -> 0 | F71: ='[2]Parametros SMA'!F71 -> 0 | G71: ='[2]Parametros SMA'!G71 -> 0 | H71: ='[2]Parametros SMA'!H71 -> 0 | I71: ='[2]Parametros SMA'!I71 -> 0 | J71: ='[2]Parametros SMA'!J71 -> 0 | ... N71: ='[2]Parametros SMA'!N71 -> 0
A72: 2172 | B72: PARRAL | C72: ='[2]Parametros SMA'!C72 -> 0 | D72: ='[2]Parametros SMA'!D72 -> 0 | E72: ='[2]Parametros SMA'!E72 -> 0 | F72: ='[2]Parametros SMA'!F72 -> 0 | G72: ='[2]Parametros SMA'!G72 -> 0 | H72: ='[2]Parametros SMA'!H72 -> 0 | I72: ='[2]Parametros SMA'!I72 -> 0 | J72: ='[2]Parametros SMA'!J72 -> 0 | ... N72: ='[2]Parametros SMA'!N72 -> 0
A73: 2526 | B73: LOPEZ | C73: ='[2]Parametros SMA'!C73 -> 0 | D73: ='[2]Parametros SMA'!D73 -> 0 | E73: ='[2]Parametros SMA'!E73 -> 0 | F73: ='[2]Parametros SMA'!F73 -> 0 | G73: ='[2]Parametros SMA'!G73 -> 0 | H73: ='[2]Parametros SMA'!H73 -> 0 | I73: ='[2]Parametros SMA'!I73 -> 0 | J73: ='[2]Parametros SMA'!J73 -> 0 | ... N73: ='[2]Parametros SMA'!N73 -> 0
A74: 4179 | B74: GEMELA CH | C74: ='[2]Parametros SMA'!C74 -> 0 | D74: ='[2]Parametros SMA'!D74 -> 0 | E74: ='[2]Parametros SMA'!E74 -> 0 | F74: ='[2]Parametros SMA'!F74 -> 0 | G74: ='[2]Parametros SMA'!G74 -> 0 | H74: ='[2]Parametros SMA'!H74 -> 0 | I74: ='[2]Parametros SMA'!I74 -> 0 | J74: ='[2]Parametros SMA'!J74 -> 0 | ... N74: ='[2]Parametros SMA'!N74 -> 0
A75: 4188 | B75: GEMELA G | C75: ='[2]Parametros SMA'!C75 -> 0 | D75: ='[2]Parametros SMA'!D75 -> 0 | E75: ='[2]Parametros SMA'!E75 -> 0 | F75: ='[2]Parametros SMA'!F75 -> 0 | G75: ='[2]Parametros SMA'!G75 -> 0 | H75: ='[2]Parametros SMA'!H75 -> 0 | I75: ='[2]Parametros SMA'!I75 -> 0 | J75: ='[2]Parametros SMA'!J75 -> 0 | ... N75: ='[2]Parametros SMA'!N75 -> 0
A76: 5317 | B76: MUNICIPIO | C76: ='[2]Parametros SMA'!C76 -> 0 | D76: ='[2]Parametros SMA'!D76 -> 0 | E76: ='[2]Parametros SMA'!E76 -> 0 | F76: ='[2]Parametros SMA'!F76 -> 0 | G76: ='[2]Parametros SMA'!G76 -> 0 | H76: ='[2]Parametros SMA'!H76 -> 0 | I76: ='[2]Parametros SMA'!I76 -> 0 | J76: ='[2]Parametros SMA'!J76 -> 0 | ... N76: ='[2]Parametros SMA'!N76 -> 0
A77: 6410 | B77: MISIONES | C77: ='[2]Parametros SMA'!C77 -> 0 | D77: ='[2]Parametros SMA'!D77 -> 0 | E77: ='[2]Parametros SMA'!E77 -> 0 | F77: ='[2]Parametros SMA'!F77 -> 0 | G77: ='[2]Parametros SMA'!G77 -> 0 | H77: ='[2]Parametros SMA'!H77 -> 0 | I77: ='[2]Parametros SMA'!I77 -> 0 | J77: ='[2]Parametros SMA'!J77 -> 0 | ... N77: ='[2]Parametros SMA'!N77 -> 0
A78: 6947 | B78: P PALOS | C78: ='[2]Parametros SMA'!C78 -> 0 | D78: ='[2]Parametros SMA'!D78 -> 0 | E78: ='[2]Parametros SMA'!E78 -> 0 | F78: ='[2]Parametros SMA'!F78 -> 0 | G78: ='[2]Parametros SMA'!G78 -> 0 | H78: ='[2]Parametros SMA'!H78 -> 0 | I78: ='[2]Parametros SMA'!I78 -> 0 | J78: ='[2]Parametros SMA'!J78 -> 0 | ... N78: ='[2]Parametros SMA'!N78 -> 0
A79: 7167 | B79: M MADRID | C79: ='[2]Parametros SMA'!C79 -> 0 | D79: ='[2]Parametros SMA'!D79 -> 0 | E79: ='[2]Parametros SMA'!E79 -> 0 | F79: ='[2]Parametros SMA'!F79 -> 0 | G79: ='[2]Parametros SMA'!G79 -> 0 | H79: ='[2]Parametros SMA'!H79 -> 0 | I79: ='[2]Parametros SMA'!I79 -> 0 | J79: ='[2]Parametros SMA'!J79 -> 0 | ... N79: ='[2]Parametros SMA'!N79 -> 0
... A93: 3184 | B93: PRAXEDIS | C93: ='[2]Parametros SMA'!C93 -> 0 | D93: ='[2]Parametros SMA'!D93 -> 0 | E93: ='[2]Parametros SMA'!E93 -> 0 | F93: ='[2]Parametros SMA'!F93 -> 0 | G93: ='[2]Parametros SMA'!G93 -> 0 | H93: ='[2]Parametros SMA'!H93 -> 0 | I93: ='[2]Parametros SMA'!I93 -> 0 | J93: ='[2]Parametros SMA'!J93 -> 0 | ... N93: ='[2]Parametros SMA'!N93 -> 0
A95: PRECIO PREMIUM | C95: Enero | D95: Febrero | E95: Marzo | F95: Abril | G95: Mayo | H95: Junio | I95: Julio | J95: Agosto | K95: Septiembre | L95: Octubre | M95: Noviembre | N95: Diciembre
B96: HERMANOS ESCOBAR | C96: ='[2]Parametros SMA'!C96 -> 0 | D96: ='[2]Parametros SMA'!D96 -> 0 | E96: ='[2]Parametros SMA'!E96 -> 0 | F96: ='[2]Parametros SMA'!F96 -> 0 | G96: ='[2]Parametros SMA'!G96 -> 0 | H96: ='[2]Parametros SMA'!H96 -> 0 | I96: ='[2]Parametros SMA'!I96 -> 0 | J96: ='[2]Parametros SMA'!J96 -> 0 | ... N96: ='[2]Parametros SMA'!N96 -> 0
A97: 1149 | B97: LERDO | C97: ='[2]Parametros SMA'!C97 -> 0 | D97: ='[2]Parametros SMA'!D97 -> 0 | E97: ='[2]Parametros SMA'!E97 -> 0 | F97: ='[2]Parametros SMA'!F97 -> 0 | G97: ='[2]Parametros SMA'!G97 -> 0 | H97: ='[2]Parametros SMA'!H97 -> 0 | I97: ='[2]Parametros SMA'!I97 -> 0 | J97: ='[2]Parametros SMA'!J97 -> 0 | ... N97: ='[2]Parametros SMA'!N97 -> 0
A98: 1163 | B98: TECNOLOGICO | C98: ='[2]Parametros SMA'!C98 -> 0 | D98: ='[2]Parametros SMA'!D98 -> 0 | E98: ='[2]Parametros SMA'!E98 -> 0 | F98: ='[2]Parametros SMA'!F98 -> 0 | G98: ='[2]Parametros SMA'!G98 -> 0 | H98: ='[2]Parametros SMA'!H98 -> 0 | I98: ='[2]Parametros SMA'!I98 -> 0 | J98: ='[2]Parametros SMA'!J98 -> 0 | ... N98: ='[2]Parametros SMA'!N98 -> 0
A99: 1376 | B99: DELICIAS | C99: ='[2]Parametros SMA'!C99 -> 0 | D99: ='[2]Parametros SMA'!D99 -> 0 | E99: ='[2]Parametros SMA'!E99 -> 0 | F99: ='[2]Parametros SMA'!F99 -> 0 | G99: ='[2]Parametros SMA'!G99 -> 0 | H99: ='[2]Parametros SMA'!H99 -> 0 | I99: ='[2]Parametros SMA'!I99 -> 0 | J99: ='[2]Parametros SMA'!J99 -> 0 | ... N99: ='[2]Parametros SMA'!N99 -> 0
A100: 2172 | B100: PARRAL | C100: ='[2]Parametros SMA'!C100 -> 0 | D100: ='[2]Parametros SMA'!D100 -> 0 | E100: ='[2]Parametros SMA'!E100 -> 0 | F100: ='[2]Parametros SMA'!F100 -> 0 | G100: ='[2]Parametros SMA'!G100 -> 0 | H100: ='[2]Parametros SMA'!H100 -> 0 | I100: ='[2]Parametros SMA'!I100 -> 0 | J100: ='[2]Parametros SMA'!J100 -> 0 | ... N100: ='[2]Parametros SMA'!N100 -> 0
A101: 2526 | B101: LOPEZ | C101: ='[2]Parametros SMA'!C101 -> 0 | D101: ='[2]Parametros SMA'!D101 -> 0 | E101: ='[2]Parametros SMA'!E101 -> 0 | F101: ='[2]Parametros SMA'!F101 -> 0 | G101: ='[2]Parametros SMA'!G101 -> 0 | H101: ='[2]Parametros SMA'!H101 -> 0 | I101: ='[2]Parametros SMA'!I101 -> 0 | J101: ='[2]Parametros SMA'!J101 -> 0 | ... N101: ='[2]Parametros SMA'!N101 -> 0
A102: 4179 | B102: GEMELA CH | C102: ='[2]Parametros SMA'!C102 -> 0 | D102: ='[2]Parametros SMA'!D102 -> 0 | E102: ='[2]Parametros SMA'!E102 -> 0 | F102: ='[2]Parametros SMA'!F102 -> 0 | G102: ='[2]Parametros SMA'!G102 -> 0 | H102: ='[2]Parametros SMA'!H102 -> 0 | I102: ='[2]Parametros SMA'!I102 -> 0 | J102: ='[2]Parametros SMA'!J102 -> 0 | ... N102: ='[2]Parametros SMA'!N102 -> 0
A103: 4188 | B103: GEMELA G | C103: ='[2]Parametros SMA'!C103 -> 0 | D103: ='[2]Parametros SMA'!D103 -> 0 | E103: ='[2]Parametros SMA'!E103 -> 0 | F103: ='[2]Parametros SMA'!F103 -> 0 | G103: ='[2]Parametros SMA'!G103 -> 0 | H103: ='[2]Parametros SMA'!H103 -> 0 | I103: ='[2]Parametros SMA'!I103 -> 0 | J103: ='[2]Parametros SMA'!J103 -> 0 | ... N103: ='[2]Parametros SMA'!N103 -> 0
A104: 5317 | B104: MUNICIPIO | C104: ='[2]Parametros SMA'!C104 -> 0 | D104: ='[2]Parametros SMA'!D104 -> 0 | E104: ='[2]Parametros SMA'!E104 -> 0 | F104: ='[2]Parametros SMA'!F104 -> 0 | G104: ='[2]Parametros SMA'!G104 -> 0 | H104: ='[2]Parametros SMA'!H104 -> 0 | I104: ='[2]Parametros SMA'!I104 -> 0 | J104: ='[2]Parametros SMA'!J104 -> 0 | ... N104: ='[2]Parametros SMA'!N104 -> 0
A105: 6410 | B105: MISIONES | C105: ='[2]Parametros SMA'!C105 -> 0 | D105: ='[2]Parametros SMA'!D105 -> 0 | E105: ='[2]Parametros SMA'!E105 -> 0 | F105: ='[2]Parametros SMA'!F105 -> 0 | G105: ='[2]Parametros SMA'!G105 -> 0 | H105: ='[2]Parametros SMA'!H105 -> 0 | I105: ='[2]Parametros SMA'!I105 -> 0 | J105: ='[2]Parametros SMA'!J105 -> 0 | ... N105: ='[2]Parametros SMA'!N105 -> 0
A106: 6947 | B106: P PALOS | C106: ='[2]Parametros SMA'!C106 -> 0 | D106: ='[2]Parametros SMA'!D106 -> 0 | E106: ='[2]Parametros SMA'!E106 -> 0 | F106: ='[2]Parametros SMA'!F106 -> 0 | G106: ='[2]Parametros SMA'!G106 -> 0 | H106: ='[2]Parametros SMA'!H106 -> 0 | I106: ='[2]Parametros SMA'!I106 -> 0 | J106: ='[2]Parametros SMA'!J106 -> 0 | ... N106: ='[2]Parametros SMA'!N106 -> 0
A107: 7167 | B107: M MADRID | C107: ='[2]Parametros SMA'!C107 -> 0 | D107: ='[2]Parametros SMA'!D107 -> 0 | E107: ='[2]Parametros SMA'!E107 -> 0 | F107: ='[2]Parametros SMA'!F107 -> 0 | G107: ='[2]Parametros SMA'!G107 -> 0 | H107: ='[2]Parametros SMA'!H107 -> 0 | I107: ='[2]Parametros SMA'!I107 -> 0 | J107: ='[2]Parametros SMA'!J107 -> 0 | ... N107: ='[2]Parametros SMA'!N107 -> 0
A108: 5465 | B108: AZTECAS | C108: ='[2]Parametros SMA'!C108 -> 0 | D108: ='[2]Parametros SMA'!D108 -> 0 | E108: ='[2]Parametros SMA'!E108 -> 0 | F108: ='[2]Parametros SMA'!F108 -> 0 | G108: ='[2]Parametros SMA'!G108 -> 0 | H108: ='[2]Parametros SMA'!H108 -> 0 | I108: ='[2]Parametros SMA'!I108 -> 0 | J108: ='[2]Parametros SMA'!J108 -> 0 | ... N108: ='[2]Parametros SMA'!N108 -> 0
... A121: 3184 | B121: PRAXEDIS | C121: ='[2]Parametros SMA'!C121 -> 0 | D121: ='[2]Parametros SMA'!D121 -> 0 | E121: ='[2]Parametros SMA'!E121 -> 0 | F121: ='[2]Parametros SMA'!F121 -> 0 | G121: ='[2]Parametros SMA'!G121 -> 0 | H121: ='[2]Parametros SMA'!H121 -> 0 | I121: ='[2]Parametros SMA'!I121 -> 0 | J121: ='[2]Parametros SMA'!J121 -> 0 | ... N121: ='[2]Parametros SMA'!N121 -> 0
A124: PRECIO DIESEL | C124: Enero | D124: Febrero | E124: Marzo | F124: Abril | G124: Mayo | H124: Junio | I124: Julio | J124: Agosto | K124: Septiembre | L124: Octubre | M124: Noviembre | N124: Diciembre
B125: HERMANOS ESCOBAR | C125: ='[2]Parametros SMA'!C125 -> 0 | D125: ='[2]Parametros SMA'!D125 -> 0 | E125: ='[2]Parametros SMA'!E125 -> 0 | F125: ='[2]Parametros SMA'!F125 -> 0 | G125: ='[2]Parametros SMA'!G125 -> 0 | H125: ='[2]Parametros SMA'!H125 -> 0 | I125: ='[2]Parametros SMA'!I125 -> 0 | J125: ='[2]Parametros SMA'!J125 -> 0 | ... N125: ='[2]Parametros SMA'!N125 -> 0
A126: 1149 | B126: LERDO | C126: ='[2]Parametros SMA'!C126 -> 0 | D126: ='[2]Parametros SMA'!D126 -> 0 | E126: ='[2]Parametros SMA'!E126 -> 0 | F126: ='[2]Parametros SMA'!F126 -> 0 | G126: ='[2]Parametros SMA'!G126 -> 0 | H126: ='[2]Parametros SMA'!H126 -> 0 | I126: ='[2]Parametros SMA'!I126 -> 0 | J126: ='[2]Parametros SMA'!J126 -> 0 | ... N126: ='[2]Parametros SMA'!N126 -> 0
A127: 1163 | B127: TECNOLOGICO | C127: ='[2]Parametros SMA'!C127 -> 0 | D127: ='[2]Parametros SMA'!D127 -> 0 | E127: ='[2]Parametros SMA'!E127 -> 0 | F127: ='[2]Parametros SMA'!F127 -> 0 | G127: ='[2]Parametros SMA'!G127 -> 0 | H127: ='[2]Parametros SMA'!H127 -> 0 | I127: ='[2]Parametros SMA'!I127 -> 0 | J127: ='[2]Parametros SMA'!J127 -> 0 | ... N127: ='[2]Parametros SMA'!N127 -> 0
A128: 1376 | B128: DELICIAS | C128: ='[2]Parametros SMA'!C128 -> 0 | D128: ='[2]Parametros SMA'!D128 -> 0 | E128: ='[2]Parametros SMA'!E128 -> 0 | F128: ='[2]Parametros SMA'!F128 -> 0 | G128: ='[2]Parametros SMA'!G128 -> 0 | H128: ='[2]Parametros SMA'!H128 -> 0 | I128: ='[2]Parametros SMA'!I128 -> 0 | J128: ='[2]Parametros SMA'!J128 -> 0 | ... N128: ='[2]Parametros SMA'!N128 -> 0
A129: 2172 | B129: PARRAL | C129: ='[2]Parametros SMA'!C129 -> 0 | D129: ='[2]Parametros SMA'!D129 -> 0 | E129: ='[2]Parametros SMA'!E129 -> 0 | F129: ='[2]Parametros SMA'!F129 -> 0 | G129: ='[2]Parametros SMA'!G129 -> 0 | H129: ='[2]Parametros SMA'!H129 -> 0 | I129: ='[2]Parametros SMA'!I129 -> 0 | J129: ='[2]Parametros SMA'!J129 -> 0 | ... N129: ='[2]Parametros SMA'!N129 -> 0
A130: 2526 | B130: LOPEZ | C130: ='[2]Parametros SMA'!C130 -> 0 | D130: ='[2]Parametros SMA'!D130 -> 0 | E130: ='[2]Parametros SMA'!E130 -> 0 | F130: ='[2]Parametros SMA'!F130 -> 0 | G130: ='[2]Parametros SMA'!G130 -> 0 | H130: ='[2]Parametros SMA'!H130 -> 0 | I130: ='[2]Parametros SMA'!I130 -> 0 | J130: ='[2]Parametros SMA'!J130 -> 0 | ... N130: ='[2]Parametros SMA'!N130 -> 0
A131: 4179 | B131: GEMELA CH | C131: ='[2]Parametros SMA'!C131 -> 0 | D131: ='[2]Parametros SMA'!D131 -> 0 | E131: ='[2]Parametros SMA'!E131 -> 0 | F131: ='[2]Parametros SMA'!F131 -> 0 | G131: ='[2]Parametros SMA'!G131 -> 0 | H131: ='[2]Parametros SMA'!H131 -> 0 | I131: ='[2]Parametros SMA'!I131 -> 0 | J131: ='[2]Parametros SMA'!J131 -> 0 | ... N131: ='[2]Parametros SMA'!N131 -> 0
A132: 4188 | B132: GEMELA G | C132: ='[2]Parametros SMA'!C132 -> 0 | D132: ='[2]Parametros SMA'!D132 -> 0 | E132: ='[2]Parametros SMA'!E132 -> 0 | F132: ='[2]Parametros SMA'!F132 -> 0 | G132: ='[2]Parametros SMA'!G132 -> 0 | H132: ='[2]Parametros SMA'!H132 -> 0 | I132: ='[2]Parametros SMA'!I132 -> 0 | J132: ='[2]Parametros SMA'!J132 -> 0 | ... N132: ='[2]Parametros SMA'!N132 -> 0
A133: 5317 | B133: MUNICIPIO | C133: ='[2]Parametros SMA'!C133 -> 0 | D133: ='[2]Parametros SMA'!D133 -> 0 | E133: ='[2]Parametros SMA'!E133 -> 0 | F133: ='[2]Parametros SMA'!F133 -> 0 | G133: ='[2]Parametros SMA'!G133 -> 0 | H133: ='[2]Parametros SMA'!H133 -> 0 | I133: ='[2]Parametros SMA'!I133 -> 0 | J133: ='[2]Parametros SMA'!J133 -> 0 | ... N133: ='[2]Parametros SMA'!N133 -> 0
A134: 6410 | B134: MISIONES | C134: ='[2]Parametros SMA'!C134 -> 0 | D134: ='[2]Parametros SMA'!D134 -> 0 | E134: ='[2]Parametros SMA'!E134 -> 0 | F134: ='[2]Parametros SMA'!F134 -> 0 | G134: ='[2]Parametros SMA'!G134 -> 0 | H134: ='[2]Parametros SMA'!H134 -> 0 | I134: ='[2]Parametros SMA'!I134 -> 0 | J134: ='[2]Parametros SMA'!J134 -> 0 | ... N134: ='[2]Parametros SMA'!N134 -> 0
A135: 6947 | B135: P PALOS | C135: ='[2]Parametros SMA'!C135 -> 0 | D135: ='[2]Parametros SMA'!D135 -> 0 | E135: ='[2]Parametros SMA'!E135 -> 0 | F135: ='[2]Parametros SMA'!F135 -> 0 | G135: ='[2]Parametros SMA'!G135 -> 0 | H135: ='[2]Parametros SMA'!H135 -> 0 | I135: ='[2]Parametros SMA'!I135 -> 0 | J135: ='[2]Parametros SMA'!J135 -> 0 | ... N135: ='[2]Parametros SMA'!N135 -> 0
A136: 7167 | B136: M MADRID | C136: ='[2]Parametros SMA'!C136 -> 0 | D136: ='[2]Parametros SMA'!D136 -> 0 | E136: ='[2]Parametros SMA'!E136 -> 0 | F136: ='[2]Parametros SMA'!F136 -> 0 | G136: ='[2]Parametros SMA'!G136 -> 0 | H136: ='[2]Parametros SMA'!H136 -> 0 | I136: ='[2]Parametros SMA'!I136 -> 0 | J136: ='[2]Parametros SMA'!J136 -> 0 | ... N136: ='[2]Parametros SMA'!N136 -> 0
A137: 5465 | B137: AZTECAS | C137: ='[2]Parametros SMA'!C137 -> 0 | D137: ='[2]Parametros SMA'!D137 -> 0 | E137: ='[2]Parametros SMA'!E137 -> 0 | F137: ='[2]Parametros SMA'!F137 -> 0 | G137: ='[2]Parametros SMA'!G137 -> 0 | H137: ='[2]Parametros SMA'!H137 -> 0 | I137: ='[2]Parametros SMA'!I137 -> 0 | J137: ='[2]Parametros SMA'!J137 -> 0 | ... N137: ='[2]Parametros SMA'!N137 -> 0
... A150: 3184 | B150: PRAXEDIS | C150: ='[2]Parametros SMA'!C150 -> 0 | D150: ='[2]Parametros SMA'!D150 -> 0 | E150: ='[2]Parametros SMA'!E150 -> 0 | F150: ='[2]Parametros SMA'!F150 -> 0 | G150: ='[2]Parametros SMA'!G150 -> 0 | H150: ='[2]Parametros SMA'!H150 -> 0 | I150: ='[2]Parametros SMA'!I150 -> 0 | J150: ='[2]Parametros SMA'!J150 -> 0 | ... N150: ='[2]Parametros SMA'!N150 -> 0
A154: WINDSTAR- REGULAR | C154: ENE | D154: FEB | E154: MAR | F154: ABR | G154: MAY | H154: JUN | I154: JUL | J154: AGO | K154: SEP | L154: OCT | M154: NOV | N154: DIC
A155: 1147 | B155: MALECON | C155: 0 | D155: 0 | E155: 0 | F155: 0 | G155: 0 | H155: 0 | I155: 0 | J155: 0 | K155: 0 | L155: 0 | M155: 0 | N155: 0
A156: 1149 | B156: LERDO | C156: 0 | D156: 0 | E156: 0 | F156: 0 | G156: 0 | H156: 0 | I156: 0 | J156: 0 | K156: 0 | L156: 0 | M156: 0 | N156: 0
A157: 1163 | B157: TECNOLOGICO | C157: 0 | D157: 0 | E157: 0 | F157: 0 | G157: 0 | H157: 0 | I157: 0 | J157: 0 | K157: 0 | L157: 0 | M157: 0 | N157: 0
A158: 1376 | B158: DELICIAS | C158: 0 | D158: 0 | E158: 0 | F158: 0 | G158: 0 | H158: 0 | I158: 0 | J158: 0 | K158: 0 | L158: 0 | M158: 0 | N158: 0
...

Sheet S

Sheet CONTABILIDAD-FISCAL
I1: Mantenimiento de Imagen | Y1: 2 | Z1: 3 | AA1: 4 | AB1: 5 | AC1: 6 | AD1: 7 | AE1: 8 | AF1: 9 | AG1: 10 | AH1: 11 | AI1: 12 | AJ1: 13 | AM1: 17
J2: 2024 | V2: TOTAL ANUAL | Y2: 2025 | AK2: TOTAL ANUAL
J3: ENE | K3: FEB | L3: MAR | M3: ABR | N3: MAY | O3: JUN | P3: JUL | Q3: AGO | R3: SEP | S3: OCT | T3: NOV | U3: DIC | V3: 2025 | W3: % Part | Y3: ENE | Z3: FEB | AA3: MAR | AB3: ABR | AC3: MAY | AD3: JUN | AE3: JUL | AF3: AGO | AG3: SEP | AH3: OCT | AI3: NOV | AJ3: DIC | AK3: 2026 | AL3: % Part | AM3: Var vs AA%
I4: INGRESOS
A6: A - INGRESOS | E6: ( mas ) | I6: A - INGRESOS | V6: =SUM(J6:U6) -> 0 | W6: =V6/V$6 -> #DIV/0! | Y6: =SUM(Y7:Y9) -> 0 | Z6: =SUM(Z7:Z9) -> 0 | AA6: =SUM(AA7:AA9) -> 0 | AB6: =SUM(AB7:AB9) -> 0 | AC6: =SUM(AC7:AC9) -> 0 | AD6: =SUM(AD7:AD9) -> 0 | AE6: =SUM(AE7:AE9) -> 0 | AF6: =SUM(AF7:AF9) -> 0 | ... AJ6: =SUM(AJ7:AJ9) -> 0 | AK6: =SUM(Y6:AJ6) -> 0 | AL6: =AK6/AK$6 -> #DIV/0! | AM6: =IFERROR(AK6/V6-1,0) -> 0
A7: A - INGRESOS | B7: estaciones | C7: INGRESOS MAGNA | D7: INGRESOS FORANEOS MAGNA | I7: T-MAXIMA REGULAR | V7: =SUM(J7:U7) -> 0 | W7: =V7/V$6 -> #DIV/0! | Y7: 0 | Z7: 0 | AA7: 0 | AB7: 0 | AC7: 0 | AD7: 0 | AE7: 0 | AF7: 0 | AG7: 0 | AH7: 0 | AI7: 0 | AJ7: 0 | AK7: =SUM(Y7:AJ7) -> 0 | AL7: =AK7/AK$6 -> #DIV/0! | AM7: =IFERROR(AK7/V7-1,0) -> 0
A8: A - INGRESOS | B8: estaciones | C8: INGRESOS PREMIUM | D8: INGRESOS FORANEOS PREMIUM | I8: T-SUPER PREMIUM | V8: =SUM(J8:U8) -> 0 | W8: =V8/V$6 -> #DIV/0! | Y8: 0 | Z8: 0 | AA8: 0 | AB8: 0 | AC8: 0 | AD8: 0 | AE8: 0 | AF8: 0 | AG8: 0 | AH8: 0 | AI8: 0 | AJ8: 0 | AK8: =SUM(Y8:AJ8) -> 0 | AL8: =AK8/AK$6 -> #DIV/0! | AM8: =IFERROR(AK8/V8-1,0) -> 0
A9: A - INGRESOS | B9: estaciones | C9: INGRESOS DIESEL | D9: INGRESOS FORANEOS DIESEL | I9: DIESEL AUTOMOTRIZ | V9: =SUM(J9:U9) -> 0 | W9: =V9/V$6 -> #DIV/0! | Y9: 0 | Z9: 0 | AA9: 0 | AB9: 0 | AC9: 0 | AD9: 0 | AE9: 0 | AF9: 0 | AG9: 0 | AH9: 0 | AI9: 0 | AJ9: 0 | AK9: =SUM(Y9:AJ9) -> 0 | AL9: =AK9/AK$6 -> #DIV/0! | AM9: =IFERROR(AK9/V9-1,0) -> 0
A10: A - INGRESOS | B10: estaciones | C10: INGRESOS ADITIVOS | D10: INGRESOS ESPECIALES | E10: INGRESOS FORANEOS ADITIVOS | F10: INGRESOS FORANEOS ESPECIALES | G10: INGRESOS FORANEOS LUBRICANTES | H10: INGRESOS LUBRICANTES | I10: INGRESOS ACEITES Y LUBRICANTES | V10: =SUM(J10:U10) -> 0 | W10: =V10/V$6 -> #DIV/0! | Y10: 0 | Z10: 0 | AA10: 0 | AB10: 0 | AC10: 0 | AD10: 0 | AE10: 0 | AF10: 0 | AG10: 0 | AH10: 0 | AI10: 0 | AJ10: 0 | AK10: =SUM(Y10:AJ10) -> 0 | AL10: =AK10/AK$6 -> #DIV/0! | AM10: =IFERROR(AK10/V10-1,0) -> 0
I11: SOBRANTE COMBUSTIBLES
A12: B - COSTO DE VENTA | E12: ( menos ) | I12: B - COSTO DE VENTA | V12: =SUM(J12:U12) -> 0 | W12: =V12/V$6 -> #DIV/0! | Y12: =SUM(Y13:Y32) -> 0 | Z12: =SUM(Z13:Z32) -> 0 | AA12: =SUM(AA13:AA32) -> 0 | AB12: =SUM(AB13:AB32) -> 0 | AC12: =SUM(AC13:AC32) -> 0 | AD12: =SUM(AD13:AD32) -> 0 | AE12: =SUM(AE13:AE32) -> 0 | AF12: =SUM(AF13:AF32) -> 0 | ... AJ12: =SUM(AJ13:AJ32) -> 0 | AK12: =SUM(Y12:AJ12) -> 0 | AL12: =AK12/AK$6 -> #DIV/0! | AM12: =IFERROR(AK12/V12-1,0) -> 0
A13: B - COSTO DE VENTA | C13: COSTO MAGNA | D13: COSTO FORANEO MAGNA | I13: GASOLINA REGULAR | V13: =SUM(J13:U13) -> 0 | W13: =V13/V$6 -> #DIV/0! | Y13: 0 | Z13: 0 | AA13: 0 | AB13: 0 | AC13: 0 | AD13: 0 | AE13: 0 | AF13: 0 | AG13: 0 | AH13: 0 | AI13: 0 | AJ13: 0 | AK13: =SUM(Y13:AJ13) -> 0 | AL13: =AK13/AK$6 -> #DIV/0! | AM13: =IFERROR(AK13/V13-1,0) -> 0
A14: B - COSTO DE VENTA | C14: COSTO PREMIUM | D14: COSTO FORANEO PREMIUM | I14: GASOLINA PREMIUM | V14: =SUM(J14:U14) -> 0 | W14: =V14/V$6 -> #DIV/0! | Y14: 0 | Z14: 0 | AA14: 0 | AB14: 0 | AC14: 0 | AD14: 0 | AE14: 0 | AF14: 0 | AG14: 0 | AH14: 0 | AI14: 0 | AJ14: 0 | AK14: =SUM(Y14:AJ14) -> 0 | AL14: =AK14/AK$6 -> #DIV/0! | AM14: =IFERROR(AK14/V14-1,0) -> 0
A15: B - COSTO DE VENTA | C15: COSTO DIESEL | D15: COSTO FORANEO DIESEL | I15: DIESEL | V15: =SUM(J15:U15) -> 0 | W15: =V15/V$6 -> #DIV/0! | Y15: 0 | Z15: 0 | AA15: 0 | AB15: 0 | AC15: 0 | AD15: 0 | AE15: 0 | AF15: 0 | AG15: 0 | AH15: 0 | AI15: 0 | AJ15: 0 | AK15: =SUM(Y15:AJ15) -> 0 | AL15: =AK15/AK$6 -> #DIV/0! | AM15: =IFERROR(AK15/V15-1,0) -> 0
A16: B - COSTO DE VENTA | C16: Merma Magna | I16: MERMA GASOLINA REGULAR | V16: =SUM(J16:U16) -> 0 | W16: =V16/V$6 -> #DIV/0! | Y16: 0 | Z16: 0 | AA16: 0 | AB16: 0 | AC16: 0 | AD16: 0 | AE16: 0 | AF16: 0 | AG16: 0 | AH16: 0 | AI16: 0 | AJ16: 0 | AK16: =SUM(Y16:AJ16) -> 0 | AL16: =AK16/AK$6 -> #DIV/0! | AM16: =IFERROR(AK16/V16-1,0) -> 0
A17: B - COSTO DE VENTA | C17: Merma Premium | I17: MERMA GASOLINA PREMIUM | V17: =SUM(J17:U17) -> 0 | W17: =V17/V$6 -> #DIV/0! | Y17: 0 | Z17: 0 | AA17: 0 | AB17: 0 | AC17: 0 | AD17: 0 | AE17: 0 | AF17: 0 | AG17: 0 | AH17: 0 | AI17: 0 | AJ17: 0 | AK17: =SUM(Y17:AJ17) -> 0 | AL17: =AK17/AK$6 -> #DIV/0! | AM17: =IFERROR(AK17/V17-1,0) -> 0
A18: B - COSTO DE VENTA | C18: Merma Diesel | I18: MERMA DIESEL | V18: =SUM(J18:U18) -> 0 | W18: =V18/V$6 -> #DIV/0! | Y18: 0 | Z18: 0 | AA18: 0 | AB18: 0 | AC18: 0 | AD18: 0 | AE18: 0 | AF18: 0 | AG18: 0 | AH18: 0 | AI18: 0 | AJ18: 0 | AK18: =SUM(Y18:AJ18) -> 0 | AL18: =AK18/AK$6 -> #DIV/0! | AM18: =IFERROR(AK18/V18-1,0) -> 0
A19: B - COSTO DE VENTA | C19: ADITIVO PARA GASOLINA TMAXIMA (REGULAR) | D19: ADITIVO PARA GASOLINA TMAXIMA( REGULAR) | I19: ADITIVO TOTAL POWER GASOLINA REG | V19: =SUM(J19:U19) -> 0 | W19: =V19/V$6 -> #DIV/0! | Y19: 0 | Z19: 0 | AA19: 0 | AB19: 0 | AC19: 0 | AD19: 0 | AE19: 0 | AF19: 0 | AG19: 0 | AH19: 0 | AI19: 0 | AJ19: 0 | AK19: =SUM(Y19:AJ19) -> 0 | AL19: =AK19/AK$6 -> #DIV/0! | AM19: =IFERROR(AK19/V19-1,0) -> 0
A20: B - COSTO DE VENTA | C20: ADITIVO PARA GASOLINA TSUPER (PREMIUM) | I20: ADITIVO TOTAL POWER GASOLINA PREM | V20: =SUM(J20:U20) -> 0 | W20: =V20/V$6 -> #DIV/0! | Y20: 0 | Z20: 0 | AA20: 0 | AB20: 0 | AC20: 0 | AD20: 0 | AE20: 0 | AF20: 0 | AG20: 0 | AH20: 0 | AI20: 0 | AJ20: 0 | AK20: =SUM(Y20:AJ20) -> 0 | AL20: =AK20/AK$6 -> #DIV/0! | AM20: =IFERROR(AK20/V20-1,0) -> 0
A21: B - COSTO DE VENTA | C21: FLETE MAGNA | I21: FLETE GASOLINA REGULAR | V21: =SUM(J21:U21) -> 0 | W21: =V21/V$6 -> #DIV/0! | Y21: 0 | Z21: 0 | AA21: 0 | AB21: 0 | AC21: 0 | AD21: 0 | AE21: 0 | AF21: 0 | AG21: 0 | AH21: 0 | AI21: 0 | AJ21: 0 | AK21: =SUM(Y21:AJ21) -> 0 | AL21: =AK21/AK$6 -> #DIV/0! | AM21: =IFERROR(AK21/V21-1,0) -> 0
A22: B - COSTO DE VENTA | C22: FLETE PREMIUM | I22: FLETE GASOLINA PREMIUM | V22: =SUM(J22:U22) -> 0 | W22: =V22/V$6 -> #DIV/0! | Y22: 0 | Z22: 0 | AA22: 0 | AB22: 0 | AC22: 0 | AD22: 0 | AE22: 0 | AF22: 0 | AG22: 0 | AH22: 0 | AI22: 0 | AJ22: 0 | AK22: =SUM(Y22:AJ22) -> 0 | AL22: =AK22/AK$6 -> #DIV/0! | AM22: =IFERROR(AK22/V22-1,0) -> 0
A23: B - COSTO DE VENTA | C23: FLETE DIESEL | I23: FLETE DIESEL | V23: =SUM(J23:U23) -> 0 | W23: =V23/V$6 -> #DIV/0! | Y23: 0 | Z23: 0 | AA23: 0 | AB23: 0 | AC23: 0 | AD23: 0 | AE23: 0 | AF23: 0 | AG23: 0 | AH23: 0 | AI23: 0 | AJ23: 0 | AK23: =SUM(Y23:AJ23) -> 0 | AL23: =AK23/AK$6 -> #DIV/0! | AM23: =IFERROR(AK23/V23-1,0) -> 0
A24: B - COSTO DE VENTA | C24: Estimulo IEPS Magna | D24: INGRESOS FORANEOS MAGNA | I24: ESTIMULO REGULAR | V24: =SUM(J24:U24) -> 0 | W24: =V24/V$6 -> #DIV/0! | Y24: 0 | Z24: 0 | AA24: 0 | AB24: 0 | AC24: 0 | AD24: 0 | AE24: 0 | AF24: 0 | AG24: 0 | AH24: 0 | AI24: 0 | AJ24: 0 | AK24: =SUM(Y24:AJ24) -> 0 | AL24: =AK24/AK$6 -> #DIV/0! | AM24: =IFERROR(AK24/V24-1,0) -> 0
A25: B - COSTO DE VENTA | C25: Estimulo IEPS Premium | D25: INGRESOS FORANEOS MAGNA | I25: ESTIMULO PREMIUM | V25: =SUM(J25:U25) -> 0 | W25: =V25/V$6 -> #DIV/0! | Y25: 0 | Z25: 0 | AA25: 0 | AB25: 0 | AC25: 0 | AD25: 0 | AE25: 0 | AF25: 0 | AG25: 0 | AH25: 0 | AI25: 0 | AJ25: 0 | AK25: =SUM(Y25:AJ25) -> 0 | AL25: =AK25/AK$6 -> #DIV/0! | AM25: =IFERROR(AK25/V25-1,0) -> 0
I26: SOBRANTE MAGNA
I27: SOBRANTE PREMIUM
I28: SOBRANTE DIESEL
I29: COSTO ACEITES Y LUBRICANTES | V29: =SUM(J29:U29) -> 0 | W29: =V29/V$6 -> #DIV/0! | Y29: 0 | Z29: 0 | AA29: 0 | AB29: 0 | AC29: 0 | AD29: 0 | AE29: 0 | AF29: 0 | AG29: 0 | AH29: 0 | AI29: 0 | AJ29: 0 | AK29: =SUM(Y29:AJ29) -> 0 | AL29: =AK29/AK$6 -> #DIV/0! | AM29: =IFERROR(AK29/V29-1,0) -> 0
I30: BONIFICACION COMPRA DE COMBUSTIBLE MAGNA | V30: =SUM(J30:U30) -> 0 | W30: =V30/V$6 -> #DIV/0! | Y30: 0 | Z30: 0 | AA30: 0 | AB30: 0 | AC30: 0 | AD30: 0 | AE30: 0 | AF30: 0 | AG30: 0 | AH30: 0 | AI30: 0 | AJ30: 0 | AK30: =SUM(Y30:AJ30) -> 0 | AL30: =AK30/AK$6 -> #DIV/0! | AM30: =IFERROR(AK30/V30-1,0) -> 0
I31: BONIFICACION COMPRA DE COMBUSTIBLE PREMIUM
I32: BONIFICACION COMPRA DE COMBUSTIBLE DIESEL | V32: =SUM(J32:U32) -> 0 | W32: =V32/V$6 -> #DIV/0! | Y32: 0 | Z32: 0 | AA32: 0 | AB32: 0 | AC32: 0 | AD32: 0 | AE32: 0 | AF32: 0 | AG32: 0 | AH32: 0 | AI32: 0 | AJ32: 0 | AK32: =SUM(Y32:AJ32) -> 0 | AL32: =AK32/AK$6 -> #DIV/0! | AM32: =IFERROR(AK32/V32-1,0) -> 0
I33: MARGEN DE UTILIDAD | V33: =V6-V12 -> 0 | W33: =V33/V$6 -> #DIV/0! | Y33: =Y6-Y12 -> 0 | Z33: =Z6-Z12 -> 0 | AA33: =AA6-AA12 -> 0 | AB33: =AB6-AB12 -> 0 | AC33: =AC6-AC12 -> 0 | AD33: =AD6-AD12 -> 0 | AE33: =AE6-AE12 -> 0 | AF33: =AF6-AF12 -> 0 | ... AK33: =AK6-AK12 -> 0 | AL33: =AK33/AK$6 -> #DIV/0! | AM33: =IFERROR(AK33/V33-1,0) -> 0
I34: Regular | V34: =SUM(J34:U34) -> 0 | Y34: =+Y44*Y40 -> 0 | Z34: =+Z44*Z40 -> 0 | AA34: =+AA44*AA40 -> 0 | AB34: =+AB44*AB40 -> 0 | AC34: =+AC44*AC40 -> 0 | AD34: =+AD44*AD40 -> 0 | AE34: =+AE44*AE40 -> 0 | AF34: =+AF44*AF40 -> 0 | ... AJ34: =+AJ44*AJ40 -> 0 | AK34: =SUM(Y34:AJ34) -> 0 | AM34: =IFERROR(AK34/V34-1,0) -> 0
I35: Premium | V35: =SUM(J35:U35) -> 0 | Y35: =+Y45*Y41 -> 0 | Z35: =+Z45*Z41 -> 0 | AA35: =+AA45*AA41 -> 0 | AB35: =+AB45*AB41 -> 0 | AC35: =+AC45*AC41 -> 0 | AD35: =+AD45*AD41 -> 0 | AE35: =+AE45*AE41 -> 0 | AF35: =+AF45*AF41 -> 0 | ... AJ35: =+AJ45*AJ41 -> 0 | AK35: =SUM(Y35:AJ35) -> 0 | AM35: =IFERROR(AK35/V35-1,0) -> 0
I36: Diesel | V36: =SUM(J36:U36) -> 0 | Y36: =+Y46*Y42 -> 0 | Z36: =+Z46*Z42 -> 0 | AA36: =+AA46*AA42 -> 0 | AB36: =+AB46*AB42 -> 0 | AC36: =+AC46*AC42 -> 0 | AD36: =+AD46*AD42 -> 0 | AE36: =+AE46*AE42 -> 0 | AF36: =+AF46*AF42 -> 0 | ... AJ36: =+AJ46*AJ42 -> 0 | AK36: =SUM(Y36:AJ36) -> 0 | AM36: =IFERROR(AK36/V36-1,0) -> 0
I37: *Otros Conceptos
I38: * Aceites y Lubricantes
I39: Litros vendidos | V39: =SUM(J39:U39) -> 0 | W39: =V39/V$39 -> #DIV/0! | Y39: =SUM(Y40:Y42) -> 0 | Z39: =SUM(Z40:Z42) -> 0 | AA39: =SUM(AA40:AA42) -> 0 | AB39: =SUM(AB40:AB42) -> 0 | AC39: =SUM(AC40:AC42) -> 0 | AD39: =SUM(AD40:AD42) -> 0 | AE39: =SUM(AE40:AE42) -> 0 | AF39: =SUM(AF40:AF42) -> 0 | ... AJ39: =SUM(AJ40:AJ42) -> 0 | AK39: =SUM(Y39:AJ39) -> 0 | AL39: =AK39/AK$39 -> #DIV/0! | AM39: =IFERROR(AK39/V39-1,0) -> 0
I40: Regular | V40: =SUM(J40:U40) -> 0 | W40: =V40/V$39 -> #DIV/0! | Y40: 0 | Z40: 0 | AA40: 0 | AB40: 0 | AC40: 0 | AD40: 0 | AE40: 0 | AF40: 0 | AG40: 0 | AH40: 0 | AI40: 0 | AJ40: 0 | AK40: =SUM(Y40:AJ40) -> 0 | AL40: =AK40/AK$39 -> #DIV/0! | AM40: =IFERROR(AK40/V40-1,0) -> 0
I41: Premium | V41: =SUM(J41:U41) -> 0 | W41: =V41/V$39 -> #DIV/0! | Y41: 0 | Z41: 0 | AA41: 0 | AB41: 0 | AC41: 0 | AD41: 0 | AE41: 0 | AF41: 0 | AG41: 0 | AH41: 0 | AI41: 0 | AJ41: 0 | AK41: =SUM(Y41:AJ41) -> 0 | AL41: =AK41/AK$39 -> #DIV/0! | AM41: =IFERROR(AK41/V41-1,0) -> 0
I42: Diesel | V42: =SUM(J42:U42) -> 0 | W42: =V42/V$39 -> #DIV/0! | Y42: 0 | Z42: 0 | AA42: 0 | AB42: 0 | AC42: 0 | AD42: 0 | AE42: 0 | AF42: 0 | AG42: 0 | AH42: 0 | AI42: 0 | AJ42: 0 | AK42: =SUM(Y42:AJ42) -> 0 | AL42: =AK42/AK$39 -> #DIV/0! | AM42: =IFERROR(AK42/V42-1,0) -> 0
I43: Margen de utilidad por litro | V43: =SUM(J43:U43) -> 0 | Y43: =IFERROR(Y33/Y39,0) -> 0 | Z43: =IFERROR(Z33/Z39,0) -> 0 | AA43: =IFERROR(AA33/AA39,0) -> 0 | AB43: =IFERROR(AB33/AB39,0) -> 0 | AC43: =IFERROR(AC33/AC39,0) -> 0 | AD43: =IFERROR(AD33/AD39,0) -> 0 | AE43: =IFERROR(AE33/AE39,0) -> 0 | AF43: =IFERROR(AF33/AF39,0) -> 0 | ... AJ43: =IFERROR(AJ33/AJ39,0) -> 0 | AK43: =SUM(Y43:AJ43) -> 0 | AM43: =IFERROR(AK43/V43-1,0) -> 0
I44: Regular | V44: =IFERROR((V7-(V13+V16+V19+V21+V24))/V40,0) -> 0 | Y44: =IFERROR((Y7-(Y13+Y16+Y19+Y21+Y24))/Y40,0) -> 0 | Z44: =IFERROR((Z7-(Z13+Z16+Z19+Z21+Z24))/Z40,0) -> 0 | AA44: =IFERROR((AA7-(AA13+AA16+AA19+AA21+AA24))/AA40,0) -> 0 | AB44: =IFERROR((AB7-(AB13+AB16+AB19+AB21+AB24))/AB40,0) -> 0 | AC44: =IFERROR((AC7-(AC13+AC16+AC19+AC21+AC24))/AC40,0) -> 0 | AD44: =IFERROR((AD7-(AD13+AD16+AD19+AD21+AD24))/AD40,0) -> 0 | AE44: =IFERROR((AE7-(AE13+AE16+AE19+AE21+AE24))/AE40,0) -> 0 | AF44: =IFERROR((AF7-(AF13+AF16+AF19+AF21+AF24))/AF40,0) -> 0 | ... AK44: =IFERROR((AK7-(AK13+AK16+AK19+AK21+AK24))/AK40,0) -> 0 | AM44: =IFERROR(AK44/V44-1,0) -> 0
I45: Premium | V45: =IFERROR((V8-(V14+V17+V20+V22+V25))/V41,0) -> 0 | Y45: =IFERROR((Y8-(Y14+Y17+Y20+Y22+Y25))/Y41,0) -> 0 | Z45: =IFERROR((Z8-(Z14+Z17+Z20+Z22+Z25))/Z41,0) -> 0 | AA45: =IFERROR((AA8-(AA14+AA17+AA20+AA22+AA25))/AA41,0) -> 0 | AB45: =IFERROR((AB8-(AB14+AB17+AB20+AB22+AB25))/AB41,0) -> 0 | AC45: =IFERROR((AC8-(AC14+AC17+AC20+AC22+AC25))/AC41,0) -> 0 | AD45: =IFERROR((AD8-(AD14+AD17+AD20+AD22+AD25))/AD41,0) -> 0 | AE45: =IFERROR((AE8-(AE14+AE17+AE20+AE22+AE25))/AE41,0) -> 0 | AF45: =IFERROR((AF8-(AF14+AF17+AF20+AF22+AF25))/AF41,0) -> 0 | ... AK45: =IFERROR((AK8-(AK14+AK17+AK20+AK22+AK25))/AK41,0) -> 0 | AM45: =IFERROR(AK45/V45-1,0) -> 0
I46: Diesel | V46: =IFERROR((V9-(V15+V18+V23))/V42,0) -> 0 | Y46: =IFERROR((Y9-(Y15+Y18+Y23))/Y42,0) -> 0 | Z46: =IFERROR((Z9-(Z15+Z18+Z23))/Z42,0) -> 0 | AA46: =IFERROR((AA9-(AA15+AA18+AA23))/AA42,0) -> 0 | AB46: =IFERROR((AB9-(AB15+AB18+AB23))/AB42,0) -> 0 | AC46: =IFERROR((AC9-(AC15+AC18+AC23))/AC42,0) -> 0 | AD46: =IFERROR((AD9-(AD15+AD18+AD23))/AD42,0) -> 0 | AE46: =IFERROR((AE9-(AE15+AE18+AE23))/AE42,0) -> 0 | AF46: =IFERROR((AF9-(AF15+AF18+AF23))/AF42,0) -> 0 | ... AK46: =IFERROR((AK9-(AK15+AK18+AK23))/AK42,0) -> 0 | AM46: =IFERROR(AK46/V46-1,0) -> 0
E48: ( menos ) | I48: GASTO ESTACIONES
A50: E - GASTOS DE OPERACIÓN | B50: estaciones | I50: E - GASTOS DE OPERACIÓN | V50: =SUM(V51:V89) -> 0 | W50: =V50/V$6 -> #DIV/0! | Y50: =SUM(Y51:Y89) -> 0 | Z50: =SUM(Z51:Z89) -> 0 | AA50: =SUM(AA51:AA89) -> 0 | AB50: =SUM(AB51:AB89) -> 0 | AC50: =SUM(AC51:AC89) -> 0 | AD50: =SUM(AD51:AD89) -> 0 | AE50: =SUM(AE51:AE89) -> 0 | AF50: =SUM(AF51:AF89) -> 0 | ... AK50: =SUM(AK51:AK89) -> 0 | AL50: =AK50/AK$6 -> #DIV/0! | AM50: =IFERROR(AK50/V50-1,0) -> 0
A51: E - GASTOS DE OPERACIÓN | B51: estaciones | C51: Servicios Administrativos | I51: Traslado de Valores | V51: =SUM(J51:U51) -> 0 | W51: =V51/V$6 -> #DIV/0! | Y51: 0 | Z51: 0 | AA51: 0 | AB51: 0 | AC51: 0 | AD51: 0 | AE51: 0 | AF51: 0 | AG51: 0 | AH51: 0 | AI51: 0 | AJ51: 0 | AK51: =SUM(Y51:AJ51) -> 0 | AL51: =AK51/AK$6 -> #DIV/0! | AM51: =IFERROR(AK51/V51-1,0) -> 0
A52: E - GASTOS DE OPERACIÓN | B52: estaciones | I52: Servicios Administrativos | V52: =SUM(J52:U52) -> 0 | W52: =V52/V$6 -> #DIV/0! | Y52: 0 | Z52: 0 | AA52: 0 | AB52: 0 | AC52: 0 | AD52: 0 | AE52: 0 | AF52: 0 | AG52: 0 | AH52: 0 | AI52: 0 | AJ52: 0 | AK52: =SUM(Y52:AJ52) -> 0 | AL52: =AK52/AK$6 -> #DIV/0! | AM52: =IFERROR(AK52/V52-1,0) -> 0
A53: E - GASTOS DE OPERACIÓN | B53: estaciones | I53: Otros Gastos | V53: =SUM(J53:U53) -> 0 | W53: =V53/V$6 -> #DIV/0! | Y53: 0 | Z53: 0 | AA53: 0 | AB53: 0 | AC53: 0 | AD53: 0 | AE53: 0 | AF53: 0 | AG53: 0 | AH53: 0 | AI53: 0 | AJ53: 0 | AK53: =SUM(Y53:AJ53) -> 0 | AL53: =AK53/AK$6 -> #DIV/0! | AM53: =IFERROR(AK53/V53-1,0) -> 0
A54: E - GASTOS DE OPERACIÓN | B54: estaciones | I54: Otros impuestos y derechos | V54: =SUM(J54:U54) -> 0 | W54: =V54/V$6 -> #DIV/0! | Y54: 0 | Z54: 0 | AA54: 0 | AB54: 0 | AC54: 0 | AD54: 0 | AE54: 0 | AF54: 0 | AG54: 0 | AH54: 0 | AI54: 0 | AJ54: 0 | AK54: =SUM(Y54:AJ54) -> 0 | AL54: =AK54/AK$6 -> #DIV/0! | AM54: =IFERROR(AK54/V54-1,0) -> 0
A55: E - GASTOS DE OPERACIÓN | B55: estaciones | C55: Costo Marketing | I55: Limpieza | V55: =SUM(J55:U55) -> 0 | W55: =V55/V$6 -> #DIV/0! | Y55: 0 | Z55: 0 | AA55: 0 | AB55: 0 | AC55: 0 | AD55: 0 | AE55: 0 | AF55: 0 | AG55: 0 | AH55: 0 | AI55: 0 | AJ55: 0 | AK55: =SUM(Y55:AJ55) -> 0 | AL55: =AK55/AK$6 -> #DIV/0! | AM55: =IFERROR(AK55/V55-1,0) -> 0
A56: E - GASTOS DE OPERACIÓN | B56: estaciones | I56: Propaganda y publicidad | V56: =SUM(J56:U56) -> 0 | W56: =V56/V$6 -> #DIV/0! | Y56: 0 | Z56: 0 | AA56: 0 | AB56: 0 | AC56: 0 | AD56: 0 | AE56: 0 | AF56: 0 | AG56: 0 | AH56: 0 | AI56: 0 | AJ56: 0 | AK56: =SUM(Y56:AJ56) -> 0 | AL56: =AK56/AK$6 -> #DIV/0! | AM56: =IFERROR(AK56/V56-1,0) -> 0
A57: E - GASTOS DE OPERACIÓN | B57: estaciones | I57: Capacitación al personal | V57: =SUM(J57:U57) -> 0 | W57: =V57/V$6 -> #DIV/0! | Y57: 0 | Z57: 0 | AA57: 0 | AB57: 0 | AC57: 0 | AD57: 0 | AE57: 0 | AF57: 0 | AG57: 0 | AH57: 0 | AI57: 0 | AJ57: 0 | AK57: =SUM(Y57:AJ57) -> 0 | AL57: =AK57/AK$6 -> #DIV/0! | AM57: =IFERROR(AK57/V57-1,0) -> 0
A58: E - GASTOS DE OPERACIÓN | B58: estaciones | I58: Honorarios Fiscales P.M. | V58: =SUM(J58:U58) -> 0 | W58: =V58/V$6 -> #DIV/0! | Y58: 0 | Z58: 0 | AA58: 0 | AB58: 0 | AC58: 0 | AD58: 0 | AE58: 0 | AF58: 0 | AG58: 0 | AH58: 0 | AI58: 0 | AJ58: 0 | AK58: =SUM(Y58:AJ58) -> 0 | AL58: =AK58/AK$6 -> #DIV/0! | AM58: =IFERROR(AK58/V58-1,0) -> 0
A59: E - GASTOS DE OPERACIÓN | B59: estaciones | I59: Honorarios Administrativos P.M. | V59: =SUM(J59:U59) -> 0 | W59: =V59/V$6 -> #DIV/0! | Y59: 0 | Z59: 0 | AA59: 0 | AB59: 0 | AC59: 0 | AD59: 0 | AE59: 0 | AF59: 0 | AG59: 0 | AH59: 0 | AI59: 0 | AJ59: 0 | AK59: =SUM(Y59:AJ59) -> 0 | AL59: =AK59/AK$6 -> #DIV/0! | AM59: =IFERROR(AK59/V59-1,0) -> 0
A60: E - GASTOS DE OPERACIÓN | B60: estaciones | I60: Asistencia técnica | V60: =SUM(J60:U60) -> 0 | W60: =V60/V$6 -> #DIV/0! | Y60: 0 | Z60: 0 | AA60: 0 | AB60: 0 | AC60: 0 | AD60: 0 | AE60: 0 | AF60: 0 | AG60: 0 | AH60: 0 | AI60: 0 | AJ60: 0 | AK60: =SUM(Y60:AJ60) -> 0 | AL60: =AK60/AK$6 -> #DIV/0! | AM60: =IFERROR(AK60/V60-1,0) -> 0
A61: E - GASTOS DE OPERACIÓN | B61: estaciones | I61: Gastos no deducibles (sin requisitos fiscales) | V61: =SUM(J61:U61) -> 0 | W61: =V61/V$6 -> #DIV/0! | Y61: 0 | Z61: 0 | AA61: 0 | AB61: 0 | AC61: 0 | AD61: 0 | AE61: 0 | AF61: 0 | AG61: 0 | AH61: 0 | AI61: 0 | AJ61: 0 | AK61: =SUM(Y61:AJ61) -> 0 | AL61: =AK61/AK$6 -> #DIV/0! | AM61: =IFERROR(AK61/V61-1,0) -> 0
A62: E - GASTOS DE OPERACIÓN | B62: estaciones | I62: Papelería y artículos de oficina | V62: =SUM(J62:U62) -> 0 | W62: =V62/V$6 -> #DIV/0! | Y62: 0 | Z62: 0 | AA62: 0 | AB62: 0 | AC62: 0 | AD62: 0 | AE62: 0 | AF62: 0 | AG62: 0 | AH62: 0 | AI62: 0 | AJ62: 0 | AK62: =SUM(Y62:AJ62) -> 0 | AL62: =AK62/AK$6 -> #DIV/0! | AM62: =IFERROR(AK62/V62-1,0) -> 0
A63: E - GASTOS DE OPERACIÓN | B63: estaciones | I63: Faltantes | V63: =SUM(J63:U63) -> 0 | W63: =V63/V$6 -> #DIV/0! | Y63: 0 | Z63: 0 | AA63: 0 | AB63: 0 | AC63: 0 | AD63: 0 | AE63: 0 | AF63: 0 | AG63: 0 | AH63: 0 | AI63: 0 | AJ63: 0 | AK63: =SUM(Y63:AJ63) -> 0 | AL63: =AK63/AK$6 -> #DIV/0! | AM63: =IFERROR(AK63/V63-1,0) -> 0
A64: E - GASTOS DE OPERACIÓN | B64: estaciones | I64: Licencias y Permisos | V64: =SUM(J64:U64) -> 0 | W64: =V64/V$6 -> #DIV/0! | Y64: 0 | Z64: 0 | AA64: 0 | AB64: 0 | AC64: 0 | AD64: 0 | AE64: 0 | AF64: 0 | AG64: 0 | AH64: 0 | AI64: 0 | AJ64: 0 | AK64: =SUM(Y64:AJ64) -> 0 | AL64: =AK64/AK$6 -> #DIV/0! | AM64: =IFERROR(AK64/V64-1,0) -> 0
A65: E - GASTOS DE OPERACIÓN | B65: estaciones | I65: Licencias, Software, Antivirus | V65: =SUM(J65:U65) -> 0 | W65: =V65/V$6 -> #DIV/0! | Y65: 0 | Z65: 0 | AA65: 0 | AB65: 0 | AC65: 0 | AD65: 0 | AE65: 0 | AF65: 0 | AG65: 0 | AH65: 0 | AI65: 0 | AJ65: 0 | AK65: =SUM(Y65:AJ65) -> 0 | AL65: =AK65/AK$6 -> #DIV/0! | AM65: =IFERROR(AK65/V65-1,0) -> 0
A66: E - GASTOS DE OPERACIÓN | B66: estaciones | I66: Fletes Combustible | V66: =SUM(J66:U66) -> 0 | W66: =V66/V$6 -> #DIV/0! | Y66: 0 | Z66: 0 | AA66: 0 | AB66: 0 | AC66: 0 | AD66: 0 | AE66: 0 | AF66: 0 | AG66: 0 | AH66: 0 | AI66: 0 | AJ66: 0 | AK66: =SUM(Y66:AJ66) -> 0 | AL66: =AK66/AK$6 -> #DIV/0! | AM66: =IFERROR(AK66/V66-1,0) -> 0
A67: E - GASTOS DE OPERACIÓN | B67: estaciones | I67: Viáticos y gastos de viaje | V67: =SUM(J67:U67) -> 0 | W67: =V67/V$6 -> #DIV/0! | Y67: 0 | Z67: 0 | AA67: 0 | AB67: 0 | AC67: 0 | AD67: 0 | AE67: 0 | AF67: 0 | AG67: 0 | AH67: 0 | AI67: 0 | AJ67: 0 | AK67: =SUM(Y67:AJ67) -> 0 | AL67: =AK67/AK$6 -> #DIV/0! | AM67: =IFERROR(AK67/V67-1,0) -> 0
... A73: E - GASTOS DE OPERACIÓN | B73: estaciones | I73: Consumos Propios Combustibles | V73: =SUM(J73:U73) -> 0 | W73: =V73/V$6 -> #DIV/0! | Y73: 0 | Z73: 0 | AA73: 0 | AB73: 0 | AC73: 0 | AD73: 0 | AE73: 0 | AF73: 0 | AG73: 0 | AH73: 0 | AI73: 0 | AJ73: 0 | AK73: =SUM(Y73:AJ73) -> 0 | AL73: =AK73/AK$6 -> #DIV/0! | AM73: =IFERROR(AK73/V73-1,0) -> 0
I74: Renta Equipo de Sistemas
I75: Timbrado Facturas
I76: Uniformes
I77: Contratacion Empleados
I78: Seguros y fianzas
I79: Honorarios Legales P.F.
I80: Prediales
I81: Certificado para el cumplimiento SAT anexo 30 y 31
I82: Arrendamiento Tecnologico
I83: Asesoría en sistemas
I84: Combustibles Reembolsos
I85: Honorarios Admvos P.F.
... I89: Vigilancia y seguridad
A90: C - NOMINA | B90: estaciones | I90: C - NOMINA | V90: =SUM(V91:V105) -> 0 | W90: =V90/V$6 -> #DIV/0! | Y90: =SUM(Y91:Y105) -> 0 | Z90: =SUM(Z91:Z105) -> 0 | AA90: =SUM(AA91:AA105) -> 0 | AB90: =SUM(AB91:AB105) -> 0 | AC90: =SUM(AC91:AC105) -> 0 | AD90: =SUM(AD91:AD105) -> 0 | AE90: =SUM(AE91:AE105) -> 0 | AF90: =SUM(AF91:AF105) -> 0 | ... AK90: =SUM(AK91:AK105) -> 0 | AL90: =AK90/AK$6 -> #DIV/0! | AM90: =IFERROR(AK90/V90-1,0) -> 0
A91: C - NOMINA | B91: estaciones | I91: Aguinaldo | V91: =SUM(J91:U91) -> 0 | W91: =V91/V$6 -> #DIV/0! | AK91: =SUM(Y91:AJ91) -> 0 | AL91: =AK91/AK$6 -> #DIV/0! | AM91: =IFERROR(AK91/V91-1,0) -> 0
A92: C - NOMINA | B92: estaciones | I92: Compensaciones | V92: =SUM(J92:U92) -> 0 | W92: =V92/V$6 -> #DIV/0! | AK92: =SUM(Y92:AJ92) -> 0 | AL92: =AK92/AK$6 -> #DIV/0! | AM92: =IFERROR(AK92/V92-1,0) -> 0
A93: C - NOMINA | B93: estaciones | I93: Días festivos | V93: =SUM(J93:U93) -> 0 | W93: =V93/V$6 -> #DIV/0! | AK93: =SUM(Y93:AJ93) -> 0 | AL93: =AK93/AK$6 -> #DIV/0! | AM93: =IFERROR(AK93/V93-1,0) -> 0
A94: C - NOMINA | B94: estaciones | I94: Fondo de ahorro | V94: =SUM(J94:U94) -> 0 | W94: =V94/V$6 -> #DIV/0! | AK94: =SUM(Y94:AJ94) -> 0 | AL94: =AK94/AK$6 -> #DIV/0! | AM94: =IFERROR(AK94/V94-1,0) -> 0
A95: C - NOMINA | B95: estaciones | I95: Indemnizaciones | V95: =SUM(J95:U95) -> 0 | W95: =V95/V$6 -> #DIV/0! | AK95: =SUM(Y95:AJ95) -> 0 | AL95: =AK95/AK$6 -> #DIV/0! | AM95: =IFERROR(AK95/V95-1,0) -> 0
A96: C - NOMINA | B96: estaciones | I96: Premios de asistencia | V96: =SUM(J96:U96) -> 0 | W96: =V96/V$6 -> #DIV/0! | AK96: =SUM(Y96:AJ96) -> 0 | AL96: =AK96/AK$6 -> #DIV/0! | AM96: =IFERROR(AK96/V96-1,0) -> 0
A97: C - NOMINA | B97: estaciones | I97: Premios de puntualidad | V97: =SUM(J97:U97) -> 0 | W97: =V97/V$6 -> #DIV/0! | AK97: =SUM(Y97:AJ97) -> 0 | AL97: =AK97/AK$6 -> #DIV/0! | AM97: =IFERROR(AK97/V97-1,0) -> 0
A98: C - NOMINA | B98: estaciones | I98: Previsión social | V98: =SUM(J98:U98) -> 0 | W98: =V98/V$6 -> #DIV/0! | AK98: =SUM(Y98:AJ98) -> 0 | AL98: =AK98/AK$6 -> #DIV/0! | AM98: =IFERROR(AK98/V98-1,0) -> 0
A99: C - NOMINA | B99: estaciones | I99: Prima dominical | V99: =SUM(J99:U99) -> 0 | W99: =V99/V$6 -> #DIV/0! | AK99: =SUM(Y99:AJ99) -> 0 | AL99: =AK99/AK$6 -> #DIV/0! | AM99: =IFERROR(AK99/V99-1,0) -> 0
A100: C - NOMINA | B100: estaciones | I100: Prima vacacional | V100: =SUM(J100:U100) -> 0 | W100: =V100/V$6 -> #DIV/0! | AK100: =SUM(Y100:AJ100) -> 0 | AL100: =AK100/AK$6 -> #DIV/0! | AM100: =IFERROR(AK100/V100-1,0) -> 0
A101: C - NOMINA | B101: estaciones | I101: Primas de antigüedad | V101: =SUM(J101:U101) -> 0 | W101: =V101/V$6 -> #DIV/0! | AK101: =SUM(Y101:AJ101) -> 0 | AL101: =AK101/AK$6 -> #DIV/0! | AM101: =IFERROR(AK101/V101-1,0) -> 0
A102: C - NOMINA | B102: estaciones | I102: PTU | V102: =SUM(J102:U102) -> 0 | W102: =V102/V$6 -> #DIV/0! | AK102: =SUM(Y102:AJ102) -> 0 | AL102: =AK102/AK$6 -> #DIV/0! | AM102: =IFERROR(AK102/V102-1,0) -> 0
... A105: C - NOMINA | B105: estaciones | I105: Vacaciones | V105: =SUM(J105:U105) -> 0 | W105: =V105/V$6 -> #DIV/0! | AK105: =SUM(Y105:AJ105) -> 0 | AL105: =AK105/AK$6 -> #DIV/0! | AM105: =IFERROR(AK105/V105-1,0) -> 0
A106: D - COSTO SOCIAL | B106: estaciones | I106: D - COSTO SOCIAL | V106: =SUM(V107:V110) -> 0 | W106: =V106/V$6 -> #DIV/0! | Y106: =SUM(Y107:Y110) -> 0 | Z106: =SUM(Z107:Z110) -> 0 | AA106: =SUM(AA107:AA110) -> 0 | AB106: =SUM(AB107:AB110) -> 0 | AC106: =SUM(AC107:AC110) -> 0 | AD106: =SUM(AD107:AD110) -> 0 | AE106: =SUM(AE107:AE110) -> 0 | AF106: =SUM(AF107:AF110) -> 0 | ... AK106: =SUM(AK107:AK110) -> 0 | AL106: =AK106/AK$6 -> #DIV/0! | AM106: =IFERROR(AK106/V106-1,0) -> 0
A107: D - COSTO SOCIAL | B107: estaciones | I107: Aportaciones al infonavit | V107: =SUM(J107:U107) -> 0 | W107: =V107/V$6 -> #DIV/0! | AK107: =SUM(Y107:AJ107) -> 0 | AL107: =AK107/AK$6 -> #DIV/0! | AM107: =IFERROR(AK107/V107-1,0) -> 0
A108: D - COSTO SOCIAL | B108: estaciones | I108: Aportaciones al SAR | V108: =SUM(J108:U108) -> 0 | W108: =V108/V$6 -> #DIV/0! | AK108: =SUM(Y108:AJ108) -> 0 | AL108: =AK108/AK$6 -> #DIV/0! | AM108: =IFERROR(AK108/V108-1,0) -> 0
A109: D - COSTO SOCIAL | B109: estaciones | I109: Cuotas al IMSS | V109: =SUM(J109:U109) -> 0 | W109: =V109/V$6 -> #DIV/0! | AK109: =SUM(Y109:AJ109) -> 0 | AL109: =AK109/AK$6 -> #DIV/0! | AM109: =IFERROR(AK109/V109-1,0) -> 0
A110: D - COSTO SOCIAL | B110: estaciones | I110: Impuesto Estatal | V110: =SUM(J110:U110) -> 0 | W110: =V110/V$6 -> #DIV/0! | AK110: =SUM(Y110:AJ110) -> 0 | AL110: =AK110/AK$6 -> #DIV/0! | AM110: =IFERROR(AK110/V110-1,0) -> 0
A111: F - MANTENIMIENTO | B111: estaciones | C111: Mantenimiento de Imagen | I111: F - MANTENIMIENTO | V111: =SUM(V112:V114) -> 0 | W111: =V111/V$6 -> #DIV/0! | Y111: =SUM(Y112:Y114) -> 0 | Z111: =SUM(Z112:Z114) -> 0 | AA111: =SUM(AA112:AA114) -> 0 | AB111: =SUM(AB112:AB114) -> 0 | AC111: =SUM(AC112:AC114) -> 0 | AD111: =SUM(AD112:AD114) -> 0 | AE111: =SUM(AE112:AE114) -> 0 | AF111: =SUM(AF112:AF114) -> 0 | ... AK111: =SUM(AK112:AK114) -> 0 | AL111: =AK111/AK$6 -> #DIV/0! | AM111: =IFERROR(AK111/V111-1,0) -> 0
A112: F - MANTENIMIENTO | B112: estaciones | I112: Mantenimiento de Equipo de Computo | V112: =SUM(J112:U112) -> 0 | W112: =V112/V$6 -> #DIV/0! | Y112: 0 | Z112: 0 | AA112: 0 | AB112: 0 | AC112: 0 | AD112: 0 | AE112: 0 | AF112: 0 | AG112: 0 | AH112: 0 | AI112: 0 | AJ112: 0 | AK112: =SUM(Y112:AJ112) -> 0 | AL112: =AK112/AK$6 -> #DIV/0! | AM112: =IFERROR(AK112/V112-1,0) -> 0
A113: F - MANTENIMIENTO | B113: estaciones | I113: Certificacion SASISOPA | V113: =SUM(J113:U113) -> 0 | W113: =V113/V$6 -> #DIV/0! | Y113: 0 | Z113: 0 | AA113: 0 | AB113: 0 | AC113: 0 | AD113: 0 | AE113: 0 | AF113: 0 | AG113: 0 | AH113: 0 | AI113: 0 | AJ113: 0 | AK113: =SUM(Y113:AJ113) -> 0 | AL113: =AK113/AK$6 -> #DIV/0! | AM113: =IFERROR(AK113/V113-1,0) -> 0
...

Sheet COM-MKT
I1: Mantenimiento de Imagen | Y1: 2 | Z1: 3 | AA1: 4 | AB1: 5 | AC1: 6 | AD1: 7 | AE1: 8 | AF1: 9 | AG1: 10 | AH1: 11 | AI1: 12 | AJ1: 13 | AM1: 17
J2: 2024 | V2: TOTAL ANUAL | Y2: 2025 | AK2: TOTAL ANUAL
J3: ENE | K3: FEB | L3: MAR | M3: ABR | N3: MAY | O3: JUN | P3: JUL | Q3: AGO | R3: SEP | S3: OCT | T3: NOV | U3: DIC | V3: 2024 | W3: % Part | Y3: ENE | Z3: FEB | AA3: MAR | AB3: ABR | AC3: MAY | AD3: JUN | AE3: JUL | AF3: AGO | AG3: SEP | AH3: OCT | AI3: NOV | AJ3: DIC | AK3: 2025 | AL3: % Part | AM3: Var vs AA%
I4: INGRESOS
A6: A - INGRESOS | E6: ( mas ) | I6: A - INGRESOS | V6: =SUM(J6:U6) -> 0 | W6: =V6/V$6 -> #DIV/0! | Y6: =SUM(Y7:Y9) -> 0 | Z6: =SUM(Z7:Z9) -> 0 | AA6: =SUM(AA7:AA9) -> 0 | AB6: =SUM(AB7:AB9) -> 0 | AC6: =SUM(AC7:AC9) -> 0 | AD6: =SUM(AD7:AD9) -> 0 | AE6: =SUM(AE7:AE9) -> 0 | AF6: =SUM(AF7:AF9) -> 0 | ... AJ6: =SUM(AJ7:AJ9) -> 0 | AK6: =SUM(Y6:AJ6) -> 0 | AL6: =AK6/AK$6 -> #DIV/0! | AM6: =IFERROR(AK6/V6-1,0) -> 0
A7: A - INGRESOS | B7: estaciones | C7: INGRESOS MAGNA | D7: INGRESOS FORANEOS MAGNA | I7: T-MAXIMA REGULAR | V7: =SUM(J7:U7) -> 0 | W7: =V7/V$6 -> #DIV/0! | Y7: 0 | Z7: 0 | AA7: 0 | AB7: 0 | AC7: 0 | AD7: 0 | AE7: 0 | AF7: 0 | AG7: 0 | AH7: 0 | AI7: 0 | AJ7: 0 | AK7: =SUM(Y7:AJ7) -> 0 | AL7: =AK7/AK$6 -> #DIV/0! | AM7: =IFERROR(AK7/V7-1,0) -> 0
A8: A - INGRESOS | B8: estaciones | C8: INGRESOS PREMIUM | D8: INGRESOS FORANEOS PREMIUM | I8: T-SUPER PREMIUM | V8: =SUM(J8:U8) -> 0 | W8: =V8/V$6 -> #DIV/0! | Y8: 0 | Z8: 0 | AA8: 0 | AB8: 0 | AC8: 0 | AD8: 0 | AE8: 0 | AF8: 0 | AG8: 0 | AH8: 0 | AI8: 0 | AJ8: 0 | AK8: =SUM(Y8:AJ8) -> 0 | AL8: =AK8/AK$6 -> #DIV/0! | AM8: =IFERROR(AK8/V8-1,0) -> 0
A9: A - INGRESOS | B9: estaciones | C9: INGRESOS DIESEL | D9: INGRESOS FORANEOS DIESEL | I9: DIESEL AUTOMOTRIZ | V9: =SUM(J9:U9) -> 0 | W9: =V9/V$6 -> #DIV/0! | Y9: 0 | Z9: 0 | AA9: 0 | AB9: 0 | AC9: 0 | AD9: 0 | AE9: 0 | AF9: 0 | AG9: 0 | AH9: 0 | AI9: 0 | AJ9: 0 | AK9: =SUM(Y9:AJ9) -> 0 | AL9: =AK9/AK$6 -> #DIV/0! | AM9: =IFERROR(AK9/V9-1,0) -> 0
A10: A - INGRESOS | B10: estaciones | C10: INGRESOS ADITIVOS | D10: INGRESOS ESPECIALES | E10: INGRESOS FORANEOS ADITIVOS | F10: INGRESOS FORANEOS ESPECIALES | G10: INGRESOS FORANEOS LUBRICANTES | H10: INGRESOS LUBRICANTES | I10: INGRESOS ACEITES Y LUBRICANTES | V10: =SUM(J10:U10) -> 0 | W10: =V10/V$6 -> #DIV/0! | Y10: 0 | Z10: 0 | AA10: 0 | AB10: 0 | AC10: 0 | AD10: 0 | AE10: 0 | AF10: 0 | AG10: 0 | AH10: 0 | AI10: 0 | AJ10: 0 | AK10: =SUM(Y10:AJ10) -> 0 | AL10: =AK10/AK$6 -> #DIV/0! | AM10: =IFERROR(AK10/V10-1,0) -> 0
I11: SOBRANTE COMBUSTIBLES
A12: B - COSTO DE VENTA | E12: ( menos ) | I12: B - COSTO DE VENTA | V12: =SUM(J12:U12) -> 0 | W12: =V12/V$6 -> #DIV/0! | Y12: =SUM(Y13:Y32) -> 0 | Z12: =SUM(Z13:Z32) -> 0 | AA12: =SUM(AA13:AA32) -> 0 | AB12: =SUM(AB13:AB32) -> 0 | AC12: =SUM(AC13:AC32) -> 0 | AD12: =SUM(AD13:AD32) -> 0 | AE12: =SUM(AE13:AE32) -> 0 | AF12: =SUM(AF13:AF32) -> 0 | ... AJ12: =SUM(AJ13:AJ32) -> 0 | AK12: =SUM(Y12:AJ12) -> 0 | AL12: =AK12/AK$6 -> #DIV/0! | AM12: =IFERROR(AK12/V12-1,0) -> 0
A13: B - COSTO DE VENTA | C13: COSTO MAGNA | D13: COSTO FORANEO MAGNA | I13: GASOLINA REGULAR | V13: =SUM(J13:U13) -> 0 | W13: =V13/V$6 -> #DIV/0! | Y13: 0 | Z13: 0 | AA13: 0 | AB13: 0 | AC13: 0 | AD13: 0 | AE13: 0 | AF13: 0 | AG13: 0 | AH13: 0 | AI13: 0 | AJ13: 0 | AK13: =SUM(Y13:AJ13) -> 0 | AL13: =AK13/AK$6 -> #DIV/0! | AM13: =IFERROR(AK13/V13-1,0) -> 0
A14: B - COSTO DE VENTA | C14: COSTO PREMIUM | D14: COSTO FORANEO PREMIUM | I14: GASOLINA PREMIUM | V14: =SUM(J14:U14) -> 0 | W14: =V14/V$6 -> #DIV/0! | Y14: 0 | Z14: 0 | AA14: 0 | AB14: 0 | AC14: 0 | AD14: 0 | AE14: 0 | AF14: 0 | AG14: 0 | AH14: 0 | AI14: 0 | AJ14: 0 | AK14: =SUM(Y14:AJ14) -> 0 | AL14: =AK14/AK$6 -> #DIV/0! | AM14: =IFERROR(AK14/V14-1,0) -> 0
A15: B - COSTO DE VENTA | C15: COSTO DIESEL | D15: COSTO FORANEO DIESEL | I15: DIESEL | V15: =SUM(J15:U15) -> 0 | W15: =V15/V$6 -> #DIV/0! | Y15: 0 | Z15: 0 | AA15: 0 | AB15: 0 | AC15: 0 | AD15: 0 | AE15: 0 | AF15: 0 | AG15: 0 | AH15: 0 | AI15: 0 | AJ15: 0 | AK15: =SUM(Y15:AJ15) -> 0 | AL15: =AK15/AK$6 -> #DIV/0! | AM15: =IFERROR(AK15/V15-1,0) -> 0
A16: B - COSTO DE VENTA | C16: Merma Magna | I16: MERMA GASOLINA REGULAR | V16: =SUM(J16:U16) -> 0 | W16: =V16/V$6 -> #DIV/0! | Y16: 0 | Z16: 0 | AA16: 0 | AB16: 0 | AC16: 0 | AD16: 0 | AE16: 0 | AF16: 0 | AG16: 0 | AH16: 0 | AI16: 0 | AJ16: 0 | AK16: =SUM(Y16:AJ16) -> 0 | AL16: =AK16/AK$6 -> #DIV/0! | AM16: =IFERROR(AK16/V16-1,0) -> 0
A17: B - COSTO DE VENTA | C17: Merma Premium | I17: MERMA GASOLINA PREMIUM | V17: =SUM(J17:U17) -> 0 | W17: =V17/V$6 -> #DIV/0! | Y17: 0 | Z17: 0 | AA17: 0 | AB17: 0 | AC17: 0 | AD17: 0 | AE17: 0 | AF17: 0 | AG17: 0 | AH17: 0 | AI17: 0 | AJ17: 0 | AK17: =SUM(Y17:AJ17) -> 0 | AL17: =AK17/AK$6 -> #DIV/0! | AM17: =IFERROR(AK17/V17-1,0) -> 0
A18: B - COSTO DE VENTA | C18: Merma Diesel | I18: MERMA DIESEL | V18: =SUM(J18:U18) -> 0 | W18: =V18/V$6 -> #DIV/0! | Y18: 0 | Z18: 0 | AA18: 0 | AB18: 0 | AC18: 0 | AD18: 0 | AE18: 0 | AF18: 0 | AG18: 0 | AH18: 0 | AI18: 0 | AJ18: 0 | AK18: =SUM(Y18:AJ18) -> 0 | AL18: =AK18/AK$6 -> #DIV/0! | AM18: =IFERROR(AK18/V18-1,0) -> 0
A19: B - COSTO DE VENTA | C19: ADITIVO PARA GASOLINA TMAXIMA (REGULAR) | D19: ADITIVO PARA GASOLINA TMAXIMA( REGULAR) | I19: ADITIVO TOTAL POWER GASOLINA REG | V19: =SUM(J19:U19) -> 0 | W19: =V19/V$6 -> #DIV/0! | Y19: 0 | Z19: 0 | AA19: 0 | AB19: 0 | AC19: 0 | AD19: 0 | AE19: 0 | AF19: 0 | AG19: 0 | AH19: 0 | AI19: 0 | AJ19: 0 | AK19: =SUM(Y19:AJ19) -> 0 | AL19: =AK19/AK$6 -> #DIV/0! | AM19: =IFERROR(AK19/V19-1,0) -> 0
A20: B - COSTO DE VENTA | C20: ADITIVO PARA GASOLINA TSUPER (PREMIUM) | I20: ADITIVO TOTAL POWER GASOLINA PREM | V20: =SUM(J20:U20) -> 0 | W20: =V20/V$6 -> #DIV/0! | Y20: 0 | Z20: 0 | AA20: 0 | AB20: 0 | AC20: 0 | AD20: 0 | AE20: 0 | AF20: 0 | AG20: 0 | AH20: 0 | AI20: 0 | AJ20: 0 | AK20: =SUM(Y20:AJ20) -> 0 | AL20: =AK20/AK$6 -> #DIV/0! | AM20: =IFERROR(AK20/V20-1,0) -> 0
A21: B - COSTO DE VENTA | C21: FLETE MAGNA | I21: FLETE GASOLINA REGULAR | V21: =SUM(J21:U21) -> 0 | W21: =V21/V$6 -> #DIV/0! | Y21: 0 | Z21: 0 | AA21: 0 | AB21: 0 | AC21: 0 | AD21: 0 | AE21: 0 | AF21: 0 | AG21: 0 | AH21: 0 | AI21: 0 | AJ21: 0 | AK21: =SUM(Y21:AJ21) -> 0 | AL21: =AK21/AK$6 -> #DIV/0! | AM21: =IFERROR(AK21/V21-1,0) -> 0
A22: B - COSTO DE VENTA | C22: FLETE PREMIUM | I22: FLETE GASOLINA PREMIUM | V22: =SUM(J22:U22) -> 0 | W22: =V22/V$6 -> #DIV/0! | Y22: 0 | Z22: 0 | AA22: 0 | AB22: 0 | AC22: 0 | AD22: 0 | AE22: 0 | AF22: 0 | AG22: 0 | AH22: 0 | AI22: 0 | AJ22: 0 | AK22: =SUM(Y22:AJ22) -> 0 | AL22: =AK22/AK$6 -> #DIV/0! | AM22: =IFERROR(AK22/V22-1,0) -> 0
A23: B - COSTO DE VENTA | C23: FLETE DIESEL | I23: FLETE DIESEL | V23: =SUM(J23:U23) -> 0 | W23: =V23/V$6 -> #DIV/0! | Y23: 0 | Z23: 0 | AA23: 0 | AB23: 0 | AC23: 0 | AD23: 0 | AE23: 0 | AF23: 0 | AG23: 0 | AH23: 0 | AI23: 0 | AJ23: 0 | AK23: =SUM(Y23:AJ23) -> 0 | AL23: =AK23/AK$6 -> #DIV/0! | AM23: =IFERROR(AK23/V23-1,0) -> 0
A24: B - COSTO DE VENTA | C24: Estimulo IEPS Magna | D24: INGRESOS FORANEOS MAGNA | I24: ESTIMULO REGULAR | V24: =SUM(J24:U24) -> 0 | W24: =V24/V$6 -> #DIV/0! | Y24: 0 | Z24: 0 | AA24: 0 | AB24: 0 | AC24: 0 | AD24: 0 | AE24: 0 | AF24: 0 | AG24: 0 | AH24: 0 | AI24: 0 | AJ24: 0 | AK24: =SUM(Y24:AJ24) -> 0 | AL24: =AK24/AK$6 -> #DIV/0! | AM24: =IFERROR(AK24/V24-1,0) -> 0
A25: B - COSTO DE VENTA | C25: Estimulo IEPS Premium | D25: INGRESOS FORANEOS MAGNA | I25: ESTIMULO PREMIUM | V25: =SUM(J25:U25) -> 0 | W25: =V25/V$6 -> #DIV/0! | Y25: 0 | Z25: 0 | AA25: 0 | AB25: 0 | AC25: 0 | AD25: 0 | AE25: 0 | AF25: 0 | AG25: 0 | AH25: 0 | AI25: 0 | AJ25: 0 | AK25: =SUM(Y25:AJ25) -> 0 | AL25: =AK25/AK$6 -> #DIV/0! | AM25: =IFERROR(AK25/V25-1,0) -> 0
I26: SOBRANTE MAGNA
I27: SOBRANTE PREMIUM
I28: SOBRANTE DIESEL
I29: COSTO ACEITES Y LUBRICANTES
I30: BONIFICACION COMPRA DE COMBUSTIBLE MAGNA
I31: BONIFICACION COMPRA DE COMBUSTIBLE PREMIUM
I32: BONIFICACION COMPRA DE COMBUSTIBLE DIESEL | V32: =SUM(J32:U32) -> 0 | W32: =V32/V$6 -> #DIV/0! | Y32: 0 | Z32: 0 | AA32: 0 | AB32: 0 | AC32: 0 | AD32: 0 | AE32: 0 | AF32: 0 | AG32: 0 | AH32: 0 | AI32: 0 | AJ32: 0 | AK32: =SUM(Y32:AJ32) -> 0 | AL32: =AK32/AK$6 -> #DIV/0! | AM32: =IFERROR(AK32/V32-1,0) -> 0
I33: MARGEN DE UTILIDAD | V33: =V6-V12 -> 0 | W33: =V33/V$6 -> #DIV/0! | Y33: =Y6-Y12 -> 0 | Z33: =Z6-Z12 -> 0 | AA33: =AA6-AA12 -> 0 | AB33: =AB6-AB12 -> 0 | AC33: =AC6-AC12 -> 0 | AD33: =AD6-AD12 -> 0 | AE33: =AE6-AE12 -> 0 | AF33: =AF6-AF12 -> 0 | ... AK33: =AK6-AK12 -> 0 | AL33: =AK33/AK$6 -> #DIV/0! | AM33: =IFERROR(AK33/V33-1,0) -> 0
I34: Regular | V34: =SUM(J34:U34) -> 0 | Y34: =+Y44*Y40 -> 0 | Z34: =+Z44*Z40 -> 0 | AA34: =+AA44*AA40 -> 0 | AB34: =+AB44*AB40 -> 0 | AC34: =+AC44*AC40 -> 0 | AD34: =+AD44*AD40 -> 0 | AE34: =+AE44*AE40 -> 0 | AF34: =+AF44*AF40 -> 0 | ... AJ34: =+AJ44*AJ40 -> 0 | AK34: =SUM(Y34:AJ34) -> 0 | AM34: =IFERROR(AK34/V34-1,0) -> 0
I35: Premium | V35: =SUM(J35:U35) -> 0 | Y35: =+Y45*Y41 -> 0 | Z35: =+Z45*Z41 -> 0 | AA35: =+AA45*AA41 -> 0 | AB35: =+AB45*AB41 -> 0 | AC35: =+AC45*AC41 -> 0 | AD35: =+AD45*AD41 -> 0 | AE35: =+AE45*AE41 -> 0 | AF35: =+AF45*AF41 -> 0 | ... AJ35: =+AJ45*AJ41 -> 0 | AK35: =SUM(Y35:AJ35) -> 0 | AM35: =IFERROR(AK35/V35-1,0) -> 0
I36: Diesel | V36: =SUM(J36:U36) -> 0 | Y36: =+Y46*Y42 -> 0 | Z36: =+Z46*Z42 -> 0 | AA36: =+AA46*AA42 -> 0 | AB36: =+AB46*AB42 -> 0 | AC36: =+AC46*AC42 -> 0 | AD36: =+AD46*AD42 -> 0 | AE36: =+AE46*AE42 -> 0 | AF36: =+AF46*AF42 -> 0 | ... AJ36: =+AJ46*AJ42 -> 0 | AK36: =SUM(Y36:AJ36) -> 0 | AM36: =IFERROR(AK36/V36-1,0) -> 0
I37: *Otros Conceptos
I38: * Aceites y Lubricantes
I39: Litros vendidos | V39: =SUM(J39:U39) -> 0 | W39: =V39/V$39 -> #DIV/0! | Y39: =SUM(Y40:Y42) -> 0 | Z39: =SUM(Z40:Z42) -> 0 | AA39: =SUM(AA40:AA42) -> 0 | AB39: =SUM(AB40:AB42) -> 0 | AC39: =SUM(AC40:AC42) -> 0 | AD39: =SUM(AD40:AD42) -> 0 | AE39: =SUM(AE40:AE42) -> 0 | AF39: =SUM(AF40:AF42) -> 0 | ... AJ39: =SUM(AJ40:AJ42) -> 0 | AK39: =SUM(Y39:AJ39) -> 0 | AL39: =AK39/AK$39 -> #DIV/0! | AM39: =IFERROR(AK39/V39-1,0) -> 0
I40: Regular | V40: =SUM(J40:U40) -> 0 | W40: =V40/V$39 -> #DIV/0! | Y40: 0 | Z40: 0 | AA40: 0 | AB40: 0 | AC40: 0 | AD40: 0 | AE40: 0 | AF40: 0 | AG40: 0 | AH40: 0 | AI40: 0 | AJ40: 0 | AK40: =SUM(Y40:AJ40) -> 0 | AL40: =AK40/AK$39 -> #DIV/0! | AM40: =IFERROR(AK40/V40-1,0) -> 0
I41: Premium | V41: =SUM(J41:U41) -> 0 | W41: =V41/V$39 -> #DIV/0! | Y41: 0 | Z41: 0 | AA41: 0 | AB41: 0 | AC41: 0 | AD41: 0 | AE41: 0 | AF41: 0 | AG41: 0 | AH41: 0 | AI41: 0 | AJ41: 0 | AK41: =SUM(Y41:AJ41) -> 0 | AL41: =AK41/AK$39 -> #DIV/0! | AM41: =IFERROR(AK41/V41-1,0) -> 0
I42: Diesel | V42: =SUM(J42:U42) -> 0 | W42: =V42/V$39 -> #DIV/0! | Y42: 0 | Z42: 0 | AA42: 0 | AB42: 0 | AC42: 0 | AD42: 0 | AE42: 0 | AF42: 0 | AG42: 0 | AH42: 0 | AI42: 0 | AJ42: 0 | AK42: =SUM(Y42:AJ42) -> 0 | AL42: =AK42/AK$39 -> #DIV/0! | AM42: =IFERROR(AK42/V42-1,0) -> 0
I43: Margen de utilidad por litro | V43: =SUM(J43:U43) -> 0 | Y43: =IFERROR(Y33/Y39,0) -> 0 | Z43: =IFERROR(Z33/Z39,0) -> 0 | AA43: =IFERROR(AA33/AA39,0) -> 0 | AB43: =IFERROR(AB33/AB39,0) -> 0 | AC43: =IFERROR(AC33/AC39,0) -> 0 | AD43: =IFERROR(AD33/AD39,0) -> 0 | AE43: =IFERROR(AE33/AE39,0) -> 0 | AF43: =IFERROR(AF33/AF39,0) -> 0 | ... AJ43: =IFERROR(AJ33/AJ39,0) -> 0 | AK43: =SUM(Y43:AJ43) -> 0 | AM43: =IFERROR(AK43/V43-1,0) -> 0
I44: Regular | V44: =IFERROR((V7-(V13+V16+V19+V21+V24))/V40,0) -> 0 | Y44: =IFERROR((Y7-(Y13+Y16+Y19+Y21+Y24))/Y40,0) -> 0 | Z44: =IFERROR((Z7-(Z13+Z16+Z19+Z21+Z24))/Z40,0) -> 0 | AA44: =IFERROR((AA7-(AA13+AA16+AA19+AA21+AA24))/AA40,0) -> 0 | AB44: =IFERROR((AB7-(AB13+AB16+AB19+AB21+AB24))/AB40,0) -> 0 | AC44: =IFERROR((AC7-(AC13+AC16+AC19+AC21+AC24))/AC40,0) -> 0 | AD44: =IFERROR((AD7-(AD13+AD16+AD19+AD21+AD24))/AD40,0) -> 0 | AE44: =IFERROR((AE7-(AE13+AE16+AE19+AE21+AE24))/AE40,0) -> 0 | AF44: =IFERROR((AF7-(AF13+AF16+AF19+AF21+AF24))/AF40,0) -> 0 | ... AK44: =IFERROR((AK7-(AK13+AK16+AK19+AK21+AK24))/AK40,0) -> 0 | AM44: =IFERROR(AK44/V44-1,0) -> 0
I45: Premium | V45: =IFERROR((V8-(V14+V17+V20+V22+V25))/V41,0) -> 0 | Y45: =IFERROR((Y8-(Y14+Y17+Y20+Y22+Y25))/Y41,0) -> 0 | Z45: =IFERROR((Z8-(Z14+Z17+Z20+Z22+Z25))/Z41,0) -> 0 | AA45: =IFERROR((AA8-(AA14+AA17+AA20+AA22+AA25))/AA41,0) -> 0 | AB45: =IFERROR((AB8-(AB14+AB17+AB20+AB22+AB25))/AB41,0) -> 0 | AC45: =IFERROR((AC8-(AC14+AC17+AC20+AC22+AC25))/AC41,0) -> 0 | AD45: =IFERROR((AD8-(AD14+AD17+AD20+AD22+AD25))/AD41,0) -> 0 | AE45: =IFERROR((AE8-(AE14+AE17+AE20+AE22+AE25))/AE41,0) -> 0 | AF45: =IFERROR((AF8-(AF14+AF17+AF20+AF22+AF25))/AF41,0) -> 0 | ... AK45: =IFERROR((AK8-(AK14+AK17+AK20+AK22+AK25))/AK41,0) -> 0 | AM45: =IFERROR(AK45/V45-1,0) -> 0
I46: Diesel | V46: =IFERROR((V9-(V15+V18+V23))/V42,0) -> 0 | Y46: =IFERROR((Y9-(Y15+Y18+Y23))/Y42,0) -> 0 | Z46: =IFERROR((Z9-(Z15+Z18+Z23))/Z42,0) -> 0 | AA46: =IFERROR((AA9-(AA15+AA18+AA23))/AA42,0) -> 0 | AB46: =IFERROR((AB9-(AB15+AB18+AB23))/AB42,0) -> 0 | AC46: =IFERROR((AC9-(AC15+AC18+AC23))/AC42,0) -> 0 | AD46: =IFERROR((AD9-(AD15+AD18+AD23))/AD42,0) -> 0 | AE46: =IFERROR((AE9-(AE15+AE18+AE23))/AE42,0) -> 0 | AF46: =IFERROR((AF9-(AF15+AF18+AF23))/AF42,0) -> 0 | ... AK46: =IFERROR((AK9-(AK15+AK18+AK23))/AK42,0) -> 0 | AM46: =IFERROR(AK46/V46-1,0) -> 0
E48: ( menos ) | I48: GASTO ESTACIONES
A50: E - GASTOS DE OPERACIÓN | B50: estaciones | I50: E - GASTOS DE OPERACIÓN | V50: =SUM(V51:V89) -> 0 | W50: =V50/V$6 -> #DIV/0! | Y50: =SUM(Y51:Y89) -> 0 | Z50: =SUM(Z51:Z89) -> 0 | AA50: =SUM(AA51:AA89) -> 0 | AB50: =SUM(AB51:AB89) -> 0 | AC50: =SUM(AC51:AC89) -> 0 | AD50: =SUM(AD51:AD89) -> 0 | AE50: =SUM(AE51:AE89) -> 0 | AF50: =SUM(AF51:AF89) -> 0 | ... AK50: =SUM(AK51:AK89) -> 0 | AL50: =AK50/AK$6 -> #DIV/0! | AM50: =IFERROR(AK50/V50-1,0) -> 0
A51: E - GASTOS DE OPERACIÓN | B51: estaciones | C51: Servicios Administrativos | I51: Traslado de Valores | V51: =SUM(J51:U51) -> 0 | W51: =V51/V$6 -> #DIV/0! | Y51: 0 | Z51: 0 | AA51: 0 | AB51: 0 | AC51: 0 | AD51: 0 | AE51: 0 | AF51: 0 | AG51: 0 | AH51: 0 | AI51: 0 | AJ51: 0 | AK51: =SUM(Y51:AJ51) -> 0 | AL51: =AK51/AK$6 -> #DIV/0! | AM51: =IFERROR(AK51/V51-1,0) -> 0
A52: E - GASTOS DE OPERACIÓN | B52: estaciones | I52: Servicios Administrativos | V52: =SUM(J52:U52) -> 0 | W52: =V52/V$6 -> #DIV/0! | Y52: 0 | Z52: 0 | AA52: 0 | AB52: 0 | AC52: 0 | AD52: 0 | AE52: 0 | AF52: 0 | AG52: 0 | AH52: 0 | AI52: 0 | AJ52: 0 | AK52: =SUM(Y52:AJ52) -> 0 | AL52: =AK52/AK$6 -> #DIV/0! | AM52: =IFERROR(AK52/V52-1,0) -> 0
A53: E - GASTOS DE OPERACIÓN | B53: estaciones | I53: Otros Gastos | V53: =SUM(J53:U53) -> 0 | W53: =V53/V$6 -> #DIV/0! | Y53: 0 | Z53: 0 | AA53: 0 | AB53: 0 | AC53: 0 | AD53: 0 | AE53: 0 | AF53: 0 | AG53: 0 | AH53: 0 | AI53: 0 | AJ53: 0 | AK53: =SUM(Y53:AJ53) -> 0 | AL53: =AK53/AK$6 -> #DIV/0! | AM53: =IFERROR(AK53/V53-1,0) -> 0
A54: E - GASTOS DE OPERACIÓN | B54: estaciones | I54: Otros impuestos y derechos | V54: =SUM(J54:U54) -> 0 | W54: =V54/V$6 -> #DIV/0! | Y54: 0 | Z54: 0 | AA54: 0 | AB54: 0 | AC54: 0 | AD54: 0 | AE54: 0 | AF54: 0 | AG54: 0 | AH54: 0 | AI54: 0 | AJ54: 0 | AK54: =SUM(Y54:AJ54) -> 0 | AL54: =AK54/AK$6 -> #DIV/0! | AM54: =IFERROR(AK54/V54-1,0) -> 0
A55: E - GASTOS DE OPERACIÓN | B55: estaciones | C55: Costo Marketing | I55: Limpieza | V55: =SUM(J55:U55) -> 0 | W55: =V55/V$6 -> #DIV/0! | Y55: 0 | Z55: 0 | AA55: 0 | AB55: 0 | AC55: 0 | AD55: 0 | AE55: 0 | AF55: 0 | AG55: 0 | AH55: 0 | AI55: 0 | AJ55: 0 | AK55: =SUM(Y55:AJ55) -> 0 | AL55: =AK55/AK$6 -> #DIV/0! | AM55: =IFERROR(AK55/V55-1,0) -> 0
A56: E - GASTOS DE OPERACIÓN | B56: estaciones | I56: Propaganda y publicidad | V56: =SUM(J56:U56) -> 0 | W56: =V56/V$6 -> #DIV/0! | Y56: 0 | Z56: 0 | AA56: 0 | AB56: 0 | AC56: 0 | AD56: 0 | AE56: 0 | AF56: 0 | AG56: 0 | AH56: 0 | AI56: 0 | AJ56: 0 | AK56: =SUM(Y56:AJ56) -> 0 | AL56: =AK56/AK$6 -> #DIV/0! | AM56: =IFERROR(AK56/V56-1,0) -> 0
A57: E - GASTOS DE OPERACIÓN | B57: estaciones | I57: Capacitación al personal | V57: =SUM(J57:U57) -> 0 | W57: =V57/V$6 -> #DIV/0! | Y57: 0 | Z57: 0 | AA57: 0 | AB57: 0 | AC57: 0 | AD57: 0 | AE57: 0 | AF57: 0 | AG57: 0 | AH57: 0 | AI57: 0 | AJ57: 0 | AK57: =SUM(Y57:AJ57) -> 0 | AL57: =AK57/AK$6 -> #DIV/0! | AM57: =IFERROR(AK57/V57-1,0) -> 0
A58: E - GASTOS DE OPERACIÓN | B58: estaciones | I58: Honorarios Fiscales P.M. | V58: =SUM(J58:U58) -> 0 | W58: =V58/V$6 -> #DIV/0! | Y58: 0 | Z58: 0 | AA58: 0 | AB58: 0 | AC58: 0 | AD58: 0 | AE58: 0 | AF58: 0 | AG58: 0 | AH58: 0 | AI58: 0 | AJ58: 0 | AK58: =SUM(Y58:AJ58) -> 0 | AL58: =AK58/AK$6 -> #DIV/0! | AM58: =IFERROR(AK58/V58-1,0) -> 0
A59: E - GASTOS DE OPERACIÓN | B59: estaciones | I59: Honorarios Administrativos P.M. | V59: =SUM(J59:U59) -> 0 | W59: =V59/V$6 -> #DIV/0! | Y59: 0 | Z59: 0 | AA59: 0 | AB59: 0 | AC59: 0 | AD59: 0 | AE59: 0 | AF59: 0 | AG59: 0 | AH59: 0 | AI59: 0 | AJ59: 0 | AK59: =SUM(Y59:AJ59) -> 0 | AL59: =AK59/AK$6 -> #DIV/0! | AM59: =IFERROR(AK59/V59-1,0) -> 0
A60: E - GASTOS DE OPERACIÓN | B60: estaciones | I60: Asistencia técnica | V60: =SUM(J60:U60) -> 0 | W60: =V60/V$6 -> #DIV/0! | Y60: 0 | Z60: 0 | AA60: 0 | AB60: 0 | AC60: 0 | AD60: 0 | AE60: 0 | AF60: 0 | AG60: 0 | AH60: 0 | AI60: 0 | AJ60: 0 | AK60: =SUM(Y60:AJ60) -> 0 | AL60: =AK60/AK$6 -> #DIV/0! | AM60: =IFERROR(AK60/V60-1,0) -> 0
A61: E - GASTOS DE OPERACIÓN | B61: estaciones | I61: Gastos no deducibles (sin requisitos fiscales) | V61: =SUM(J61:U61) -> 0 | W61: =V61/V$6 -> #DIV/0! | Y61: 0 | Z61: 0 | AA61: 0 | AB61: 0 | AC61: 0 | AD61: 0 | AE61: 0 | AF61: 0 | AG61: 0 | AH61: 0 | AI61: 0 | AJ61: 0 | AK61: =SUM(Y61:AJ61) -> 0 | AL61: =AK61/AK$6 -> #DIV/0! | AM61: =IFERROR(AK61/V61-1,0) -> 0
A62: E - GASTOS DE OPERACIÓN | B62: estaciones | I62: Papelería y artículos de oficina | V62: =SUM(J62:U62) -> 0 | W62: =V62/V$6 -> #DIV/0! | Y62: 0 | Z62: 0 | AA62: 0 | AB62: 0 | AC62: 0 | AD62: 0 | AE62: 0 | AF62: 0 | AG62: 0 | AH62: 0 | AI62: 0 | AJ62: 0 | AK62: =SUM(Y62:AJ62) -> 0 | AL62: =AK62/AK$6 -> #DIV/0! | AM62: =IFERROR(AK62/V62-1,0) -> 0
A63: E - GASTOS DE OPERACIÓN | B63: estaciones | I63: Faltantes | V63: =SUM(J63:U63) -> 0 | W63: =V63/V$6 -> #DIV/0! | Y63: 0 | Z63: 0 | AA63: 0 | AB63: 0 | AC63: 0 | AD63: 0 | AE63: 0 | AF63: 0 | AG63: 0 | AH63: 0 | AI63: 0 | AJ63: 0 | AK63: =SUM(Y63:AJ63) -> 0 | AL63: =AK63/AK$6 -> #DIV/0! | AM63: =IFERROR(AK63/V63-1,0) -> 0
A64: E - GASTOS DE OPERACIÓN | B64: estaciones | I64: Licencias y Permisos | V64: =SUM(J64:U64) -> 0 | W64: =V64/V$6 -> #DIV/0! | Y64: 0 | Z64: 0 | AA64: 0 | AB64: 0 | AC64: 0 | AD64: 0 | AE64: 0 | AF64: 0 | AG64: 0 | AH64: 0 | AI64: 0 | AJ64: 0 | AK64: =SUM(Y64:AJ64) -> 0 | AL64: =AK64/AK$6 -> #DIV/0! | AM64: =IFERROR(AK64/V64-1,0) -> 0
A65: E - GASTOS DE OPERACIÓN | B65: estaciones | I65: Licencias, Software, Antivirus | V65: =SUM(J65:U65) -> 0 | W65: =V65/V$6 -> #DIV/0! | Y65: 0 | Z65: 0 | AA65: 0 | AB65: 0 | AC65: 0 | AD65: 0 | AE65: 0 | AF65: 0 | AG65: 0 | AH65: 0 | AI65: 0 | AJ65: 0 | AK65: =SUM(Y65:AJ65) -> 0 | AL65: =AK65/AK$6 -> #DIV/0! | AM65: =IFERROR(AK65/V65-1,0) -> 0
A66: E - GASTOS DE OPERACIÓN | B66: estaciones | I66: Fletes Combustible | V66: =SUM(J66:U66) -> 0 | W66: =V66/V$6 -> #DIV/0! | Y66: 0 | Z66: 0 | AA66: 0 | AB66: 0 | AC66: 0 | AD66: 0 | AE66: 0 | AF66: 0 | AG66: 0 | AH66: 0 | AI66: 0 | AJ66: 0 | AK66: =SUM(Y66:AJ66) -> 0 | AL66: =AK66/AK$6 -> #DIV/0! | AM66: =IFERROR(AK66/V66-1,0) -> 0
A67: E - GASTOS DE OPERACIÓN | B67: estaciones | I67: Viáticos y gastos de viaje | V67: =SUM(J67:U67) -> 0 | W67: =V67/V$6 -> #DIV/0! | Y67: 0 | Z67: 0 | AA67: 0 | AB67: 0 | AC67: 0 | AD67: 0 | AE67: 0 | AF67: 0 | AG67: 0 | AH67: 0 | AI67: 0 | AJ67: 0 | AK67: =SUM(Y67:AJ67) -> 0 | AL67: =AK67/AK$6 -> #DIV/0! | AM67: =IFERROR(AK67/V67-1,0) -> 0
... A73: E - GASTOS DE OPERACIÓN | B73: estaciones | I73: Consumos Propios Combustibles | V73: =SUM(J73:U73) -> 0 | W73: =V73/V$6 -> #DIV/0! | Y73: 0 | Z73: 0 | AA73: 0 | AB73: 0 | AC73: 0 | AD73: 0 | AE73: 0 | AF73: 0 | AG73: 0 | AH73: 0 | AI73: 0 | AJ73: 0 | AK73: =SUM(Y73:AJ73) -> 0 | AL73: =AK73/AK$6 -> #DIV/0! | AM73: =IFERROR(AK73/V73-1,0) -> 0
I74: Renta Equipo de Sistemas
I75: Timbrado Facturas
I76: Uniformes
I77: Contratacion Empleados
I78: Seguros y fianzas
I79: Honorarios Legales P.F.
I80: Prediales
I81: Certificado para el cumplimiento SAT anexo 30 y 31
I82: Arrendamiento Tecnologico
I83: Asesoría en sistemas
I84: Combustibles Reembolsos
I85: Honorarios Admvos P.F.
... I89: Vigilancia y seguridad
A90: C - NOMINA | B90: estaciones | I90: C - NOMINA | V90: =SUM(V91:V105) -> 0 | W90: =V90/V$6 -> #DIV/0! | Y90: =SUM(Y91:Y105) -> 0 | Z90: =SUM(Z91:Z105) -> 0 | AA90: =SUM(AA91:AA105) -> 0 | AB90: =SUM(AB91:AB105) -> 0 | AC90: =SUM(AC91:AC105) -> 0 | AD90: =SUM(AD91:AD105) -> 0 | AE90: =SUM(AE91:AE105) -> 0 | AF90: =SUM(AF91:AF105) -> 0 | ... AK90: =SUM(AK91:AK105) -> 0 | AL90: =AK90/AK$6 -> #DIV/0! | AM90: =IFERROR(AK90/V90-1,0) -> 0
A91: C - NOMINA | B91: estaciones | I91: Aguinaldo | V91: =SUM(J91:U91) -> 0 | W91: =V91/V$6 -> #DIV/0! | AK91: =SUM(Y91:AJ91) -> 0 | AL91: =AK91/AK$6 -> #DIV/0! | AM91: =IFERROR(AK91/V91-1,0) -> 0
A92: C - NOMINA | B92: estaciones | I92: Compensaciones | V92: =SUM(J92:U92) -> 0 | W92: =V92/V$6 -> #DIV/0! | AK92: =SUM(Y92:AJ92) -> 0 | AL92: =AK92/AK$6 -> #DIV/0! | AM92: =IFERROR(AK92/V92-1,0) -> 0
A93: C - NOMINA | B93: estaciones | I93: Días festivos | V93: =SUM(J93:U93) -> 0 | W93: =V93/V$6 -> #DIV/0! | AK93: =SUM(Y93:AJ93) -> 0 | AL93: =AK93/AK$6 -> #DIV/0! | AM93: =IFERROR(AK93/V93-1,0) -> 0
A94: C - NOMINA | B94: estaciones | I94: Fondo de ahorro | V94: =SUM(J94:U94) -> 0 | W94: =V94/V$6 -> #DIV/0! | AK94: =SUM(Y94:AJ94) -> 0 | AL94: =AK94/AK$6 -> #DIV/0! | AM94: =IFERROR(AK94/V94-1,0) -> 0
A95: C - NOMINA | B95: estaciones | I95: Indemnizaciones | V95: =SUM(J95:U95) -> 0 | W95: =V95/V$6 -> #DIV/0! | AK95: =SUM(Y95:AJ95) -> 0 | AL95: =AK95/AK$6 -> #DIV/0! | AM95: =IFERROR(AK95/V95-1,0) -> 0
A96: C - NOMINA | B96: estaciones | I96: Premios de asistencia | V96: =SUM(J96:U96) -> 0 | W96: =V96/V$6 -> #DIV/0! | AK96: =SUM(Y96:AJ96) -> 0 | AL96: =AK96/AK$6 -> #DIV/0! | AM96: =IFERROR(AK96/V96-1,0) -> 0
A97: C - NOMINA | B97: estaciones | I97: Premios de puntualidad | V97: =SUM(J97:U97) -> 0 | W97: =V97/V$6 -> #DIV/0! | AK97: =SUM(Y97:AJ97) -> 0 | AL97: =AK97/AK$6 -> #DIV/0! | AM97: =IFERROR(AK97/V97-1,0) -> 0
A98: C - NOMINA | B98: estaciones | I98: Previsión social | V98: =SUM(J98:U98) -> 0 | W98: =V98/V$6 -> #DIV/0! | AK98: =SUM(Y98:AJ98) -> 0 | AL98: =AK98/AK$6 -> #DIV/0! | AM98: =IFERROR(AK98/V98-1,0) -> 0
A99: C - NOMINA | B99: estaciones | I99: Prima dominical | V99: =SUM(J99:U99) -> 0 | W99: =V99/V$6 -> #DIV/0! | AK99: =SUM(Y99:AJ99) -> 0 | AL99: =AK99/AK$6 -> #DIV/0! | AM99: =IFERROR(AK99/V99-1,0) -> 0
A100: C - NOMINA | B100: estaciones | I100: Prima vacacional | V100: =SUM(J100:U100) -> 0 | W100: =V100/V$6 -> #DIV/0! | AK100: =SUM(Y100:AJ100) -> 0 | AL100: =AK100/AK$6 -> #DIV/0! | AM100: =IFERROR(AK100/V100-1,0) -> 0
A101: C - NOMINA | B101: estaciones | I101: Primas de antigüedad | V101: =SUM(J101:U101) -> 0 | W101: =V101/V$6 -> #DIV/0! | AK101: =SUM(Y101:AJ101) -> 0 | AL101: =AK101/AK$6 -> #DIV/0! | AM101: =IFERROR(AK101/V101-1,0) -> 0
A102: C - NOMINA | B102: estaciones | I102: PTU | V102: =SUM(J102:U102) -> 0 | W102: =V102/V$6 -> #DIV/0! | AK102: =SUM(Y102:AJ102) -> 0 | AL102: =AK102/AK$6 -> #DIV/0! | AM102: =IFERROR(AK102/V102-1,0) -> 0
... A105: C - NOMINA | B105: estaciones | I105: Vacaciones | V105: =SUM(J105:U105) -> 0 | W105: =V105/V$6 -> #DIV/0! | AK105: =SUM(Y105:AJ105) -> 0 | AL105: =AK105/AK$6 -> #DIV/0! | AM105: =IFERROR(AK105/V105-1,0) -> 0
A106: D - COSTO SOCIAL | B106: estaciones | I106: D - COSTO SOCIAL | V106: =SUM(V107:V110) -> 0 | W106: =V106/V$6 -> #DIV/0! | Y106: =SUM(Y107:Y110) -> 0 | Z106: =SUM(Z107:Z110) -> 0 | AA106: =SUM(AA107:AA110) -> 0 | AB106: =SUM(AB107:AB110) -> 0 | AC106: =SUM(AC107:AC110) -> 0 | AD106: =SUM(AD107:AD110) -> 0 | AE106: =SUM(AE107:AE110) -> 0 | AF106: =SUM(AF107:AF110) -> 0 | ... AK106: =SUM(AK107:AK110) -> 0 | AL106: =AK106/AK$6 -> #DIV/0! | AM106: =IFERROR(AK106/V106-1,0) -> 0
A107: D - COSTO SOCIAL | B107: estaciones | I107: Aportaciones al infonavit | V107: =SUM(J107:U107) -> 0 | W107: =V107/V$6 -> #DIV/0! | AK107: =SUM(Y107:AJ107) -> 0 | AL107: =AK107/AK$6 -> #DIV/0! | AM107: =IFERROR(AK107/V107-1,0) -> 0
A108: D - COSTO SOCIAL | B108: estaciones | I108: Aportaciones al SAR | V108: =SUM(J108:U108) -> 0 | W108: =V108/V$6 -> #DIV/0! | AK108: =SUM(Y108:AJ108) -> 0 | AL108: =AK108/AK$6 -> #DIV/0! | AM108: =IFERROR(AK108/V108-1,0) -> 0
A109: D - COSTO SOCIAL | B109: estaciones | I109: Cuotas al IMSS | V109: =SUM(J109:U109) -> 0 | W109: =V109/V$6 -> #DIV/0! | AK109: =SUM(Y109:AJ109) -> 0 | AL109: =AK109/AK$6 -> #DIV/0! | AM109: =IFERROR(AK109/V109-1,0) -> 0
A110: D - COSTO SOCIAL | B110: estaciones | I110: Impuesto Estatal | V110: =SUM(J110:U110) -> 0 | W110: =V110/V$6 -> #DIV/0! | AK110: =SUM(Y110:AJ110) -> 0 | AL110: =AK110/AK$6 -> #DIV/0! | AM110: =IFERROR(AK110/V110-1,0) -> 0
A111: F - MANTENIMIENTO | B111: estaciones | C111: Mantenimiento de Imagen | I111: F - MANTENIMIENTO | V111: =SUM(V112:V114) -> 0 | W111: =V111/V$6 -> #DIV/0! | Y111: =SUM(Y112:Y114) -> 0 | Z111: =SUM(Z112:Z114) -> 0 | AA111: =SUM(AA112:AA114) -> 0 | AB111: =SUM(AB112:AB114) -> 0 | AC111: =SUM(AC112:AC114) -> 0 | AD111: =SUM(AD112:AD114) -> 0 | AE111: =SUM(AE112:AE114) -> 0 | AF111: =SUM(AF112:AF114) -> 0 | ... AK111: =SUM(AK112:AK114) -> 0 | AL111: =AK111/AK$6 -> #DIV/0! | AM111: =IFERROR(AK111/V111-1,0) -> 0
A112: F - MANTENIMIENTO | B112: estaciones | I112: Mantenimiento de Equipo de Computo | V112: =SUM(J112:U112) -> 0 | W112: =V112/V$6 -> #DIV/0! | Y112: 0 | Z112: 0 | AA112: 0 | AB112: 0 | AC112: 0 | AD112: 0 | AE112: 0 | AF112: 0 | AG112: 0 | AH112: 0 | AI112: 0 | AJ112: 0 | AK112: =SUM(Y112:AJ112) -> 0 | AL112: =AK112/AK$6 -> #DIV/0! | AM112: =IFERROR(AK112/V112-1,0) -> 0
A113: F - MANTENIMIENTO | B113: estaciones | I113: Certificacion SASISOPA | V113: =SUM(J113:U113) -> 0 | W113: =V113/V$6 -> #DIV/0! | Y113: 0 | Z113: 0 | AA113: 0 | AB113: 0 | AC113: 0 | AD113: 0 | AE113: 0 | AF113: 0 | AG113: 0 | AH113: 0 | AI113: 0 | AJ113: 0 | AK113: =SUM(Y113:AJ113) -> 0 | AL113: =AK113/AK$6 -> #DIV/0! | AM113: =IFERROR(AK113/V113-1,0) -> 0
...

Sheet Z

Sheet EDO RESULTADOS MISMAS EST
I1: Mantenimiento de Imagen | J1: 2 | K1: 3 | L1: 4 | M1: 5 | N1: 6 | O1: 7 | Y1: 2 | Z1: 3 | AA1: 4 | AB1: 5 | AC1: 6 | AD1: 7 | AM1: 17 | AQ1: 17
J2: 2025 | V2: TOTAL ANUAL | Y2: 2026 | AK2: PPTO ANUAL MISMAS EST | AO2: PPTO ANUAL TODAS ES
J3: ENE | K3: FEB | L3: MAR | M3: ABR | N3: MAY | O3: JUN | P3: JUL | Q3: AGO | R3: SEP | S3: OCT | T3: NOV | U3: DIC | V3: 2025 | W3: % Part | Y3: ENE | Z3: FEB | AA3: MAR | AB3: ABR | AC3: MAY | AD3: JUN | AE3: JUL | AF3: AGO | AG3: SEP | AH3: OCT | AI3: NOV | AJ3: DIC | AK3: 2026 | AL3: % Part | AM3: Var vs AA% | AO3: 2024 | AP3: % Part | AQ3: Var vs AA%
I4: INGRESOS
A6: A - INGRESOS | E6: ( mas ) | I6: A - INGRESOS | J6: ='TOTAL ESTACIONES'!J6 -> 26878636 | K6: ='TOTAL ESTACIONES'!K6 -> 25528487 | L6: ='TOTAL ESTACIONES'!L6 -> 28307270 | M6: ='TOTAL ESTACIONES'!M6 -> 26579702 | N6: ='TOTAL ESTACIONES'!N6 -> 27359376 | O6: ='TOTAL ESTACIONES'!O6 -> 26727235 | P6: ='TOTAL ESTACIONES'!P6 -> 27912533 | Q6: ='TOTAL ESTACIONES'!Q6 -> 28233403 | ... AM6: ='TOTAL ESTACIONES'!AM6 -> 0.088549483 | AO6: 4.4076062e+09 | AP6: 1 | AQ6: 0.16822054
A7: A - INGRESOS | B7: estaciones | C7: INGRESOS MAGNA | D7: INGRESOS FORANEOS MAGNA | I7: MAXIMA | J7: ='TOTAL ESTACIONES'!J7 -> 19095888 | K7: ='TOTAL ESTACIONES'!K7 -> 17878224 | L7: ='TOTAL ESTACIONES'!L7 -> 19531849 | M7: ='TOTAL ESTACIONES'!M7 -> 18128009 | N7: ='TOTAL ESTACIONES'!N7 -> 18229490 | O7: ='TOTAL ESTACIONES'!O7 -> 18404815 | P7: ='TOTAL ESTACIONES'!P7 -> 19054499 | Q7: ='TOTAL ESTACIONES'!Q7 -> 19328904 | ... AM7: ='TOTAL ESTACIONES'!AM7 -> 0.095949069 | AO7: 3.4888525e+09 | AP7: 0.79155268 | AQ7: 0.14554128
A8: A - INGRESOS | B8: estaciones | C8: INGRESOS PREMIUM | D8: INGRESOS FORANEOS PREMIUM | I8: SUPER | J8: ='TOTAL ESTACIONES'!J8 -> 5623556 | K8: ='TOTAL ESTACIONES'!K8 -> 5345115 | L8: ='TOTAL ESTACIONES'!L8 -> 6151225 | M8: ='TOTAL ESTACIONES'!M8 -> 5648910 | N8: ='TOTAL ESTACIONES'!N8 -> 6559926 | O8: ='TOTAL ESTACIONES'!O8 -> 5655884 | P8: ='TOTAL ESTACIONES'!P8 -> 5857615 | Q8: ='TOTAL ESTACIONES'!Q8 -> 6197597 | ... AM8: ='TOTAL ESTACIONES'!AM8 -> 0.078467684 | AO8: 3.5285587e+08 | AP8: 0.080056124 | AQ8: 0.26460768
A9: A - INGRESOS | B9: estaciones | C9: INGRESOS DIESEL | D9: INGRESOS FORANEOS DIESEL | I9: DIESEL | J9: ='TOTAL ESTACIONES'!J9 -> 2090208 | K9: ='TOTAL ESTACIONES'!K9 -> 2235534 | L9: ='TOTAL ESTACIONES'!L9 -> 2555308 | M9: ='TOTAL ESTACIONES'!M9 -> 2773749 | N9: ='TOTAL ESTACIONES'!N9 -> 2487478 | O9: ='TOTAL ESTACIONES'!O9 -> 2589338 | P9: ='TOTAL ESTACIONES'!P9 -> 2919953 | Q9: ='TOTAL ESTACIONES'!Q9 -> 2619067 | ... AM9: ='TOTAL ESTACIONES'!AM9 -> 0.06380043 | AO9: 5.6589782e+08 | AP9: 0.12839119 | AQ9: 0.3070746
I10: INGRESOS ACEITES Y LUBRICANTES | J10: ='TOTAL ESTACIONES'!J10 -> 68984 | K10: ='TOTAL ESTACIONES'!K10 -> 69614 | L10: ='TOTAL ESTACIONES'!L10 -> 68888 | M10: ='TOTAL ESTACIONES'!M10 -> 29034 | N10: ='TOTAL ESTACIONES'!N10 -> 82482 | O10: ='TOTAL ESTACIONES'!O10 -> 77198 | P10: ='TOTAL ESTACIONES'!P10 -> 80466 | Q10: ='TOTAL ESTACIONES'!Q10 -> 87835 | ... AM10: ='TOTAL ESTACIONES'!AM10 -> -0.11393663 | AO10: 0 | AP10: 0 | AQ10: -1
I11: SOBRANTE COMBUSTIBLES | J11: ='TOTAL ESTACIONES'!J11 -> 0 | K11: ='TOTAL ESTACIONES'!K11 -> 0 | L11: ='TOTAL ESTACIONES'!L11 -> 0 | M11: ='TOTAL ESTACIONES'!M11 -> 0 | N11: ='TOTAL ESTACIONES'!N11 -> 0 | O11: ='TOTAL ESTACIONES'!O11 -> 0 | P11: ='TOTAL ESTACIONES'!P11 -> 0 | Q11: ='TOTAL ESTACIONES'!Q11 -> 0 | ... AM11: ='TOTAL ESTACIONES'!AM11 -> -1 | AO11: 0 | AP11: 0 | AQ11: -1
A12: B - COSTO DE VENTA | E12: ( menos ) | I12: B - COSTO DE VENTA | J12: ='TOTAL ESTACIONES'!J12 -> 24443667 | K12: ='TOTAL ESTACIONES'!K12 -> 22953018 | L12: ='TOTAL ESTACIONES'!L12 -> 25490800 | M12: ='TOTAL ESTACIONES'!M12 -> 23658529 | N12: ='TOTAL ESTACIONES'!N12 -> 24196460 | O12: ='TOTAL ESTACIONES'!O12 -> 23804842 | P12: ='TOTAL ESTACIONES'!P12 -> 25118023 | Q12: ='TOTAL ESTACIONES'!Q12 -> 25414036 | ... AM12: ='TOTAL ESTACIONES'!AM12 -> 0.092700589 | AO12: 3.7568617e+09 | AP12: 0.85235875 | AQ12: 0.16747315
A13: B - COSTO DE VENTA | C13: COSTO MAGNA | D13: COSTO FORANEO MAGNA | I13: GASOLINA REGULAR | J13: ='TOTAL ESTACIONES'!J13 -> 17491983 | K13: ='TOTAL ESTACIONES'!K13 -> 16105749 | L13: ='TOTAL ESTACIONES'!L13 -> 17633587 | M13: ='TOTAL ESTACIONES'!M13 -> 16414267 | N13: ='TOTAL ESTACIONES'!N13 -> 16550960 | O13: ='TOTAL ESTACIONES'!O13 -> 16752932 | P13: ='TOTAL ESTACIONES'!P13 -> 17303449 | Q13: ='TOTAL ESTACIONES'!Q13 -> 17528380 | ... AM13: ='TOTAL ESTACIONES'!AM13 -> 0.10115578 | AO13: 3.5232571e+09 | AP13: 0.7993584 | AQ13: 0.13050349
A14: B - COSTO DE VENTA | C14: COSTO PREMIUM | D14: COSTO FORANEO PREMIUM | I14: GASOLINA PREMIUM | J14: ='TOTAL ESTACIONES'!J14 -> 4933868 | K14: ='TOTAL ESTACIONES'!K14 -> 4692149 | L14: ='TOTAL ESTACIONES'!L14 -> 5366599 | M14: ='TOTAL ESTACIONES'!M14 -> 4909439 | N14: ='TOTAL ESTACIONES'!N14 -> 5542662 | O14: ='TOTAL ESTACIONES'!O14 -> 4823156 | P14: ='TOTAL ESTACIONES'!P14 -> 5160135 | Q14: ='TOTAL ESTACIONES'!Q14 -> 5519068 | ... AM14: ='TOTAL ESTACIONES'!AM14 -> 0.068487031 | AO14: 3.4716629e+08 | AP14: 0.078765269 | AQ14: 0.24745089
A15: B - COSTO DE VENTA | C15: COSTO DIESEL | D15: COSTO FORANEO DIESEL | I15: DIESEL | J15: ='TOTAL ESTACIONES'!J15 -> 1953610 | K15: ='TOTAL ESTACIONES'!K15 -> 2086291 | L15: ='TOTAL ESTACIONES'!L15 -> 2425049 | M15: ='TOTAL ESTACIONES'!M15 -> 2457800 | N15: ='TOTAL ESTACIONES'!N15 -> 2174432 | O15: ='TOTAL ESTACIONES'!O15 -> 2274518 | P15: ='TOTAL ESTACIONES'!P15 -> 2653742 | Q15: ='TOTAL ESTACIONES'!Q15 -> 2343362 | ... AM15: ='TOTAL ESTACIONES'!AM15 -> 0.065487529 | AO15: 5.0123784e+08 | AP15: 0.1137211 | AQ15: 0.29638109
A16: B - COSTO DE VENTA | C16: Merma Magna | I16: MERMA GASOLINA REGULAR | J16: ='TOTAL ESTACIONES'!J16 -> 0 | K16: ='TOTAL ESTACIONES'!K16 -> 0 | L16: ='TOTAL ESTACIONES'!L16 -> 49100 | M16: ='TOTAL ESTACIONES'!M16 -> 0 | N16: ='TOTAL ESTACIONES'!N16 -> 0 | O16: ='TOTAL ESTACIONES'!O16 -> 0 | P16: ='TOTAL ESTACIONES'!P16 -> 0 | Q16: ='TOTAL ESTACIONES'!Q16 -> 0 | ... AM16: ='TOTAL ESTACIONES'!AM16 -> -1 | AO16: 0 | AP16: 0 | AQ16: -1
A17: B - COSTO DE VENTA | C17: Merma Premium | I17: MERMA GASOLINA PREMIUM | J17: ='TOTAL ESTACIONES'!J17 -> 7882 | K17: ='TOTAL ESTACIONES'!K17 -> 14264 | L17: ='TOTAL ESTACIONES'!L17 -> 0 | M17: ='TOTAL ESTACIONES'!M17 -> 0 | N17: ='TOTAL ESTACIONES'!N17 -> 16710 | O17: ='TOTAL ESTACIONES'!O17 -> 0 | P17: ='TOTAL ESTACIONES'!P17 -> 0 | Q17: ='TOTAL ESTACIONES'!Q17 -> 3686 | ... AM17: ='TOTAL ESTACIONES'!AM17 -> -1 | AO17: 0 | AP17: 0 | AQ17: -1
A18: B - COSTO DE VENTA | C18: Merma Diesel | I18: MERMA DIESEL | J18: ='TOTAL ESTACIONES'!J18 -> 0 | K18: ='TOTAL ESTACIONES'!K18 -> 0 | L18: ='TOTAL ESTACIONES'!L18 -> 0 | M18: ='TOTAL ESTACIONES'!M18 -> 0 | N18: ='TOTAL ESTACIONES'!N18 -> 0 | O18: ='TOTAL ESTACIONES'!O18 -> 0 | P18: ='TOTAL ESTACIONES'!P18 -> 0 | Q18: ='TOTAL ESTACIONES'!Q18 -> 0 | ... AM18: ='TOTAL ESTACIONES'!AM18 -> -1 | AO18: 0 | AP18: 0 | AQ18: -1
A19: B - COSTO DE VENTA | C19: ADITIVO PARA GASOLINA TMAXIMA (REGULAR) | D19: ADITIVO PARA GASOLINA TMAXIMA( REGULAR) | I19: ADITIVO TOTAL POWER GASOLINA REG | J19: ='TOTAL ESTACIONES'!J19 -> 37098 | K19: ='TOTAL ESTACIONES'!K19 -> 30373 | L19: ='TOTAL ESTACIONES'!L19 -> 39778 | M19: ='TOTAL ESTACIONES'!M19 -> 31691 | N19: ='TOTAL ESTACIONES'!N19 -> 35405 | O19: ='TOTAL ESTACIONES'!O19 -> 33757 | P19: ='TOTAL ESTACIONES'!P19 -> 37244 | Q19: ='TOTAL ESTACIONES'!Q19 -> 38255 | ... AM19: ='TOTAL ESTACIONES'!AM19 -> -1 | AO19: 0 | AP19: 0 | AQ19: -1
A20: B - COSTO DE VENTA | C20: ADITIVO PARA GASOLINA TSUPER (PREMIUM) | I20: ADITIVO TOTAL POWER GASOLINA PREM | J20: ='TOTAL ESTACIONES'!J20 -> 10383 | K20: ='TOTAL ESTACIONES'!K20 -> 7510 | L20: ='TOTAL ESTACIONES'!L20 -> 11713 | M20: ='TOTAL ESTACIONES'!M20 -> 9665 | N20: ='TOTAL ESTACIONES'!N20 -> 10014 | O20: ='TOTAL ESTACIONES'!O20 -> 10264 | P20: ='TOTAL ESTACIONES'!P20 -> 11873 | Q20: ='TOTAL ESTACIONES'!Q20 -> 9035 | ... AM20: ='TOTAL ESTACIONES'!AM20 -> -1 | AO20: 0 | AP20: 0 | AQ20: -1
A21: B - COSTO DE VENTA | C21: FLETE MAGNA | I21: FLETE GASOLINA REGULAR | J21: ='TOTAL ESTACIONES'!J21 -> 0 | K21: ='TOTAL ESTACIONES'!K21 -> 0 | L21: ='TOTAL ESTACIONES'!L21 -> 0 | M21: ='TOTAL ESTACIONES'!M21 -> 0 | N21: ='TOTAL ESTACIONES'!N21 -> 0 | O21: ='TOTAL ESTACIONES'!O21 -> 0 | P21: ='TOTAL ESTACIONES'!P21 -> 0 | Q21: ='TOTAL ESTACIONES'!Q21 -> 0 | ... AM21: ='TOTAL ESTACIONES'!AM21 -> 0 | AO21: 0 | AP21: 0 | AQ21: -1
A22: B - COSTO DE VENTA | C22: FLETE PREMIUM | I22: FLETE GASOLINA PREMIUM | J22: ='TOTAL ESTACIONES'!J22 -> 0 | K22: ='TOTAL ESTACIONES'!K22 -> 0 | L22: ='TOTAL ESTACIONES'!L22 -> 0 | M22: ='TOTAL ESTACIONES'!M22 -> 0 | N22: ='TOTAL ESTACIONES'!N22 -> 0 | O22: ='TOTAL ESTACIONES'!O22 -> 0 | P22: ='TOTAL ESTACIONES'!P22 -> 0 | Q22: ='TOTAL ESTACIONES'!Q22 -> 0 | ... AM22: ='TOTAL ESTACIONES'!AM22 -> 0 | AO22: 0 | AP22: 0 | AQ22: -1
A23: B - COSTO DE VENTA | C23: FLETE DIESEL | I23: FLETE DIESEL | J23: ='TOTAL ESTACIONES'!J23 -> 0 | K23: ='TOTAL ESTACIONES'!K23 -> 0 | L23: ='TOTAL ESTACIONES'!L23 -> 0 | M23: ='TOTAL ESTACIONES'!M23 -> 0 | N23: ='TOTAL ESTACIONES'!N23 -> 0 | O23: ='TOTAL ESTACIONES'!O23 -> 0 | P23: ='TOTAL ESTACIONES'!P23 -> 0 | Q23: ='TOTAL ESTACIONES'!Q23 -> 0 | ... AM23: ='TOTAL ESTACIONES'!AM23 -> 0 | AO23: 0 | AP23: 0 | AQ23: -1
A24: B - COSTO DE VENTA | C24: Estimulo IEPS Magna | D24: INGRESOS FORANEOS MAGNA | I24: ESTIMULO REGULAR | J24: ='TOTAL ESTACIONES'!J24 -> 0 | K24: ='TOTAL ESTACIONES'!K24 -> 0 | L24: ='TOTAL ESTACIONES'!L24 -> 267 | M24: ='TOTAL ESTACIONES'!M24 -> 0 | N24: ='TOTAL ESTACIONES'!N24 -> 0 | O24: ='TOTAL ESTACIONES'!O24 -> 0 | P24: ='TOTAL ESTACIONES'!P24 -> 0 | Q24: ='TOTAL ESTACIONES'!Q24 -> 0 | ... AM24: ='TOTAL ESTACIONES'!AM24 -> -1 | AO24: -5.7784199e+08 | AP24: -0.13110109 | AQ24: 0.066558616
I25: ESTIMULO PREMIUM | J25: ='TOTAL ESTACIONES'!J25 -> 0 | K25: ='TOTAL ESTACIONES'!K25 -> 0 | L25: ='TOTAL ESTACIONES'!L25 -> 1204 | M25: ='TOTAL ESTACIONES'!M25 -> 2070 | N25: ='TOTAL ESTACIONES'!N25 -> 0 | O25: ='TOTAL ESTACIONES'!O25 -> 0 | P25: ='TOTAL ESTACIONES'!P25 -> 2068 | Q25: ='TOTAL ESTACIONES'!Q25 -> 0 | ... AM25: ='TOTAL ESTACIONES'!AM25 -> -1 | AO25: -36957483 | AP25: -0.0083849329 | AQ25: 0.064257395
I26: SOBRANTE MAGNA | J26: ='TOTAL ESTACIONES'!J26 -> -16996 | K26: ='TOTAL ESTACIONES'!K26 -> -26879 | L26: ='TOTAL ESTACIONES'!L26 -> -49360 | M26: ='TOTAL ESTACIONES'!M26 -> -134972 | N26: ='TOTAL ESTACIONES'!N26 -> -145599 | O26: ='TOTAL ESTACIONES'!O26 -> -112171 | P26: ='TOTAL ESTACIONES'!P26 -> -72748 | Q26: ='TOTAL ESTACIONES'!Q26 -> -71093 | ... AM26: ='TOTAL ESTACIONES'!AM26 -> -1 | AO26: 0 | AP26: 0 | AQ26: -1
I27: SOBRANTE PREMIUM | J27: ='TOTAL ESTACIONES'!J27 -> -15808 | K27: ='TOTAL ESTACIONES'!K27 -> -8530 | L27: ='TOTAL ESTACIONES'!L27 -> -22247 | M27: ='TOTAL ESTACIONES'!M27 -> -24612 | N27: ='TOTAL ESTACIONES'!N27 -> -30658 | O27: ='TOTAL ESTACIONES'!O27 -> -20889 | P27: ='TOTAL ESTACIONES'!P27 -> -26813 | Q27: ='TOTAL ESTACIONES'!Q27 -> -8260 | ... AM27: ='TOTAL ESTACIONES'!AM27 -> -1 | AO27: 6.507445e+08 | AP27: 0.14764125 | AQ27: 0.17255416
I28: SOBRANTE DIESEL | J28: ='TOTAL ESTACIONES'!J28 -> -6436 | K28: ='TOTAL ESTACIONES'!K28 -> 0 | L28: ='TOTAL ESTACIONES'!L28 -> -18941 | M28: ='TOTAL ESTACIONES'!M28 -> -22943 | N28: ='TOTAL ESTACIONES'!N28 -> -9722 | O28: ='TOTAL ESTACIONES'!O28 -> -17371 | P28: ='TOTAL ESTACIONES'!P28 -> -18629 | Q28: ='TOTAL ESTACIONES'!Q28 -> -16467 | ... AM28: ='TOTAL ESTACIONES'!AM28 -> -1 | AO28: 5.4343746e+08 | AP28: #REF! | AQ28: 0.13532128
I29: COSTO ACEITES Y LUBRICANTES | J29: ='TOTAL ESTACIONES'!J29 -> 48083 | K29: ='TOTAL ESTACIONES'!K29 -> 52091 | L29: ='TOTAL ESTACIONES'!L29 -> 54051 | M29: ='TOTAL ESTACIONES'!M29 -> 16124 | N29: ='TOTAL ESTACIONES'!N29 -> 52256 | O29: ='TOTAL ESTACIONES'!O29 -> 60646 | P29: ='TOTAL ESTACIONES'!P29 -> 67702 | Q29: ='TOTAL ESTACIONES'!Q29 -> 68070 | ... AM29: ='TOTAL ESTACIONES'!AM29 -> -0.10860852 | AO29: 42647062 | AP29: #REF! | AQ29: 0.48513341
I30: BONIFICACION COMPRA DE COMBUSTIBLE MAGNA | J30: ='TOTAL ESTACIONES'!J30 -> 0 | K30: ='TOTAL ESTACIONES'!K30 -> 0 | L30: ='TOTAL ESTACIONES'!L30 -> 0 | M30: ='TOTAL ESTACIONES'!M30 -> 0 | N30: ='TOTAL ESTACIONES'!N30 -> 0 | O30: ='TOTAL ESTACIONES'!O30 -> 0 | P30: ='TOTAL ESTACIONES'!P30 -> 0 | Q30: ='TOTAL ESTACIONES'!Q30 -> 0 | ... AM30: ='TOTAL ESTACIONES'!AM30 -> 0 | AO30: 64659974 | AP30: #REF! | AQ30: 0.41061113
I31: BONIFICACION COMPRA DE COMBUSTIBLE PREMIUM | J31: ='TOTAL ESTACIONES'!J31 -> 0 | K31: ='TOTAL ESTACIONES'!K31 -> 0 | L31: ='TOTAL ESTACIONES'!L31 -> 0 | M31: ='TOTAL ESTACIONES'!M31 -> 0 | N31: ='TOTAL ESTACIONES'!N31 -> 0 | O31: ='TOTAL ESTACIONES'!O31 -> 0 | P31: ='TOTAL ESTACIONES'!P31 -> 0 | Q31: ='TOTAL ESTACIONES'!Q31 -> 0 | ... AM31: ='TOTAL ESTACIONES'!AM31 -> 0 | AO31: 0 | AP31: #REF! | AQ31: -1
I32: BONIFICACION COMPRA DE COMBUSTIBLE DIESEL | J32: 0 | K32: ='TOTAL ESTACIONES'!K32 -> 0 | L32: ='TOTAL ESTACIONES'!L32 -> 0 | M32: ='TOTAL ESTACIONES'!M32 -> 0 | N32: ='TOTAL ESTACIONES'!N32 -> 0 | O32: ='TOTAL ESTACIONES'!O32 -> 0 | P32: ='TOTAL ESTACIONES'!P32 -> 0 | Q32: ='TOTAL ESTACIONES'!Q32 -> 0 | R32: ='TOTAL ESTACIONES'!R32 -> 0 | ... AM32: ='TOTAL ESTACIONES'!AM32 -> 0 | AO32: 2.4593624e+08 | AQ32: 0.1359541
I33: MARGEN DE UTILIDAD | J33: ='TOTAL ESTACIONES'!J33 -> 2434969 | K33: ='TOTAL ESTACIONES'!K33 -> 2575469 | L33: ='TOTAL ESTACIONES'!L33 -> 2816470 | M33: ='TOTAL ESTACIONES'!M33 -> 2921173 | N33: ='TOTAL ESTACIONES'!N33 -> 3162916 | O33: ='TOTAL ESTACIONES'!O33 -> 2922393 | P33: ='TOTAL ESTACIONES'!P33 -> 2794510 | Q33: ='TOTAL ESTACIONES'!Q33 -> 2819367 | ... AM33: ='TOTAL ESTACIONES'!AM33 -> 0.052059696 | AO33: 2.0184766e+08 | AP33: 0.045795303 | AQ33: 0.11498405 | AR33: =+AK33-V33 -> 1752691.5
I34: *Regular | J34: ='TOTAL ESTACIONES'!J34 -> 1583804 | K34: ='TOTAL ESTACIONES'!K34 -> 1768980 | L34: ='TOTAL ESTACIONES'!L34 -> 1858476 | M34: ='TOTAL ESTACIONES'!M34 -> 1817025 | N34: ='TOTAL ESTACIONES'!N34 -> 1788723 | O34: ='TOTAL ESTACIONES'!O34 -> 1730298 | P34: ='TOTAL ESTACIONES'!P34 -> 1786554 | Q34: ='TOTAL ESTACIONES'!Q34 -> 1833363 | ... AM34: ='TOTAL ESTACIONES'!AM34 -> 0.050590609 | AO34: 17513400 | AP34: 0.0039734494 | AQ34: 0.2160961
I35: *Premium | J35: ='TOTAL ESTACIONES'!J35 -> 687232 | K35: ='TOTAL ESTACIONES'!K35 -> 639721 | L35: ='TOTAL ESTACIONES'!L35 -> 793954 | M35: ='TOTAL ESTACIONES'!M35 -> 752348 | N35: ='TOTAL ESTACIONES'!N35 -> 1021198 | O35: ='TOTAL ESTACIONES'!O35 -> 843354 | P35: ='TOTAL ESTACIONES'!P35 -> 710352 | Q35: ='TOTAL ESTACIONES'!Q35 -> 674069 | ... AM35: ='TOTAL ESTACIONES'!AM35 -> 0.096472781 | AO35: 26575182 | AP35: 0.0060293911 | AQ35: 0.26135799
I36: *Diesel | J36: ='TOTAL ESTACIONES'!J36 -> 143034 | K36: ='TOTAL ESTACIONES'!K36 -> 149243 | L36: ='TOTAL ESTACIONES'!L36 -> 149199 | M36: ='TOTAL ESTACIONES'!M36 -> 338891 | N36: ='TOTAL ESTACIONES'!N36 -> 322767 | O36: ='TOTAL ESTACIONES'!O36 -> 332192 | P36: ='TOTAL ESTACIONES'!P36 -> 284840 | Q36: ='TOTAL ESTACIONES'!Q36 -> 292173 | ... AM36: ='TOTAL ESTACIONES'!AM36 -> -0.059416968 | AO36: 2.6459886 | AQ36: 0.029597448
I37: *Otros Conceptos | J37: ='TOTAL ESTACIONES'!J37 -> 20901 | K37: ='TOTAL ESTACIONES'!K37 -> 17524 | L37: ='TOTAL ESTACIONES'!L37 -> 14837 | M37: ='TOTAL ESTACIONES'!M37 -> 12910 | N37: ='TOTAL ESTACIONES'!N37 -> 30226 | O37: ='TOTAL ESTACIONES'!O37 -> 16552 | P37: ='TOTAL ESTACIONES'!P37 -> 12763 | Q37: ='TOTAL ESTACIONES'!Q37 -> 19765 | ... AM37: ='TOTAL ESTACIONES'!AM37 -> -1
I38: * Aceites y Lubricantes | J38: ='TOTAL ESTACIONES'!J38 -> 0 | K38: ='TOTAL ESTACIONES'!K38 -> 0 | L38: ='TOTAL ESTACIONES'!L38 -> 0 | M38: ='TOTAL ESTACIONES'!M38 -> 0 | N38: ='TOTAL ESTACIONES'!N38 -> 0 | O38: ='TOTAL ESTACIONES'!O38 -> 0 | P38: ='TOTAL ESTACIONES'!P38 -> 0 | Q38: ='TOTAL ESTACIONES'!Q38 -> 0 | ... AM38: ='TOTAL ESTACIONES'!AM38 -> 0 | AO38: 2.6923149 | AP38: 6.108338e-10 | AQ38: 0.03693009
I39: Litros vendidos | J39: ='TOTAL ESTACIONES'!J39 -> 1223164 | K39: ='TOTAL ESTACIONES'!K39 -> 1160892 | L39: ='TOTAL ESTACIONES'!L39 -> 1313320 | M39: ='TOTAL ESTACIONES'!M39 -> 1240762 | N39: ='TOTAL ESTACIONES'!N39 -> 1272351 | O39: ='TOTAL ESTACIONES'!O39 -> 1247404 | P39: ='TOTAL ESTACIONES'!P39 -> 1302246 | Q39: ='TOTAL ESTACIONES'!Q39 -> 1316933 | ... AM39: ='TOTAL ESTACIONES'!AM39 -> 0.048636775 | AO39: 2.4351104 | AP39: 5.5247911e-10 | AQ39: 0.11346523 | AR39: =+AK39/12 -> 1366631.3 | AS39: AUMENTOEN VTA GOMEZ A 1,365M
I40: Maxima | J40: ='TOTAL ESTACIONES'!J40 -> 1223164 | K40: ='TOTAL ESTACIONES'!K40 -> 830539 | L40: ='TOTAL ESTACIONES'!L40 -> 933279 | M40: ='TOTAL ESTACIONES'!M40 -> 873321 | N40: ='TOTAL ESTACIONES'!N40 -> 878218 | O40: ='TOTAL ESTACIONES'!O40 -> 887806 | P40: ='TOTAL ESTACIONES'!P40 -> 918225 | Q40: ='TOTAL ESTACIONES'!Q40 -> 931120 | ... AM40: ='TOTAL ESTACIONES'!AM40 -> 0.027932192 | AO40: 2.4330962 | AP40: 5.5202214e-10 | AQ40: 0.11307939
I41: Super | J41: ='TOTAL ESTACIONES'!J41 -> 887027 | K41: ='TOTAL ESTACIONES'!K41 -> 231283 | L41: ='TOTAL ESTACIONES'!L41 -> 266800 | M41: ='TOTAL ESTACIONES'!M41 -> 244981 | N41: ='TOTAL ESTACIONES'!N41 -> 284526 | O41: ='TOTAL ESTACIONES'!O41 -> 245926 | P41: ='TOTAL ESTACIONES'!P41 -> 256948 | Q41: ='TOTAL ESTACIONES'!Q41 -> 271880 | ... AM41: ='TOTAL ESTACIONES'!AM41 -> -0.14710953
E42: ( menos ) | I42: Diesel | J42: ='TOTAL ESTACIONES'!J42 -> 243300 | K42: ='TOTAL ESTACIONES'!K42 -> 99070 | L42: ='TOTAL ESTACIONES'!L42 -> 113241 | M42: ='TOTAL ESTACIONES'!M42 -> 122460 | N42: ='TOTAL ESTACIONES'!N42 -> 109607 | O42: ='TOTAL ESTACIONES'!O42 -> 113673 | P42: ='TOTAL ESTACIONES'!P42 -> 127073 | Q42: ='TOTAL ESTACIONES'!Q42 -> 113934 | ... AM42: ='TOTAL ESTACIONES'!AM42 -> -0.081872266
I43: Margen de utilidad por combustible | J43: ='TOTAL ESTACIONES'!J43 -> 1.9907134 | K43: ='TOTAL ESTACIONES'!K43 -> 2.2185259 | L43: ='TOTAL ESTACIONES'!L43 -> 2.1445421 | M43: ='TOTAL ESTACIONES'!M43 -> 2.3543379 | N43: ='TOTAL ESTACIONES'!N43 -> 2.4858832 | O43: ='TOTAL ESTACIONES'!O43 -> 2.3427799 | P43: ='TOTAL ESTACIONES'!P43 -> 2.1459156 | Q43: ='TOTAL ESTACIONES'!Q43 -> 2.1408583 | ... AM43: ='TOTAL ESTACIONES'!AM43 -> 0.0032641624
A44: E - GASTOS DE OPERACIÓN | B44: estaciones | I44: Maxima | J44: ='TOTAL ESTACIONES'!J44 -> 1.3241994 | K44: ='TOTAL ESTACIONES'!K44 -> 2.1443966 | L44: ='TOTAL ESTACIONES'!L44 -> 2.0049117 | M44: ='TOTAL ESTACIONES'!M44 -> 1.9905098 | N44: ='TOTAL ESTACIONES'!N44 -> 1.9462001 | O44: ='TOTAL ESTACIONES'!O44 -> 1.8841639 | P44: ='TOTAL ESTACIONES'!P44 -> 1.9361954 | Q44: ='TOTAL ESTACIONES'!Q44 -> 1.9425896 | ... AM44: ='TOTAL ESTACIONES'!AM44 -> 0.022042716 | AO44: 19598287 | AP44: 0.0044464695 | AQ44: 0.3287516
A45: E - GASTOS DE OPERACIÓN | B45: estaciones | C45: Servicios Administrativos | I45: Super | J45: ='TOTAL ESTACIONES'!J45 -> 0.77589746 | K45: ='TOTAL ESTACIONES'!K45 -> 2.7615605 | L45: ='TOTAL ESTACIONES'!L45 -> 3.0073576 | M45: ='TOTAL ESTACIONES'!M45 -> 3.1036856 | N45: ='TOTAL ESTACIONES'!N45 -> 3.5507335 | O45: ='TOTAL ESTACIONES'!O45 -> 3.4567268 | P45: ='TOTAL ESTACIONES'!P45 -> 2.7789319 | Q45: ='TOTAL ESTACIONES'!Q45 -> 2.5427027 | ... AM45: ='TOTAL ESTACIONES'!AM45 -> 0.28559624 | AO45: 7218265.7 | AP45: 0.0016376839 | AQ45: 0.24066657
A46: E - GASTOS DE OPERACIÓN | B46: estaciones | I46: Diesel | J46: ='TOTAL ESTACIONES'!J46 -> 0.6312947 | K46: ='TOTAL ESTACIONES'!K46 -> 1.7777531 | L46: ='TOTAL ESTACIONES'!L46 -> 1.5861658 | M46: ='TOTAL ESTACIONES'!M46 -> 3.6821901 | N46: ='TOTAL ESTACIONES'!N46 -> 4.1844499 | O46: ='TOTAL ESTACIONES'!O46 -> 3.7563098 | P46: ='TOTAL ESTACIONES'!P46 -> 2.6674353 | Q46: ='TOTAL ESTACIONES'!Q46 -> 3.0438499 | ... AM46: ='TOTAL ESTACIONES'!AM46 -> 0.024457706 | AO46: 446400 | AP46: 0.00010127947 | AQ46: 0.037504052
A47: E - GASTOS DE OPERACIÓN | B47: estaciones | AO47: 0 | AP47: 0 | AQ47: -1 | AR47: =+AK6/AK39 -> 21.878564
A48: E - GASTOS DE OPERACIÓN | B48: estaciones | I48: GASTO ESTACIONES | AO48: 1004640 | AP48: 0.00022793325 | AQ48: 0.82748833
A49: E - GASTOS DE OPERACIÓN | B49: estaciones | C49: Costo Marketing | AO49: 230499.1 | AP49: 5.2295756e-05 | AQ49: 7.2444774
A50: E - GASTOS DE OPERACIÓN | B50: estaciones | I50: E - GASTOS DE OPERACIÓN | J50: ='TOTAL ESTACIONES'!J50 -> 149335 | K50: ='TOTAL ESTACIONES'!K50 -> 140634 | L50: ='TOTAL ESTACIONES'!L50 -> 144094 | M50: ='TOTAL ESTACIONES'!M50 -> 146807 | N50: ='TOTAL ESTACIONES'!N50 -> 133714 | O50: ='TOTAL ESTACIONES'!O50 -> 211152 | P50: ='TOTAL ESTACIONES'!P50 -> 171855 | Q50: ='TOTAL ESTACIONES'!Q50 -> 232162 | ... AL50: ='TOTAL ESTACIONES'!AL50 -> 0.0062370677 | AM50: =+AK50/V50-1 -> 0.067608776 | AO50: 0 | AP50: 0 | AQ50: -1 | AR50: =+AK50-V50 -> 141717.29 | AS50: =+V50*1.0375 -> 2174742.6 | AT50: =+AS50-AK50 -> -63112.134
A51: E - GASTOS DE OPERACIÓN | B51: estaciones | I51: Traslado de Valores | J51: ='TOTAL ESTACIONES'!J51 -> 71186 | K51: ='TOTAL ESTACIONES'!K51 -> 61124 | L51: ='TOTAL ESTACIONES'!L51 -> 62666 | M51: ='TOTAL ESTACIONES'!M51 -> 63208 | N51: ='TOTAL ESTACIONES'!N51 -> 60682 | O51: ='TOTAL ESTACIONES'!O51 -> 63108 | P51: ='TOTAL ESTACIONES'!P51 -> 63432 | Q51: ='TOTAL ESTACIONES'!Q51 -> 62303 | ... AM51: ='TOTAL ESTACIONES'!AM51 -> 0.064873781 | AO51: 721958.48 | AP51: 0.00016379832 | AQ51: 0.22172791 | AR51: =+AK51-V51 -> 50089.375
A52: E - GASTOS DE OPERACIÓN | B52: estaciones | I52: Servicios Administrativos | J52: ='TOTAL ESTACIONES'!J52 -> 4000 | K52: ='TOTAL ESTACIONES'!K52 -> 5000 | L52: ='TOTAL ESTACIONES'!L52 -> 4000 | M52: ='TOTAL ESTACIONES'!M52 -> 4000 | N52: ='TOTAL ESTACIONES'!N52 -> 5000 | O52: ='TOTAL ESTACIONES'!O52 -> 4000 | P52: ='TOTAL ESTACIONES'!P52 -> 4000 | Q52: ='TOTAL ESTACIONES'!Q52 -> 5000 | ... AM52: ='TOTAL ESTACIONES'!AM52 -> -0.051294118 | AO52: 1101110.8 | AP52: 0.00024982059 | AQ52: 0.24826578 | AR52: =+AK52-V52 -> -2725
A53: E - GASTOS DE OPERACIÓN | B53: estaciones | I53: Otros Gastos | J53: ='TOTAL ESTACIONES'!J53 -> 386 | K53: ='TOTAL ESTACIONES'!K53 -> 0 | L53: ='TOTAL ESTACIONES'!L53 -> 0 | M53: ='TOTAL ESTACIONES'!M53 -> 0 | N53: ='TOTAL ESTACIONES'!N53 -> 0 | O53: ='TOTAL ESTACIONES'!O53 -> 0 | P53: ='TOTAL ESTACIONES'!P53 -> 4841 | Q53: ='TOTAL ESTACIONES'!Q53 -> 0 | ... AM53: ='TOTAL ESTACIONES'!AM53 -> 0.43785704 | AO53: 279218.19 | AP53: 6.3349169e-05 | AQ53: 497.60391 | AR53: =+AK53-V53 -> 4560.5
I54: Otros impuestos y derechos | J54: ='TOTAL ESTACIONES'!J54 -> 0 | K54: ='TOTAL ESTACIONES'!K54 -> 0 | L54: ='TOTAL ESTACIONES'!L54 -> 0 | M54: ='TOTAL ESTACIONES'!M54 -> 0 | N54: ='TOTAL ESTACIONES'!N54 -> 0 | O54: ='TOTAL ESTACIONES'!O54 -> 0 | P54: ='TOTAL ESTACIONES'!P54 -> 0 | Q54: ='TOTAL ESTACIONES'!Q54 -> 0 | ... AM54: ='TOTAL ESTACIONES'!AM54 -> 0 | AO54: 0 | AP54: 0 | AQ54: -1 | AR54: =+AK54-V54 -> 23897.12
I55: Limpieza | J55: ='TOTAL ESTACIONES'!J55 -> 7403 | K55: ='TOTAL ESTACIONES'!K55 -> 4200 | L55: ='TOTAL ESTACIONES'!L55 -> 0 | M55: ='TOTAL ESTACIONES'!M55 -> 6021 | N55: ='TOTAL ESTACIONES'!N55 -> 5080 | O55: ='TOTAL ESTACIONES'!O55 -> 4579 | P55: ='TOTAL ESTACIONES'!P55 -> 1996 | Q55: ='TOTAL ESTACIONES'!Q55 -> 8097 | ... AM55: ='TOTAL ESTACIONES'!AM55 -> 0.21029793 | AO55: 0 | AP55: 0 | AQ55: -1 | AR55: =+AK55-V55 -> 11989.203
I56: Propaganda y publicidad | J56: ='TOTAL ESTACIONES'!J56 -> 28950 | K56: ='TOTAL ESTACIONES'!K56 -> 43277 | L56: ='TOTAL ESTACIONES'!L56 -> 55400 | M56: ='TOTAL ESTACIONES'!M56 -> 46508 | N56: ='TOTAL ESTACIONES'!N56 -> 28961 | O56: ='TOTAL ESTACIONES'!O56 -> 56934 | P56: ='TOTAL ESTACIONES'!P56 -> 58133 | Q56: ='TOTAL ESTACIONES'!Q56 -> 116238 | ... AM56: ='TOTAL ESTACIONES'!AM56 -> 0.037911961 | AO56: 0 | AP56: 0 | AQ56: -1 | AR56: =+AK56-V56 -> 23417.536 | AS56: Listo | AT56: =+V56*1.0375 -> 640845.08 | AU56: =+AT56-AK56 -> -254.461 | AV56: =+AU56/12/2 -> -10.602542 | AW56: =+AV56/1.0375 -> -10.219317
I57: Capacitación al personal | J57: ='TOTAL ESTACIONES'!J57 -> 0 | K57: ='TOTAL ESTACIONES'!K57 -> 0 | L57: ='TOTAL ESTACIONES'!L57 -> 0 | M57: ='TOTAL ESTACIONES'!M57 -> 0 | N57: ='TOTAL ESTACIONES'!N57 -> 0 | O57: ='TOTAL ESTACIONES'!O57 -> 0 | P57: ='TOTAL ESTACIONES'!P57 -> 0 | Q57: ='TOTAL ESTACIONES'!Q57 -> 0 | ... AM57: ='TOTAL ESTACIONES'!AM57 -> 1.1430146 | AO57: 0 | AP57: 0 | AQ57: 0 | AR57: =+AK57-V57 -> 4160.5733
I58: Honorarios Fiscales P.M. | J58: ='TOTAL ESTACIONES'!J58 -> 0 | K58: ='TOTAL ESTACIONES'!K58 -> 0 | L58: ='TOTAL ESTACIONES'!L58 -> 0 | M58: ='TOTAL ESTACIONES'!M58 -> 0 | N58: ='TOTAL ESTACIONES'!N58 -> 0 | O58: ='TOTAL ESTACIONES'!O58 -> 0 | P58: ='TOTAL ESTACIONES'!P58 -> 0 | Q58: ='TOTAL ESTACIONES'!Q58 -> 0 | ... AM58: ='TOTAL ESTACIONES'!AM58 -> 0 | AO58: 0 | AP58: 0 | AQ58: -1 | AR58: =+AK58-V58 -> 0
I59: Honorarios Administrativos P.M. | J59: ='TOTAL ESTACIONES'!J59 -> 0 | K59: ='TOTAL ESTACIONES'!K59 -> 0 | L59: ='TOTAL ESTACIONES'!L59 -> 0 | M59: ='TOTAL ESTACIONES'!M59 -> 0 | N59: ='TOTAL ESTACIONES'!N59 -> 0 | O59: ='TOTAL ESTACIONES'!O59 -> 0 | P59: ='TOTAL ESTACIONES'!P59 -> 0 | Q59: ='TOTAL ESTACIONES'!Q59 -> 0 | ... AM59: ='TOTAL ESTACIONES'!AM59 -> 0 | AO59: 343092 | AP59: 7.7840892e-05 | AQ59: 0.084376956 | AR59: =+AK59-V59 -> 0
I60: Asistencia técnica | J60: ='TOTAL ESTACIONES'!J60 -> 0 | K60: ='TOTAL ESTACIONES'!K60 -> 0 | L60: ='TOTAL ESTACIONES'!L60 -> 0 | M60: ='TOTAL ESTACIONES'!M60 -> 0 | N60: ='TOTAL ESTACIONES'!N60 -> 0 | O60: ='TOTAL ESTACIONES'!O60 -> 0 | P60: ='TOTAL ESTACIONES'!P60 -> 0 | Q60: ='TOTAL ESTACIONES'!Q60 -> 0 | ... AM60: ='TOTAL ESTACIONES'!AM60 -> 0 | AO60: 0 | AP60: 0 | AQ60: 0 | AR60: =+AK60-V60 -> 0
A61: E - GASTOS DE OPERACIÓN | B61: estaciones | I61: Gastos no deducibles (sin requisitos fiscales) | J61: ='TOTAL ESTACIONES'!J61 -> 1500 | K61: ='TOTAL ESTACIONES'!K61 -> 554 | L61: ='TOTAL ESTACIONES'!L61 -> -555 | M61: ='TOTAL ESTACIONES'!M61 -> 169 | N61: ='TOTAL ESTACIONES'!N61 -> 1200 | O61: ='TOTAL ESTACIONES'!O61 -> -2719 | P61: ='TOTAL ESTACIONES'!P61 -> 4319 | Q61: ='TOTAL ESTACIONES'!Q61 -> 783 | ... AM61: ='TOTAL ESTACIONES'!AM61 -> -1 | AO61: 230499.1 | AP61: 5.2295756e-05 | AQ61: -5.8995545 | AR61: =+AK61-V61 -> -7553 | AS61: Listo
A62: E - GASTOS DE OPERACIÓN | B62: estaciones | I62: Papelería y artículos de oficina | J62: ='TOTAL ESTACIONES'!J62 -> 4603 | K62: ='TOTAL ESTACIONES'!K62 -> 2640 | L62: ='TOTAL ESTACIONES'!L62 -> 1962 | M62: ='TOTAL ESTACIONES'!M62 -> 3960 | N62: ='TOTAL ESTACIONES'!N62 -> 3161 | O62: ='TOTAL ESTACIONES'!O62 -> 3802 | P62: ='TOTAL ESTACIONES'!P62 -> 3025 | Q62: ='TOTAL ESTACIONES'!Q62 -> 5693 | ... AM62: ='TOTAL ESTACIONES'!AM62 -> 0.053444354 | AO62: 2418673.4 | AP62: 0.00054874988 | AQ62: 0.79309425 | AR62: =+AK62-V62 -> 2205.575
A63: E - GASTOS DE OPERACIÓN | B63: estaciones | I63: Faltantes | J63: ='TOTAL ESTACIONES'!J63 -> 0 | K63: ='TOTAL ESTACIONES'!K63 -> 0 | L63: ='TOTAL ESTACIONES'!L63 -> 0 | M63: ='TOTAL ESTACIONES'!M63 -> 0 | N63: ='TOTAL ESTACIONES'!N63 -> 0 | O63: ='TOTAL ESTACIONES'!O63 -> 0 | P63: ='TOTAL ESTACIONES'!P63 -> 0 | Q63: ='TOTAL ESTACIONES'!Q63 -> 0 | ... AM63: ='TOTAL ESTACIONES'!AM63 -> 0 | AO63: 0 | AP63: 0 | AQ63: 0 | AR63: =+AK63-V63 -> 0
A64: E - GASTOS DE OPERACIÓN | B64: estaciones | I64: Licencias y Permisos | J64: ='TOTAL ESTACIONES'!J64 -> 0 | K64: ='TOTAL ESTACIONES'!K64 -> 0 | L64: ='TOTAL ESTACIONES'!L64 -> 0 | M64: ='TOTAL ESTACIONES'!M64 -> 0 | N64: ='TOTAL ESTACIONES'!N64 -> 0 | O64: ='TOTAL ESTACIONES'!O64 -> 0 | P64: ='TOTAL ESTACIONES'!P64 -> 0 | Q64: ='TOTAL ESTACIONES'!Q64 -> 0 | ... AM64: ='TOTAL ESTACIONES'!AM64 -> 0 | AO64: 0 | AP64: 0 | AQ64: -1 | AR64: =+AK64-V64 -> 0
A65: E - GASTOS DE OPERACIÓN | B65: estaciones | I65: Licencias, Software, Antivirus | J65: ='TOTAL ESTACIONES'!J65 -> 7256 | K65: ='TOTAL ESTACIONES'!K65 -> 7256 | L65: ='TOTAL ESTACIONES'!L65 -> 7256 | M65: ='TOTAL ESTACIONES'!M65 -> 7256 | N65: ='TOTAL ESTACIONES'!N65 -> 7256 | O65: ='TOTAL ESTACIONES'!O65 -> 7256 | P65: ='TOTAL ESTACIONES'!P65 -> 7256 | Q65: ='TOTAL ESTACIONES'!Q65 -> 7256 | ... AM65: ='TOTAL ESTACIONES'!AM65 -> 0.6082852 | AO65: 409356.29 | AP65: 9.2874968e-05 | AQ65: 0.11739717 | AR65: =+AK65-V65 -> 52964.609 | AS65: Son Licencias que no se pagaban en 2025
A66: E - GASTOS DE OPERACIÓN | B66: estaciones | I66: Fletes Combustible | J66: ='TOTAL ESTACIONES'!J66 -> 0 | K66: ='TOTAL ESTACIONES'!K66 -> 0 | L66: ='TOTAL ESTACIONES'!L66 -> 0 | M66: ='TOTAL ESTACIONES'!M66 -> 0 | N66: ='TOTAL ESTACIONES'!N66 -> 0 | O66: ='TOTAL ESTACIONES'!O66 -> 0 | P66: ='TOTAL ESTACIONES'!P66 -> 0 | Q66: ='TOTAL ESTACIONES'!Q66 -> 0 | ... AM66: ='TOTAL ESTACIONES'!AM66 -> 0 | AO66: 0 | AP66: 0 | AQ66: 0 | AR66: =+AK66-V66 -> 0
A67: E - GASTOS DE OPERACIÓN | B67: estaciones | I67: Viáticos y gastos de viaje | J67: ='TOTAL ESTACIONES'!J67 -> 0 | K67: ='TOTAL ESTACIONES'!K67 -> 0 | L67: ='TOTAL ESTACIONES'!L67 -> 0 | M67: ='TOTAL ESTACIONES'!M67 -> 3048 | N67: ='TOTAL ESTACIONES'!N67 -> 2097 | O67: ='TOTAL ESTACIONES'!O67 -> 2669 | P67: ='TOTAL ESTACIONES'!P67 -> 2793 | Q67: ='TOTAL ESTACIONES'!Q67 -> 0 | ... AM67: ='TOTAL ESTACIONES'!AM67 -> -1 | AO67: 167582.09 | AP67: 3.8021112e-05 | AQ67: 0.031923392 | AR67: =+AK67-V67 -> -10850 | AS67: Listo
A68: E - GASTOS DE OPERACIÓN | B68: estaciones | I68: Recolección de Basura | J68: ='TOTAL ESTACIONES'!J68 -> 1664 | K68: ='TOTAL ESTACIONES'!K68 -> 1664 | L68: ='TOTAL ESTACIONES'!L68 -> 1664 | M68: ='TOTAL ESTACIONES'!M68 -> 1664 | N68: ='TOTAL ESTACIONES'!N68 -> 1664 | O68: ='TOTAL ESTACIONES'!O68 -> 1664 | P68: ='TOTAL ESTACIONES'!P68 -> 3328 | Q68: ='TOTAL ESTACIONES'!Q68 -> 1664 | ... AM68: ='TOTAL ESTACIONES'!AM68 -> -0.04 | AO68: 0 | AP68: 0 | AQ68: -1 | AR68: =+AK68-V68 -> -865.28 | AS68: Listo
A69: E - GASTOS DE OPERACIÓN | B69: estaciones | I69: Honorarios de Consultoria | J69: ='TOTAL ESTACIONES'!J69 -> 0 | K69: ='TOTAL ESTACIONES'!K69 -> 0 | L69: ='TOTAL ESTACIONES'!L69 -> 0 | M69: ='TOTAL ESTACIONES'!M69 -> 0 | N69: ='TOTAL ESTACIONES'!N69 -> 0 | O69: ='TOTAL ESTACIONES'!O69 -> 0 | P69: ='TOTAL ESTACIONES'!P69 -> 0 | Q69: ='TOTAL ESTACIONES'!Q69 -> 0 | ... AM69: ='TOTAL ESTACIONES'!AM69 -> 0 | AO69: 0 | AP69: 0 | AQ69: -1 | AR69: =+AK69-V69 -> 0
A70: E - GASTOS DE OPERACIÓN | B70: estaciones | I70: Agua para consumo | J70: ='TOTAL ESTACIONES'!J70 -> 0 | K70: ='TOTAL ESTACIONES'!K70 -> 0 | L70: ='TOTAL ESTACIONES'!L70 -> 0 | M70: ='TOTAL ESTACIONES'!M70 -> 0 | N70: ='TOTAL ESTACIONES'!N70 -> 0 | O70: ='TOTAL ESTACIONES'!O70 -> 0 | P70: ='TOTAL ESTACIONES'!P70 -> 0 | Q70: ='TOTAL ESTACIONES'!Q70 -> 0 | ... AM70: ='TOTAL ESTACIONES'!AM70 -> 0 | AO70: 0 | AP70: 0 | AQ70: -1 | AR70: =+AK70-V70 -> 8985.6 | AS70: Contabilidad / Puede que sea Viaticos
A71: E - GASTOS DE OPERACIÓN | B71: estaciones | I71: Fletes Mensajeria | J71: ='TOTAL ESTACIONES'!J71 -> 0 | K71: ='TOTAL ESTACIONES'!K71 -> 0 | L71: ='TOTAL ESTACIONES'!L71 -> 0 | M71: ='TOTAL ESTACIONES'!M71 -> 0 | N71: ='TOTAL ESTACIONES'!N71 -> 0 | O71: ='TOTAL ESTACIONES'!O71 -> 0 | P71: ='TOTAL ESTACIONES'!P71 -> 0 | Q71: ='TOTAL ESTACIONES'!Q71 -> 0 | ... AM71: ='TOTAL ESTACIONES'!AM71 -> 0 | AO71: 231497.51 | AP71: 5.2522276e-05 | AQ71: 0.06 | AR71: =+AK71-V71 -> 0
A72: E - GASTOS DE OPERACIÓN | B72: estaciones | I72: Honorarios Administrativos P.F. | J72: ='TOTAL ESTACIONES'!J72 -> 0 | K72: ='TOTAL ESTACIONES'!K72 -> 0 | L72: ='TOTAL ESTACIONES'!L72 -> 0 | M72: ='TOTAL ESTACIONES'!M72 -> 0 | N72: ='TOTAL ESTACIONES'!N72 -> 0 | O72: ='TOTAL ESTACIONES'!O72 -> 0 | P72: ='TOTAL ESTACIONES'!P72 -> 0 | Q72: ='TOTAL ESTACIONES'!Q72 -> 0 | ... AM72: ='TOTAL ESTACIONES'!AM72 -> 0 | AO72: 817328.52 | AP72: 0.00018543592 | AQ72: 2.6545724 | AR72: =+AK72-V72 -> 0
A73: E - GASTOS DE OPERACIÓN | B73: estaciones | I73: Consumos Propios Combustibles | J73: ='TOTAL ESTACIONES'!J73 -> 0 | K73: ='TOTAL ESTACIONES'!K73 -> 5215 | L73: ='TOTAL ESTACIONES'!L73 -> 2103 | M73: ='TOTAL ESTACIONES'!M73 -> 1656 | N73: ='TOTAL ESTACIONES'!N73 -> 1812 | O73: ='TOTAL ESTACIONES'!O73 -> 1949 | P73: ='TOTAL ESTACIONES'!P73 -> 2020 | Q73: ='TOTAL ESTACIONES'!Q73 -> 725 | ... AM73: ='TOTAL ESTACIONES'!AM73 -> -1 | AO73: 0 | AP73: 0 | AQ73: 0 | AR73: =+AK73-V73 -> -16175
A74: E - GASTOS DE OPERACIÓN | B74: estaciones | I74: Renta Equipo de Sistemas | J74: ='TOTAL ESTACIONES'!J74 -> 1620 | K74: ='TOTAL ESTACIONES'!K74 -> 1867 | L74: ='TOTAL ESTACIONES'!L74 -> 1554 | M74: ='TOTAL ESTACIONES'!M74 -> 1597 | N74: ='TOTAL ESTACIONES'!N74 -> 1515 | O74: ='TOTAL ESTACIONES'!O74 -> 1645 | P74: ='TOTAL ESTACIONES'!P74 -> 1654 | Q74: ='TOTAL ESTACIONES'!Q74 -> 1616 | ... AM74: ='TOTAL ESTACIONES'!AM74 -> 0.33840982 | AO74: 3050316.1 | AP74: 0.00069205731 | AQ74: 0.063 | AR74: =+AK74-V74 -> 6595.3325
A75: E - GASTOS DE OPERACIÓN | B75: estaciones | I75: Timbrado Facturas | J75: ='TOTAL ESTACIONES'!J75 -> 3272 | K75: ='TOTAL ESTACIONES'!K75 -> 5065 | L75: ='TOTAL ESTACIONES'!L75 -> 3231 | M75: ='TOTAL ESTACIONES'!M75 -> 3598 | N75: ='TOTAL ESTACIONES'!N75 -> 3473 | O75: ='TOTAL ESTACIONES'!O75 -> 5434 | P75: ='TOTAL ESTACIONES'!P75 -> 4665 | Q75: ='TOTAL ESTACIONES'!Q75 -> 4760 | ... AM75: ='TOTAL ESTACIONES'!AM75 -> -0.15030375 | AO75: 353957.24 | AP75: 8.0306003e-05 | AQ75: 27.041748 | AR75: =+AK75-V75 -> -6906.2975
I76: Uniformes | J76: ='TOTAL ESTACIONES'!J76 -> 13204 | K76: ='TOTAL ESTACIONES'!K76 -> 0 | L76: ='TOTAL ESTACIONES'!L76 -> 2041 | M76: ='TOTAL ESTACIONES'!M76 -> 620 | N76: ='TOTAL ESTACIONES'!N76 -> 2676 | O76: ='TOTAL ESTACIONES'!O76 -> 58059 | P76: ='TOTAL ESTACIONES'!P76 -> 9140 | Q76: ='TOTAL ESTACIONES'!Q76 -> 6869 | ... AM76: ='TOTAL ESTACIONES'!AM76 -> 0.035606147 | AO76: 0 | AP76: 0 | AQ76: 0 | AR76: =+AK76-V76 -> 6195.2361 | AS76: Diana
I77: Contratacion Empleados | J77: ='TOTAL ESTACIONES'!J77 -> 0 | K77: ='TOTAL ESTACIONES'!K77 -> 0 | L77: ='TOTAL ESTACIONES'!L77 -> 0 | M77: ='TOTAL ESTACIONES'!M77 -> 730 | N77: ='TOTAL ESTACIONES'!N77 -> 0 | O77: ='TOTAL ESTACIONES'!O77 -> 0 | P77: ='TOTAL ESTACIONES'!P77 -> 0 | Q77: ='TOTAL ESTACIONES'!Q77 -> 1460 | ... AM77: ='TOTAL ESTACIONES'!AM77 -> 1.6149895 | AO77: 0 | AP77: 0 | AQ77: -1 | AR77: =+AK77-V77 -> 5216.416
I78: Seguros y fianzas | J78: ='TOTAL ESTACIONES'!J78 -> 4291 | K78: ='TOTAL ESTACIONES'!K78 -> 2772 | L78: ='TOTAL ESTACIONES'!L78 -> 2772 | M78: ='TOTAL ESTACIONES'!M78 -> 2772 | N78: ='TOTAL ESTACIONES'!N78 -> 2772 | O78: ='TOTAL ESTACIONES'!O78 -> 2772 | P78: ='TOTAL ESTACIONES'!P78 -> 1253 | Q78: ='TOTAL ESTACIONES'!Q78 -> 2772 | ... AM78: ='TOTAL ESTACIONES'!AM78 -> -0.93212387 | AO78: 0 | AP78: 0 | AQ78: 0 | AR78: =+AK78-V78 -> -25838.474
I79: Honorarios Legales P.F. | J79: ='TOTAL ESTACIONES'!J79 -> 0 | K79: ='TOTAL ESTACIONES'!K79 -> 0 | L79: ='TOTAL ESTACIONES'!L79 -> 0 | M79: ='TOTAL ESTACIONES'!M79 -> 0 | N79: ='TOTAL ESTACIONES'!N79 -> 0 | O79: ='TOTAL ESTACIONES'!O79 -> 0 | P79: ='TOTAL ESTACIONES'!P79 -> 0 | Q79: ='TOTAL ESTACIONES'!Q79 -> 0 | ... AM79: ='TOTAL ESTACIONES'!AM79 -> 0 | AO79: 0 | AP79: 0 | AQ79: -1 | AR79: =+AK79-V79 -> 0
I80: Prediales | J80: ='TOTAL ESTACIONES'!J80 -> 0 | K80: ='TOTAL ESTACIONES'!K80 -> 0 | L80: ='TOTAL ESTACIONES'!L80 -> 0 | M80: ='TOTAL ESTACIONES'!M80 -> 0 | N80: ='TOTAL ESTACIONES'!N80 -> 0 | O80: ='TOTAL ESTACIONES'!O80 -> 0 | P80: ='TOTAL ESTACIONES'!P80 -> 0 | Q80: ='TOTAL ESTACIONES'!Q80 -> 0 | ... AM80: ='TOTAL ESTACIONES'!AM80 -> 0 | AO80: 573892.2 | AP80: 0.00013020496 | AQ80: 0.47501311 | AR80: =+AK80-V80 -> 22251.84
A81: C - NOMINA | B81: estaciones | I81: Certificado para el cumplimiento SAT anexo 30 y 31 | J81: ='TOTAL ESTACIONES'!J81 -> 0 | K81: ='TOTAL ESTACIONES'!K81 -> 0 | L81: ='TOTAL ESTACIONES'!L81 -> 0 | M81: ='TOTAL ESTACIONES'!M81 -> 0 | N81: ='TOTAL ESTACIONES'!N81 -> 0 | O81: ='TOTAL ESTACIONES'!O81 -> 0 | P81: ='TOTAL ESTACIONES'!P81 -> 0 | Q81: ='TOTAL ESTACIONES'!Q81 -> 0 | ... AM81: ='TOTAL ESTACIONES'!AM81 -> -0.036991164 | AO81: 84376394 | AP81: 0.01914336 | AQ81: 0.3576927 | AR81: =+AK81-V81 -> -1423.42
A82: C - NOMINA | B82: estaciones | I82: Arrendamiento Tecnologico | J82: ='TOTAL ESTACIONES'!J82 -> 0 | K82: ='TOTAL ESTACIONES'!K82 -> 0 | L82: ='TOTAL ESTACIONES'!L82 -> 0 | M82: ='TOTAL ESTACIONES'!M82 -> 0 | N82: ='TOTAL ESTACIONES'!N82 -> 0 | O82: ='TOTAL ESTACIONES'!O82 -> 0 | P82: ='TOTAL ESTACIONES'!P82 -> 0 | Q82: ='TOTAL ESTACIONES'!Q82 -> 0 | ... AM82: ='TOTAL ESTACIONES'!AM82 -> 0 | AO82: 2447479.4 | AP82: 0.00055528541 | AQ82: 0.40769365 | AR82: =+AK82-V82 -> 0
A83: C - NOMINA | B83: estaciones | I83: Asesoría en sistemas | J83: ='TOTAL ESTACIONES'!J83 -> 0 | K83: ='TOTAL ESTACIONES'!K83 -> 0 | L83: ='TOTAL ESTACIONES'!L83 -> 0 | M83: ='TOTAL ESTACIONES'!M83 -> 0 | N83: ='TOTAL ESTACIONES'!N83 -> 0 | O83: ='TOTAL ESTACIONES'!O83 -> 0 | P83: ='TOTAL ESTACIONES'!P83 -> 0 | Q83: ='TOTAL ESTACIONES'!Q83 -> 0 | ... AM83: ='TOTAL ESTACIONES'!AM83 -> 0 | AO83: 9194940.3 | AP83: 0.0020861529 | AQ83: 0.39739825 | AR83: =+AK83-V83 -> 0
A84: C - NOMINA | B84: estaciones | I84: Combustibles Reembolsos | J84: ='TOTAL ESTACIONES'!J84 -> 0 | K84: ='TOTAL ESTACIONES'!K84 -> 0 | L84: ='TOTAL ESTACIONES'!L84 -> 0 | M84: ='TOTAL ESTACIONES'!M84 -> 0 | N84: ='TOTAL ESTACIONES'!N84 -> 0 | O84: ='TOTAL ESTACIONES'!O84 -> 0 | P84: ='TOTAL ESTACIONES'!P84 -> 0 | Q84: ='TOTAL ESTACIONES'!Q84 -> 0 | ... AM84: ='TOTAL ESTACIONES'!AM84 -> 0 | AO84: 576608.07 | AP84: 0.00013082114 | AQ84: 0.73982376 | AR84: =+AK84-V84 -> 0
A85: C - NOMINA | B85: estaciones | I85: Honorarios Admvos P.F. | J85: ='TOTAL ESTACIONES'!J85 -> 0 | K85: ='TOTAL ESTACIONES'!K85 -> 0 | L85: ='TOTAL ESTACIONES'!L85 -> 0 | M85: ='TOTAL ESTACIONES'!M85 -> 0 | N85: ='TOTAL ESTACIONES'!N85 -> 0 | O85: ='TOTAL ESTACIONES'!O85 -> 0 | P85: ='TOTAL ESTACIONES'!P85 -> 0 | Q85: ='TOTAL ESTACIONES'!Q85 -> 0 | ... AM85: ='TOTAL ESTACIONES'!AM85 -> 0 | AO85: 3573320 | AP85: 0.0008107167 | AQ85: 0.55792511 | AR85: =+AK85-V85 -> 0
A86: C - NOMINA | B86: estaciones | I86: Capacitacion al personal | J86: ='TOTAL ESTACIONES'!J86 -> 0 | K86: ='TOTAL ESTACIONES'!K86 -> 0 | L86: ='TOTAL ESTACIONES'!L86 -> 0 | M86: ='TOTAL ESTACIONES'!M86 -> 0 | N86: ='TOTAL ESTACIONES'!N86 -> 0 | O86: ='TOTAL ESTACIONES'!O86 -> 0 | P86: ='TOTAL ESTACIONES'!P86 -> 0 | Q86: ='TOTAL ESTACIONES'!Q86 -> 0 | ... AM86: ='TOTAL ESTACIONES'!AM86 -> -1 | AO86: 0 | AP86: 0 | AQ86: -1 | AR86: =+AK86-V86 -> -3640
A87: C - NOMINA | B87: estaciones | I87: Recargos Fiscales | J87: ='TOTAL ESTACIONES'!J87 -> 0 | K87: ='TOTAL ESTACIONES'!K87 -> 0 | L87: ='TOTAL ESTACIONES'!L87 -> 0 | M87: ='TOTAL ESTACIONES'!M87 -> 0 | N87: ='TOTAL ESTACIONES'!N87 -> 0 | O87: ='TOTAL ESTACIONES'!O87 -> 0 | P87: ='TOTAL ESTACIONES'!P87 -> 0 | Q87: ='TOTAL ESTACIONES'!Q87 -> 0 | ... AM87: ='TOTAL ESTACIONES'!AM87 -> 0 | AO87: 4364566.8 | AP87: 0.00099023518 | AQ87: 0.33067474 | AR87: =+AK87-V87 -> 0
A88: C - NOMINA | B88: estaciones | I88: Eventos | J88: ='TOTAL ESTACIONES'!J88 -> 0 | K88: ='TOTAL ESTACIONES'!K88 -> 0 | L88: ='TOTAL ESTACIONES'!L88 -> 0 | M88: ='TOTAL ESTACIONES'!M88 -> 0 | N88: ='TOTAL ESTACIONES'!N88 -> 6365 | O88: ='TOTAL ESTACIONES'!O88 -> 0 | P88: ='TOTAL ESTACIONES'!P88 -> 0 | Q88: ='TOTAL ESTACIONES'!Q88 -> 6926 | ... AM88: ='TOTAL ESTACIONES'!AM88 -> -0.056812553 | AO88: 3224251.1 | AP88: 0.00073151978 | AQ88: 0.39344092 | AR88: =+AK88-V88 -> -4835.155
A89: C - NOMINA | B89: estaciones | I89: Vigilancia y seguridad | J89: ='TOTAL ESTACIONES'!J89 -> 0 | K89: ='TOTAL ESTACIONES'!K89 -> 0 | L89: ='TOTAL ESTACIONES'!L89 -> 0 | M89: ='TOTAL ESTACIONES'!M89 -> 0 | N89: ='TOTAL ESTACIONES'!N89 -> 0 | O89: ='TOTAL ESTACIONES'!O89 -> 0 | P89: ='TOTAL ESTACIONES'!P89 -> 0 | Q89: ='TOTAL ESTACIONES'!Q89 -> 0 | ... AM89: ='TOTAL ESTACIONES'!AM89 -> 0 | AO89: 0 | AP89: 0 | AQ89: -1 | AR89: =+AK89-V89 -> 0
A90: C - NOMINA | B90: estaciones | I90: C - NOMINA | J90: ='TOTAL ESTACIONES'!J90 -> 455748 | K90: ='TOTAL ESTACIONES'!K90 -> 395847 | L90: ='TOTAL ESTACIONES'!L90 -> 458006 | M90: ='TOTAL ESTACIONES'!M90 -> 395986 | N90: ='TOTAL ESTACIONES'!N90 -> 442702 | O90: ='TOTAL ESTACIONES'!O90 -> 446225 | P90: ='TOTAL ESTACIONES'!P90 -> 415847 | Q90: ='TOTAL ESTACIONES'!Q90 -> 423349 | ... AL90: ='TOTAL ESTACIONES'!AL90 -> 0.016593323 | AM90: =+AK90/V90-1 -> 0.13276619 | AO90: 571078.53 | AP90: 0.0001295666 | AQ90: 0.34972762 | AR90: =+AK90-V90 -> 697801.72 | AS90: Listo
A91: C - NOMINA | B91: estaciones | I91: Aguinaldo | J91: ='TOTAL ESTACIONES'!J91 -> 13172 | K91: ='TOTAL ESTACIONES'!K91 -> 10989 | L91: ='TOTAL ESTACIONES'!L91 -> 12027 | M91: ='TOTAL ESTACIONES'!M91 -> 11867 | N91: ='TOTAL ESTACIONES'!N91 -> 12419 | O91: ='TOTAL ESTACIONES'!O91 -> 11699 | P91: ='TOTAL ESTACIONES'!P91 -> 11918 | Q91: ='TOTAL ESTACIONES'!Q91 -> 12155 | ... AM91: ='TOTAL ESTACIONES'!AM91 -> 0.15530941 | AO91: 0 | AP91: 0 | AQ91: -1 | AR91: =+AK91-V91 -> 22802.537
A92: C - NOMINA | B92: estaciones | I92: Compensaciones | J92: ='TOTAL ESTACIONES'!J92 -> 49863 | K92: ='TOTAL ESTACIONES'!K92 -> 36134 | L92: ='TOTAL ESTACIONES'!L92 -> 48036 | M92: ='TOTAL ESTACIONES'!M92 -> 27064 | N92: ='TOTAL ESTACIONES'!N92 -> 44098 | O92: ='TOTAL ESTACIONES'!O92 -> 59674 | P92: ='TOTAL ESTACIONES'!P92 -> 41327 | Q92: ='TOTAL ESTACIONES'!Q92 -> 0 | ... AM92: ='TOTAL ESTACIONES'!AM92 -> 0.056685801 | AO92: 0 | AP92: 0 | AQ92: 0 | AR92: =+AK92-V92 -> 29856.397
A93: C - NOMINA | B93: estaciones | I93: Días festivos | J93: ='TOTAL ESTACIONES'!J93 -> 11896 | K93: ='TOTAL ESTACIONES'!K93 -> 12287 | L93: ='TOTAL ESTACIONES'!L93 -> 12044 | M93: ='TOTAL ESTACIONES'!M93 -> 0 | N93: ='TOTAL ESTACIONES'!N93 -> 12287 | O93: ='TOTAL ESTACIONES'!O93 -> 0 | P93: ='TOTAL ESTACIONES'!P93 -> 0 | Q93: ='TOTAL ESTACIONES'!Q93 -> 0 | ... AM93: ='TOTAL ESTACIONES'!AM93 -> 0.38436023 | AO93: 59555333 | AP93: 0.013511945 | AQ93: 0.50787992 | AR93: =+AK93-V93 -> 26373.093
A94: C - NOMINA | B94: estaciones | I94: Fondo de ahorro | J94: ='TOTAL ESTACIONES'!J94 -> 17158 | K94: ='TOTAL ESTACIONES'!K94 -> 15186 | L94: ='TOTAL ESTACIONES'!L94 -> 17183 | M94: ='TOTAL ESTACIONES'!M94 -> 16371 | N94: ='TOTAL ESTACIONES'!N94 -> 16875 | O94: ='TOTAL ESTACIONES'!O94 -> 16430 | P94: ='TOTAL ESTACIONES'!P94 -> 16396 | Q94: ='TOTAL ESTACIONES'!Q94 -> 15630 | ... AM94: ='TOTAL ESTACIONES'!AM94 -> 0.12474032 | AO94: 0 | AP94: 0 | AQ94: -1 | AR94: =+AK94-V94 -> 24719.158
A95: C - NOMINA | B95: estaciones | I95: Indemnizaciones | J95: ='TOTAL ESTACIONES'!J95 -> 0 | K95: ='TOTAL ESTACIONES'!K95 -> 0 | L95: ='TOTAL ESTACIONES'!L95 -> 0 | M95: ='TOTAL ESTACIONES'!M95 -> 0 | N95: ='TOTAL ESTACIONES'!N95 -> 0 | O95: ='TOTAL ESTACIONES'!O95 -> 0 | P95: ='TOTAL ESTACIONES'!P95 -> 0 | Q95: ='TOTAL ESTACIONES'!Q95 -> 55943 | ... AM95: ='TOTAL ESTACIONES'!AM95 -> -1 | AO95: 0 | AP95: 0 | AQ95: -1 | AR95: =+AK95-V95 -> -99454.222
A96: D - COSTO SOCIAL | B96: estaciones | I96: Premios de asistencia | J96: ='TOTAL ESTACIONES'!J96 -> 28662 | K96: ='TOTAL ESTACIONES'!K96 -> 26477 | L96: ='TOTAL ESTACIONES'!L96 -> 30215 | M96: ='TOTAL ESTACIONES'!M96 -> 26182 | N96: ='TOTAL ESTACIONES'!N96 -> 29569 | O96: ='TOTAL ESTACIONES'!O96 -> 29292 | P96: ='TOTAL ESTACIONES'!P96 -> 26945 | Q96: ='TOTAL ESTACIONES'!Q96 -> 27036 | ... AM96: ='TOTAL ESTACIONES'!AM96 -> 0.016017219 | AO96: 15763375 | AP96: 0.0035764027 | AQ96: 0.17030665 | AR96: =+AK96-V96 -> 5460.4673
A97: D - COSTO SOCIAL | B97: estaciones | I97: Premios de puntualidad | J97: ='TOTAL ESTACIONES'!J97 -> 23699 | K97: ='TOTAL ESTACIONES'!K97 -> 22711 | L97: ='TOTAL ESTACIONES'!L97 -> 25639 | M97: ='TOTAL ESTACIONES'!M97 -> 21887 | N97: ='TOTAL ESTACIONES'!N97 -> 25914 | O97: ='TOTAL ESTACIONES'!O97 -> 25554 | P97: ='TOTAL ESTACIONES'!P97 -> 24027 | Q97: ='TOTAL ESTACIONES'!Q97 -> 23205 | ... AM97: ='TOTAL ESTACIONES'!AM97 -> 0.029834658 | AO97: 3588441.5 | AP97: 0.00081414749 | AQ97: 0.51951629 | AR97: =+AK97-V97 -> 8889.5739
A98: D - COSTO SOCIAL | B98: estaciones | I98: Previsión social | J98: ='TOTAL ESTACIONES'!J98 -> 0 | K98: ='TOTAL ESTACIONES'!K98 -> 0 | L98: ='TOTAL ESTACIONES'!L98 -> 0 | M98: ='TOTAL ESTACIONES'!M98 -> 0 | N98: ='TOTAL ESTACIONES'!N98 -> 0 | O98: ='TOTAL ESTACIONES'!O98 -> 0 | P98: ='TOTAL ESTACIONES'!P98 -> 0 | Q98: ='TOTAL ESTACIONES'!Q98 -> 0 | ... AM98: ='TOTAL ESTACIONES'!AM98 -> 0 | AO98: 4178733.5 | AP98: 0.00094807323 | AQ98: 0.81448847 | AR98: =+AK98-V98 -> 0
A99: D - COSTO SOCIAL | B99: estaciones | I99: Prima dominical | J99: ='TOTAL ESTACIONES'!J99 -> 7488 | K99: ='TOTAL ESTACIONES'!K99 -> 6640 | L99: ='TOTAL ESTACIONES'!L99 -> 6918 | M99: ='TOTAL ESTACIONES'!M99 -> 6659 | N99: ='TOTAL ESTACIONES'!N99 -> 6578 | O99: ='TOTAL ESTACIONES'!O99 -> 6602 | P99: ='TOTAL ESTACIONES'!P99 -> 6671 | Q99: ='TOTAL ESTACIONES'!Q99 -> 6439 | ... AM99: ='TOTAL ESTACIONES'!AM99 -> 0.14507499 | AO99: 7940461.3 | AP99: 0.001801536 | AQ99: 0.20347279 | AR99: =+AK99-V99 -> 11676.279
A100: D - COSTO SOCIAL | B100: estaciones | I100: Prima vacacional | J100: ='TOTAL ESTACIONES'!J100 -> 2923 | K100: ='TOTAL ESTACIONES'!K100 -> 2385 | L100: ='TOTAL ESTACIONES'!L100 -> 2660 | M100: ='TOTAL ESTACIONES'!M100 -> 2620 | N100: ='TOTAL ESTACIONES'!N100 -> 2743 | O100: ='TOTAL ESTACIONES'!O100 -> 2625 | P100: ='TOTAL ESTACIONES'!P100 -> 2682 | Q100: ='TOTAL ESTACIONES'!Q100 -> 2809 | ... AM100: ='TOTAL ESTACIONES'!AM100 -> 0.11127807 | AO100: 55738.326 | AP100: 1.264594e-05 | AQ100: -0.97474399 | AR100: =+AK100-V100 -> 3680.1257
A101: F - MANTENIMIENTO | B101: estaciones | C101: Mantenimiento de Imagen | I101: Primas de antigüedad | J101: ='TOTAL ESTACIONES'!J101 -> 0 | K101: ='TOTAL ESTACIONES'!K101 -> 0 | L101: ='TOTAL ESTACIONES'!L101 -> 5586 | M101: ='TOTAL ESTACIONES'!M101 -> 0 | N101: ='TOTAL ESTACIONES'!N101 -> 0 | O101: ='TOTAL ESTACIONES'!O101 -> 9444 | P101: ='TOTAL ESTACIONES'!P101 -> 0 | Q101: ='TOTAL ESTACIONES'!Q101 -> 6080 | ... AM101: ='TOTAL ESTACIONES'!AM101 -> -1 | AO101: 17625022 | AP101: 0.0039987742 | AQ101: 0.23759562 | AR101: =+AK101-V101 -> -24530
...

Sheet TOTAL ESTACIONES
I1: 1147 | J1: 2 | K1: 3 | L1: 4 | M1: 5 | N1: 6 | O1: 7 | Y1: 2 | Z1: =+Y1+1 -> 3 | AA1: =+Z1+1 -> 4 | AB1: =+AA1+1 -> 5 | AC1: =+AB1+1 -> 6 | AD1: =+AC1+1 -> 7 | AE1: =+AD1+1 -> 8 | AF1: =+AE1+1 -> 9 | AG1: =+AF1+1 -> 10 | ... AK1: =+AJ1+1 -> 14 | AM1: 17
J2: 2025 | V2: TOTAL ANUAL | Y2: 2026 | AK2: TOTAL ANUAL
J3: ENE | K3: FEB | L3: MAR | M3: ABR | N3: MAY | O3: JUN | P3: JUL | Q3: AGO | R3: SEP | S3: OCT | T3: NOV | U3: DIC | V3: 2025 | W3: % Part | Y3: ENE | Z3: FEB | AA3: MAR | AB3: ABR | AC3: MAY | AD3: JUN | AE3: JUL | AF3: AGO | AG3: SEP | AH3: OCT | AI3: NOV | AJ3: DIC | AK3: 2026 | AL3: % Part | AM3: Var vs AA%
I4: INGRESOS
A6: A - INGRESOS | E6: ( mas ) | I6: A - INGRESOS | J6: =SUM(J7:J11) -> 26878636 | K6: =SUM(K7:K11) -> 25528487 | L6: =SUM(L7:L11) -> 28307270 | M6: =SUM(M7:M11) -> 26579702 | N6: =SUM(N7:N11) -> 27359376 | O6: =SUM(O7:O11) -> 26727235 | P6: =SUM(P7:P11) -> 27912533 | Q6: =SUM(Q7:Q11) -> 28233403 | ... V6: =SUM(V7:V11) -> 3.2961219e+08 | W6: =V6/V$6 -> 1 | Y6: =SUM(Y7:Y11) -> 27944944 | Z6: =SUM(Z7:Z11) -> 26629774 | AA6: =SUM(AA7:AA11) -> 29599780 | AB6: =SUM(AB7:AB11) -> 28667280 | AC6: =SUM(AC7:AC11) -> 29293497 | AD6: =SUM(AD7:AD11) -> 28502875 | AE6: =SUM(AE7:AE11) -> 29846068 | AF6: =SUM(AF7:AF11) -> 30746358 | ... AK6: =SUM(AK7:AK11) -> 3.5879918e+08 | AL6: =AK6/AK$6 -> 1 | AM6: =IFERROR(AK6/V6-1,0) -> 0.088549483
A7: A - INGRESOS | B7: estaciones | C7: INGRESOS MAGNA | D7: INGRESOS FORANEOS MAGNA | I7: MAXIMA | J7: =SUM(A:B!J7) -> 19095888 | K7: =SUM(A:B!K7) -> 17878224 | L7: =SUM(A:B!L7) -> 19531849 | M7: =SUM(A:B!M7) -> 18128009 | N7: =SUM(A:B!N7) -> 18229490 | O7: =SUM(A:B!O7) -> 18404815 | P7: =SUM(A:B!P7) -> 19054499 | Q7: =SUM(A:B!Q7) -> 19328904 | ... U7: =SUM(A:B!U7) -> 19683942 | V7: =SUM(J7:U7) -> 2.2908738e+08 | W7: =V7/V$6 -> 0.69502095 | Y7: =SUM(A:B!Y7) -> 20069259 | Z7: =SUM(A:B!Z7) -> 18878938 | AA7: =SUM(A:B!AA7) -> 20696571 | AB7: =SUM(A:B!AB7) -> 19985650 | AC7: =SUM(A:B!AC7) -> 19971013 | AD7: =SUM(A:B!AD7) -> 19987524 | AE7: =SUM(A:B!AE7) -> 20742643 | AF7: =SUM(A:B!AF7) -> 21382459 | ... AJ7: =SUM(A:B!AJ7) -> 22296641 | AK7: =SUM(Y7:AJ7) -> 2.510681e+08 | AL7: =AK7/AK$6 -> 0.69974547 | AM7: =IFERROR(AK7/V7-1,0) -> 0.095949069
A8: A - INGRESOS | B8: estaciones | C8: INGRESOS PREMIUM | D8: INGRESOS FORANEOS PREMIUM | I8: SUPER | J8: =SUM(A:B!J8) -> 5623556 | K8: =SUM(A:B!K8) -> 5345115 | L8: =SUM(A:B!L8) -> 6151225 | M8: =SUM(A:B!M8) -> 5648910 | N8: =SUM(A:B!N8) -> 6559926 | O8: =SUM(A:B!O8) -> 5655884 | P8: =SUM(A:B!P8) -> 5857615 | Q8: =SUM(A:B!Q8) -> 6197597 | ... U8: =SUM(A:B!U8) -> 4928022.3 | V8: =SUM(J8:U8) -> 69879978 | W8: =V8/V$6 -> 0.21200666 | Y8: =SUM(A:B!Y8) -> 5721139.6 | Z8: =SUM(A:B!Z8) -> 5449897 | AA8: =SUM(A:B!AA8) -> 6281390.6 | AB8: =SUM(A:B!AB8) -> 5824968.5 | AC8: =SUM(A:B!AC8) -> 6759520.8 | AD8: =SUM(A:B!AD8) -> 5854609.9 | AE8: =SUM(A:B!AE8) -> 6129670 | AF8: =SUM(A:B!AF8) -> 6631650.4 | ... AJ8: =SUM(A:B!AJ8) -> 6621310.6 | AK8: =SUM(Y8:AJ8) -> 75363298 | AL8: =AK8/AK$6 -> 0.21004312 | AM8: =IFERROR(AK8/V8-1,0) -> 0.078467684
A9: A - INGRESOS | B9: estaciones | C9: INGRESOS DIESEL | D9: INGRESOS FORANEOS DIESEL | I9: DIESEL | J9: =SUM(A:B!J9) -> 2090208 | K9: =SUM(A:B!K9) -> 2235534 | L9: =SUM(A:B!L9) -> 2555308 | M9: =SUM(A:B!M9) -> 2773749 | N9: =SUM(A:B!N9) -> 2487478 | O9: =SUM(A:B!O9) -> 2589338 | P9: =SUM(A:B!P9) -> 2919953 | Q9: =SUM(A:B!Q9) -> 2619067 | ... U9: =SUM(A:B!U9) -> 1813405.3 | V9: =SUM(J9:U9) -> 29789555 | W9: =V9/V$6 -> 0.090377589 | Y9: =SUM(A:B!Y9) -> 2101264.8 | Z9: =SUM(A:B!Z9) -> 2246999.9 | AA9: =SUM(A:B!AA9) -> 2566198.5 | AB9: =SUM(A:B!AB9) -> 2802661.6 | AC9: =SUM(A:B!AC9) -> 2506382.7 | AD9: =SUM(A:B!AD9) -> 2604761.2 | AE9: =SUM(A:B!AE9) -> 2917835.2 | AF9: =SUM(A:B!AF9) -> 2674948.2 | ... AJ9: =SUM(A:B!AJ9) -> 2589138.1 | AK9: =SUM(Y9:AJ9) -> 31690141 | AL9: =AK9/AK$6 -> 0.088322782 | AM9: =IFERROR(AK9/V9-1,0) -> 0.06380043
I10: INGRESOS ACEITES Y LUBRICANTES | J10: =SUM(A:B!J10) -> 68984 | K10: =SUM(A:B!K10) -> 69614 | L10: =SUM(A:B!L10) -> 68888 | M10: =SUM(A:B!M10) -> 29034 | N10: =SUM(A:B!N10) -> 82482 | O10: =SUM(A:B!O10) -> 77198 | P10: =SUM(A:B!P10) -> 80466 | Q10: =SUM(A:B!Q10) -> 87835 | ... U10: =SUM(A:B!U10) -> 57600 | V10: =SUM(J10:U10) -> 764776 | W10: =V10/V$6 -> 0.0023202297 | Y10: =SUM(A:B!Y10) -> 53280 | Z10: =SUM(A:B!Z10) -> 53940 | AA10: =SUM(A:B!AA10) -> 55620 | AB10: =SUM(A:B!AB10) -> 54000 | AC10: =SUM(A:B!AC10) -> 56580 | AD10: =SUM(A:B!AD10) -> 55980 | AE10: =SUM(A:B!AE10) -> 55920 | AF10: =SUM(A:B!AF10) -> 57300 | ... AJ10: =SUM(A:B!AJ10) -> 59880 | AK10: =SUM(Y10:AJ10) -> 677640 | AL10: =AK10/AK$6 -> 0.0018886331 | AM10: =IFERROR(AK10/V10-1,0) -> -0.11393663
I11: SOBRANTE COMBUSTIBLE | J11: =SUM(A:B!J11) -> 0 | K11: =SUM(A:B!K11) -> 0 | L11: =SUM(A:B!L11) -> 0 | M11: =SUM(A:B!M11) -> 0 | N11: =SUM(A:B!N11) -> 0 | O11: =SUM(A:B!O11) -> 0 | P11: =SUM(A:B!P11) -> 0 | Q11: =SUM(A:B!Q11) -> 0 | ... U11: =SUM(A:B!U11) -> 0 | V11: =SUM(J11:U11) -> 90502 | W11: =V11/V$6 -> 0.00027457116 | Y11: =SUM(A:B!Y11) -> 0 | Z11: =SUM(A:B!Z11) -> 0 | AA11: =SUM(A:B!AA11) -> 0 | AB11: =SUM(A:B!AB11) -> 0 | AC11: =SUM(A:B!AC11) -> 0 | AD11: =SUM(A:B!AD11) -> 0 | AE11: =SUM(A:B!AE11) -> 0 | AF11: =SUM(A:B!AF11) -> 0 | ... AJ11: =SUM(A:B!AJ11) -> 0 | AK11: =SUM(Y11:AJ11) -> 0 | AL11: =AK11/AK$6 -> 0 | AM11: =IFERROR(AK11/V11-1,0) -> -1
A12: B - COSTO DE VENTA | E12: ( menos ) | I12: B - COSTO DE VENTA | J12: =SUM(J13:J32) -> 24443667 | K12: =SUM(K13:K32) -> 22953018 | L12: =SUM(L13:L32) -> 25490800 | M12: =SUM(M13:M32) -> 23658529 | N12: =SUM(N13:N32) -> 24196460 | O12: =SUM(O13:O32) -> 23804842 | P12: =SUM(P13:P32) -> 25118023 | Q12: =SUM(Q13:Q32) -> 25414036 | ... U12: =SUM(U13:U32) -> 23870496 | V12: =SUM(V13:V29) -> 2.9594523e+08 | W12: =V12/V$6 -> 0.89785889 | Y12: =SUM(Y13:Y32) -> 25186024 | Z12: =SUM(Z13:Z32) -> 24068620 | AA12: =SUM(AA13:AA32) -> 26544130 | AB12: =SUM(AB13:AB32) -> 25888493 | AC12: =SUM(AC13:AC32) -> 26362658 | AD12: =SUM(AD13:AD32) -> 25744522 | AE12: =SUM(AE13:AE32) -> 26850833 | AF12: =SUM(AF13:AF32) -> 27683501 | ... AJ12: =SUM(AJ13:AJ32) -> 28510625 | AK12: =SUM(Y12:AJ12) -> 3.2337953e+08 | AL12: =AK12/AK$6 -> 0.90128281 | AM12: =IFERROR(AK12/V12-1,0) -> 0.092700589
A13: B - COSTO DE VENTA | C13: COSTO MAGNA | D13: COSTO FORANEO MAGNA | I13: GASOLINA REGULAR | J13: =SUM(A:B!J13) -> 17491983 | K13: =SUM(A:B!K13) -> 16105749 | L13: =SUM(A:B!L13) -> 17633587 | M13: =SUM(A:B!M13) -> 16414267 | N13: =SUM(A:B!N13) -> 16550960 | O13: =SUM(A:B!O13) -> 16752932 | P13: =SUM(A:B!P13) -> 17303449 | Q13: =SUM(A:B!Q13) -> 17528380 | ... U13: =SUM(A:B!U13) -> 17748781 | V13: =SUM(J13:U13) -> 2.0763024e+08 | W13: =V13/V$6 -> 0.62992283 | Y13: =SUM(A:B!Y13) -> 18268310 | Z13: =SUM(A:B!Z13) -> 17247148 | AA13: =SUM(A:B!AA13) -> 18765788 | AB13: =SUM(A:B!AB13) -> 18233965 | AC13: =SUM(A:B!AC13) -> 18195727 | AD13: =SUM(A:B!AD13) -> 18213411 | AE13: =SUM(A:B!AE13) -> 18857424 | AF13: =SUM(A:B!AF13) -> 19454504 | ... AJ13: =SUM(A:B!AJ13) -> 20340563 | AK13: =SUM(Y13:AJ13) -> 2.2863324e+08 | AL13: =AK13/AK$6 -> 0.63721786 | AM13: =IFERROR(AK13/V13-1,0) -> 0.10115578
A14: B - COSTO DE VENTA | C14: COSTO PREMIUM | D14: COSTO FORANEO PREMIUM | I14: GASOLINA PREMIUM | J14: =SUM(A:B!J14) -> 4933868 | K14: =SUM(A:B!K14) -> 4692149 | L14: =SUM(A:B!L14) -> 5366599 | M14: =SUM(A:B!M14) -> 4909439 | N14: =SUM(A:B!N14) -> 5542662 | O14: =SUM(A:B!O14) -> 4823156 | P14: =SUM(A:B!P14) -> 5160135 | Q14: =SUM(A:B!Q14) -> 5519068 | ... U14: =SUM(A:B!U14) -> 4424658.4 | V14: =SUM(J14:U14) -> 61294501 | W14: =V14/V$6 -> 0.18595945 | Y14: =SUM(A:B!Y14) -> 4970410 | Z14: =SUM(A:B!Z14) -> 4748550.6 | AA14: =SUM(A:B!AA14) -> 5422697.3 | AB14: =SUM(A:B!AB14) -> 5082200.1 | AC14: =SUM(A:B!AC14) -> 5835553.5 | AD14: =SUM(A:B!AD14) -> 5129082.5 | AE14: =SUM(A:B!AE14) -> 5317297.7 | AF14: =SUM(A:B!AF14) -> 5746258.5 | ... AJ14: =SUM(A:B!AJ14) -> 5766809 | AK14: =SUM(Y14:AJ14) -> 65492380 | AL14: =AK14/AK$6 -> 0.18253213 | AM14: =IFERROR(AK14/V14-1,0) -> 0.068487031
A15: B - COSTO DE VENTA | C15: COSTO DIESEL | D15: COSTO FORANEO DIESEL | I15: DIESEL | J15: =SUM(A:B!J15) -> 1953610 | K15: =SUM(A:B!K15) -> 2086291 | L15: =SUM(A:B!L15) -> 2425049 | M15: =SUM(A:B!M15) -> 2457800 | N15: =SUM(A:B!N15) -> 2174432 | O15: =SUM(A:B!O15) -> 2274518 | P15: =SUM(A:B!P15) -> 2653742 | Q15: =SUM(A:B!Q15) -> 2343362 | ... U15: =SUM(A:B!U15) -> 1648096.2 | V15: =SUM(J15:U15) -> 26915297 | W15: =V15/V$6 -> 0.081657469 | Y15: =SUM(A:B!Y15) -> 1902016.8 | Z15: =SUM(A:B!Z15) -> 2027072.5 | AA15: =SUM(A:B!AA15) -> 2308368.1 | AB15: =SUM(A:B!AB15) -> 2526428.2 | AC15: =SUM(A:B!AC15) -> 2283284.2 | AD15: =SUM(A:B!AD15) -> 2354445.4 | AE15: =SUM(A:B!AE15) -> 2628579.4 | AF15: =SUM(A:B!AF15) -> 2434033.6 | ... AJ15: =SUM(A:B!AJ15) -> 2352354.9 | AK15: =SUM(Y15:AJ15) -> 28677913 | AL15: =AK15/AK$6 -> 0.079927478 | AM15: =IFERROR(AK15/V15-1,0) -> 0.065487529
A16: B - COSTO DE VENTA | C16: Merma Magna | I16: MERMA GASOLINA REGULAR | J16: =SUM(A:B!J16) -> 0 | K16: =SUM(A:B!K16) -> 0 | L16: =SUM(A:B!L16) -> 49100 | M16: =SUM(A:B!M16) -> 0 | N16: =SUM(A:B!N16) -> 0 | O16: =SUM(A:B!O16) -> 0 | P16: =SUM(A:B!P16) -> 0 | Q16: =SUM(A:B!Q16) -> 0 | ... U16: =SUM(A:B!U16) -> 0 | V16: =SUM(J16:U16) -> 49100 | W16: =V16/V$6 -> 0.00014896294 | Y16: =SUM(A:B!Y16) -> 0 | Z16: =SUM(A:B!Z16) -> 0 | AA16: =SUM(A:B!AA16) -> 0 | AB16: =SUM(A:B!AB16) -> 0 | AC16: =SUM(A:B!AC16) -> 0 | AD16: =SUM(A:B!AD16) -> 0 | AE16: =SUM(A:B!AE16) -> 0 | AF16: =SUM(A:B!AF16) -> 0 | ... AJ16: =SUM(A:B!AJ16) -> 0 | AK16: =SUM(Y16:AJ16) -> 0 | AL16: =AK16/AK$6 -> 0 | AM16: =IFERROR(AK16/V16-1,0) -> -1
A17: B - COSTO DE VENTA | C17: Merma Premium | I17: MERMA GASOLINA PREMIUM | J17: =SUM(A:B!J17) -> 7882 | K17: =SUM(A:B!K17) -> 14264 | L17: =SUM(A:B!L17) -> 0 | M17: =SUM(A:B!M17) -> 0 | N17: =SUM(A:B!N17) -> 16710 | O17: =SUM(A:B!O17) -> 0 | P17: =SUM(A:B!P17) -> 0 | Q17: =SUM(A:B!Q17) -> 3686 | ... U17: =SUM(A:B!U17) -> 0 | V17: =SUM(J17:U17) -> 42542 | W17: =V17/V$6 -> 0.00012906683 | Y17: =SUM(A:B!Y17) -> 0 | Z17: =SUM(A:B!Z17) -> 0 | AA17: =SUM(A:B!AA17) -> 0 | AB17: =SUM(A:B!AB17) -> 0 | AC17: =SUM(A:B!AC17) -> 0 | AD17: =SUM(A:B!AD17) -> 0 | AE17: =SUM(A:B!AE17) -> 0 | AF17: =SUM(A:B!AF17) -> 0 | ... AJ17: =SUM(A:B!AJ17) -> 0 | AK17: =SUM(Y17:AJ17) -> 0 | AL17: =AK17/AK$6 -> 0 | AM17: =IFERROR(AK17/V17-1,0) -> -1
A18: B - COSTO DE VENTA | C18: Merma Diesel | I18: MERMA DIESEL | J18: =SUM(A:B!J18) -> 0 | K18: =SUM(A:B!K18) -> 0 | L18: =SUM(A:B!L18) -> 0 | M18: =SUM(A:B!M18) -> 0 | N18: =SUM(A:B!N18) -> 0 | O18: =SUM(A:B!O18) -> 0 | P18: =SUM(A:B!P18) -> 0 | Q18: =SUM(A:B!Q18) -> 0 | ... U18: =SUM(A:B!U18) -> 0 | V18: =SUM(J18:U18) -> 33294 | W18: =V18/V$6 -> 0.00010100961 | Y18: =SUM(A:B!Y18) -> 0 | Z18: =SUM(A:B!Z18) -> 0 | AA18: =SUM(A:B!AA18) -> 0 | AB18: =SUM(A:B!AB18) -> 0 | AC18: =SUM(A:B!AC18) -> 0 | AD18: =SUM(A:B!AD18) -> 0 | AE18: =SUM(A:B!AE18) -> 0 | AF18: =SUM(A:B!AF18) -> 0 | ... AJ18: =SUM(A:B!AJ18) -> 0 | AK18: =SUM(Y18:AJ18) -> 0 | AL18: =AK18/AK$6 -> 0 | AM18: =IFERROR(AK18/V18-1,0) -> -1
I19: SOBRANTE MAGNA | J19: =SUM(A:B!J19) -> 37098 | K19: =SUM(A:B!K19) -> 30373 | L19: =SUM(A:B!L19) -> 39778 | M19: =SUM(A:B!M19) -> 31691 | N19: =SUM(A:B!N19) -> 35405 | O19: =SUM(A:B!O19) -> 33757 | P19: =SUM(A:B!P19) -> 37244 | Q19: =SUM(A:B!Q19) -> 38255 | ... U19: =SUM(A:B!U19) -> 0 | V19: =SUM(J19:U19) -> 359163 | W19: =V19/V$6 -> 0.0010896533 | Y19: =SUM(A:B!Y19) -> 0 | Z19: =SUM(A:B!Z19) -> 0 | AA19: =SUM(A:B!AA19) -> 0 | AB19: =SUM(A:B!AB19) -> 0 | AC19: =SUM(A:B!AC19) -> 0 | AD19: =SUM(A:B!AD19) -> 0 | AE19: =SUM(A:B!AE19) -> 0 | AF19: =SUM(A:B!AF19) -> 0 | ... AJ19: =SUM(A:B!AJ19) -> 0 | AK19: =SUM(Y19:AJ19) -> 0 | AL19: =AK19/AK$6 -> 0 | AM19: =IFERROR(AK19/V19-1,0) -> -1
I20: SOBRANTE PREMIUM | J20: =SUM(A:B!J20) -> 10383 | K20: =SUM(A:B!K20) -> 7510 | L20: =SUM(A:B!L20) -> 11713 | M20: =SUM(A:B!M20) -> 9665 | N20: =SUM(A:B!N20) -> 10014 | O20: =SUM(A:B!O20) -> 10264 | P20: =SUM(A:B!P20) -> 11873 | Q20: =SUM(A:B!Q20) -> 9035 | ... U20: =SUM(A:B!U20) -> 0 | V20: =SUM(J20:U20) -> 102881 | W20: =V20/V$6 -> 0.00031212741 | Y20: =SUM(A:B!Y20) -> 0 | Z20: =SUM(A:B!Z20) -> 0 | AA20: =SUM(A:B!AA20) -> 0 | AB20: =SUM(A:B!AB20) -> 0 | AC20: =SUM(A:B!AC20) -> 0 | AD20: =SUM(A:B!AD20) -> 0 | AE20: =SUM(A:B!AE20) -> 0 | AF20: =SUM(A:B!AF20) -> 0 | ... AJ20: =SUM(A:B!AJ20) -> 0 | AK20: =SUM(Y20:AJ20) -> 0 | AL20: =AK20/AK$6 -> 0 | AM20: =IFERROR(AK20/V20-1,0) -> -1
I21: SOBRANTE DIESEL | J21: =SUM(A:B!J21) -> 0 | K21: =SUM(A:B!K21) -> 0 | L21: =SUM(A:B!L21) -> 0 | M21: =SUM(A:B!M21) -> 0 | N21: =SUM(A:B!N21) -> 0 | O21: =SUM(A:B!O21) -> 0 | P21: =SUM(A:B!P21) -> 0 | Q21: =SUM(A:B!Q21) -> 0 | ... U21: =SUM(A:B!U21) -> 0 | V21: =SUM(J21:U21) -> 0 | W21: =V21/V$6 -> 0 | Y21: =SUM(A:B!Y21) -> 0 | Z21: =SUM(A:B!Z21) -> 0 | AA21: =SUM(A:B!AA21) -> 0 | AB21: =SUM(A:B!AB21) -> 0 | AC21: =SUM(A:B!AC21) -> 0 | AD21: =SUM(A:B!AD21) -> 0 | AE21: =SUM(A:B!AE21) -> 0 | AF21: =SUM(A:B!AF21) -> 0 | ... AJ21: =SUM(A:B!AJ21) -> 0 | AK21: =SUM(Y21:AJ21) -> 0 | AL21: =AK21/AK$6 -> 0 | AM21: =IFERROR(AK21/V21-1,0) -> 0
A22: B - COSTO DE VENTA | C22: ADITIVO PARA GASOLINA TMAXIMA (REGULAR) | D22: ADITIVO PARA GASOLINA TMAXIMA( REGULAR) | I22: ADITIVO TOTAL POWER GASOLINA REG | J22: =SUM(A:B!J22) -> 0 | K22: =SUM(A:B!K22) -> 0 | L22: =SUM(A:B!L22) -> 0 | M22: =SUM(A:B!M22) -> 0 | N22: =SUM(A:B!N22) -> 0 | O22: =SUM(A:B!O22) -> 0 | P22: =SUM(A:B!P22) -> 0 | Q22: =SUM(A:B!Q22) -> 0 | ... U22: =SUM(A:B!U22) -> 0 | V22: =SUM(J22:U22) -> 0 | W22: =V22/V$6 -> 0 | Y22: =SUM(A:B!Y22) -> 0 | Z22: =SUM(A:B!Z22) -> 0 | AA22: =SUM(A:B!AA22) -> 0 | AB22: =SUM(A:B!AB22) -> 0 | AC22: =SUM(A:B!AC22) -> 0 | AD22: =SUM(A:B!AD22) -> 0 | AE22: =SUM(A:B!AE22) -> 0 | AF22: =SUM(A:B!AF22) -> 0 | ... AJ22: =SUM(A:B!AJ22) -> 0 | AK22: =SUM(Y22:AJ22) -> 0 | AL22: =AK22/AK$6 -> 0 | AM22: =IFERROR(AK22/V22-1,0) -> 0
A23: B - COSTO DE VENTA | C23: ADITIVO PARA GASOLINA TSUPER (PREMIUM) | I23: ADITIVO TOTAL POWER GASOLINA PREM | J23: =SUM(A:B!J23) -> 0 | K23: =SUM(A:B!K23) -> 0 | L23: =SUM(A:B!L23) -> 0 | M23: =SUM(A:B!M23) -> 0 | N23: =SUM(A:B!N23) -> 0 | O23: =SUM(A:B!O23) -> 0 | P23: =SUM(A:B!P23) -> 0 | Q23: =SUM(A:B!Q23) -> 0 | ... U23: =SUM(A:B!U23) -> 0 | V23: =SUM(J23:U23) -> 0 | W23: =V23/V$6 -> 0 | Y23: =SUM(A:B!Y23) -> 0 | Z23: =SUM(A:B!Z23) -> 0 | AA23: =SUM(A:B!AA23) -> 0 | AB23: =SUM(A:B!AB23) -> 0 | AC23: =SUM(A:B!AC23) -> 0 | AD23: =SUM(A:B!AD23) -> 0 | AE23: =SUM(A:B!AE23) -> 0 | AF23: =SUM(A:B!AF23) -> 0 | ... AJ23: =SUM(A:B!AJ23) -> 0 | AK23: =SUM(Y23:AJ23) -> 0 | AL23: =AK23/AK$6 -> 0 | AM23: =IFERROR(AK23/V23-1,0) -> 0
A24: B - COSTO DE VENTA | C24: FLETE MAGNA | I24: FLETE GASOLINA REGULAR | J24: =SUM(A:B!J24) -> 0 | K24: =SUM(A:B!K24) -> 0 | L24: =SUM(A:B!L24) -> 267 | M24: =SUM(A:B!M24) -> 0 | N24: =SUM(A:B!N24) -> 0 | O24: =SUM(A:B!O24) -> 0 | P24: =SUM(A:B!P24) -> 0 | Q24: =SUM(A:B!Q24) -> 0 | ... U24: =SUM(A:B!U24) -> 0 | V24: =SUM(J24:U24) -> 267 | W24: =V24/V$6 -> 8.1004286e-07 | Y24: =SUM(A:B!Y24) -> 0 | Z24: =SUM(A:B!Z24) -> 0 | AA24: =SUM(A:B!AA24) -> 0 | AB24: =SUM(A:B!AB24) -> 0 | AC24: =SUM(A:B!AC24) -> 0 | AD24: =SUM(A:B!AD24) -> 0 | AE24: =SUM(A:B!AE24) -> 0 | AF24: =SUM(A:B!AF24) -> 0 | ... AJ24: =SUM(A:B!AJ24) -> 0 | AK24: =SUM(Y24:AJ24) -> 0 | AL24: =AK24/AK$6 -> 0 | AM24: =IFERROR(AK24/V24-1,0) -> -1
A25: B - COSTO DE VENTA | C25: FLETE PREMIUM | I25: FLETE GASOLINA PREMIUM | J25: =SUM(A:B!J25) -> 0 | K25: =SUM(A:B!K25) -> 0 | L25: =SUM(A:B!L25) -> 1204 | M25: =SUM(A:B!M25) -> 2070 | N25: =SUM(A:B!N25) -> 0 | O25: =SUM(A:B!O25) -> 0 | P25: =SUM(A:B!P25) -> 2068 | Q25: =SUM(A:B!Q25) -> 0 | ... U25: =SUM(A:B!U25) -> 0 | V25: =SUM(J25:U25) -> 5342 | W25: =V25/V$6 -> 1.6206925e-05 | Y25: =SUM(A:B!Y25) -> 0 | Z25: =SUM(A:B!Z25) -> 0 | AA25: =SUM(A:B!AA25) -> 0 | AB25: =SUM(A:B!AB25) -> 0 | AC25: =SUM(A:B!AC25) -> 0 | AD25: =SUM(A:B!AD25) -> 0 | AE25: =SUM(A:B!AE25) -> 0 | AF25: =SUM(A:B!AF25) -> 0 | ... AJ25: =SUM(A:B!AJ25) -> 0 | AK25: =SUM(Y25:AJ25) -> 0 | AL25: =AK25/AK$6 -> 0 | AM25: =IFERROR(AK25/V25-1,0) -> -1
A26: B - COSTO DE VENTA | C26: FLETE DIESEL | I26: FLETE DIESEL | J26: =SUM(A:B!J26) -> -16996 | K26: =SUM(A:B!K26) -> -26879 | L26: =SUM(A:B!L26) -> -49360 | M26: =SUM(A:B!M26) -> -134972 | N26: =SUM(A:B!N26) -> -145599 | O26: =SUM(A:B!O26) -> -112171 | P26: =SUM(A:B!P26) -> -72748 | Q26: =SUM(A:B!Q26) -> -71093 | ... U26: =SUM(A:B!U26) -> 0 | V26: =SUM(J26:U26) -> -797725 | W26: =V26/V$6 -> -0.0024201927 | Y26: =SUM(A:B!Y26) -> 0 | Z26: =SUM(A:B!Z26) -> 0 | AA26: =SUM(A:B!AA26) -> 0 | AB26: =SUM(A:B!AB26) -> 0 | AC26: =SUM(A:B!AC26) -> 0 | AD26: =SUM(A:B!AD26) -> 0 | AE26: =SUM(A:B!AE26) -> 0 | AF26: =SUM(A:B!AF26) -> 0 | ... AJ26: =SUM(A:B!AJ26) -> 0 | AK26: =SUM(Y26:AJ26) -> 0 | AL26: =AK26/AK$6 -> 0 | AM26: =IFERROR(AK26/V26-1,0) -> -1
A27: B - COSTO DE VENTA | C27: Estimulo IEPS Magna | D27: INGRESOS FORANEOS MAGNA | I27: ESTIMULO REGULAR | J27: =SUM(A:B!J27) -> -15808 | K27: =SUM(A:B!K27) -> -8530 | L27: =SUM(A:B!L27) -> -22247 | M27: =SUM(A:B!M27) -> -24612 | N27: =SUM(A:B!N27) -> -30658 | O27: =SUM(A:B!O27) -> -20889 | P27: =SUM(A:B!P27) -> -26813 | Q27: =SUM(A:B!Q27) -> -8260 | ... U27: =SUM(A:B!U27) -> 0 | V27: =SUM(J27:U27) -> -202571 | W27: =V27/V$6 -> -0.00061457375 | Y27: =SUM(A:B!Y27) -> 0 | Z27: =SUM(A:B!Z27) -> 0 | AA27: =SUM(A:B!AA27) -> 0 | AB27: =SUM(A:B!AB27) -> 0 | AC27: =SUM(A:B!AC27) -> 0 | AD27: =SUM(A:B!AD27) -> 0 | AE27: =SUM(A:B!AE27) -> 0 | AF27: =SUM(A:B!AF27) -> 0 | ... AJ27: =SUM(A:B!AJ27) -> 0 | AK27: =SUM(Y27:AJ27) -> 0 | AL27: =AK27/AK$6 -> 0 | AM27: =IFERROR(AK27/V27-1,0) -> -1
A28: B - COSTO DE VENTA | C28: Estimulo IEPS Premium | D28: INGRESOS FORANEOS MAGNA | I28: ESTIMULO PREMIUM | J28: =SUM(A:B!J28) -> -6436 | K28: =SUM(A:B!K28) -> 0 | L28: =SUM(A:B!L28) -> -18941 | M28: =SUM(A:B!M28) -> -22943 | N28: =SUM(A:B!N28) -> -9722 | O28: =SUM(A:B!O28) -> -17371 | P28: =SUM(A:B!P28) -> -18629 | Q28: =SUM(A:B!Q28) -> -16467 | ... U28: =SUM(A:B!U28) -> 0 | V28: =SUM(J28:U28) -> -133277 | W28: =V28/V$6 -> -0.00040434488 | Y28: =SUM(A:B!Y28) -> 0 | Z28: =SUM(A:B!Z28) -> 0 | AA28: =SUM(A:B!AA28) -> 0 | AB28: =SUM(A:B!AB28) -> 0 | AC28: =SUM(A:B!AC28) -> 0 | AD28: =SUM(A:B!AD28) -> 0 | AE28: =SUM(A:B!AE28) -> 0 | AF28: =SUM(A:B!AF28) -> 0 | ... AJ28: =SUM(A:B!AJ28) -> 0 | AK28: =SUM(Y28:AJ28) -> 0 | AL28: =AK28/AK$6 -> 0 | AM28: =IFERROR(AK28/V28-1,0) -> -1
I29: COSTO ACEITES Y LUBRICANTES | J29: =SUM(A:B!J29) -> 48083 | K29: =SUM(A:B!K29) -> 52091 | L29: =SUM(A:B!L29) -> 54051 | M29: =SUM(A:B!M29) -> 16124 | N29: =SUM(A:B!N29) -> 52256 | O29: =SUM(A:B!O29) -> 60646 | P29: =SUM(A:B!P29) -> 67702 | Q29: =SUM(A:B!Q29) -> 68070 | ... U29: =SUM(A:B!U29) -> 48960 | V29: =SUM(J29:U29) -> 646174 | W29: =V29/V$6 -> 0.0019604069 | Y29: =SUM(A:B!Y29) -> 45288 | Z29: =SUM(A:B!Z29) -> 45849 | AA29: =SUM(A:B!AA29) -> 47277 | AB29: =SUM(A:B!AB29) -> 45900 | AC29: =SUM(A:B!AC29) -> 48093 | AD29: =SUM(A:B!AD29) -> 47583 | AE29: =SUM(A:B!AE29) -> 47532 | AF29: =SUM(A:B!AF29) -> 48705 | ... AJ29: =SUM(A:B!AJ29) -> 50898 | AK29: =SUM(Y29:AJ29) -> 575994 | AL29: =AK29/AK$6 -> 0.0016053381 | AM29: =IFERROR(AK29/V29-1,0) -> -0.10860852
I30: BONIFICACION COMPRA DE COMBUSTIBLE MAGNA | J30: =SUM(A:B!J30) -> 0 | K30: =SUM(A:B!K30) -> 0 | L30: =SUM(A:B!L30) -> 0 | M30: =SUM(A:B!M30) -> 0 | N30: =SUM(A:B!N30) -> 0 | O30: =SUM(A:B!O30) -> 0 | P30: =SUM(A:B!P30) -> 0 | Q30: =SUM(A:B!Q30) -> 0 | ... U30: =SUM(A:B!U30) -> 0 | V30: =SUM(J30:U30) -> 0 | W30: =V30/V$6 -> 0 | Y30: =SUM(A:B!Y30) -> 0 | Z30: =SUM(A:B!Z30) -> 0 | AA30: =SUM(A:B!AA30) -> 0 | AB30: =SUM(A:B!AB30) -> 0 | AC30: =SUM(A:B!AC30) -> 0 | AD30: =SUM(A:B!AD30) -> 0 | AE30: =SUM(A:B!AE30) -> 0 | AF30: =SUM(A:B!AF30) -> 0 | ... AJ30: =SUM(A:B!AJ30) -> 0 | AK30: =SUM(Y30:AJ30) -> 0 | AL30: =AK30/AK$6 -> 0 | AM30: =IFERROR(AK30/V30-1,0) -> 0
I31: BONIFICACION COMPRA DE COMBUSTIBLE PREMIUM | J31: =SUM(A:B!J31) -> 0 | K31: =SUM(A:B!K31) -> 0 | L31: =SUM(A:B!L31) -> 0 | M31: =SUM(A:B!M31) -> 0 | N31: =SUM(A:B!N31) -> 0 | O31: =SUM(A:B!O31) -> 0 | P31: =SUM(A:B!P31) -> 0 | Q31: =SUM(A:B!Q31) -> 0 | ... U31: =SUM(A:B!U31) -> 0 | V31: =SUM(J31:U31) -> 0 | W31: =V31/V$6 -> 0 | Y31: =SUM(A:B!Y31) -> 0 | Z31: =SUM(A:B!Z31) -> 0 | AA31: =SUM(A:B!AA31) -> 0 | AB31: =SUM(A:B!AB31) -> 0 | AC31: =SUM(A:B!AC31) -> 0 | AD31: =SUM(A:B!AD31) -> 0 | AE31: =SUM(A:B!AE31) -> 0 | AF31: =SUM(A:B!AF31) -> 0 | ... AJ31: =SUM(A:B!AJ31) -> 0 | AK31: =SUM(Y31:AJ31) -> 0 | AL31: =AK31/AK$6 -> 0 | AM31: =IFERROR(AK31/V31-1,0) -> 0
I32: BONIFICACION COMPRA DE COMBUSTIBLE DIESEL | J32: =SUM(A:B!J32) -> 0 | K32: =SUM(A:B!K32) -> 0 | L32: =SUM(A:B!L32) -> 0 | M32: =SUM(A:B!M32) -> 0 | N32: =SUM(A:B!N32) -> 0 | O32: =SUM(A:B!O32) -> 0 | P32: =SUM(A:B!P32) -> 0 | Q32: =SUM(A:B!Q32) -> 0 | ... U32: =SUM(A:B!U32) -> 0 | V32: =SUM(J32:U32) -> 0 | W32: =V32/V$6 -> 0 | Y32: =SUM(A:B!Y32) -> 0 | Z32: =SUM(A:B!Z32) -> 0 | AA32: =SUM(A:B!AA32) -> 0 | AB32: =SUM(A:B!AB32) -> 0 | AC32: =SUM(A:B!AC32) -> 0 | AD32: =SUM(A:B!AD32) -> 0 | AE32: =SUM(A:B!AE32) -> 0 | AF32: =SUM(A:B!AF32) -> 0 | ... AJ32: =SUM(A:B!AJ32) -> 0 | AK32: =SUM(Y32:AJ32) -> 0 | AL32: =AK32/AK$6 -> 0 | AM32: =IFERROR(AK32/V32-1,0) -> 0
I33: MARGEN DE UTILIDAD | J33: =J6-J12 -> 2434969 | K33: =K6-K12 -> 2575469 | L33: =L6-L12 -> 2816470 | M33: =M6-M12 -> 2921173 | N33: =N6-N12 -> 3162916 | O33: =O6-O12 -> 2922393 | P33: =P6-P12 -> 2794510 | Q33: =Q6-Q12 -> 2819367 | R33: =SUM(R34:R38) -> 2845425 | S33: =SUM(S34:S38) -> 2819768 | T33: =SUM(T34:T38) -> 2828187.7 | U33: =SUM(U34:U38) -> 2831126.9 | V33: =V6-V12 -> 33666956 | W33: =V33/V$6 -> 0.10214111 | Y33: =Y6-Y12 -> 2758919.4 | Z33: =Z6-Z12 -> 2561154.2 | AA33: =AA6-AA12 -> 3055649.6 | AB33: =AB6-AB12 -> 2778786.8 | AC33: =AC6-AC12 -> 2930839.3 | AD33: =AD6-AD12 -> 2758353.2 | AE33: =AE6-AE12 -> 2995235.3 | AF33: =AF6-AF12 -> 3062857 | ... AK33: =AK6-AK12 -> 35419648 | AL33: =AK33/AK$6 -> 0.098717193 | AM33: =IFERROR(AK33/V33-1,0) -> 0.052059696
I34: *Regular | J34: =SUM(A:B!J34) -> 1583804 | K34: =SUM(A:B!K34) -> 1768980 | L34: =SUM(A:B!L34) -> 1858476 | M34: =SUM(A:B!M34) -> 1817025 | N34: =SUM(A:B!N34) -> 1788723 | O34: =SUM(A:B!O34) -> 1730298 | P34: =SUM(A:B!P34) -> 1786554 | Q34: =SUM(A:B!Q34) -> 1833363 | R34: =+AVERAGE(O34:Q34) -> 1783405 | S34: =+AVERAGE(P34:R34) -> 1801107.3 | T34: =+AVERAGE(Q34:S34) -> 1805958.4 | U34: =+AVERAGE(R34:T34) -> 1796823.6 | V34: =SUM(J34:U34) -> 21354517 | W34: =V34/V$39 -> 1.3654702 | Y34: =SUM(A:B!Y34) -> 1800949.8 | Z34: =SUM(A:B!Z34) -> 1631789.5 | AA34: =SUM(A:B!AA34) -> 1930782.9 | AB34: =SUM(A:B!AB34) -> 1751684.9 | AC34: =SUM(A:B!AC34) -> 1775286.5 | AD34: =SUM(A:B!AD34) -> 1774113.1 | AE34: =SUM(A:B!AE34) -> 1885219.1 | AF34: =SUM(A:B!AF34) -> 1927955.5 | ... AJ34: =SUM(A:B!AJ34) -> 1956077.5 | AK34: =SUM(Y34:AJ34) -> 22434855 | AL34: =AK34/AK$39 -> 1.3680144 | AM34: =IFERROR(AK34/V34-1,0) -> 0.050590609
I35: *Premium | J35: =SUM(A:B!J35) -> 687232 | K35: =SUM(A:B!K35) -> 639721 | L35: =SUM(A:B!L35) -> 793954 | M35: =SUM(A:B!M35) -> 752348 | N35: =SUM(A:B!N35) -> 1021198 | O35: =SUM(A:B!O35) -> 843354 | P35: =SUM(A:B!P35) -> 710352 | Q35: =SUM(A:B!Q35) -> 674069 | R35: =+AVERAGE(O35:Q35) -> 742591.67 | S35: =+AVERAGE(P35:R35) -> 709004.22 | T35: =+AVERAGE(Q35:S35) -> 708554.96 | U35: =+AVERAGE(R35:T35) -> 720050.28 | V35: =SUM(J35:U35) -> 9002429.1 | W35: =V35/V$39 -> 0.57564161 | Y35: =SUM(A:B!Y35) -> 750729.54 | Z35: =SUM(A:B!Z35) -> 701346.35 | AA35: =SUM(A:B!AA35) -> 858693.28 | AB35: =SUM(A:B!AB35) -> 742768.4 | AC35: =SUM(A:B!AC35) -> 923967.28 | AD35: =SUM(A:B!AD35) -> 725527.35 | AE35: =SUM(A:B!AE35) -> 812372.37 | AF35: =SUM(A:B!AF35) -> 885391.9 | ... AJ35: =SUM(A:B!AJ35) -> 854501.58 | AK35: =SUM(Y35:AJ35) -> 9870918.5 | AL35: =AK35/AK$39 -> 0.60190084 | AM35: =IFERROR(AK35/V35-1,0) -> 0.096472781
I36: *Diesel | J36: =SUM(A:B!J36) -> 143034 | K36: =SUM(A:B!K36) -> 149243 | L36: =SUM(A:B!L36) -> 149199 | M36: =SUM(A:B!M36) -> 338891 | N36: =SUM(A:B!N36) -> 322767 | O36: =SUM(A:B!O36) -> 332192 | P36: =SUM(A:B!P36) -> 284840 | Q36: =SUM(A:B!Q36) -> 292173 | R36: =+AVERAGE(O36:Q36) -> 303068.33 | S36: =+AVERAGE(P36:R36) -> 293360.44 | T36: =+AVERAGE(Q36:S36) -> 296200.59 | U36: =+AVERAGE(R36:T36) -> 297543.12 | V36: =SUM(J36:U36) -> 3202511.5 | W36: =V36/V$39 -> 0.20477794 | Y36: =SUM(A:B!Y36) -> 199248 | Z36: =SUM(A:B!Z36) -> 219927.33 | AA36: =SUM(A:B!AA36) -> 257830.37 | AB36: =SUM(A:B!AB36) -> 276233.46 | AC36: =SUM(A:B!AC36) -> 223098.48 | AD36: =SUM(A:B!AD36) -> 250315.8 | AE36: =SUM(A:B!AE36) -> 289255.85 | AF36: =SUM(A:B!AF36) -> 240914.58 | ... AJ36: =SUM(A:B!AJ36) -> 236783.2 | AK36: =SUM(Y36:AJ36) -> 3012228 | AL36: =AK36/AK$39 -> 0.18367719 | AM36: =IFERROR(AK36/V36-1,0) -> -0.059416968
I37: *Otros Conceptos | J37: =SUM(A:B!J37) -> 20901 | K37: =SUM(A:B!K37) -> 17524 | L37: =SUM(A:B!L37) -> 14837 | M37: =SUM(A:B!M37) -> 12910 | N37: =SUM(A:B!N37) -> 30226 | O37: =SUM(A:B!O37) -> 16552 | P37: =SUM(A:B!P37) -> 12763 | Q37: =SUM(A:B!Q37) -> 19765 | R37: =+AVERAGE(O37:Q37) -> 16360 | S37: =+AVERAGE(P37:R37) -> 16296 | T37: =+AVERAGE(Q37:S37) -> 17473.667 | U37: =+AVERAGE(R37:T37) -> 16709.889 | V37: =SUM(J37:U37) -> 212317.56 | W37: =V37/V$39 -> 0.013576204 | Y37: =SUM(A:B!Y37) -> 0 | Z37: =SUM(A:B!Z37) -> 0 | AA37: =SUM(A:B!AA37) -> 0 | AB37: =SUM(A:B!AB37) -> 0 | AC37: =SUM(A:B!AC37) -> 0 | AD37: =SUM(A:B!AD37) -> 0 | AE37: =SUM(A:B!AE37) -> 0 | AF37: =SUM(A:B!AF37) -> 0 | ... AJ37: =SUM(A:B!AJ37) -> 0 | AK37: =SUM(Y37:AJ37) -> 0 | AL37: =AK37/AK$39 -> 0 | AM37: =IFERROR(AK37/V37-1,0) -> -1
I38: * Aceites y Lubricantes | J38: =SUM(A:B!J38) -> 0 | K38: =SUM(A:B!K38) -> 0 | L38: =SUM(A:B!L38) -> 0 | M38: =SUM(A:B!M38) -> 0 | N38: =SUM(A:B!N38) -> 0 | O38: =SUM(A:B!O38) -> 0 | P38: =SUM(A:B!P38) -> 0 | Q38: =SUM(A:B!Q38) -> 0 | R38: =+AVERAGE(O38:Q38) -> 0 | S38: =+AVERAGE(P38:R38) -> 0 | T38: =+AVERAGE(Q38:S38) -> 0 | U38: =+AVERAGE(R38:T38) -> 0 | V38: =SUM(J38:U38) -> 0 | W38: =V38/V$39 -> 0 | Y38: =SUM(A:B!Y38) -> 7992 | Z38: =SUM(A:B!Z38) -> 8091 | AA38: =SUM(A:B!AA38) -> 8343 | AB38: =SUM(A:B!AB38) -> 8100 | AC38: =SUM(A:B!AC38) -> 8487 | AD38: =SUM(A:B!AD38) -> 8397 | AE38: =SUM(A:B!AE38) -> 8388 | AF38: =SUM(A:B!AF38) -> 8595 | ... AJ38: =SUM(A:B!AJ38) -> 8982 | AK38: =SUM(Y38:AJ38) -> 101646 | AL38: =AK38/AK$39 -> 0.0061980871 | AM38: =IFERROR(AK38/V38-1,0) -> 0
I39: Litros vendidos | J39: =SUM(A:B!J39) -> 1223164 | K39: =SUM(A:B!K39) -> 1160892 | L39: =SUM(A:B!L39) -> 1313320 | M39: =SUM(A:B!M39) -> 1240762 | N39: =SUM(A:B!N39) -> 1272351 | O39: =SUM(A:B!O39) -> 1247404 | P39: =SUM(A:B!P39) -> 1302246 | Q39: =SUM(A:B!Q39) -> 1316933 | ... U39: =SUM(A:B!U39) -> 1369146 | V39: =SUM(J39:U39) -> 15638948 | W39: =V39/V$39 -> 1 | Y39: =SUM(A:B!Y39) -> 1286437.7 | Z39: =SUM(A:B!Z39) -> 1223958.7 | AA39: =SUM(A:B!AA39) -> 1358263.7 | AB39: =SUM(A:B!AB39) -> 1314350.7 | AC39: =SUM(A:B!AC39) -> 1339341.7 | AD39: =SUM(A:B!AD39) -> 1303945.7 | AE39: =SUM(A:B!AE39) -> 1363676.7 | AF39: =SUM(A:B!AF39) -> 1402774.7 | ... AJ39: =SUM(A:B!AJ39) -> 1434781.7 | AK39: =SUM(Y39:AJ39) -> 16399576 | AL39: =AK39/AK$39 -> 1 | AM39: =IFERROR(AK39/V39-1,0) -> 0.048636775
I40: Maxima | J40: =SUM(A:B!J39) -> 1223164 | K40: =SUM(A:B!K40) -> 830539 | L40: =SUM(A:B!L40) -> 933279 | M40: =SUM(A:B!M40) -> 873321 | N40: =SUM(A:B!N40) -> 878218 | O40: =SUM(A:B!O40) -> 887806 | P40: =SUM(A:B!P40) -> 918225 | Q40: =SUM(A:B!Q40) -> 931120 | R40: =SUM(A:B!R40) -> 952306 | ... U40: =SUM(A:B!U40) -> 979221 | V40: =SUM(J40:U40) -> 11404046 | W40: =V40/V$39 -> 0.729208 | Y40: =SUM(A:B!Y40) -> 942905.67 | Z40: =SUM(A:B!Z40) -> 886006.67 | AA40: =SUM(A:B!AA40) -> 970242.67 | AB40: =SUM(A:B!AB40) -> 935885.67 | AC40: =SUM(A:B!AC40) -> 934172.67 | AD40: =SUM(A:B!AD40) -> 933917.67 | AE40: =SUM(A:B!AE40) -> 968135.67 | AF40: =SUM(A:B!AF40) -> 996901.67 | ... AJ40: =SUM(A:B!AJ40) -> 1034961.7 | AK40: =SUM(Y40:AJ40) -> 11722586 | AL40: =AK40/AK$39 -> 0.71481031 | AM40: =IFERROR(AK40/V40-1,0) -> 0.027932192
I41: Super | J41: =SUM(A:B!J40) -> 887027 | K41: =SUM(A:B!K41) -> 231283 | L41: =SUM(A:B!L41) -> 266800 | M41: =SUM(A:B!M41) -> 244981 | N41: =SUM(A:B!N41) -> 284526 | O41: =SUM(A:B!O41) -> 245926 | P41: =SUM(A:B!P41) -> 256948 | Q41: =SUM(A:B!Q41) -> 271880 | R41: =SUM(A:B!R41) -> 273083 | ... U41: =SUM(A:B!U41) -> 276035 | V41: =SUM(J41:U41) -> 3816476 | W41: =V41/V$39 -> 0.24403662 | Y41: =SUM(A:B!Y41) -> 248652 | Z41: =SUM(A:B!Z41) -> 236603 | AA41: =SUM(A:B!AA41) -> 272402 | AB41: =SUM(A:B!AB41) -> 252331 | AC41: =SUM(A:B!AC41) -> 292493 | AD41: =SUM(A:B!AD41) -> 253058 | AE41: =SUM(A:B!AE41) -> 264656 | AF41: =SUM(A:B!AF41) -> 286015 | ... AJ41: =SUM(A:B!AJ41) -> 284316 | AK41: =SUM(Y41:AJ41) -> 3255036 | AL41: =AK41/AK$39 -> 0.19848294 | AM41: =IFERROR(AK41/V41-1,0) -> -0.14710953
I42: Diesel | J42: =SUM(A:B!J41) -> 243300 | K42: =SUM(A:B!K42) -> 99070 | L42: =SUM(A:B!L42) -> 113241 | M42: =SUM(A:B!M42) -> 122460 | N42: =SUM(A:B!N42) -> 109607 | O42: =SUM(A:B!O42) -> 113673 | P42: =SUM(A:B!P42) -> 127073 | Q42: =SUM(A:B!Q42) -> 113934 | R42: =SUM(A:B!R42) -> 122369 | ... U42: =SUM(A:B!U42) -> 113890 | V42: =SUM(J42:U42) -> 1548754 | W42: =V42/V$39 -> 0.099031853 | Y42: =SUM(A:B!Y42) -> 94880 | Z42: =SUM(A:B!Z42) -> 101349 | AA42: =SUM(A:B!AA42) -> 115619 | AB42: =SUM(A:B!AB42) -> 126134 | AC42: =SUM(A:B!AC42) -> 112676 | AD42: =SUM(A:B!AD42) -> 116970 | AE42: =SUM(A:B!AE42) -> 130885 | AF42: =SUM(A:B!AF42) -> 119858 | ... AJ42: =SUM(A:B!AJ42) -> 115504 | AK42: =SUM(Y42:AJ42) -> 1421954 | AL42: =AK42/AK$39 -> 0.086706754 | AM42: =IFERROR(AK42/V42-1,0) -> -0.081872266
I43: Margen de utilidad por combustible | J43: =J33/J39 -> 1.9907134 | K43: =K33/K39 -> 2.2185259 | L43: =L33/L39 -> 2.1445421 | M43: =M33/M39 -> 2.3543379 | N43: =N33/N39 -> 2.4858832 | O43: =O33/O39 -> 2.3427799 | P43: =P33/P39 -> 2.1459156 | Q43: =Q33/Q39 -> 2.1408583 | ... V43: =V33/V39 -> 2.1527635 | W43: =V43/V$39 -> 1.3765398e-07 | Y43: =Y33/Y39 -> 2.1446195 | Z43: =Z33/Z39 -> 2.0925169 | AA43: =AA33/AA39 -> 2.2496733 | AB43: =AB33/AB39 -> 2.1141898 | AC43: =AC33/AC39 -> 2.1882686 | AD43: =AD33/AD39 -> 2.1153897 | AE43: =AE33/AE39 -> 2.196441 | AF43: =AF33/AF39 -> 2.1834277 | ... AK43: =AK33/AK39 -> 2.1597905 | AL43: =AK43/AK$39 -> 1.3169795e-07 | AM43: =IFERROR(AK43/V43-1,0) -> 0.0032641624
I44: Maxima | J44: =IFERROR((J7+J11-(J13+J16+J22+J24+J27))/J40,0) -> 1.3241994 | K44: =IFERROR((K7+K11-(K13+K16+K22+K24+K27))/K40,0) -> 2.1443966 | L44: =IFERROR((L7+L11-(L13+L16+L22+L24+L27))/L40,0) -> 2.0049117 | M44: =IFERROR((M7+M11-(M13+M16+M22+M24+M27))/M40,0) -> 1.9905098 | N44: =IFERROR((N7+N11-(N13+N16+N22+N24+N27))/N40,0) -> 1.9462001 | O44: =IFERROR((O7+O11-(O13+O16+O22+O24+O27))/O40,0) -> 1.8841639 | P44: =IFERROR((P7+P11-(P13+P16+P22+P24+P27))/P40,0) -> 1.9361954 | Q44: =IFERROR((Q7+Q11-(Q13+Q16+Q22+Q24+Q27))/Q40,0) -> 1.9425896 | R44: =R34/R40 -> 1.8727226 | S44: =S34/S40 -> 1.7992541 | T44: =T34/T40 -> 1.8135445 | U44: =U34/U40 -> 1.8349521 | V44: =V34/V40 -> 1.8725387 | W44: =V44/V$39 -> 1.1973559e-07 | Y44: =IFERROR((Y7+Y11-(Y13+Y16+Y22+Y24+Y27))/Y40,0) -> 1.91 | Z44: =IFERROR((Z7+Z11-(Z13+Z16+Z22+Z24+Z27))/Z40,0) -> 1.8417351 | AA44: =IFERROR((AA7+AA11-(AA13+AA16+AA22+AA24+AA27))/AA40,0) -> 1.99 | AB44: =IFERROR((AB7+AB11-(AB13+AB16+AB22+AB24+AB27))/AB40,0) -> 1.8716869 | AC44: =IFERROR((AC7+AC11-(AC13+AC16+AC22+AC24+AC27))/AC40,0) -> 1.9003837 | AD44: =IFERROR((AD7+AD11-(AD13+AD16+AD22+AD24+AD27))/AD40,0) -> 1.8996461 | AE44: =IFERROR((AE7+AE11-(AE13+AE16+AE22+AE24+AE27))/AE40,0) -> 1.9472674 | AF44: =IFERROR((AF7+AF11-(AF13+AF16+AF22+AF24+AF27))/AF40,0) -> 1.9339475 | ... AJ44: =IFERROR((AJ7+AJ11-(AJ13+AJ16+AJ22+AJ24+AJ27))/AJ40,0) -> 1.89 | AK44: =AK34/AK40 -> 1.9138145 | AL44: =AK44/AK$39 -> 1.1669903e-07 | AM44: =IFERROR(AK44/V44-1,0) -> 0.022042716
I45: Super | J45: =IFERROR((J8+J11-(J14+J17+J23+J25+J28))/J41,0) -> 0.77589746 | K45: =IFERROR((K8+K11-(K14+K17+K23+K25+K28))/K41,0) -> 2.7615605 | L45: =IFERROR((L8+L11-(L14+L17+L23+L25+L28))/L41,0) -> 3.0073576 | M45: =IFERROR((M8+M11-(M14+M17+M23+M25+M28))/M41,0) -> 3.1036856 | N45: =IFERROR((N8+N11-(N14+N17+N23+N25+N28))/N41,0) -> 3.5507335 | O45: =IFERROR((O8+O11-(O14+O17+O23+O25+O28))/O41,0) -> 3.4567268 | P45: =IFERROR((P8+P11-(P14+P17+P23+P25+P28))/P41,0) -> 2.7789319 | Q45: =IFERROR((Q8+Q11-(Q14+Q17+Q23+Q25+Q28))/Q41,0) -> 2.5427027 | R45: =R35/R41 -> 2.7192893 | S45: =S35/S41 -> 2.3850273 | T45: =T35/T41 -> 2.5241169 | U45: =U35/U41 -> 2.608547 | V45: =V35/V41 -> 2.3588329 | W45: =V45/V$39 -> 1.5083066e-07 | Y45: =IFERROR((Y8-(Y14+Y17+Y23+Y25+Y28))/Y41,0) -> 3.0191977 | Z45: =IFERROR((Z8-(Z14+Z17+Z23+Z25+Z28))/Z41,0) -> 2.9642327 | AA45: =IFERROR((AA8-(AA14+AA17+AA23+AA25+AA28))/AA41,0) -> 3.1523017 | AB45: =IFERROR((AB8-(AB14+AB17+AB23+AB25+AB28))/AB41,0) -> 2.9436272 | AC45: =IFERROR((AC8-(AC14+AC17+AC23+AC25+AC28))/AC41,0) -> 3.1589381 | AD45: =IFERROR((AD8-(AD14+AD17+AD23+AD25+AD28))/AD41,0) -> 2.8670398 | AE45: =IFERROR((AE8-(AE14+AE17+AE23+AE25+AE28))/AE41,0) -> 3.0695407 | AF45: =IFERROR((AF8-(AF14+AF17+AF23+AF25+AF28))/AF41,0) -> 3.0956135 | ... AJ45: =IFERROR((AJ8-(AJ14+AJ17+AJ23+AJ25+AJ28))/AJ41,0) -> 3.0054643 | AK45: =AK35/AK41 -> 3.0325067 | AL45: =AK45/AK$39 -> 1.8491373e-07 | AM45: =IFERROR(AK45/V45-1,0) -> 0.28559624
I46: Diesel | J46: =IFERROR((J9-(J15+J18+J26))/J42,0) -> 0.6312947 | K46: =IFERROR((K9-(K15+K18+K26))/K42,0) -> 1.7777531 | L46: =IFERROR((L9-(L15+L18+L26))/L42,0) -> 1.5861658 | M46: =IFERROR((M9-(M15+M18+M26))/M42,0) -> 3.6821901 | N46: =IFERROR((N9-(N15+N18+N26))/N42,0) -> 4.1844499 | O46: =IFERROR((O9-(O15+O18+O26))/O42,0) -> 3.7563098 | P46: =IFERROR((P9-(P15+P18+P26))/P42,0) -> 2.6674353 | Q46: =IFERROR((Q9-(Q15+Q18+Q26))/Q42,0) -> 3.0438499 | R46: =R36/R42 -> 2.4766757 | S46: =S36/S42 -> 1.9524952 | T46: =T36/T42 -> 2.4706442 | U46: =U36/U42 -> 2.6125483 | V46: =V36/V42 -> 2.0677987 | W46: =V46/V$39 -> 1.3222109e-07 | Y46: =IFERROR((Y9-(Y15+Y18+Y26))/Y42,0) -> 2.1 | Z46: =IFERROR((Z9-(Z15+Z18+Z26))/Z42,0) -> 2.17 | AA46: =IFERROR((AA9-(AA15+AA18+AA26))/AA42,0) -> 2.23 | AB46: =IFERROR((AB9-(AB15+AB18+AB26))/AB42,0) -> 2.19 | AC46: =IFERROR((AC9-(AC15+AC18+AC26))/AC42,0) -> 1.98 | AD46: =IFERROR((AD9-(AD15+AD18+AD26))/AD42,0) -> 2.14 | AE46: =IFERROR((AE9-(AE15+AE18+AE26))/AE42,0) -> 2.21 | AF46: =IFERROR((AF9-(AF15+AF18+AF26))/AF42,0) -> 2.01 | ... AJ46: =IFERROR((AJ9-(AJ15+AJ18+AJ26))/AJ42,0) -> 2.05 | AK46: =AK36/AK42 -> 2.1183723 | AL46: =AK46/AK$39 -> 1.2917238e-07 | AM46: =IFERROR(AK46/V46-1,0) -> 0.024457706
E48: ( menos ) | I48: GASTO ESTACIONES
A50: E - GASTOS DE OPERACIÓN | B50: estaciones | I50: E - GASTOS DE OPERACIÓN | J50: =SUM(J51:J89) -> 149335 | K50: =SUM(K51:K89) -> 140634 | L50: =SUM(L51:L89) -> 144094 | M50: =SUM(M51:M89) -> 146807 | N50: =SUM(N51:N89) -> 133714 | O50: =SUM(O51:O89) -> 211152 | P50: =SUM(P51:P89) -> 171855 | Q50: =SUM(Q51:Q89) -> 232162 | ... V50: =SUM(V51:V89) -> 2096137.5 | W50: =V50/V$6 -> 0.0063594052 | Y50: =SUM(Y51:Y89) -> 173323.12 | Z50: =SUM(Z51:Z89) -> 151901.52 | AA50: =SUM(AA51:AA89) -> 196710.12 | AB50: =SUM(AB51:AB89) -> 149019.89 | AC50: =SUM(AC51:AC89) -> 245649.72 | AD50: =SUM(AD51:AD89) -> 167657.56 | AE50: =SUM(AE51:AE89) -> 147464.02 | AF50: =SUM(AF51:AF89) -> 172216.74 | ... AK50: =SUM(AK51:AK89) -> 2237854.8 | AL50: =AK50/AK$6 -> 0.0062370677 | AM50: =IFERROR(AK50/V50-1,0) -> 0.067608776
A51: E - GASTOS DE OPERACIÓN | B51: estaciones | C51: Servicios Administrativos | I51: Traslado de Valores | J51: =SUM(A:B!J51) -> 71186 | K51: =SUM(A:B!K51) -> 61124 | L51: =SUM(A:B!L51) -> 62666 | M51: =SUM(A:B!M51) -> 63208 | N51: =SUM(A:B!N51) -> 60682 | O51: =SUM(A:B!O51) -> 63108 | P51: =SUM(A:B!P51) -> 63432 | Q51: =SUM(A:B!Q51) -> 62303 | ... U51: =SUM(A:B!U51) -> 65339.812 | V51: =SUM(J51:U51) -> 772105.06 | W51: =V51/V$6 -> 0.0023424651 | Y51: =SUM(A:B!Y51) -> 59657.677 | Z51: =SUM(A:B!Z51) -> 61089.918 | AA51: =SUM(A:B!AA51) -> 68165.223 | AB51: =SUM(A:B!AB51) -> 66689.4 | AC51: =SUM(A:B!AC51) -> 69755.167 | AD51: =SUM(A:B!AD51) -> 68382.835 | AE51: =SUM(A:B!AE51) -> 70447.4 | AF51: =SUM(A:B!AF51) -> 71160.917 | ... AJ51: =SUM(A:B!AJ51) -> 70588.419 | AK51: =SUM(Y51:AJ51) -> 822194.44 | AL51: =AK51/AK$6 -> 0.0022915171 | AM51: =IFERROR(AK51/V51-1,0) -> 0.064873781
A52: E - GASTOS DE OPERACIÓN | B52: estaciones | I52: Servicios Administrativos | J52: =SUM(A:B!J52) -> 4000 | K52: =SUM(A:B!K52) -> 5000 | L52: =SUM(A:B!L52) -> 4000 | M52: =SUM(A:B!M52) -> 4000 | N52: =SUM(A:B!N52) -> 5000 | O52: =SUM(A:B!O52) -> 4000 | P52: =SUM(A:B!P52) -> 4000 | Q52: =SUM(A:B!Q52) -> 5000 | ... U52: =SUM(A:B!U52) -> 4625 | V52: =SUM(J52:U52) -> 53125 | W52: =V52/V$6 -> 0.00016117426 | Y52: =SUM(A:B!Y52) -> 4200 | Z52: =SUM(A:B!Z52) -> 4200 | AA52: =SUM(A:B!AA52) -> 4200 | AB52: =SUM(A:B!AB52) -> 4200 | AC52: =SUM(A:B!AC52) -> 4200 | AD52: =SUM(A:B!AD52) -> 4200 | AE52: =SUM(A:B!AE52) -> 4200 | AF52: =SUM(A:B!AF52) -> 4200 | ... AJ52: =SUM(A:B!AJ52) -> 4200 | AK52: =SUM(Y52:AJ52) -> 50400 | AL52: =AK52/AK$6 -> 0.00014046855 | AM52: =IFERROR(AK52/V52-1,0) -> -0.051294118
A53: E - GASTOS DE OPERACIÓN | B53: estaciones | I53: Otros Gastos | J53: =SUM(A:B!J53) -> 386 | K53: =SUM(A:B!K53) -> 0 | L53: =SUM(A:B!L53) -> 0 | M53: =SUM(A:B!M53) -> 0 | N53: =SUM(A:B!N53) -> 0 | O53: =SUM(A:B!O53) -> 0 | P53: =SUM(A:B!P53) -> 4841 | Q53: =SUM(A:B!Q53) -> 0 | ... T53: =SUM(A:B!T53) -> 1414.5 | U53: =2400+557 -> 2957 | V53: =SUM(J53:U53) -> 10415.5 | W53: =V53/V$6 -> 3.1599256e-05 | Y53: =SUM(A:B!Y53) -> 1040 | Z53: =SUM(A:B!Z53) -> 1040 | AA53: =SUM(A:B!AA53) -> 1040 | AB53: =SUM(A:B!AB53) -> 1040 | AC53: =SUM(A:B!AC53) -> 1040 | AD53: =SUM(A:B!AD53) -> 1040 | AE53: =SUM(A:B!AE53) -> 1040 | AF53: =SUM(A:B!AF53) -> 1040 | ... AJ53: =SUM(A:B!AJ53) -> 3536 | AK53: =SUM(Y53:AJ53) -> 14976 | AL53: =AK53/AK$6 -> 4.1739226e-05 | AM53: =IFERROR(AK53/V53-1,0) -> 0.43785704
A54: E - GASTOS DE OPERACIÓN | B54: estaciones | I54: Otros impuestos y derechos | J54: =SUM(A:B!J54) -> 0 | K54: =SUM(A:B!K54) -> 0 | L54: =SUM(A:B!L54) -> 0 | M54: =SUM(A:B!M54) -> 0 | N54: =SUM(A:B!N54) -> 0 | O54: =SUM(A:B!O54) -> 0 | P54: =SUM(A:B!P54) -> 0 | Q54: =SUM(A:B!Q54) -> 0 | ... U54: =SUM(A:B!U54) -> 0 | V54: =SUM(J54:U54) -> 0 | W54: =V54/V$6 -> 0 | Y54: =SUM(A:B!Y54) -> 0 | Z54: =SUM(A:B!Z54) -> 0 | AA54: =SUM(A:B!AA54) -> 0 | AB54: =SUM(A:B!AB54) -> 0 | AC54: =SUM(A:B!AC54) -> 0 | AD54: =SUM(A:B!AD54) -> 23897.12 | AE54: =SUM(A:B!AE54) -> 0 | AF54: =SUM(A:B!AF54) -> 0 | ... AJ54: =SUM(A:B!AJ54) -> 0 | AK54: =SUM(Y54:AJ54) -> 23897.12 | AL54: =AK54/AK$6 -> 6.6603051e-05 | AM54: =IFERROR(AK54/V54-1,0) -> 0
A55: E - GASTOS DE OPERACIÓN | B55: estaciones | C55: Costo Marketing | I55: Limpieza | J55: =SUM(A:B!J55) -> 7403 | K55: =SUM(A:B!K55) -> 4200 | L55: =SUM(A:B!L55) -> 0 | M55: =SUM(A:B!M55) -> 6021 | N55: =SUM(A:B!N55) -> 5080 | O55: =SUM(A:B!O55) -> 4579 | P55: =SUM(A:B!P55) -> 1996 | Q55: =SUM(A:B!Q55) -> 8097 | ... U55: =SUM(A:B!U55) -> 5546.3125 | V55: =SUM(J55:U55) -> 57010.562 | W55: =V55/V$6 -> 0.00017296254 | Y55: =SUM(A:B!Y55) -> 5749.9805 | Z55: =SUM(A:B!Z55) -> 5749.9805 | AA55: =SUM(A:B!AA55) -> 5749.9805 | AB55: =SUM(A:B!AB55) -> 5749.9805 | AC55: =SUM(A:B!AC55) -> 5749.9805 | AD55: =SUM(A:B!AD55) -> 5749.9805 | AE55: =SUM(A:B!AE55) -> 5749.9805 | AF55: =SUM(A:B!AF55) -> 5749.9805 | ... AJ55: =SUM(A:B!AJ55) -> 5749.9805 | AK55: =SUM(Y55:AJ55) -> 68999.766 | AL55: =AK55/AK$6 -> 0.00019230748 | AM55: =IFERROR(AK55/V55-1,0) -> 0.21029793
A56: E - GASTOS DE OPERACIÓN | B56: estaciones | E56: x | I56: Propaganda y publicidad | J56: =SUM(A:B!J56) -> 28950 | K56: =SUM(A:B!K56) -> 43277 | L56: =SUM(A:B!L56) -> 55400 | M56: =SUM(A:B!M56) -> 46508 | N56: =SUM(A:B!N56) -> 28961 | O56: =SUM(A:B!O56) -> 56934 | P56: =SUM(A:B!P56) -> 58133 | Q56: =SUM(A:B!Q56) -> 116238 | ... U56: =SUM(A:B!U56) -> 50000 | V56: =SUM(J56:U56) -> 617682 | W56: =V56/V$6 -> 0.0018739659 | Y56: =SUM(A:B!Y56) -> 49560.588 | Z56: =SUM(A:B!Z56) -> 44592.108 | AA56: =SUM(A:B!AA56) -> 87341.738 | AB56: =SUM(A:B!AB56) -> 35690.248 | AC56: =SUM(A:B!AC56) -> 121707.06 | AD56: =SUM(A:B!AD56) -> 5258.308 | AE56: =SUM(A:B!AE56) -> 27409.448 | AF56: =SUM(A:B!AF56) -> 49250.058 | ... AJ56: =SUM(A:B!AJ56) -> 58358.938 | AK56: =SUM(Y56:AJ56) -> 641099.54 | AL56: =AK56/AK$6 -> 0.0017867921 | AM56: =IFERROR(AK56/V56-1,0) -> 0.037911961
A57: E - GASTOS DE OPERACIÓN | B57: estaciones | E57: x | I57: Capacitación al personal | J57: =SUM(A:B!J57) -> 0 | K57: =SUM(A:B!K57) -> 0 | L57: =SUM(A:B!L57) -> 0 | M57: =SUM(A:B!M57) -> 0 | N57: =SUM(A:B!N57) -> 0 | O57: =SUM(A:B!O57) -> 0 | P57: =SUM(A:B!P57) -> 0 | Q57: =SUM(A:B!Q57) -> 0 | ... U57: =SUM(A:B!U57) -> 0 | V57: =SUM(J57:U57) -> 3640 | W57: =V57/V$6 -> 1.1043281e-05 | Y57: =SUM(A:B!Y57) -> 0 | Z57: =SUM(A:B!Z57) -> 6568.9038 | AA57: =SUM(A:B!AA57) -> 1231.6695 | AB57: =SUM(A:B!AB57) -> 0 | AC57: =SUM(A:B!AC57) -> 0 | AD57: =SUM(A:B!AD57) -> 0 | AE57: =SUM(A:B!AE57) -> 0 | AF57: =SUM(A:B!AF57) -> 0 | ... AJ57: =SUM(A:B!AJ57) -> 0 | AK57: =SUM(Y57:AJ57) -> 7800.5733 | AL57: =AK57/AK$6 -> 2.1740778e-05 | AM57: =IFERROR(AK57/V57-1,0) -> 1.1430146
A58: E - GASTOS DE OPERACIÓN | B58: estaciones | I58: Honorarios Fiscales P.M. | J58: =SUM(A:B!J58) -> 0 | K58: =SUM(A:B!K58) -> 0 | L58: =SUM(A:B!L58) -> 0 | M58: =SUM(A:B!M58) -> 0 | N58: =SUM(A:B!N58) -> 0 | O58: =SUM(A:B!O58) -> 0 | P58: =SUM(A:B!P58) -> 0 | Q58: =SUM(A:B!Q58) -> 0 | ... U58: =SUM(A:B!U58) -> 0 | V58: =SUM(J58:U58) -> 0 | W58: =V58/V$6 -> 0 | Y58: =SUM(A:B!Y58) -> 0 | Z58: =SUM(A:B!Z58) -> 0 | AA58: =SUM(A:B!AA58) -> 0 | AB58: =SUM(A:B!AB58) -> 0 | AC58: =SUM(A:B!AC58) -> 0 | AD58: =SUM(A:B!AD58) -> 0 | AE58: =SUM(A:B!AE58) -> 0 | AF58: =SUM(A:B!AF58) -> 0 | ... AJ58: =SUM(A:B!AJ58) -> 0 | AK58: =SUM(Y58:AJ58) -> 0 | AL58: =AK58/AK$6 -> 0 | AM58: =IFERROR(AK58/V58-1,0) -> 0
A59: E - GASTOS DE OPERACIÓN | B59: estaciones | I59: Honorarios Administrativos P.M. | J59: =SUM(A:B!J59) -> 0 | K59: =SUM(A:B!K59) -> 0 | L59: =SUM(A:B!L59) -> 0 | M59: =SUM(A:B!M59) -> 0 | N59: =SUM(A:B!N59) -> 0 | O59: =SUM(A:B!O59) -> 0 | P59: =SUM(A:B!P59) -> 0 | Q59: =SUM(A:B!Q59) -> 0 | ... U59: =SUM(A:B!U59) -> 0 | V59: =SUM(J59:U59) -> 0 | W59: =V59/V$6 -> 0 | Y59: =SUM(A:B!Y59) -> 0 | Z59: =SUM(A:B!Z59) -> 0 | AA59: =SUM(A:B!AA59) -> 0 | AB59: =SUM(A:B!AB59) -> 0 | AC59: =SUM(A:B!AC59) -> 0 | AD59: =SUM(A:B!AD59) -> 0 | AE59: =SUM(A:B!AE59) -> 0 | AF59: =SUM(A:B!AF59) -> 0 | ... AJ59: =SUM(A:B!AJ59) -> 0 | AK59: =SUM(Y59:AJ59) -> 0 | AL59: =AK59/AK$6 -> 0 | AM59: =IFERROR(AK59/V59-1,0) -> 0
A60: E - GASTOS DE OPERACIÓN | B60: estaciones | I60: Asistencia técnica | J60: =SUM(A:B!J60) -> 0 | K60: =SUM(A:B!K60) -> 0 | L60: =SUM(A:B!L60) -> 0 | M60: =SUM(A:B!M60) -> 0 | N60: =SUM(A:B!N60) -> 0 | O60: =SUM(A:B!O60) -> 0 | P60: =SUM(A:B!P60) -> 0 | Q60: =SUM(A:B!Q60) -> 0 | ... U60: =SUM(A:B!U60) -> 0 | V60: =SUM(J60:U60) -> 0 | W60: =V60/V$6 -> 0 | Y60: =SUM(A:B!Y60) -> 0 | Z60: =SUM(A:B!Z60) -> 0 | AA60: =SUM(A:B!AA60) -> 0 | AB60: =SUM(A:B!AB60) -> 0 | AC60: =SUM(A:B!AC60) -> 0 | AD60: =SUM(A:B!AD60) -> 0 | AE60: =SUM(A:B!AE60) -> 0 | AF60: =SUM(A:B!AF60) -> 0 | ... AJ60: =SUM(A:B!AJ60) -> 0 | AK60: =SUM(Y60:AJ60) -> 0 | AL60: =AK60/AK$6 -> 0 | AM60: =IFERROR(AK60/V60-1,0) -> 0
A61: E - GASTOS DE OPERACIÓN | B61: estaciones | I61: Gastos no deducibles (sin requisitos fiscales) | J61: =SUM(A:B!J61) -> 1500 | K61: =SUM(A:B!K61) -> 554 | L61: =SUM(A:B!L61) -> -555 | M61: =SUM(A:B!M61) -> 169 | N61: =SUM(A:B!N61) -> 1200 | O61: =SUM(A:B!O61) -> -2719 | P61: =SUM(A:B!P61) -> 4319 | Q61: =SUM(A:B!Q61) -> 783 | ... U61: =SUM(A:B!U61) -> 0 | V61: =SUM(J61:U61) -> 7553 | W61: =V61/V$6 -> 2.2914808e-05 | Y61: =SUM(A:B!Y61) -> 0 | Z61: =SUM(A:B!Z61) -> 0 | AA61: =SUM(A:B!AA61) -> 0 | AB61: =SUM(A:B!AB61) -> 0 | AC61: =SUM(A:B!AC61) -> 0 | AD61: =SUM(A:B!AD61) -> 0 | AE61: =SUM(A:B!AE61) -> 0 | AF61: =SUM(A:B!AF61) -> 0 | ... AJ61: =SUM(A:B!AJ61) -> 0 | AK61: =SUM(Y61:AJ61) -> 0 | AL61: =AK61/AK$6 -> 0 | AM61: =IFERROR(AK61/V61-1,0) -> -1
A62: E - GASTOS DE OPERACIÓN | B62: estaciones | I62: Papelería y artículos de oficina | J62: =SUM(A:B!J62) -> 4603 | K62: =SUM(A:B!K62) -> 2640 | L62: =SUM(A:B!L62) -> 1962 | M62: =SUM(A:B!M62) -> 3960 | N62: =SUM(A:B!N62) -> 3161 | O62: =SUM(A:B!O62) -> 3802 | P62: =SUM(A:B!P62) -> 3025 | Q62: =SUM(A:B!Q62) -> 5693 | ... U62: =SUM(A:B!U62) -> 3623.125 | V62: =SUM(J62:U62) -> 41268.625 | W62: =V62/V$6 -> 0.00012520358 | Y62: =SUM(A:B!Y62) -> 3622.85 | Z62: =SUM(A:B!Z62) -> 3622.85 | AA62: =SUM(A:B!AA62) -> 3622.85 | AB62: =SUM(A:B!AB62) -> 3622.85 | AC62: =SUM(A:B!AC62) -> 3622.85 | AD62: =SUM(A:B!AD62) -> 3622.85 | AE62: =SUM(A:B!AE62) -> 3622.85 | AF62: =SUM(A:B!AF62) -> 3622.85 | ... AJ62: =SUM(A:B!AJ62) -> 3622.85 | AK62: =SUM(Y62:AJ62) -> 43474.2 | AL62: =AK62/AK$6 -> 0.00012116583 | AM62: =IFERROR(AK62/V62-1,0) -> 0.053444354
A63: E - GASTOS DE OPERACIÓN | B63: estaciones | I63: Faltantes | J63: =SUM(A:B!J63) -> 0 | K63: =SUM(A:B!K63) -> 0 | L63: =SUM(A:B!L63) -> 0 | M63: =SUM(A:B!M63) -> 0 | N63: =SUM(A:B!N63) -> 0 | O63: =SUM(A:B!O63) -> 0 | P63: =SUM(A:B!P63) -> 0 | Q63: =SUM(A:B!Q63) -> 0 | ... U63: =SUM(A:B!U63) -> 0 | V63: =SUM(J63:U63) -> 0 | W63: =V63/V$6 -> 0 | Y63: =SUM(A:B!Y63) -> 0 | Z63: =SUM(A:B!Z63) -> 0 | AA63: =SUM(A:B!AA63) -> 0 | AB63: =SUM(A:B!AB63) -> 0 | AC63: =SUM(A:B!AC63) -> 0 | AD63: =SUM(A:B!AD63) -> 0 | AE63: =SUM(A:B!AE63) -> 0 | AF63: =SUM(A:B!AF63) -> 0 | ... AJ63: =SUM(A:B!AJ63) -> 0 | AK63: =SUM(Y63:AJ63) -> 0 | AL63: =AK63/AK$6 -> 0 | AM63: =IFERROR(AK63/V63-1,0) -> 0
A64: E - GASTOS DE OPERACIÓN | B64: estaciones | I64: Licencias y Permisos | J64: =SUM(A:B!J64) -> 0 | K64: =SUM(A:B!K64) -> 0 | L64: =SUM(A:B!L64) -> 0 | M64: =SUM(A:B!M64) -> 0 | N64: =SUM(A:B!N64) -> 0 | O64: =SUM(A:B!O64) -> 0 | P64: =SUM(A:B!P64) -> 0 | Q64: =SUM(A:B!Q64) -> 0 | ... U64: =SUM(A:B!U64) -> 0 | V64: =SUM(J64:U64) -> 0 | W64: =V64/V$6 -> 0 | Y64: =SUM(A:B!Y64) -> 0 | Z64: =SUM(A:B!Z64) -> 0 | AA64: =SUM(A:B!AA64) -> 0 | AB64: =SUM(A:B!AB64) -> 0 | AC64: =SUM(A:B!AC64) -> 0 | AD64: =SUM(A:B!AD64) -> 0 | AE64: =SUM(A:B!AE64) -> 0 | AF64: =SUM(A:B!AF64) -> 0 | ... AJ64: =SUM(A:B!AJ64) -> 0 | AK64: =SUM(Y64:AJ64) -> 0 | AL64: =AK64/AK$6 -> 0 | AM64: =IFERROR(AK64/V64-1,0) -> 0
A65: E - GASTOS DE OPERACIÓN | B65: estaciones | I65: Licencias, Software, Antivirus | J65: =SUM(A:B!J65) -> 7256 | K65: =SUM(A:B!K65) -> 7256 | L65: =SUM(A:B!L65) -> 7256 | M65: =SUM(A:B!M65) -> 7256 | N65: =SUM(A:B!N65) -> 7256 | O65: =SUM(A:B!O65) -> 7256 | P65: =SUM(A:B!P65) -> 7256 | Q65: =SUM(A:B!Q65) -> 7256 | ... U65: =SUM(A:B!U65) -> 7256 | V65: =SUM(J65:U65) -> 87072 | W65: =V65/V$6 -> 0.00026416499 | Y65: =SUM(A:B!Y65) -> 11669.717 | Z65: =SUM(A:B!Z65) -> 11669.717 | AA65: =SUM(A:B!AA65) -> 11669.717 | AB65: =SUM(A:B!AB65) -> 11669.717 | AC65: =SUM(A:B!AC65) -> 11669.717 | AD65: =SUM(A:B!AD65) -> 11669.717 | AE65: =SUM(A:B!AE65) -> 11669.717 | AF65: =SUM(A:B!AF65) -> 11669.717 | ... AJ65: =SUM(A:B!AJ65) -> 11669.717 | AK65: =SUM(Y65:AJ65) -> 140036.61 | AL65: =AK65/AK$6 -> 0.00039029245 | AM65: =IFERROR(AK65/V65-1,0) -> 0.6082852
A66: E - GASTOS DE OPERACIÓN | B66: estaciones | I66: Fletes Combustible | J66: =SUM(A:B!J66) -> 0 | K66: =SUM(A:B!K66) -> 0 | L66: =SUM(A:B!L66) -> 0 | M66: =SUM(A:B!M66) -> 0 | N66: =SUM(A:B!N66) -> 0 | O66: =SUM(A:B!O66) -> 0 | P66: =SUM(A:B!P66) -> 0 | Q66: =SUM(A:B!Q66) -> 0 | ... U66: =SUM(A:B!U66) -> 0 | V66: =SUM(J66:U66) -> 0 | W66: =V66/V$6 -> 0 | Y66: =SUM(A:B!Y66) -> 0 | Z66: =SUM(A:B!Z66) -> 0 | AA66: =SUM(A:B!AA66) -> 0 | AB66: =SUM(A:B!AB66) -> 0 | AC66: =SUM(A:B!AC66) -> 0 | AD66: =SUM(A:B!AD66) -> 0 | AE66: =SUM(A:B!AE66) -> 0 | AF66: =SUM(A:B!AF66) -> 0 | ... AJ66: =SUM(A:B!AJ66) -> 0 | AK66: =SUM(Y66:AJ66) -> 0 | AL66: =AK66/AK$6 -> 0 | AM66: =IFERROR(AK66/V66-1,0) -> 0
A67: E - GASTOS DE OPERACIÓN | B67: estaciones | I67: Viáticos y gastos de viaje | J67: =SUM(A:B!J67) -> 0 | K67: =SUM(A:B!K67) -> 0 | L67: =SUM(A:B!L67) -> 0 | M67: =SUM(A:B!M67) -> 3048 | N67: =SUM(A:B!N67) -> 2097 | O67: =SUM(A:B!O67) -> 2669 | P67: =SUM(A:B!P67) -> 2793 | Q67: =SUM(A:B!Q67) -> 0 | ... U67: =SUM(A:B!U67) -> 0 | V67: =SUM(J67:U67) -> 10850 | W67: =V67/V$6 -> 3.2917472e-05 | Y67: =SUM(A:B!Y67) -> 0 | Z67: =SUM(A:B!Z67) -> 0 | AA67: =SUM(A:B!AA67) -> 0 | AB67: =SUM(A:B!AB67) -> 0 | AC67: =SUM(A:B!AC67) -> 0 | AD67: =SUM(A:B!AD67) -> 0 | AE67: =SUM(A:B!AE67) -> 0 | AF67: =SUM(A:B!AF67) -> 0 | ... AJ67: =SUM(A:B!AJ67) -> 0 | AK67: =SUM(Y67:AJ67) -> 0 | AL67: =AK67/AK$6 -> 0 | AM67: =IFERROR(AK67/V67-1,0) -> -1
A68: E - GASTOS DE OPERACIÓN | B68: estaciones | I68: Recolección de Basura | J68: =SUM(A:B!J68) -> 1664 | K68: =SUM(A:B!K68) -> 1664 | L68: =SUM(A:B!L68) -> 1664 | M68: =SUM(A:B!M68) -> 1664 | N68: =SUM(A:B!N68) -> 1664 | O68: =SUM(A:B!O68) -> 1664 | P68: =SUM(A:B!P68) -> 3328 | Q68: =SUM(A:B!Q68) -> 1664 | ... U68: =SUM(A:B!U68) -> 1664 | V68: =SUM(J68:U68) -> 21632 | W68: =V68/V$6 -> 6.5628641e-05 | Y68: =SUM(A:B!Y68) -> 1730.56 | Z68: =SUM(A:B!Z68) -> 1730.56 | AA68: =SUM(A:B!AA68) -> 1730.56 | AB68: =SUM(A:B!AB68) -> 1730.56 | AC68: =SUM(A:B!AC68) -> 1730.56 | AD68: =SUM(A:B!AD68) -> 1730.56 | AE68: =SUM(A:B!AE68) -> 1730.56 | AF68: =SUM(A:B!AF68) -> 1730.56 | ... AJ68: =SUM(A:B!AJ68) -> 1730.56 | AK68: =SUM(Y68:AJ68) -> 20766.72 | AL68: =AK68/AK$6 -> 5.7878393e-05 | AM68: =IFERROR(AK68/V68-1,0) -> -0.04
A69: E - GASTOS DE OPERACIÓN | B69: estaciones | I69: Honorarios de Consultoria | J69: =SUM(A:B!J69) -> 0 | K69: =SUM(A:B!K69) -> 0 | L69: =SUM(A:B!L69) -> 0 | M69: =SUM(A:B!M69) -> 0 | N69: =SUM(A:B!N69) -> 0 | O69: =SUM(A:B!O69) -> 0 | P69: =SUM(A:B!P69) -> 0 | Q69: =SUM(A:B!Q69) -> 0 | ... U69: =SUM(A:B!U69) -> 0 | V69: =SUM(J69:U69) -> 0 | W69: =V69/V$6 -> 0 | Y69: =SUM(A:B!Y69) -> 0 | Z69: =SUM(A:B!Z69) -> 0 | AA69: =SUM(A:B!AA69) -> 0 | AB69: =SUM(A:B!AB69) -> 0 | AC69: =SUM(A:B!AC69) -> 0 | AD69: =SUM(A:B!AD69) -> 0 | AE69: =SUM(A:B!AE69) -> 0 | AF69: =SUM(A:B!AF69) -> 0 | ... AJ69: =SUM(A:B!AJ69) -> 0 | AK69: =SUM(Y69:AJ69) -> 0 | AL69: =AK69/AK$6 -> 0 | AM69: =IFERROR(AK69/V69-1,0) -> 0
... A71: E - GASTOS DE OPERACIÓN | B71: estaciones | I71: Fletes Mensajeria | J71: =SUM(A:B!J71) -> 0 | K71: =SUM(A:B!K71) -> 0 | L71: =SUM(A:B!L71) -> 0 | M71: =SUM(A:B!M71) -> 0 | N71: =SUM(A:B!N71) -> 0 | O71: =SUM(A:B!O71) -> 0 | P71: =SUM(A:B!P71) -> 0 | Q71: =SUM(A:B!Q71) -> 0 | ... U71: =SUM(A:B!U71) -> 0 | V71: =SUM(J71:U71) -> 0 | W71: =V71/V$6 -> 0 | Y71: =SUM(A:B!Y71) -> 0 | Z71: =SUM(A:B!Z71) -> 0 | AA71: =SUM(A:B!AA71) -> 0 | AB71: =SUM(A:B!AB71) -> 0 | AC71: =SUM(A:B!AC71) -> 0 | AD71: =SUM(A:B!AD71) -> 0 | AE71: =SUM(A:B!AE71) -> 0 | AF71: =SUM(A:B!AF71) -> 0 | ... AJ71: =SUM(A:B!AJ71) -> 0 | AK71: =SUM(Y71:AJ71) -> 0 | AL71: =AK71/AK$6 -> 0 | AM71: =IFERROR(AK71/V71-1,0) -> 0
I72: Honorarios Administrativos P.F. | J72: =SUM(A:B!J72) -> 0 | K72: =SUM(A:B!K72) -> 0 | L72: =SUM(A:B!L72) -> 0 | M72: =SUM(A:B!M72) -> 0 | N72: =SUM(A:B!N72) -> 0 | O72: =SUM(A:B!O72) -> 0 | P72: =SUM(A:B!P72) -> 0 | Q72: =SUM(A:B!Q72) -> 0 | ... U72: =SUM(A:B!U72) -> 0 | V72: =SUM(J72:U72) -> 0 | W72: =V72/V$6 -> 0 | Y72: =SUM(A:B!Y72) -> 0 | Z72: =SUM(A:B!Z72) -> 0 | AA72: =SUM(A:B!AA72) -> 0 | AB72: =SUM(A:B!AB72) -> 0 | AC72: =SUM(A:B!AC72) -> 0 | AD72: =SUM(A:B!AD72) -> 0 | AE72: =SUM(A:B!AE72) -> 0 | AF72: =SUM(A:B!AF72) -> 0 | ... AJ72: =SUM(A:B!AJ72) -> 0 | AK72: =SUM(Y72:AJ72) -> 0 | AL72: =AK72/AK$6 -> 0 | AM72: =IFERROR(AK72/V72-1,0) -> 0
I73: Consumos Propios Combustibles | J73: =SUM(A:B!J73) -> 0 | K73: =SUM(A:B!K73) -> 5215 | L73: =SUM(A:B!L73) -> 2103 | M73: =SUM(A:B!M73) -> 1656 | N73: =SUM(A:B!N73) -> 1812 | O73: =SUM(A:B!O73) -> 1949 | P73: =SUM(A:B!P73) -> 2020 | Q73: =SUM(A:B!Q73) -> 725 | ... U73: =SUM(A:B!U73) -> 0 | V73: =SUM(J73:U73) -> 16175 | W73: =V73/V$6 -> 4.9072821e-05 | Y73: =SUM(A:B!Y73) -> 0 | Z73: =SUM(A:B!Z73) -> 0 | AA73: =SUM(A:B!AA73) -> 0 | AB73: =SUM(A:B!AB73) -> 0 | AC73: =SUM(A:B!AC73) -> 0 | AD73: =SUM(A:B!AD73) -> 0 | AE73: =SUM(A:B!AE73) -> 0 | AF73: =SUM(A:B!AF73) -> 0 | ... AJ73: =SUM(A:B!AJ73) -> 0 | AK73: =SUM(Y73:AJ73) -> 0 | AL73: =AK73/AK$6 -> 0 | AM73: =IFERROR(AK73/V73-1,0) -> -1
I74: Renta Equipo de Sistemas | J74: =SUM(A:B!J74) -> 1620 | K74: =SUM(A:B!K74) -> 1867 | L74: =SUM(A:B!L74) -> 1554 | M74: =SUM(A:B!M74) -> 1597 | N74: =SUM(A:B!N74) -> 1515 | O74: =SUM(A:B!O74) -> 1645 | P74: =SUM(A:B!P74) -> 1654 | Q74: =SUM(A:B!Q74) -> 1616 | ... U74: =SUM(A:B!U74) -> 1607.4375 | V74: =SUM(J74:U74) -> 19489.188 | W74: =V74/V$6 -> 5.912763e-05 | Y74: =SUM(A:B!Y74) -> 2173.71 | Z74: =SUM(A:B!Z74) -> 2173.71 | AA74: =SUM(A:B!AA74) -> 2173.71 | AB74: =SUM(A:B!AB74) -> 2173.71 | AC74: =SUM(A:B!AC74) -> 2173.71 | AD74: =SUM(A:B!AD74) -> 2173.71 | AE74: =SUM(A:B!AE74) -> 2173.71 | AF74: =SUM(A:B!AF74) -> 2173.71 | ... AJ74: =SUM(A:B!AJ74) -> 2173.71 | AK74: =SUM(Y74:AJ74) -> 26084.52 | AL74: =AK74/AK$6 -> 7.2699498e-05 | AM74: =IFERROR(AK74/V74-1,0) -> 0.33840982
I75: Timbrado Facturas | J75: =SUM(A:B!J75) -> 3272 | K75: =SUM(A:B!K75) -> 5065 | L75: =SUM(A:B!L75) -> 3231 | M75: =SUM(A:B!M75) -> 3598 | N75: =SUM(A:B!N75) -> 3473 | O75: =SUM(A:B!O75) -> 5434 | P75: =SUM(A:B!P75) -> 4665 | Q75: =SUM(A:B!Q75) -> 4760 | ... U75: =SUM(A:B!U75) -> 3442.1875 | V75: =SUM(J75:U75) -> 45948.938 | W75: =V75/V$6 -> 0.00013940303 | Y75: =SUM(A:B!Y75) -> 3315.9502 | Z75: =SUM(A:B!Z75) -> 2995.0518 | AA75: =SUM(A:B!AA75) -> 3315.9502 | AB75: =SUM(A:B!AB75) -> 3208.9841 | AC75: =SUM(A:B!AC75) -> 3315.9502 | AD75: =SUM(A:B!AD75) -> 3208.9841 | AE75: =SUM(A:B!AE75) -> 3315.9502 | AF75: =SUM(A:B!AF75) -> 3315.9502 | ... AJ75: =SUM(A:B!AJ75) -> 3315.9502 | AK75: =SUM(Y75:AJ75) -> 39042.64 | AL75: =AK75/AK$6 -> 0.00010881474 | AM75: =IFERROR(AK75/V75-1,0) -> -0.15030375
E76: x | I76: Uniformes | J76: =SUM(A:B!J76) -> 13204 | K76: =SUM(A:B!K76) -> 0 | L76: =SUM(A:B!L76) -> 2041 | M76: =SUM(A:B!M76) -> 620 | N76: =SUM(A:B!N76) -> 2676 | O76: =SUM(A:B!O76) -> 58059 | P76: =SUM(A:B!P76) -> 9140 | Q76: =SUM(A:B!Q76) -> 6869 | ... U76: =SUM(A:B!U76) -> 15358.72 | V76: =SUM(J76:U76) -> 173993.44 | W76: =V76/V$6 -> 0.0005278732 | Y76: =SUM(A:B!Y76) -> 5719.9212 | Z76: =SUM(A:B!Z76) -> 5719.9212 | AA76: =SUM(A:B!AA76) -> 5719.9212 | AB76: =SUM(A:B!AB76) -> 11439.842 | AC76: =SUM(A:B!AC76) -> 14299.803 | AD76: =SUM(A:B!AD76) -> 28599.606 | AE76: =SUM(A:B!AE76) -> 14299.803 | AF76: =SUM(A:B!AF76) -> 8579.8818 | ... AJ76: =SUM(A:B!AJ76) -> 22879.685 | AK76: =SUM(Y76:AJ76) -> 180188.68 | AL76: =AK76/AK$6 -> 0.00050219924 | AM76: =IFERROR(AK76/V76-1,0) -> 0.035606147
E77: x | I77: Contratacion Empleados | J77: =SUM(A:B!J77) -> 0 | K77: =SUM(A:B!K77) -> 0 | L77: =SUM(A:B!L77) -> 0 | M77: =SUM(A:B!M77) -> 730 | N77: =SUM(A:B!N77) -> 0 | O77: =SUM(A:B!O77) -> 0 | P77: =SUM(A:B!P77) -> 0 | Q77: =SUM(A:B!Q77) -> 1460 | ... U77: =SUM(A:B!U77) -> 520 | V77: =SUM(J77:U77) -> 3230 | W77: =V77/V$6 -> 9.7993949e-06 | Y77: =SUM(A:B!Y77) -> 0 | Z77: =SUM(A:B!Z77) -> 0 | AA77: =SUM(A:B!AA77) -> 0 | AB77: =SUM(A:B!AB77) -> 1055.802 | AC77: =SUM(A:B!AC77) -> 0 | AD77: =SUM(A:B!AD77) -> 1055.802 | AE77: =SUM(A:B!AE77) -> 1055.802 | AF77: =SUM(A:B!AF77) -> 3167.406 | ... AJ77: =SUM(A:B!AJ77) -> 0 | AK77: =SUM(Y77:AJ77) -> 8446.416 | AL77: =AK77/AK$6 -> 2.354079e-05 | AM77: =IFERROR(AK77/V77-1,0) -> 1.6149895
I78: Seguros y fianzas | J78: =SUM(A:B!J78) -> 4291 | K78: =SUM(A:B!K78) -> 2772 | L78: =SUM(A:B!L78) -> 2772 | M78: =SUM(A:B!M78) -> 2772 | N78: =SUM(A:B!N78) -> 2772 | O78: =SUM(A:B!O78) -> 2772 | P78: =SUM(A:B!P78) -> 1253 | Q78: =SUM(A:B!Q78) -> 2772 | ... U78: =SUM(A:B!U78) -> 0 | V78: =SUM(J78:U78) -> 27720 | W78: =V78/V$6 -> 8.4098832e-05 | Y78: =SUM(A:B!Y78) -> 1881.5264 | Z78: =SUM(A:B!Z78) -> 0 | AA78: =SUM(A:B!AA78) -> 0 | AB78: =SUM(A:B!AB78) -> 0 | AC78: =SUM(A:B!AC78) -> 0 | AD78: =SUM(A:B!AD78) -> 0 | AE78: =SUM(A:B!AE78) -> 0 | AF78: =SUM(A:B!AF78) -> 0 | ... AJ78: =SUM(A:B!AJ78) -> 0 | AK78: =SUM(Y78:AJ78) -> 1881.5264 | AL78: =AK78/AK$6 -> 5.243954e-06 | AM78: =IFERROR(AK78/V78-1,0) -> -0.93212387
I79: Honorarios Legales P.F. | J79: =SUM(A:B!J79) -> 0 | K79: =SUM(A:B!K79) -> 0 | L79: =SUM(A:B!L79) -> 0 | M79: =SUM(A:B!M79) -> 0 | N79: =SUM(A:B!N79) -> 0 | O79: =SUM(A:B!O79) -> 0 | P79: =SUM(A:B!P79) -> 0 | Q79: =SUM(A:B!Q79) -> 0 | ... U79: =SUM(A:B!U79) -> 0 | V79: =SUM(J79:U79) -> 0 | W79: =V79/V$6 -> 0 | Y79: =SUM(A:B!Y79) -> 0 | Z79: =SUM(A:B!Z79) -> 0 | AA79: =SUM(A:B!AA79) -> 0 | AB79: =SUM(A:B!AB79) -> 0 | AC79: =SUM(A:B!AC79) -> 0 | AD79: =SUM(A:B!AD79) -> 0 | AE79: =SUM(A:B!AE79) -> 0 | AF79: =SUM(A:B!AF79) -> 0 | ... AJ79: =SUM(A:B!AJ79) -> 0 | AK79: =SUM(Y79:AJ79) -> 0 | AL79: =AK79/AK$6 -> 0 | AM79: =IFERROR(AK79/V79-1,0) -> 0
I80: Prediales | J80: =SUM(A:B!J80) -> 0 | K80: =SUM(A:B!K80) -> 0 | L80: =SUM(A:B!L80) -> 0 | M80: =SUM(A:B!M80) -> 0 | N80: =SUM(A:B!N80) -> 0 | O80: =SUM(A:B!O80) -> 0 | P80: =SUM(A:B!P80) -> 0 | Q80: =SUM(A:B!Q80) -> 0 | ... U80: =SUM(A:B!U80) -> 0 | V80: =SUM(J80:U80) -> 0 | W80: =V80/V$6 -> 0 | Y80: =SUM(A:B!Y80) -> 22251.84 | Z80: =SUM(A:B!Z80) -> 0 | AA80: =SUM(A:B!AA80) -> 0 | AB80: =SUM(A:B!AB80) -> 0 | AC80: =SUM(A:B!AC80) -> 0 | AD80: =SUM(A:B!AD80) -> 0 | AE80: =SUM(A:B!AE80) -> 0 | AF80: =SUM(A:B!AF80) -> 0 | ... AJ80: =SUM(A:B!AJ80) -> 0 | AK80: =SUM(Y80:AJ80) -> 22251.84 | AL80: =AK80/AK$6 -> 6.2017533e-05 | AM80: =IFERROR(AK80/V80-1,0) -> 0
I81: Certificado para el cumplimiento SAT anexo 30 y 31 | J81: =SUM(A:B!J81) -> 0 | K81: =SUM(A:B!K81) -> 0 | L81: =SUM(A:B!L81) -> 0 | M81: =SUM(A:B!M81) -> 0 | N81: =SUM(A:B!N81) -> 0 | O81: =SUM(A:B!O81) -> 0 | P81: =SUM(A:B!P81) -> 0 | Q81: =SUM(A:B!Q81) -> 0 | ... U81: =SUM(A:B!U81) -> 0 | V81: =SUM(J81:U81) -> 38480 | W81: =V81/V$6 -> 0.00011674326 | Y81: =SUM(A:B!Y81) -> 0 | Z81: =SUM(A:B!Z81) -> 0 | AA81: =SUM(A:B!AA81) -> 0 | AB81: =SUM(A:B!AB81) -> 0 | AC81: =SUM(A:B!AC81) -> 0 | AD81: =SUM(A:B!AD81) -> 0 | AE81: =SUM(A:B!AE81) -> 0 | AF81: =SUM(A:B!AF81) -> 0 | ... AJ81: =SUM(A:B!AJ81) -> 0 | AK81: =SUM(Y81:AJ81) -> 37056.58 | AL81: =AK81/AK$6 -> 0.00010327944 | AM81: =IFERROR(AK81/V81-1,0) -> -0.036991164
I82: Arrendamiento Tecnologico | J82: =SUM(A:B!J82) -> 0 | K82: =SUM(A:B!K82) -> 0 | L82: =SUM(A:B!L82) -> 0 | M82: =SUM(A:B!M82) -> 0 | N82: =SUM(A:B!N82) -> 0 | O82: =SUM(A:B!O82) -> 0 | P82: =SUM(A:B!P82) -> 0 | Q82: =SUM(A:B!Q82) -> 0 | ... U82: =SUM(A:B!U82) -> 0 | V82: =SUM(J82:U82) -> 0 | W82: =V82/V$6 -> 0 | Y82: =SUM(A:B!Y82) -> 0 | Z82: =SUM(A:B!Z82) -> 0 | AA82: =SUM(A:B!AA82) -> 0 | AB82: =SUM(A:B!AB82) -> 0 | AC82: =SUM(A:B!AC82) -> 0 | AD82: =SUM(A:B!AD82) -> 0 | AE82: =SUM(A:B!AE82) -> 0 | AF82: =SUM(A:B!AF82) -> 0 | ... AJ82: =SUM(A:B!AJ82) -> 0 | AK82: =SUM(Y82:AJ82) -> 0 | AL82: =AK82/AK$6 -> 0 | AM82: =IFERROR(AK82/V82-1,0) -> 0
I83: Asesoría en sistemas | J83: =SUM(A:B!J83) -> 0 | K83: =SUM(A:B!K83) -> 0 | L83: =SUM(A:B!L83) -> 0 | M83: =SUM(A:B!M83) -> 0 | N83: =SUM(A:B!N83) -> 0 | O83: =SUM(A:B!O83) -> 0 | P83: =SUM(A:B!P83) -> 0 | Q83: =SUM(A:B!Q83) -> 0 | ... U83: =SUM(A:B!U83) -> 0 | V83: =SUM(J83:U83) -> 0 | W83: =V83/V$6 -> 0 | Y83: =SUM(A:B!Y83) -> 0 | Z83: =SUM(A:B!Z83) -> 0 | AA83: =SUM(A:B!AA83) -> 0 | AB83: =SUM(A:B!AB83) -> 0 | AC83: =SUM(A:B!AC83) -> 0 | AD83: =SUM(A:B!AD83) -> 0 | AE83: =SUM(A:B!AE83) -> 0 | AF83: =SUM(A:B!AF83) -> 0 | ... AJ83: =SUM(A:B!AJ83) -> 0 | AK83: =SUM(Y83:AJ83) -> 0 | AL83: =AK83/AK$6 -> 0 | AM83: =IFERROR(AK83/V83-1,0) -> 0
I84: Combustibles Reembolsos | J84: =SUM(A:B!J84) -> 0 | K84: =SUM(A:B!K84) -> 0 | L84: =SUM(A:B!L84) -> 0 | M84: =SUM(A:B!M84) -> 0 | N84: =SUM(A:B!N84) -> 0 | O84: =SUM(A:B!O84) -> 0 | P84: =SUM(A:B!P84) -> 0 | Q84: =SUM(A:B!Q84) -> 0 | ... U84: =SUM(A:B!U84) -> 0 | V84: =SUM(J84:U84) -> 0 | W84: =V84/V$6 -> 0 | Y84: =SUM(A:B!Y84) -> 0 | Z84: =SUM(A:B!Z84) -> 0 | AA84: =SUM(A:B!AA84) -> 0 | AB84: =SUM(A:B!AB84) -> 0 | AC84: =SUM(A:B!AC84) -> 0 | AD84: =SUM(A:B!AD84) -> 0 | AE84: =SUM(A:B!AE84) -> 0 | AF84: =SUM(A:B!AF84) -> 0 | ... AJ84: =SUM(A:B!AJ84) -> 0 | AK84: =SUM(Y84:AJ84) -> 0 | AL84: =AK84/AK$6 -> 0 | AM84: =IFERROR(AK84/V84-1,0) -> 0
I85: Honorarios Admvos P.F. | J85: =SUM(A:B!J85) -> 0 | K85: =SUM(A:B!K85) -> 0 | L85: =SUM(A:B!L85) -> 0 | M85: =SUM(A:B!M85) -> 0 | N85: =SUM(A:B!N85) -> 0 | O85: =SUM(A:B!O85) -> 0 | P85: =SUM(A:B!P85) -> 0 | Q85: =SUM(A:B!Q85) -> 0 | ... U85: =SUM(A:B!U85) -> 0 | V85: =SUM(J85:U85) -> 0 | W85: =V85/V$6 -> 0 | Y85: =SUM(A:B!Y85) -> 0 | Z85: =SUM(A:B!Z85) -> 0 | AA85: =SUM(A:B!AA85) -> 0 | AB85: =SUM(A:B!AB85) -> 0 | AC85: =SUM(A:B!AC85) -> 0 | AD85: =SUM(A:B!AD85) -> 0 | AE85: =SUM(A:B!AE85) -> 0 | AF85: =SUM(A:B!AF85) -> 0 | ... AJ85: =SUM(A:B!AJ85) -> 0 | AK85: =SUM(Y85:AJ85) -> 0 | AL85: =AK85/AK$6 -> 0 | AM85: =IFERROR(AK85/V85-1,0) -> 0
I86: Capacitacion al personal | J86: =SUM(A:B!J86) -> 0 | K86: =SUM(A:B!K86) -> 0 | L86: =SUM(A:B!L86) -> 0 | M86: =SUM(A:B!M86) -> 0 | N86: =SUM(A:B!N86) -> 0 | O86: =SUM(A:B!O86) -> 0 | P86: =SUM(A:B!P86) -> 0 | Q86: =SUM(A:B!Q86) -> 0 | ... U86: =SUM(A:B!U86) -> 0 | V86: =SUM(J86:U86) -> 3640 | W86: =V86/V$6 -> 1.1043281e-05 | Y86: =SUM(A:B!Y86) -> 0 | Z86: =SUM(A:B!Z86) -> 0 | AA86: =SUM(A:B!AA86) -> 0 | AB86: =SUM(A:B!AB86) -> 0 | AC86: =SUM(A:B!AC86) -> 0 | AD86: =SUM(A:B!AD86) -> 0 | AE86: =SUM(A:B!AE86) -> 0 | AF86: =SUM(A:B!AF86) -> 0 | ... AJ86: =SUM(A:B!AJ86) -> 0 | AK86: =SUM(Y86:AJ86) -> 0 | AL86: =AK86/AK$6 -> 0 | AM86: =IFERROR(AK86/V86-1,0) -> -1
I87: Recargos Fiscales | J87: =SUM(A:B!J87) -> 0 | K87: =SUM(A:B!K87) -> 0 | L87: =SUM(A:B!L87) -> 0 | M87: =SUM(A:B!M87) -> 0 | N87: =SUM(A:B!N87) -> 0 | O87: =SUM(A:B!O87) -> 0 | P87: =SUM(A:B!P87) -> 0 | Q87: =SUM(A:B!Q87) -> 0 | ... U87: =SUM(A:B!U87) -> 0 | V87: =SUM(J87:U87) -> 0 | W87: =V87/V$6 -> 0 | Y87: =SUM(A:B!Y87) -> 0 | Z87: =SUM(A:B!Z87) -> 0 | AA87: =SUM(A:B!AA87) -> 0 | AB87: =SUM(A:B!AB87) -> 0 | AC87: =SUM(A:B!AC87) -> 0 | AD87: =SUM(A:B!AD87) -> 0 | AE87: =SUM(A:B!AE87) -> 0 | AF87: =SUM(A:B!AF87) -> 0 | ... AJ87: =SUM(A:B!AJ87) -> 0 | AK87: =SUM(Y87:AJ87) -> 0 | AL87: =AK87/AK$6 -> 0 | AM87: =IFERROR(AK87/V87-1,0) -> 0
E88: x | I88: Eventos | J88: =SUM(A:B!J88) -> 0 | K88: =SUM(A:B!K88) -> 0 | L88: =SUM(A:B!L88) -> 0 | M88: =SUM(A:B!M88) -> 0 | N88: =SUM(A:B!N88) -> 6365 | O88: =SUM(A:B!O88) -> 0 | P88: =SUM(A:B!P88) -> 0 | Q88: =SUM(A:B!Q88) -> 6926 | ... U88: =SUM(A:B!U88) -> 70720 | V88: =SUM(J88:U88) -> 85107.16 | W88: =V88/V$6 -> 0.00025820392 | Y88: =SUM(A:B!Y88) -> 0 | Z88: =SUM(A:B!Z88) -> 0 | AA88: =SUM(A:B!AA88) -> 0 | AB88: =SUM(A:B!AB88) -> 0 | AC88: =SUM(A:B!AC88) -> 5636.1195 | AD88: =SUM(A:B!AD88) -> 6319.2855 | AE88: =SUM(A:B!AE88) -> 0 | AF88: =SUM(A:B!AF88) -> 5806.911 | ... AJ88: =SUM(A:B!AJ88) -> 58069.11 | AK88: =SUM(Y88:AJ88) -> 80272.005 | AL88: =AK88/AK$6 -> 0.00022372405 | AM88: =IFERROR(AK88/V88-1,0) -> -0.056812553
A89: E - GASTOS DE OPERACIÓN | B89: estaciones | I89: Vigilancia y seguridad | J89: =SUM(A:B!J89) -> 0 | K89: =SUM(A:B!K89) -> 0 | L89: =SUM(A:B!L89) -> 0 | M89: =SUM(A:B!M89) -> 0 | N89: =SUM(A:B!N89) -> 0 | O89: =SUM(A:B!O89) -> 0 | P89: =SUM(A:B!P89) -> 0 | Q89: =SUM(A:B!Q89) -> 0 | ... U89: =SUM(A:B!U89) -> 0 | V89: =SUM(J89:U89) -> 0 | W89: =V89/V$6 -> 0 | Y89: =SUM(A:B!Y89) -> 0 | Z89: =SUM(A:B!Z89) -> 0 | AA89: =SUM(A:B!AA89) -> 0 | AB89: =SUM(A:B!AB89) -> 0 | AC89: =SUM(A:B!AC89) -> 0 | AD89: =SUM(A:B!AD89) -> 0 | AE89: =SUM(A:B!AE89) -> 0 | AF89: =SUM(A:B!AF89) -> 0 | ... AJ89: =SUM(A:B!AJ89) -> 0 | AK89: =SUM(Y89:AJ89) -> 0 | AL89: =AK89/AK$6 -> 0 | AM89: =IFERROR(AK89/V89-1,0) -> 0
A90: C - NOMINA | B90: estaciones | I90: C - NOMINA | J90: =SUM(J91:J105) -> 455748 | K90: =SUM(K91:K105) -> 395847 | L90: =SUM(L91:L105) -> 458006 | M90: =SUM(M91:M105) -> 395986 | N90: =SUM(N91:N105) -> 442702 | O90: =SUM(O91:O105) -> 446225 | P90: =SUM(P91:P105) -> 415847 | Q90: =SUM(Q91:Q105) -> 423349 | ... V90: =SUM(V91:V105) -> 5255869 | W90: =V90/V$6 -> 0.015945615 | Y90: =SUM(Y91:Y105) -> 510267.03 | Z90: =SUM(Z91:Z105) -> 466687.91 | AA90: =SUM(AA91:AA105) -> 510267.03 | AB90: =SUM(AB91:AB105) -> 482170.85 | AC90: =SUM(AC91:AC105) -> 510267.03 | AD90: =SUM(AD91:AD105) -> 482170.85 | AE90: =SUM(AE91:AE105) -> 496697.22 | AF90: =SUM(AF91:AF105) -> 496697.22 | ... AK90: =SUM(AK91:AK105) -> 5953670.7 | AL90: =AK90/AK$6 -> 0.016593323 | AM90: =IFERROR(AK90/V90-1,0) -> 0.13276619
A91: C - NOMINA | B91: estaciones | I91: Aguinaldo | J91: =SUM(A:B!J91) -> 13172 | K91: =SUM(A:B!K91) -> 10989 | L91: =SUM(A:B!L91) -> 12027 | M91: =SUM(A:B!M91) -> 11867 | N91: =SUM(A:B!N91) -> 12419 | O91: =SUM(A:B!O91) -> 11699 | P91: =SUM(A:B!P91) -> 11918 | Q91: =SUM(A:B!Q91) -> 12155 | ... U91: =SUM(A:B!U91) -> 12545.812 | V91: =SUM(J91:U91) -> 146820.06 | W91: =V91/V$6 -> 0.00044543275 | Y91: =SUM(A:B!Y91) -> 14406.303 | Z91: =SUM(A:B!Z91) -> 13012.145 | AA91: =SUM(A:B!AA91) -> 14406.303 | AB91: =SUM(A:B!AB91) -> 13941.583 | AC91: =SUM(A:B!AC91) -> 14406.303 | AD91: =SUM(A:B!AD91) -> 13941.583 | AE91: =SUM(A:B!AE91) -> 14406.303 | AF91: =SUM(A:B!AF91) -> 14406.303 | ... AJ91: =SUM(A:B!AJ91) -> 14406.303 | AK91: =SUM(Y91:AJ91) -> 169622.6 | AL91: =AK91/AK$6 -> 0.0004727508 | AM91: =IFERROR(AK91/V91-1,0) -> 0.15530941
A92: C - NOMINA | B92: estaciones | I92: Compensaciones | J92: =SUM(A:B!J92) -> 49863 | K92: =SUM(A:B!K92) -> 36134 | L92: =SUM(A:B!L92) -> 48036 | M92: =SUM(A:B!M92) -> 27064 | N92: =SUM(A:B!N92) -> 44098 | O92: =SUM(A:B!O92) -> 59674 | P92: =SUM(A:B!P92) -> 41327 | Q92: =SUM(A:B!Q92) -> 0 | ... U92: =SUM(A:B!U92) -> 44100.75 | V92: =SUM(J92:U92) -> 526699.75 | W92: =V92/V$6 -> 0.0015979377 | Y92: =SUM(A:B!Y92) -> 46379.679 | Z92: =SUM(A:B!Z92) -> 46379.679 | AA92: =SUM(A:B!AA92) -> 46379.679 | AB92: =SUM(A:B!AB92) -> 46379.679 | AC92: =SUM(A:B!AC92) -> 46379.679 | AD92: =SUM(A:B!AD92) -> 46379.679 | AE92: =SUM(A:B!AE92) -> 46379.679 | AF92: =SUM(A:B!AF92) -> 46379.679 | ... AJ92: =SUM(A:B!AJ92) -> 46379.679 | AK92: =SUM(Y92:AJ92) -> 556556.15 | AL92: =AK92/AK$6 -> 0.0015511634 | AM92: =IFERROR(AK92/V92-1,0) -> 0.056685801
A93: C - NOMINA | B93: estaciones | I93: Días festivos | J93: =SUM(A:B!J93) -> 11896 | K93: =SUM(A:B!K93) -> 12287 | L93: =SUM(A:B!L93) -> 12044 | M93: =SUM(A:B!M93) -> 0 | N93: =SUM(A:B!N93) -> 12287 | O93: =SUM(A:B!O93) -> 0 | P93: =SUM(A:B!P93) -> 0 | Q93: =SUM(A:B!Q93) -> 0 | ... U93: =SUM(A:B!U93) -> 4020.3125 | V93: =SUM(J93:U93) -> 68615.562 | W93: =V93/V$6 -> 0.00020817059 | Y93: =SUM(A:B!Y93) -> 13569.808 | Z93: =SUM(A:B!Z93) -> 13569.808 | AA93: =SUM(A:B!AA93) -> 13569.808 | AB93: =SUM(A:B!AB93) -> 0 | AC93: =SUM(A:B!AC93) -> 13569.808 | AD93: =SUM(A:B!AD93) -> 0 | AE93: =SUM(A:B!AE93) -> 0 | AF93: =SUM(A:B!AF93) -> 0 | ... AJ93: =SUM(A:B!AJ93) -> 13569.808 | AK93: =SUM(Y93:AJ93) -> 94988.656 | AL93: =AK93/AK$6 -> 0.00026474045 | AM93: =IFERROR(AK93/V93-1,0) -> 0.38436023
A94: C - NOMINA | B94: estaciones | I94: Fondo de ahorro | J94: =SUM(A:B!J94) -> 17158 | K94: =SUM(A:B!K94) -> 15186 | L94: =SUM(A:B!L94) -> 17183 | M94: =SUM(A:B!M94) -> 16371 | N94: =SUM(A:B!N94) -> 16875 | O94: =SUM(A:B!O94) -> 16430 | P94: =SUM(A:B!P94) -> 16396 | Q94: =SUM(A:B!Q94) -> 15630 | ... U94: =SUM(A:B!U94) -> 16513.188 | V94: =SUM(J94:U94) -> 198164.94 | W94: =V94/V$6 -> 0.00060120634 | Y94: =SUM(A:B!Y94) -> 18929.882 | Z94: =SUM(A:B!Z94) -> 17097.958 | AA94: =SUM(A:B!AA94) -> 18929.882 | AB94: =SUM(A:B!AB94) -> 18319.241 | AC94: =SUM(A:B!AC94) -> 18929.882 | AD94: =SUM(A:B!AD94) -> 18319.241 | AE94: =SUM(A:B!AE94) -> 18929.882 | AF94: =SUM(A:B!AF94) -> 18929.882 | ... AJ94: =SUM(A:B!AJ94) -> 18929.882 | AK94: =SUM(Y94:AJ94) -> 222884.1 | AL94: =AK94/AK$6 -> 0.00062119455 | AM94: =IFERROR(AK94/V94-1,0) -> 0.12474032
A95: C - NOMINA | B95: estaciones | I95: Indemnizaciones | J95: =SUM(A:B!J95) -> 0 | K95: =SUM(A:B!K95) -> 0 | L95: =SUM(A:B!L95) -> 0 | M95: =SUM(A:B!M95) -> 0 | N95: =SUM(A:B!N95) -> 0 | O95: =SUM(A:B!O95) -> 0 | P95: =SUM(A:B!P95) -> 0 | Q95: =SUM(A:B!Q95) -> 55943 | ... U95: =SUM(A:B!U95) -> 24863.556 | V95: =SUM(J95:U95) -> 99454.222 | W95: =V95/V$6 -> 0.00030173102 | Y95: =SUM(A:B!Y95) -> 0 | Z95: =SUM(A:B!Z95) -> 0 | AA95: =SUM(A:B!AA95) -> 0 | AB95: =SUM(A:B!AB95) -> 0 | AC95: =SUM(A:B!AC95) -> 0 | AD95: =SUM(A:B!AD95) -> 0 | AE95: =SUM(A:B!AE95) -> 0 | AF95: =SUM(A:B!AF95) -> 0 | ... AJ95: =SUM(A:B!AJ95) -> 0 | AK95: =SUM(Y95:AJ95) -> 0 | AL95: =AK95/AK$6 -> 0 | AM95: =IFERROR(AK95/V95-1,0) -> -1
A96: C - NOMINA | B96: estaciones | I96: Premios de asistencia | J96: =SUM(A:B!J96) -> 28662 | K96: =SUM(A:B!K96) -> 26477 | L96: =SUM(A:B!L96) -> 30215 | M96: =SUM(A:B!M96) -> 26182 | N96: =SUM(A:B!N96) -> 29569 | O96: =SUM(A:B!O96) -> 29292 | P96: =SUM(A:B!P96) -> 26945 | Q96: =SUM(A:B!Q96) -> 27036 | ... U96: =SUM(A:B!U96) -> 28714.062 | V96: =SUM(J96:U96) -> 340912.31 | W96: =V96/V$6 -> 0.0010342831 | Y96: =SUM(A:B!Y96) -> 29417.962 | Z96: =SUM(A:B!Z96) -> 26571.063 | AA96: =SUM(A:B!AA96) -> 29417.962 | AB96: =SUM(A:B!AB96) -> 28468.996 | AC96: =SUM(A:B!AC96) -> 29417.962 | AD96: =SUM(A:B!AD96) -> 28468.996 | AE96: =SUM(A:B!AE96) -> 29417.962 | AF96: =SUM(A:B!AF96) -> 29417.962 | ... AJ96: =SUM(A:B!AJ96) -> 29417.962 | AK96: =SUM(Y96:AJ96) -> 346372.78 | AL96: =AK96/AK$6 -> 0.0009653667 | AM96: =IFERROR(AK96/V96-1,0) -> 0.016017219
A97: C - NOMINA | B97: estaciones | I97: Premios de puntualidad | J97: =SUM(A:B!J97) -> 23699 | K97: =SUM(A:B!K97) -> 22711 | L97: =SUM(A:B!L97) -> 25639 | M97: =SUM(A:B!M97) -> 21887 | N97: =SUM(A:B!N97) -> 25914 | O97: =SUM(A:B!O97) -> 25554 | P97: =SUM(A:B!P97) -> 24027 | Q97: =SUM(A:B!Q97) -> 23205 | ... U97: =SUM(A:B!U97) -> 25706.062 | V97: =SUM(J97:U97) -> 297961.31 | W97: =V97/V$6 -> 0.00090397541 | Y97: =SUM(A:B!Y97) -> 26061.308 | Z97: =SUM(A:B!Z97) -> 23539.246 | AA97: =SUM(A:B!AA97) -> 26061.308 | AB97: =SUM(A:B!AB97) -> 25220.621 | AC97: =SUM(A:B!AC97) -> 26061.308 | AD97: =SUM(A:B!AD97) -> 25220.621 | AE97: =SUM(A:B!AE97) -> 26061.308 | AF97: =SUM(A:B!AF97) -> 26061.308 | ... AJ97: =SUM(A:B!AJ97) -> 26061.308 | AK97: =SUM(Y97:AJ97) -> 306850.89 | AL97: =AK97/AK$6 -> 0.00085521625 | AM97: =IFERROR(AK97/V97-1,0) -> 0.029834658
A98: C - NOMINA | B98: estaciones | I98: Previsión social | J98: =SUM(A:B!J98) -> 0 | K98: =SUM(A:B!K98) -> 0 | L98: =SUM(A:B!L98) -> 0 | M98: =SUM(A:B!M98) -> 0 | N98: =SUM(A:B!N98) -> 0 | O98: =SUM(A:B!O98) -> 0 | P98: =SUM(A:B!P98) -> 0 | Q98: =SUM(A:B!Q98) -> 0 | ... U98: =SUM(A:B!U98) -> 0 | V98: =SUM(J98:U98) -> 0 | W98: =V98/V$6 -> 0 | Y98: =SUM(A:B!Y98) -> 0 | Z98: =SUM(A:B!Z98) -> 0 | AA98: =SUM(A:B!AA98) -> 0 | AB98: =SUM(A:B!AB98) -> 0 | AC98: =SUM(A:B!AC98) -> 0 | AD98: =SUM(A:B!AD98) -> 0 | AE98: =SUM(A:B!AE98) -> 0 | AF98: =SUM(A:B!AF98) -> 0 | ... AJ98: =SUM(A:B!AJ98) -> 0 | AK98: =SUM(Y98:AJ98) -> 0 | AL98: =AK98/AK$6 -> 0 | AM98: =IFERROR(AK98/V98-1,0) -> 0
A99: C - NOMINA | B99: estaciones | I99: Prima dominical | J99: =SUM(A:B!J99) -> 7488 | K99: =SUM(A:B!K99) -> 6640 | L99: =SUM(A:B!L99) -> 6918 | M99: =SUM(A:B!M99) -> 6659 | N99: =SUM(A:B!N99) -> 6578 | O99: =SUM(A:B!O99) -> 6602 | P99: =SUM(A:B!P99) -> 6671 | Q99: =SUM(A:B!Q99) -> 6439 | ... U99: =SUM(A:B!U99) -> 6585.6875 | V99: =SUM(J99:U99) -> 80484.438 | W99: =V99/V$6 -> 0.00024417919 | Y99: =SUM(A:B!Y99) -> 7827.3485 | Z99: =SUM(A:B!Z99) -> 7069.8632 | AA99: =SUM(A:B!AA99) -> 7827.3485 | AB99: =SUM(A:B!AB99) -> 7574.8534 | AC99: =SUM(A:B!AC99) -> 7827.3485 | AD99: =SUM(A:B!AD99) -> 7574.8534 | AE99: =SUM(A:B!AE99) -> 7827.3485 | AF99: =SUM(A:B!AF99) -> 7827.3485 | ... AJ99: =SUM(A:B!AJ99) -> 7827.3485 | AK99: =SUM(Y99:AJ99) -> 92160.716 | AL99: =AK99/AK$6 -> 0.00025685877 | AM99: =IFERROR(AK99/V99-1,0) -> 0.14507499
A100: C - NOMINA | B100: estaciones | I100: Prima vacacional | J100: =SUM(A:B!J100) -> 2923 | K100: =SUM(A:B!K100) -> 2385 | L100: =SUM(A:B!L100) -> 2660 | M100: =SUM(A:B!M100) -> 2620 | N100: =SUM(A:B!N100) -> 2743 | O100: =SUM(A:B!O100) -> 2625 | P100: =SUM(A:B!P100) -> 2682 | Q100: =SUM(A:B!Q100) -> 2809 | ... U100: =SUM(A:B!U100) -> 2886.6875 | V100: =SUM(J100:U100) -> 33071.438 | W100: =V100/V$6 -> 0.00010033439 | Y100: =SUM(A:B!Y100) -> 3121.3656 | Z100: =SUM(A:B!Z100) -> 2819.298 | AA100: =SUM(A:B!AA100) -> 3121.3656 | AB100: =SUM(A:B!AB100) -> 3020.6764 | AC100: =SUM(A:B!AC100) -> 3121.3656 | AD100: =SUM(A:B!AD100) -> 3020.6764 | AE100: =SUM(A:B!AE100) -> 3121.3656 | AF100: =SUM(A:B!AF100) -> 3121.3656 | ... AJ100: =SUM(A:B!AJ100) -> 3121.3656 | AK100: =SUM(Y100:AJ100) -> 36751.563 | AL100: =AK100/AK$6 -> 0.00010242934 | AM100: =IFERROR(AK100/V100-1,0) -> 0.11127807
A101: C - NOMINA | B101: estaciones | I101: Primas de antigüedad | J101: =SUM(A:B!J101) -> 0 | K101: =SUM(A:B!K101) -> 0 | L101: =SUM(A:B!L101) -> 5586 | M101: =SUM(A:B!M101) -> 0 | N101: =SUM(A:B!N101) -> 0 | O101: =SUM(A:B!O101) -> 9444 | P101: =SUM(A:B!P101) -> 0 | Q101: =SUM(A:B!Q101) -> 6080 | ... U101: =SUM(A:B!U101) -> 1900 | V101: =SUM(J101:U101) -> 24530 | W101: =V101/V$6 -> 7.4420791e-05 | Y101: =SUM(A:B!Y101) -> 0 | Z101: =SUM(A:B!Z101) -> 0 | AA101: =SUM(A:B!AA101) -> 0 | AB101: =SUM(A:B!AB101) -> 0 | AC101: =SUM(A:B!AC101) -> 0 | AD101: =SUM(A:B!AD101) -> 0 | AE101: =SUM(A:B!AE101) -> 0 | AF101: =SUM(A:B!AF101) -> 0 | ... AJ101: =SUM(A:B!AJ101) -> 0 | AK101: =SUM(Y101:AJ101) -> 0 | AL101: =AK101/AK$6 -> 0 | AM101: =IFERROR(AK101/V101-1,0) -> -1
